Workbook

Sheet ANALISIS RIESGOS
A1: MATRIZ DE RIESGOS Y OPORTUNIDADES
A3: Ítem | B3: Identificación | C3: ESPECIALIDAD | D3: Análisis | E3: Rubro | F3: Gravedad | G3: Monto S/. | H3: Amenazas | I3: Oportunidad | J3: Observaciones | K3: ESTATUS RO | L3: Responsable | M3: Soluciones
A4: 01 | B4: Debido a la modalidad del contrato (suma alzada): se tenga que ejecutar mayores prestaciones adicionales sin que necesariamente sean reconocidos por la Entidad. Mov. De Tierras | C4: MOV. DE TIERRAS | D4: Gestionar ante la Entidad adicionales y deductivos vinculantes, no obstante sean rechazados se deberá dejar antecedes para un posterior reconocimiento mediante la via que corresponda. | E4: METRADO | F4: MUY BAJA | G4: 15000 | H4: =+IF(G4>0,G4,0) -> 15000 | J4: Costo total que se podria presentar en cualquier momento | K4: No Considerado en RO | L4: Obra | M4: Elaboración del presupuesto compromiso con metrados reales lo que permitirá determinar la brecha entre lo considerado en el Expediente Técnico y lo realmente a ejecutar. | AE4: ALTA
A5: =+A4+1 -> 2 | B5: Debido a la modalidad del contrato (suma alzada): se tenga que ejecutar mayores prestaciones adicionales sin que necesariamente sean reconocidos por la Entidad. Estructuras | C5: ESTRUCTURAS | D5: Gestionar ante la Entidad adicionales y deductivos vinculantes, no obstante sean rechazados se deberá dejar antecedes para un posterior reconocimiento mediante la via que corresponda. | E5: METRADO | F5: MUY BAJA | G5: 25000 | H5: =+IF(G5>0,G5,0) -> 25000 | J5: Costo total que se podria presentar en cualquier momento | K5: No Considerado en RO | L5: Obra | M5: Elaboración del presupuesto compromiso con metrados reales lo que permitirá determinar la brecha entre lo considerado en el Expediente Técnico y lo realmente a ejecutar. | AE5: ALTA
A6: =+A5+1 -> 3 | B6: Adecuaciones | C6: GG | D6: Adecuaciones de instalaciones de obra. | E6: EXTERNO | F6: ALTA | G6: 5000 | H6: =+IF(G6>0,G6,0) -> 5000 | J6: Costo mensual que se podria considerar en el mes de octubre y noviembre | K6: Costo Considerado en RO | L6: Área legal | M6: Se solicita apoyo al área legal
A7: =+A6+1 -> 4 | B7: Paralizaciones varias,: gremios sindicales, paro de transportistas, etc. | C7: GG | D7: Costos Stand by asociados a paralizaciones | E7: EXTERNO | F7: MUY BAJA | G7: 5000 | H7: =+IF(G7>0,G7,0) -> 5000 | J7: Costo mensual que se podria presentar en cada mes de la obra | K7: No Considerado en RO | L7: Externo | M7: Se realizará una contingencia ante estos eventos días antes. Envío de comunicación ante la entidad comunicando evento.
A8: =+A7+1 -> 5 | B8: Alquiler de GE para suministro de energía de obra | C8: ELÉCTRICAS | D8: Se puede dar si se corta la Energia Eléctrica | E8: EXTERNO | F8: ALTA | G8: 3000 | H8: =+IF(G8>0,G8,0) -> 3000 | J8: Costo mensual de combustible y alquiler de GE por si se corta la energia electrica | K8: No Considerado en RO | L8: Area Legal | M8: Enviar costo de adicional a Entidad. Revisar contingencia de órganos de control de contratos, de revisar GE defintivos de acuerdo a rpta de entidad.
A9: =+A8+1 -> 6 | B9: Sobre costo de Agregados (Estructuras) | C9: ESTRUCTURAS | D9: Podria darse debido a la inaccesibilidad de la cantera actual por lluvias | E9: EXTERNO | F9: MUY BAJA | H9: =+IF(G9>0,G9,0) -> 0 | J9: Suministro de agregados en el mes de septiembre, podría ser un 20% al estimado inciialmente debido a la lejanía de las canteras | K9: No Considerado en RO | L9: Obra | M9: Encontrar proveedores con lleguen al costo considerando viaje puesto en obra.
A10: =+A9+1 -> 7 | F10: MUY BAJA | H10: =+IF(G10>0,G10,0) -> 0
A11: =+A10+1 -> 8 | F11: MUY BAJA | H11: =+IF(G11>0,G11,0) -> 0
G12: =SUM(G4:G11) -> 53000 | H12: =SUM(H4:H11) -> 53000 | I12: =SUM(I4:I11) -> 0
B19: Etiquetas de fila | C19: Suma de Amenazas | D19: Suma de Oportunidad
B20: METRADO | C20: 0
B21: PANDEMIA | C21: 0 | D21: 1958414.8
B22: PLAZO | D22: 3779808.1
B23: ALCANCE | C23: -7095143.5 | D23: 681215.99
B24: EXTERNO | C24: -210000
B25: SUPERVISION | C25: -1514650 | D25: 20586
B26: CONTRATO | C26: 0
B27: ENTIDAD | C27: -1087010.2
B28: INGENIERIA | C28: -3582801.2 | D28: 0
B29: Total general | C29: -13489605 | D29: 6440024.9

Sheet PRESUPUESTOS
A1: ANALISIS DE PRESUPUESTOS
A3: PROYECTO: | B3: I.E. N° 1182 "EL BOSQUE" - CERCO + INGRESOS Y CASETAS
A5: PC | B5: ITEM | C5: DESCRIPCION | D5: UND | E5: CONTRACTUAL - VENTA | I5: META INICIAL -MES ANTERIOR | M5: META ACTUALIZADO
E6: METRADO | F6: P.U. (S/.) | G6: PARCIAL (S/.) | I6: METRADO | J6: P.U. (S/.) | K6: PARCIAL (S/.) | M6: METRADO | N6: P.U. (S/.) | O6: MANO DE OBRA | P6: MATERIALES | Q6: EQUIPOS | R6: SERVICIOS | S6: SUBCONTRATOS | T6: PARCIAL (S/.)
B7: 01 | C7: OBRAS PROVISIONALES, TRABAJOS PRELIMINARES, SEGURIDAD Y SALUD
B8: 01.02 | C8: Trabajos Preliminares
B9: 01.02.04 | C9: Trazo, Niveles y Replanteo
A10: 100 | B10: 01.02.04.01 | C10: TRAZO Y REPLANTEO PRELIMINAR | D10: M2 | E10: 897.34 | F10: 2.04 | G10: =ROUND(E10*F10,2) -> 1830.57 | I10: 942.21 | J10: 1.33 | K10: =ROUND(I10*J10,2) -> 1253.14 | M10: 942.21 | N10: =SUM(O10:S10) -> 1.33 | O10: 1.03 | Q10: 0.3 | T10: =ROUND(M10*N10,2) -> 1253.14
A11: 100 | B11: 01.02.04.02 | C11: TRAZO Y REPLANTEO DURANTE EL PROCESO | D11: m2 | E11: 897.34 | F11: 2.04 | G11: =ROUND(E11*F11,2) -> 1830.57 | I11: 942.21 | J11: 1.33 | K11: =ROUND(I11*J11,2) -> 1253.14 | M11: 942.21 | N11: =SUM(O11:S11) -> 1.33 | O11: 1.03 | Q11: 0.3 | T11: =ROUND(M11*N11,2) -> 1253.14
B12: 02 | C12: ESTRUCTURAS | T12: =ROUND(M12*N12,2) -> 0
B13: 02.01 | C13: Movimiento de Tierras | T13: =ROUND(M13*N13,2) -> 0
B14: 02.01.01 | C14: Excavaciones | T14: =ROUND(M14*N14,2) -> 0
A15: 200 | B15: 02.01.01.01 | C15: EXCAV.ZANJAS Y ZAPATA RT>2kg/cm2 H=1.5m | D15: m3 | E15: 41.9 | F15: 46.74 | G15: =ROUND(E15*F15,2) -> 1958.41 | I15: 39.81 | J15: 29.22 | K15: =ROUND(I15*J15,2) -> 1163.25 | M15: 39.81 | N15: =SUM(O15:S15) -> 29.22 | O15: 10.22 | S15: 19 | T15: =ROUND(M15*N15,2) -> 1163.25
A16: 200 | B16: 02.01.01.02 | C16: EXCAV.ZANJAS Y ZAPATA RT>2kg/cm2 H=2.0m | D16: m3 | E16: 1975.16 | F16: 50.99 | G16: =ROUND(E16*F16,2) -> 100713.41 | I16: 1876.4 | J16: 33.36 | K16: =ROUND(I16*J16,2) -> 62596.7 | M16: 1876.4 | N16: =SUM(O16:S16) -> 33.36 | O16: 12.26 | S16: 21.1 | T16: =ROUND(M16*N16,2) -> 62596.7
B17: 02.01.03 | C17: Rellenos | T17: =ROUND(M17*N17,2) -> 0
A18: 200 | B18: 02.01.03.01 | C18: RELLENO COMPACTADO C/EQUIPO MAT/PROPIO | D18: m3 | E18: 1197.91 | F18: 26.01 | G18: =ROUND(E18*F18,2) -> 31157.64 | I18: 1138.01 | J18: 15 | K18: =ROUND(I18*J18,2) -> 17070.15 | M18: 1138.01 | N18: =SUM(O18:S18) -> 15 | S18: 15 | T18: =ROUND(M18*N18,2) -> 17070.15
B19: 02.01.04 | C19: Eliminacion de Material Excedente | T19: =ROUND(M19*N19,2) -> 0
A20: 200 | B20: 02.01.04.01 | C20: ACARREO INTERNO, MATERIAL PROCEDENTE DE EXCAVACIONES | D20: m3 | E20: 68.91 | F20: 17.53 | G20: =ROUND(E20*F20,2) -> 1207.99 | T20: =ROUND(M20*N20,2) -> 0
A21: 200 | B21: 02.01.04.02 | C21: ELIMINACION MATERIAL EXCEDENTE ACARREADO | D21: M3 | E21: 68.91 | F21: 16.02 | G21: =ROUND(E21*F21,2) -> 1103.94 | T21: =ROUND(M21*N21,2) -> 0
A22: 200 | B22: 02.01.04.03 | C22: ELIMINACION MATERIAL EXCEDENTE C/MAQUINA | D22: m3 | E22: 995.9 | F22: 21.84 | G22: =ROUND(E22*F22,2) -> 21750.46 | I22: 1118.06 | J22: 18.27 | K22: =ROUND(I22*J22,2) -> 20426.96 | M22: 1118.06 | N22: =SUM(O22:S22) -> 18.27 | S22: 18.27 | T22: =ROUND(M22*N22,2) -> 20426.96
B23: 02.01.05 | C23: Nivelacion Interior y Apisonado | T23: =ROUND(M23*N23,2) -> 0
A24: 200 | B24: 02.01.05.01 | C24: ESCARIFICADO Y COMPACTACION CON PLANCHA COMPACTADORA e = 30 cm | D24: m2 | E24: 68.95 | F24: 4.72 | G24: =ROUND(E24*F24,2) -> 325.44 | I24: 70.33 | J24: 4.36 | K24: =ROUND(I24*J24,2) -> 306.64 | M24: 70.33 | N24: =SUM(O24:S24) -> 4.36 | O24: 2.39 | Q24: 1.97 | T24: =ROUND(M24*N24,2) -> 306.64
A25: 200 | B25: 02.01.05.02 | C25: ESCARIFICADO Y COMPACTACION CON PLANCHA COMPACTADORA H=0.60m (02 CAPAS 30cm c/u) | D25: m2 | E25: 8.56 | F25: 7.85 | G25: =ROUND(E25*F25,2) -> 67.2 | I25: 8.73 | J25: 7.37 | K25: =ROUND(I25*J25,2) -> 64.34 | M25: 8.73 | N25: =SUM(O25:S25) -> 7.37 | O25: 4.04 | Q25: 3.33 | T25: =ROUND(M25*N25,2) -> 64.34
A26: 200 | B26: 02.01.05.05 | C26: AFIRMADO DE 8" PARA PISOS,PATIOS Y VEREDAS,COMPACTADO. | D26: m2 | E26: 68.95 | F26: 15.19 | G26: =ROUND(E26*F26,2) -> 1047.35 | I26: 70.33 | J26: 11.5 | K26: =ROUND(I26*J26,2) -> 808.8 | M26: 70.33 | N26: =SUM(O26:S26) -> 11.5 | S26: 11.5 | T26: =ROUND(M26*N26,2) -> 808.8
A27: 200 | B27: 02.01.05.06 | C27: AFIRMADO DE 12" EN PISOS INTERIOR/EXTERIOR,COMPACTADO. | D27: m2 | E27: 8.56 | F27: 21.79 | G27: =ROUND(E27*F27,2) -> 186.52 | I27: 8.73 | J27: 14.5 | K27: =ROUND(I27*J27,2) -> 126.59 | M27: 8.73 | N27: =SUM(O27:S27) -> 14.5 | S27: 14.5 | T27: =ROUND(M27*N27,2) -> 126.59
B28: 02.02 | C28: Obras de Concreto Simple | T28: =ROUND(M28*N28,2) -> 0
B29: 02.02.01 | C29: Falsos Cimientos | T29: =ROUND(M29*N29,2) -> 0
A30: 300 | B30: 02.02.01.01 | C30: SUBCIMIENTO, SUBZAPATA MEZCLA 1:12 + 30 % P.G. | D30: m3 | E30: 323.69 | F30: 173.72 | G30: =ROUND(E30*F30,2) -> 56231.43 | I30: 330.16 | J30: 184.1 | K30: =ROUND(I30*J30,2) -> 60782.46 | M30: 330.16 | N30: =SUM(O30:S30) -> 184.1 | O30: 23.88 | P30: 17.82 | Q30: 0.72 | S30: 141.68 | T30: =ROUND(M30*N30,2) -> 60782.46
B31: 02.02.02 | C31: Cimientos | T31: =ROUND(M31*N31,2) -> 0
A32: 300 | B32: 02.02.02.02 | C32: CIMIENTOS CORRIDOS 1:10 + 30 % P.G. f'c >=100Kg/cm2 | D32: m3 | E32: 24.73 | F32: 179.78 | G32: =ROUND(E32*F32,2) -> 4445.96 | I32: 24.24 | J32: 182.46 | K32: =ROUND(I32*J32,2) -> 4422.83 | M32: 24.24 | N32: =SUM(O32:S32) -> 182.46 | O32: 22.29 | P32: 17.82 | Q32: 0.67 | S32: 141.68 | T32: =ROUND(M32*N32,2) -> 4422.83
A33: 400 | B33: 02.02.02.03 | C33: CIMIENTO CORRIDO - ENCOFRADO Y DESENCOFRADO | D33: m2 | E33: 23.09 | F33: 46.17 | G33: =ROUND(E33*F33,2) -> 1066.07 | I33: 22.63 | J33: 23.83 | K33: =ROUND(I33*J33,2) -> 539.27 | M33: 22.63 | N33: =SUM(O33:S33) -> 23.83 | O33: 16.71 | P33: 6.62 | Q33: 0.5 | T33: =ROUND(M33*N33,2) -> 539.27
A34: 300 | B34: 02.02.02.04 | C34: CALZADURA: CONCRETO C:H 1:10 + 30 % P.G. | D34: m3 | E34: 163.82 | F34: 179.78 | G34: =ROUND(E34*F34,2) -> 29451.56 | I34: 160.54 | J34: 207.85 | K34: =ROUND(I34*J34,2) -> 33368.24 | M34: 160.54 | N34: =SUM(O34:S34) -> 207.85 | O34: 42.36 | P34: 17.82 | Q34: 5.99 | S34: 141.68 | T34: =ROUND(M34*N34,2) -> 33368.24
A35: 400 | B35: 02.02.02.05 | C35: CALZADURA: ENCOFRADO Y DESENCOFRADO | D35: m2 | E35: 327.63 | F35: 37.47 | G35: =ROUND(E35*F35,2) -> 12276.3 | I35: 321.08 | J35: 26.53 | K35: =ROUND(I35*J35,2) -> 8518.25 | M35: 321.08 | N35: =SUM(O35:S35) -> 26.53 | O35: 20.06 | P35: 5.87 | Q35: 0.6 | T35: =ROUND(M35*N35,2) -> 8518.25
B36: 02.02.03 | C36: Sobrecimientos | T36: =ROUND(M36*N36,2) -> 0
A37: 300 | B37: 02.02.03.01 | C37: SOBRECIMIENTO, CONCRETO 1:8 + 25% P.M. f'c >=100Kg/cm2 | D37: m3 | E37: 3.21 | F37: 260.59 | G37: =ROUND(E37*F37,2) -> 836.49 | I37: 3.15 | J37: 201.22 | K37: =ROUND(I37*J37,2) -> 633.84 | M37: 3.15 | N37: =SUM(O37:S37) -> 201.22 | O37: 30.77 | P37: 14.58 | Q37: 4.07 | S37: 151.8 | T37: =ROUND(M37*N37,2) -> 633.84
A38: 400 | B38: 02.02.03.02 | C38: SOBRECIMIENTO, ENCOFRADO Y DESENCOFRADO | D38: m2 | E38: 43.95 | F38: 37.7 | G38: =ROUND(E38*F38,2) -> 1656.92 | I38: 43.07 | J38: 24.18 | K38: =ROUND(I38*J38,2) -> 1041.43 | M38: 43.07 | N38: =SUM(O38:S38) -> 24.18 | O38: 17.22 | P38: 6.44 | Q38: 0.52 | T38: =ROUND(M38*N38,2) -> 1041.43
B39: 02.03 | C39: Obras de Concreto Armado | T39: =ROUND(M39*N39,2) -> 0
B40: 02.03.02 | C40: Zapatas | T40: =ROUND(M40*N40,2) -> 0
A41: 300 | B41: 02.03.02.01 | C41: ZAPATAS.- CONCRETO 210 kg/cm2 | D41: m3 | E41: 396.75 | F41: 292.79 | G41: =ROUND(E41*F41,2) -> 116164.43 | I41: 412.62 | J41: 286.6 | K41: =ROUND(I41*J41,2) -> 118256.89 | M41: 412.62 | N41: =SUM(O41:S41) -> 286.6 | O41: 30.77 | Q41: 2.49 | S41: 253.34 | T41: =ROUND(M41*N41,2) -> 118256.89
A42: 500 | B42: 02.03.02.03 | C42: ZAPATAS.- ACERO Fy=4200 kg/cm2 | D42: KG | E42: 17534.91 | F42: 4.02 | G42: =ROUND(E42*F42,2) -> 70490.34 | I42: 17359.56 | J42: 3.4 | K42: =ROUND(I42*J42,2) -> 59022.5 | M42: 17359.56 | N42: =SUM(O42:S42) -> 3.4 | P42: 2.66 | S42: 0.74 | T42: =ROUND(M42*N42,2) -> 59022.5
B43: 02.03.05 | C43: Placas y Muros de Contención | T43: =ROUND(M43*N43,2) -> 0
A44: 300 | B44: 02.03.05.02 | C44: PLACAS, CONCRETO F'c=210 kg/cm2 - 1 piso | D44: m3 | E44: 6.69 | F44: 454.82 | G44: =ROUND(E44*F44,2) -> 3042.75 | I44: 6.62 | J44: 290.45 | K44: =ROUND(I44*J44,2) -> 1922.78 | M44: 6.62 | N44: =SUM(O44:S44) -> 290.45 | O44: 35.29 | Q44: 35.71 | S44: 219.45 | T44: =ROUND(M44*N44,2) -> 1922.78
A45: 400 | B45: 02.03.05.04 | C45: PLACAS, ENCOFRADO Y DESENCOFRADO | D45: m2 | E45: 74.18 | F45: 59.78 | G45: =ROUND(E45*F45,2) -> 4434.48 | I45: 73.44 | J45: 33.69 | K45: =ROUND(I45*J45,2) -> 2474.19 | M45: 73.44 | N45: =SUM(O45:S45) -> 33.69 | O45: 24.75 | P45: 8.2 | Q45: 0.74 | T45: =ROUND(M45*N45,2) -> 2474.19
A46: 500 | B46: 02.03.05.05 | C46: PLACAS, ACERO Fy=4200 kg/cm2 | D46: KG | E46: 419.35 | F46: 4.02 | G46: =ROUND(E46*F46,2) -> 1685.79 | I46: 415.16 | J46: 3.4 | K46: =ROUND(I46*J46,2) -> 1411.54 | M46: 415.16 | N46: =SUM(O46:S46) -> 3.4 | P46: 2.66 | S46: 0.74 | T46: =ROUND(M46*N46,2) -> 1411.54
A47: 300 | B47: 02.03.05.07 | C47: MUROS DE CONTENC.- CONCRETO 210 kg/cm2 | D47: m3 | E47: 256.52 | F47: 417.41 | G47: =ROUND(E47*F47,2) -> 107074.01 | I47: 253.95 | J47: 328.19 | K47: =ROUND(I47*J47,2) -> 83343.85 | M47: 253.95 | N47: =SUM(O47:S47) -> 328.19 | O47: 42.36 | Q47: 37.79 | S47: 248.04 | T47: =ROUND(M47*N47,2) -> 83343.85
A48: 400 | B48: 02.03.05.09 | C48: MUROS DE CONTENC.- ENCOF. Y DESENCOFRADO | D48: m2 | E48: 2096.19 | F48: 51.21 | G48: =ROUND(E48*F48,2) -> 107345.89 | I48: 2075.23 | J48: 30.97 | K48: =ROUND(I48*J48,2) -> 64269.87 | M48: 2075.23 | N48: =SUM(O48:S48) -> 30.97 | O48: 24.75 | P48: 5.48 | Q48: 0.74 | T48: =ROUND(M48*N48,2) -> 64269.87
A49: 500 | B49: 02.03.05.11 | C49: MUROS DE CONTENC.- ACERO Fy=4200 kg/cm2 | D49: kg | E49: 18595.1 | F49: 4.02 | G49: =ROUND(E49*F49,2) -> 74752.3 | T49: =ROUND(M49*N49,2) -> 0
B50: 02.03.06 | C50: Columnas | T50: =ROUND(M50*N50,2) -> 0
A51: 300 | B51: 02.03.06.02 | C51: COLUMNAS - CONCRETO 210 KG/CM² - 1 PISO | D51: m3 | E51: 66.63 | F51: 442.62 | G51: =ROUND(E51*F51,2) -> 29491.77 | I51: 67.96 | J51: 291.23 | K51: =ROUND(I51*J51,2) -> 19791.99 | M51: 67.96 | N51: =SUM(O51:S51) -> 291.23 | O51: 35.29 | Q51: 36.49 | S51: 219.45 | T51: =ROUND(M51*N51,2) -> 19791.99
A52: 400 | B52: 02.03.06.06 | C52: COLUMNAS.- ENCOFRADO Y DESENCOFRADO | D52: m2 | E52: 901.38 | F52: 60.48 | G52: =ROUND(E52*F52,2) -> 54515.46 | I52: 919.41 | J52: 37.49 | K52: =ROUND(I52*J52,2) -> 34468.68 | M52: 919.41 | N52: =SUM(O52:S52) -> 37.49 | O52: 24.75 | P52: 0.58 | Q52: 0.74 | S52: 11.42 | T52: =ROUND(M52*N52,2) -> 34468.68
A53: 500 | B53: 02.03.06.10 | C53: COLUMNAS.- ACERO Fy=4200 kg/cm2 | D53: KG | E53: 11604.02 | F53: 4.02 | G53: =ROUND(E53*F53,2) -> 46648.16 | I53: 11836.1 | J53: 3.4 | K53: =ROUND(I53*J53,2) -> 40242.74 | M53: 11836.1 | N53: =SUM(O53:S53) -> 3.4 | P53: 2.66 | S53: 0.74 | T53: =ROUND(M53*N53,2) -> 40242.74
B54: 02.03.07 | C54: Vigas | T54: =ROUND(M54*N54,2) -> 0
A55: 300 | B55: 02.03.07.02 | C55: VIGAS.- CONCRETO 210 kg/cm2 - 1 piso | D55: m3 | E55: 36.12 | F55: 325.93 | G55: =ROUND(E55*F55,2) -> 11772.59 | I55: 36.84 | J55: 294.5 | K55: =ROUND(I55*J55,2) -> 10849.38 | M55: 36.84 | N55: =SUM(O55:S55) -> 294.5 | O55: 40.97 | Q55: 34.08 | S55: 219.45 | T55: =ROUND(M55*N55,2) -> 10849.38
A56: 400 | B56: 02.03.07.06 | C56: VIGAS.- ENCOFRADO Y DESENCOFRADO | D56: m2 | E56: 545.23 | F56: 70.38 | G56: =ROUND(E56*F56,2) -> 38373.29 | I56: 556.13 | J56: 43.56 | K56: =ROUND(I56*J56,2) -> 24225.02 | M56: 556.13 | N56: =SUM(O56:S56) -> 43.56 | O56: 21.21 | P56: 0.29 | Q56: 0.64 | S56: 21.42 | T56: =ROUND(M56*N56,2) -> 24225.02
A57: 500 | B57: 02.03.07.08 | C57: VIGAS.- ACERO Fy=4200 kg/cm2 | D57: KG | E57: 5144.6 | F57: 4.02 | G57: =ROUND(E57*F57,2) -> 20681.29 | I57: 5247.49 | J57: 3.4 | K57: =ROUND(I57*J57,2) -> 17841.47 | M57: 5247.49 | N57: =SUM(O57:S57) -> 3.4 | P57: 2.66 | S57: 0.74 | T57: =ROUND(M57*N57,2) -> 17841.47
B58: 02.03.08 | C58: Losas Macizas | T58: =ROUND(M58*N58,2) -> 0
A59: 300 | B59: 02.03.08.01 | C59: LOSAS MACIZAS.- CONC.210 kg/cm2 - 1 PISO | D59: M3 | E59: 0.63 | F59: 325.93 | G59: =ROUND(E59*F59,2) -> 205.34 | I59: 0.64 | J59: 294.5 | K59: =ROUND(I59*J59,2) -> 188.48 | M59: 0.64 | N59: =SUM(O59:S59) -> 294.5 | O59: 40.97 | Q59: 34.08 | S59: 219.45 | T59: =ROUND(M59*N59,2) -> 188.48
A60: 400 | B60: 02.03.08.03 | C60: LOSAS MACIZAS.- ENCOFRADO Y DESENCOFRADO | D60: m2 | E60: 6.54 | F60: 55.43 | G60: =ROUND(E60*F60,2) -> 362.51 | I60: 6.67 | J60: 33.34 | K60: =ROUND(I60*J60,2) -> 222.38 | M60: 6.67 | N60: =SUM(O60:S60) -> 33.34 | O60: 15.27 | P60: 6.38 | Q60: 0.46 | S60: 11.23 | T60: =ROUND(M60*N60,2) -> 222.38
A61: 500 | B61: 02.03.08.04 | C61: LOSAS MACIZAS.- ACERO Fy=4,200 kg/cm2 | D61: KG | E61: 73.15 | F61: 4.02 | G61: =ROUND(E61*F61,2) -> 294.06 | I61: 74.61 | J61: 3.4 | K61: =ROUND(I61*J61,2) -> 253.67 | M61: 74.61 | N61: =SUM(O61:S61) -> 3.4 | P61: 2.66 | S61: 0.74 | T61: =ROUND(M61*N61,2) -> 253.67
B62: 02.03.09 | C62: Losas Aligeradas | T62: =ROUND(M62*N62,2) -> 0
A63: 300 | B63: 02.03.09.01 | C63: LOSA ALIGERADA - CONCRETO 210 kg/cm2 - 1 PISO | D63: m3 | E63: 2.13 | F63: 315.52 | G63: =ROUND(E63*F63,2) -> 672.06 | I63: 2.17 | J63: 294.5 | K63: =ROUND(I63*J63,2) -> 639.07 | M63: 2.17 | N63: =SUM(O63:S63) -> 294.5 | P63: 40.97 | Q63: 34.08 | S63: 219.45 | T63: =ROUND(M63*N63,2) -> 639.07
A64: 400 | B64: 02.03.09.03 | C64: LOSA ALIGERADA.- ENCOFRADO Y DESENCOFRADO | D64: m2 | E64: 24.72 | F64: 43.61 | G64: =ROUND(E64*F64,2) -> 1078.04 | I64: 25.21 | J64: 25.75 | K64: =ROUND(I64*J64,2) -> 649.16 | M64: 25.21 | N64: =SUM(O64:S64) -> 25.75 | O64: 15.27 | P64: 5.09 | Q64: 0.46 | S64: 4.93 | T64: =ROUND(M64*N64,2) -> 649.16
A65: 500 | B65: 02.03.09.04 | C65: LOSA ALIGERADA.- ACERO Fy=4,200 kg/cm2 | D65: KG | E65: 93.93 | F65: 4.02 | G65: =ROUND(E65*F65,2) -> 377.6 | I65: 95.81 | J65: 3.4 | K65: =ROUND(I65*J65,2) -> 325.75 | M65: 95.81 | N65: =SUM(O65:S65) -> 3.4 | P65: 2.66 | S65: 0.74 | T65: =ROUND(M65*N65,2) -> 325.75
A66: 300 | B66: 02.03.09.05 | C66: LOSA ALIGERADA.- LADR. HUECO 15x30x30 | D66: und | E66: 205.92 | F66: 2.49 | G66: =ROUND(E66*F66,2) -> 512.74 | I66: 210.04 | J66: 2.39 | K66: =ROUND(I66*J66,2) -> 502 | M66: 210.04 | N66: =SUM(O66:S66) -> 2.39 | O66: 0.95 | P66: 1.41 | S66: 0.03 | T66: =ROUND(M66*N66,2) -> 502
B67: 02.03.15 | C67: Gradas Armadas en Pisos | T67: =ROUND(M67*N67,2) -> 0
A68: 300 | B68: 02.03.15.01 | C68: GRADAS EN PISO, CONCRETO F'c=175 kg/cm2. | D68: m2 | E68: 12.31 | F68: 80.04 | G68: =ROUND(E68*F68,2) -> 985.29 | I68: 12.56 | J68: 59.8 | K68: =ROUND(I68*J68,2) -> 751.09 | M68: 12.56 | N68: =SUM(O68:S68) -> 59.8 | O68: 16.29 | Q68: 2.31 | S68: 41.2 | T68: =ROUND(M68*N68,2) -> 751.09
A69: 400 | B69: 02.03.15.03 | C69: GRADAS, ENCOFRADO Y DESENCOFRADO | D69: m2 | E69: 6.96 | F69: 41.15 | G69: =ROUND(E69*F69,2) -> 286.4 | I69: 7.1 | J69: 27.36 | K69: =ROUND(I69*J69,2) -> 194.26 | M69: 7.1 | N69: =SUM(O69:S69) -> 27.36 | O69: 20.06 | P69: 6.7 | Q69: 0.6 | T69: =ROUND(M69*N69,2) -> 194.26
A70: 500 | B70: 02.03.15.04 | C70: GRADAS EN PISO, ACERO fy=4200kg/cm2 | D70: kg | E70: 83.01 | F70: 4.02 | G70: =ROUND(E70*F70,2) -> 333.7 | I70: 84.67 | J70: 3.4 | K70: =ROUND(I70*J70,2) -> 287.88 | M70: 84.67 | N70: =SUM(O70:S70) -> 3.4 | P70: 2.66 | S70: 0.74 | T70: =ROUND(M70*N70,2) -> 287.88
C71: COSTO DIRECTO | G71: =SUM(G7:G70) -> 960724.52 | K71: =SUM(K7:K70) -> 696510.67 | T71: =SUM(T7:T70) -> 696510.67
C72: GASTOS GENERALES (10%) | G72: =ROUND(G71*0.1,2) -> 96072.45 | K72: =ROUND(K71*0.12,2) -> 83581.28 | T72: =ROUND(T71*0.12,2) -> 83581.28
C73: UTILIDAD (8%) | G73: =ROUND(G71*0.08,2) -> 76857.96 | K73: 0
C74: SUBTOTAL | G74: =SUM(G71:G73) -> 1133654.9 | K74: =SUM(K71:K73) -> 780091.95 | T74: =SUM(T71:T73) -> 780091.95
C75: IGV (18.00%) | G75: =ROUND(G74*0.18,2) -> 204057.89 | K75: =ROUND(K74*0.18,2) -> 140416.55 | T75: =ROUND(T74*0.18,2) -> 140416.55
C76: COSTO TOTAL (INC. IGV) | G76: =SUM(G74:G75) -> 1337712.8 | K76: =SUM(K74:K75) -> 920508.5 | T76: =SUM(T74:T75) -> 920508.5

Sheet COSTO DIRECTO
A1: ANALISIS DE AVANCE
A3: PROYECTO: | B3: I.E. N° 1182 "EL BOSQUE" - CERCO + INGRESOS Y CASETAS
E4: ANALISIS DE PRECIOS VENTA | L4: COSTO PREVISTO
A5: PC | B5: ITEM | C5: DESCRIPCION | D5: UND | E5: CONTRACTUAL | F5: VENTA ACTUAL | H5: VENTA PENDIENTE | J5: VENTA TOTAL | L5: PREVISTO | M5: PREVISTO ACTUAL | O5: PREVISTO PENDIENTE | Q5: PREVISTO TOTAL
E6: P.U. (S/.) | F6: METRADO EJECUTADO | G6: PARCIAL (S/.) | H6: METRADO POR EJECUT | I6: PARCIAL (S/.) | J6: METRADO CONTRATO | K6: PARCIAL (S/.) | L6: P.U. (S/.) | M6: METRADO EJECUTADO REAL | N6: PARCIAL (S/.) | O6: METRADO POR EJECUT | P6: PARCIAL (S/.) | Q6: METRADO TOTAL REAL | R6: PARCIAL (S/.)
B7: 01 | C7: OBRAS PROVISIONALES, TRABAJOS PRELIMINARES, SEGURIDAD Y SALUD
B8: 01.02 | C8: Trabajos Preliminares
B9: 01.02.04 | C9: Trazo, Niveles y Replanteo
A10: 100 | B10: 01.02.04.01 | C10: TRAZO Y REPLANTEO PRELIMINAR | D10: M2 | E10: =PRESUPUESTOS!F10 -> 2.04 | F10: =IF(Q10=0,0,((M10/Q10)*J10)) -> 0 | G10: =ROUND(E10*F10,2) -> 0 | H10: =J10-F10 -> 897.34 | I10: =ROUND(E10*H10,2) -> 1830.57 | J10: =PRESUPUESTOS!E10 -> 897.34 | K10: =ROUND(E10*J10,2) -> 1830.57 | L10: =PRESUPUESTOS!N10 -> 1.33 | M10: 0 | N10: =ROUND(M10*L10,2) -> 0 | O10: =Q10-M10 -> 942.21 | P10: =ROUND(O10*L10,2) -> 1253.14 | Q10: =PRESUPUESTOS!M10 -> 942.21 | R10: =ROUND(Q10*L10,2) -> 1253.14
A11: 100 | B11: 01.02.04.02 | C11: TRAZO Y REPLANTEO DURANTE EL PROCESO | D11: m2 | E11: =PRESUPUESTOS!F11 -> 2.04 | F11: =IF(Q11=0,0,((M11/Q11)*J11)) -> 224.335 | G11: =ROUND(E11*F11,2) -> 457.64 | H11: =J11-F11 -> 673.005 | I11: =ROUND(E11*H11,2) -> 1372.93 | J11: =PRESUPUESTOS!E11 -> 897.34 | K11: =ROUND(E11*J11,2) -> 1830.57 | L11: =PRESUPUESTOS!N11 -> 1.33 | M11: 235.5525 | N11: =ROUND(M11*L11,2) -> 313.28 | O11: =Q11-M11 -> 706.6575 | P11: =ROUND(O11*L11,2) -> 939.85 | Q11: =PRESUPUESTOS!M11 -> 942.21 | R11: =ROUND(Q11*L11,2) -> 1253.14
B12: 02 | C12: ESTRUCTURAS
B13: 02.01 | C13: Movimiento de Tierras
B14: 02.01.01 | C14: Excavaciones
A15: 200 | B15: 02.01.01.01 | C15: EXCAV.ZANJAS Y ZAPATA RT>2kg/cm2 H=1.5m | D15: m3 | E15: =PRESUPUESTOS!F15 -> 46.74 | F15: =IF(Q15=0,0,((M15/Q15)*J15)) -> 0 | G15: =ROUND(E15*F15,2) -> 0 | H15: =J15-F15 -> 41.9 | I15: =ROUND(E15*H15,2) -> 1958.41 | J15: =PRESUPUESTOS!E15 -> 41.9 | K15: =ROUND(E15*J15,2) -> 1958.41 | L15: =PRESUPUESTOS!N15 -> 29.22 | M15: 0 | N15: =ROUND(M15*L15,2) -> 0 | O15: =Q15-M15 -> 39.81 | P15: =ROUND(O15*L15,2) -> 1163.25 | Q15: =PRESUPUESTOS!M15 -> 39.81 | R15: =ROUND(Q15*L15,2) -> 1163.25
A16: 200 | B16: 02.01.01.02 | C16: EXCAV.ZANJAS Y ZAPATA RT>2kg/cm2 H=2.0m | D16: m3 | E16: =PRESUPUESTOS!F16 -> 50.99 | F16: =IF(Q16=0,0,((M16/Q16)*J16)) -> 0 | G16: =ROUND(E16*F16,2) -> 0 | H16: =J16-F16 -> 1975.16 | I16: =ROUND(E16*H16,2) -> 100713.41 | J16: =PRESUPUESTOS!E16 -> 1975.16 | K16: =ROUND(E16*J16,2) -> 100713.41 | L16: =PRESUPUESTOS!N16 -> 33.36 | M16: 0 | N16: =ROUND(M16*L16,2) -> 0 | O16: =Q16-M16 -> 1876.4 | P16: =ROUND(O16*L16,2) -> 62596.7 | Q16: =PRESUPUESTOS!M16 -> 1876.4 | R16: =ROUND(Q16*L16,2) -> 62596.7
B17: 02.01.03 | C17: Rellenos
A18: 200 | B18: 02.01.03.01 | C18: RELLENO COMPACTADO C/EQUIPO MAT/PROPIO | D18: m3 | E18: =PRESUPUESTOS!F18 -> 26.01 | F18: =IF(Q18=0,0,((M18/Q18)*J18)) -> 838.537 | G18: =ROUND(E18*F18,2) -> 21810.35 | H18: =J18-F18 -> 359.373 | I18: =ROUND(E18*H18,2) -> 9347.29 | J18: =PRESUPUESTOS!E18 -> 1197.91 | K18: =ROUND(E18*J18,2) -> 31157.64 | L18: =PRESUPUESTOS!N18 -> 15 | M18: 796.607 | N18: =ROUND(M18*L18,2) -> 11949.11 | O18: =Q18-M18 -> 341.403 | P18: =ROUND(O18*L18,2) -> 5121.05 | Q18: =PRESUPUESTOS!M18 -> 1138.01 | R18: =ROUND(Q18*L18,2) -> 17070.15
B19: 02.01.04 | C19: Eliminacion de Material Excedente
A20: 200 | B20: 02.01.04.01 | C20: ACARREO INTERNO, MATERIAL PROCEDENTE DE EXCAVACIONES | D20: m3 | E20: =PRESUPUESTOS!F20 -> 17.53 | F20: =IF(Q20=0,0,((M20/Q20)*J20)) -> 0 | G20: =ROUND(E20*F20,2) -> 0 | H20: =J20-F20 -> 68.91 | I20: =ROUND(E20*H20,2) -> 1207.99 | J20: =PRESUPUESTOS!E20 -> 68.91 | K20: =ROUND(E20*J20,2) -> 1207.99 | L20: =PRESUPUESTOS!N20 -> 0 | M20: 0 | N20: =ROUND(M20*L20,2) -> 0 | O20: =Q20-M20 -> 0 | P20: =ROUND(O20*L20,2) -> 0 | Q20: =PRESUPUESTOS!M20 -> 0 | R20: =ROUND(Q20*L20,2) -> 0
A21: 200 | B21: 02.01.04.02 | C21: ELIMINACION MATERIAL EXCEDENTE ACARREADO | D21: M3 | E21: =PRESUPUESTOS!F21 -> 16.02 | F21: =IF(Q21=0,0,((M21/Q21)*J21)) -> 0 | G21: =ROUND(E21*F21,2) -> 0 | H21: =J21-F21 -> 68.91 | I21: =ROUND(E21*H21,2) -> 1103.94 | J21: =PRESUPUESTOS!E21 -> 68.91 | K21: =ROUND(E21*J21,2) -> 1103.94 | L21: =PRESUPUESTOS!N21 -> 0 | M21: 0 | N21: =ROUND(M21*L21,2) -> 0 | O21: =Q21-M21 -> 0 | P21: =ROUND(O21*L21,2) -> 0 | Q21: =PRESUPUESTOS!M21 -> 0 | R21: =ROUND(Q21*L21,2) -> 0
A22: 200 | B22: 02.01.04.03 | C22: ELIMINACION MATERIAL EXCEDENTE C/MAQUINA | D22: m3 | E22: =PRESUPUESTOS!F22 -> 21.84 | F22: =IF(Q22=0,0,((M22/Q22)*J22)) -> 0 | G22: =ROUND(E22*F22,2) -> 0 | H22: =J22-F22 -> 995.9 | I22: =ROUND(E22*H22,2) -> 21750.46 | J22: =PRESUPUESTOS!E22 -> 995.9 | K22: =ROUND(E22*J22,2) -> 21750.46 | L22: =PRESUPUESTOS!N22 -> 18.27 | M22: 0 | N22: =ROUND(M22*L22,2) -> 0 | O22: =Q22-M22 -> 1118.06 | P22: =ROUND(O22*L22,2) -> 20426.96 | Q22: =PRESUPUESTOS!M22 -> 1118.06 | R22: =ROUND(Q22*L22,2) -> 20426.96
B23: 02.01.05 | C23: Nivelacion Interior y Apisonado | E23: =PRESUPUESTOS!F23 -> 0 | F23: =IF(Q23=0,0,((M23/Q23)*J23)) -> 0 | G23: =ROUND(E23*F23,2) -> 0 | H23: =J23-F23 -> 0 | I23: =ROUND(E23*H23,2) -> 0 | J23: =PRESUPUESTOS!E23 -> 0 | K23: =ROUND(E23*J23,2) -> 0 | L23: =PRESUPUESTOS!N23 -> 0 | N23: =ROUND(M23*L23,2) -> 0 | O23: =Q23-M23 -> 0 | P23: =ROUND(O23*L23,2) -> 0 | Q23: =PRESUPUESTOS!M23 -> 0 | R23: =ROUND(Q23*L23,2) -> 0
A24: 200 | B24: 02.01.05.01 | C24: ESCARIFICADO Y COMPACTACION CON PLANCHA COMPACTADORA e = 30 cm | D24: m2 | E24: =PRESUPUESTOS!F24 -> 4.72 | F24: =IF(Q24=0,0,((M24/Q24)*J24)) -> 0 | G24: =ROUND(E24*F24,2) -> 0 | H24: =J24-F24 -> 68.95 | I24: =ROUND(E24*H24,2) -> 325.44 | J24: =PRESUPUESTOS!E24 -> 68.95 | K24: =ROUND(E24*J24,2) -> 325.44 | L24: =PRESUPUESTOS!N24 -> 4.36 | M24: 0 | N24: =ROUND(M24*L24,2) -> 0 | O24: =Q24-M24 -> 70.33 | P24: =ROUND(O24*L24,2) -> 306.64 | Q24: =PRESUPUESTOS!M24 -> 70.33 | R24: =ROUND(Q24*L24,2) -> 306.64
A25: 200 | B25: 02.01.05.02 | C25: ESCARIFICADO Y COMPACTACION CON PLANCHA COMPACTADORA H=0.60m (02 CAPAS 30cm c/u) | D25: m2 | E25: =PRESUPUESTOS!F25 -> 7.85 | F25: =IF(Q25=0,0,((M25/Q25)*J25)) -> 5.136 | G25: =ROUND(E25*F25,2) -> 40.32 | H25: =J25-F25 -> 3.424 | I25: =ROUND(E25*H25,2) -> 26.88 | J25: =PRESUPUESTOS!E25 -> 8.56 | K25: =ROUND(E25*J25,2) -> 67.2 | L25: =PRESUPUESTOS!N25 -> 7.37 | M25: 5.238 | N25: =ROUND(M25*L25,2) -> 38.6 | O25: =Q25-M25 -> 3.492 | P25: =ROUND(O25*L25,2) -> 25.74 | Q25: =PRESUPUESTOS!M25 -> 8.73 | R25: =ROUND(Q25*L25,2) -> 64.34
A26: 200 | B26: 02.01.05.05 | C26: AFIRMADO DE 8" PARA PISOS,PATIOS Y VEREDAS,COMPACTADO. | D26: m2 | E26: =PRESUPUESTOS!F26 -> 15.19 | F26: =IF(Q26=0,0,((M26/Q26)*J26)) -> 0 | G26: =ROUND(E26*F26,2) -> 0 | H26: =J26-F26 -> 68.95 | I26: =ROUND(E26*H26,2) -> 1047.35 | J26: =PRESUPUESTOS!E26 -> 68.95 | K26: =ROUND(E26*J26,2) -> 1047.35 | L26: =PRESUPUESTOS!N26 -> 11.5 | M26: 0 | N26: =ROUND(M26*L26,2) -> 0 | O26: =Q26-M26 -> 70.33 | P26: =ROUND(O26*L26,2) -> 808.8 | Q26: =PRESUPUESTOS!M26 -> 70.33 | R26: =ROUND(Q26*L26,2) -> 808.8
A27: 200 | B27: 02.01.05.06 | C27: AFIRMADO DE 12" EN PISOS INTERIOR/EXTERIOR,COMPACTADO. | D27: m2 | E27: =PRESUPUESTOS!F27 -> 21.79 | F27: =IF(Q27=0,0,((M27/Q27)*J27)) -> 4.28 | G27: =ROUND(E27*F27,2) -> 93.26 | H27: =J27-F27 -> 4.28 | I27: =ROUND(E27*H27,2) -> 93.26 | J27: =PRESUPUESTOS!E27 -> 8.56 | K27: =ROUND(E27*J27,2) -> 186.52 | L27: =PRESUPUESTOS!N27 -> 14.5 | M27: 4.365 | N27: =ROUND(M27*L27,2) -> 63.29 | O27: =Q27-M27 -> 4.365 | P27: =ROUND(O27*L27,2) -> 63.29 | Q27: =PRESUPUESTOS!M27 -> 8.73 | R27: =ROUND(Q27*L27,2) -> 126.59
B28: 02.02 | C28: Obras de Concreto Simple | E28: =PRESUPUESTOS!F28 -> 0 | F28: =IF(Q28=0,0,((M28/Q28)*J28)) -> 0 | G28: =ROUND(E28*F28,2) -> 0 | H28: =J28-F28 -> 0 | I28: =ROUND(E28*H28,2) -> 0 | J28: =PRESUPUESTOS!E28 -> 0 | K28: =ROUND(E28*J28,2) -> 0 | L28: =PRESUPUESTOS!N28 -> 0 | N28: =ROUND(M28*L28,2) -> 0 | O28: =Q28-M28 -> 0 | P28: =ROUND(O28*L28,2) -> 0 | Q28: =PRESUPUESTOS!M28 -> 0 | R28: =ROUND(Q28*L28,2) -> 0
B29: 02.02.01 | C29: Falsos Cimientos | E29: =PRESUPUESTOS!F29 -> 0 | F29: =IF(Q29=0,0,((M29/Q29)*J29)) -> 0 | G29: =ROUND(E29*F29,2) -> 0 | H29: =J29-F29 -> 0 | I29: =ROUND(E29*H29,2) -> 0 | J29: =PRESUPUESTOS!E29 -> 0 | K29: =ROUND(E29*J29,2) -> 0 | L29: =PRESUPUESTOS!N29 -> 0 | N29: =ROUND(M29*L29,2) -> 0 | O29: =Q29-M29 -> 0 | P29: =ROUND(O29*L29,2) -> 0 | Q29: =PRESUPUESTOS!M29 -> 0 | R29: =ROUND(Q29*L29,2) -> 0
A30: 300 | B30: 02.02.01.01 | C30: SUBCIMIENTO, SUBZAPATA MEZCLA 1:12 + 30 % P.G. | D30: m3 | E30: =PRESUPUESTOS!F30 -> 173.72 | F30: =IF(Q30=0,0,((M30/Q30)*J30)) -> 97.107 | G30: =ROUND(E30*F30,2) -> 16869.43 | H30: =J30-F30 -> 226.583 | I30: =ROUND(E30*H30,2) -> 39362 | J30: =PRESUPUESTOS!E30 -> 323.69 | K30: =ROUND(E30*J30,2) -> 56231.43 | L30: =PRESUPUESTOS!N30 -> 184.1 | M30: 99.048 | N30: =ROUND(M30*L30,2) -> 18234.74 | O30: =Q30-M30 -> 231.112 | P30: =ROUND(O30*L30,2) -> 42547.72 | Q30: =PRESUPUESTOS!M30 -> 330.16 | R30: =ROUND(Q30*L30,2) -> 60782.46
B31: 02.02.02 | C31: Cimientos | E31: =PRESUPUESTOS!F31 -> 0 | F31: =IF(Q31=0,0,((M31/Q31)*J31)) -> 0 | G31: =ROUND(E31*F31,2) -> 0 | H31: =J31-F31 -> 0 | I31: =ROUND(E31*H31,2) -> 0 | J31: =PRESUPUESTOS!E31 -> 0 | K31: =ROUND(E31*J31,2) -> 0 | L31: =PRESUPUESTOS!N31 -> 0 | N31: =ROUND(M31*L31,2) -> 0 | O31: =Q31-M31 -> 0 | P31: =ROUND(O31*L31,2) -> 0 | Q31: =PRESUPUESTOS!M31 -> 0 | R31: =ROUND(Q31*L31,2) -> 0
A32: 300 | B32: 02.02.02.02 | C32: CIMIENTOS CORRIDOS 1:10 + 30 % P.G. f'c >=100Kg/cm2 | D32: m3 | E32: =PRESUPUESTOS!F32 -> 179.78 | F32: =IF(Q32=0,0,((M32/Q32)*J32)) -> 17.311 | G32: =ROUND(E32*F32,2) -> 3112.17 | H32: =J32-F32 -> 7.419 | I32: =ROUND(E32*H32,2) -> 1333.79 | J32: =PRESUPUESTOS!E32 -> 24.73 | K32: =ROUND(E32*J32,2) -> 4445.96 | L32: =PRESUPUESTOS!N32 -> 182.46 | M32: 16.968 | N32: =ROUND(M32*L32,2) -> 3095.98 | O32: =Q32-M32 -> 7.272 | P32: =ROUND(O32*L32,2) -> 1326.85 | Q32: =PRESUPUESTOS!M32 -> 24.24 | R32: =ROUND(Q32*L32,2) -> 4422.83
A33: 400 | B33: 02.02.02.03 | C33: CIMIENTO CORRIDO - ENCOFRADO Y DESENCOFRADO | D33: m2 | E33: =PRESUPUESTOS!F33 -> 46.17 | F33: =IF(Q33=0,0,((M33/Q33)*J33)) -> 13.854 | G33: =ROUND(E33*F33,2) -> 639.64 | H33: =J33-F33 -> 9.236 | I33: =ROUND(E33*H33,2) -> 426.43 | J33: =PRESUPUESTOS!E33 -> 23.09 | K33: =ROUND(E33*J33,2) -> 1066.07 | L33: =PRESUPUESTOS!N33 -> 23.83 | M33: 13.578 | N33: =ROUND(M33*L33,2) -> 323.56 | O33: =Q33-M33 -> 9.052 | P33: =ROUND(O33*L33,2) -> 215.71 | Q33: =PRESUPUESTOS!M33 -> 22.63 | R33: =ROUND(Q33*L33,2) -> 539.27
A34: 300 | B34: 02.02.02.04 | C34: CALZADURA: CONCRETO C:H 1:10 + 30 % P.G. | D34: m3 | E34: =PRESUPUESTOS!F34 -> 179.78 | F34: =IF(Q34=0,0,((M34/Q34)*J34)) -> 0 | G34: =ROUND(E34*F34,2) -> 0 | H34: =J34-F34 -> 163.82 | I34: =ROUND(E34*H34,2) -> 29451.56 | J34: =PRESUPUESTOS!E34 -> 163.82 | K34: =ROUND(E34*J34,2) -> 29451.56 | L34: =PRESUPUESTOS!N34 -> 207.85 | M34: 0 | N34: =ROUND(M34*L34,2) -> 0 | O34: =Q34-M34 -> 160.54 | P34: =ROUND(O34*L34,2) -> 33368.24 | Q34: =PRESUPUESTOS!M34 -> 160.54 | R34: =ROUND(Q34*L34,2) -> 33368.24
A35: 400 | B35: 02.02.02.05 | C35: CALZADURA: ENCOFRADO Y DESENCOFRADO | D35: m2 | E35: =PRESUPUESTOS!F35 -> 37.47 | F35: =IF(Q35=0,0,((M35/Q35)*J35)) -> 0 | G35: =ROUND(E35*F35,2) -> 0 | H35: =J35-F35 -> 327.63 | I35: =ROUND(E35*H35,2) -> 12276.3 | J35: =PRESUPUESTOS!E35 -> 327.63 | K35: =ROUND(E35*J35,2) -> 12276.3 | L35: =PRESUPUESTOS!N35 -> 26.53 | M35: 0 | N35: =ROUND(M35*L35,2) -> 0 | O35: =Q35-M35 -> 321.08 | P35: =ROUND(O35*L35,2) -> 8518.25 | Q35: =PRESUPUESTOS!M35 -> 321.08 | R35: =ROUND(Q35*L35,2) -> 8518.25
B36: 02.02.03 | C36: Sobrecimientos | E36: =PRESUPUESTOS!F36 -> 0 | F36: =IF(Q36=0,0,((M36/Q36)*J36)) -> 0 | G36: =ROUND(E36*F36,2) -> 0 | H36: =J36-F36 -> 0 | I36: =ROUND(E36*H36,2) -> 0 | J36: =PRESUPUESTOS!E36 -> 0 | K36: =ROUND(E36*J36,2) -> 0 | L36: =PRESUPUESTOS!N36 -> 0 | N36: =ROUND(M36*L36,2) -> 0 | O36: =Q36-M36 -> 0 | P36: =ROUND(O36*L36,2) -> 0 | Q36: =PRESUPUESTOS!M36 -> 0 | R36: =ROUND(Q36*L36,2) -> 0
A37: 300 | B37: 02.02.03.01 | C37: SOBRECIMIENTO, CONCRETO 1:8 + 25% P.M. f'c >=100Kg/cm2 | D37: m3 | E37: =PRESUPUESTOS!F37 -> 260.59 | F37: =IF(Q37=0,0,((M37/Q37)*J37)) -> 1.605 | G37: =ROUND(E37*F37,2) -> 418.25 | H37: =J37-F37 -> 1.605 | I37: =ROUND(E37*H37,2) -> 418.25 | J37: =PRESUPUESTOS!E37 -> 3.21 | K37: =ROUND(E37*J37,2) -> 836.49 | L37: =PRESUPUESTOS!N37 -> 201.22 | M37: 1.575 | N37: =ROUND(M37*L37,2) -> 316.92 | O37: =Q37-M37 -> 1.575 | P37: =ROUND(O37*L37,2) -> 316.92 | Q37: =PRESUPUESTOS!M37 -> 3.15 | R37: =ROUND(Q37*L37,2) -> 633.84
A38: 400 | B38: 02.02.03.02 | C38: SOBRECIMIENTO, ENCOFRADO Y DESENCOFRADO | D38: m2 | E38: =PRESUPUESTOS!F38 -> 37.7 | F38: =IF(Q38=0,0,((M38/Q38)*J38)) -> 17.58 | G38: =ROUND(E38*F38,2) -> 662.77 | H38: =J38-F38 -> 26.37 | I38: =ROUND(E38*H38,2) -> 994.15 | J38: =PRESUPUESTOS!E38 -> 43.95 | K38: =ROUND(E38*J38,2) -> 1656.92 | L38: =PRESUPUESTOS!N38 -> 24.18 | M38: 17.228 | N38: =ROUND(M38*L38,2) -> 416.57 | O38: =Q38-M38 -> 25.842 | P38: =ROUND(O38*L38,2) -> 624.86 | Q38: =PRESUPUESTOS!M38 -> 43.07 | R38: =ROUND(Q38*L38,2) -> 1041.43
B39: 02.03 | C39: Obras de Concreto Armado | E39: =PRESUPUESTOS!F39 -> 0 | F39: =IF(Q39=0,0,((M39/Q39)*J39)) -> 0 | G39: =ROUND(E39*F39,2) -> 0 | H39: =J39-F39 -> 0 | I39: =ROUND(E39*H39,2) -> 0 | J39: =PRESUPUESTOS!E39 -> 0 | K39: =ROUND(E39*J39,2) -> 0 | L39: =PRESUPUESTOS!N39 -> 0 | N39: =ROUND(M39*L39,2) -> 0 | O39: =Q39-M39 -> 0 | P39: =ROUND(O39*L39,2) -> 0 | Q39: =PRESUPUESTOS!M39 -> 0 | R39: =ROUND(Q39*L39,2) -> 0
B40: 02.03.02 | C40: Zapatas | E40: =PRESUPUESTOS!F40 -> 0 | F40: =IF(Q40=0,0,((M40/Q40)*J40)) -> 0 | G40: =ROUND(E40*F40,2) -> 0 | H40: =J40-F40 -> 0 | I40: =ROUND(E40*H40,2) -> 0 | J40: =PRESUPUESTOS!E40 -> 0 | K40: =ROUND(E40*J40,2) -> 0 | L40: =PRESUPUESTOS!N40 -> 0 | N40: =ROUND(M40*L40,2) -> 0 | O40: =Q40-M40 -> 0 | P40: =ROUND(O40*L40,2) -> 0 | Q40: =PRESUPUESTOS!M40 -> 0 | R40: =ROUND(Q40*L40,2) -> 0
A41: 300 | B41: 02.03.02.01 | C41: ZAPATAS.- CONCRETO 210 kg/cm2 | D41: m3 | E41: =PRESUPUESTOS!F41 -> 292.79 | F41: =IF(Q41=0,0,((M41/Q41)*J41)) -> 198.375 | G41: =ROUND(E41*F41,2) -> 58082.22 | H41: =J41-F41 -> 198.375 | I41: =ROUND(E41*H41,2) -> 58082.22 | J41: =PRESUPUESTOS!E41 -> 396.75 | K41: =ROUND(E41*J41,2) -> 116164.43 | L41: =PRESUPUESTOS!N41 -> 286.6 | M41: 206.31 | N41: =ROUND(M41*L41,2) -> 59128.45 | O41: =Q41-M41 -> 206.31 | P41: =ROUND(O41*L41,2) -> 59128.45 | Q41: =PRESUPUESTOS!M41 -> 412.62 | R41: =ROUND(Q41*L41,2) -> 118256.89
A42: 500 | B42: 02.03.02.03 | C42: ZAPATAS.- ACERO Fy=4200 kg/cm2 | D42: KG | E42: =PRESUPUESTOS!F42 -> 4.02 | F42: =IF(Q42=0,0,((M42/Q42)*J42)) -> 8767.455 | G42: =ROUND(E42*F42,2) -> 35245.17 | H42: =J42-F42 -> 8767.455 | I42: =ROUND(E42*H42,2) -> 35245.17 | J42: =PRESUPUESTOS!E42 -> 17534.91 | K42: =ROUND(E42*J42,2) -> 70490.34 | L42: =PRESUPUESTOS!N42 -> 3.4 | M42: 8679.78 | N42: =ROUND(M42*L42,2) -> 29511.25 | O42: =Q42-M42 -> 8679.78 | P42: =ROUND(O42*L42,2) -> 29511.25 | Q42: =PRESUPUESTOS!M42 -> 17359.56 | R42: =ROUND(Q42*L42,2) -> 59022.5
B43: 02.03.05 | C43: Placas y Muros de Contención | E43: =PRESUPUESTOS!F43 -> 0 | F43: =IF(Q43=0,0,((M43/Q43)*J43)) -> 0 | G43: =ROUND(E43*F43,2) -> 0 | H43: =J43-F43 -> 0 | I43: =ROUND(E43*H43,2) -> 0 | J43: =PRESUPUESTOS!E43 -> 0 | K43: =ROUND(E43*J43,2) -> 0 | L43: =PRESUPUESTOS!N43 -> 0 | N43: =ROUND(M43*L43,2) -> 0 | O43: =Q43-M43 -> 0 | P43: =ROUND(O43*L43,2) -> 0 | Q43: =PRESUPUESTOS!M43 -> 0 | R43: =ROUND(Q43*L43,2) -> 0
A44: 300 | B44: 02.03.05.02 | C44: PLACAS, CONCRETO F'c=210 kg/cm2 - 1 piso | D44: m3 | E44: =PRESUPUESTOS!F44 -> 454.82 | F44: =IF(Q44=0,0,((M44/Q44)*J44)) -> 4.014 | G44: =ROUND(E44*F44,2) -> 1825.65 | H44: =J44-F44 -> 2.676 | I44: =ROUND(E44*H44,2) -> 1217.1 | J44: =PRESUPUESTOS!E44 -> 6.69 | K44: =ROUND(E44*J44,2) -> 3042.75 | L44: =PRESUPUESTOS!N44 -> 290.45 | M44: 3.972 | N44: =ROUND(M44*L44,2) -> 1153.67 | O44: =Q44-M44 -> 2.648 | P44: =ROUND(O44*L44,2) -> 769.11 | Q44: =PRESUPUESTOS!M44 -> 6.62 | R44: =ROUND(Q44*L44,2) -> 1922.78
A45: 400 | B45: 02.03.05.04 | C45: PLACAS, ENCOFRADO Y DESENCOFRADO | D45: m2 | E45: =PRESUPUESTOS!F45 -> 59.78 | F45: =IF(Q45=0,0,((M45/Q45)*J45)) -> 22.254 | G45: =ROUND(E45*F45,2) -> 1330.34 | H45: =J45-F45 -> 51.926 | I45: =ROUND(E45*H45,2) -> 3104.14 | J45: =PRESUPUESTOS!E45 -> 74.18 | K45: =ROUND(E45*J45,2) -> 4434.48 | L45: =PRESUPUESTOS!N45 -> 33.69 | M45: 22.032 | N45: =ROUND(M45*L45,2) -> 742.26 | O45: =Q45-M45 -> 51.408 | P45: =ROUND(O45*L45,2) -> 1731.94 | Q45: =PRESUPUESTOS!M45 -> 73.44 | R45: =ROUND(Q45*L45,2) -> 2474.19
A46: 500 | B46: 02.03.05.05 | C46: PLACAS, ACERO Fy=4200 kg/cm2 | D46: KG | E46: =PRESUPUESTOS!F46 -> 4.02 | F46: =IF(Q46=0,0,((M46/Q46)*J46)) -> 125.805 | G46: =ROUND(E46*F46,2) -> 505.74 | H46: =J46-F46 -> 293.545 | I46: =ROUND(E46*H46,2) -> 1180.05 | J46: =PRESUPUESTOS!E46 -> 419.35 | K46: =ROUND(E46*J46,2) -> 1685.79 | L46: =PRESUPUESTOS!N46 -> 3.4 | M46: 124.548 | N46: =ROUND(M46*L46,2) -> 423.46 | O46: =Q46-M46 -> 290.612 | P46: =ROUND(O46*L46,2) -> 988.08 | Q46: =PRESUPUESTOS!M46 -> 415.16 | R46: =ROUND(Q46*L46,2) -> 1411.54
A47: 300 | B47: 02.03.05.07 | C47: MUROS DE CONTENC.- CONCRETO 210 kg/cm2 | D47: m3 | E47: =PRESUPUESTOS!F47 -> 417.41 | F47: =IF(Q47=0,0,((M47/Q47)*J47)) -> 153.912 | G47: =ROUND(E47*F47,2) -> 64244.41 | H47: =J47-F47 -> 102.608 | I47: =ROUND(E47*H47,2) -> 42829.61 | J47: =PRESUPUESTOS!E47 -> 256.52 | K47: =ROUND(E47*J47,2) -> 107074.01 | L47: =PRESUPUESTOS!N47 -> 328.19 | M47: 152.37 | N47: =ROUND(M47*L47,2) -> 50006.31 | O47: =Q47-M47 -> 101.58 | P47: =ROUND(O47*L47,2) -> 33337.54 | Q47: =PRESUPUESTOS!M47 -> 253.95 | R47: =ROUND(Q47*L47,2) -> 83343.85
A48: 400 | B48: 02.03.05.09 | C48: MUROS DE CONTENC.- ENCOF. Y DESENCOFRADO | D48: m2 | E48: =PRESUPUESTOS!F48 -> 51.21 | F48: =IF(Q48=0,0,((M48/Q48)*J48)) -> 628.857 | G48: =ROUND(E48*F48,2) -> 32203.77 | H48: =J48-F48 -> 1467.333 | I48: =ROUND(E48*H48,2) -> 75142.12 | J48: =PRESUPUESTOS!E48 -> 2096.19 | K48: =ROUND(E48*J48,2) -> 107345.89 | L48: =PRESUPUESTOS!N48 -> 30.97 | M48: 622.569 | N48: =ROUND(M48*L48,2) -> 19280.96 | O48: =Q48-M48 -> 1452.661 | P48: =ROUND(O48*L48,2) -> 44988.91 | Q48: =PRESUPUESTOS!M48 -> 2075.23 | R48: =ROUND(Q48*L48,2) -> 64269.87
A49: 500 | B49: 02.03.05.11 | C49: MUROS DE CONTENC.- ACERO Fy=4200 kg/cm2 | D49: kg | E49: =PRESUPUESTOS!F49 -> 4.02 | F49: =IF(Q49=0,0,((M49/Q49)*J49)) -> 0 | G49: =ROUND(E49*F49,2) -> 0 | H49: =J49-F49 -> 18595.1 | I49: =ROUND(E49*H49,2) -> 74752.3 | J49: =PRESUPUESTOS!E49 -> 18595.1 | K49: =ROUND(E49*J49,2) -> 74752.3 | L49: =PRESUPUESTOS!N49 -> 0 | M49: 0 | N49: =ROUND(M49*L49,2) -> 0 | O49: =Q49-M49 -> 0 | P49: =ROUND(O49*L49,2) -> 0 | Q49: =PRESUPUESTOS!M49 -> 0 | R49: =ROUND(Q49*L49,2) -> 0
B50: 02.03.06 | C50: Columnas | E50: =PRESUPUESTOS!F50 -> 0 | F50: =IF(Q50=0,0,((M50/Q50)*J50)) -> 0 | G50: =ROUND(E50*F50,2) -> 0 | H50: =J50-F50 -> 0 | I50: =ROUND(E50*H50,2) -> 0 | J50: =PRESUPUESTOS!E50 -> 0 | K50: =ROUND(E50*J50,2) -> 0 | L50: =PRESUPUESTOS!N50 -> 0 | N50: =ROUND(M50*L50,2) -> 0 | O50: =Q50-M50 -> 0 | P50: =ROUND(O50*L50,2) -> 0 | Q50: =PRESUPUESTOS!M50 -> 0 | R50: =ROUND(Q50*L50,2) -> 0
A51: 300 | B51: 02.03.06.02 | C51: COLUMNAS - CONCRETO 210 KG/CM² - 1 PISO | D51: m3 | E51: =PRESUPUESTOS!F51 -> 442.62 | F51: =IF(Q51=0,0,((M51/Q51)*J51)) -> 0 | G51: =ROUND(E51*F51,2) -> 0 | H51: =J51-F51 -> 66.63 | I51: =ROUND(E51*H51,2) -> 29491.77 | J51: =PRESUPUESTOS!E51 -> 66.63 | K51: =ROUND(E51*J51,2) -> 29491.77 | L51: =PRESUPUESTOS!N51 -> 291.23 | M51: 0 | N51: =ROUND(M51*L51,2) -> 0 | O51: =Q51-M51 -> 67.96 | P51: =ROUND(O51*L51,2) -> 19791.99 | Q51: =PRESUPUESTOS!M51 -> 67.96 | R51: =ROUND(Q51*L51,2) -> 19791.99
A52: 400 | B52: 02.03.06.06 | C52: COLUMNAS.- ENCOFRADO Y DESENCOFRADO | D52: m2 | E52: =PRESUPUESTOS!F52 -> 60.48 | F52: =IF(Q52=0,0,((M52/Q52)*J52)) -> 270.414 | G52: =ROUND(E52*F52,2) -> 16354.64 | H52: =J52-F52 -> 630.966 | I52: =ROUND(E52*H52,2) -> 38160.82 | J52: =PRESUPUESTOS!E52 -> 901.38 | K52: =ROUND(E52*J52,2) -> 54515.46 | L52: =PRESUPUESTOS!N52 -> 37.49 | M52: 275.823 | N52: =ROUND(M52*L52,2) -> 10340.6 | O52: =Q52-M52 -> 643.587 | P52: =ROUND(O52*L52,2) -> 24128.08 | Q52: =PRESUPUESTOS!M52 -> 919.41 | R52: =ROUND(Q52*L52,2) -> 34468.68
A53: 500 | B53: 02.03.06.10 | C53: COLUMNAS.- ACERO Fy=4200 kg/cm2 | D53: KG | E53: =PRESUPUESTOS!F53 -> 4.02 | F53: =IF(Q53=0,0,((M53/Q53)*J53)) -> 6962.412 | G53: =ROUND(E53*F53,2) -> 27988.9 | H53: =J53-F53 -> 4641.608 | I53: =ROUND(E53*H53,2) -> 18659.26 | J53: =PRESUPUESTOS!E53 -> 11604.02 | K53: =ROUND(E53*J53,2) -> 46648.16 | L53: =PRESUPUESTOS!N53 -> 3.4 | M53: 7101.66 | N53: =ROUND(M53*L53,2) -> 24145.64 | O53: =Q53-M53 -> 4734.44 | P53: =ROUND(O53*L53,2) -> 16097.1 | Q53: =PRESUPUESTOS!M53 -> 11836.1 | R53: =ROUND(Q53*L53,2) -> 40242.74
B54: 02.03.07 | C54: Vigas | E54: =PRESUPUESTOS!F54 -> 0 | F54: =IF(Q54=0,0,((M54/Q54)*J54)) -> 0 | G54: =ROUND(E54*F54,2) -> 0 | H54: =J54-F54 -> 0 | I54: =ROUND(E54*H54,2) -> 0 | J54: =PRESUPUESTOS!E54 -> 0 | K54: =ROUND(E54*J54,2) -> 0 | L54: =PRESUPUESTOS!N54 -> 0 | N54: =ROUND(M54*L54,2) -> 0 | O54: =Q54-M54 -> 0 | P54: =ROUND(O54*L54,2) -> 0 | Q54: =PRESUPUESTOS!M54 -> 0 | R54: =ROUND(Q54*L54,2) -> 0
A55: 300 | B55: 02.03.07.02 | C55: VIGAS.- CONCRETO 210 kg/cm2 - 1 piso | D55: m3 | E55: =PRESUPUESTOS!F55 -> 325.93 | F55: =IF(Q55=0,0,((M55/Q55)*J55)) -> 0 | G55: =ROUND(E55*F55,2) -> 0 | H55: =J55-F55 -> 36.12 | I55: =ROUND(E55*H55,2) -> 11772.59 | J55: =PRESUPUESTOS!E55 -> 36.12 | K55: =ROUND(E55*J55,2) -> 11772.59 | L55: =PRESUPUESTOS!N55 -> 294.5 | M55: 0 | N55: =ROUND(M55*L55,2) -> 0 | O55: =Q55-M55 -> 36.84 | P55: =ROUND(O55*L55,2) -> 10849.38 | Q55: =PRESUPUESTOS!M55 -> 36.84 | R55: =ROUND(Q55*L55,2) -> 10849.38
A56: 400 | B56: 02.03.07.06 | C56: VIGAS.- ENCOFRADO Y DESENCOFRADO | D56: m2 | E56: =PRESUPUESTOS!F56 -> 70.38 | F56: =IF(Q56=0,0,((M56/Q56)*J56)) -> 163.569 | G56: =ROUND(E56*F56,2) -> 11511.99 | H56: =J56-F56 -> 381.661 | I56: =ROUND(E56*H56,2) -> 26861.3 | J56: =PRESUPUESTOS!E56 -> 545.23 | K56: =ROUND(E56*J56,2) -> 38373.29 | L56: =PRESUPUESTOS!N56 -> 43.56 | M56: 166.839 | N56: =ROUND(M56*L56,2) -> 7267.51 | O56: =Q56-M56 -> 389.291 | P56: =ROUND(O56*L56,2) -> 16957.52 | Q56: =PRESUPUESTOS!M56 -> 556.13 | R56: =ROUND(Q56*L56,2) -> 24225.02
A57: 500 | B57: 02.03.07.08 | C57: VIGAS.- ACERO Fy=4200 kg/cm2 | D57: KG | E57: =PRESUPUESTOS!F57 -> 4.02 | F57: =IF(Q57=0,0,((M57/Q57)*J57)) -> 3086.76 | G57: =ROUND(E57*F57,2) -> 12408.78 | H57: =J57-F57 -> 2057.84 | I57: =ROUND(E57*H57,2) -> 8272.52 | J57: =PRESUPUESTOS!E57 -> 5144.6 | K57: =ROUND(E57*J57,2) -> 20681.29 | L57: =PRESUPUESTOS!N57 -> 3.4 | M57: 3148.494 | N57: =ROUND(M57*L57,2) -> 10704.88 | O57: =Q57-M57 -> 2098.996 | P57: =ROUND(O57*L57,2) -> 7136.59 | Q57: =PRESUPUESTOS!M57 -> 5247.49 | R57: =ROUND(Q57*L57,2) -> 17841.47
B58: 02.03.08 | C58: Losas Macizas | E58: =PRESUPUESTOS!F58 -> 0 | F58: =IF(Q58=0,0,((M58/Q58)*J58)) -> 0 | G58: =ROUND(E58*F58,2) -> 0 | H58: =J58-F58 -> 0 | I58: =ROUND(E58*H58,2) -> 0 | J58: =PRESUPUESTOS!E58 -> 0 | K58: =ROUND(E58*J58,2) -> 0 | L58: =PRESUPUESTOS!N58 -> 0 | N58: =ROUND(M58*L58,2) -> 0 | O58: =Q58-M58 -> 0 | P58: =ROUND(O58*L58,2) -> 0 | Q58: =PRESUPUESTOS!M58 -> 0 | R58: =ROUND(Q58*L58,2) -> 0
A59: 300 | B59: 02.03.08.01 | C59: LOSAS MACIZAS.- CONC.210 kg/cm2 - 1 PISO | D59: M3 | E59: =PRESUPUESTOS!F59 -> 325.93 | F59: =IF(Q59=0,0,((M59/Q59)*J59)) -> 0 | G59: =ROUND(E59*F59,2) -> 0 | H59: =J59-F59 -> 0.63 | I59: =ROUND(E59*H59,2) -> 205.34 | J59: =PRESUPUESTOS!E59 -> 0.63 | K59: =ROUND(E59*J59,2) -> 205.34 | L59: =PRESUPUESTOS!N59 -> 294.5 | M59: 0 | N59: =ROUND(M59*L59,2) -> 0 | O59: =Q59-M59 -> 0.64 | P59: =ROUND(O59*L59,2) -> 188.48 | Q59: =PRESUPUESTOS!M59 -> 0.64 | R59: =ROUND(Q59*L59,2) -> 188.48
A60: 400 | B60: 02.03.08.03 | C60: LOSAS MACIZAS.- ENCOFRADO Y DESENCOFRADO | D60: m2 | E60: =PRESUPUESTOS!F60 -> 55.43 | F60: =IF(Q60=0,0,((M60/Q60)*J60)) -> 1.9237601 | G60: =ROUND(E60*F60,2) -> 106.63 | H60: =J60-F60 -> 4.6162399 | I60: =ROUND(E60*H60,2) -> 255.88 | J60: =PRESUPUESTOS!E60 -> 6.54 | K60: =ROUND(E60*J60,2) -> 362.51 | L60: =PRESUPUESTOS!N60 -> 33.34 | M60: 1.962 | N60: =ROUND(M60*L60,2) -> 65.41 | O60: =Q60-M60 -> 4.708 | P60: =ROUND(O60*L60,2) -> 156.96 | Q60: =PRESUPUESTOS!M60 -> 6.67 | R60: =ROUND(Q60*L60,2) -> 222.38
A61: 500 | B61: 02.03.08.04 | C61: LOSAS MACIZAS.- ACERO Fy=4,200 kg/cm2 | D61: KG | E61: =PRESUPUESTOS!F61 -> 4.02 | F61: =IF(Q61=0,0,((M61/Q61)*J61)) -> 43.031142 | G61: =ROUND(E61*F61,2) -> 172.99 | H61: =J61-F61 -> 30.118858 | I61: =ROUND(E61*H61,2) -> 121.08 | J61: =PRESUPUESTOS!E61 -> 73.15 | K61: =ROUND(E61*J61,2) -> 294.06 | L61: =PRESUPUESTOS!N61 -> 3.4 | M61: 43.89 | N61: =ROUND(M61*L61,2) -> 149.23 | O61: =Q61-M61 -> 30.72 | P61: =ROUND(O61*L61,2) -> 104.45 | Q61: =PRESUPUESTOS!M61 -> 74.61 | R61: =ROUND(Q61*L61,2) -> 253.67
B62: 02.03.09 | C62: Losas Aligeradas | E62: =PRESUPUESTOS!F62 -> 0 | F62: =IF(Q62=0,0,((M62/Q62)*J62)) -> 0 | G62: =ROUND(E62*F62,2) -> 0 | H62: =J62-F62 -> 0 | I62: =ROUND(E62*H62,2) -> 0 | J62: =PRESUPUESTOS!E62 -> 0 | K62: =ROUND(E62*J62,2) -> 0 | L62: =PRESUPUESTOS!N62 -> 0 | N62: =ROUND(M62*L62,2) -> 0 | O62: =Q62-M62 -> 0 | P62: =ROUND(O62*L62,2) -> 0 | Q62: =PRESUPUESTOS!M62 -> 0 | R62: =ROUND(Q62*L62,2) -> 0
A63: 300 | B63: 02.03.09.01 | C63: LOSA ALIGERADA - CONCRETO 210 kg/cm2 - 1 PISO | D63: m3 | E63: =PRESUPUESTOS!F63 -> 315.52 | F63: =IF(Q63=0,0,((M63/Q63)*J63)) -> 0 | G63: =ROUND(E63*F63,2) -> 0 | H63: =J63-F63 -> 2.13 | I63: =ROUND(E63*H63,2) -> 672.06 | J63: =PRESUPUESTOS!E63 -> 2.13 | K63: =ROUND(E63*J63,2) -> 672.06 | L63: =PRESUPUESTOS!N63 -> 294.5 | M63: 0 | N63: =ROUND(M63*L63,2) -> 0 | O63: =Q63-M63 -> 2.17 | P63: =ROUND(O63*L63,2) -> 639.07 | Q63: =PRESUPUESTOS!M63 -> 2.17 | R63: =ROUND(Q63*L63,2) -> 639.07
A64: 400 | B64: 02.03.09.03 | C64: LOSA ALIGERADA.- ENCOFRADO Y DESENCOFRADO | D64: m2 | E64: =PRESUPUESTOS!F64 -> 43.61 | F64: =IF(Q64=0,0,((M64/Q64)*J64)) -> 7.416 | G64: =ROUND(E64*F64,2) -> 323.41 | H64: =J64-F64 -> 17.304 | I64: =ROUND(E64*H64,2) -> 754.63 | J64: =PRESUPUESTOS!E64 -> 24.72 | K64: =ROUND(E64*J64,2) -> 1078.04 | L64: =PRESUPUESTOS!N64 -> 25.75 | M64: 7.563 | N64: =ROUND(M64*L64,2) -> 194.75 | O64: =Q64-M64 -> 17.647 | P64: =ROUND(O64*L64,2) -> 454.41 | Q64: =PRESUPUESTOS!M64 -> 25.21 | R64: =ROUND(Q64*L64,2) -> 649.16
A65: 500 | B65: 02.03.09.04 | C65: LOSA ALIGERADA.- ACERO Fy=4,200 kg/cm2 | D65: KG | E65: =PRESUPUESTOS!F65 -> 4.02 | F65: =IF(Q65=0,0,((M65/Q65)*J65)) -> 56.358 | G65: =ROUND(E65*F65,2) -> 226.56 | H65: =J65-F65 -> 37.572 | I65: =ROUND(E65*H65,2) -> 151.04 | J65: =PRESUPUESTOS!E65 -> 93.93 | K65: =ROUND(E65*J65,2) -> 377.6 | L65: =PRESUPUESTOS!N65 -> 3.4 | M65: 57.486 | N65: =ROUND(M65*L65,2) -> 195.45 | O65: =Q65-M65 -> 38.324 | P65: =ROUND(O65*L65,2) -> 130.3 | Q65: =PRESUPUESTOS!M65 -> 95.81 | R65: =ROUND(Q65*L65,2) -> 325.75
A66: 300 | B66: 02.03.09.05 | C66: LOSA ALIGERADA.- LADR. HUECO 15x30x30 | D66: und | E66: =PRESUPUESTOS!F66 -> 2.49 | F66: =IF(Q66=0,0,((M66/Q66)*J66)) -> 61.776 | G66: =ROUND(E66*F66,2) -> 153.82 | H66: =J66-F66 -> 144.144 | I66: =ROUND(E66*H66,2) -> 358.92 | J66: =PRESUPUESTOS!E66 -> 205.92 | K66: =ROUND(E66*J66,2) -> 512.74 | L66: =PRESUPUESTOS!N66 -> 2.39 | M66: 63.012 | N66: =ROUND(M66*L66,2) -> 150.6 | O66: =Q66-M66 -> 147.028 | P66: =ROUND(O66*L66,2) -> 351.4 | Q66: =PRESUPUESTOS!M66 -> 210.04 | R66: =ROUND(Q66*L66,2) -> 502
B67: 02.03.15 | C67: Gradas Armadas en Pisos | E67: =PRESUPUESTOS!F67 -> 0 | F67: =IF(Q67=0,0,((M67/Q67)*J67)) -> 0 | G67: =ROUND(E67*F67,2) -> 0 | H67: =J67-F67 -> 0 | I67: =ROUND(E67*H67,2) -> 0 | J67: =PRESUPUESTOS!E67 -> 0 | K67: =ROUND(E67*J67,2) -> 0 | L67: =PRESUPUESTOS!N67 -> 0 | N67: =ROUND(M67*L67,2) -> 0 | O67: =Q67-M67 -> 0 | P67: =ROUND(O67*L67,2) -> 0 | Q67: =PRESUPUESTOS!M67 -> 0 | R67: =ROUND(Q67*L67,2) -> 0
A68: 300 | B68: 02.03.15.01 | C68: GRADAS EN PISO, CONCRETO F'c=175 kg/cm2. | D68: m2 | E68: =PRESUPUESTOS!F68 -> 80.04 | F68: =IF(Q68=0,0,((M68/Q68)*J68)) -> 0 | G68: =ROUND(E68*F68,2) -> 0 | H68: =J68-F68 -> 12.31 | I68: =ROUND(E68*H68,2) -> 985.29 | J68: =PRESUPUESTOS!E68 -> 12.31 | K68: =ROUND(E68*J68,2) -> 985.29 | L68: =PRESUPUESTOS!N68 -> 59.8 | M68: 0 | N68: =ROUND(M68*L68,2) -> 0 | O68: =Q68-M68 -> 12.56 | P68: =ROUND(O68*L68,2) -> 751.09 | Q68: =PRESUPUESTOS!M68 -> 12.56 | R68: =ROUND(Q68*L68,2) -> 751.09
A69: 400 | B69: 02.03.15.03 | C69: GRADAS, ENCOFRADO Y DESENCOFRADO | D69: m2 | E69: =PRESUPUESTOS!F69 -> 41.15 | F69: =IF(Q69=0,0,((M69/Q69)*J69)) -> 2.088 | G69: =ROUND(E69*F69,2) -> 85.92 | H69: =J69-F69 -> 4.872 | I69: =ROUND(E69*H69,2) -> 200.48 | J69: =PRESUPUESTOS!E69 -> 6.96 | K69: =ROUND(E69*J69,2) -> 286.4 | L69: =PRESUPUESTOS!N69 -> 27.36 | M69: 2.13 | N69: =ROUND(M69*L69,2) -> 58.28 | O69: =Q69-M69 -> 4.97 | P69: =ROUND(O69*L69,2) -> 135.98 | Q69: =PRESUPUESTOS!M69 -> 7.1 | R69: =ROUND(Q69*L69,2) -> 194.26
A70: 500 | B70: 02.03.15.04 | C70: GRADAS EN PISO, ACERO fy=4200kg/cm2 | D70: kg | E70: =PRESUPUESTOS!F70 -> 4.02 | F70: =IF(Q70=0,0,((M70/Q70)*J70)) -> 24.903 | G70: =ROUND(E70*F70,2) -> 100.11 | H70: =J70-F70 -> 58.107 | I70: =ROUND(E70*H70,2) -> 233.59 | J70: =PRESUPUESTOS!E70 -> 83.01 | K70: =ROUND(E70*J70,2) -> 333.7 | L70: =PRESUPUESTOS!N70 -> 3.4 | M70: 25.401 | N70: =ROUND(M70*L70,2) -> 86.36 | O70: =Q70-M70 -> 59.269 | P70: =ROUND(O70*L70,2) -> 201.51 | Q70: =PRESUPUESTOS!M70 -> 84.67 | R70: =ROUND(Q70*L70,2) -> 287.88
C71: COSTO DIRECTO | G71: =SUM(G7:G70) -> 306974.88 | I71: =SUM(I7:I70) -> 653749.69 | K71: =SUM(K7:K70) -> 960724.52 | N71: =SUM(N7:N70) -> 248357.12 | P71: =SUM(P7:P70) -> 448153.56 | R71: =SUM(R7:R70) -> 696510.67
C72: GASTOS GENERALES (10%) | G72: =ROUND(G71*0.1,2) -> 30697.49 | I72: =ROUND(I71*0.1,2) -> 65374.97 | K72: =ROUND(K71*0.1,2) -> 96072.45 | N72: =ROUND(N71*0.1,2) -> 24835.71 | P72: =ROUND(P71*0.1,2) -> 44815.36 | R72: =ROUND(R71*0.1,2) -> 69651.07
C73: UTILIDAD (8%) | G73: =ROUND(G71*0.08,2) -> 24557.99 | I73: =ROUND(I71*0.08,2) -> 52299.98 | K73: =ROUND(K71*0.08,2) -> 76857.96
C74: SUBTOTAL | G74: =SUM(G71:G73) -> 362230.36 | I74: =SUM(I71:I73) -> 771424.64 | K74: =SUM(K71:K73) -> 1133654.9 | N74: =SUM(N71:N73) -> 273192.83 | P74: =SUM(P71:P73) -> 492968.92 | R74: =SUM(R71:R73) -> 766161.74
C75: IGV (18.00%) | G75: =ROUND(G74*0.18,2) -> 65201.46 | I75: =ROUND(I74*0.18,2) -> 138856.44 | K75: =ROUND(K74*0.18,2) -> 204057.89 | N75: =ROUND(N74*0.18,2) -> 49174.71 | P75: =ROUND(P74*0.18,2) -> 88734.41 | R75: =ROUND(R74*0.18,2) -> 137909.11
C76: COSTO TOTAL (INC. IGV) | G76: =SUM(G74:G75) -> 427431.82 | I76: =SUM(I74:I75) -> 910281.08 | K76: =SUM(K74:K75) -> 1337712.8 | N76: =SUM(N74:N75) -> 322367.54 | P76: =SUM(P74:P75) -> 581703.33 | R76: =SUM(R74:R75) -> 904070.85
J81: 130 | L81: 220 | M81: reales
J83: =+L83*0.59 -> 95.3145 | L83: 161.55 | M83: presup
L85: =+J81/L81 -> 0.59090909

Sheet COSTO INDIRECTO
B1: COSTOS INDIRECTOS
B3: ITEM | C3: DESCRIPCION | D3: COSTO PREVISTO META | K3: PREVISTO ACTUALIZADO | N3: COSTO PREVISTO EJECUTADO
D4: UNIDAD | E4: CANTIDAD | F4: TIEMPO | G4: PARTICIPACION | H4: COSTO | I4: PARCIAL | K4: COSTO | L4: PARCIAL | N4: METRADO | O4: COSTO PREVISTO A LA FECHA | P4: COSTO PENDIENTE
C5: GASTOS GENERALES FIJOS | I5: =SUM(I6:I9) -> 3500 | L5: =SUM(L6:L9) -> 6400 | O5: =SUM(O6:O9) -> 800 | P5: =SUM(P6:P9) -> 5600
B6: 1 | C6: Pruebas y ensayos
C7: Diseño de Mezcla | D7: est | E7: 2 | H7: 750 | I7: =E7*H7 -> 1500 | L7: =+'ANALISIS COSTOS INDIRECTOS'!L7 -> 1600 | N7: 0.4 | O7: =SUM('ANALISIS COSTOS INDIRECTOS'!N7) -> 800 | P7: =L7-O7 -> 800
C8: Ensayos Varios | D8: und | E8: 2 | H8: 500 | I8: =E8*H8 -> 1000 | L8: =+'ANALISIS COSTOS INDIRECTOS'!L8 -> 2400 | N8: 0 | O8: =SUM('ANALISIS COSTOS INDIRECTOS'!N8) -> 0 | P8: =L8-O8 -> 2400
C9: Rotura de Probetas | D9: Und | E9: 2 | H9: 500 | I9: =E9*H9 -> 1000 | L9: =+'ANALISIS COSTOS INDIRECTOS'!L9 -> 2400 | N9: 0 | O9: =SUM('ANALISIS COSTOS INDIRECTOS'!N9) -> 0 | P9: =L9-O9 -> 2400
C11: GASTOS GENERALES VARIABLES | I11: =SUM(I12:I34) -> 160049.99 | L11: =SUM(L12:L34) -> 231312.21 | O11: =SUM(O12:O34) -> 70733.441 | P11: =SUM(P12:P34) -> 160578.77
B12: 1.01 | C12: Personal Profesional
C13: Residente de obra (Ing.Civil) | D13: mes | E13: 1 | F13: 5 | G13: 1 | H13: 10000 | I13: =+E13*F13*G13*H13 -> 50000 | L13: =+'ANALISIS COSTOS INDIRECTOS'!L13 -> 81000 | N13: 1 | O13: =SUM('ANALISIS COSTOS INDIRECTOS'!N13) -> 27000 | P13: =L13-O13 -> 54000
C14: Especialista de calidad(Ing.Civil) | D14: mes | E14: 1 | F14: 5 | G14: 0.5 | H14: 4500 | I14: =+E14*F14*G14*H14 -> 11250 | L14: =+'ANALISIS COSTOS INDIRECTOS'!L14 -> 25800 | N14: 1 | O14: =SUM('ANALISIS COSTOS INDIRECTOS'!N14) -> 8600 | P14: =L14-O14 -> 17200
C15: Especialista de Seguridad (Ing. De Seguridad) | D15: mes | E15: 1 | F15: 5 | G15: 1 | H15: 4000 | I15: =+E15*F15*G15*H15 -> 20000 | L15: =+'ANALISIS COSTOS INDIRECTOS'!L15 -> 25200 | N15: 1 | O15: =SUM('ANALISIS COSTOS INDIRECTOS'!N15) -> 8400 | P15: =L15-O15 -> 16800
C16: Administrador de obra | D16: mes | E16: 1 | F16: 5 | G16: 1 | H16: 3000 | I16: =+E16*F16*G16*H16 -> 15000 | L16: =+'ANALISIS COSTOS INDIRECTOS'!L16 -> 12500 | N16: 1 | O16: =SUM('ANALISIS COSTOS INDIRECTOS'!N16) -> 2500 | P16: =L16-O16 -> 10000
B17: 2.01 | C17: Personal Tecnico
C18: Maestro de Obra | D18: mes | E18: 1 | F18: 5 | G18: 1 | H18: 3500 | I18: =+E18*F18*G18*H18 -> 17500 | L18: =+'ANALISIS COSTOS INDIRECTOS'!L18 -> 21000 | N18: 1 | O18: =SUM('ANALISIS COSTOS INDIRECTOS'!N18) -> 7000 | P18: =L18-O18 -> 14000
C19: Almacenero | D19: mes | E19: 1 | F19: 5 | G19: 1 | H19: 1500 | I19: =+E19*F19*G19*H19 -> 7500 | L19: =+'ANALISIS COSTOS INDIRECTOS'!L19 -> 10800 | N19: 1 | O19: =SUM('ANALISIS COSTOS INDIRECTOS'!N19) -> 3600 | P19: =L19-O19 -> 7200
C20: Guardián | D20: mes | E20: 1 | F20: 5 | G20: 1 | H20: 1300 | I20: =+E20*F20*G20*H20 -> 6500 | L20: =+'ANALISIS COSTOS INDIRECTOS'!L20 -> 8100 | N20: 1 | O20: =SUM('ANALISIS COSTOS INDIRECTOS'!N20) -> 2700 | P20: =L20-O20 -> 5400
C21: Asistente técnico | D21: mes | E21: 1 | F21: 5 | G21: 1 | H21: 2000 | I21: =+E21*F21*G21*H21 -> 10000 | L21: =+'ANALISIS COSTOS INDIRECTOS'!L21 -> 12600 | N21: 1 | O21: =SUM('ANALISIS COSTOS INDIRECTOS'!N21) -> 4200 | P21: =L21-O21 -> 8400
B22: 3.01 | C22: Consumos, Moviliarios y Servicios Oficinas
C23: Utiles de oficina y dibujo | D23: mes | F23: 5 | H23: 100 | I23: =+F23*H23 -> 500 | L23: =+'ANALISIS COSTOS INDIRECTOS'!L23 -> 980 | N23: 1 | O23: =SUM('ANALISIS COSTOS INDIRECTOS'!N23) -> 200 | P23: =L23-O23 -> 780
C24: Cuaderno de Obra y Legalizacion | D24: vez | F24: 1 | H24: 250 | I24: =+F24*H24 -> 250 | L24: =+'ANALISIS COSTOS INDIRECTOS'!L24 -> 600 | N24: 0.2 | O24: =SUM('ANALISIS COSTOS INDIRECTOS'!N24) -> 300 | P24: =L24-O24 -> 300
C25: Insumos para impresora y fotocopiadora | D25: mes | F25: 5 | H25: 100 | I25: =+F25*H25 -> 500 | L25: =+'ANALISIS COSTOS INDIRECTOS'!L25 -> 615 | N25: 1 | O25: =SUM('ANALISIS COSTOS INDIRECTOS'!N25) -> 120 | P25: =L25-O25 -> 495
C26: Pólizas y Seguros | D26: mes | F26: 5 | H26: 500 | I26: =+F26*H26 -> 2500 | L26: =+'ANALISIS COSTOS INDIRECTOS'!L26 -> 3120 | N26: 1 | O26: =SUM('ANALISIS COSTOS INDIRECTOS'!N26) -> 600 | P26: =L26-O26 -> 2520
C27: Implementos de seguridad | D27: vez | F27: 1 | H27: 900 | I27: =+F27*H27 -> 900 | L27: =+'ANALISIS COSTOS INDIRECTOS'!L27 -> 4620 | N27: 0.2 | O27: =SUM('ANALISIS COSTOS INDIRECTOS'!N27) -> 850 | P27: =L27-O27 -> 3770
C28: Botiquín | D28: mes | F28: 5 | H28: 150 | I28: =+F28*H28 -> 750 | L28: =+'ANALISIS COSTOS INDIRECTOS'!L28 -> 560 | N28: 1 | O28: =SUM('ANALISIS COSTOS INDIRECTOS'!N28) -> 100 | P28: =L28-O28 -> 460
C29: Liquidaciòn de obra | D29: vez | F29: 1 | H29: 1000 | I29: =+F29*H29 -> 1000 | L29: =+'ANALISIS COSTOS INDIRECTOS'!L29 -> 1000 | N29: 0 | O29: =SUM('ANALISIS COSTOS INDIRECTOS'!N29) -> 0 | P29: =L29-O29 -> 1000
B30: 4.01 | C30: Gastos Financieros
C31: Carta Fianza de Adelanto Directo | F31: 5 | G31: 0.0013 | H31: 192144.9 | I31: =+F31*G31*H31 -> 1248.9419 | L31: =+'ANALISIS COSTOS INDIRECTOS'!L31 -> 2401.8113 | N31: 1 | O31: =SUM('ANALISIS COSTOS INDIRECTOS'!N31) -> 480.36226 | P31: =L31-O31 -> 1921.449
C32: Carta Fianza de Adelanto de Materiales | F32: 5 | G32: 0.0013 | H32: 384289.81 | I32: =+F32*G32*H32 -> 2497.8838 | L32: =+'ANALISIS COSTOS INDIRECTOS'!L32 -> 4803.6226 | N32: 1 | O32: =SUM('ANALISIS COSTOS INDIRECTOS'!N32) -> 960.72452 | P32: =L32-O32 -> 3842.8981
C33: Carta Fianza de Fiel cumplimiento | F33: 5 | G33: 0.0013 | H33: 96072.452 | I33: =+F33*G33*H33 -> 624.47094 | L33: =+'ANALISIS COSTOS INDIRECTOS'!L33 -> 1200.9057 | N33: 1 | O33: =SUM('ANALISIS COSTOS INDIRECTOS'!N33) -> 240.18113 | P33: =L33-O33 -> 960.72452
C34: SENCICO | F34: 5 | G34: 0.002 | H34: 1152869.4 | I34: =+F34*G34*H34 -> 11528.694 | L34: =+'ANALISIS COSTOS INDIRECTOS'!L34 -> 14410.868 | N34: 1 | O34: =SUM('ANALISIS COSTOS INDIRECTOS'!N34) -> 2882.1736 | P34: =L34-O34 -> 11528.694

Sheet ANALISIS COSTOS INDIRECTOS
B1: ANALISIS DE COSTOS INDIRECTOS
B3: ITEM | C3: DESCRIPCION | D3: COSTO PREVISTO META | K3: PREVISTO ACTUALIZADO | N3: MESES
D4: UNIDAD | E4: CANTIDAD | F4: TIEMPO | G4: PARTICIPACION | H4: COSTO | I4: PARCIAL | K4: COSTO | L4: PARCIAL | N4: MES 1 NOVIEMBRE | O4: MES 2 DICIEMBRE | P4: MES 3 ENERO | Q4: MES 4 FEBRERO | R4: MES 5 MARZO
C5: GASTOS GENERALES FIJOS | I5: =SUM(I6:I9) -> 3500 | L5: =SUM(L6:L9) -> 6400
B6: 1 | C6: Pruebas y ensayos
C7: Diseño de Mezcla | D7: est | E7: 2 | H7: 750 | I7: =E7*H7 -> 1500 | L7: =SUM(N7:R7) -> 1600 | N7: 800 | O7: 800
C8: Ensayos Varios | D8: und | E8: 2 | H8: 500 | I8: =E8*H8 -> 1000 | L8: =SUM(N8:R8) -> 2400 | O8: 600 | P8: 600 | Q8: 600 | R8: 600
C9: Rotura de Probetas | D9: Und | E9: 2 | H9: 500 | I9: =E9*H9 -> 1000 | L9: =SUM(N9:R9) -> 2400 | O9: 600 | P9: 600 | Q9: 600 | R9: 600
C11: GASTOS GENERALES VARIABLES | I11: =SUM(I12:I34) -> 160049.99 | L11: =SUM(L12:L34) -> 231312.21
B12: 1.01 | C12: Personal Profesional
C13: Residente de obra (Ing.Civil) | D13: mes | E13: 1 | F13: 5 | G13: 1 | H13: 10000 | I13: =+E13*F13*G13*H13 -> 50000 | L13: =SUM(N13:R13) -> 81000 | N13: =13500*2 -> 27000 | O13: 13500 | P13: 13500 | Q13: 13500 | R13: 13500
C14: Especialista de calidad(Ing.Civil) | D14: mes | E14: 1 | F14: 5 | G14: 0.5 | H14: 4500 | I14: =+E14*F14*G14*H14 -> 11250 | L14: =SUM(N14:R14) -> 25800 | N14: =4300*2 -> 8600 | O14: 4300 | P14: 4300 | Q14: 4300 | R14: 4300
C15: Especialista de Seguridad (Ing. De Seguridad) | D15: mes | E15: 1 | F15: 5 | G15: 1 | H15: 4000 | I15: =+E15*F15*G15*H15 -> 20000 | L15: =SUM(N15:R15) -> 25200 | N15: =4200*2 -> 8400 | O15: 4200 | P15: 4200 | Q15: 4200 | R15: 4200
C16: Administrador de obra | D16: mes | E16: 1 | F16: 5 | G16: 1 | H16: 3000 | I16: =+E16*F16*G16*H16 -> 15000 | L16: =SUM(N16:R16) -> 12500 | N16: 2500 | O16: 2500 | P16: 2500 | Q16: 2500 | R16: 2500
B17: 2.01 | C17: Personal Tecnico
C18: Maestro de Obra | D18: mes | E18: 1 | F18: 5 | G18: 1 | H18: 3500 | I18: =+E18*F18*G18*H18 -> 17500 | L18: =SUM(N18:R18) -> 21000 | N18: =3500*2 -> 7000 | O18: 3500 | P18: 3500 | Q18: 3500 | R18: 3500
C19: Almacenero | D19: mes | E19: 1 | F19: 5 | G19: 1 | H19: 1500 | I19: =+E19*F19*G19*H19 -> 7500 | L19: =SUM(N19:R19) -> 10800 | N19: =1800*2 -> 3600 | O19: 1800 | P19: 1800 | Q19: 1800 | R19: 1800
C20: Guardián | D20: mes | E20: 1 | F20: 5 | G20: 1 | H20: 1300 | I20: =+E20*F20*G20*H20 -> 6500 | L20: =SUM(N20:R20) -> 8100 | N20: =1350*2 -> 2700 | O20: 1350 | P20: 1350 | Q20: 1350 | R20: 1350
C21: Asistente técnico | D21: mes | E21: 1 | F21: 5 | G21: 1 | H21: 2000 | I21: =+E21*F21*G21*H21 -> 10000 | L21: =SUM(N21:R21) -> 12600 | N21: =2100*2 -> 4200 | O21: 2100 | P21: 2100 | Q21: 2100 | R21: 2100
B22: 3.01 | C22: Consumos, Moviliarios y Servicios Oficinas
C23: Utiles de oficina y dibujo | D23: mes | F23: 5 | H23: 100 | I23: =+F23*H23 -> 500 | L23: =SUM(N23:R23) -> 980 | N23: 200 | O23: 200 | P23: 210 | Q23: 180 | R23: 190
C24: Cuaderno de Obra y Legalizacion | D24: vez | F24: 1 | H24: 250 | I24: =+F24*H24 -> 250 | L24: =SUM(N24:R24) -> 600 | N24: 300 | P24: 300
C25: Insumos para impresora y fotocopiadora | D25: mes | F25: 5 | H25: 100 | I25: =+F25*H25 -> 500 | L25: =SUM(N25:R25) -> 615 | N25: 120 | O25: 120 | P25: 120 | Q25: 125 | R25: 130
C26: Pólizas y Seguros | D26: mes | F26: 5 | H26: 500 | I26: =+F26*H26 -> 2500 | L26: =SUM(N26:R26) -> 3120 | N26: 600 | O26: 600 | P26: 650 | Q26: 650 | R26: 620
C27: Implementos de seguridad | D27: vez | F27: 1 | H27: 900 | I27: =+F27*H27 -> 900 | L27: =SUM(N27:R27) -> 4620 | N27: 850 | O27: 920 | P27: 970 | Q27: 930 | R27: 950
C28: Botiquín | D28: mes | F28: 5 | H28: 150 | I28: =+F28*H28 -> 750 | L28: =SUM(N28:R28) -> 560 | N28: 100 | O28: 105 | P28: 120 | Q28: 125 | R28: 110
C29: Liquidaciòn de obra | D29: vez | F29: 1 | H29: 1000 | I29: =+F29*H29 -> 1000 | L29: =SUM(N29:R29) -> 1000 | R29: 1000
B30: 4.01 | C30: Gastos Financieros
C31: Carta Fianza de Adelanto Directo | F31: 5 | G31: 0.0013 | H31: 192144.9 | I31: =+F31*G31*H31 -> 1248.9419 | L31: =SUM(N31:R31) -> 2401.8113 | N31: =+H31*0.25% -> 480.36226 | O31: =+H31*0.25% -> 480.36226 | P31: =+H31*0.25% -> 480.36226 | Q31: =+H31*0.25% -> 480.36226 | R31: =+H31*0.25% -> 480.36226
C32: Carta Fianza de Adelanto de Materiales | F32: 5 | G32: 0.0013 | H32: 384289.81 | I32: =+F32*G32*H32 -> 2497.8838 | L32: =SUM(N32:R32) -> 4803.6226 | N32: =+H32*0.25% -> 960.72452 | O32: =+H32*0.25% -> 960.72452 | P32: =+H32*0.25% -> 960.72452 | Q32: =+H32*0.25% -> 960.72452 | R32: =+H32*0.25% -> 960.72452
C33: Carta Fianza de Fiel cumplimiento | F33: 5 | G33: 0.0013 | H33: 96072.452 | I33: =+F33*G33*H33 -> 624.47094 | L33: =SUM(N33:R33) -> 1200.9057 | N33: =+H33*0.25% -> 240.18113 | O33: =+H33*0.25% -> 240.18113 | P33: =+H33*0.25% -> 240.18113 | Q33: =+H33*0.25% -> 240.18113 | R33: =+H33*0.25% -> 240.18113
C34: SENCICO | F34: 5 | G34: 0.002 | H34: 1152869.4 | I34: =+F34*G34*H34 -> 11528.694 | L34: =SUM(N34:R34) -> 14410.868 | N34: =+H34*0.25% -> 2882.1736 | O34: =+H34*0.25% -> 2882.1736 | P34: =+H34*0.25% -> 2882.1736 | Q34: =+H34*0.25% -> 2882.1736 | R34: =+H34*0.25% -> 2882.1736

Sheet RESUMEN - ANALISIS
A1: RESUMEN
A3: PROYECTO: | B3: I.E. N° 1182 "EL BOSQUE" - CERCO + INGRESOS Y CASETAS
C4: ANALISIS DE PRECIOS VENTA | F4: COSTO PREVISTO
A5: CODIGO | B5: PARTIDA DE CONTROL | C5: COSTO TOTAL VENTA | D5: % | E5: COSTO EJECUTADO VENTA | F5: COSTO TOTAL META | G5: % | H5: COSTO EJECUTADO META
B6: PRESUPUESTO CONTRACTUAL
A7: 100 | B7: OBRAS PROVISIONALES | C7: =SUMIF('COSTO DIRECTO'!$A$7:$A$70,'RESUMEN - ANALISIS'!A7,'COSTO DIRECTO'!$K$7:$K$70) -> 3661.14 | D7: =E7/C7 -> 0.12499932 | E7: =SUMIF('COSTO DIRECTO'!$A$7:$A$70,'RESUMEN - ANALISIS'!A7,'COSTO DIRECTO'!$G$7:$G$70) -> 457.64 | F7: =SUMIF('COSTO DIRECTO'!$A$7:$A$70,'RESUMEN - ANALISIS'!A7,'COSTO DIRECTO'!$R$7:$R$70) -> 2506.28 | G7: =H7/F7 -> 0.12499801 | H7: =SUMIF('COSTO DIRECTO'!$A$7:$A$70,'RESUMEN - ANALISIS'!A7,'COSTO DIRECTO'!$N$7:$N$70) -> 313.28
A8: 200 | B8: MOVIMIENTO DE TIERRAS | C8: =SUMIF('COSTO DIRECTO'!$A$7:$A$70,'RESUMEN - ANALISIS'!A8,'COSTO DIRECTO'!$K$7:$K$70) -> 159518.36 | D8: =E8/C8 -> 0.13756366 | E8: =SUMIF('COSTO DIRECTO'!$A$7:$A$70,'RESUMEN - ANALISIS'!A8,'COSTO DIRECTO'!$G$7:$G$70) -> 21943.93 | F8: =SUMIF('COSTO DIRECTO'!$A$7:$A$70,'RESUMEN - ANALISIS'!A8,'COSTO DIRECTO'!$R$7:$R$70) -> 102563.43 | G8: =H8/F8 -> 0.11749802 | H8: =SUMIF('COSTO DIRECTO'!$A$7:$A$70,'RESUMEN - ANALISIS'!A8,'COSTO DIRECTO'!$N$7:$N$70) -> 12051
A9: 300 | B9: CONCRETO | C9: =SUMIF('COSTO DIRECTO'!$A$7:$A$70,'RESUMEN - ANALISIS'!A9,'COSTO DIRECTO'!$K$7:$K$70) -> 360886.42 | D9: =E9/C9 -> 0.40097366 | E9: =SUMIF('COSTO DIRECTO'!$A$7:$A$70,'RESUMEN - ANALISIS'!A9,'COSTO DIRECTO'!$G$7:$G$70) -> 144705.95 | F9: =SUMIF('COSTO DIRECTO'!$A$7:$A$70,'RESUMEN - ANALISIS'!A9,'COSTO DIRECTO'!$R$7:$R$70) -> 335452.9 | G9: =H9/F9 -> 0.39375623 | H9: =SUMIF('COSTO DIRECTO'!$A$7:$A$70,'RESUMEN - ANALISIS'!A9,'COSTO DIRECTO'!$N$7:$N$70) -> 132086.67
A10: 400 | B10: ENCOFRADO | C10: =SUMIF('COSTO DIRECTO'!$A$7:$A$70,'RESUMEN - ANALISIS'!A10,'COSTO DIRECTO'!$K$7:$K$70) -> 221395.36 | D10: =E10/C10 -> 0.28554849 | E10: =SUMIF('COSTO DIRECTO'!$A$7:$A$70,'RESUMEN - ANALISIS'!A10,'COSTO DIRECTO'!$G$7:$G$70) -> 63219.11 | F10: =SUMIF('COSTO DIRECTO'!$A$7:$A$70,'RESUMEN - ANALISIS'!A10,'COSTO DIRECTO'!$R$7:$R$70) -> 136602.51 | G10: =H10/F10 -> 0.28322979 | H10: =SUMIF('COSTO DIRECTO'!$A$7:$A$70,'RESUMEN - ANALISIS'!A10,'COSTO DIRECTO'!$N$7:$N$70) -> 38689.9
A11: 500 | B11: ACERO | C11: =SUMIF('COSTO DIRECTO'!$A$7:$A$70,'RESUMEN - ANALISIS'!A11,'COSTO DIRECTO'!$K$7:$K$70) -> 215263.24 | D11: =E11/C11 -> 0.35606753 | E11: =SUMIF('COSTO DIRECTO'!$A$7:$A$70,'RESUMEN - ANALISIS'!A11,'COSTO DIRECTO'!$G$7:$G$70) -> 76648.25 | F11: =SUMIF('COSTO DIRECTO'!$A$7:$A$70,'RESUMEN - ANALISIS'!A11,'COSTO DIRECTO'!$R$7:$R$70) -> 119385.55 | G11: =H11/F11 -> 0.54626603 | H11: =SUMIF('COSTO DIRECTO'!$A$7:$A$70,'RESUMEN - ANALISIS'!A11,'COSTO DIRECTO'!$N$7:$N$70) -> 65216.27
B12: TOTALES | C12: =SUM(C7:C11) -> 960724.52 | E12: =SUM(E7:E11) -> 306974.88 | F12: =SUM(F7:F11) -> 696510.67 | H12: =SUM(H7:H11) -> 248357.12
A15: CODIGO | B15: PARTIDA DE CONTROL | C15: COSTO TOTAL VENTA | D15: % | E15: COSTO EJECUTADO VENTA | F15: COSTO TOTAL META | G15: % | H15: COSTO EJECUTADO META
A17: 600 | B17: GASTOS GENERALES | C17: =PRESUPUESTOS!G72 -> 96072.45 | D17: =E17/C17 -> 0.31952436 | E17: =E12*0.1 -> 30697.488 | F17: ='COSTO INDIRECTO'!L5+'COSTO INDIRECTO'!L11 -> 237712.21 | G17: =H17/F17 -> 0.30092456 | H17: ='COSTO INDIRECTO'!O5+'COSTO INDIRECTO'!O11 -> 71533.441
B18: UTILIDAD | C18: =PRESUPUESTOS!G73 -> 76857.96 | D18: =E18/C18 -> 0.31952436 | E18: =E12*0.08 -> 24557.99
B20: OTROS
B21: REINTEGROS POR FORMULA POLINOMICA | C21: =C12*0.02 -> 19214.49 | D21: =E21/C21 -> 0.062452866 | E21: 1200
B23: CONTINGENCIAS
B24: CONTING. INFRAESTRUCTURAS (2%) | F24: =F12*0.02 -> 13930.213 | G24: =H24/F24 -> 0 | H24: 0
B25: CONTING. EQUIP. BIOMEDICO (2%) | F25: 0
B26: CONTING. LEVANT. OBSERVACIONES (1.5%) | F26: =F12*0.015 -> 10447.66 | G26: =H26/F26 -> 0 | H26: 0
B28: TOTALES | C28: =SUM(C16:C27) -> 192144.9 | E28: =SUM(E16:E27) -> 56455.478 | F28: =SUM(F16:F27) -> 262090.08 | H28: =SUM(H16:H27) -> 71533.441
B31: RESUMEN | C31: ACUM A JULIO 2024 | E31: META ACTUAL TOTAL | F31: META ANTERIOR | H31: DIFERENCIA
B33: TOTAL COSTO REAL | C33: =#REF!+#REF! -> #REF! | E33: =F12 -> 696510.67 | H33: =+F33-E33 -> -696510.67
B35: TOTAL COSTO VENTA | C35: =E12+E28 -> 363430.36 | E35: =C12 -> 960724.52 | H35: =+F35-E35 -> -960724.52
B37: RESULTADO OPERATIVO | C37: =C35-C33 -> #REF! | E37: =E35-E33 -> 264213.85 | F37: =F35-F33 -> 0
B38: MARGEN DE UTILIDAD | C38: =C37/C35 -> #REF! | E38: =E37/E35 -> 0.2750152 | F38: =F37/F35 -> #DIV/0!

Sheet DIFERENCIAS
C3: VENTA (S/) | E3: META TOTAL (PRESENTE MES) (S/) | I3: META TOTAL (MES ANTERIOR) (S/) | M3: META INICIAL (S/)
A4: UC | B4: DESCRIPCIÓN | C4: INGRESO PREVISTO TOTAL | E4: COSTO PREVISTO | F4: RENTABILIDAD | I4: COSTO PREVISTO | J4: RENTABILIDAD | M4: COSTO PREVISTO | N4: RENTABILIDAD | Q4: DESVIACIONES (META INICIAL TOTAL- META TOTAL)
B5: PRESUPUESTO CONTRACTUAL
A6: 100 | B6: OBRAS PROVISIONALES | C6: =+'RESUMEN - ANALISIS'!C7 -> 3661.14 | E6: =+'RESUMEN - ANALISIS'!F7 -> 2506.28 | F6: =C6-E6 -> 1154.86 | G6: =+F6/C6 -> 0.31543727 | I6: =+'RESUMEN - ANALISIS'!F7 -> 2506.28 | J6: =C6-I6 -> 1154.86 | K6: =J6/C6 -> 0.31543727 | M6: =+'RESUMEN - ANALISIS'!F7 -> 2506.28 | N6: =C6-M6 -> 1154.86 | O6: =N6/C6 -> 0.31543727 | Q6: =E6-M6 -> 0 | R6: =M6/E6 -> 1
A7: 200 | B7: MOVIMIENTO DE TIERRAS | C7: =+'RESUMEN - ANALISIS'!C8 -> 159518.36 | E7: =+'RESUMEN - ANALISIS'!F8 -> 102563.43 | F7: =C7-E7 -> 56954.93 | G7: =+F7/C7 -> 0.3570431 | I7: =+'RESUMEN - ANALISIS'!F8 -> 102563.43 | J7: =C7-I7 -> 56954.93 | K7: =J7/C7 -> 0.3570431 | M7: =+'RESUMEN - ANALISIS'!F8 -> 102563.43 | N7: =C7-M7 -> 56954.93 | O7: =N7/C7 -> 0.3570431 | Q7: =E7-M7 -> 0 | R7: =M7/E7 -> 1
A8: 300 | B8: CONCRETO | C8: =+'RESUMEN - ANALISIS'!C9 -> 360886.42 | E8: =+'RESUMEN - ANALISIS'!F9 -> 335452.9 | F8: =C8-E8 -> 25433.52 | G8: =+F8/C8 -> 0.070475137 | I8: =+'RESUMEN - ANALISIS'!F9 -> 335452.9 | J8: =C8-I8 -> 25433.52 | K8: =J8/C8 -> 0.070475137 | M8: =+'RESUMEN - ANALISIS'!F9 -> 335452.9 | N8: =C8-M8 -> 25433.52 | O8: =N8/C8 -> 0.070475137 | Q8: =E8-M8 -> 0 | R8: =M8/E8 -> 1
A9: 400 | B9: ENCOFRADO | C9: =+'RESUMEN - ANALISIS'!C10 -> 221395.36 | E9: =+'RESUMEN - ANALISIS'!F10 -> 136602.51 | F9: =C9-E9 -> 84792.85 | G9: =+F9/C9 -> 0.3829929 | I9: =+'RESUMEN - ANALISIS'!F10 -> 136602.51 | J9: =C9-I9 -> 84792.85 | K9: =J9/C9 -> 0.3829929 | M9: =+'RESUMEN - ANALISIS'!F10 -> 136602.51 | N9: =C9-M9 -> 84792.85 | O9: =N9/C9 -> 0.3829929 | Q9: =E9-M9 -> 0 | R9: =M9/E9 -> 1
A10: 500 | B10: ACERO | C10: =+'RESUMEN - ANALISIS'!C11 -> 215263.24 | E10: =+'RESUMEN - ANALISIS'!F11 -> 119385.55 | F10: =C10-E10 -> 95877.69 | G10: =+F10/C10 -> 0.44539741 | I10: =+'RESUMEN - ANALISIS'!F11 -> 119385.55 | J10: =C10-I10 -> 95877.69 | K10: =J10/C10 -> 0.44539741 | M10: =+'RESUMEN - ANALISIS'!F11 -> 119385.55 | N10: =C10-M10 -> 95877.69 | O10: =N10/C10 -> 0.44539741 | Q10: =E10-M10 -> 0 | R10: =M10/E10 -> 1
A11: 600 | B11: GASTOS GENERALES | C11: =+'RESUMEN - ANALISIS'!C17 -> 96072.45 | E11: =+'RESUMEN - ANALISIS'!F17 -> 237712.21 | F11: =C11-E11 -> -141639.76 | G11: =+F11/C11 -> -1.4743015 | I11: =+'RESUMEN - ANALISIS'!F17 -> 237712.21 | J11: =C11-I11 -> -141639.76 | K11: =J11/C11 -> -1.4743015 | M11: =+'RESUMEN - ANALISIS'!F17 -> 237712.21 | N11: =C11-M11 -> -141639.76 | O11: =N11/C11 -> -1.4743015 | Q11: =E11-M11 -> 0 | R11: =M11/E11 -> 1
A12: TOTALES VENTA Y COSTE DIRECTO | C12: =SUM(C5:C11) -> 1056797 | E12: =SUM(E5:E11) -> 934222.88 | F12: =C12-E12 -> 122574.09 | G12: =F12/C12 -> 0.11598642 | I12: =SUM(I5:I11) -> 934222.88 | J12: =C12-I12 -> 122574.09 | K12: =J12/C12 -> 0.11598642 | M12: =SUM(M5:M11) -> 934222.88 | N12: =C12-M12 -> 122574.09 | O12: =N12/C12 -> 0.11598642 | Q12: =SUM(Q5:Q11) -> 0 | R12: =E12/M12 -> 1

Sheet COSTOS INCURRIDOS
J2: NOVIEMBRE | L2: DICIEMBRE | N2: ENERO | P2: FEBRERO | R2: MARZO
A3: ITEM | B3: DESCRIPCION | C3: PROVEEDOR | D3: UNIDAD | E3: CANTIDAD | F3: P.U. | G3: SUBTOTAL | H3: PARTIDA DE CONTROL | I3: TIPO DE COSTO | J3: METRADO UTILIZADO | K3: SUB TOTAL | L3: METRADO UTILIZADO | M3: SUB TOTAL | N3: METRADO UTILIZADO | O3: SUB TOTAL | P3: METRADO UTILIZADO | Q3: SUB TOTAL | R3: METRADO UTILIZADO | S3: SUB TOTAL
B4: ORDENES DE COMPRA
A5: OC001 | B5: ALAMBRE NEGRO RECOCIDO N° 8 | D5: kg | E5: 530 | F5: 2.9 | G5: =+E5*F5 -> 1537 | H5: 400 | I5: MATERIALES | J5: 212 | K5: =+J5*F5 -> 614.8 | L5: 132.5 | M5: =+L5*F5 -> 384.25 | N5: 106 | O5: =+N5*F5 -> 307.4 | P5: 79.5 | Q5: =+P5*F5 -> 230.55 | S5: =+R5*F5 -> 0
A6: OC001 | B6: CLAVOS PARA MADERA CON CABEZA DE 4" | D6: kg | E6: 550 | F6: 3.06 | G6: =+E6*F6 -> 1683 | H6: 400 | I6: MATERIALES | J6: 220 | K6: =+J6*F6 -> 673.2 | L6: 137.5 | M6: =+L6*F6 -> 420.75 | N6: 110 | O6: =+N6*F6 -> 336.6 | P6: 82.5 | Q6: =+P6*F6 -> 252.45
A7: OC001 | B7: CLAVOS PARA MADERA CON CABEZA DE 3" | D7: kg | E7: 15 | F7: 3.06 | G7: =+E7*F7 -> 45.9 | H7: 400 | I7: MATERIALES | J7: 6 | K7: =+J7*F7 -> 18.36 | L7: 3.75 | M7: =+L7*F7 -> 11.475 | N7: 1.5 | O7: =+N7*F7 -> 4.59 | P7: 3.75 | Q7: =+P7*F7 -> 11.475
A8: OC001 | B8: ALAMBRE NEGRO N° 16 | D8: kg | E8: 880 | F8: 2.9 | G8: =+E8*F8 -> 2552 | H8: 500 | I8: MATERIALES | L8: 237.6 | M8: =+L8*F8 -> 689.04 | N8: 484 | O8: =+N8*F8 -> 1403.6 | P8: 158.4 | Q8: =+P8*F8 -> 459.36
A9: OC001 | B9: ALAMBRE NEGRO RECOCIDO N° 16 | D9: kg | E9: 900 | F9: 2.9 | G9: =+E9*F9 -> 2610 | H9: 500 | I9: MATERIALES | L9: 243 | M9: =+L9*F9 -> 704.7 | N9: 495 | O9: =+N9*F9 -> 1435.5 | P9: 162 | Q9: =+P9*F9 -> 469.8
A10: OC002 | B10: TRIPLAY FENOLICO | D10: p2 | E10: 2000 | F10: 4.5 | G10: =+E10*F10 -> 9000 | H10: 400 | I10: MATERIALES | J10: 500 | K10: =+J10*F10 -> 2250 | L10: 600 | M10: =+L10*F10 -> 2700 | N10: 400 | O10: =+N10*F10 -> 1800 | P10: 500 | Q10: =+P10*F10 -> 2250
A11: OC003 | B11: PIEDRA GRANDE DE 8" | D11: m3 | E11: 170.7807 | F11: 54 | G11: =+E11*F11 -> 9222.1578 | H11: 300 | I11: MATERIALES | J11: 170.7807 | K11: =+J11*F11 -> 9222.1578
A12: OC004 | B12: ACERO CORRUGADO fy = 4200 kg/cm2 GRADO 60 | D12: kg | E12: 37571.338 | F12: 2.35 | G12: =+E12*F12 -> 88292.644 | H12: 500 | I12: MATERIALES | L12: 10100 | M12: =+L12*F12 -> 23735 | N12: 20660 | O12: =+N12*F12 -> 48551 | P12: 6811.34 | Q12: =+P12*F12 -> 16006.649
A13: OC005 | B13: LADRILLO PARA TECHO 8H DE 15X30X30 cm | D13: und | E13: 220.542 | F13: 11.23 | G13: =+E13*F13 -> 2476.6867 | H13: 300 | I13: MATERIALES | N13: 88 | O13: =+N13*F13 -> 988.24 | P13: 132.54 | Q13: =+P13*F13 -> 1488.4242
A14: OC006 | B14: SC CONCRETO PREMEZCLADO F'C=100 KG/CM2 | D14: m3 | E14: 399.10255 | F14: 180 | G14: =+E14*F14 -> 71838.459 | H14: 300 | I14: MATERIALES | J14: 399.10255 | K14: =+J14*F14 -> 71838.459
A15: OC006 | B15: SC CONCRETO PREMEZCLADO F'C=210 KG/CM2 | D15: m3 | E15: 557.3187 | F15: 200 | G15: =+E15*F15 -> 111463.74 | H15: 300 | I15: MATERIALES | N15: 250 | O15: =+N15*F15 -> 50000 | P15: 200 | Q15: =+P15*F15 -> 40000 | R15: 107.32 | S15: =+R15*F15 -> 21464
A16: OC006 | B16: SC CONCRETO PREMEZCLADO F'C=210 KG/CM2 H67 CON ADITIVO INPERMEBILIZANTE | D16: m3 | E16: 269.187 | F16: 230 | G16: =+E16*F16 -> 61913.01 | H16: 300 | I16: MATERIALES | N16: 156 | O16: =+N16*F16 -> 35880 | P16: 113.19 | Q16: =+P16*F16 -> 26033.7
A17: OC006 | B17: SC CONCRETO PREMEZCLADO F'C=175 KG/CM2 | D17: kg | E17: 2.512 | F17: 190 | G17: =+E17*F17 -> 477.28 | H17: 300 | I17: MATERIALES | L17: 0.9 | M17: =+L17*F17 -> 171 | N17: 1.0048 | O17: =+N17*F17 -> 190.912 | P17: 0.61 | Q17: =+P17*F17 -> 115.9
B18: ORDENES DE SERVICIO
A19: OS001 | B19: NIVEL TOPOGRAFICO | D19: hm | E19: 26.38188 | F19: 8.1 | G19: =+E19*F19 -> 213.69323 | H19: 100 | I19: EQUIPOS | J19: 15 | K19: =+J19*F19 -> 121.5 | L19: 9 | M19: =+L19*F19 -> 72.9 | N19: 2.38 | O19: =+N19*F19 -> 19.278
A20: OS001 | B20: ESTACION TOTAL | D20: hm | E20: 26.38188 | F20: 14 | G20: =+E20*F20 -> 369.34632 | H20: 100 | I20: EQUIPOS | J20: 8.4 | K20: =+J20*F20 -> 117.6 | L20: 7.3 | M20: =+L20*F20 -> 102.2 | N20: 5 | O20: =+N20*F20 -> 70 | P20: 5.68 | Q20: =+P20*F20 -> 79.52
A21: OS002 | B21: PLANCHA COMPACTADORA VIBRT. 4,0 HP | D21: hm | E21: 6.187654 | F21: 26.11 | G21: =+E21*F21 -> 161.55965 | H21: 200 | I21: EQUIPOS | N21: 3 | O21: =+N21*F21 -> 78.33 | P21: 2 | Q21: =+P21*F21 -> 52.22 | R21: 1.19 | S21: =+R21*F21 -> 31.0709
A22: OS002 | B22: VIBRADOR A GASOLINA | D22: hm | E22: 505.08573 | F22: 5.9 | G22: =+E22*F22 -> 2980.0058 | H22: 300 | I22: EQUIPOS | N22: 313 | O22: =+N22*F22 -> 1846.7 | P22: 177 | Q22: =+P22*F22 -> 1044.3 | R22: 15.09 | S22: =+R22*F22 -> 89.031
A23: OS002 | B23: BOMBAS | D23: m3 | E23: 389.1285 | F23: 30 | G23: =+E23*F23 -> 11673.855 | H23: 300 | I23: EQUIPOS | N23: 235 | O23: =+N23*F23 -> 7050 | P23: 137 | Q23: =+P23*F23 -> 4110 | R23: 17.13 | S23: =+R23*F23 -> 513.9
A24: OS003 | B24: SC MANO DE OBRA ACERO CORRUGADO | D24: kg | E24: 35113.4 | F24: 0.74 | G24: =+E24*F24 -> 25983.916 | H24: 500 | I24: SUBCONTRATO
A25: OS004 | B25: SC AFIRMADO COMPACTADO 8" | D25: m2 | E25: 70.33 | F25: 13 | G25: =+E25*F25 -> 914.29 | H25: 200 | I25: SUBCONTRATO
A26: OS004 | B26: SC AFIRMADO COMPACTADO 12" | D26: m2 | E26: 8.73 | F26: 15 | G26: =+E26*F26 -> 130.95 | H26: 200 | I26: SUBCONTRATO
A27: OS004 | B27: SC EXCAVACION DE ZANJAS Y ZAPATAS Rt> 2KG/CM2 H=1.5m | D27: m3 | E27: 39.81 | F27: 19 | G27: =+E27*F27 -> 756.39 | H27: 200 | I27: SUBCONTRATO
A28: OS004 | B28: SC EXCAVACION DE ZANJAS Y ZAPATAS Rt> 2KG/CM2 H=2.00m | D28: m3 | E28: 1876.4 | F28: 21.1 | G28: =+E28*F28 -> 39592.04 | H28: 200 | I28: SUBCONTRATO
A29: OS004 | B29: SC RELLENO COMPACTADO CON EQUIPO | D29: m3 | E29: 1138.01 | F29: 15 | G29: =+E29*F29 -> 17070.15 | H29: 200 | I29: SUBCONTRATO
A30: OS004 | B30: SC ELIMINACION DE MATERIAL EXCEDENTE CON VOLQUETES | D30: m3 | E30: 1173.963 | F30: 17.4 | G30: =+E30*F30 -> 20426.956 | H30: 200 | I30: SUBCONTRATO
A31: OS005 | B31: SC ALQUILER DE ENCOFRADO COLUMNAS | D31: m2 | E31: 551.646 | F31: 19.04 | G31: =+E31*F31 -> 10503.34 | H31: 400 | I31: SERVICIOS | N31: 195 | O31: =+N31*F31 -> 3712.8 | P31: 356.65 | Q31: =+P31*F31 -> 6790.616
A32: OS005 | B32: SC ALQUILER DE ENCOFRADO VIGAS | D32: m2 | E32: 444.904 | F32: 26.78 | G32: =+E32*F32 -> 11914.529 | H32: 400 | I32: SERVICIOS | N32: 145 | O32: =+N32*F32 -> 3883.1 | P32: 299.9 | Q32: =+P32*F32 -> 8031.322
A33: OS005 | B33: SC ALQUILER DE ENCOFRADO LOSAS MACIZAS | D33: m2 | E33: 6.67 | F33: 11.23 | G33: =+E33*F33 -> 74.9041 | H33: 400 | I33: SERVICIOS | N33: 2 | O33: =+N33*F33 -> 22.46 | P33: 4.67 | Q33: =+P33*F33 -> 52.4441
A34: OS005 | B34: SC ALQUILER DE ENCOFRADO LOSAS ALIGERADAS | D34: m2 | E34: 11.064669 | F34: 11.23 | G34: =+E34*F34 -> 124.25623 | H34: 400 | I34: SERVICIOS | N34: 3 | O34: =+N34*F34 -> 33.69 | P34: 8.06 | Q34: =+P34*F34 -> 90.5138

Sheet STAFF
A2: MONTO DE PLANILLAS DE EMPLEADOS
A4: MES | B4: MONTO
A5: JULIO | B5: =32500*2 -> 65000
A6: AGOSTO | B6: 29800
A7: SEPTIEMBRE | B7: 31200
A8: OCTUBRE | B8: 33000
A9: NOVIEMBRE | B9: 25460
A10: TOTAL | B10: =SUM(B5:B9) -> 184460

Sheet OBREROS
B2: REGISTRO DE RECURSOS SEMANAL (EN HORAS HOMBRE)
B4: =+[1]Procesos!A4 -> CR: | C4: =[2]Caratula!C6 -> 001
B5: =+[1]Procesos!A5 -> PROYECTO: | C5: =[2]Caratula!C7 -> I.E. N° 1182 "EL BOSQUE" - CERCO + INGRESOS Y CASETAS
B6: =+[1]Procesos!A6 -> CORTE: | C6: =[2]Caratula!C8 -> 45504
E7: Previsto | I7: Previsto
B8: CÓDIGO | C8: DESCRIPCIÓN | D8: UND | E8: ORIG | F8: REV. 1 | G8: REV. 2 | H8: REV. 3 | I8: REV. 4 | J8: PREV | K8: N° DE SEMANA / FECHA DE CORTE | AE8: ACUM
K9: =[2]Semanas!B8 -> 1 | L9: =[2]Semanas!C8 -> 2 | M9: =[2]Semanas!D8 -> 3 | N9: =[2]Semanas!E8 -> 4 | O9: =[2]Semanas!F8 -> 5 | P9: =[2]Semanas!G8 -> 6 | Q9: =[2]Semanas!H8 -> 7 | R9: =[2]Semanas!I8 -> 8 | ... AD9: =[2]Semanas!U8 -> 20
K10: =[2]Semanas!B9 -> 45481 | L10: =[2]Semanas!C9 -> 45488 | M10: =[2]Semanas!D9 -> 45495 | N10: =[2]Semanas!E9 -> 45502 | O10: =[2]Semanas!F9 -> 45509 | P10: =[2]Semanas!G9 -> 45516 | Q10: =[2]Semanas!H9 -> 45523 | R10: =[2]Semanas!I9 -> 45530 | ... AD10: =[2]Semanas!U9 -> 45614
A11: =+A10+1 -> 1 | B11: 100 | C11: =+VLOOKUP(B11,[2]Procesos!A12:$C$40,2,0) -> OBRAS PROVISIONALES | D11: =[2]Procesos!$B$7 -> HH | E11: 100.63 | J11: =SUMIF($E$7:$J$7,"Previsto",E11:I11) -> 100.63 | K11: 12.8 | L11: 14.2 | M11: 10.2 | N11: 11.2 | O11: 11.4 | P11: 11.35 | Q11: 9.5 | R11: 11.5 | S11: 4.5 | T11: 4.2 | U11: 3 | V11: 2.8 | W11: 4.2 | X11: 4.5 | Y11: 4.5 | Z11: 4.3 | AA11: 0 | AB11: 0 | AC11: 0 | AD11: 0 | AE11: =SUM(K11:AD11) -> 124.15 | AG11: 17
A12: =+A11+1 -> 2 | B12: 200 | C12: =+VLOOKUP(B12,[2]Procesos!A13:$C$40,2,0) -> MOVIMIENTO DE TIERRAS | D12: =[2]Procesos!$B$7 -> HH | E12: 3931.7 | J12: =SUMIF($E$7:$J$7,"Previsto",E12:I12) -> 3931.7 | K12: 385 | L12: 375 | M12: 390 | N12: 400 | O12: 385 | P12: 405 | Q12: 380 | R12: 395 | S12: 180 | T12: 182 | U12: 185 | V12: 190 | W12: 4.5 | X12: 5 | Y12: 4.25 | Z12: 4.3 | AA12: 3.5 | AB12: 3.8 | AC12: 3.5 | AD12: 3 | AE12: =SUM(K12:AD12) -> 3883.85
A13: =+A12+1 -> 3 | B13: 300 | C13: =+VLOOKUP(B13,[2]Procesos!A14:$C$40,2,0) -> CONCRETO | D13: =[2]Procesos!$B$7 -> HH | E13: 2487.06 | J13: =SUMIF($E$7:$J$7,"Previsto",E13:I13) -> 2487.06 | K13: 0 | L13: 0 | M13: 0 | N13: 0 | O13: 190 | P13: 195 | Q13: 165 | R13: 174 | S13: 260 | T13: 280 | U13: 290 | V13: 285 | W13: 140 | X13: 146 | Y13: 150 | Z13: 155 | AA13: 20 | AB13: 22 | AC13: 24 | AD13: 21 | AE13: =SUM(K13:AD13) -> 2517
A14: =+A13+1 -> 4 | B14: 400 | C14: =+VLOOKUP(B14,[2]Procesos!A15:$C$40,2,0) -> ENCOFRADO | D14: =[2]Procesos!$B$7 -> HH | E14: 5370.78 | J14: =SUMIF($E$7:$J$7,"Previsto",E14:I14) -> 5370.78 | K14: 0 | L14: 0 | M14: 0 | N14: 0 | O14: 490 | P14: 465 | Q14: 460 | R14: 480 | S14: 365 | T14: 390 | U14: 375 | V14: 382 | W14: 500 | X14: 505 | Y14: 495 | Z14: 498 | AA14: 0 | AB14: 0 | AC14: 0 | AD14: 0 | AE14: =SUM(K14:AD14) -> 5405
A15: =+A14+1 -> 5 | B15: 500 | C15: =+VLOOKUP(B15,[2]Procesos!A16:$C$40,2,0) -> ACERO | D15: =[2]Procesos!$B$7 -> HH | E15: 39327.01 | J15: =SUMIF($E$7:$J$7,"Previsto",E15:I15) -> 39327.01 | K15: 0 | L15: 0 | M15: 0 | N15: 0 | O15: 4100 | P15: 4150 | Q15: 4050 | R15: 4060 | S15: 4600 | T15: 4800 | U15: 4820 | V15: 4500 | W15: 1290 | X15: 1260 | Y15: 1280 | Z15: 1240 | AA15: 0 | AB15: 0 | AC15: 0 | AD15: 0 | AE15: =SUM(K15:AD15) -> 40150
C19: TOTALES | E19: =+SUM(E11:E15) -> 51217.18 | F19: =SUM(F11:F18) -> 0 | G19: =SUM(G11:G18) -> 0 | H19: =SUM(H11:H18) -> 0 | I19: =SUM(I11:I18) -> 0 | J19: =+SUM(J11:J15) -> 51217.18 | K19: =SUM(K11:K18) -> 397.8 | L19: =SUM(L11:L18) -> 389.2 | M19: =SUM(M11:M18) -> 400.2 | N19: =SUM(N11:N18) -> 411.2 | O19: =SUM(O11:O18) -> 5176.4 | P19: =SUM(P11:P18) -> 5226.35 | Q19: =SUM(Q11:Q18) -> 5064.5 | R19: =SUM(R11:R18) -> 5120.5 | ... AE19: =SUM(AE11:AE18) -> 52080
B25: REGISTRO DE RECURSOS SEMANAL (EN COSTO)
E28: Previsto | I28: Previsto
B29: CÓDIGO | C29: DESCRIPCIÓN | D29: UND | E29: ORIG | F29: REV. 1 | G29: REV. 2 | H29: REV. 3 | I29: REV. 4 | J29: PREV | K29: N° DE SEMANA / FECHA DE CORTE | AE29: ACUM
K30: 1 | L30: 2 | M30: 3 | N30: 4 | O30: 5 | P30: 6 | Q30: 7 | R30: 8 | S30: 9 | T30: 10 | U30: 11 | V30: 12 | W30: 13 | X30: 14 | Y30: 15 | Z30: 16 | AA30: 17 | AB30: 18 | AC30: 19 | AD30: 20
K31: 45481 | L31: 45488 | M31: 45495 | N31: 45502 | O31: 45509 | P31: 45516 | Q31: 45523 | R31: 45530 | S31: 45537 | T31: 45544 | U31: 45551 | V31: 45558 | W31: 45565 | X31: 45572 | Y31: 45579 | Z31: 45586 | AA31: 45593 | AB31: 45600 | AC31: 45607 | AD31: 45614
A32: =+A31+1 -> 1 | B32: 100 | C32: OBRAS PROVISIONALES | D32: S/ | E32: 1710.71 | J32: 1710.71 | K32: 217.6 | L32: 241.4 | M32: 173.4 | N32: 190.4 | O32: 193.8 | P32: 192.95 | Q32: 161.5 | R32: 195.5 | S32: 76.5 | T32: 71.4 | U32: 51 | V32: 47.6 | W32: 71.4 | X32: 76.5 | Y32: 76.5 | Z32: 73.1 | AA32: 0 | AB32: 0 | AC32: 0 | AD32: 0 | AE32: =SUM(K32:AD32) -> 2110.55
A33: =+A32+1 -> 2 | B33: 200 | C33: MOVIMIENTO DE TIERRAS | D33: S/ | E33: 66838.9 | J33: 66838.9 | K33: 6545 | L33: 6375 | M33: 6630 | N33: 6800 | O33: 6545 | P33: 6885 | Q33: 6460 | R33: 6715 | S33: 3060 | T33: 3094 | U33: 3145 | V33: 3230 | W33: 76.5 | X33: 85 | Y33: 72.25 | Z33: 73.1 | AA33: 59.5 | AB33: 64.6 | AC33: 59.5 | AD33: 51 | AE33: =SUM(K33:AD33) -> 66025.45
A34: =+A33+1 -> 3 | B34: 300 | C34: CONCRETO | D34: S/ | E34: 42280.02 | J34: 42280.02 | K34: 0 | L34: 0 | M34: 0 | N34: 0 | O34: 3230 | P34: 3315 | Q34: 2805 | R34: 2958 | S34: 4420 | T34: 4760 | U34: 4930 | V34: 4845 | W34: 2380 | X34: 2482 | Y34: 2550 | Z34: 2635 | AA34: 340 | AB34: 374 | AC34: 408 | AD34: 357 | AE34: =SUM(K34:AD34) -> 42789
A35: =+A34+1 -> 4 | B35: 400 | C35: ENCOFRADO | D35: S/ | E35: 91303.26 | J35: 91303.26 | K35: 0 | L35: 0 | M35: 0 | N35: 0 | O35: 8330 | P35: 7905 | Q35: 7820 | R35: 8160 | S35: 6205 | T35: 6630 | U35: 6375 | V35: 6494 | W35: 8500 | X35: 8585 | Y35: 8415 | Z35: 8466 | AA35: 0 | AB35: 0 | AC35: 0 | AD35: 0 | AE35: =SUM(K35:AD35) -> 91885
A36: =+A35+1 -> 5 | B36: 500 | C36: ACERO | D36: S/ | E36: 668559.17 | J36: 668559.17 | K36: 0 | L36: 0 | M36: 0 | N36: 0 | O36: 69700 | P36: 70550 | Q36: 68850 | R36: 69020 | S36: 78200 | T36: 81600 | U36: 81940 | V36: 76500 | W36: 21930 | X36: 21420 | Y36: 21760 | Z36: 21080 | AA36: 0 | AB36: 0 | AC36: 0 | AD36: 0 | AE36: =SUM(K36:AD36) -> 682550
C40: TOTALES | E40: =+SUM(E32:E36) -> 870692.06 | F40: =SUM(F32:F39) -> 0 | G40: =SUM(G32:G39) -> 0 | H40: =SUM(H32:H39) -> 0 | I40: =SUM(I32:I39) -> 0 | J40: =+SUM(J32:J36) -> 870692.06 | K40: =SUM(K32:K39) -> 6762.6 | L40: =SUM(L32:L39) -> 6616.4 | M40: =SUM(M32:M39) -> 6803.4 | N40: =SUM(N32:N39) -> 6990.4 | O40: =SUM(O32:O39) -> 87998.8 | P40: =SUM(P32:P39) -> 88847.95 | Q40: =SUM(Q32:Q39) -> 86096.5 | R40: =SUM(R32:R39) -> 87048.5 | ... AE40: =SUM(AE32:AE39) -> 885360
N45: 822.8 | O45: 743.75 | P45: 246.5 | Q45: 297.5 | R45: 0
N46: 26350 | O46: 26605 | P46: 12529 | Q46: 306.85 | R46: 234.6
N47: 0 | O47: 12308 | P47: 18955 | Q47: 10047 | R47: 1479
N48: 0 | O48: 32215 | P48: 25704 | Q48: 33966 | R48: 0
N49: 0 | O49: 278120 | P49: 318240 | Q49: 86190 | R49: 0

Sheet PRODUCCION
A2: REGISTRO DE PRODUCCIÓN (AVANCE) SEMANAL
D7: Previsto
A8: CÓDIGO | B8: DESCRIPCIÓN | C8: UND | D8: ORIG | E8: REV. 1 | F8: REV. 2 | G8: REV. 3 | H8: REV. 4 | I8: PREV | J8: N° DE SEMANA / FECHA DE CORTE | AD8: ACUM
J9: 1 | K9: 2 | L9: 3 | M9: 4 | N9: 5 | O9: 6 | P9: 7 | Q9: 8 | R9: 9 | S9: 10 | T9: 11 | U9: 12 | V9: 13 | W9: 14 | X9: 15 | Y9: 16 | Z9: 17 | AA9: 18 | AB9: 19 | AC9: 20 | AF9: N° DE SEMANA / FECHA DE CORTE
J10: 45481 | K10: 45488 | L10: 45495 | M10: 45502 | N10: 45509 | O10: 45516 | P10: 45523 | Q10: 45530 | R10: 45537 | S10: 45544 | T10: 45551 | U10: 45558 | V10: 45565 | W10: 45572 | X10: 45579 | Y10: 45586 | Z10: 45593 | AA10: 45600 | AB10: 45607 | AC10: 45614 | AF10: 1 | AG10: 2 | AH10: 3 | AI10: 4 | AJ10: 5 | AK10: 6 | AL10: 7 | AM10: 8 | AN10: 9 | AO10: 10 | AP10: 11 | AQ10: 12 | AR10: 13 | AS10: 14 | AT10: 15 | AU10: 16 | AV10: 17 | AW10: 18 | AX10: 19 | AY10: 20
B11: OBRAS PROVISIONALES, TRABAJOS PRELIMINARES, SEGURIDAD Y SALUD | AF11: 45481 | AG11: 45488 | AH11: 45495 | AI11: 45502 | AJ11: 45509 | AK11: 45516 | AL11: 45523 | AM11: 45530 | AN11: 45537 | AO11: 45544 | AP11: 45551 | AQ11: 45558 | AR11: 45565 | AS11: 45572 | AT11: 45579 | AU11: 45586 | AV11: 45593 | AW11: 45600 | AX11: 45607 | AY11: 45614
B12: Trabajos Preliminares | AE12: 100 | AF12: 0.08358036 | AG12: 0.086366372 | AH12: 0.087480777 | AI12: 0.094724408 | AJ12: 0.094724408 | AK12: 0.089152384 | AL12: 0.078008336 | AM12: 0.086366372 | AN12: 0.02786012 | AO12: 0.02786012 | AP12: 0.028974525 | AQ12: 0.030646132 | AR12: 0.032317739 | AS12: 0.032874941 | AT12: 0.030646132 | AU12: 0.028417322 | AV12: 0 | AW12: 0 | AX12: 0 | AY12: 0
B13: Trazo, Niveles y Replanteo | AE13: 200 | AF13: 0.10248538 | AG13: 0.10931774 | AH13: 0.1115952 | AI13: 0.11387265 | AJ13: 0.084265761 | AK13: 0.085404487 | AL13: 0.084038015 | AM13: 0.086543214 | AN13: 0.046687786 | AO13: 0.043271607 | AP13: 0.04554906 | AQ13: 0.046687786 | AR13: 0.002277453 | AS13: 0.0066046137 | AT13: 0.004554906 | AU13: 0.0050103966 | AV13: 0 | AW13: 0 | AX13: 0 | AY13: 0
A14: 100 | B14: TRAZO Y REPLANTEO PRELIMINAR | C14: M2 | D14: 897.34 | I14: 897.34 | J14: 75 | K14: 77.5 | L14: 78.5 | M14: 85 | N14: =$D14*AJ$12 -> 85 | O14: =$D14*AK$12 -> 80 | P14: =$D14*AL$12 -> 70 | Q14: =$D14*AM$12 -> 77.5 | R14: =$D14*AN$12 -> 25 | S14: =$D14*AO$12 -> 25 | T14: =$D14*AP$12 -> 26 | U14: =$D14*AQ$12 -> 27.5 | ... AC14: =$D14*AY$12 -> 0 | AE14: 300 | AF14: 0 | AG14: 0 | AH14: 0 | AI14: 0 | AJ14: 0.12230665 | AK14: 0.11319871 | AL14: 0.11580098 | AM14: 0.11710211 | AN14: 0.19517019 | AO14: 0.19517019 | AP14: 0.20818153 | AQ14: 0.18215884 | AR14: 0.078068075 | AS14: 0.080670345 | AT14: 0.083272614 | AU14: 0.085874883 | AV14: 0.019517019 | AW14: 0.015613615 | AX14: 0.018215884 | AY14: 0.020818153
A15: 100 | B15: TRAZO Y REPLANTEO DURANTE EL PROCESO | C15: m2 | D15: 897.34 | I15: 897.34 | J15: 75 | K15: 77.5 | L15: 78.5 | M15: 85 | N15: =$D15*AJ$12 -> 85 | O15: =$D15*AK$12 -> 80 | P15: =$D15*AL$12 -> 70 | Q15: =$D15*AM$12 -> 77.5 | R15: =$D15*AN$12 -> 25 | S15: =$D15*AO$12 -> 25 | T15: =$D15*AP$12 -> 26 | U15: =$D15*AQ$12 -> 27.5 | ... AC15: =$D15*AY$12 -> 0 | AE15: 400 | AF15: 0 | AG15: 0 | AH15: 0 | AI15: 0 | AJ15: 0.095753994 | AK15: 0.098489823 | AL15: 0.097121909 | AM15: 0.097942657 | AN15: 0.076603195 | AO15: 0.076603195 | AP15: 0.071131539 | AQ15: 0.076603195 | AR15: 0.082074852 | AS15: 0.084810681 | AT15: 0.086178595 | AU15: 0.080706938 | AV15: 0 | AW15: 0 | AX15: 0 | AY15: 0
B16: ESTRUCTURAS | AE16: 500 | AF16: 0 | AG16: 0 | AH16: 0 | AI16: 0 | AJ16: 0.10308495 | AK16: 0.10476568 | AL16: 0.10177771 | AM16: 0.10084397 | AN16: 0.11204886 | AO16: 0.11204886 | AP16: 0.11186211 | AQ16: 0.12512122 | AR16: 0.028012214 | AS16: 0.026144733 | AT16: 0.035482138 | AU16: 0.031747176 | AV16: 0 | AW16: 0 | AX16: 0 | AY16: 0
B17: Movimiento de Tierras
B18: Excavaciones
A19: 200 | B19: EXCAV.ZANJAS Y ZAPATA RT>2kg/cm2 H=1.5m | C19: m3 | D19: 41.9 | I19: 41.9 | J19: 4.3 | K19: 4.5804134 | L19: 4.6758387 | M19: 4.771264 | N19: =$D19*AJ$13 -> 3.5307354 | O19: =$D19*AK$13 -> 3.578448 | P19: =$D19*AL$13 -> 3.5211928 | Q19: =$D19*AM$13 -> 3.6261606 | R19: =$D19*AN$13 -> 1.9562182 | S19: =$D19*AO$13 -> 1.8130803 | T19: =$D19*AP$13 -> 1.9085056 | U19: =$D19*AQ$13 -> 1.9562182 | ... AC19: =$D19*AY$13 -> 0
A20: 200 | B20: EXCAV.ZANJAS Y ZAPATA RT>2kg/cm2 H=2.0m | C20: m3 | D20: 1975.16 | I20: 1975.16 | J20: 202.43 | K20: 215.92003 | L20: 220.41837 | M20: 224.9167 | N20: =$D20*AJ$13 -> 166.43836 | O20: =$D20*AK$13 -> 168.68753 | P20: =$D20*AL$13 -> 165.98853 | Q20: =$D20*AM$13 -> 170.93669 | R20: =$D20*AN$13 -> 92.215848 | S20: =$D20*AO$13 -> 85.468347 | T20: =$D20*AP$13 -> 89.966681 | U20: =$D20*AQ$13 -> 92.215848 | ... AC20: =$D20*AY$13 -> 0
B21: Rellenos
A22: 200 | B22: RELLENO COMPACTADO C/EQUIPO MAT/PROPIO | C22: m3 | D22: 1197.91 | I22: 1197.91 | J22: 122.77 | K22: 130.95282 | L22: 133.681 | M22: 136.40919 | N22: =$D22*AJ$13 -> 100.9428 | O22: =$D22*AK$13 -> 102.30689 | P22: =$D22*AL$13 -> 100.66998 | Q22: =$D22*AM$13 -> 103.67098 | R22: =$D22*AN$13 -> 55.927766 | S22: =$D22*AO$13 -> 51.83549 | T22: =$D22*AP$13 -> 54.563674 | U22: =$D22*AQ$13 -> 55.927766 | ... AC22: =$D22*AY$13 -> 0
B23: Eliminacion de Material Excedente
A24: 200 | B24: ACARREO INTERNO, MATERIAL PROCEDENTE DE EXCAVACIONES | C24: m3 | D24: 68.91 | I24: 68.91 | J24: 7.06 | K24: 7.5330857 | L24: 7.690025 | M24: 7.8469643 | N24: =$D24*AJ$13 -> 5.8067536 | O24: =$D24*AK$13 -> 5.8852232 | P24: =$D24*AL$13 -> 5.7910596 | Q24: =$D24*AM$13 -> 5.9636928 | R24: =$D24*AN$13 -> 3.2172554 | S24: =$D24*AO$13 -> 2.9818464 | T24: =$D24*AP$13 -> 3.1387857 | U24: =$D24*AQ$13 -> 3.2172554 | ... AC24: =$D24*AY$13 -> 0
A25: 200 | B25: ELIMINACION MATERIAL EXCEDENTE ACARREADO | C25: M3 | D25: 68.91 | I25: 68.91 | J25: 7.06 | K25: 7.5330857 | L25: 7.690025 | M25: 7.8469643 | N25: =$D25*AJ$13 -> 5.8067536 | O25: =$D25*AK$13 -> 5.8852232 | P25: =$D25*AL$13 -> 5.7910596 | Q25: =$D25*AM$13 -> 5.9636928 | R25: =$D25*AN$13 -> 3.2172554 | S25: =$D25*AO$13 -> 2.9818464 | T25: =$D25*AP$13 -> 3.1387857 | U25: =$D25*AQ$13 -> 3.2172554 | ... AC25: =$D25*AY$13 -> 0
A26: 200 | B26: ELIMINACION MATERIAL EXCEDENTE C/MAQUINA | C26: m3 | D26: 995.9 | I26: 995.9 | J26: 102.07 | K26: 108.86954 | L26: 111.13766 | M26: 113.40577 | N26: =$D26*AJ$13 -> 83.920271 | O26: =$D26*AK$13 -> 85.054329 | P26: =$D26*AL$13 -> 83.693459 | Q26: =$D26*AM$13 -> 86.188386 | R26: =$D26*AN$13 -> 46.496366 | S26: =$D26*AO$13 -> 43.094193 | T26: =$D26*AP$13 -> 45.362309 | U26: =$D26*AQ$13 -> 46.496366 | ... AC26: =$D26*AY$13 -> 0
B27: Nivelacion Interior y Apisonado
A28: 200 | B28: ESCARIFICADO Y COMPACTACION CON PLANCHA COMPACTADORA e = 30 cm | C28: m2 | D28: 68.95 | I28: 68.95 | J28: 7.07 | K28: 7.5374584 | L28: 7.6944888 | M28: 7.8515192 | N28: =$D28*AJ$13 -> 5.8101242 | O28: =$D28*AK$13 -> 5.8886394 | P28: =$D28*AL$13 -> 5.7944212 | Q28: =$D28*AM$13 -> 5.9671546 | R28: =$D28*AN$13 -> 3.2191229 | S28: =$D28*AO$13 -> 2.9835773 | T28: =$D28*AP$13 -> 3.1406077 | U28: =$D28*AQ$13 -> 3.2191229 | ... AC28: =$D28*AY$13 -> 0
A29: 200 | B29: ESCARIFICADO Y COMPACTACION CON PLANCHA COMPACTADORA H=0.60m (02 CAPAS 30cm c/u) | C29: m2 | D29: 8.56 | I29: 8.56 | J29: 0.88 | K29: 0.93575988 | L29: 0.95525488 | M29: 0.97474988 | N29: =$D29*AJ$13 -> 0.72131491 | O29: =$D29*AK$13 -> 0.73106241 | P29: =$D29*AL$13 -> 0.71936541 | Q29: =$D29*AM$13 -> 0.74080991 | R29: =$D29*AN$13 -> 0.39964745 | S29: =$D29*AO$13 -> 0.37040495 | T29: =$D29*AP$13 -> 0.38989995 | U29: =$D29*AQ$13 -> 0.39964745 | ... AC29: =$D29*AY$13 -> 0
A30: 200 | B30: AFIRMADO DE 8" PARA PISOS,PATIOS Y VEREDAS,COMPACTADO. | C30: m2 | D30: 68.95 | I30: 68.95 | J30: 7.07 | K30: 7.5374584 | L30: 7.6944888 | M30: 7.8515192 | N30: =$D30*AJ$13 -> 5.8101242 | O30: =$D30*AK$13 -> 5.8886394 | P30: =$D30*AL$13 -> 5.7944212 | Q30: =$D30*AM$13 -> 5.9671546 | R30: =$D30*AN$13 -> 3.2191229 | S30: =$D30*AO$13 -> 2.9835773 | T30: =$D30*AP$13 -> 3.1406077 | U30: =$D30*AQ$13 -> 3.2191229 | ... AC30: =$D30*AY$13 -> 0
A31: 200 | B31: AFIRMADO DE 12" EN PISOS INTERIOR/EXTERIOR,COMPACTADO. | C31: m2 | D31: 8.56 | I31: 8.56 | J31: 0.88 | K31: 0.93575988 | L31: 0.95525488 | M31: 0.97474988 | N31: =$D31*AJ$13 -> 0.72131491 | O31: =$D31*AK$13 -> 0.73106241 | P31: =$D31*AL$13 -> 0.71936541 | Q31: =$D31*AM$13 -> 0.74080991 | R31: =$D31*AN$13 -> 0.39964745 | S31: =$D31*AO$13 -> 0.37040495 | T31: =$D31*AP$13 -> 0.38989995 | U31: =$D31*AQ$13 -> 0.39964745 | ... AC31: =$D31*AY$13 -> 0
B32: Obras de Concreto Simple
B33: Falsos Cimientos
A34: 300 | B34: SUBCIMIENTO, SUBZAPATA MEZCLA 1:12 + 30 % P.G. | C34: m3 | D34: 323.69 | I34: 323.69 | J34: =+D34*K34 -> 0 | K34: =+E34*L34 -> 0 | L34: =+F34*M34 -> 0 | M34: =+G34*N34 -> 0 | N34: =$I34*AF$14 -> 0 | O34: =$I34*AG$14 -> 0 | P34: =$I34*AH$14 -> 0 | Q34: =$I34*AI$14 -> 0 | R34: =$I34*AJ$14 -> 39.58944 | S34: =$I34*AK$14 -> 36.64129 | T34: =$I34*AL$14 -> 37.483619 | U34: =$I34*AM$14 -> 37.904783 | ... AC34: =$I34*AU$14 -> 27.796841
B35: Cimientos
A36: 300 | B36: CIMIENTOS CORRIDOS 1:10 + 30 % P.G. f'c >=100Kg/cm2 | C36: m3 | D36: 24.73 | I36: 24.73 | J36: =+D36*K36 -> 0 | K36: =+E36*L36 -> 0 | L36: =+F36*M36 -> 0 | M36: =+G36*N36 -> 0 | N36: =$I36*AF$14 -> 0 | O36: =$I36*AG$14 -> 0 | P36: =$I36*AH$14 -> 0 | Q36: =$I36*AI$14 -> 0 | R36: =$I36*AJ$14 -> 3.0246435 | S36: =$I36*AK$14 -> 2.7994041 | T36: =$I36*AL$14 -> 2.8637582 | U36: =$I36*AM$14 -> 2.8959353 | ... AC36: =$I36*AU$14 -> 2.1236859
A37: 400 | B37: CIMIENTO CORRIDO - ENCOFRADO Y DESENCOFRADO | C37: m2 | D37: 23.09 | I37: 23.09 | J37: =+D37*K37 -> 0 | K37: =+E37*L37 -> 0 | L37: =+F37*M37 -> 0 | M37: =+G37*N37 -> 0 | N37: =$I37*AJ$15 -> 2.2109597 | O37: =$I37*AK$15 -> 2.27413 | P37: =$I37*AL$15 -> 2.2425449 | Q37: =$I37*AM$15 -> 2.261496 | R37: =$I37*AN$15 -> 1.7687678 | S37: =$I37*AO$15 -> 1.7687678 | T37: =$I37*AP$15 -> 1.6424272 | U37: =$I37*AQ$15 -> 1.7687678 | ... AC37: =$I37*AY$15 -> 0
A38: 300 | B38: CALZADURA: CONCRETO C:H 1:10 + 30 % P.G. | C38: m3 | D38: 163.82 | I38: 163.82 | J38: =+D38*K38 -> 0 | K38: =+E38*L38 -> 0 | L38: =+F38*M38 -> 0 | M38: =+G38*N38 -> 0 | N38: =$I38*AF$14 -> 0 | O38: =$I38*AG$14 -> 0 | P38: =$I38*AH$14 -> 0 | Q38: =$I38*AI$14 -> 0 | R38: =$I38*AJ$14 -> 20.036276 | S38: =$I38*AK$14 -> 18.544213 | T38: =$I38*AL$14 -> 18.970516 | U38: =$I38*AM$14 -> 19.183668 | ... AC38: =$I38*AU$14 -> 14.068023
A39: 400 | B39: CALZADURA: ENCOFRADO Y DESENCOFRADO | C39: m2 | D39: 327.63 | I39: 327.63 | J39: =+D39*K39 -> 0 | K39: =+E39*L39 -> 0 | L39: =+F39*M39 -> 0 | M39: =+G39*N39 -> 0 | N39: =$I39*AJ$15 -> 31.371881 | O39: =$I39*AK$15 -> 32.268221 | P39: =$I39*AL$15 -> 31.820051 | Q39: =$I39*AM$15 -> 32.088953 | R39: =$I39*AN$15 -> 25.097505 | S39: =$I39*AO$15 -> 25.097505 | T39: =$I39*AP$15 -> 23.304826 | U39: =$I39*AQ$15 -> 25.097505 | ... AC39: =$I39*AY$15 -> 0
B40: Sobrecimientos
A41: 300 | B41: SOBRECIMIENTO, CONCRETO 1:8 + 25% P.M. f'c >=100Kg/cm2 | C41: m3 | D41: 3.21 | I41: 3.21 | J41: =+D41*K41 -> 0 | K41: =+E41*L41 -> 0 | L41: =+F41*M41 -> 0 | M41: =+G41*N41 -> 0 | N41: =$I41*AF$14 -> 0 | O41: =$I41*AG$14 -> 0 | P41: =$I41*AH$14 -> 0 | Q41: =$I41*AI$14 -> 0 | R41: =$I41*AJ$14 -> 0.39260435 | S41: =$I41*AK$14 -> 0.36336786 | T41: =$I41*AL$14 -> 0.37172114 | U41: =$I41*AM$14 -> 0.37589778 | ... AC41: =$I41*AU$14 -> 0.27565837
A42: 400 | B42: SOBRECIMIENTO, ENCOFRADO Y DESENCOFRADO | C42: m2 | D42: 43.95 | I42: 43.95 | J42: =+D42*K42 -> 0 | K42: =+E42*L42 -> 0 | L42: =+F42*M42 -> 0 | M42: =+G42*N42 -> 0 | N42: =$I42*AJ$15 -> 4.208388 | O42: =$I42*AK$15 -> 4.3286277 | P42: =$I42*AL$15 -> 4.2685079 | Q42: =$I42*AM$15 -> 4.3045798 | R42: =$I42*AN$15 -> 3.3667104 | S42: =$I42*AO$15 -> 3.3667104 | T42: =$I42*AP$15 -> 3.1262311 | U42: =$I42*AQ$15 -> 3.3667104 | ... AC42: =$I42*AY$15 -> 0
B43: Obras de Concreto Armado
B44: Zapatas
A45: 300 | B45: ZAPATAS.- CONCRETO 210 kg/cm2 | C45: m3 | D45: 396.75 | I45: 396.75 | J45: 0 | K45: 0 | L45: 0 | M45: 0 | N45: =$I45*AF$14 -> 0 | O45: =$I45*AG$14 -> 0 | P45: =$I45*AH$14 -> 0 | Q45: =$I45*AI$14 -> 0 | R45: =$I45*AJ$14 -> 48.525164 | S45: =$I45*AK$14 -> 44.911588 | T45: =$I45*AL$14 -> 45.944038 | U45: =$I45*AM$14 -> 46.460263 | ... AC45: =$I45*AU$14 -> 34.07086
A46: 500 | B46: ZAPATAS.- ACERO Fy=4200 kg/cm2 | C46: KG | D46: 17534.91 | I46: 17534.91 | J46: 0 | K46: 0 | L46: 0 | M46: 0 | N46: =$I46*AJ$16 -> 1807.5853 | O46: =$I46*AK$16 -> 1837.0568 | P46: =$I46*AL$16 -> 1784.663 | Q46: =$I46*AM$16 -> 1768.2899 | R46: =$I46*AN$16 -> 1964.7666 | S46: =$I46*AO$16 -> 1964.7666 | T46: =$I46*AP$16 -> 1961.492 | U46: =$I46*AQ$16 -> 2193.9894 | ... AC46: =$I46*AY$16 -> 0
B47: Placas y Muros de Contención
A48: 300 | B48: PLACAS, CONCRETO F'c=210 kg/cm2 - 1 piso | C48: m3 | D48: 6.69 | I48: 6.69 | J48: 0 | K48: 0 | L48: 0 | M48: 0 | N48: =$I48*AF$14 -> 0 | O48: =$I48*AG$14 -> 0 | P48: =$I48*AH$14 -> 0 | Q48: =$I48*AI$14 -> 0 | R48: =$I48*AJ$14 -> 0.8182315 | S48: =$I48*AK$14 -> 0.75729937 | T48: =$I48*AL$14 -> 0.77470855 | U48: =$I48*AM$14 -> 0.78341314 | ... AC48: =$I48*AU$14 -> 0.57450297
A49: 400 | B49: PLACAS, ENCOFRADO Y DESENCOFRADO | C49: m2 | D49: 74.18 | I49: 74.18 | J49: 0 | K49: 0 | L49: 0 | M49: 0 | N49: =$I49*AJ$15 -> 7.1030313 | O49: =$I49*AK$15 -> 7.305975 | P49: =$I49*AL$15 -> 7.2045032 | Q49: =$I49*AM$15 -> 7.2653863 | R49: =$I49*AN$15 -> 5.682425 | S49: =$I49*AO$15 -> 5.682425 | T49: =$I49*AP$15 -> 5.2765375 | U49: =$I49*AQ$15 -> 5.682425 | ... AC49: =$I49*AY$15 -> 0
A50: 500 | B50: PLACAS, ACERO Fy=4200 kg/cm2 | C50: KG | D50: 419.35 | I50: 419.35 | J50: 0 | K50: 0 | L50: 0 | M50: 0 | N50: =$I50*AJ$16 -> 43.228673 | O50: =$I50*AK$16 -> 43.933488 | P50: =$I50*AL$16 -> 42.680483 | Q50: =$I50*AM$16 -> 42.288919 | R50: =$I50*AN$16 -> 46.987688 | S50: =$I50*AO$16 -> 46.987688 | T50: =$I50*AP$16 -> 46.909375 | U50: =$I50*AQ$16 -> 52.469585 | ... AC50: =$I50*AY$16 -> 0
A51: 300 | B51: MUROS DE CONTENC.- CONCRETO 210 kg/cm2 | C51: m3 | D51: 256.52 | I51: 256.52 | J51: 0 | K51: 0 | L51: 0 | M51: 0 | N51: =$I51*AF$14 -> 0 | O51: =$I51*AG$14 -> 0 | P51: =$I51*AH$14 -> 0 | Q51: =$I51*AI$14 -> 0 | R51: =$I51*AJ$14 -> 31.374102 | S51: =$I51*AK$14 -> 29.037733 | T51: =$I51*AL$14 -> 29.705267 | U51: =$I51*AM$14 -> 30.039034 | ... AC51: =$I51*AU$14 -> 22.028625
A52: 400 | B52: MUROS DE CONTENC.- ENCOF. Y DESENCOFRADO | C52: m2 | D52: 2096.19 | I52: 2096.19 | J52: 0 | K52: 0 | L52: 0 | M52: 0 | N52: =$I52*AJ$15 -> 200.71857 | O52: =$I52*AK$15 -> 206.45338 | P52: =$I52*AL$15 -> 203.58597 | Q52: =$I52*AM$15 -> 205.30642 | R52: =$I52*AN$15 -> 160.57485 | S52: =$I52*AO$15 -> 160.57485 | T52: =$I52*AP$15 -> 149.10522 | U52: =$I52*AQ$15 -> 160.57485 | ... AC52: =$I52*AY$15 -> 0
A53: 500 | B53: MUROS DE CONTENC.- ACERO Fy=4200 kg/cm2 | C53: kg | D53: 18595.1 | I53: 18595.1 | J53: 0 | K53: 0 | L53: 0 | M53: 0 | N53: =$I53*AJ$16 -> 1916.8749 | O53: =$I53*AK$16 -> 1948.1283 | P53: =$I53*AL$16 -> 1892.5667 | Q53: =$I53*AM$16 -> 1875.2037 | R53: =$I53*AN$16 -> 2083.5597 | S53: =$I53*AO$16 -> 2083.5597 | T53: =$I53*AP$16 -> 2080.0871 | U53: =$I53*AQ$16 -> 2326.6417 | ... AC53: =$I53*AY$16 -> 0
B54: Columnas
A55: 300 | B55: COLUMNAS - CONCRETO 210 KG/CM² - 1 PISO | C55: m3 | D55: 66.63 | I55: 66.63 | J55: 0 | K55: 0 | L55: 0 | M55: 0 | N55: =$I55*AF$14 -> 0 | O55: =$I55*AG$14 -> 0 | P55: =$I55*AH$14 -> 0 | Q55: =$I55*AI$14 -> 0 | R55: =$I55*AJ$14 -> 8.1492922 | S55: =$I55*AK$14 -> 7.54243 | T55: =$I55*AL$14 -> 7.7158192 | U55: =$I55*AM$14 -> 7.8025138 | ... AC55: =$I55*AU$14 -> 5.7218434
A56: 400 | B56: COLUMNAS.- ENCOFRADO Y DESENCOFRADO | C56: m2 | D56: 901.38 | I56: 901.38 | J56: 0 | K56: 0 | L56: 0 | M56: 0 | N56: =$I56*AJ$15 -> 86.310735 | O56: =$I56*AK$15 -> 88.776756 | P56: =$I56*AL$15 -> 87.543746 | Q56: =$I56*AM$15 -> 88.283552 | R56: =$I56*AN$15 -> 69.048588 | S56: =$I56*AO$15 -> 69.048588 | T56: =$I56*AP$15 -> 64.116546 | U56: =$I56*AQ$15 -> 69.048588 | ... AC56: =$I56*AY$15 -> 0
A57: 500 | B57: COLUMNAS.- ACERO Fy=4200 kg/cm2 | C57: KG | D57: 11604.02 | I57: 11604.02 | J57: 0 | K57: 0 | L57: 0 | M57: 0 | N57: =$I57*AJ$16 -> 1196.1998 | O57: =$I57*AK$16 -> 1215.7031 | P57: =$I57*AL$16 -> 1181.0306 | Q57: =$I57*AM$16 -> 1170.1955 | R57: =$I57*AN$16 -> 1300.2172 | S57: =$I57*AO$16 -> 1300.2172 | T57: =$I57*AP$16 -> 1298.0501 | U57: =$I57*AQ$16 -> 1451.9092 | ... AC57: =$I57*AY$16 -> 0
B58: Vigas
A59: 300 | B59: VIGAS.- CONCRETO 210 kg/cm2 - 1 piso | C59: m3 | D59: 36.12 | I59: 36.12 | J59: 0 | K59: 0 | L59: 0 | M59: 0 | N59: =$I59*AF$14 -> 0 | O59: =$I59*AG$14 -> 0 | P59: =$I59*AH$14 -> 0 | Q59: =$I59*AI$14 -> 0 | R59: =$I59*AJ$14 -> 4.4177162 | S59: =$I59*AK$14 -> 4.0887374 | T59: =$I59*AL$14 -> 4.1827313 | U59: =$I59*AM$14 -> 4.2297283 | ... AC59: =$I59*AU$14 -> 3.1018008
A60: 400 | B60: VIGAS.- ENCOFRADO Y DESENCOFRADO | C60: m2 | D60: 545.23 | I60: 545.23 | J60: 0 | K60: 0 | L60: 0 | M60: 0 | N60: =$I60*AJ$15 -> 52.20795 | O60: =$I60*AK$15 -> 53.699606 | P60: =$I60*AL$15 -> 52.953778 | Q60: =$I60*AM$15 -> 53.401275 | R60: =$I60*AN$15 -> 41.76636 | S60: =$I60*AO$15 -> 41.76636 | T60: =$I60*AP$15 -> 38.783049 | U60: =$I60*AQ$15 -> 41.76636 | ... AC60: =$I60*AY$15 -> 0
A61: 500 | B61: VIGAS.- ACERO Fy=4200 kg/cm2 | C61: KG | D61: 5144.6 | I61: 5144.6 | J61: 0 | K61: 0 | L61: 0 | M61: 0 | N61: =$I61*AJ$16 -> 530.33082 | O61: =$I61*AK$16 -> 538.97752 | P61: =$I61*AL$16 -> 523.60561 | Q61: =$I61*AM$16 -> 518.80189 | R61: =$I61*AN$16 -> 576.44655 | S61: =$I61*AO$16 -> 576.44655 | T61: =$I61*AP$16 -> 575.4858 | U61: =$I61*AQ$16 -> 643.69864 | ... AC61: =$I61*AY$16 -> 0
B62: Losas Macizas
A63: 300 | B63: LOSAS MACIZAS.- CONC.210 kg/cm2 - 1 PISO | C63: M3 | D63: 0.63 | I63: 0.63 | J63: 0 | K63: 0 | L63: 0 | M63: 0 | N63: =$I63*AF$14 -> 0 | O63: =$I63*AG$14 -> 0 | P63: =$I63*AH$14 -> 0 | Q63: =$I63*AI$14 -> 0 | R63: =$I63*AJ$14 -> 0.07705319 | S63: =$I63*AK$14 -> 0.071315187 | T63: =$I63*AL$14 -> 0.072954616 | U63: =$I63*AM$14 -> 0.073774331 | ... AC63: =$I63*AU$14 -> 0.054101176
A64: 400 | B64: LOSAS MACIZAS.- ENCOFRADO Y DESENCOFRADO | C64: m2 | D64: 6.54 | I64: 6.54 | J64: 0 | K64: 0 | L64: 0 | M64: 0 | N64: =$I64*AJ$15 -> 0.62623112 | O64: =$I64*AK$15 -> 0.64412344 | P64: =$I64*AL$15 -> 0.63517728 | Q64: =$I64*AM$15 -> 0.64054498 | R64: =$I64*AN$15 -> 0.5009849 | S64: =$I64*AO$15 -> 0.5009849 | T64: =$I64*AP$15 -> 0.46520026 | U64: =$I64*AQ$15 -> 0.5009849 | ... AC64: =$I64*AY$15 -> 0
A65: 500 | B65: LOSAS MACIZAS.- ACERO Fy=4,200 kg/cm2 | C65: KG | D65: 73.15 | I65: 73.15 | J65: 0 | K65: 0 | L65: 0 | M65: 0 | N65: =$I65*AJ$16 -> 7.5406639 | O65: =$I65*AK$16 -> 7.6636095 | P65: =$I65*AL$16 -> 7.4450396 | Q65: =$I65*AM$16 -> 7.3767365 | R65: =$I65*AN$16 -> 8.1963738 | S65: =$I65*AO$16 -> 8.1963738 | T65: =$I65*AP$16 -> 8.1827132 | U65: =$I65*AQ$16 -> 9.1526175 | ... AC65: =$I65*AY$16 -> 0
B66: Losas Aligeradas
A67: 300 | B67: LOSA ALIGERADA - CONCRETO 210 kg/cm2 - 1 PISO | C67: m3 | D67: 2.13 | I67: 2.13 | J67: 0 | K67: 0 | L67: 0 | M67: 0 | N67: =$I67*AF$14 -> 0 | O67: =$I67*AG$14 -> 0 | P67: =$I67*AH$14 -> 0 | Q67: =$I67*AI$14 -> 0 | R67: =$I67*AJ$14 -> 0.26051317 | S67: =$I67*AK$14 -> 0.24111325 | T67: =$I67*AL$14 -> 0.24665608 | U67: =$I67*AM$14 -> 0.2494275 | ... AC67: =$I67*AU$14 -> 0.1829135
A68: 400 | B68: LOSA ALIGERADA.- ENCOFRADO Y DESENCOFRADO | C68: m2 | D68: 24.72 | I68: 24.72 | J68: 0 | K68: 0 | L68: 0 | M68: 0 | N68: =$I68*AJ$15 -> 2.3670387 | O68: =$I68*AK$15 -> 2.4346684 | P68: =$I68*AL$15 -> 2.4008536 | Q68: =$I68*AM$15 -> 2.4211425 | R68: =$I68*AN$15 -> 1.893631 | S68: =$I68*AO$15 -> 1.893631 | T68: =$I68*AP$15 -> 1.7583716 | U68: =$I68*AQ$15 -> 1.893631 | ... AC68: =$I68*AY$15 -> 0
A69: 500 | B69: LOSA ALIGERADA.- ACERO Fy=4,200 kg/cm2 | C69: KG | D69: 93.93 | I69: 93.93 | J69: 0 | K69: 0 | L69: 0 | M69: 0 | N69: =$I69*AJ$16 -> 9.6827691 | O69: =$I69*AK$16 -> 9.8406404 | P69: =$I69*AL$16 -> 9.5599804 | Q69: =$I69*AM$16 -> 9.4722742 | R69: =$I69*AN$16 -> 10.524749 | S69: =$I69*AO$16 -> 10.524749 | T69: =$I69*AP$16 -> 10.507208 | U69: =$I69*AQ$16 -> 11.752636 | ... AC69: =$I69*AY$16 -> 0
A70: 300 | B70: LOSA ALIGERADA.- LADR. HUECO 15x30x30 | C70: und | D70: 205.92 | I70: 205.92 | J70: 0 | K70: 0 | L70: 0 | M70: 0 | N70: =$I70*AF$14 -> 0 | O70: =$I70*AG$14 -> 0 | P70: =$I70*AH$14 -> 0 | Q70: =$I70*AI$14 -> 0 | R70: =$I70*AJ$14 -> 25.185386 | S70: =$I70*AK$14 -> 23.309878 | T70: =$I70*AL$14 -> 23.845737 | U70: =$I70*AM$14 -> 24.113667 | ... AC70: =$I70*AU$14 -> 17.683356
B71: Gradas Armadas en Pisos
A72: 300 | B72: GRADAS EN PISO, CONCRETO F'c=175 kg/cm2. | C72: m2 | D72: 12.31 | I72: 12.31 | J72: 0 | K72: 0 | L72: 0 | M72: 0 | N72: =$I72*AF$14 -> 0 | O72: =$I72*AG$14 -> 0 | P72: =$I72*AH$14 -> 0 | Q72: =$I72*AI$14 -> 0 | R72: =$I72*AJ$14 -> 1.5055949 | S72: =$I72*AK$14 -> 1.3934761 | T72: =$I72*AL$14 -> 1.42551 | U72: =$I72*AM$14 -> 1.441527 | ... AC72: =$I72*AU$14 -> 1.0571198
A73: 400 | B73: GRADAS, ENCOFRADO Y DESENCOFRADO | C73: m2 | D73: 6.96 | I73: 6.96 | J73: 0 | K73: 0 | L73: 0 | M73: 0 | N73: =$I73*AJ$15 -> 0.6664478 | O73: =$I73*AK$15 -> 0.68548917 | P73: =$I73*AL$15 -> 0.67596848 | Q73: =$I73*AM$15 -> 0.68168089 | R73: =$I73*AN$15 -> 0.53315824 | S73: =$I73*AO$15 -> 0.53315824 | T73: =$I73*AP$15 -> 0.49507551 | U73: =$I73*AQ$15 -> 0.53315824 | ... AC73: =$I73*AY$15 -> 0
A74: 500 | B74: GRADAS EN PISO, ACERO fy=4200kg/cm2 | C74: kg | D74: 83.01 | I74: 83.01 | J74: 0 | K74: 0 | L74: 0 | M74: 0 | N74: =$I74*AJ$16 -> 8.5570815 | O74: =$I74*AK$16 -> 8.6965991 | P74: =$I74*AL$16 -> 8.4485678 | Q74: =$I74*AM$16 -> 8.371058 | R74: =$I74*AN$16 -> 9.3011756 | S74: =$I74*AO$16 -> 9.3011756 | T74: =$I74*AP$16 -> 9.2856736 | U74: =$I74*AQ$16 -> 10.386313 | ... AC74: =$I74*AY$16 -> 0

Sheet SUBCONTRATOS
A2: PC | B2: ITEM | C2: RECURSOS | D2: UND | E2: SUBCONTRATO | H2: MES 1 NOVIEMBRE | J2: MES 2 DICIEMBRE | L2: MES 3 ENERO | N2: MES 4 FEBRERO | P2: MES 5 MARZO
E3: METRADO | F3: PRECIO | G3: SUBTOTAL | H3: METRADO | I3: MONTO | J3: METRADO | K3: MONTO | L3: METRADO | M3: MONTO | N3: METRADO | O3: MONTO | P3: METRADO | Q3: MONTO
A4: 300 | B4: OS003 | C4: SC MANO DE OBRA ACERO CORRUGADO | D4: kg | E4: 35113.4 | F4: 0.74 | G4: =E4*F4 -> 25983.916 | J4: 9500 | K4: =J4*F4 -> 7030 | L4: 19300 | M4: =L4*F4 -> 14282 | N4: 6313.4 | O4: =N4*F4 -> 4671.916
A6: 200 | B6: OS004 | C6: SC AFIRMADO COMPACTADO 8" | D6: m2 | E6: 70.33 | F6: 13 | G6: =E6*F6 -> 914.29 | L6: 32 | M6: =L6*F6 -> 416 | N6: 35 | O6: =N6*F6 -> 455 | P6: 3.33 | Q6: =P6*F6 -> 43.29
A7: 200 | B7: OS004 | C7: SC AFIRMADO COMPACTADO 12" | D7: m2 | E7: 8.73 | F7: 15 | G7: =E7*F7 -> 130.95 | L7: 4.365 | M7: =L7*F7 -> 65.475 | N7: 3.492 | O7: =N7*F7 -> 52.38 | P7: 0.873 | Q7: =P7*F7 -> 13.095
A8: 200 | B8: OS004 | C8: SC EXCAVACION DE ZANJAS Y ZAPATAS Rt> 2KG/CM2 H=1.5m | D8: m3 | E8: 39.81 | F8: 19 | G8: =E8*F8 -> 756.39 | H8: 24 | I8: =H8*F8 -> 456 | J8: 15.81 | K8: =J8*F8 -> 300.39
A9: 200 | B9: OS004 | C9: SC EXCAVACION DE ZANJAS Y ZAPATAS Rt> 2KG/CM2 H=2.00m | D9: m3 | E9: 1876.4 | F9: 21.1 | G9: =E9*F9 -> 39592.04 | H9: 1150 | I9: =H9*F9 -> 24265 | J9: 726.4 | K9: =J9*F9 -> 15327.04
A10: 200 | B10: OS004 | C10: SC RELLENO COMPACTADO CON EQUIPO | D10: m3 | E10: 1138.01 | F10: 15 | G10: =E10*F10 -> 17070.15 | J10: 341.403 | K10: =J10*F10 -> 5121.045 | L10: 398.3035 | M10: =L10*F10 -> 5974.5525 | N10: 398.3035 | O10: =N10*F10 -> 5974.5525
A11: 200 | B11: OS004 | C11: SC ELIMINACION DE MATERIAL EXCEDENTE CON VOLQUETES | D11: m3 | E11: 1173.963 | F11: 17.4 | G11: =E11*F11 -> 20426.956 | H11: 470 | I11: =H11*F11 -> 8178 | J11: 703.96 | K11: =J11*F11 -> 12248.904

Sheet CAJA CHICA GG
J2: MES 1 NOVIEMBRE | L2: MES 2 DICIEMBRE | N2: MES 3 ENERO | P2: MES 4 FEBRERO | R2: MES 5 MARZO
A3: ITEM | B3: DESCRIPCION | C3: PROVEEDOR | D3: UNIDAD | E3: CANTIDAD | F3: P.U. | G3: SUBTOTAL | H3: PARTIDA DE CONTROL | I3: TIPO DE COSTO | J3: METRADO UTILIZADO | K3: SUB TOTAL | L3: METRADO UTILIZADO | M3: SUB TOTAL | N3: METRADO UTILIZADO | O3: SUB TOTAL | P3: METRADO UTILIZADO | Q3: SUB TOTAL | R3: METRADO UTILIZADO | S3: SUB TOTAL
B4: ENSAYOS DE LABORATORIO | E4: 1 | F4: 400 | G4: 400 | H4: 600 | I4: SERVICIO | K4: 400 | M4: 380 | O4: 401 | Q4: 385 | S4: 396
B5: POLIZAS DE SEGURO | E5: 1 | F5: 1200 | G5: 1200 | H5: 600 | I5: SERVICIO | K5: 1200 | M5: 1150 | O5: 1210 | Q5: 1180 | S5: 1350
B6: UTILES DE OFICINA | E6: 1 | F6: 450 | G6: 450 | H6: 600 | I6: MATERIALES | K6: 450 | M6: 430 | O6: 435 | Q6: 465 | S6: 445
B7: CARTA FIANZA DE FIEL CUMPLIMIENTO | G7: =1337712.82*0.1*0.03 -> 4013.1385 | H7: 600 | I7: GASTOS FINANC | K7: =G7*0.2 -> 802.62769 | M7: 805 | O7: 803 | Q7: 803.5 | S7: 790
B8: CARTA FIANZA DE ADELANTO DIRECTO | G8: =1337712.82*0.1*0.03 -> 4013.1385 | H8: 600 | I8: GASTOS FINANC | K8: =+G8*0.2 -> 802.62769 | M8: 800.1 | O8: 795 | Q8: 801.45 | S8: 780
B9: IMPLEMENTOS DE SEGURIDAD | E9: 1 | F9: 1000 | G9: 1000 | H9: 600 | I9: MATERIALES | K9: 230 | M9: 200 | O9: 210 | Q9: 225 | S9: 185
B10: MEDICAMENTOS | E10: 1 | F10: 1000 | G10: 1000 | H10: 600 | I10: MATERIALES | K10: 220 | M10: 180 | O10: 205 | Q10: 192 | S10: 215
B11: SENCICO (0.2% DEL PPTO TOTAL) | G11: =1337712.82*0.002 -> 2675.4256 | H11: 600 | I11: GASTOS FINANC | K11: =+G11*0.2 -> 535.08513 | M11: 540 | O11: 526 | Q11: 515 | S11: 520
B12: CONAFOVICER (2% DE LA MO) | G12: =870692.06*0.02 -> 17413.841 | H12: 600 | I12: GASTOS FINANC | K12: =+G12*0.2 -> 3482.7682 | M12: 3378 | O12: 3510 | Q12: 3650 | S12: 3250

Sheet CRONOG CONT VENTA
A1: CRONOGRAMA VALORIZADO DE OBRA - PROGRAMACION VENTA
A3: PROYECTO: | B3: I.E. N° 1182 "EL BOSQUE" - CERCO + INGRESOS Y CASETAS
A5: ITEM | B5: DESCRIPCION | C5: UND | D5: CONTRACTUAL | G5: PROGRAMACION
D6: METRADO | E6: P.U. (S/.) | F6: PARCIAL (S/.) | G6: 45597 | H6: 45627 | I6: 45658 | J6: 45689 | K6: 45717 | N6: 45597 | O6: 45627 | P6: 45658 | Q6: 45689 | R6: 45717
A7: 01 | B7: OBRAS PROVISIONALES, TRABAJOS PRELIMINARES, SEGURIDAD Y SALUD
A8: 01.02 | B8: Trabajos Preliminares
A9: 01.02.04 | B9: Trazo, Niveles y Replanteo
A10: 01.02.04.01 | B10: TRAZO Y REPLANTEO PRELIMINAR | C10: M2 | D10: 897.34 | E10: 2.04 | F10: 1830.57 | G10: =$F10*N10 -> 915.285 | H10: =$F10*O10 -> 915.285 | I10: =$F10*P10 -> 0 | J10: =$F10*Q10 -> 0 | K10: =$F10*R10 -> 0 | L10: =F10-SUM(G10:K10) -> 0 | N10: 0.5 | O10: 0.5
A11: 01.02.04.02 | B11: TRAZO Y REPLANTEO DURANTE EL PROCESO | C11: m2 | D11: 897.34 | E11: 2.04 | F11: 1830.57 | G11: =$F11*N11 -> 457.6425 | H11: =$F11*O11 -> 457.6425 | I11: =$F11*P11 -> 457.6425 | J11: =$F11*Q11 -> 457.6425 | K11: =$F11*R11 -> 0 | L11: =F11-SUM(G11:K11) -> 0 | N11: 0.25 | O11: 0.25 | P11: 0.25 | Q11: 0.25
A12: 02 | B12: ESTRUCTURAS
A13: 02.01 | B13: Movimiento de Tierras
A14: 02.01.01 | B14: Excavaciones
A15: 02.01.01.01 | B15: EXCAV.ZANJAS Y ZAPATA RT>2kg/cm2 H=1.5m | C15: m3 | D15: 41.9 | E15: 46.74 | F15: 1958.41 | G15: =$F15*N15 -> 979.205 | H15: =$F15*O15 -> 979.205 | I15: =$F15*P15 -> 0 | J15: =$F15*Q15 -> 0 | K15: =$F15*R15 -> 0 | L15: =F15-SUM(G15:K15) -> 0 | N15: 0.5 | O15: 0.5
A16: 02.01.01.02 | B16: EXCAV.ZANJAS Y ZAPATA RT>2kg/cm2 H=2.0m | C16: m3 | D16: 1975.16 | E16: 50.99 | F16: 100713.41 | G16: =$F16*N16 -> 50356.705 | H16: =$F16*O16 -> 50356.705 | I16: =$F16*P16 -> 0 | J16: =$F16*Q16 -> 0 | K16: =$F16*R16 -> 0 | L16: =F16-SUM(G16:K16) -> 0 | N16: 0.5 | O16: 0.5
A17: 02.01.03 | B17: Rellenos
A18: 02.01.03.01 | B18: RELLENO COMPACTADO C/EQUIPO MAT/PROPIO | C18: m3 | D18: 1197.91 | E18: 26.01 | F18: 31157.64 | G18: =$F18*N18 -> 0 | H18: =$F18*O18 -> 15578.82 | I18: =$F18*P18 -> 15578.82 | J18: =$F18*Q18 -> 0 | K18: =$F18*R18 -> 0 | L18: =F18-SUM(G18:K18) -> 0 | O18: 0.5 | P18: 0.5
A19: 02.01.04 | B19: Eliminacion de Material Excedente
A20: 02.01.04.01 | B20: ACARREO INTERNO, MATERIAL PROCEDENTE DE EXCAVACIONES | C20: m3 | D20: 68.91 | E20: 17.53 | F20: 1207.99 | G20: =$F20*N20 -> 362.397 | H20: =$F20*O20 -> 603.995 | I20: =$F20*P20 -> 241.598 | J20: =$F20*Q20 -> 0 | K20: =$F20*R20 -> 0 | L20: =F20-SUM(G20:K20) -> 0 | N20: 0.3 | O20: 0.5 | P20: 0.2
A21: 02.01.04.02 | B21: ELIMINACION MATERIAL EXCEDENTE ACARREADO | C21: M3 | D21: 68.91 | E21: 16.02 | F21: 1103.94 | G21: =$F21*N21 -> 331.182 | H21: =$F21*O21 -> 331.182 | I21: =$F21*P21 -> 441.576 | J21: =$F21*Q21 -> 0 | K21: =$F21*R21 -> 0 | L21: =F21-SUM(G21:K21) -> 0 | N21: 0.3 | O21: 0.3 | P21: 0.4
A22: 02.01.04.03 | B22: ELIMINACION MATERIAL EXCEDENTE C/MAQUINA | C22: m3 | D22: 995.9 | E22: 21.84 | F22: 21750.46 | G22: =$F22*N22 -> 6525.138 | H22: =$F22*O22 -> 6525.138 | I22: =$F22*P22 -> 8700.184 | J22: =$F22*Q22 -> 0 | K22: =$F22*R22 -> 0 | L22: =F22-SUM(G22:K22) -> 0 | N22: 0.3 | O22: 0.3 | P22: 0.4
A23: 02.01.05 | B23: Nivelacion Interior y Apisonado
A24: 02.01.05.01 | B24: ESCARIFICADO Y COMPACTACION CON PLANCHA COMPACTADORA e = 30 cm | C24: m2 | D24: 68.95 | E24: 4.72 | F24: 325.44 | G24: =$F24*N24 -> 65.088 | H24: =$F24*O24 -> 130.176 | I24: =$F24*P24 -> 130.176 | J24: =$F24*Q24 -> 0 | K24: =$F24*R24 -> 0 | L24: =F24-SUM(G24:K24) -> 0 | N24: 0.2 | O24: 0.4 | P24: 0.4
A25: 02.01.05.02 | B25: ESCARIFICADO Y COMPACTACION CON PLANCHA COMPACTADORA H=0.60m (02 CAPAS 30cm c/u) | C25: m2 | D25: 8.56 | E25: 7.85 | F25: 67.2 | G25: =$F25*N25 -> 13.44 | H25: =$F25*O25 -> 26.88 | I25: =$F25*P25 -> 26.88 | J25: =$F25*Q25 -> 0 | K25: =$F25*R25 -> 0 | L25: =F25-SUM(G25:K25) -> 0 | N25: 0.2 | O25: 0.4 | P25: 0.4
A26: 02.01.05.05 | B26: AFIRMADO DE 8" PARA PISOS,PATIOS Y VEREDAS,COMPACTADO. | C26: m2 | D26: 68.95 | E26: 15.19 | F26: 1047.35 | G26: =$F26*N26 -> 209.47 | H26: =$F26*O26 -> 418.94 | I26: =$F26*P26 -> 418.94 | J26: =$F26*Q26 -> 0 | K26: =$F26*R26 -> 0 | L26: =F26-SUM(G26:K26) -> 0 | N26: 0.2 | O26: 0.4 | P26: 0.4
A27: 02.01.05.06 | B27: AFIRMADO DE 12" EN PISOS INTERIOR/EXTERIOR,COMPACTADO. | C27: m2 | D27: 8.56 | E27: 21.79 | F27: 186.52 | G27: =$F27*N27 -> 37.304 | H27: =$F27*O27 -> 74.608 | I27: =$F27*P27 -> 74.608 | J27: =$F27*Q27 -> 0 | K27: =$F27*R27 -> 0 | L27: =F27-SUM(G27:K27) -> 0 | N27: 0.2 | O27: 0.4 | P27: 0.4
A28: 02.02 | B28: Obras de Concreto Simple
A29: 02.02.01 | B29: Falsos Cimientos
A30: 02.02.01.01 | B30: SUBCIMIENTO, SUBZAPATA MEZCLA 1:12 + 30 % P.G. | C30: m3 | D30: 323.69 | E30: 173.72 | F30: 56231.43 | G30: =$F30*N30 -> 0 | H30: =$F30*O30 -> 28115.715 | I30: =$F30*P30 -> 28115.715 | J30: =$F30*Q30 -> 0 | K30: =$F30*R30 -> 0 | L30: =F30-SUM(G30:K30) -> 0 | O30: 0.5 | P30: 0.5
A31: 02.02.02 | B31: Cimientos
A32: 02.02.02.02 | B32: CIMIENTOS CORRIDOS 1:10 + 30 % P.G. f'c >=100Kg/cm2 | C32: m3 | D32: 24.73 | E32: 179.78 | F32: 4445.96 | G32: =$F32*N32 -> 0 | H32: =$F32*O32 -> 0 | I32: =$F32*P32 -> 2222.98 | J32: =$F32*Q32 -> 2222.98 | K32: =$F32*R32 -> 0 | L32: =F32-SUM(G32:K32) -> 0 | P32: 0.5 | Q32: 0.5
A33: 02.02.02.03 | B33: CIMIENTO CORRIDO - ENCOFRADO Y DESENCOFRADO | C33: m2 | D33: 23.09 | E33: 46.17 | F33: 1066.07 | G33: =$F33*N33 -> 0 | H33: =$F33*O33 -> 426.428 | I33: =$F33*P33 -> 426.428 | J33: =$F33*Q33 -> 213.214 | K33: =$F33*R33 -> 0 | L33: =F33-SUM(G33:K33) -> 0 | O33: 0.4 | P33: 0.4 | Q33: 0.2
A34: 02.02.02.04 | B34: CALZADURA: CONCRETO C:H 1:10 + 30 % P.G. | C34: m3 | D34: 163.82 | E34: 179.78 | F34: 29451.56 | G34: =$F34*N34 -> 29451.56 | H34: =$F34*O34 -> 0 | I34: =$F34*P34 -> 0 | J34: =$F34*Q34 -> 0 | K34: =$F34*R34 -> 0 | L34: =F34-SUM(G34:K34) -> 0 | N34: 1
A35: 02.02.02.05 | B35: CALZADURA: ENCOFRADO Y DESENCOFRADO | C35: m2 | D35: 327.63 | E35: 37.47 | F35: 12276.3 | G35: =$F35*N35 -> 12276.3 | H35: =$F35*O35 -> 0 | I35: =$F35*P35 -> 0 | J35: =$F35*Q35 -> 0 | K35: =$F35*R35 -> 0 | L35: =F35-SUM(G35:K35) -> 0 | N35: 1
A36: 02.02.03 | B36: Sobrecimientos
A37: 02.02.03.01 | B37: SOBRECIMIENTO, CONCRETO 1:8 + 25% P.M. f'c >=100Kg/cm2 | C37: m3 | D37: 3.21 | E37: 260.59 | F37: 836.49 | G37: =$F37*N37 -> 0 | H37: =$F37*O37 -> 0 | I37: =$F37*P37 -> 418.245 | J37: =$F37*Q37 -> 418.245 | K37: =$F37*R37 -> 0 | L37: =F37-SUM(G37:K37) -> 0 | P37: 0.5 | Q37: 0.5
A38: 02.02.03.02 | B38: SOBRECIMIENTO, ENCOFRADO Y DESENCOFRADO | C38: m2 | D38: 43.95 | E38: 37.7 | F38: 1656.92 | G38: =$F38*N38 -> 0 | H38: =$F38*O38 -> 662.768 | I38: =$F38*P38 -> 662.768 | J38: =$F38*Q38 -> 331.384 | K38: =$F38*R38 -> 0 | L38: =F38-SUM(G38:K38) -> 0 | O38: 0.4 | P38: 0.4 | Q38: 0.2
A39: 02.03 | B39: Obras de Concreto Armado
A40: 02.03.02 | B40: Zapatas
A41: 02.03.02.01 | B41: ZAPATAS.- CONCRETO 210 kg/cm2 | C41: m3 | D41: 396.75 | E41: 292.79 | F41: 116164.43 | G41: =$F41*N41 -> 34849.329 | H41: =$F41*O41 -> 81315.101 | I41: =$F41*P41 -> 0 | J41: =$F41*Q41 -> 0 | K41: =$F41*R41 -> 0 | L41: =F41-SUM(G41:K41) -> 0 | N41: 0.3 | O41: 0.7
A42: 02.03.02.03 | B42: ZAPATAS.- ACERO Fy=4200 kg/cm2 | C42: KG | D42: 17534.91 | E42: 4.02 | F42: 70490.34 | G42: =$F42*N42 -> 21147.102 | H42: =$F42*O42 -> 49343.238 | I42: =$F42*P42 -> 0 | J42: =$F42*Q42 -> 0 | K42: =$F42*R42 -> 0 | L42: =F42-SUM(G42:K42) -> 0 | N42: 0.3 | O42: 0.7
A43: 02.03.05 | B43: Placas y Muros de Contención
A44: 02.03.05.02 | B44: PLACAS, CONCRETO F'c=210 kg/cm2 - 1 piso | C44: m3 | D44: 6.69 | E44: 454.82 | F44: 3042.75 | G44: =$F44*N44 -> 0 | H44: =$F44*O44 -> 912.825 | I44: =$F44*P44 -> 912.825 | J44: =$F44*Q44 -> 1217.1 | K44: =$F44*R44 -> 0 | L44: =F44-SUM(G44:K44) -> 0 | O44: 0.3 | P44: 0.3 | Q44: 0.4
A45: 02.03.05.04 | B45: PLACAS, ENCOFRADO Y DESENCOFRADO | C45: m2 | D45: 74.18 | E45: 59.78 | F45: 4434.48 | G45: =$F45*N45 -> 0 | H45: =$F45*O45 -> 1330.344 | I45: =$F45*P45 -> 1330.344 | J45: =$F45*Q45 -> 1773.792 | K45: =$F45*R45 -> 0 | L45: =F45-SUM(G45:K45) -> 0 | O45: 0.3 | P45: 0.3 | Q45: 0.4
A46: 02.03.05.05 | B46: PLACAS, ACERO Fy=4200 kg/cm2 | C46: KG | D46: 419.35 | E46: 4.02 | F46: 1685.79 | G46: =$F46*N46 -> 0 | H46: =$F46*O46 -> 505.737 | I46: =$F46*P46 -> 505.737 | J46: =$F46*Q46 -> 674.316 | K46: =$F46*R46 -> 0 | L46: =F46-SUM(G46:K46) -> 0 | O46: 0.3 | P46: 0.3 | Q46: 0.4
A47: 02.03.05.07 | B47: MUROS DE CONTENC.- CONCRETO 210 kg/cm2 | C47: m3 | D47: 256.52 | E47: 417.41 | F47: 107074.01 | G47: =$F47*N47 -> 0 | H47: =$F47*O47 -> 32122.203 | I47: =$F47*P47 -> 32122.203 | J47: =$F47*Q47 -> 42829.604 | K47: =$F47*R47 -> 0 | L47: =F47-SUM(G47:K47) -> 0 | O47: 0.3 | P47: 0.3 | Q47: 0.4
A48: 02.03.05.09 | B48: MUROS DE CONTENC.- ENCOF. Y DESENCOFRADO | C48: m2 | D48: 2096.19 | E48: 51.21 | F48: 107345.89 | G48: =$F48*N48 -> 0 | H48: =$F48*O48 -> 32203.767 | I48: =$F48*P48 -> 32203.767 | J48: =$F48*Q48 -> 42938.356 | K48: =$F48*R48 -> 0 | L48: =F48-SUM(G48:K48) -> 0 | O48: 0.3 | P48: 0.3 | Q48: 0.4
A49: 02.03.05.11 | B49: MUROS DE CONTENC.- ACERO Fy=4200 kg/cm2 | C49: kg | D49: 18595.1 | E49: 4.02 | F49: 74752.3 | G49: =$F49*N49 -> 0 | H49: =$F49*O49 -> 22425.69 | I49: =$F49*P49 -> 22425.69 | J49: =$F49*Q49 -> 29900.92 | K49: =$F49*R49 -> 0 | L49: =F49-SUM(G49:K49) -> 0 | O49: 0.3 | P49: 0.3 | Q49: 0.4
A50: 02.03.06 | B50: Columnas
A51: 02.03.06.02 | B51: COLUMNAS - CONCRETO 210 KG/CM² - 1 PISO | C51: m3 | D51: 66.63 | E51: 442.62 | F51: 29491.77 | G51: =$F51*N51 -> 0 | H51: =$F51*O51 -> 0 | I51: =$F51*P51 -> 8847.531 | J51: =$F51*Q51 -> 8847.531 | K51: =$F51*R51 -> 11796.708 | L51: =F51-SUM(G51:K51) -> 0 | P51: 0.3 | Q51: 0.3 | R51: 0.4
A52: 02.03.06.06 | B52: COLUMNAS.- ENCOFRADO Y DESENCOFRADO | C52: m2 | D52: 901.38 | E52: 60.48 | F52: 54515.46 | G52: =$F52*N52 -> 0 | H52: =$F52*O52 -> 0 | I52: =$F52*P52 -> 16354.638 | J52: =$F52*Q52 -> 16354.638 | K52: =$F52*R52 -> 21806.184 | L52: =F52-SUM(G52:K52) -> 0 | P52: 0.3 | Q52: 0.3 | R52: 0.4
A53: 02.03.06.10 | B53: COLUMNAS.- ACERO Fy=4200 kg/cm2 | C53: KG | D53: 11604.02 | E53: 4.02 | F53: 46648.16 | G53: =$F53*N53 -> 0 | H53: =$F53*O53 -> 0 | I53: =$F53*P53 -> 13994.448 | J53: =$F53*Q53 -> 13994.448 | K53: =$F53*R53 -> 18659.264 | L53: =F53-SUM(G53:K53) -> 0 | P53: 0.3 | Q53: 0.3 | R53: 0.4
A54: 02.03.07 | B54: Vigas
A55: 02.03.07.02 | B55: VIGAS.- CONCRETO 210 kg/cm2 - 1 piso | C55: m3 | D55: 36.12 | E55: 325.93 | F55: 11772.59 | G55: =$F55*N55 -> 0 | H55: =$F55*O55 -> 0 | I55: =$F55*P55 -> 3531.777 | J55: =$F55*Q55 -> 3531.777 | K55: =$F55*R55 -> 4709.036 | L55: =F55-SUM(G55:K55) -> 0 | P55: 0.3 | Q55: 0.3 | R55: 0.4
A56: 02.03.07.06 | B56: VIGAS.- ENCOFRADO Y DESENCOFRADO | C56: m2 | D56: 545.23 | E56: 70.38 | F56: 38373.29 | G56: =$F56*N56 -> 0 | H56: =$F56*O56 -> 0 | I56: =$F56*P56 -> 11511.987 | J56: =$F56*Q56 -> 11511.987 | K56: =$F56*R56 -> 15349.316 | L56: =F56-SUM(G56:K56) -> 0 | P56: 0.3 | Q56: 0.3 | R56: 0.4
A57: 02.03.07.08 | B57: VIGAS.- ACERO Fy=4200 kg/cm2 | C57: KG | D57: 5144.6 | E57: 4.02 | F57: 20681.29 | G57: =$F57*N57 -> 0 | H57: =$F57*O57 -> 0 | I57: =$F57*P57 -> 6204.387 | J57: =$F57*Q57 -> 6204.387 | K57: =$F57*R57 -> 8272.516 | L57: =F57-SUM(G57:K57) -> 0 | P57: 0.3 | Q57: 0.3 | R57: 0.4
A58: 02.03.08 | B58: Losas Macizas
A59: 02.03.08.01 | B59: LOSAS MACIZAS.- CONC.210 kg/cm2 - 1 PISO | C59: M3 | D59: 0.63 | E59: 325.93 | F59: 205.34 | G59: =$F59*N59 -> 0 | H59: =$F59*O59 -> 0 | I59: =$F59*P59 -> 61.602 | J59: =$F59*Q59 -> 61.602 | K59: =$F59*R59 -> 82.136 | L59: =F59-SUM(G59:K59) -> 0 | P59: 0.3 | Q59: 0.3 | R59: 0.4
A60: 02.03.08.03 | B60: LOSAS MACIZAS.- ENCOFRADO Y DESENCOFRADO | C60: m2 | D60: 6.54 | E60: 55.43 | F60: 362.51 | G60: =$F60*N60 -> 0 | H60: =$F60*O60 -> 0 | I60: =$F60*P60 -> 108.753 | J60: =$F60*Q60 -> 108.753 | K60: =$F60*R60 -> 145.004 | L60: =F60-SUM(G60:K60) -> 0 | P60: 0.3 | Q60: 0.3 | R60: 0.4
A61: 02.03.08.04 | B61: LOSAS MACIZAS.- ACERO Fy=4,200 kg/cm2 | C61: KG | D61: 73.15 | E61: 4.02 | F61: 294.06 | G61: =$F61*N61 -> 0 | H61: =$F61*O61 -> 0 | I61: =$F61*P61 -> 88.218 | J61: =$F61*Q61 -> 88.218 | K61: =$F61*R61 -> 117.624 | L61: =F61-SUM(G61:K61) -> 0 | P61: 0.3 | Q61: 0.3 | R61: 0.4
A62: 02.03.09 | B62: Losas Aligeradas
A63: 02.03.09.01 | B63: LOSA ALIGERADA - CONCRETO 210 kg/cm2 - 1 PISO | C63: m3 | D63: 2.13 | E63: 315.52 | F63: 672.06 | G63: =$F63*N63 -> 0 | H63: =$F63*O63 -> 0 | I63: =$F63*P63 -> 201.618 | J63: =$F63*Q63 -> 201.618 | K63: =$F63*R63 -> 268.824 | L63: =F63-SUM(G63:K63) -> 0 | P63: 0.3 | Q63: 0.3 | R63: 0.4
A64: 02.03.09.03 | B64: LOSA ALIGERADA.- ENCOFRADO Y DESENCOFRADO | C64: m2 | D64: 24.72 | E64: 43.61 | F64: 1078.04 | G64: =$F64*N64 -> 0 | H64: =$F64*O64 -> 0 | I64: =$F64*P64 -> 323.412 | J64: =$F64*Q64 -> 323.412 | K64: =$F64*R64 -> 431.216 | L64: =F64-SUM(G64:K64) -> 0 | P64: 0.3 | Q64: 0.3 | R64: 0.4
A65: 02.03.09.04 | B65: LOSA ALIGERADA.- ACERO Fy=4,200 kg/cm2 | C65: KG | D65: 93.93 | E65: 4.02 | F65: 377.6 | G65: =$F65*N65 -> 0 | H65: =$F65*O65 -> 0 | I65: =$F65*P65 -> 113.28 | J65: =$F65*Q65 -> 113.28 | K65: =$F65*R65 -> 151.04 | L65: =F65-SUM(G65:K65) -> 0 | P65: 0.3 | Q65: 0.3 | R65: 0.4
A66: 02.03.09.05 | B66: LOSA ALIGERADA.- LADR. HUECO 15x30x30 | C66: und | D66: 205.92 | E66: 2.49 | F66: 512.74 | G66: =$F66*N66 -> 0 | H66: =$F66*O66 -> 0 | I66: =$F66*P66 -> 153.822 | J66: =$F66*Q66 -> 153.822 | K66: =$F66*R66 -> 205.096 | L66: =F66-SUM(G66:K66) -> 0 | P66: 0.3 | Q66: 0.3 | R66: 0.4
A67: 02.03.15 | B67: Gradas Armadas en Pisos
A68: 02.03.15.01 | B68: GRADAS EN PISO, CONCRETO F'c=175 kg/cm2. | C68: m2 | D68: 12.31 | E68: 80.04 | F68: 985.29 | G68: =$F68*N68 -> 0 | H68: =$F68*O68 -> 0 | I68: =$F68*P68 -> 295.587 | J68: =$F68*Q68 -> 295.587 | K68: =$F68*R68 -> 394.116 | L68: =F68-SUM(G68:K68) -> 0 | P68: 0.3 | Q68: 0.3 | R68: 0.4
A69: 02.03.15.03 | B69: GRADAS, ENCOFRADO Y DESENCOFRADO | C69: m2 | D69: 6.96 | E69: 41.15 | F69: 286.4 | G69: =$F69*N69 -> 0 | H69: =$F69*O69 -> 0 | I69: =$F69*P69 -> 85.92 | J69: =$F69*Q69 -> 85.92 | K69: =$F69*R69 -> 114.56 | L69: =F69-SUM(G69:K69) -> 0 | P69: 0.3 | Q69: 0.3 | R69: 0.4
A70: 02.03.15.04 | B70: GRADAS EN PISO, ACERO fy=4200kg/cm2 | C70: kg | D70: 83.01 | E70: 4.02 | F70: 333.7 | G70: =$F70*N70 -> 0 | H70: =$F70*O70 -> 0 | I70: =$F70*P70 -> 100.11 | J70: =$F70*Q70 -> 100.11 | K70: =$F70*R70 -> 133.48 | L70: =F70-SUM(G70:K70) -> 0 | P70: 0.3 | Q70: 0.3 | R70: 0.4
B71: COSTO DIRECTO | F71: =SUM(F7:F70) -> 960724.52 | G71: =SUM(G7:G70) -> 157977.15 | H71: =SUM(H7:H70) -> 325762.39 | I71: =SUM(I7:I70) -> 209394.22 | J71: =SUM(J7:J70) -> 184954.64 | K71: =SUM(K7:K70) -> 82636.12
B72: GASTOS GENERALES (10%) | F72: =F71*0.15 -> 144108.68 | G72: =G71*0.15 -> 23696.572 | H72: =H71*0.15 -> 48864.359 | I72: =I71*0.15 -> 31409.132 | J72: =J71*0.15 -> 27743.197 | K72: =K71*0.15 -> 12395.418
B73: UTILIDAD (5%) | F73: =F71*0.05 -> 48036.226 | G73: =G71*0.05 -> 7898.8574 | H73: =H71*0.05 -> 16288.12 | I73: =I71*0.05 -> 10469.711 | J73: =J71*0.05 -> 9247.7322 | K73: =K71*0.05 -> 4131.806
B74: SUBTOTAL | F74: =SUM(F71:F73) -> 1152869.4 | G74: =SUM(G71:G73) -> 189572.58 | H74: =SUM(H71:H73) -> 390914.87 | I74: =SUM(I71:I73) -> 251273.06 | J74: =SUM(J71:J73) -> 221945.57 | K74: =SUM(K71:K73) -> 99163.344
B75: IGV (18.00%) | F75: =ROUND(F74*0.18,2) -> 207516.5 | G75: =ROUND(G74*0.18,2) -> 34123.06 | H75: =ROUND(H74*0.18,2) -> 70364.68 | I75: =ROUND(I74*0.18,2) -> 45229.15 | J75: =ROUND(J74*0.18,2) -> 39950.2 | K75: =ROUND(K74*0.18,2) -> 17849.4
B76: COSTO TOTAL (INC. IGV) | F76: =SUM(F74:F75) -> 1360385.9 | G76: =SUM(G74:G75) -> 223695.64 | H76: =SUM(H74:H75) -> 461279.55 | I76: =SUM(I74:I75) -> 296502.21 | J76: =SUM(J74:J75) -> 261895.77 | K76: =SUM(K74:K75) -> 117012.74

Sheet CRONOG CONT META
A1: CRONOGRAMA VALORIZADO DE OBRA - PROGRAMACION VENTA CON COSTOS META
A3: PROYECTO: | B3: I.E. N° 1182 "EL BOSQUE" - CERCO + INGRESOS Y CASETAS
T4: METRADOS
A5: ITEM | B5: DESCRIPCION | C5: UND | D5: CONTRACTUAL | G5: PROGRAMACION
D6: METRADO | E6: P.U. (S/.) | F6: PARCIAL (S/.) | G6: 45597 | H6: 45627 | I6: 45658 | J6: 45689 | K6: 45717 | N6: 45597 | O6: 45627 | P6: 45658 | Q6: 45689 | R6: 45717 | T6: 45597 | U6: 45627 | V6: 45658 | W6: 45689 | X6: 45717
A7: 01 | B7: OBRAS PROVISIONALES, TRABAJOS PRELIMINARES, SEGURIDAD Y SALUD
A8: 01.02 | B8: Trabajos Preliminares
A9: 01.02.04 | B9: Trazo, Niveles y Replanteo
A10: 01.02.04.01 | B10: TRAZO Y REPLANTEO PRELIMINAR | C10: M2 | D10: 942.21 | E10: 1.33 | F10: 1253.14 | G10: =$F10*N10 -> 626.57 | H10: =$F10*O10 -> 626.57 | I10: =$F10*P10 -> 0 | J10: =$F10*Q10 -> 0 | K10: =$F10*R10 -> 0 | L10: =F10-SUM(G10:K10) -> 0 | N10: 0.5 | O10: 0.5 | T10: =N10*$D10 -> 471.105 | U10: =O10*$D10 -> 471.105 | V10: =P10*$D10 -> 0 | W10: =Q10*$D10 -> 0 | X10: =R10*$D10 -> 0
A11: 01.02.04.02 | B11: TRAZO Y REPLANTEO DURANTE EL PROCESO | C11: m2 | D11: 942.21 | E11: 1.33 | F11: 1253.14 | G11: =$F11*N11 -> 313.285 | H11: =$F11*O11 -> 313.285 | I11: =$F11*P11 -> 313.285 | J11: =$F11*Q11 -> 313.285 | K11: =$F11*R11 -> 0 | L11: =F11-SUM(G11:K11) -> 0 | N11: 0.25 | O11: 0.25 | P11: 0.25 | Q11: 0.25 | T11: =N11*$D11 -> 235.5525 | U11: =O11*$D11 -> 235.5525 | V11: =P11*$D11 -> 235.5525 | W11: =Q11*$D11 -> 235.5525 | X11: =R11*$D11 -> 0
A12: 02 | B12: ESTRUCTURAS
A13: 02.01 | B13: Movimiento de Tierras
A14: 02.01.01 | B14: Excavaciones
A15: 02.01.01.01 | B15: EXCAV.ZANJAS Y ZAPATA RT>2kg/cm2 H=1.5m | C15: m3 | D15: 39.81 | E15: 29.22 | F15: 1163.25 | G15: =$F15*N15 -> 581.625 | H15: =$F15*O15 -> 581.625 | I15: =$F15*P15 -> 0 | J15: =$F15*Q15 -> 0 | K15: =$F15*R15 -> 0 | L15: =F15-SUM(G15:K15) -> 0 | N15: 0.5 | O15: 0.5 | T15: =N15*$D15 -> 19.905 | U15: =O15*$D15 -> 19.905 | V15: =P15*$D15 -> 0 | W15: =Q15*$D15 -> 0 | X15: =R15*$D15 -> 0
A16: 02.01.01.02 | B16: EXCAV.ZANJAS Y ZAPATA RT>2kg/cm2 H=2.0m | C16: m3 | D16: 1876.4 | E16: 33.36 | F16: 62596.7 | G16: =$F16*N16 -> 31298.35 | H16: =$F16*O16 -> 31298.35 | I16: =$F16*P16 -> 0 | J16: =$F16*Q16 -> 0 | K16: =$F16*R16 -> 0 | L16: =F16-SUM(G16:K16) -> 0 | N16: 0.5 | O16: 0.5 | T16: =N16*$D16 -> 938.2 | U16: =O16*$D16 -> 938.2 | V16: =P16*$D16 -> 0 | W16: =Q16*$D16 -> 0 | X16: =R16*$D16 -> 0
A17: 02.01.03 | B17: Rellenos
A18: 02.01.03.01 | B18: RELLENO COMPACTADO C/EQUIPO MAT/PROPIO | C18: m3 | D18: 1138.01 | E18: 15 | F18: 17070.15 | G18: =$F18*N18 -> 0 | H18: =$F18*O18 -> 8535.075 | I18: =$F18*P18 -> 8535.075 | J18: =$F18*Q18 -> 0 | K18: =$F18*R18 -> 0 | L18: =F18-SUM(G18:K18) -> 0 | O18: 0.5 | P18: 0.5 | T18: =N18*$D18 -> 0 | U18: =O18*$D18 -> 569.005 | V18: =P18*$D18 -> 569.005 | W18: =Q18*$D18 -> 0 | X18: =R18*$D18 -> 0
A19: 02.01.04 | B19: Eliminacion de Material Excedente
A20: 02.01.04.01 | B20: ACARREO INTERNO, MATERIAL PROCEDENTE DE EXCAVACIONES | C20: m3 | D20: 1118.06 | E20: 18.27 | F20: 20426.96 | G20: =$F20*N20 -> 6128.088 | H20: =$F20*O20 -> 10213.48 | I20: =$F20*P20 -> 4085.392 | J20: =$F20*Q20 -> 0 | K20: =$F20*R20 -> 0 | L20: =F20-SUM(G20:K20) -> 0 | N20: 0.3 | O20: 0.5 | P20: 0.2 | T20: =N20*$D20 -> 335.418 | U20: =O20*$D20 -> 559.03 | V20: =P20*$D20 -> 223.612 | W20: =Q20*$D20 -> 0 | X20: =R20*$D20 -> 0
A21: 02.01.04.02 | B21: ELIMINACION MATERIAL EXCEDENTE ACARREADO | C21: M3 | G21: =$F21*N21 -> 0 | H21: =$F21*O21 -> 0 | I21: =$F21*P21 -> 0 | J21: =$F21*Q21 -> 0 | K21: =$F21*R21 -> 0 | L21: =F21-SUM(G21:K21) -> 0 | N21: 0.3 | O21: 0.3 | P21: 0.4 | T21: =N21*$D21 -> 0 | U21: =O21*$D21 -> 0 | V21: =P21*$D21 -> 0 | W21: =Q21*$D21 -> 0 | X21: =R21*$D21 -> 0
A22: 02.01.04.03 | B22: ELIMINACION MATERIAL EXCEDENTE C/MAQUINA | C22: m3 | G22: =$F22*N22 -> 0 | H22: =$F22*O22 -> 0 | I22: =$F22*P22 -> 0 | J22: =$F22*Q22 -> 0 | K22: =$F22*R22 -> 0 | L22: =F22-SUM(G22:K22) -> 0 | N22: 0.3 | O22: 0.3 | P22: 0.4 | T22: =N22*$D22 -> 0 | U22: =O22*$D22 -> 0 | V22: =P22*$D22 -> 0 | W22: =Q22*$D22 -> 0 | X22: =R22*$D22 -> 0
A23: 02.01.05 | B23: Nivelacion Interior y Apisonado
A24: 02.01.05.01 | B24: ESCARIFICADO Y COMPACTACION CON PLANCHA COMPACTADORA e = 30 cm | C24: m2 | D24: 70.33 | E24: 4.36 | F24: 306.64 | G24: =$F24*N24 -> 61.328 | H24: =$F24*O24 -> 122.656 | I24: =$F24*P24 -> 122.656 | J24: =$F24*Q24 -> 0 | K24: =$F24*R24 -> 0 | L24: =F24-SUM(G24:K24) -> 0 | N24: 0.2 | O24: 0.4 | P24: 0.4 | T24: =N24*$D24 -> 14.066 | U24: =O24*$D24 -> 28.132 | V24: =P24*$D24 -> 28.132 | W24: =Q24*$D24 -> 0 | X24: =R24*$D24 -> 0
A25: 02.01.05.02 | B25: ESCARIFICADO Y COMPACTACION CON PLANCHA COMPACTADORA H=0.60m (02 CAPAS 30cm c/u) | C25: m2 | D25: 8.73 | E25: 7.37 | F25: 64.34 | G25: =$F25*N25 -> 12.868 | H25: =$F25*O25 -> 25.736 | I25: =$F25*P25 -> 25.736 | J25: =$F25*Q25 -> 0 | K25: =$F25*R25 -> 0 | L25: =F25-SUM(G25:K25) -> 0 | N25: 0.2 | O25: 0.4 | P25: 0.4 | T25: =N25*$D25 -> 1.746 | U25: =O25*$D25 -> 3.492 | V25: =P25*$D25 -> 3.492 | W25: =Q25*$D25 -> 0 | X25: =R25*$D25 -> 0
A26: 02.01.05.05 | B26: AFIRMADO DE 8" PARA PISOS,PATIOS Y VEREDAS,COMPACTADO. | C26: m2 | D26: 70.33 | E26: 11.5 | F26: 808.8 | G26: =$F26*N26 -> 161.76 | H26: =$F26*O26 -> 323.52 | I26: =$F26*P26 -> 323.52 | J26: =$F26*Q26 -> 0 | K26: =$F26*R26 -> 0 | L26: =F26-SUM(G26:K26) -> 0 | N26: 0.2 | O26: 0.4 | P26: 0.4 | T26: =N26*$D26 -> 14.066 | U26: =O26*$D26 -> 28.132 | V26: =P26*$D26 -> 28.132 | W26: =Q26*$D26 -> 0 | X26: =R26*$D26 -> 0
A27: 02.01.05.06 | B27: AFIRMADO DE 12" EN PISOS INTERIOR/EXTERIOR,COMPACTADO. | C27: m2 | D27: 8.73 | E27: 14.5 | F27: 126.59 | G27: =$F27*N27 -> 25.318 | H27: =$F27*O27 -> 50.636 | I27: =$F27*P27 -> 50.636 | J27: =$F27*Q27 -> 0 | K27: =$F27*R27 -> 0 | L27: =F27-SUM(G27:K27) -> 0 | N27: 0.2 | O27: 0.4 | P27: 0.4 | T27: =N27*$D27 -> 1.746 | U27: =O27*$D27 -> 3.492 | V27: =P27*$D27 -> 3.492 | W27: =Q27*$D27 -> 0 | X27: =R27*$D27 -> 0
A28: 02.02 | B28: Obras de Concreto Simple
A29: 02.02.01 | B29: Falsos Cimientos
A30: 02.02.01.01 | B30: SUBCIMIENTO, SUBZAPATA MEZCLA 1:12 + 30 % P.G. | C30: m3 | D30: 330.16 | E30: 184.1 | F30: 60782.46 | G30: =$F30*N30 -> 0 | H30: =$F30*O30 -> 30391.23 | I30: =$F30*P30 -> 30391.23 | J30: =$F30*Q30 -> 0 | K30: =$F30*R30 -> 0 | L30: =F30-SUM(G30:K30) -> 0 | O30: 0.5 | P30: 0.5 | T30: =N30*$D30 -> 0 | U30: =O30*$D30 -> 165.08 | V30: =P30*$D30 -> 165.08 | W30: =Q30*$D30 -> 0 | X30: =R30*$D30 -> 0
A31: 02.02.02 | B31: Cimientos
A32: 02.02.02.02 | B32: CIMIENTOS CORRIDOS 1:10 + 30 % P.G. f'c >=100Kg/cm2 | C32: m3 | D32: 24.24 | E32: 182.46 | F32: 4422.83 | G32: =$F32*N32 -> 0 | H32: =$F32*O32 -> 0 | I32: =$F32*P32 -> 2211.415 | J32: =$F32*Q32 -> 2211.415 | K32: =$F32*R32 -> 0 | L32: =F32-SUM(G32:K32) -> 0 | P32: 0.5 | Q32: 0.5 | T32: =N32*$D32 -> 0 | U32: =O32*$D32 -> 0 | V32: =P32*$D32 -> 12.12 | W32: =Q32*$D32 -> 12.12 | X32: =R32*$D32 -> 0
A33: 02.02.02.03 | B33: CIMIENTO CORRIDO - ENCOFRADO Y DESENCOFRADO | C33: m2 | D33: 22.63 | E33: 23.83 | F33: 539.27 | G33: =$F33*N33 -> 0 | H33: =$F33*O33 -> 215.708 | I33: =$F33*P33 -> 215.708 | J33: =$F33*Q33 -> 107.854 | K33: =$F33*R33 -> 0 | L33: =F33-SUM(G33:K33) -> 0 | O33: 0.4 | P33: 0.4 | Q33: 0.2 | T33: =N33*$D33 -> 0 | U33: =O33*$D33 -> 9.052 | V33: =P33*$D33 -> 9.052 | W33: =Q33*$D33 -> 4.526 | X33: =R33*$D33 -> 0
A34: 02.02.02.04 | B34: CALZADURA: CONCRETO C:H 1:10 + 30 % P.G. | C34: m3 | D34: 160.54 | E34: 207.85 | F34: 33368.24 | G34: =$F34*N34 -> 33368.24 | H34: =$F34*O34 -> 0 | I34: =$F34*P34 -> 0 | J34: =$F34*Q34 -> 0 | K34: =$F34*R34 -> 0 | L34: =F34-SUM(G34:K34) -> 0 | N34: 1 | T34: =N34*$D34 -> 160.54 | U34: =O34*$D34 -> 0 | V34: =P34*$D34 -> 0 | W34: =Q34*$D34 -> 0 | X34: =R34*$D34 -> 0
A35: 02.02.02.05 | B35: CALZADURA: ENCOFRADO Y DESENCOFRADO | C35: m2 | D35: 321.08 | E35: 26.53 | F35: 8518.25 | G35: =$F35*N35 -> 8518.25 | H35: =$F35*O35 -> 0 | I35: =$F35*P35 -> 0 | J35: =$F35*Q35 -> 0 | K35: =$F35*R35 -> 0 | L35: =F35-SUM(G35:K35) -> 0 | N35: 1 | T35: =N35*$D35 -> 321.08 | U35: =O35*$D35 -> 0 | V35: =P35*$D35 -> 0 | W35: =Q35*$D35 -> 0 | X35: =R35*$D35 -> 0
A36: 02.02.03 | B36: Sobrecimientos
A37: 02.02.03.01 | B37: SOBRECIMIENTO, CONCRETO 1:8 + 25% P.M. f'c >=100Kg/cm2 | C37: m3 | D37: 3.15 | E37: 201.22 | F37: 633.84 | G37: =$F37*N37 -> 0 | H37: =$F37*O37 -> 0 | I37: =$F37*P37 -> 316.92 | J37: =$F37*Q37 -> 316.92 | K37: =$F37*R37 -> 0 | L37: =F37-SUM(G37:K37) -> 0 | P37: 0.5 | Q37: 0.5 | T37: =N37*$D37 -> 0 | U37: =O37*$D37 -> 0 | V37: =P37*$D37 -> 1.575 | W37: =Q37*$D37 -> 1.575 | X37: =R37*$D37 -> 0
A38: 02.02.03.02 | B38: SOBRECIMIENTO, ENCOFRADO Y DESENCOFRADO | C38: m2 | D38: 43.07 | E38: 24.18 | F38: 1041.43 | G38: =$F38*N38 -> 0 | H38: =$F38*O38 -> 416.572 | I38: =$F38*P38 -> 416.572 | J38: =$F38*Q38 -> 208.286 | K38: =$F38*R38 -> 0 | L38: =F38-SUM(G38:K38) -> 0 | O38: 0.4 | P38: 0.4 | Q38: 0.2 | T38: =N38*$D38 -> 0 | U38: =O38*$D38 -> 17.228 | V38: =P38*$D38 -> 17.228 | W38: =Q38*$D38 -> 8.614 | X38: =R38*$D38 -> 0
A39: 02.03 | B39: Obras de Concreto Armado
A40: 02.03.02 | B40: Zapatas
A41: 02.03.02.01 | B41: ZAPATAS.- CONCRETO 210 kg/cm2 | C41: m3 | D41: 412.62 | E41: 286.6 | F41: 118256.89 | G41: =$F41*N41 -> 35477.067 | H41: =$F41*O41 -> 82779.823 | I41: =$F41*P41 -> 0 | J41: =$F41*Q41 -> 0 | K41: =$F41*R41 -> 0 | L41: =F41-SUM(G41:K41) -> 0 | N41: 0.3 | O41: 0.7 | T41: =N41*$D41 -> 123.786 | U41: =O41*$D41 -> 288.834 | V41: =P41*$D41 -> 0 | W41: =Q41*$D41 -> 0 | X41: =R41*$D41 -> 0
A42: 02.03.02.03 | B42: ZAPATAS.- ACERO Fy=4200 kg/cm2 | C42: KG | D42: 17359.56 | E42: 3.4 | F42: 59022.5 | G42: =$F42*N42 -> 17706.75 | H42: =$F42*O42 -> 41315.75 | I42: =$F42*P42 -> 0 | J42: =$F42*Q42 -> 0 | K42: =$F42*R42 -> 0 | L42: =F42-SUM(G42:K42) -> 0 | N42: 0.3 | O42: 0.7 | T42: =N42*$D42 -> 5207.868 | U42: =O42*$D42 -> 12151.692 | V42: =P42*$D42 -> 0 | W42: =Q42*$D42 -> 0 | X42: =R42*$D42 -> 0
A43: 02.03.05 | B43: Placas y Muros de Contención
A44: 02.03.05.02 | B44: PLACAS, CONCRETO F'c=210 kg/cm2 - 1 piso | C44: m3 | D44: 6.62 | E44: 290.45 | F44: 1922.78 | G44: =$F44*N44 -> 0 | H44: =$F44*O44 -> 576.834 | I44: =$F44*P44 -> 576.834 | J44: =$F44*Q44 -> 769.112 | K44: =$F44*R44 -> 0 | L44: =F44-SUM(G44:K44) -> 0 | O44: 0.3 | P44: 0.3 | Q44: 0.4 | T44: =N44*$D44 -> 0 | U44: =O44*$D44 -> 1.986 | V44: =P44*$D44 -> 1.986 | W44: =Q44*$D44 -> 2.648 | X44: =R44*$D44 -> 0
A45: 02.03.05.04 | B45: PLACAS, ENCOFRADO Y DESENCOFRADO | C45: m2 | D45: 73.44 | E45: 33.69 | F45: 2474.19 | G45: =$F45*N45 -> 0 | H45: =$F45*O45 -> 742.257 | I45: =$F45*P45 -> 742.257 | J45: =$F45*Q45 -> 989.676 | K45: =$F45*R45 -> 0 | L45: =F45-SUM(G45:K45) -> 0 | O45: 0.3 | P45: 0.3 | Q45: 0.4 | T45: =N45*$D45 -> 0 | U45: =O45*$D45 -> 22.032 | V45: =P45*$D45 -> 22.032 | W45: =Q45*$D45 -> 29.376 | X45: =R45*$D45 -> 0
A46: 02.03.05.05 | B46: PLACAS, ACERO Fy=4200 kg/cm2 | C46: KG | D46: 415.16 | E46: 3.4 | F46: 1411.54 | G46: =$F46*N46 -> 0 | H46: =$F46*O46 -> 423.462 | I46: =$F46*P46 -> 423.462 | J46: =$F46*Q46 -> 564.616 | K46: =$F46*R46 -> 0 | L46: =F46-SUM(G46:K46) -> 0 | O46: 0.3 | P46: 0.3 | Q46: 0.4 | T46: =N46*$D46 -> 0 | U46: =O46*$D46 -> 124.548 | V46: =P46*$D46 -> 124.548 | W46: =Q46*$D46 -> 166.064 | X46: =R46*$D46 -> 0
A47: 02.03.05.07 | B47: MUROS DE CONTENC.- CONCRETO 210 kg/cm2 | C47: m3 | D47: 253.95 | E47: 328.19 | F47: 83343.85 | G47: =$F47*N47 -> 0 | H47: =$F47*O47 -> 25003.155 | I47: =$F47*P47 -> 25003.155 | J47: =$F47*Q47 -> 33337.54 | K47: =$F47*R47 -> 0 | L47: =F47-SUM(G47:K47) -> 0 | O47: 0.3 | P47: 0.3 | Q47: 0.4 | T47: =N47*$D47 -> 0 | U47: =O47*$D47 -> 76.185 | V47: =P47*$D47 -> 76.185 | W47: =Q47*$D47 -> 101.58 | X47: =R47*$D47 -> 0
A48: 02.03.05.09 | B48: MUROS DE CONTENC.- ENCOF. Y DESENCOFRADO | C48: m2 | D48: 2075.23 | E48: 30.97 | F48: 64269.87 | G48: =$F48*N48 -> 0 | H48: =$F48*O48 -> 19280.961 | I48: =$F48*P48 -> 19280.961 | J48: =$F48*Q48 -> 25707.948 | K48: =$F48*R48 -> 0 | L48: =F48-SUM(G48:K48) -> 0 | O48: 0.3 | P48: 0.3 | Q48: 0.4 | T48: =N48*$D48 -> 0 | U48: =O48*$D48 -> 622.569 | V48: =P48*$D48 -> 622.569 | W48: =Q48*$D48 -> 830.092 | X48: =R48*$D48 -> 0
A49: 02.03.05.11 | B49: MUROS DE CONTENC.- ACERO Fy=4200 kg/cm2 | C49: kg | G49: =$F49*N49 -> 0 | H49: =$F49*O49 -> 0 | I49: =$F49*P49 -> 0 | J49: =$F49*Q49 -> 0 | K49: =$F49*R49 -> 0 | L49: =F49-SUM(G49:K49) -> 0 | O49: 0.3 | P49: 0.3 | Q49: 0.4 | T49: =N49*$D49 -> 0 | U49: =O49*$D49 -> 0 | V49: =P49*$D49 -> 0 | W49: =Q49*$D49 -> 0 | X49: =R49*$D49 -> 0
A50: 02.03.06 | B50: Columnas
A51: 02.03.06.02 | B51: COLUMNAS - CONCRETO 210 KG/CM² - 1 PISO | C51: m3 | D51: 67.96 | E51: 291.23 | F51: 19791.99 | G51: =$F51*N51 -> 0 | H51: =$F51*O51 -> 0 | I51: =$F51*P51 -> 5937.597 | J51: =$F51*Q51 -> 5937.597 | K51: =$F51*R51 -> 7916.796 | L51: =F51-SUM(G51:K51) -> 0 | P51: 0.3 | Q51: 0.3 | R51: 0.4 | T51: =N51*$D51 -> 0 | U51: =O51*$D51 -> 0 | V51: =P51*$D51 -> 20.388 | W51: =Q51*$D51 -> 20.388 | X51: =R51*$D51 -> 27.184
A52: 02.03.06.06 | B52: COLUMNAS.- ENCOFRADO Y DESENCOFRADO | C52: m2 | D52: 919.41 | E52: 37.49 | F52: 34468.68 | G52: =$F52*N52 -> 0 | H52: =$F52*O52 -> 0 | I52: =$F52*P52 -> 10340.604 | J52: =$F52*Q52 -> 10340.604 | K52: =$F52*R52 -> 13787.472 | L52: =F52-SUM(G52:K52) -> 0 | P52: 0.3 | Q52: 0.3 | R52: 0.4 | T52: =N52*$D52 -> 0 | U52: =O52*$D52 -> 0 | V52: =P52*$D52 -> 275.823 | W52: =Q52*$D52 -> 275.823 | X52: =R52*$D52 -> 367.764
A53: 02.03.06.10 | B53: COLUMNAS.- ACERO Fy=4200 kg/cm2 | C53: KG | D53: 11836.1 | E53: 3.4 | F53: 40242.74 | G53: =$F53*N53 -> 0 | H53: =$F53*O53 -> 0 | I53: =$F53*P53 -> 12072.822 | J53: =$F53*Q53 -> 12072.822 | K53: =$F53*R53 -> 16097.096 | L53: =F53-SUM(G53:K53) -> 0 | P53: 0.3 | Q53: 0.3 | R53: 0.4 | T53: =N53*$D53 -> 0 | U53: =O53*$D53 -> 0 | V53: =P53*$D53 -> 3550.83 | W53: =Q53*$D53 -> 3550.83 | X53: =R53*$D53 -> 4734.44
A54: 02.03.07 | B54: Vigas
A55: 02.03.07.02 | B55: VIGAS.- CONCRETO 210 kg/cm2 - 1 piso | C55: m3 | D55: 36.84 | E55: 294.5 | F55: 10849.38 | G55: =$F55*N55 -> 0 | H55: =$F55*O55 -> 0 | I55: =$F55*P55 -> 3254.814 | J55: =$F55*Q55 -> 3254.814 | K55: =$F55*R55 -> 4339.752 | L55: =F55-SUM(G55:K55) -> 0 | P55: 0.3 | Q55: 0.3 | R55: 0.4 | T55: =N55*$D55 -> 0 | U55: =O55*$D55 -> 0 | V55: =P55*$D55 -> 11.052 | W55: =Q55*$D55 -> 11.052 | X55: =R55*$D55 -> 14.736
A56: 02.03.07.06 | B56: VIGAS.- ENCOFRADO Y DESENCOFRADO | C56: m2 | D56: 556.13 | E56: 43.56 | F56: 24225.02 | G56: =$F56*N56 -> 0 | H56: =$F56*O56 -> 0 | I56: =$F56*P56 -> 7267.506 | J56: =$F56*Q56 -> 7267.506 | K56: =$F56*R56 -> 9690.008 | L56: =F56-SUM(G56:K56) -> 0 | P56: 0.3 | Q56: 0.3 | R56: 0.4 | T56: =N56*$D56 -> 0 | U56: =O56*$D56 -> 0 | V56: =P56*$D56 -> 166.839 | W56: =Q56*$D56 -> 166.839 | X56: =R56*$D56 -> 222.452
A57: 02.03.07.08 | B57: VIGAS.- ACERO Fy=4200 kg/cm2 | C57: KG | D57: 5247.49 | E57: 3.4 | F57: 17841.47 | G57: =$F57*N57 -> 0 | H57: =$F57*O57 -> 0 | I57: =$F57*P57 -> 5352.441 | J57: =$F57*Q57 -> 5352.441 | K57: =$F57*R57 -> 7136.588 | L57: =F57-SUM(G57:K57) -> 0 | P57: 0.3 | Q57: 0.3 | R57: 0.4 | T57: =N57*$D57 -> 0 | U57: =O57*$D57 -> 0 | V57: =P57*$D57 -> 1574.247 | W57: =Q57*$D57 -> 1574.247 | X57: =R57*$D57 -> 2098.996
A58: 02.03.08 | B58: Losas Macizas
A59: 02.03.08.01 | B59: LOSAS MACIZAS.- CONC.210 kg/cm2 - 1 PISO | C59: M3 | D59: 0.63 | E59: 325.93 | F59: 205.34 | G59: =$F59*N59 -> 0 | H59: =$F59*O59 -> 0 | I59: =$F59*P59 -> 61.602 | J59: =$F59*Q59 -> 61.602 | K59: =$F59*R59 -> 82.136 | L59: =F59-SUM(G59:K59) -> 0 | P59: 0.3 | Q59: 0.3 | R59: 0.4 | T59: =N59*$D59 -> 0 | U59: =O59*$D59 -> 0 | V59: =P59*$D59 -> 0.189 | W59: =Q59*$D59 -> 0.189 | X59: =R59*$D59 -> 0.252
A60: 02.03.08.03 | B60: LOSAS MACIZAS.- ENCOFRADO Y DESENCOFRADO | C60: m2 | D60: 6.54 | E60: 55.43 | F60: 362.51 | G60: =$F60*N60 -> 0 | H60: =$F60*O60 -> 0 | I60: =$F60*P60 -> 108.753 | J60: =$F60*Q60 -> 108.753 | K60: =$F60*R60 -> 145.004 | L60: =F60-SUM(G60:K60) -> 0 | P60: 0.3 | Q60: 0.3 | R60: 0.4 | T60: =N60*$D60 -> 0 | U60: =O60*$D60 -> 0 | V60: =P60*$D60 -> 1.962 | W60: =Q60*$D60 -> 1.962 | X60: =R60*$D60 -> 2.616
A61: 02.03.08.04 | B61: LOSAS MACIZAS.- ACERO Fy=4,200 kg/cm2 | C61: KG | D61: 73.15 | E61: 4.02 | F61: 294.06 | G61: =$F61*N61 -> 0 | H61: =$F61*O61 -> 0 | I61: =$F61*P61 -> 88.218 | J61: =$F61*Q61 -> 88.218 | K61: =$F61*R61 -> 117.624 | L61: =F61-SUM(G61:K61) -> 0 | P61: 0.3 | Q61: 0.3 | R61: 0.4 | T61: =N61*$D61 -> 0 | U61: =O61*$D61 -> 0 | V61: =P61*$D61 -> 21.945 | W61: =Q61*$D61 -> 21.945 | X61: =R61*$D61 -> 29.26
A62: 02.03.09 | B62: Losas Aligeradas
A63: 02.03.09.01 | B63: LOSA ALIGERADA - CONCRETO 210 kg/cm2 - 1 PISO | C63: m3 | D63: 2.17 | E63: 294.5 | F63: 639.07 | G63: =$F63*N63 -> 0 | H63: =$F63*O63 -> 0 | I63: =$F63*P63 -> 191.721 | J63: =$F63*Q63 -> 191.721 | K63: =$F63*R63 -> 255.628 | L63: =F63-SUM(G63:K63) -> 0 | P63: 0.3 | Q63: 0.3 | R63: 0.4 | T63: =N63*$D63 -> 0 | U63: =O63*$D63 -> 0 | V63: =P63*$D63 -> 0.651 | W63: =Q63*$D63 -> 0.651 | X63: =R63*$D63 -> 0.868
A64: 02.03.09.03 | B64: LOSA ALIGERADA.- ENCOFRADO Y DESENCOFRADO | C64: m2 | D64: 25.21 | E64: 25.75 | F64: 649.16 | G64: =$F64*N64 -> 0 | H64: =$F64*O64 -> 0 | I64: =$F64*P64 -> 194.748 | J64: =$F64*Q64 -> 194.748 | K64: =$F64*R64 -> 259.664 | L64: =F64-SUM(G64:K64) -> 0 | P64: 0.3 | Q64: 0.3 | R64: 0.4 | T64: =N64*$D64 -> 0 | U64: =O64*$D64 -> 0 | V64: =P64*$D64 -> 7.563 | W64: =Q64*$D64 -> 7.563 | X64: =R64*$D64 -> 10.084
A65: 02.03.09.04 | B65: LOSA ALIGERADA.- ACERO Fy=4,200 kg/cm2 | C65: KG | D65: 95.81 | E65: 3.4 | F65: 325.75 | G65: =$F65*N65 -> 0 | H65: =$F65*O65 -> 0 | I65: =$F65*P65 -> 97.725 | J65: =$F65*Q65 -> 97.725 | K65: =$F65*R65 -> 130.3 | L65: =F65-SUM(G65:K65) -> 0 | P65: 0.3 | Q65: 0.3 | R65: 0.4 | T65: =N65*$D65 -> 0 | U65: =O65*$D65 -> 0 | V65: =P65*$D65 -> 28.743 | W65: =Q65*$D65 -> 28.743 | X65: =R65*$D65 -> 38.324
A66: 02.03.09.05 | B66: LOSA ALIGERADA.- LADR. HUECO 15x30x30 | C66: und | D66: 210.04 | E66: 2.39 | F66: 502 | G66: =$F66*N66 -> 0 | H66: =$F66*O66 -> 0 | I66: =$F66*P66 -> 150.6 | J66: =$F66*Q66 -> 150.6 | K66: =$F66*R66 -> 200.8 | L66: =F66-SUM(G66:K66) -> 0 | P66: 0.3 | Q66: 0.3 | R66: 0.4 | T66: =N66*$D66 -> 0 | U66: =O66*$D66 -> 0 | V66: =P66*$D66 -> 63.012 | W66: =Q66*$D66 -> 63.012 | X66: =R66*$D66 -> 84.016
A67: 02.03.15 | B67: Gradas Armadas en Pisos
A68: 02.03.15.01 | B68: GRADAS EN PISO, CONCRETO F'c=175 kg/cm2. | C68: m2 | D68: 12.56 | E68: 59.8 | F68: 751.09 | G68: =$F68*N68 -> 0 | H68: =$F68*O68 -> 0 | I68: =$F68*P68 -> 225.327 | J68: =$F68*Q68 -> 225.327 | K68: =$F68*R68 -> 300.436 | L68: =F68-SUM(G68:K68) -> 0 | P68: 0.3 | Q68: 0.3 | R68: 0.4 | T68: =N68*$D68 -> 0 | U68: =O68*$D68 -> 0 | V68: =P68*$D68 -> 3.768 | W68: =Q68*$D68 -> 3.768 | X68: =R68*$D68 -> 5.024
A69: 02.03.15.03 | B69: GRADAS, ENCOFRADO Y DESENCOFRADO | C69: m2 | D69: 7.1 | E69: 27.36 | F69: 194.26 | G69: =$F69*N69 -> 0 | H69: =$F69*O69 -> 0 | I69: =$F69*P69 -> 58.278 | J69: =$F69*Q69 -> 58.278 | K69: =$F69*R69 -> 77.704 | L69: =F69-SUM(G69:K69) -> 0 | P69: 0.3 | Q69: 0.3 | R69: 0.4 | T69: =N69*$D69 -> 0 | U69: =O69*$D69 -> 0 | V69: =P69*$D69 -> 2.13 | W69: =Q69*$D69 -> 2.13 | X69: =R69*$D69 -> 2.84
A70: 02.03.15.04 | B70: GRADAS EN PISO, ACERO fy=4200kg/cm2 | C70: kg | D70: 84.67 | E70: 3.4 | F70: 287.88 | G70: =$F70*N70 -> 0 | H70: =$F70*O70 -> 0 | I70: =$F70*P70 -> 86.364 | J70: =$F70*Q70 -> 86.364 | K70: =$F70*R70 -> 115.152 | L70: =F70-SUM(G70:K70) -> 0 | P70: 0.3 | Q70: 0.3 | R70: 0.4 | T70: =N70*$D70 -> 0 | U70: =O70*$D70 -> 0 | V70: =P70*$D70 -> 25.401 | W70: =Q70*$D70 -> 25.401 | X70: =R70*$D70 -> 33.868
B71: COSTO DIRECTO | F71: =SUM(F7:F70) -> 696708.05 | G71: =SUM(G7:G70) -> 134279.5 | H71: =SUM(H7:H70) -> 253236.68 | I71: =SUM(I7:I70) -> 138523.93 | J71: =SUM(J7:J70) -> 110015.77 | K71: =SUM(K7:K70) -> 60652.16
B72: GASTOS GENERALES (10%) | F72: =F71*0.15 -> 104506.21 | G72: =G71*0.15 -> 20141.925 | H72: =H71*0.15 -> 37985.503 | I72: =I71*0.15 -> 20778.59 | J72: =J71*0.15 -> 16502.366 | K72: =K71*0.15 -> 9097.824
B73: UTILIDAD (5%) | F73: =F71*0.05 -> 34835.402 | G73: =G71*0.05 -> 6713.975 | H73: =H71*0.05 -> 12661.834 | I73: =I71*0.05 -> 6926.1967 | J73: =J71*0.05 -> 5500.7886 | K73: =K71*0.05 -> 3032.608
B74: SUBTOTAL | F74: =SUM(F71:F73) -> 836049.66 | G74: =SUM(G71:G73) -> 161135.4 | H74: =SUM(H71:H73) -> 303884.02 | I74: =SUM(I71:I73) -> 166228.72 | J74: =SUM(J71:J73) -> 132018.93 | K74: =SUM(K71:K73) -> 72782.592
B75: IGV (18.00%) | F75: =ROUND(F74*0.18,2) -> 150488.94 | G75: =ROUND(G74*0.18,2) -> 29004.37 | H75: =ROUND(H74*0.18,2) -> 54699.12 | I75: =ROUND(I74*0.18,2) -> 29921.17 | J75: =ROUND(J74*0.18,2) -> 23763.41 | K75: =ROUND(K74*0.18,2) -> 13100.87
B76: COSTO TOTAL (INC. IGV) | F76: =SUM(F74:F75) -> 986538.6 | G76: =SUM(G74:G75) -> 190139.77 | H76: =SUM(H74:H75) -> 358583.14 | I76: =SUM(I74:I75) -> 196149.89 | J76: =SUM(J74:J75) -> 155782.34 | K76: =SUM(K74:K75) -> 85883.462

Sheet CRONOG INTERNO VENTA
A1: CRONOGRAMA VALORIZADO DE OBRA - PROGRAMACION VENTA
A3: PROYECTO: | B3: I.E. N° 1182 "EL BOSQUE" - CERCO + INGRESOS Y CASETAS | T3: METRADOS
T4: =+T10+T11 -> 673.005 | U4: =+U10+U11 -> 673.005 | V4: =+V10+V11 -> 224.335
A5: ITEM | B5: DESCRIPCION | C5: UND | D5: CONTRACTUAL | G5: PROGRAMACION
D6: METRADO | E6: P.U. (S/.) | F6: PARCIAL (S/.) | G6: 45474 | H6: 45505 | I6: 45536 | J6: 45566 | K6: 45597 | N6: 45597 | O6: 45627 | P6: 45658 | Q6: 45689 | R6: 45717 | T6: 45597 | U6: 45627 | V6: 45658 | W6: 45689 | X6: 45717
A7: 01 | B7: OBRAS PROVISIONALES, TRABAJOS PRELIMINARES, SEGURIDAD Y SALUD
A8: 01.02 | B8: Trabajos Preliminares
A9: 01.02.04 | B9: Trazo, Niveles y Replanteo
A10: 01.02.04.01 | B10: TRAZO Y REPLANTEO PRELIMINAR | C10: m2 | D10: 897.34 | E10: 2.04 | F10: 1830.57 | G10: =$F10*N10 -> 915.285 | H10: =$F10*O10 -> 915.285 | I10: =$F10*P10 -> 0 | J10: =$F10*Q10 -> 0 | K10: =$F10*R10 -> 0 | L10: =F10-SUM(G10:K10) -> 0 | N10: 0.5 | O10: 0.5 | T10: =+$D10*N10 -> 448.67 | U10: =+$D10*O10 -> 448.67 | V10: =+$D10*P10 -> 0 | W10: =+$D10*Q10 -> 0 | X10: =+$D10*R10 -> 0
A11: 01.02.04.02 | B11: TRAZO Y REPLANTEO DURANTE EL PROCESO | C11: m2 | D11: 897.34 | E11: 2.04 | F11: 1830.57 | G11: =$F11*N11 -> 457.6425 | H11: =$F11*O11 -> 457.6425 | I11: =$F11*P11 -> 457.6425 | J11: =$F11*Q11 -> 457.6425 | K11: =$F11*R11 -> 0 | L11: =F11-SUM(G11:K11) -> 0 | N11: 0.25 | O11: 0.25 | P11: 0.25 | Q11: 0.25 | T11: =+$D11*N11 -> 224.335 | U11: =+$D11*O11 -> 224.335 | V11: =+$D11*P11 -> 224.335 | W11: =+$D11*Q11 -> 224.335 | X11: =+$D11*R11 -> 0
A12: 02 | B12: ESTRUCTURAS
A13: 02.01 | B13: Movimiento de Tierras
A14: 02.01.01 | B14: Excavaciones
A15: 02.01.01.01 | B15: EXCAV.ZANJAS Y ZAPATA RT>2kg/cm2 H=1.5m | C15: m3 | D15: 41.9 | E15: 46.74 | F15: 1958.41 | G15: =$F15*N15 -> 1370.887 | H15: =$F15*O15 -> 587.523 | I15: =$F15*P15 -> 0 | J15: =$F15*Q15 -> 0 | K15: =$F15*R15 -> 0 | L15: =F15-SUM(G15:K15) -> 0 | N15: 0.7 | O15: 0.3 | T15: =+$D15*N15 -> 29.33 | U15: =+$D15*O15 -> 12.57 | V15: =+$D15*P15 -> 0 | W15: =+$D15*Q15 -> 0 | X15: =+$D15*R15 -> 0 | Z15: =SUM(T15:T27)/4 -> 494.7005 | AA15: =SUM(U15:U27)/4 -> 382.83775 | AB15: =SUM(V15:V27)/4 -> 210.72565 | AC15: =SUM(W15:W27)/4 -> 4.799225 | AD15: =SUM(X15:X27)/4 -> 4.654125
A16: 02.01.01.02 | B16: EXCAV.ZANJAS Y ZAPATA RT>2kg/cm2 H=2.0m | C16: m3 | D16: 1975.16 | E16: 50.99 | F16: 100713.41 | G16: =$F16*N16 -> 70499.387 | H16: =$F16*O16 -> 30214.023 | I16: =$F16*P16 -> 0 | J16: =$F16*Q16 -> 0 | K16: =$F16*R16 -> 0 | L16: =F16-SUM(G16:K16) -> 0 | N16: 0.7 | O16: 0.3 | T16: =+$D16*N16 -> 1382.612 | U16: =+$D16*O16 -> 592.548 | V16: =+$D16*P16 -> 0 | W16: =+$D16*Q16 -> 0 | X16: =+$D16*R16 -> 0
A17: 02.01.03 | B17: Rellenos
A18: 02.01.03.01 | B18: RELLENO COMPACTADO C/EQUIPO MAT/PROPIO | C18: m3 | D18: 1197.91 | E18: 26.01 | F18: 31157.64 | G18: =$F18*N18 -> 0 | H18: =$F18*O18 -> 9347.292 | I18: =$F18*P18 -> 21810.348 | J18: =$F18*Q18 -> 0 | K18: =$F18*R18 -> 0 | L18: =F18-SUM(G18:K18) -> 0 | O18: 0.3 | P18: 0.7 | T18: =+$D18*N18 -> 0 | U18: =+$D18*O18 -> 359.373 | V18: =+$D18*P18 -> 838.537 | W18: =+$D18*Q18 -> 0 | X18: =+$D18*R18 -> 0
A19: 02.01.04 | B19: Eliminacion de Material Excedente
A20: 02.01.04.01 | B20: ACARREO INTERNO, MATERIAL PROCEDENTE DE EXCAVACIONES | C20: m3 | D20: 68.91 | E20: 17.53 | F20: 1207.99 | G20: =$F20*N20 -> 603.995 | H20: =$F20*O20 -> 603.995 | I20: =$F20*P20 -> 0 | J20: =$F20*Q20 -> 0 | K20: =$F20*R20 -> 0 | L20: =F20-SUM(G20:K20) -> 0 | N20: 0.5 | O20: 0.5 | T20: =+$D20*N20 -> 34.455 | U20: =+$D20*O20 -> 34.455 | V20: =+$D20*P20 -> 0 | W20: =+$D20*Q20 -> 0 | X20: =+$D20*R20 -> 0
A21: 02.01.04.02 | B21: ELIMINACION MATERIAL EXCEDENTE ACARREADO | C21: M3 | D21: 68.91 | E21: 16.02 | F21: 1103.94 | G21: =$F21*N21 -> 551.97 | H21: =$F21*O21 -> 551.97 | I21: =$F21*P21 -> 0 | J21: =$F21*Q21 -> 0 | K21: =$F21*R21 -> 0 | L21: =F21-SUM(G21:K21) -> 0 | N21: 0.5 | O21: 0.5 | T21: =+$D21*N21 -> 34.455 | U21: =+$D21*O21 -> 34.455 | V21: =+$D21*P21 -> 0 | W21: =+$D21*Q21 -> 0 | X21: =+$D21*R21 -> 0
A22: 02.01.04.03 | B22: ELIMINACION MATERIAL EXCEDENTE C/MAQUINA | C22: m3 | D22: 995.9 | E22: 21.84 | F22: 21750.46 | G22: =$F22*N22 -> 10875.23 | H22: =$F22*O22 -> 10875.23 | I22: =$F22*P22 -> 0 | J22: =$F22*Q22 -> 0 | K22: =$F22*R22 -> 0 | L22: =F22-SUM(G22:K22) -> 0 | N22: 0.5 | O22: 0.5 | T22: =+$D22*N22 -> 497.95 | U22: =+$D22*O22 -> 497.95 | V22: =+$D22*P22 -> 0 | W22: =+$D22*Q22 -> 0 | X22: =+$D22*R22 -> 0
A23: 02.01.05 | B23: Nivelacion Interior y Apisonado
A24: 02.01.05.01 | B24: ESCARIFICADO Y COMPACTACION CON PLANCHA COMPACTADORA e = 30 cm | C24: m2 | D24: 68.95 | E24: 4.72 | F24: 325.44 | G24: =$F24*N24 -> 0 | H24: =$F24*O24 -> 0 | I24: =$F24*P24 -> 0 | J24: =$F24*Q24 -> 162.72 | K24: =$F24*R24 -> 162.72 | L24: =F24-SUM(G24:K24) -> 0 | Q24: 0.5 | R24: 0.5 | T24: =+$D24*N24 -> 0 | U24: =+$D24*O24 -> 0 | V24: =+$D24*P24 -> 0 | W24: =+$D24*Q24*0.3 -> 10.3425 | X24: =+$D24*R24*0.3 -> 10.3425
A25: 02.01.05.02 | B25: ESCARIFICADO Y COMPACTACION CON PLANCHA COMPACTADORA H=0.60m (02 CAPAS 30cm c/u) | C25: m2 | D25: 8.56 | E25: 7.85 | F25: 67.2 | G25: =$F25*N25 -> 0 | H25: =$F25*O25 -> 0 | I25: =$F25*P25 -> 40.32 | J25: =$F25*Q25 -> 26.88 | K25: =$F25*R25 -> 0 | L25: =F25-SUM(G25:K25) -> 0 | P25: 0.6 | Q25: 0.4 | T25: =+$D25*N25 -> 0 | U25: =+$D25*O25 -> 0 | V25: =+$D25*P25*0.6 -> 3.0816 | W25: =+$D25*Q25*0.6 -> 2.0544 | X25: =+$D25*R25 -> 0
A26: 02.01.05.05 | B26: AFIRMADO DE 8" PARA PISOS,PATIOS Y VEREDAS,COMPACTADO. | C26: m2 | D26: 68.95 | E26: 15.19 | F26: 1047.35 | G26: =$F26*N26 -> 0 | H26: =$F26*O26 -> 0 | I26: =$F26*P26 -> 0 | J26: =$F26*Q26 -> 418.94 | K26: =$F26*R26 -> 628.41 | L26: =F26-SUM(G26:K26) -> 0 | Q26: 0.4 | R26: 0.6 | T26: =+$D26*N26 -> 0 | U26: =+$D26*O26 -> 0 | V26: =+$D26*P26 -> 0 | W26: =+$D26*Q26*8*0.025 -> 5.516 | X26: =+$D26*R26*8*0.025 -> 8.274
A27: 02.01.05.06 | B27: AFIRMADO DE 12" EN PISOS INTERIOR/EXTERIOR,COMPACTADO. | C27: m2 | D27: 8.56 | E27: 21.79 | F27: 186.52 | G27: =$F27*N27 -> 0 | H27: =$F27*O27 -> 0 | I27: =$F27*P27 -> 93.26 | J27: =$F27*Q27 -> 93.26 | K27: =$F27*R27 -> 0 | L27: =F27-SUM(G27:K27) -> 0 | P27: 0.5 | Q27: 0.5 | T27: =+$D27*N27 -> 0 | U27: =+$D27*O27 -> 0 | V27: =+$D27*P27*12*0.025 -> 1.284 | W27: =+$D27*Q27*12*0.025 -> 1.284 | X27: =+$D27*R27 -> 0
A28: 02.02 | B28: Obras de Concreto Simple
A29: 02.02.01 | B29: Falsos Cimientos
A30: 02.02.01.01 | B30: SUBCIMIENTO, SUBZAPATA MEZCLA 1:12 + 30 % P.G. | C30: m3 | D30: 323.69 | E30: 173.72 | F30: 56231.43 | G30: =$F30*N30 -> 0 | H30: =$F30*O30 -> 39362.001 | I30: =$F30*P30 -> 16869.429 | J30: =$F30*Q30 -> 0 | K30: =$F30*R30 -> 0 | L30: =F30-SUM(G30:K30) -> 0 | O30: 0.7 | P30: 0.3 | T30: =+$D30*N30 -> 0 | U30: =+$D30*O30 -> 226.583 | V30: =+$D30*P30 -> 97.107 | W30: =+$D30*Q30 -> 0 | X30: =+$D30*R30 -> 0 | Y30: =+D30+D32+D34 -> 512.24 | Z30: =(+S30+S32+S34)/4 -> 0 | AA30: =(+T30+T32+T34)/4 -> 40.955 | AB30: =(+U30+U32+U34)/4 -> 58.5005 | AC30: =(+V30+V32+V34)/4 -> 28.6045 | AD30: =(+W30+W32+W34)/4 -> 0
A31: 02.02.02 | B31: Cimientos | Y31: =+D33+D35 -> 350.72 | Z31: =(+S33+S35)/4 -> 0 | AA31: =(+T33+T35)/4 -> 81.9075 | AB31: =(+U33+U35)/4 -> 2.309 | AC31: =(+V33+V35)/4 -> 3.4635 | AD31: =(+W33+W35)/4 -> 0
A32: 02.02.02.02 | B32: CIMIENTOS CORRIDOS 1:10 + 30 % P.G. f'c >=100Kg/cm2 | C32: m3 | D32: 24.73 | E32: 179.78 | F32: 4445.96 | G32: =$F32*N32 -> 0 | H32: =$F32*O32 -> 1333.788 | I32: =$F32*P32 -> 3112.172 | J32: =$F32*Q32 -> 0 | K32: =$F32*R32 -> 0 | L32: =F32-SUM(G32:K32) -> 0 | O32: 0.3 | P32: 0.7 | T32: =+$D32*N32 -> 0 | U32: =+$D32*O32 -> 7.419 | V32: =+$D32*P32 -> 17.311 | W32: =+$D32*Q32 -> 0 | X32: =+$D32*R32 -> 0
A33: 02.02.02.03 | B33: CIMIENTO CORRIDO - ENCOFRADO Y DESENCOFRADO | C33: m2 | D33: 23.09 | E33: 46.17 | F33: 1066.07 | G33: =$F33*N33 -> 0 | H33: =$F33*O33 -> 426.428 | I33: =$F33*P33 -> 639.642 | J33: =$F33*Q33 -> 0 | K33: =$F33*R33 -> 0 | L33: =F33-SUM(G33:K33) -> 0 | O33: 0.4 | P33: 0.6 | T33: =+$D33*N33 -> 0 | U33: =+$D33*O33 -> 9.236 | V33: =+$D33*P33 -> 13.854 | W33: =+$D33*Q33 -> 0 | X33: =+$D33*R33 -> 0
A34: 02.02.02.04 | B34: CALZADURA: CONCRETO C:H 1:10 + 30 % P.G. | C34: m3 | D34: 163.82 | E34: 179.78 | F34: 29451.56 | G34: =$F34*N34 -> 29451.56 | H34: =$F34*O34 -> 0 | I34: =$F34*P34 -> 0 | J34: =$F34*Q34 -> 0 | K34: =$F34*R34 -> 0 | L34: =F34-SUM(G34:K34) -> 0 | N34: 1 | T34: =+$D34*N34 -> 163.82 | U34: =+$D34*O34 -> 0 | V34: =+$D34*P34 -> 0 | W34: =+$D34*Q34 -> 0 | X34: =+$D34*R34 -> 0
A35: 02.02.02.05 | B35: CALZADURA: ENCOFRADO Y DESENCOFRADO | C35: m2 | D35: 327.63 | E35: 37.47 | F35: 12276.3 | G35: =$F35*N35 -> 12276.3 | H35: =$F35*O35 -> 0 | I35: =$F35*P35 -> 0 | J35: =$F35*Q35 -> 0 | K35: =$F35*R35 -> 0 | L35: =F35-SUM(G35:K35) -> 0 | N35: 1 | T35: =+$D35*N35 -> 327.63 | U35: =+$D35*O35 -> 0 | V35: =+$D35*P35 -> 0 | W35: =+$D35*Q35 -> 0 | X35: =+$D35*R35 -> 0
A36: 02.02.03 | B36: Sobrecimientos
A37: 02.02.03.01 | B37: SOBRECIMIENTO, CONCRETO 1:8 + 25% P.M. f'c >=100Kg/cm2 | C37: m3 | D37: 3.21 | E37: 260.59 | F37: 836.49 | G37: =$F37*N37 -> 0 | H37: =$F37*O37 -> 0 | I37: =$F37*P37 -> 418.245 | J37: =$F37*Q37 -> 418.245 | K37: =$F37*R37 -> 0 | L37: =F37-SUM(G37:K37) -> 0 | P37: 0.5 | Q37: 0.5 | T37: =+$D37*N37 -> 0 | U37: =+$D37*O37 -> 0 | V37: =+$D37*P37 -> 1.605 | W37: =+$D37*Q37 -> 1.605 | X37: =+$D37*R37 -> 0
A38: 02.02.03.02 | B38: SOBRECIMIENTO, ENCOFRADO Y DESENCOFRADO | C38: m2 | D38: 43.95 | E38: 37.7 | F38: 1656.92 | G38: =$F38*N38 -> 0 | H38: =$F38*O38 -> 662.768 | I38: =$F38*P38 -> 662.768 | J38: =$F38*Q38 -> 331.384 | K38: =$F38*R38 -> 0 | L38: =F38-SUM(G38:K38) -> 0 | O38: 0.4 | P38: 0.4 | Q38: 0.2 | T38: =+$D38*N38 -> 0 | U38: =+$D38*O38 -> 17.58 | V38: =+$D38*P38 -> 17.58 | W38: =+$D38*Q38 -> 8.79 | X38: =+$D38*R38 -> 0
A39: 02.03 | B39: Obras de Concreto Armado
A40: 02.03.02 | B40: Zapatas
A41: 02.03.02.01 | B41: ZAPATAS.- CONCRETO 210 kg/cm2 | C41: m3 | D41: 396.75 | E41: 292.79 | F41: 116164.43 | G41: =$F41*N41 -> 0 | H41: =$F41*O41 -> 58082.215 | I41: =$F41*P41 -> 58082.215 | J41: =$F41*Q41 -> 0 | K41: =$F41*R41 -> 0 | L41: =F41-SUM(G41:K41) -> 0 | O41: 0.5 | P41: 0.5 | T41: =+$D41*N41 -> 0 | U41: =+$D41*O41 -> 198.375 | V41: =+$D41*P41 -> 198.375 | W41: =+$D41*Q41 -> 0 | X41: =+$D41*R41 -> 0 | Z41: =(T41+T44+T47+T51+T55+T59+T63+T68)/4 -> 0 | AA41: =(U41+U44+U47+U51+U55+U59+U63+U68)/4 -> 49.59375 | AB41: =(V41+V44+V47+V51+V55+V59+V63+V68)/4 -> 89.07525 | AC41: =(W41+W44+W47+W51+W55+W59+W63+W68)/4 -> 43.994 | AD41: =(X41+X44+X47+X51+X55+X59+X63+X68)/4 -> 11.782 | AF41: =+D41+D44+D47+D51+D55+D59+D63+(D68*0.25) -> 768.5475 | AG41: =(+T41+T44+T47+T51+T55+T59+T63+(T68*0.25))/4 -> 0 | AH41: =(+U41+U44+U47+U51+U55+U59+U63+(U68*0.25))/4 -> 49.59375 | AI41: =(+V41+V44+V47+V51+V55+V59+V63+(V68*0.25))/4 -> 89.07525 | AJ41: =(+W41+W44+W47+W51+W55+W59+W63+(W68*0.25))/4 -> 42.609125 | AK41: =(+X41+X44+X47+X51+X55+X59+X63+(X68*0.25))/4 -> 10.85875
A42: 02.03.02.03 | B42: ZAPATAS.- ACERO Fy=4200 kg/cm2 | C42: KG | D42: 17534.91 | E42: 4.02 | F42: 70490.34 | G42: =$F42*N42 -> 0 | H42: =$F42*O42 -> 35245.17 | I42: =$F42*P42 -> 35245.17 | J42: =$F42*Q42 -> 0 | K42: =$F42*R42 -> 0 | L42: =F42-SUM(G42:K42) -> 0 | O42: 0.5 | P42: 0.5 | T42: =+$D42*N42 -> 0 | U42: =+$D42*O42 -> 8767.455 | V42: =+$D42*P42 -> 8767.455 | W42: =+$D42*Q42 -> 0 | X42: =+$D42*R42 -> 0 | Z42: =+(T45+T48+T52+T56+T60+T64+T69)/4 -> 0 | AA42: =+(U45+U48+U52+U56+U60+U64+U69)/4 -> 271.29625 | AB42: =+(V45+V48+V52+V56+V60+V64+V69)/4 -> 274.14 | AC42: =+(W45+W48+W52+W56+W60+W64+W69)/4 -> 368.36375 | AD42: =+(X45+X48+X52+X56+X60+X64+X69)/4 -> 0
A43: 02.03.05 | B43: Placas y Muros de Contención | Z43: =+(T42+T49+T57+T61+T65+T70)/4 -> 0 | AA43: =+(U42+U49+U57+U61+U65+U70)/4 -> 5446.0063 | AB43: =+(V42+V49+V57+V61+V65+V70)/4 -> 4389.474 | AC43: =+(W42+W49+W57+W61+W65+W70)/4 -> 545.69475 | AD43: =+(X42+X49+X57+X61+X65+X70)/4 -> 0 | AF43: =+D42+D46+D49+D53+D57+D61+D65+D70 -> 53548.07 | AG43: =(T42+T46+T49+T53+T57+T61+T65+T70)/4 -> 0 | AH43: =(U42+U46+U49+U53+U57+U61+U65+U70)/4 -> 5519.3925 | AI43: =(V42+V46+V49+V53+V57+V61+V65+V70)/4 -> 6161.5282 | AJ43: =(W42+W46+W49+W53+W57+W61+W65+W70)/4 -> 1706.0968 | AK43: =(X42+X46+X49+X53+X57+X61+X65+X70)/4 -> 0
A44: 02.03.05.02 | B44: PLACAS, CONCRETO F'c=210 kg/cm2 - 1 piso | C44: m3 | D44: 6.69 | E44: 454.82 | F44: 3042.75 | G44: =$F44*N44 -> 0 | H44: =$F44*O44 -> 0 | I44: =$F44*P44 -> 1825.65 | J44: =$F44*Q44 -> 1217.1 | K44: =$F44*R44 -> 0 | L44: =F44-SUM(G44:K44) -> 0 | P44: 0.6 | Q44: 0.4 | T44: =+$D44*N44 -> 0 | U44: =+$D44*O44 -> 0 | V44: =+$D44*P44 -> 4.014 | W44: =+$D44*Q44 -> 2.676 | X44: =+$D44*R44 -> 0
A45: 02.03.05.04 | B45: PLACAS, ENCOFRADO Y DESENCOFRADO | C45: m2 | D45: 74.18 | E45: 59.78 | F45: 4434.48 | G45: =$F45*N45 -> 0 | H45: =$F45*O45 -> 2217.24 | I45: =$F45*P45 -> 1330.344 | J45: =$F45*Q45 -> 886.896 | K45: =$F45*R45 -> 0 | L45: =F45-SUM(G45:K45) -> 0 | O45: 0.5 | P45: 0.3 | Q45: 0.2 | T45: =+$D45*N45 -> 0 | U45: =+$D45*O45 -> 37.09 | V45: =+$D45*P45 -> 22.254 | W45: =+$D45*Q45 -> 14.836 | X45: =+$D45*R45 -> 0
A46: 02.03.05.05 | B46: PLACAS, ACERO Fy=4200 kg/cm2 | C46: KG | D46: 419.35 | E46: 4.02 | F46: 1685.79 | G46: =$F46*N46 -> 0 | H46: =$F46*O46 -> 1180.053 | I46: =$F46*P46 -> 505.737 | J46: =$F46*Q46 -> 0 | K46: =$F46*R46 -> 0 | L46: =F46-SUM(G46:K46) -> 0 | O46: 0.7 | P46: 0.3 | T46: =+$D46*N46 -> 0 | U46: =+$D46*O46 -> 293.545 | V46: =+$D46*P46 -> 125.805 | W46: =+$D46*Q46 -> 0 | X46: =+$D46*R46 -> 0
A47: 02.03.05.07 | B47: MUROS DE CONTENC.- CONCRETO 210 kg/cm2 | C47: m3 | D47: 256.52 | E47: 417.41 | F47: 107074.01 | G47: =$F47*N47 -> 0 | H47: =$F47*O47 -> 0 | I47: =$F47*P47 -> 64244.406 | J47: =$F47*Q47 -> 42829.604 | K47: =$F47*R47 -> 0 | L47: =F47-SUM(G47:K47) -> 0 | P47: 0.6 | Q47: 0.4 | T47: =+$D47*N47 -> 0 | U47: =+$D47*O47 -> 0 | V47: =+$D47*P47 -> 153.912 | W47: =+$D47*Q47 -> 102.608 | X47: =+$D47*R47 -> 0
A48: 02.03.05.09 | B48: MUROS DE CONTENC.- ENCOF. Y DESENCOFRADO | C48: m2 | D48: 2096.19 | E48: 51.21 | F48: 107345.89 | G48: =$F48*N48 -> 0 | H48: =$F48*O48 -> 53672.945 | I48: =$F48*P48 -> 32203.767 | J48: =$F48*Q48 -> 21469.178 | K48: =$F48*R48 -> 0 | L48: =F48-SUM(G48:K48) -> 0 | O48: 0.5 | P48: 0.3 | Q48: 0.2 | T48: =+$D48*N48 -> 0 | U48: =+$D48*O48 -> 1048.095 | V48: =+$D48*P48 -> 628.857 | W48: =+$D48*Q48 -> 419.238 | X48: =+$D48*R48 -> 0
A49: 02.03.05.11 | B49: MUROS DE CONTENC.- ACERO Fy=4200 kg/cm2 | C49: kg | D49: 18595.1 | E49: 4.02 | F49: 74752.3 | G49: =$F49*N49 -> 0 | H49: =$F49*O49 -> 52326.61 | I49: =$F49*P49 -> 22425.69 | J49: =$F49*Q49 -> 0 | K49: =$F49*R49 -> 0 | L49: =F49-SUM(G49:K49) -> 0 | O49: 0.7 | P49: 0.3 | T49: =+$D49*N49 -> 0 | U49: =+$D49*O49 -> 13016.57 | V49: =+$D49*P49 -> 5578.53 | W49: =+$D49*Q49 -> 0 | X49: =+$D49*R49 -> 0
A50: 02.03.06 | B50: Columnas
A51: 02.03.06.02 | B51: COLUMNAS - CONCRETO 210 KG/CM² - 1 PISO | C51: m3 | D51: 66.63 | E51: 442.62 | F51: 29491.77 | G51: =$F51*N51 -> 0 | H51: =$F51*O51 -> 0 | I51: =$F51*P51 -> 0 | J51: =$F51*Q51 -> 17695.062 | K51: =$F51*R51 -> 11796.708 | L51: =F51-SUM(G51:K51) -> 0 | Q51: 0.6 | R51: 0.4 | T51: =+$D51*N51 -> 0 | U51: =+$D51*O51 -> 0 | V51: =+$D51*P51 -> 0 | W51: =+$D51*Q51 -> 39.978 | X51: =+$D51*R51 -> 26.652
A52: 02.03.06.06 | B52: COLUMNAS.- ENCOFRADO Y DESENCOFRADO | C52: m2 | D52: 901.38 | E52: 60.48 | F52: 54515.46 | G52: =$F52*N52 -> 0 | H52: =$F52*O52 -> 0 | I52: =$F52*P52 -> 16354.638 | J52: =$F52*Q52 -> 38160.822 | K52: =$F52*R52 -> 0 | L52: =F52-SUM(G52:K52) -> 0 | P52: 0.3 | Q52: 0.7 | T52: =+$D52*N52 -> 0 | U52: =+$D52*O52 -> 0 | V52: =+$D52*P52 -> 270.414 | W52: =+$D52*Q52 -> 630.966 | X52: =+$D52*R52 -> 0
A53: 02.03.06.10 | B53: COLUMNAS.- ACERO Fy=4200 kg/cm2 | C53: KG | D53: 11604.02 | E53: 4.02 | F53: 46648.16 | G53: =$F53*N53 -> 0 | H53: =$F53*O53 -> 0 | I53: =$F53*P53 -> 27988.896 | J53: =$F53*Q53 -> 18659.264 | K53: =$F53*R53 -> 0 | L53: =F53-SUM(G53:K53) -> 0 | P53: 0.6 | Q53: 0.4 | T53: =+$D53*N53 -> 0 | U53: =+$D53*O53 -> 0 | V53: =+$D53*P53 -> 6962.412 | W53: =+$D53*Q53 -> 4641.608 | X53: =+$D53*R53 -> 0
A54: 02.03.07 | B54: Vigas
A55: 02.03.07.02 | B55: VIGAS.- CONCRETO 210 kg/cm2 - 1 piso | C55: m3 | D55: 36.12 | E55: 325.93 | F55: 11772.59 | G55: =$F55*N55 -> 0 | H55: =$F55*O55 -> 0 | I55: =$F55*P55 -> 0 | J55: =$F55*Q55 -> 7063.554 | K55: =$F55*R55 -> 4709.036 | L55: =F55-SUM(G55:K55) -> 0 | Q55: 0.6 | R55: 0.4 | T55: =+$D55*N55 -> 0 | U55: =+$D55*O55 -> 0 | V55: =+$D55*P55 -> 0 | W55: =+$D55*Q55 -> 21.672 | X55: =+$D55*R55 -> 14.448
A56: 02.03.07.06 | B56: VIGAS.- ENCOFRADO Y DESENCOFRADO | C56: m2 | D56: 545.23 | E56: 70.38 | F56: 38373.29 | G56: =$F56*N56 -> 0 | H56: =$F56*O56 -> 0 | I56: =$F56*P56 -> 11511.987 | J56: =$F56*Q56 -> 26861.303 | K56: =$F56*R56 -> 0 | L56: =F56-SUM(G56:K56) -> 0 | P56: 0.3 | Q56: 0.7 | T56: =+$D56*N56 -> 0 | U56: =+$D56*O56 -> 0 | V56: =+$D56*P56 -> 163.569 | W56: =+$D56*Q56 -> 381.661 | X56: =+$D56*R56 -> 0
A57: 02.03.07.08 | B57: VIGAS.- ACERO Fy=4200 kg/cm2 | C57: KG | D57: 5144.6 | E57: 4.02 | F57: 20681.29 | G57: =$F57*N57 -> 0 | H57: =$F57*O57 -> 0 | I57: =$F57*P57 -> 12408.774 | J57: =$F57*Q57 -> 8272.516 | K57: =$F57*R57 -> 0 | L57: =F57-SUM(G57:K57) -> 0 | P57: 0.6 | Q57: 0.4 | T57: =+$D57*N57 -> 0 | U57: =+$D57*O57 -> 0 | V57: =+$D57*P57 -> 3086.76 | W57: =+$D57*Q57 -> 2057.84 | X57: =+$D57*R57 -> 0
A58: 02.03.08 | B58: Losas Macizas
A59: 02.03.08.01 | B59: LOSAS MACIZAS.- CONC.210 kg/cm2 - 1 PISO | C59: M3 | D59: 0.63 | E59: 325.93 | F59: 205.34 | G59: =$F59*N59 -> 0 | H59: =$F59*O59 -> 0 | I59: =$F59*P59 -> 0 | J59: =$F59*Q59 -> 123.204 | K59: =$F59*R59 -> 82.136 | L59: =F59-SUM(G59:K59) -> 0 | Q59: 0.6 | R59: 0.4 | T59: =+$D59*N59 -> 0 | U59: =+$D59*O59 -> 0 | V59: =+$D59*P59 -> 0 | W59: =+$D59*Q59 -> 0.378 | X59: =+$D59*R59 -> 0.252
A60: 02.03.08.03 | B60: LOSAS MACIZAS.- ENCOFRADO Y DESENCOFRADO | C60: m2 | D60: 6.54 | E60: 55.43 | F60: 362.51 | G60: =$F60*N60 -> 0 | H60: =$F60*O60 -> 0 | I60: =$F60*P60 -> 108.753 | J60: =$F60*Q60 -> 253.757 | K60: =$F60*R60 -> 0 | L60: =F60-SUM(G60:K60) -> 0 | P60: 0.3 | Q60: 0.7 | T60: =+$D60*N60 -> 0 | U60: =+$D60*O60 -> 0 | V60: =+$D60*P60 -> 1.962 | W60: =+$D60*Q60 -> 4.578 | X60: =+$D60*R60 -> 0
A61: 02.03.08.04 | B61: LOSAS MACIZAS.- ACERO Fy=4,200 kg/cm2 | C61: KG | D61: 73.15 | E61: 4.02 | F61: 294.06 | G61: =$F61*N61 -> 0 | H61: =$F61*O61 -> 0 | I61: =$F61*P61 -> 176.436 | J61: =$F61*Q61 -> 117.624 | K61: =$F61*R61 -> 0 | L61: =F61-SUM(G61:K61) -> 0 | P61: 0.6 | Q61: 0.4 | T61: =+$D61*N61 -> 0 | U61: =+$D61*O61 -> 0 | V61: =+$D61*P61 -> 43.89 | W61: =+$D61*Q61 -> 29.26 | X61: =+$D61*R61 -> 0
A62: 02.03.09 | B62: Losas Aligeradas
A63: 02.03.09.01 | B63: LOSA ALIGERADA - CONCRETO 210 kg/cm2 - 1 PISO | C63: m3 | D63: 2.13 | E63: 315.52 | F63: 672.06 | G63: =$F63*N63 -> 0 | H63: =$F63*O63 -> 0 | I63: =$F63*P63 -> 0 | J63: =$F63*Q63 -> 403.236 | K63: =$F63*R63 -> 268.824 | L63: =F63-SUM(G63:K63) -> 0 | Q63: 0.6 | R63: 0.4 | T63: =+$D63*N63 -> 0 | U63: =+$D63*O63 -> 0 | V63: =+$D63*P63 -> 0 | W63: =+$D63*Q63 -> 1.278 | X63: =+$D63*R63 -> 0.852
A64: 02.03.09.03 | B64: LOSA ALIGERADA.- ENCOFRADO Y DESENCOFRADO | C64: m2 | D64: 24.72 | E64: 43.61 | F64: 1078.04 | G64: =$F64*N64 -> 0 | H64: =$F64*O64 -> 0 | I64: =$F64*P64 -> 323.412 | J64: =$F64*Q64 -> 754.628 | K64: =$F64*R64 -> 0 | L64: =F64-SUM(G64:K64) -> 0 | P64: 0.3 | Q64: 0.7 | T64: =+$D64*N64 -> 0 | U64: =+$D64*O64 -> 0 | V64: =+$D64*P64 -> 7.416 | W64: =+$D64*Q64 -> 17.304 | X64: =+$D64*R64 -> 0
A65: 02.03.09.04 | B65: LOSA ALIGERADA.- ACERO Fy=4,200 kg/cm2 | C65: KG | D65: 93.93 | E65: 4.02 | F65: 377.6 | G65: =$F65*N65 -> 0 | H65: =$F65*O65 -> 0 | I65: =$F65*P65 -> 226.56 | J65: =$F65*Q65 -> 151.04 | K65: =$F65*R65 -> 0 | L65: =F65-SUM(G65:K65) -> 0 | P65: 0.6 | Q65: 0.4 | T65: =+$D65*N65 -> 0 | U65: =+$D65*O65 -> 0 | V65: =+$D65*P65 -> 56.358 | W65: =+$D65*Q65 -> 37.572 | X65: =+$D65*R65 -> 0
A66: 02.03.09.05 | B66: LOSA ALIGERADA.- LADR. HUECO 15x30x30 | C66: und | D66: 205.92 | E66: 2.49 | F66: 512.74 | G66: =$F66*N66 -> 0 | H66: =$F66*O66 -> 0 | I66: =$F66*P66 -> 153.822 | J66: =$F66*Q66 -> 358.918 | K66: =$F66*R66 -> 0 | L66: =F66-SUM(G66:K66) -> 0 | P66: 0.3 | Q66: 0.7 | T66: =+$D66*N66 -> 0 | U66: =+$D66*O66 -> 0 | V66: =+$D66*P66 -> 61.776 | W66: =+$D66*Q66 -> 144.144 | X66: =+$D66*R66 -> 0
A67: 02.03.15 | B67: Gradas Armadas en Pisos
A68: 02.03.15.01 | B68: GRADAS EN PISO, CONCRETO F'c=175 kg/cm2. | C68: m2 | D68: 12.31 | E68: 80.04 | F68: 985.29 | G68: =$F68*N68 -> 0 | H68: =$F68*O68 -> 0 | I68: =$F68*P68 -> 0 | J68: =$F68*Q68 -> 591.174 | K68: =$F68*R68 -> 394.116 | L68: =F68-SUM(G68:K68) -> 0 | Q68: 0.6 | R68: 0.4 | T68: =+$D68*N68 -> 0 | U68: =+$D68*O68 -> 0 | V68: =+$D68*P68 -> 0 | W68: =+$D68*Q68 -> 7.386 | X68: =+$D68*R68 -> 4.924
A69: 02.03.15.03 | B69: GRADAS, ENCOFRADO Y DESENCOFRADO | C69: m2 | D69: 6.96 | E69: 41.15 | F69: 286.4 | G69: =$F69*N69 -> 0 | H69: =$F69*O69 -> 0 | I69: =$F69*P69 -> 85.92 | J69: =$F69*Q69 -> 200.48 | K69: =$F69*R69 -> 0 | L69: =F69-SUM(G69:K69) -> 0 | P69: 0.3 | Q69: 0.7 | T69: =+$D69*N69 -> 0 | U69: =+$D69*O69 -> 0 | V69: =+$D69*P69 -> 2.088 | W69: =+$D69*Q69 -> 4.872 | X69: =+$D69*R69 -> 0
A70: 02.03.15.04 | B70: GRADAS EN PISO, ACERO fy=4200kg/cm2 | C70: kg | D70: 83.01 | E70: 4.02 | F70: 333.7 | G70: =$F70*N70 -> 0 | H70: =$F70*O70 -> 0 | I70: =$F70*P70 -> 100.11 | J70: =$F70*Q70 -> 233.59 | K70: =$F70*R70 -> 0 | L70: =F70-SUM(G70:K70) -> 0 | P70: 0.3 | Q70: 0.7 | T70: =+$D70*N70 -> 0 | U70: =+$D70*O70 -> 0 | V70: =+$D70*P70 -> 24.903 | W70: =+$D70*Q70 -> 58.107 | X70: =+$D70*R70 -> 0
B71: COSTO DIRECTO | F71: =SUM(F7:F70) -> 960724.52 | G71: =SUM(G7:G70) -> 127002.26 | H71: =SUM(H7:H70) -> 298062.18 | I71: =SUM(I7:I70) -> 329406.11 | J71: =SUM(J7:J70) -> 188212.02 | K71: =SUM(K7:K70) -> 18041.95
B72: GASTOS GENERALES (10%) | F72: =F71*0.15 -> 144108.68 | G72: =G71*0.15 -> 19050.338 | H72: =H71*0.15 -> 44709.327 | I72: =I71*0.15 -> 49410.917 | J72: =J71*0.15 -> 28231.803 | K72: =K71*0.15 -> 2706.2925
B73: UTILIDAD (5%) | F73: =F71*0.05 -> 48036.226 | G73: =G71*0.05 -> 6350.1128 | H73: =H71*0.05 -> 14903.109 | I73: =I71*0.05 -> 16470.306 | J73: =J71*0.05 -> 9410.6011 | K73: =K71*0.05 -> 902.0975
B74: SUBTOTAL | F74: =SUM(F71:F73) -> 1152869.4 | G74: =SUM(G71:G73) -> 152402.71 | H74: =SUM(H71:H73) -> 357674.61 | I74: =SUM(I71:I73) -> 395287.34 | J74: =SUM(J71:J73) -> 225854.43 | K74: =SUM(K71:K73) -> 21650.34
B75: IGV (18.00%) | F75: =ROUND(F74*0.18,2) -> 207516.5 | G75: =ROUND(G74*0.18,2) -> 27432.49 | H75: =ROUND(H74*0.18,2) -> 64381.43 | I75: =ROUND(I74*0.18,2) -> 71151.72 | J75: =ROUND(J74*0.18,2) -> 40653.8 | K75: =ROUND(K74*0.18,2) -> 3897.06
B76: COSTO TOTAL (INC. IGV) | F76: =SUM(F74:F75) -> 1360385.9 | G76: =SUM(G74:G75) -> 179835.2 | H76: =SUM(H74:H75) -> 422056.04 | I76: =SUM(I74:I75) -> 466439.06 | J76: =SUM(J74:J75) -> 266508.23 | K76: =SUM(K74:K75) -> 25547.4

Sheet CRONOG INTERNO META
A1: CRONOGRAMA VALORIZADO DE OBRA- AVANCE REAL CON COSTOS VENTA
A3: PROYECTO: | B3: I.E. N° 1182 "EL BOSQUE" - CERCO + INGRESOS Y CASETAS | G3: =+G10+G11 -> 939.855 | H3: =+H10+H11 -> 939.855 | I3: =+I10+I11 -> 313.285
N4: PORCENTAJES | T4: METRADOS
A5: ITEM | B5: DESCRIPCION | C5: UND | D5: CONTRACTUAL | G5: PROGRAMACION
D6: METRADO | E6: P.U. (S/.) | F6: PARCIAL (S/.) | G6: 45597 | H6: 45627 | I6: 45658 | J6: 45689 | K6: 45717 | N6: 45597 | O6: 45627 | P6: 45658 | Q6: 45689 | R6: 45717 | T6: 45597 | U6: 45627 | V6: 45658 | W6: 45689 | X6: 45717
A7: 01 | B7: OBRAS PROVISIONALES, TRABAJOS PRELIMINARES, SEGURIDAD Y SALUD
A8: 01.02 | B8: Trabajos Preliminares
A9: 01.02.04 | B9: Trazo, Niveles y Replanteo
A10: 01.02.04.01 | B10: TRAZO Y REPLANTEO PRELIMINAR | C10: M2 | D10: 942.21 | E10: 1.33 | F10: 1253.14 | G10: =$F10*N10 -> 626.57 | H10: =$F10*O10 -> 626.57 | I10: =$F10*P10 -> 0 | J10: =$F10*Q10 -> 0 | K10: =$F10*R10 -> 0 | L10: =F10-SUM(G10:K10) -> 0 | N10: 0.5 | O10: 0.5 | T10: =N10*$D10 -> 471.105 | U10: =O10*$D10 -> 471.105 | V10: =P10*$D10 -> 0 | W10: =Q10*$D10 -> 0 | X10: =R10*$D10 -> 0
A11: 01.02.04.02 | B11: TRAZO Y REPLANTEO DURANTE EL PROCESO | C11: m2 | D11: 942.21 | E11: 1.33 | F11: 1253.14 | G11: =$F11*N11 -> 313.285 | H11: =$F11*O11 -> 313.285 | I11: =$F11*P11 -> 313.285 | J11: =$F11*Q11 -> 313.285 | K11: =$F11*R11 -> 0 | L11: =F11-SUM(G11:K11) -> 0 | N11: 0.25 | O11: 0.25 | P11: 0.25 | Q11: 0.25 | T11: =N11*$D11 -> 235.5525 | U11: =O11*$D11 -> 235.5525 | V11: =P11*$D11 -> 235.5525 | W11: =Q11*$D11 -> 235.5525 | X11: =R11*$D11 -> 0
A12: 02 | B12: ESTRUCTURAS
A13: 02.01 | B13: Movimiento de Tierras
A14: 02.01.01 | B14: Excavaciones
A15: 02.01.01.01 | B15: EXCAV.ZANJAS Y ZAPATA RT>2kg/cm2 H=1.5m | C15: m3 | D15: 39.81 | E15: 29.22 | F15: 1163.25 | G15: =$F15*N15 -> 814.275 | H15: =$F15*O15 -> 348.975 | I15: =$F15*P15 -> 0 | J15: =$F15*Q15 -> 0 | K15: =$F15*R15 -> 0 | L15: =F15-SUM(G15:K15) -> 0 | N15: 0.7 | O15: 0.3 | T15: =N15*$D15 -> 27.867 | U15: =O15*$D15 -> 11.943 | V15: =P15*$D15 -> 0 | W15: =Q15*$D15 -> 0 | X15: =R15*$D15 -> 0
A16: 02.01.01.02 | B16: EXCAV.ZANJAS Y ZAPATA RT>2kg/cm2 H=2.0m | C16: m3 | D16: 1876.4 | E16: 33.36 | F16: 62596.7 | G16: =$F16*N16 -> 43817.69 | H16: =$F16*O16 -> 18779.01 | I16: =$F16*P16 -> 0 | J16: =$F16*Q16 -> 0 | K16: =$F16*R16 -> 0 | L16: =F16-SUM(G16:K16) -> 0 | N16: 0.7 | O16: 0.3 | T16: =N16*$D16 -> 1313.48 | U16: =O16*$D16 -> 562.92 | V16: =P16*$D16 -> 0 | W16: =Q16*$D16 -> 0 | X16: =R16*$D16 -> 0
A17: 02.01.03 | B17: Rellenos
A18: 02.01.03.01 | B18: RELLENO COMPACTADO C/EQUIPO MAT/PROPIO | C18: m3 | D18: 1138.01 | E18: 15 | F18: 17070.15 | G18: =$F18*N18 -> 0 | H18: =$F18*O18 -> 5121.045 | I18: =$F18*P18 -> 11949.105 | J18: =$F18*Q18 -> 0 | K18: =$F18*R18 -> 0 | L18: =F18-SUM(G18:K18) -> 0 | O18: 0.3 | P18: 0.7 | T18: =N18*$D18 -> 0 | U18: =O18*$D18 -> 341.403 | V18: =P18*$D18 -> 796.607 | W18: =Q18*$D18 -> 0 | X18: =R18*$D18 -> 0
A19: 02.01.04 | B19: Eliminacion de Material Excedente
A20: 02.01.04.01 | B20: ACARREO INTERNO, MATERIAL PROCEDENTE DE EXCAVACIONES | C20: m3 | D20: 1118.06 | E20: 18.27 | F20: 20426.96 | G20: =$F20*N20 -> 10213.48 | H20: =$F20*O20 -> 10213.48 | I20: =$F20*P20 -> 0 | J20: =$F20*Q20 -> 0 | K20: =$F20*R20 -> 0 | L20: =F20-SUM(G20:K20) -> 0 | N20: 0.5 | O20: 0.5 | T20: =N20*$D20 -> 559.03 | U20: =O20*$D20 -> 559.03 | V20: =P20*$D20 -> 0 | W20: =Q20*$D20 -> 0 | X20: =R20*$D20 -> 0
A21: 02.01.04.02 | B21: ELIMINACION MATERIAL EXCEDENTE ACARREADO | C21: M3 | G21: =$F21*N21 -> 0 | H21: =$F21*O21 -> 0 | I21: =$F21*P21 -> 0 | J21: =$F21*Q21 -> 0 | K21: =$F21*R21 -> 0 | L21: =F21-SUM(G21:K21) -> 0 | N21: 0.5 | O21: 0.5 | T21: =N21*$D21 -> 0 | U21: =O21*$D21 -> 0 | V21: =P21*$D21 -> 0 | W21: =Q21*$D21 -> 0 | X21: =R21*$D21 -> 0
A22: 02.01.04.03 | B22: ELIMINACION MATERIAL EXCEDENTE C/MAQUINA | C22: m3 | G22: =$F22*N22 -> 0 | H22: =$F22*O22 -> 0 | I22: =$F22*P22 -> 0 | J22: =$F22*Q22 -> 0 | K22: =$F22*R22 -> 0 | L22: =F22-SUM(G22:K22) -> 0 | N22: 0.5 | O22: 0.5 | T22: =N22*$D22 -> 0 | U22: =O22*$D22 -> 0 | V22: =P22*$D22 -> 0 | W22: =Q22*$D22 -> 0 | X22: =R22*$D22 -> 0
A23: 02.01.05 | B23: Nivelacion Interior y Apisonado
A24: 02.01.05.01 | B24: ESCARIFICADO Y COMPACTACION CON PLANCHA COMPACTADORA e = 30 cm | C24: m2 | D24: 70.33 | E24: 4.36 | F24: 306.64 | G24: =$F24*N24 -> 0 | H24: =$F24*O24 -> 0 | I24: =$F24*P24 -> 0 | J24: =$F24*Q24 -> 153.32 | K24: =$F24*R24 -> 153.32 | L24: =F24-SUM(G24:K24) -> 0 | Q24: 0.5 | R24: 0.5 | T24: =N24*$D24 -> 0 | U24: =O24*$D24 -> 0 | V24: =P24*$D24 -> 0 | W24: =Q24*$D24 -> 35.165 | X24: =R24*$D24 -> 35.165
A25: 02.01.05.02 | B25: ESCARIFICADO Y COMPACTACION CON PLANCHA COMPACTADORA H=0.60m (02 CAPAS 30cm c/u) | C25: m2 | D25: 8.73 | E25: 7.37 | F25: 64.34 | G25: =$F25*N25 -> 0 | H25: =$F25*O25 -> 0 | I25: =$F25*P25 -> 38.604 | J25: =$F25*Q25 -> 25.736 | K25: =$F25*R25 -> 0 | L25: =F25-SUM(G25:K25) -> 0 | P25: 0.6 | Q25: 0.4 | T25: =N25*$D25 -> 0 | U25: =O25*$D25 -> 0 | V25: =P25*$D25 -> 5.238 | W25: =Q25*$D25 -> 3.492 | X25: =R25*$D25 -> 0
A26: 02.01.05.05 | B26: AFIRMADO DE 8" PARA PISOS,PATIOS Y VEREDAS,COMPACTADO. | C26: m2 | D26: 70.33 | E26: 11.5 | F26: 808.8 | G26: =$F26*N26 -> 0 | H26: =$F26*O26 -> 0 | I26: =$F26*P26 -> 0 | J26: =$F26*Q26 -> 323.52 | K26: =$F26*R26 -> 485.28 | L26: =F26-SUM(G26:K26) -> 0 | Q26: 0.4 | R26: 0.6 | T26: =N26*$D26 -> 0 | U26: =O26*$D26 -> 0 | V26: =P26*$D26 -> 0 | W26: =Q26*$D26 -> 28.132 | X26: =R26*$D26 -> 42.198
A27: 02.01.05.06 | B27: AFIRMADO DE 12" EN PISOS INTERIOR/EXTERIOR,COMPACTADO. | C27: m2 | D27: 8.73 | E27: 14.5 | F27: 126.59 | G27: =$F27*N27 -> 0 | H27: =$F27*O27 -> 0 | I27: =$F27*P27 -> 63.295 | J27: =$F27*Q27 -> 63.295 | K27: =$F27*R27 -> 0 | L27: =F27-SUM(G27:K27) -> 0 | P27: 0.5 | Q27: 0.5 | T27: =N27*$D27 -> 0 | U27: =O27*$D27 -> 0 | V27: =P27*$D27 -> 4.365 | W27: =Q27*$D27 -> 4.365 | X27: =R27*$D27 -> 0
A28: 02.02 | B28: Obras de Concreto Simple
A29: 02.02.01 | B29: Falsos Cimientos
A30: 02.02.01.01 | B30: SUBCIMIENTO, SUBZAPATA MEZCLA 1:12 + 30 % P.G. | C30: m3 | D30: 330.16 | E30: 184.1 | F30: 60782.46 | G30: =$F30*N30 -> 0 | H30: =$F30*O30 -> 42547.722 | I30: =$F30*P30 -> 18234.738 | J30: =$F30*Q30 -> 0 | K30: =$F30*R30 -> 0 | L30: =F30-SUM(G30:K30) -> 0 | O30: 0.7 | P30: 0.3 | T30: =N30*$D30 -> 0 | U30: =O30*$D30 -> 231.112 | V30: =P30*$D30 -> 99.048 | W30: =Q30*$D30 -> 0 | X30: =R30*$D30 -> 0
A31: 02.02.02 | B31: Cimientos
A32: 02.02.02.02 | B32: CIMIENTOS CORRIDOS 1:10 + 30 % P.G. f'c >=100Kg/cm2 | C32: m3 | D32: 24.24 | E32: 182.46 | F32: 4422.83 | G32: =$F32*N32 -> 0 | H32: =$F32*O32 -> 1326.849 | I32: =$F32*P32 -> 3095.981 | J32: =$F32*Q32 -> 0 | K32: =$F32*R32 -> 0 | L32: =F32-SUM(G32:K32) -> 0 | O32: 0.3 | P32: 0.7 | T32: =N32*$D32 -> 0 | U32: =O32*$D32 -> 7.272 | V32: =P32*$D32 -> 16.968 | W32: =Q32*$D32 -> 0 | X32: =R32*$D32 -> 0
A33: 02.02.02.03 | B33: CIMIENTO CORRIDO - ENCOFRADO Y DESENCOFRADO | C33: m2 | D33: 22.63 | E33: 23.83 | F33: 539.27 | G33: =$F33*N33 -> 0 | H33: =$F33*O33 -> 215.708 | I33: =$F33*P33 -> 323.562 | J33: =$F33*Q33 -> 0 | K33: =$F33*R33 -> 0 | L33: =F33-SUM(G33:K33) -> 0 | O33: 0.4 | P33: 0.6 | T33: =N33*$D33 -> 0 | U33: =O33*$D33 -> 9.052 | V33: =P33*$D33 -> 13.578 | W33: =Q33*$D33 -> 0 | X33: =R33*$D33 -> 0
A34: 02.02.02.04 | B34: CALZADURA: CONCRETO C:H 1:10 + 30 % P.G. | C34: m3 | D34: 160.54 | E34: 207.85 | F34: 33368.24 | G34: =$F34*N34 -> 33368.24 | H34: =$F34*O34 -> 0 | I34: =$F34*P34 -> 0 | J34: =$F34*Q34 -> 0 | K34: =$F34*R34 -> 0 | L34: =F34-SUM(G34:K34) -> 0 | N34: 1 | T34: =N34*$D34 -> 160.54 | U34: =O34*$D34 -> 0 | V34: =P34*$D34 -> 0 | W34: =Q34*$D34 -> 0 | X34: =R34*$D34 -> 0
A35: 02.02.02.05 | B35: CALZADURA: ENCOFRADO Y DESENCOFRADO | C35: m2 | D35: 321.08 | E35: 26.53 | F35: 8518.25 | G35: =$F35*N35 -> 8518.25 | H35: =$F35*O35 -> 0 | I35: =$F35*P35 -> 0 | J35: =$F35*Q35 -> 0 | K35: =$F35*R35 -> 0 | L35: =F35-SUM(G35:K35) -> 0 | N35: 1 | T35: =N35*$D35 -> 321.08 | U35: =O35*$D35 -> 0 | V35: =P35*$D35 -> 0 | W35: =Q35*$D35 -> 0 | X35: =R35*$D35 -> 0
A36: 02.02.03 | B36: Sobrecimientos
A37: 02.02.03.01 | B37: SOBRECIMIENTO, CONCRETO 1:8 + 25% P.M. f'c >=100Kg/cm2 | C37: m3 | D37: 3.15 | E37: 201.22 | F37: 633.84 | G37: =$F37*N37 -> 0 | H37: =$F37*O37 -> 0 | I37: =$F37*P37 -> 316.92 | J37: =$F37*Q37 -> 316.92 | K37: =$F37*R37 -> 0 | L37: =F37-SUM(G37:K37) -> 0 | P37: 0.5 | Q37: 0.5 | T37: =N37*$D37 -> 0 | U37: =O37*$D37 -> 0 | V37: =P37*$D37 -> 1.575 | W37: =Q37*$D37 -> 1.575 | X37: =R37*$D37 -> 0
A38: 02.02.03.02 | B38: SOBRECIMIENTO, ENCOFRADO Y DESENCOFRADO | C38: m2 | D38: 43.07 | E38: 24.18 | F38: 1041.43 | G38: =$F38*N38 -> 0 | H38: =$F38*O38 -> 416.572 | I38: =$F38*P38 -> 416.572 | J38: =$F38*Q38 -> 208.286 | K38: =$F38*R38 -> 0 | L38: =F38-SUM(G38:K38) -> 0 | O38: 0.4 | P38: 0.4 | Q38: 0.2 | T38: =N38*$D38 -> 0 | U38: =O38*$D38 -> 17.228 | V38: =P38*$D38 -> 17.228 | W38: =Q38*$D38 -> 8.614 | X38: =R38*$D38 -> 0
A39: 02.03 | B39: Obras de Concreto Armado
A40: 02.03.02 | B40: Zapatas
A41: 02.03.02.01 | B41: ZAPATAS.- CONCRETO 210 kg/cm2 | C41: m3 | D41: 412.62 | E41: 286.6 | F41: 118256.89 | G41: =$F41*N41 -> 0 | H41: =$F41*O41 -> 59128.445 | I41: =$F41*P41 -> 59128.445 | J41: =$F41*Q41 -> 0 | K41: =$F41*R41 -> 0 | L41: =F41-SUM(G41:K41) -> 0 | O41: 0.5 | P41: 0.5 | T41: =N41*$D41 -> 0 | U41: =O41*$D41 -> 206.31 | V41: =P41*$D41 -> 206.31 | W41: =Q41*$D41 -> 0 | X41: =R41*$D41 -> 0
A42: 02.03.02.03 | B42: ZAPATAS.- ACERO Fy=4200 kg/cm2 | C42: KG | D42: 17359.56 | E42: 3.4 | F42: 59022.5 | G42: =$F42*N42 -> 0 | H42: =$F42*O42 -> 29511.25 | I42: =$F42*P42 -> 29511.25 | J42: =$F42*Q42 -> 0 | K42: =$F42*R42 -> 0 | L42: =F42-SUM(G42:K42) -> 0 | O42: 0.5 | P42: 0.5 | T42: =N42*$D42 -> 0 | U42: =O42*$D42 -> 8679.78 | V42: =P42*$D42 -> 8679.78 | W42: =Q42*$D42 -> 0 | X42: =R42*$D42 -> 0
A43: 02.03.05 | B43: Placas y Muros de Contención
A44: 02.03.05.02 | B44: PLACAS, CONCRETO F'c=210 kg/cm2 - 1 piso | C44: m3 | D44: 6.62 | E44: 290.45 | F44: 1922.78 | G44: =$F44*N44 -> 0 | H44: =$F44*O44 -> 0 | I44: =$F44*P44 -> 1153.668 | J44: =$F44*Q44 -> 769.112 | K44: =$F44*R44 -> 0 | L44: =F44-SUM(G44:K44) -> 0 | P44: 0.6 | Q44: 0.4 | T44: =N44*$D44 -> 0 | U44: =O44*$D44 -> 0 | V44: =P44*$D44 -> 3.972 | W44: =Q44*$D44 -> 2.648 | X44: =R44*$D44 -> 0
A45: 02.03.05.04 | B45: PLACAS, ENCOFRADO Y DESENCOFRADO | C45: m2 | D45: 73.44 | E45: 33.69 | F45: 2474.19 | G45: =$F45*N45 -> 0 | H45: =$F45*O45 -> 1237.095 | I45: =$F45*P45 -> 742.257 | J45: =$F45*Q45 -> 494.838 | K45: =$F45*R45 -> 0 | L45: =F45-SUM(G45:K45) -> 0 | O45: 0.5 | P45: 0.3 | Q45: 0.2 | T45: =N45*$D45 -> 0 | U45: =O45*$D45 -> 36.72 | V45: =P45*$D45 -> 22.032 | W45: =Q45*$D45 -> 14.688 | X45: =R45*$D45 -> 0
A46: 02.03.05.05 | B46: PLACAS, ACERO Fy=4200 kg/cm2 | C46: KG | D46: 415.16 | E46: 3.4 | F46: 1411.54 | G46: =$F46*N46 -> 0 | H46: =$F46*O46 -> 988.078 | I46: =$F46*P46 -> 423.462 | J46: =$F46*Q46 -> 0 | K46: =$F46*R46 -> 0 | L46: =F46-SUM(G46:K46) -> 0 | O46: 0.7 | P46: 0.3 | T46: =N46*$D46 -> 0 | U46: =O46*$D46 -> 290.612 | V46: =P46*$D46 -> 124.548 | W46: =Q46*$D46 -> 0 | X46: =R46*$D46 -> 0
A47: 02.03.05.07 | B47: MUROS DE CONTENC.- CONCRETO 210 kg/cm2 | C47: m3 | D47: 253.95 | E47: 328.19 | F47: 83343.85 | G47: =$F47*N47 -> 0 | H47: =$F47*O47 -> 0 | I47: =$F47*P47 -> 50006.31 | J47: =$F47*Q47 -> 33337.54 | K47: =$F47*R47 -> 0 | L47: =F47-SUM(G47:K47) -> 0 | P47: 0.6 | Q47: 0.4 | T47: =N47*$D47 -> 0 | U47: =O47*$D47 -> 0 | V47: =P47*$D47 -> 152.37 | W47: =Q47*$D47 -> 101.58 | X47: =R47*$D47 -> 0
A48: 02.03.05.09 | B48: MUROS DE CONTENC.- ENCOF. Y DESENCOFRADO | C48: m2 | D48: 2075.23 | E48: 30.97 | F48: 64269.87 | G48: =$F48*N48 -> 0 | H48: =$F48*O48 -> 32134.935 | I48: =$F48*P48 -> 19280.961 | J48: =$F48*Q48 -> 12853.974 | K48: =$F48*R48 -> 0 | L48: =F48-SUM(G48:K48) -> 0 | O48: 0.5 | P48: 0.3 | Q48: 0.2 | T48: =N48*$D48 -> 0 | U48: =O48*$D48 -> 1037.615 | V48: =P48*$D48 -> 622.569 | W48: =Q48*$D48 -> 415.046 | X48: =R48*$D48 -> 0
A49: 02.03.05.11 | B49: MUROS DE CONTENC.- ACERO Fy=4200 kg/cm2 | C49: kg | G49: =$F49*N49 -> 0 | H49: =$F49*O49 -> 0 | I49: =$F49*P49 -> 0 | J49: =$F49*Q49 -> 0 | K49: =$F49*R49 -> 0 | L49: =F49-SUM(G49:K49) -> 0 | O49: 0.7 | P49: 0.3 | T49: =N49*$D49 -> 0 | U49: =O49*$D49 -> 0 | V49: =P49*$D49 -> 0 | W49: =Q49*$D49 -> 0 | X49: =R49*$D49 -> 0
A50: 02.03.06 | B50: Columnas
A51: 02.03.06.02 | B51: COLUMNAS - CONCRETO 210 KG/CM² - 1 PISO | C51: m3 | D51: 67.96 | E51: 291.23 | F51: 19791.99 | G51: =$F51*N51 -> 0 | H51: =$F51*O51 -> 0 | I51: =$F51*P51 -> 0 | J51: =$F51*Q51 -> 11875.194 | K51: =$F51*R51 -> 7916.796 | L51: =F51-SUM(G51:K51) -> 0 | Q51: 0.6 | R51: 0.4 | T51: =N51*$D51 -> 0 | U51: =O51*$D51 -> 0 | V51: =P51*$D51 -> 0 | W51: =Q51*$D51 -> 40.776 | X51: =R51*$D51 -> 27.184
A52: 02.03.06.06 | B52: COLUMNAS.- ENCOFRADO Y DESENCOFRADO | C52: m2 | D52: 919.41 | E52: 37.49 | F52: 34468.68 | G52: =$F52*N52 -> 0 | H52: =$F52*O52 -> 0 | I52: =$F52*P52 -> 10340.604 | J52: =$F52*Q52 -> 24128.076 | K52: =$F52*R52 -> 0 | L52: =F52-SUM(G52:K52) -> 0 | P52: 0.3 | Q52: 0.7 | T52: =N52*$D52 -> 0 | U52: =O52*$D52 -> 0 | V52: =P52*$D52 -> 275.823 | W52: =Q52*$D52 -> 643.587 | X52: =R52*$D52 -> 0
A53: 02.03.06.10 | B53: COLUMNAS.- ACERO Fy=4200 kg/cm2 | C53: KG | D53: 11836.1 | E53: 3.4 | F53: 40242.74 | G53: =$F53*N53 -> 0 | H53: =$F53*O53 -> 0 | I53: =$F53*P53 -> 24145.644 | J53: =$F53*Q53 -> 16097.096 | K53: =$F53*R53 -> 0 | L53: =F53-SUM(G53:K53) -> 0 | P53: 0.6 | Q53: 0.4 | T53: =N53*$D53 -> 0 | U53: =O53*$D53 -> 0 | V53: =P53*$D53 -> 7101.66 | W53: =Q53*$D53 -> 4734.44 | X53: =R53*$D53 -> 0
A54: 02.03.07 | B54: Vigas
A55: 02.03.07.02 | B55: VIGAS.- CONCRETO 210 kg/cm2 - 1 piso | C55: m3 | D55: 36.84 | E55: 294.5 | F55: 10849.38 | G55: =$F55*N55 -> 0 | H55: =$F55*O55 -> 0 | I55: =$F55*P55 -> 0 | J55: =$F55*Q55 -> 6509.628 | K55: =$F55*R55 -> 4339.752 | L55: =F55-SUM(G55:K55) -> 0 | Q55: 0.6 | R55: 0.4 | T55: =N55*$D55 -> 0 | U55: =O55*$D55 -> 0 | V55: =P55*$D55 -> 0 | W55: =Q55*$D55 -> 22.104 | X55: =R55*$D55 -> 14.736
A56: 02.03.07.06 | B56: VIGAS.- ENCOFRADO Y DESENCOFRADO | C56: m2 | D56: 556.13 | E56: 43.56 | F56: 24225.02 | G56: =$F56*N56 -> 0 | H56: =$F56*O56 -> 0 | I56: =$F56*P56 -> 7267.506 | J56: =$F56*Q56 -> 16957.514 | K56: =$F56*R56 -> 0 | L56: =F56-SUM(G56:K56) -> 0 | P56: 0.3 | Q56: 0.7 | T56: =N56*$D56 -> 0 | U56: =O56*$D56 -> 0 | V56: =P56*$D56 -> 166.839 | W56: =Q56*$D56 -> 389.291 | X56: =R56*$D56 -> 0
A57: 02.03.07.08 | B57: VIGAS.- ACERO Fy=4200 kg/cm2 | C57: KG | D57: 5247.49 | E57: 3.4 | F57: 17841.47 | G57: =$F57*N57 -> 0 | H57: =$F57*O57 -> 0 | I57: =$F57*P57 -> 10704.882 | J57: =$F57*Q57 -> 7136.588 | K57: =$F57*R57 -> 0 | L57: =F57-SUM(G57:K57) -> 0 | P57: 0.6 | Q57: 0.4 | T57: =N57*$D57 -> 0 | U57: =O57*$D57 -> 0 | V57: =P57*$D57 -> 3148.494 | W57: =Q57*$D57 -> 2098.996 | X57: =R57*$D57 -> 0
A58: 02.03.08 | B58: Losas Macizas
A59: 02.03.08.01 | B59: LOSAS MACIZAS.- CONC.210 kg/cm2 - 1 PISO | C59: M3 | D59: 0.63 | E59: 325.93 | F59: 205.34 | G59: =$F59*N59 -> 0 | H59: =$F59*O59 -> 0 | I59: =$F59*P59 -> 0 | J59: =$F59*Q59 -> 123.204 | K59: =$F59*R59 -> 82.136 | L59: =F59-SUM(G59:K59) -> 0 | Q59: 0.6 | R59: 0.4 | T59: =N59*$D59 -> 0 | U59: =O59*$D59 -> 0 | V59: =P59*$D59 -> 0 | W59: =Q59*$D59 -> 0.378 | X59: =R59*$D59 -> 0.252
A60: 02.03.08.03 | B60: LOSAS MACIZAS.- ENCOFRADO Y DESENCOFRADO | C60: m2 | D60: 6.54 | E60: 55.43 | F60: 362.51 | G60: =$F60*N60 -> 0 | H60: =$F60*O60 -> 0 | I60: =$F60*P60 -> 108.753 | J60: =$F60*Q60 -> 253.757 | K60: =$F60*R60 -> 0 | L60: =F60-SUM(G60:K60) -> 0 | P60: 0.3 | Q60: 0.7 | T60: =N60*$D60 -> 0 | U60: =O60*$D60 -> 0 | V60: =P60*$D60 -> 1.962 | W60: =Q60*$D60 -> 4.578 | X60: =R60*$D60 -> 0
A61: 02.03.08.04 | B61: LOSAS MACIZAS.- ACERO Fy=4,200 kg/cm2 | C61: KG | D61: 73.15 | E61: 4.02 | F61: 294.06 | G61: =$F61*N61 -> 0 | H61: =$F61*O61 -> 0 | I61: =$F61*P61 -> 176.436 | J61: =$F61*Q61 -> 117.624 | K61: =$F61*R61 -> 0 | L61: =F61-SUM(G61:K61) -> 0 | P61: 0.6 | Q61: 0.4 | T61: =N61*$D61 -> 0 | U61: =O61*$D61 -> 0 | V61: =P61*$D61 -> 43.89 | W61: =Q61*$D61 -> 29.26 | X61: =R61*$D61 -> 0
A62: 02.03.09 | B62: Losas Aligeradas
A63: 02.03.09.01 | B63: LOSA ALIGERADA - CONCRETO 210 kg/cm2 - 1 PISO | C63: m3 | D63: 2.17 | E63: 294.5 | F63: 639.07 | G63: =$F63*N63 -> 0 | H63: =$F63*O63 -> 0 | I63: =$F63*P63 -> 0 | J63: =$F63*Q63 -> 383.442 | K63: =$F63*R63 -> 255.628 | L63: =F63-SUM(G63:K63) -> 0 | Q63: 0.6 | R63: 0.4 | T63: =N63*$D63 -> 0 | U63: =O63*$D63 -> 0 | V63: =P63*$D63 -> 0 | W63: =Q63*$D63 -> 1.302 | X63: =R63*$D63 -> 0.868
A64: 02.03.09.03 | B64: LOSA ALIGERADA.- ENCOFRADO Y DESENCOFRADO | C64: m2 | D64: 25.21 | E64: 25.75 | F64: 649.16 | G64: =$F64*N64 -> 0 | H64: =$F64*O64 -> 0 | I64: =$F64*P64 -> 194.748 | J64: =$F64*Q64 -> 454.412 | K64: =$F64*R64 -> 0 | L64: =F64-SUM(G64:K64) -> 0 | P64: 0.3 | Q64: 0.7 | T64: =N64*$D64 -> 0 | U64: =O64*$D64 -> 0 | V64: =P64*$D64 -> 7.563 | W64: =Q64*$D64 -> 17.647 | X64: =R64*$D64 -> 0
A65: 02.03.09.04 | B65: LOSA ALIGERADA.- ACERO Fy=4,200 kg/cm2 | C65: KG | D65: 95.81 | E65: 3.4 | F65: 325.75 | G65: =$F65*N65 -> 0 | H65: =$F65*O65 -> 0 | I65: =$F65*P65 -> 195.45 | J65: =$F65*Q65 -> 130.3 | K65: =$F65*R65 -> 0 | L65: =F65-SUM(G65:K65) -> 0 | P65: 0.6 | Q65: 0.4 | T65: =N65*$D65 -> 0 | U65: =O65*$D65 -> 0 | V65: =P65*$D65 -> 57.486 | W65: =Q65*$D65 -> 38.324 | X65: =R65*$D65 -> 0
A66: 02.03.09.05 | B66: LOSA ALIGERADA.- LADR. HUECO 15x30x30 | C66: und | D66: 210.04 | E66: 2.39 | F66: 502 | G66: =$F66*N66 -> 0 | H66: =$F66*O66 -> 0 | I66: =$F66*P66 -> 150.6 | J66: =$F66*Q66 -> 351.4 | K66: =$F66*R66 -> 0 | L66: =F66-SUM(G66:K66) -> 0 | P66: 0.3 | Q66: 0.7 | T66: =N66*$D66 -> 0 | U66: =O66*$D66 -> 0 | V66: =P66*$D66 -> 63.012 | W66: =Q66*$D66 -> 147.028 | X66: =R66*$D66 -> 0
A67: 02.03.15 | B67: Gradas Armadas en Pisos
A68: 02.03.15.01 | B68: GRADAS EN PISO, CONCRETO F'c=175 kg/cm2. | C68: m2 | D68: 12.56 | E68: 59.8 | F68: 751.09 | G68: =$F68*N68 -> 0 | H68: =$F68*O68 -> 0 | I68: =$F68*P68 -> 0 | J68: =$F68*Q68 -> 450.654 | K68: =$F68*R68 -> 300.436 | L68: =F68-SUM(G68:K68) -> 0 | Q68: 0.6 | R68: 0.4 | T68: =N68*$D68 -> 0 | U68: =O68*$D68 -> 0 | V68: =P68*$D68 -> 0 | W68: =Q68*$D68 -> 7.536 | X68: =R68*$D68 -> 5.024
A69: 02.03.15.03 | B69: GRADAS, ENCOFRADO Y DESENCOFRADO | C69: m2 | D69: 7.1 | E69: 27.36 | F69: 194.26 | G69: =$F69*N69 -> 0 | H69: =$F69*O69 -> 0 | I69: =$F69*P69 -> 58.278 | J69: =$F69*Q69 -> 135.982 | K69: =$F69*R69 -> 0 | L69: =F69-SUM(G69:K69) -> 0 | P69: 0.3 | Q69: 0.7 | T69: =N69*$D69 -> 0 | U69: =O69*$D69 -> 0 | V69: =P69*$D69 -> 2.13 | W69: =Q69*$D69 -> 4.97 | X69: =R69*$D69 -> 0
A70: 02.03.15.04 | B70: GRADAS EN PISO, ACERO fy=4200kg/cm2 | C70: kg | D70: 84.67 | E70: 3.4 | F70: 287.88 | G70: =$F70*N70 -> 0 | H70: =$F70*O70 -> 0 | I70: =$F70*P70 -> 86.364 | J70: =$F70*Q70 -> 201.516 | K70: =$F70*R70 -> 0 | L70: =F70-SUM(G70:K70) -> 0 | P70: 0.3 | Q70: 0.7 | T70: =N70*$D70 -> 0 | U70: =O70*$D70 -> 0 | V70: =P70*$D70 -> 25.401 | W70: =Q70*$D70 -> 59.269 | X70: =R70*$D70 -> 0
B71: COSTO DIRECTO | F71: =SUM(F7:F70) -> 696708.05 | G71: =SUM(G7:G70) -> 97671.79 | H71: =SUM(H7:H70) -> 202909.02 | I71: =SUM(I7:I70) -> 248427.68 | J71: =SUM(J7:J70) -> 134166.21 | K71: =SUM(K7:K70) -> 13533.348
B72: GASTOS GENERALES (10%) | F72: =F71*0.15 -> 104506.21 | G72: =G71*0.15 -> 14650.768 | H72: =H71*0.15 -> 30436.353 | I72: =I71*0.15 -> 37264.152 | J72: =J71*0.15 -> 20124.932 | K72: =K71*0.15 -> 2030.0022
B73: UTILIDAD (5%) | F73: =F71*0.05 -> 34835.402 | G73: =G71*0.05 -> 4883.5895 | H73: =H71*0.05 -> 10145.451 | I73: =I71*0.05 -> 12421.384 | J73: =J71*0.05 -> 6708.3107 | K73: =K71*0.05 -> 676.6674
B74: SUBTOTAL | F74: =SUM(F71:F73) -> 836049.66 | G74: =SUM(G71:G73) -> 117206.15 | H74: =SUM(H71:H73) -> 243490.82 | I74: =SUM(I71:I73) -> 298113.22 | J74: =SUM(J71:J73) -> 160999.46 | K74: =SUM(K71:K73) -> 16240.018
B75: IGV (18.00%) | F75: =ROUND(F74*0.18,2) -> 150488.94 | G75: =ROUND(G74*0.18,2) -> 21097.11 | H75: =ROUND(H74*0.18,2) -> 43828.35 | I75: =ROUND(I74*0.18,2) -> 53660.38 | J75: =ROUND(J74*0.18,2) -> 28979.9 | K75: =ROUND(K74*0.18,2) -> 2923.2
B76: COSTO TOTAL (INC. IGV) | F76: =SUM(F74:F75) -> 986538.6 | G76: =SUM(G74:G75) -> 138303.26 | H76: =SUM(H74:H75) -> 287319.17 | I76: =SUM(I74:I75) -> 351773.6 | J76: =SUM(J74:J75) -> 189979.36 | K76: =SUM(K74:K75) -> 19163.218
F78: =+F42+F46+F49+F53+F57+F61+F65+F70 -> 119425.94 | H78: =+H42+H46+H49+H53+H57+H61+H65+H70 -> 30499.328 | I78: =+I42+I46+I49+I53+I57+I61+I65+I70 -> 65243.488 | J78: =+J42+J46+J49+J53+J57+J61+J65+J70 -> 23683.124
H79: =+H78/F78 -> 0.25538278 | I79: =+I78/F78 -> 0.54630919 | J79: =+J78/F78 -> 0.19830804

Sheet CRONOG COSTOS REALES
A1: CRONOGRAMA VALORIZADO DE OBRA - AVANCE REAL CON COSTOS REALES
A3: PROYECTO: | B3: I.E. N° 1182 "EL BOSQUE" - CERCO + INGRESOS Y CASETAS | N3: PORCENTAJES | T3: AVANCE DE METRADOS
A5: ITEM | B5: DESCRIPCION | C5: UND | D5: CONTRACTUAL | G5: PROGRAMACION
D6: METRADO | E6: P.U. (S/.) | F6: PARCIAL (S/.) | G6: 45474 | H6: 45505 | I6: 45536 | J6: 45566 | K6: 45597 | N6: 45474 | O6: 45505 | P6: 45536 | Q6: 45566 | R6: 45597 | T6: 45474 | U6: 45505 | V6: 45536 | W6: 45566 | X6: 45597
A7: 01 | B7: OBRAS PROVISIONALES, TRABAJOS PRELIMINARES, SEGURIDAD Y SALUD
A8: 01.02 | B8: Trabajos Preliminares
A9: 01.02.04 | B9: Trazo, Niveles y Replanteo
A10: 01.02.04.01 | B10: TRAZO Y REPLANTEO PRELIMINAR | C10: M2 | D10: 942.21 | E10: 1.33 | F10: 1253.14 | G10: =$F10*N10 -> 626.57 | H10: =$F10*O10 -> 626.57 | I10: =$F10*P10 -> 0 | J10: =$F10*Q10 -> 0 | K10: =$F10*R10 -> 0 | L10: =F10-SUM(G10:K10) -> 0 | N10: 0.5 | O10: 0.5 | T10: =N10*$D10 -> 471.105 | U10: =O10*$D10 -> 471.105 | V10: =P10*$D10 -> 0 | W10: =Q10*$D10 -> 0 | X10: =R10*$D10 -> 0
A11: 01.02.04.02 | B11: TRAZO Y REPLANTEO DURANTE EL PROCESO | C11: m2 | D11: 942.21 | E11: 1.33 | F11: 1253.14 | G11: =$F11*N11 -> 313.285 | H11: =$F11*O11 -> 313.285 | I11: =$F11*P11 -> 313.285 | J11: =$F11*Q11 -> 313.285 | K11: =$F11*R11 -> 0 | L11: =F11-SUM(G11:K11) -> 0 | N11: 0.25 | O11: 0.25 | P11: 0.25 | Q11: 0.25 | T11: =N11*$D11 -> 235.5525 | U11: =O11*$D11 -> 235.5525 | V11: =P11*$D11 -> 235.5525 | W11: =Q11*$D11 -> 235.5525 | X11: =R11*$D11 -> 0
A12: 02 | B12: ESTRUCTURAS
A13: 02.01 | B13: Movimiento de Tierras
A14: 02.01.01 | B14: Excavaciones
A15: 02.01.01.01 | B15: EXCAV.ZANJAS Y ZAPATA RT>2kg/cm2 H=1.5m | C15: m3 | D15: 39.81 | E15: 29.22 | F15: 1163.25 | G15: =$F15*N15 -> 814.275 | H15: =$F15*O15 -> 348.975 | I15: =$F15*P15 -> 0 | J15: =$F15*Q15 -> 0 | K15: =$F15*R15 -> 0 | L15: =F15-SUM(G15:K15) -> 0 | N15: 0.7 | O15: 0.3 | T15: =N15*$D15 -> 27.867 | U15: =O15*$D15 -> 11.943 | V15: =P15*$D15 -> 0 | W15: =Q15*$D15 -> 0 | X15: =R15*$D15 -> 0
A16: 02.01.01.02 | B16: EXCAV.ZANJAS Y ZAPATA RT>2kg/cm2 H=2.0m | C16: m3 | D16: 1876.4 | E16: 33.36 | F16: 62596.7 | G16: =$F16*N16 -> 43817.69 | H16: =$F16*O16 -> 18779.01 | I16: =$F16*P16 -> 0 | J16: =$F16*Q16 -> 0 | K16: =$F16*R16 -> 0 | L16: =F16-SUM(G16:K16) -> 0 | N16: 0.7 | O16: 0.3 | T16: =N16*$D16 -> 1313.48 | U16: =O16*$D16 -> 562.92 | V16: =P16*$D16 -> 0 | W16: =Q16*$D16 -> 0 | X16: =R16*$D16 -> 0
A17: 02.01.03 | B17: Rellenos
A18: 02.01.03.01 | B18: RELLENO COMPACTADO C/EQUIPO MAT/PROPIO | C18: m3 | D18: 1138.01 | E18: 15 | F18: 17070.15 | G18: =$F18*N18 -> 0 | H18: =$F18*O18 -> 5121.045 | I18: =$F18*P18 -> 11949.105 | J18: =$F18*Q18 -> 0 | K18: =$F18*R18 -> 0 | L18: =F18-SUM(G18:K18) -> 0 | O18: 0.3 | P18: 0.7 | T18: =N18*$D18 -> 0 | U18: =O18*$D18 -> 341.403 | V18: =P18*$D18 -> 796.607 | W18: =Q18*$D18 -> 0 | X18: =R18*$D18 -> 0
A19: 02.01.04 | B19: Eliminacion de Material Excedente
A20: 02.01.04.01 | B20: ACARREO INTERNO, MATERIAL PROCEDENTE DE EXCAVACIONES | C20: m3 | D20: 1118.06 | E20: 18.27 | F20: 20426.96 | G20: =$F20*N20 -> 10213.48 | H20: =$F20*O20 -> 10213.48 | I20: =$F20*P20 -> 0 | J20: =$F20*Q20 -> 0 | K20: =$F20*R20 -> 0 | L20: =F20-SUM(G20:K20) -> 0 | N20: 0.5 | O20: 0.5 | T20: =N20*$D20 -> 559.03 | U20: =O20*$D20 -> 559.03 | V20: =P20*$D20 -> 0 | W20: =Q20*$D20 -> 0 | X20: =R20*$D20 -> 0
A21: 02.01.04.02 | B21: ELIMINACION MATERIAL EXCEDENTE ACARREADO | C21: M3 | G21: =$F21*N21 -> 0 | H21: =$F21*O21 -> 0 | I21: =$F21*P21 -> 0 | J21: =$F21*Q21 -> 0 | K21: =$F21*R21 -> 0 | L21: =F21-SUM(G21:K21) -> 0 | N21: 0.5 | O21: 0.5 | T21: =N21*$D21 -> 0 | U21: =O21*$D21 -> 0 | V21: =P21*$D21 -> 0 | W21: =Q21*$D21 -> 0 | X21: =R21*$D21 -> 0
A22: 02.01.04.03 | B22: ELIMINACION MATERIAL EXCEDENTE C/MAQUINA | C22: m3 | G22: =$F22*N22 -> 0 | H22: =$F22*O22 -> 0 | I22: =$F22*P22 -> 0 | J22: =$F22*Q22 -> 0 | K22: =$F22*R22 -> 0 | L22: =F22-SUM(G22:K22) -> 0 | N22: 0.5 | O22: 0.5 | T22: =N22*$D22 -> 0 | U22: =O22*$D22 -> 0 | V22: =P22*$D22 -> 0 | W22: =Q22*$D22 -> 0 | X22: =R22*$D22 -> 0
A23: 02.01.05 | B23: Nivelacion Interior y Apisonado
A24: 02.01.05.01 | B24: ESCARIFICADO Y COMPACTACION CON PLANCHA COMPACTADORA e = 30 cm | C24: m2 | D24: 70.33 | E24: 4.36 | F24: 306.64 | G24: =$F24*N24 -> 0 | H24: =$F24*O24 -> 0 | I24: =$F24*P24 -> 0 | J24: =$F24*Q24 -> 153.32 | K24: =$F24*R24 -> 153.32 | L24: =F24-SUM(G24:K24) -> 0 | Q24: 0.5 | R24: 0.5 | T24: =N24*$D24 -> 0 | U24: =O24*$D24 -> 0 | V24: =P24*$D24 -> 0 | W24: =Q24*$D24 -> 35.165 | X24: =R24*$D24 -> 35.165
A25: 02.01.05.02 | B25: ESCARIFICADO Y COMPACTACION CON PLANCHA COMPACTADORA H=0.60m (02 CAPAS 30cm c/u) | C25: m2 | D25: 8.73 | E25: 7.37 | F25: 64.34 | G25: =$F25*N25 -> 0 | H25: =$F25*O25 -> 0 | I25: =$F25*P25 -> 38.604 | J25: =$F25*Q25 -> 25.736 | K25: =$F25*R25 -> 0 | L25: =F25-SUM(G25:K25) -> 0 | P25: 0.6 | Q25: 0.4 | T25: =N25*$D25 -> 0 | U25: =O25*$D25 -> 0 | V25: =P25*$D25 -> 5.238 | W25: =Q25*$D25 -> 3.492 | X25: =R25*$D25 -> 0
A26: 02.01.05.05 | B26: AFIRMADO DE 8" PARA PISOS,PATIOS Y VEREDAS,COMPACTADO. | C26: m2 | D26: 70.33 | E26: 11.5 | F26: 808.8 | G26: =$F26*N26 -> 0 | H26: =$F26*O26 -> 0 | I26: =$F26*P26 -> 0 | J26: =$F26*Q26 -> 323.52 | K26: =$F26*R26 -> 485.28 | L26: =F26-SUM(G26:K26) -> 0 | Q26: 0.4 | R26: 0.6 | T26: =N26*$D26 -> 0 | U26: =O26*$D26 -> 0 | V26: =P26*$D26 -> 0 | W26: =Q26*$D26 -> 28.132 | X26: =R26*$D26 -> 42.198
A27: 02.01.05.06 | B27: AFIRMADO DE 12" EN PISOS INTERIOR/EXTERIOR,COMPACTADO. | C27: m2 | D27: 8.73 | E27: 14.5 | F27: 126.59 | G27: =$F27*N27 -> 0 | H27: =$F27*O27 -> 0 | I27: =$F27*P27 -> 63.295 | J27: =$F27*Q27 -> 63.295 | K27: =$F27*R27 -> 0 | L27: =F27-SUM(G27:K27) -> 0 | P27: 0.5 | Q27: 0.5 | T27: =N27*$D27 -> 0 | U27: =O27*$D27 -> 0 | V27: =P27*$D27 -> 4.365 | W27: =Q27*$D27 -> 4.365 | X27: =R27*$D27 -> 0
A28: 02.02 | B28: Obras de Concreto Simple
A29: 02.02.01 | B29: Falsos Cimientos
A30: 02.02.01.01 | B30: SUBCIMIENTO, SUBZAPATA MEZCLA 1:12 + 30 % P.G. | C30: m3 | D30: 330.16 | E30: 184.1 | F30: 60782.46 | G30: =$F30*N30 -> 0 | H30: =$F30*O30 -> 42547.722 | I30: =$F30*P30 -> 18234.738 | J30: =$F30*Q30 -> 0 | K30: =$F30*R30 -> 0 | L30: =F30-SUM(G30:K30) -> 0 | O30: 0.7 | P30: 0.3 | T30: =N30*$D30 -> 0 | U30: =O30*$D30 -> 231.112 | V30: =P30*$D30 -> 99.048 | W30: =Q30*$D30 -> 0 | X30: =R30*$D30 -> 0
A31: 02.02.02 | B31: Cimientos
A32: 02.02.02.02 | B32: CIMIENTOS CORRIDOS 1:10 + 30 % P.G. f'c >=100Kg/cm2 | C32: m3 | D32: 24.24 | E32: 182.46 | F32: 4422.83 | G32: =$F32*N32 -> 0 | H32: =$F32*O32 -> 1326.849 | I32: =$F32*P32 -> 3095.981 | J32: =$F32*Q32 -> 0 | K32: =$F32*R32 -> 0 | L32: =F32-SUM(G32:K32) -> 0 | O32: 0.3 | P32: 0.7 | T32: =N32*$D32 -> 0 | U32: =O32*$D32 -> 7.272 | V32: =P32*$D32 -> 16.968 | W32: =Q32*$D32 -> 0 | X32: =R32*$D32 -> 0
A33: 02.02.02.03 | B33: CIMIENTO CORRIDO - ENCOFRADO Y DESENCOFRADO | C33: m2 | D33: 22.63 | E33: 23.83 | F33: 539.27 | G33: =$F33*N33 -> 0 | H33: =$F33*O33 -> 215.708 | I33: =$F33*P33 -> 323.562 | J33: =$F33*Q33 -> 0 | K33: =$F33*R33 -> 0 | L33: =F33-SUM(G33:K33) -> 0 | O33: 0.4 | P33: 0.6 | T33: =N33*$D33 -> 0 | U33: =O33*$D33 -> 9.052 | V33: =P33*$D33 -> 13.578 | W33: =Q33*$D33 -> 0 | X33: =R33*$D33 -> 0
A34: 02.02.02.04 | B34: CALZADURA: CONCRETO C:H 1:10 + 30 % P.G. | C34: m3 | D34: 160.54 | E34: 207.85 | F34: 33368.24 | G34: =$F34*N34 -> 33368.24 | H34: =$F34*O34 -> 0 | I34: =$F34*P34 -> 0 | J34: =$F34*Q34 -> 0 | K34: =$F34*R34 -> 0 | L34: =F34-SUM(G34:K34) -> 0 | N34: 1 | T34: =N34*$D34 -> 160.54 | U34: =O34*$D34 -> 0 | V34: =P34*$D34 -> 0 | W34: =Q34*$D34 -> 0 | X34: =R34*$D34 -> 0
A35: 02.02.02.05 | B35: CALZADURA: ENCOFRADO Y DESENCOFRADO | C35: m2 | D35: 321.08 | E35: 26.53 | F35: 8518.25 | G35: =$F35*N35 -> 8518.25 | H35: =$F35*O35 -> 0 | I35: =$F35*P35 -> 0 | J35: =$F35*Q35 -> 0 | K35: =$F35*R35 -> 0 | L35: =F35-SUM(G35:K35) -> 0 | N35: 1 | T35: =N35*$D35 -> 321.08 | U35: =O35*$D35 -> 0 | V35: =P35*$D35 -> 0 | W35: =Q35*$D35 -> 0 | X35: =R35*$D35 -> 0
A36: 02.02.03 | B36: Sobrecimientos
A37: 02.02.03.01 | B37: SOBRECIMIENTO, CONCRETO 1:8 + 25% P.M. f'c >=100Kg/cm2 | C37: m3 | D37: 3.15 | E37: 201.22 | F37: 633.84 | G37: =$F37*N37 -> 0 | H37: =$F37*O37 -> 0 | I37: =$F37*P37 -> 316.92 | J37: =$F37*Q37 -> 316.92 | K37: =$F37*R37 -> 0 | L37: =F37-SUM(G37:K37) -> 0 | P37: 0.5 | Q37: 0.5 | T37: =N37*$D37 -> 0 | U37: =O37*$D37 -> 0 | V37: =P37*$D37 -> 1.575 | W37: =Q37*$D37 -> 1.575 | X37: =R37*$D37 -> 0
A38: 02.02.03.02 | B38: SOBRECIMIENTO, ENCOFRADO Y DESENCOFRADO | C38: m2 | D38: 43.07 | E38: 24.18 | F38: 1041.43 | G38: =$F38*N38 -> 0 | H38: =$F38*O38 -> 416.572 | I38: =$F38*P38 -> 416.572 | J38: =$F38*Q38 -> 208.286 | K38: =$F38*R38 -> 0 | L38: =F38-SUM(G38:K38) -> 0 | O38: 0.4 | P38: 0.4 | Q38: 0.2 | T38: =N38*$D38 -> 0 | U38: =O38*$D38 -> 17.228 | V38: =P38*$D38 -> 17.228 | W38: =Q38*$D38 -> 8.614 | X38: =R38*$D38 -> 0
A39: 02.03 | B39: Obras de Concreto Armado
A40: 02.03.02 | B40: Zapatas
A41: 02.03.02.01 | B41: ZAPATAS.- CONCRETO 210 kg/cm2 | C41: m3 | D41: 412.62 | E41: 286.6 | F41: 118256.89 | G41: =$F41*N41 -> 0 | H41: =$F41*O41 -> 59128.445 | I41: =$F41*P41 -> 59128.445 | J41: =$F41*Q41 -> 0 | K41: =$F41*R41 -> 0 | L41: =F41-SUM(G41:K41) -> 0 | O41: 0.5 | P41: 0.5 | T41: =N41*$D41 -> 0 | U41: =O41*$D41 -> 206.31 | V41: =P41*$D41 -> 206.31 | W41: =Q41*$D41 -> 0 | X41: =R41*$D41 -> 0
A42: 02.03.02.03 | B42: ZAPATAS.- ACERO Fy=4200 kg/cm2 | C42: KG | D42: 17359.56 | E42: 3.4 | F42: 59022.5 | G42: =$F42*N42 -> 0 | H42: =$F42*O42 -> 29511.25 | I42: =$F42*P42 -> 29511.25 | J42: =$F42*Q42 -> 0 | K42: =$F42*R42 -> 0 | L42: =F42-SUM(G42:K42) -> 0 | O42: 0.5 | P42: 0.5 | T42: =N42*$D42 -> 0 | U42: =O42*$D42 -> 8679.78 | V42: =P42*$D42 -> 8679.78 | W42: =Q42*$D42 -> 0 | X42: =R42*$D42 -> 0
A43: 02.03.05 | B43: Placas y Muros de Contención
A44: 02.03.05.02 | B44: PLACAS, CONCRETO F'c=210 kg/cm2 - 1 piso | C44: m3 | D44: 6.62 | E44: 290.45 | F44: 1922.78 | G44: =$F44*N44 -> 0 | H44: =$F44*O44 -> 0 | I44: =$F44*P44 -> 1153.668 | J44: =$F44*Q44 -> 769.112 | K44: =$F44*R44 -> 0 | L44: =F44-SUM(G44:K44) -> 0 | P44: 0.6 | Q44: 0.4 | T44: =N44*$D44 -> 0 | U44: =O44*$D44 -> 0 | V44: =P44*$D44 -> 3.972 | W44: =Q44*$D44 -> 2.648 | X44: =R44*$D44 -> 0
