Workbook

Sheet 1Planilla
A1: ANEXO I
A2: ESTRUCTURACION LABORAL Y PLANILLA PERSONAL
A3: 1.1: DESCRIPCION SERVICIO Y TURNOS LABORALES
A4: SERVICIO : | B4: ALQUILER DE MAQUINARIA PESADA
A5: CONTRATANTE: | B5: COMPAÑÍA MINERA ANTAMINA
A6: TURNOS LABORALES: | B6: 10 DIAS DE TRABAJO POR 10 DIAS DE DESCANSO
A7: OPERACIÓN MINA : | B7: 20 HRS LABORALES NETAS DIARIAS OPERADORES MINA
A8: ADMINISTRACION MINA | B8: 12 HORAS LABORALES DIARIAS OPERACIÓN MINA
A9: CONDICION : | B9: MAQUINARIAS OPERATIVAS Y CON OPERADOR
A10: TOTAL DE MAQUINARIAS: | B10: =+'2Maq'!B8 -> 10
A11: ADMINISTRACION HUARAZ | B11: 06 días a la semana
A13: 1.2: DESCRIPCION DEL PERSONAL LABORAL ACTIVIDAD Y PLANILLA DE SALARIO
B14: HABER ACTUAL | D14: Derechos Laborales | F14: TOTAL | G14: OBSERVACION
A15: Actividad del Personal | B15: Haber mes | C15: Total Percibido | D15: Haber mes | E15: Sub total | F15: PLANILLA
A16: ADMINISTRACION HUARAZ | B16: PERCIBIDO | C16: =+C17+C23 -> 0 | D16: DESCONTADO | E16: =SUM(E17:E27) -> 0 | G16: =+C16+E16 -> 0 | H16: SUB TOTAL
A17: 1º DIRECTIVOS | C17: =SUM(B18:B22) -> 0 | E17: =SUM(D18:D22) -> 0 | G17: =SUM(F18:F21) -> 0
A18: Directivo 1º (Tiempo Parcial) | B18: =+M18 -> 0 | D18: =+N18 -> 0 | F18: =+B18+D18 -> 0 | G18: A considerar
A19: Directivo 2º (Tiempo Parcial) | B19: =+M19 -> 0 | D19: =+N19 -> 0 | F19: =+B19+D19 -> 0 | G19: A considerar
A20: Directivo 3º (Tiempo Parcial) | B20: =+M20 -> 0 | D20: =+N20 -> 0 | F20: =+B20+D20 -> 0 | G20: A considerar
A21: Directivo 4º (Tiempo Parcial) | B21: =+M21 -> 0 | D21: =+N21 -> 0 | F21: =+B21+D21 -> 0 | G21: A considerar haber y funciones
A22: Directivo 5º (Tiempo Parcial) | B22: =+M22 -> 0 | D22: =+N22 -> 0 | F22: =+B22+D22 -> 0 | G22: A considerar haber y funciones
A23: 2º Administrativo Huaraz | C23: =SUM(B24:B27) -> 0 | E23: =SUM(D24:D27) -> 0 | G23: =SUM(F24:F27) -> 0
A24: Abogado (Tiempo Parcial) | B24: =+M24 -> 0 | D24: =+N24 -> 0 | F24: =+B24+D24 -> 0 | G24: A considerar
A25: Contador (Tiempo parcial) | B25: =+M25 -> 0 | D25: =+N25 -> 0 | F25: =+B25+D25 -> 0 | G25: A considerar
A26: Asistente Contable (Tpo completo | B26: =+M26 -> 0 | D26: =+N26 -> 0 | F26: =+B26+D26 -> 0 | G26: Considerar nueva curricula
A27: Secretaria (Tiempo completo) | B27: =+M27 -> 0 | D27: =+N27 -> 0 | F27: =+B27+D27 -> 0 | G27: Considerar nueva curricula
A28: OPERACIÓN MINA | C28: =+C29+C42+C53 -> 0 | E28: =+E29+E42+E53 -> 0 | G28: =+C28+E28 -> 0 | H28: SUB TOTAL
A29: 3º Administrativo MINA | C29: =SUM(B30:B41) -> 0 | E29: =SUM(D30:D41) -> 0 | G29: =+C29+E29 -> 0 | H29: SUB TOTAL
A30: Administrador 1º Rotación | B30: =+M30 -> 0 | D30: =+B30*'6SueAct'!$C$7 -> 0 | F30: =+B30+D30 -> 0 | G30: Considerar nueva curricula
A31: Administrador 2º Rotación | B31: =+M31 -> 0 | D31: =+B31*'6SueAct'!$C$7 -> 0 | F31: =+B31+D31 -> 0 | G31: Considerar nueva curricula
A32: Almacen 1º Rotación | B32: =+M32 -> 0 | D32: =+B32*'6SueAct'!$C$7 -> 0 | F32: =+B32+D32 -> 0 | G32: Considerar nueva curricula
A33: Almacen 2º Rotación | B33: =+M33 -> 0 | D33: =+B33*'6SueAct'!$C$7 -> 0 | F33: =+B33+D33 -> 0 | G33: Considerar nueva curricula
A34: Supervisor 1º Turno 1º Rotación | B34: =+M34 -> 0 | D34: =+B34*'6SueAct'!$C$7 -> 0 | F34: =+B34+D34 -> 0 | G34: A considerar
A35: Supervisor 2º Turno 1º Rotación | B35: =+M35 -> 0 | D35: =+B35*'6SueAct'!$C$7 -> 0 | F35: =+B35+D35 -> 0 | G35: A considerar
A36: Supervisor 1º Turno 2º Rotación | B36: =+M36 -> 0 | D36: =+B36*'6SueAct'!$C$7 -> 0 | F36: =+B36+D36 -> 0 | G36: A considerar
A37: Supervisor 2º Turno 2º Rotación | B37: =+M37 -> 0 | D37: =+B37*'6SueAct'!$C$7 -> 0 | F37: =+B37+D37 -> 0 | G37: A considerar
A38: Seguridad Jefatura 1º Rotación | B38: =+M38 -> 0 | D38: =+B38*'6SueAct'!$C$7 -> 0 | F38: =+B38+D38 -> 0 | G38: Considerar nueva curricula
A39: Seguridad Supervisor 2º Rotación | B39: =+M39 -> 0 | D39: =+B39*'6SueAct'!$C$7 -> 0 | F39: =+B39+D39 -> 0 | G39: Considerar nueva curricula
A40: Gerente Operacion 1º Rotación | B40: =+M40 -> 0 | D40: =+B40*'6SueAct'!$C$7 -> 0 | F40: =+B40+D40 -> 0 | G40: Implementar y considerar curricula
B41: =+M41 -> 0 | D41: =+B41*'6SueAct'!$C$7 -> 0 | F41: =+B41+D41 -> 0 | G41: Implementar y considerar curricula
A42: 4º TALLER MINA | C42: =SUM(B43:B52) -> 0 | E42: =SUM(D43:D52) -> 0 | G42: =+C42+E42 -> 0 | H42: SUB TOTAL
A43: Tecnico Mecánico 1º Rotación | B43: =+M43 -> 0 | D43: =+B43*'6SueAct'!$C$7 -> 0 | F43: =+B43+D43 -> 0 | G43: Considerar nueva curricula
A44: Tecnico Mecánico 2º Rotación | B44: =+M44 -> 0 | D44: =+B44*'6SueAct'!$C$7 -> 0 | F44: =+B44+D44 -> 0 | G44: Considerar nueva curricula
A45: Tecnico Electricista 1º Rotación | B45: =+M45 -> 0 | D45: =+B45*'6SueAct'!$C$7 -> 0 | F45: =+B45+D45 -> 0 | G45: Considerar a futuro s/g necesidad
A46: Tecnico Electricista 2º Rotación | B46: =+M46 -> 0 | D46: =+B46*'6SueAct'!$C$7 -> 0 | F46: =+B46+D46 -> 0 | G46: Considerar a futuro s/g necesidad
A47: Técnico Mecánico Auxiliar 1ºRota | B47: =+M47 -> 0 | D47: =+B47*'6SueAct'!$C$7 -> 0 | F47: =+B47+D47 -> 0 | G47: Considerar nueva curricula
A48: Técnico Mecánico Auxiliar 2ºRota | B48: =+M48 -> 0 | D48: =+B48*'6SueAct'!$C$7 -> 0 | F48: =+B48+D48 -> 0 | G48: Considerar nueva curricula
A49: Soldador 1º Rotación | B49: =+M49 -> 0 | D49: =+B49*'6SueAct'!$C$7 -> 0 | F49: =+B49+D49 -> 0 | G49: Considerar nueva curricula
A50: Soldador 2º Rotación | B50: =+M50 -> 0 | D50: =+B50*'6SueAct'!$C$7 -> 0 | F50: =+B50+D50 -> 0 | G50: Considerar nueva curricula
A51: Llantero 1º Rotación | B51: =+M51 -> 0 | D51: =+B51*'6SueAct'!$C$7 -> 0 | F51: =+B51+D51 -> 0 | G51: Evaluar
A52: Llantero 2º Rotación | B52: =+M52 -> 0 | D52: =+B52*'6SueAct'!$C$7 -> 0 | F52: =+B52+D52 -> 0 | G52: Evaluar
A53: 5º OPERARIOS MINA | C53: =SUM(B54:B63) -> 0 | E53: =SUM(D54:D63) -> 0 | G53: =+C53+E53 -> 0 | H53: SUB TOTAL
A54: Volquete 1º Choferes 4 personas | B54: =+M54*J54 -> 0 | C54: =SUM(B54:B60) -> 0 | D54: =+B54*'6SueAct'!$C$7 -> 0 | E54: =SUM(D54:D60) -> 0 | F54: =+B54+D54 -> 0 | G54: Considerar nueva curricula
A55: Volquete 2º Choferes 4 personas | B55: =+M55*J55 -> 0 | D55: =+B55*'6SueAct'!$C$7 -> 0 | F55: =+B55+D55 -> 0 | G55: Considerar nueva curricula
A56: Volquete 3º Choferes 4 personas | B56: =+M56*J56 -> 0 | D56: =+B56*'6SueAct'!$C$7 -> 0 | F56: =+B56+D56 -> 0 | G56: Considerar nueva curricula
A57: Volquete 4º Choferes 4 personas | B57: =+M57*J57 -> 0 | D57: =+B57*'6SueAct'!$C$7 -> 0 | F57: =+B57+D57 -> 0 | G57: Considerar nueva curricula
A58: Volquete 5º Choferes 4 personas | B58: =+M58*J58 -> 0 | D58: =+B58*'6SueAct'!$C$7 -> 0 | F58: =+B58+D58 -> 0 | G58: Considerar nueva curricula
A59: Volquete 6º Choferes 4 personas | B59: =+M59*J59 -> 0 | D59: =+B59*'6SueAct'!$C$7 -> 0 | F59: =+B59+D59 -> 0 | G59: Considerar nueva curricula
A60: Volquete 7º Choferes 4 personas | B60: =+M60*J60 -> 0 | D60: =+B60*'6SueAct'!$C$7 -> 0 | F60: =+B60+D60 -> 0 | G60: Considerar nueva curricula
A61: Excavadora 1º Operador 4 personas | B61: =+M61*J61 -> 0 | C61: =SUM(B61:B63) -> 0 | D61: =+B61*'6SueAct'!$C$7 -> 0 | E61: =SUM(D61:D63) -> 0 | F61: =+B61+D61 -> 0 | G61: Considerar nueva curricula
A62: Excavadora 2º Operador 4 personas | B62: =+M62*J62 -> 0 | D62: =+B62*'6SueAct'!$C$7 -> 0 | F62: =+B62+D62 -> 0 | G62: Considerar nueva curricula
A63: Excavadora 3º Operador 4 personas | B63: =+M63*J63 -> 0 | D63: =+B63*'6SueAct'!$C$7 -> 0 | F63: =+B63+D63 -> 0 | G63: Considerar nueva curricula
A64: SALARIOS Y DERECHOS LABORALES MES | C64: =+C16+C28 -> 0 | E64: =+E16+E28 -> 0
A65: TOTAL PLANILLA MENSUAL | C65: =C64+E64 -> 0 | F65: =C65/'3insumo'!H6 -> 0
C66: TOTAL PERSONAL QUE LABORA
A67: TOTAL PERSONAL EN MINA | D67: =SUM(C67:C70) -> 0
A68: Personal Administrativo | C68: =+K30 -> 0
A69: Personal Taller Mina | C69: =+K43 -> 0
A70: Personal Operadores Mina | C70: =+K54+K61 -> 0
A71: TOTAL PERSONAL OFICINA HUARAZ | D71: =SUM(C72:C74) -> 0
A72: Personal Administrativo | C72: =+K65 -> 0
A73: Directivos | C73: =+K18 -> 0
A74: Asesor Legal | C74: =+K24 -> 0

Sheet 2Maq
A1: ANEXO II
A2: ESTRUCTURACION PERSONAL vs MAQUINARIA
A3: 1.1: DESCRICCION DEL SERVICIO
A4: SERVICIO : | B4: ACARREO DE MATERIALES EN OPERACIONES Y CARRETERA
A5: TURNOS LABORALES: | B5: 10 DIAS DE TRABAJO POR 10 DIAS DE DESCANSO
A6: HORAS CONTATADA DIA : | B6: 20 HORAS MAQUINAS DIARIAS
A7: CONDICION : | B7: MAQUINAS OPERATIVAS Y CON OPERADOR - MAQUINARIA SECA
A8: TOTAL MAQUINARIA: | B8: =SUM(B13:B14) -> 10
A9: TOTAL Hora/Maquina Mes: | B9: =B8*'6SueAct'!F7 -> 5000
A10: 1.2: DESCRICCION LABORAL
C11: PERSONAL POR | E11: TOTAL | G11: OBSERVACION
A12: Actividad del Personal | B12: Maquinaria | C12: TURNO 1 | D12: TURNO 2 | E12: PERSONAL
A13: Conductores Volquetes | B13: 7 | C13: =B13*2 -> 14 | D13: =B13*2 -> 14 | E13: =SUM(C13:D13) -> 28 | G13: De acuerdo contrato
A14: Operador - Excavadora | B14: 3 | C14: =B14*2 -> 6 | D14: =B14*2 -> 6 | E14: =SUM(C14:D14) -> 12 | G14: De acuerdo contrato
A15: Supervisor de campo | C15: =+'1Planilla'!J34+'1Planilla'!J36 -> 0 | D15: =+'1Planilla'!J35+'1Planilla'!J37 -> 0 | E15: =SUM(C15:D15) -> 0 | G15: Capacitar y Evaluar
A16: Supervisor de Seguridad | C16: 1 | D16: 1 | E16: =SUM(C16:D16) -> 2 | G16: Necesario
A17: Administrador | C17: 1 | D17: 1 | E17: =SUM(C17:D17) -> 2 | G17: =+$G$15 -> Capacitar y Evaluar
A18: Técnico Mecánico | C18: 1 | D18: 1 | E18: =SUM(C18:D18) -> 2 | G18: =+$G$15 -> Capacitar y Evaluar
A19: Técnico Electricista | C19: 0 | D19: 0 | E19: =SUM(C19:D19) -> 0 | G19: Capacitar y Evaluar
A20: Apoyo Mecánico | C20: 1 | D20: 1 | E20: =SUM(C20:D20) -> 2 | G20: =+$G$15 -> Capacitar y Evaluar
A21: Soldadores | C21: 1 | D21: 1 | E21: =SUM(C21:D21) -> 2 | G21: =+$G$15 -> Capacitar y Evaluar
A22: Almacenero | C22: 1 | D22: 1 | E22: =SUM(C22:D22) -> 2 | G22: =+$G$15 -> Capacitar y Evaluar
A23: Llantero | C23: 1 | D23: 1 | E23: =SUM(C23:D23) -> 2 | G23: =+$G$15 -> Capacitar y Evaluar
A24: GERENTE OPERACIONES | C24: 0 | D24: 0 | E24: =SUM(C24:D24) -> 0 | G24: IMPLEMENTAR
A25: JEFE DE OPERACIONES | C25: 0 | D25: 0 | E25: =SUM(C25:D25) -> 0 | G25: IMPLEMENTAR
A26: SUB TOTAL PERSONAL POR TURNO | C26: =SUM(C13:C25) -> 27 | D26: =SUM(D13:D25) -> 27 | E26: =SUM(E13:F25) -> 54
A28: 1.3: DESCRICCION DE MAQUINARIAS Y CARACTERISTICAS
A29: TIPO DE MAQUINARIA | B29: Modelo | C29: Placa | D29: Año de Fabricaci | E29: HP | F29: Horómetro | G29: Fecha de Lectura | H29: Capaciad (m³) | I29: Condicion
A31: 1.- Volquete 6X4 R | B31: FM 440 | C31: WGM 857 | D31: 2008 | E31: 440 | F31: 7054.4 | G31: 40298 | H31: 15 | I31: Operativo | J31: 1
A32: 2.- Volquete 6X4 R | B32: FM 440 | C32: WGM 858 | D32: 2008 | E32: 440 | F32: 7230.26 | G32: 40293 | H32: =+H31 -> 15 | I32: Operativo | J32: 0
A33: 3.- Volquete 6X4 R | B33: FM 440 | C33: WGM 859 | D33: 2008 | E33: 440 | F33: 7441 | G33: 40294 | H33: =+H31 -> 15 | I33: Operativo | J33: 1
A34: 4.- Volquete 6X4 R | B34: FM 420 | C34: XO6044 | D34: 2003 | E34: 420 | F34: 25590.6 | G34: 40295 | H34: =+H31 -> 15 | I34: Operativo | J34: 1
A35: 5.- Volquete 6X4 R | B35: NL 12 | C35: XO4065 | D35: 2000 | E35: 400 | F35: 30538 | G35: 40231 | H35: =+H31 -> 15 | I35: Inoperativo | J35: 1
A36: 6.- Volquete 6X4 R | B36: NL 12 | C36: XO4066 | D36: 2000 | E36: 400 | F36: 33,982.40 | G36: 40303 | H36: =+H31 -> 15 | I36: Operativo | J36: 1
A37: 7.- Volquete 6X4 R | B37: NL 12 | C37: XO5085 | D37: 2001 | E37: 400 | F37: 28749.7 | G37: 40297 | H37: =+H31 -> 15 | I37: Inoperativo | J37: 1
A38: 8.- Volquete 6X4 R | B38: NL 12 | C38: XO5387 | D38: 2001 | E38: 400 | F38: 28112.9 | G38: 40300 | H38: =+H31 -> 15 | I38: Inoperativo | J38: 1
A39: 9.- Excavadora sobre oruga | B39: BL | C39: CAT | D39: 2002 | E39: 260 | F39: 25590.6 | G39: 40301 | H39: 2,10 m³ | I39: Inoperativo | J39: 0
A40: 10.- Excavadora sobre oruga | B40: DL | C40: CAT | D40: 2007 | E40: 268 | F40: 10252.4 | G40: 40299 | H40: 2,10 m³ | I40: Inoperativo | J40: 1
A41: 11.- Excavadora sobre oruga | B41: EC360BL | C41: VOLVO | D41: 2008 | E41: 250 | F41: 7862.5 | G41: 40295 | H41: 1,96 m³ | I41: Operativo | J41: 1
A42: 12.- Excavadora sobre oruga | B42: PC300LC8 | C42: KOMATSU | D42: 2009 | E42: 246 | F42: 1625 | G42: 40302 | H42: 2,54 m³ | I42: Operativo | J42: 1
A43: NOTA: Para la estructuración del costo horario actual, solo se está considerando SIETE Volquetes y TRES Excavadoras, en
A44: conformidad al convenio y/o contrato suscrito y que en supuesto caso de que tosas las Maquinarias esten Operativas

Sheet 3insumo
B1: ANEXO III
A2: DESCRIPCION DE PARTES, INSUMOS, CANTIDADES Y COSTOS
A3: PARA EL MANTENIMIENTO PREVENTIVO PROGRAMADO
A4: EXCAVADORA KOMATSU PC300 LC-8
A6: FaCo 1 Gl = | C6: 3.785 | D6: litros | E6: I.G.V. = | F6: 1 | G6: T.C. 1 US = | H6: 2.94
A8: ITEM | B8: DESCRIPCION | C8: COD. | D8: CANT | E8: Und. | F8: Costo Unitario | G8: Costo Total S/. | H8: Costo Total $
B9: LUBRICANTES Y RETEN
A10: 1 | B10: Valvoline Premiun Blue 15W40 | C10: P15400500 | D10: 1 | E10: gal | F10: =O7/D10 -> 0 | G10: =D10*F10 -> 0 | H10: =+G10/H6 -> 0
A11: =A10+1 -> 2 | B11: Valvoline Transmission TO-4 30 | C11: TO4300500 | D11: 1 | E11: gal | F11: =O8/D11 -> 0 | G11: =D11*F11 -> 0 | H11: =+G11/H6 -> 0
A12: =A11+1 -> 3 | B12: Valvoline Transmission TO-4 10W | C12: TO4100500 | D12: 1 | E12: gal | F12: =O9/D12 -> 0 | G12: =D12*F12 -> 0 | H12: =+G12/H6 -> 0
B13: GRASA
A14: =+A12+1 -> 4 | B14: Boquillas de engrase, círculo de giro y piñon de giro | C14: VV612 | D14: 1 | E14: Kg | G14: =F16*D14 -> 0 | H14: =G14/H6 -> 0
F16: =O11 -> 0
B18: FILTROS
A19: =A14+1 -> 5 | B19: Filtro de aire primario | C19: 6001856110 | D19: 1 | E19: unid | F19: =O16/D19 -> 0 | G19: =D19*F19 -> 0 | H19: =G19/H6 -> 0
A20: =+A19+1 -> 6 | B20: Filtro de aire secundario | C20: 6001856120 | D20: 1 | E20: unid | F20: =O17/D20 -> 0 | G20: =D20*F20 -> 0 | H20: =G20/H6 -> 0
A21: =+A20+1 -> 7 | B21: Filtro de aceite del motor | C21: 6742014540 | D21: 1 | E21: unid | F21: =O18/D21 -> 0 | G21: =D21*F21 -> 0 | H21: =G21/H6 -> 0
A22: =+A21+1 -> 8 | B22: Filtro de combustible primario | C22: 6003193610 | D22: 1 | E22: unid | F22: =O19/D22 -> 0 | G22: =D22*F22 -> 0 | H22: =G22/H6 -> 0
A23: =+A22+1 -> 9 | B23: Filtro de combustible secundario | C23: 6754796140 | D23: 1 | E23: unid | F23: =O20/D23 -> 0 | G23: =D23*F23 -> 0 | H23: =G23/H6 -> 0
A24: =+A23+1 -> 10 | B24: Filtro aire acondicionado recircu. | C24: 2089797620 | D24: 1 | E24: unid | F24: =O21/D24 -> 0 | G24: =D24*F24 -> 0 | H24: =G24/H6 -> 0
A25: =+A24+1 -> 11 | B25: Filtro aire acondicionado limpio | C25: 17M9113530 | D25: 1 | E25: unid | F25: =O22/D25 -> 0 | G25: =D25*F25 -> 0 | H25: =G25/H6 -> 0
B26: FILTROS HIDRAULICOS
A27: =+A25+1 -> 12 | B27: Filtro Hidráulico | C27: 2076071182 | D27: 1 | E27: unid | F27: =O24 -> 0 | G27: =D27*F27 -> 0 | H27: =G27/H6 -> 0
A28: =+A27+1 -> 13 | B28: Cartucho | C28: 6004111191 | D28: 1 | E28: unid | F28: =O25 -> 0 | G28: =D28*F28 -> 0 | H28: =G28/H6 -> 0
A29: =+A28+1 -> 14 | B29: Respiradero adicional Hidráulico | C29: 2076051310 | D29: 1 | E29: unid | F29: =O26 -> 0 | G29: =D29*F29 -> 0 | H29: =G29/H6 -> 0
A30: =+A29+1 -> 15 | B30: Respiradero Hidráulico | C30: 20Y6021470 | D30: 1 | E30: unid | F30: =O27 -> 0 | G30: =D30*F30 -> 0 | H30: =G30/H6 -> 0
B31: ELEMENTOS DE DESGASTE
A32: =+A30+1 -> 16 | B32: Puntas roquera (Hensley) | C32: HLK30RP2 | D32: 1 | E32: unid | F32: =+O29 -> 0 | G32: =+F32*D32 -> 0 | H32: =G32/$H$6 -> 0
A33: =+A32+1 -> 17 | B33: Lock (pasador de uñas) | C33: HLKP30C | D33: 1 | E33: unid | F33: =+O30 -> 0 | G33: =+F33*D33 -> 0 | H33: =G33/$H$6 -> 0
A34: =+A33+1 -> 18 | B34: Cuchilla Lateral (Hensley) | C34: HLSCB330SO | D34: 1 | E34: unid | F34: =+O31 -> 0 | G34: =+F34*D34 -> 0 | H34: =G34/$H$6 -> 0
A35: =+A34+1 -> 19 | B35: Tuerca | C35: 25531R1 | D35: 1 | E35: unid | F35: =+O32 -> 0 | G35: =+F35*D35 -> 0 | H35: =G35/$H$6 -> 0
A36: =+A35+1 -> 20 | B36: Perno de cuchilla | C36: 209011690 | D36: 1 | E36: unid | F36: =+O33 -> 0 | G36: =+F36*D36 -> 0 | H36: =G36/$H$6 -> 0
A37: =+A36+1 -> 21 | B37: Kit de 30 pernos y tuercas | C37: 2073205061 | D37: 1 | E37: unid | F37: =+O34 -> 0 | G37: =+F37*D37 -> 0 | H37: =G37/$H$6 -> 0
A38: =+A37+1 -> 22 | B38: Tuerca | C38: 25531R1 | D38: 1 | E38: unid | F38: =+O35 -> 0 | G38: =+F38*D38 -> 0 | H38: =G38/$H$6 -> 0
A39: =+A38+1 -> 23 | B39: Zapata 700 mm Triple | C39: 2073261310 | D39: 1 | E39: unid | F39: =+O36 -> 0 | G39: =+F39*D39 -> 0 | H39: =G39/$H$6 -> 0
B40: OTROS
A41: =+A39+1 -> 24 | B41: Correa de la tranmision | D41: 1 | E41: unid | F41: =O38 -> 0 | G41: =F41*D41 -> 0 | H41: =G41/H6 -> 0
A42: =+A41+1 -> 25 | B42: Refrigerante | C42: 1400164H1 | D42: 1 | E42: gal | F42: =O39 -> 0 | G42: =D42*F42 -> 0 | H42: =G42/H6 -> 0
A43: =+A42+1 -> 26 | B43: Bateria 15 placas- 24V | D43: 1 | E43: unid | F43: =O40 -> 0 | G43: =D43*F43 -> 0 | H43: =G43/H6 -> 0
B44: MUESTRAS DE ACEITES
A45: =+A43+1 -> 27 | B45: Motor | D45: 1 | E45: unid | F45: =+O42 -> 0 | G45: =F45*D45 -> 0 | H45: =G45/H6 -> 0
A46: =+A45+1 -> 28 | B46: Mandos finales | D46: 1 | E46: unid | F46: =+F45 -> 0 | G46: =F46*D46 -> 0 | H46: =G46/H6 -> 0
A47: =+A46+1 -> 29 | B47: Rotacion | D47: 1 | E47: unid | F47: =+F45 -> 0 | G47: =F47*D47 -> 0 | H47: =G47/H6 -> 0
A48: =+A47+1 -> 30 | B48: Hidràulico | D48: 1 | E48: unid | F48: =+F45 -> 0 | G48: =F48*D48 -> 0 | H48: =G48/H6 -> 0
A49: =+A48+1 -> 31 | B49: Muestra de refrigerante | D49: 1 | E49: unid | F49: =+F45 -> 0 | G49: =F49*D49 -> 0 | H49: =G49/H6 -> 0
B50: DIESEL B2 | C50: B2 | D50: 1 | E50: gal | F50: =+G50/D50 -> 0 | G50: 0
F53: Con IGV | G53: =SUM(G10:G50) -> 0 | H53: =SUM(H9:H50) -> 0
F54: Con IGV | G54: 6923.85 | H54: 2355.05
F55: Sin IGV | G55: =SUM(G9:G50) -> 0 | H55: =SUM(H9:H50) -> 0
F56: Sin IGV | G56: 5818.36 | H56: 1979.03
F57: Diferencia | G57: =G54-G56 -> 1105.49 | H57: =H54-H56 -> 376.02
E58: 1.19 | F58: IGV | G58: =G56*E58 -> 6923.8484 | H58: =H56*E58 -> 2355.0457

Sheet 4Trans
A1: ANEXO IV
A2: CALCULO DE COSTO POR TRANSPORTE DE PARA PARTES, INSUMOS POR PESO
A3: =+'[1]3insumo'!A3:H3 -> PARA EL MANTENIMIENTO PREVENTIVO PROGRAMADO
A4: EXCAVADORA KOMAT'SU PC300LC-8
A6: Nº | B6: DESCRIPCIÓN | C6: Unidad | D6: Cant | E6: Ciclo Meses | F6: pesos (kg)
A7: 1 | B7: Aceite Motor | C7: 55 gln | D7: 1 | E7: 2 | F7: 208
A8: 2 | B8: Aceite de Mando de rotación de Giro | C8: 5 gln | D8: 1 | E8: 2 | F8: 18.91
A9: 3 | B9: Aceite Transmision caja mandos finales | C9: 5 gln | D9: 3 | E9: 2 | F9: 53.73
A10: 4 | B10: Aceite Sistema Hidraúlico | C10: 55 gln | D10: 1 | E10: 4 | F10: 226.9
A11: 5 | B11: Grasa varillaje de pluma y brazo | C11: 54 kg | D11: 1 | E11: 2 | F11: 54
A12: 6 | B12: Grasa varillaje cucharon
A13: 7 | B13: Grasa acoplador ràpido
A14: 8 | B14: Grasa cojinete de rotaciòn
A15: 9 | B15: Grasa engranaje de rotaciòn
A16: 10 | B16: Filtro Aire (P) | C16: und. | D16: 2 | E16: 2 | F16: 1.5
A17: 11 | B17: Filtro Aire (S) | C17: und. | D17: 2 | E17: 2 | F17: 2.5
A18: 12 | B18: Filtro Aceite de motor | C18: und. | D18: 4 | E18: 2 | F18: 1
A19: 13 | B19: Filtro Combustible (P) | C19: und. | D19: 4 | E19: 2 | F19: 1.5
A20: 14 | B20: Filtro Combustible (S) | C20: und. | D20: 2 | E20: 2 | F20: 1.5
A21: 15 | B21: Filtro Hidráulico Piloto | C21: und. | D21: 2 | E21: 2 | F21: 2
A22: 16 | B22: Filtro Hidráulico de Retorno | C22: und. | D22: 2 | E22: 2 | F22: 2
A23: 17 | B23: Filtro Racor | C23: und. | D23: 2 | E23: 2 | F23: 0.5
A24: 18 | B24: Filtro Elemento Tanque | C24: und. | D24: 4 | E24: 2 | F24: 1.5
A25: 19 | B25: Refrigerante | C25: 5 gln | D25: 1 | E25: 2 | F25: 18
A26: 20 | B26: Correa de trasmisión | C26: und. | D26: 1 | E26: 5 | F26: 1
A27: 21 | B27: Baterias | C27: und. | D27: 2 | E27: 5 | F27: 50
... A32: 26 | B32: PERNOS Y TERCAS | C32: und. | D32: 16 | E32: 7 | F32: 115.2
D33: Peso Total | F33: =SUM(F7:F32) -> 4961.74
A35: Transportes Pedesa - Traslado Lima @ Mina
A36: Nº | B36: Descripcion | C36: horometro | D36: Peso (kg) | F36: Costo
A37: 1 | B37: Insumos: filtros, aceites | C37: 1200 | D37: 328.64 | F37: =D37*A45 -> 0
A38: 2 | B38: Insumos: aceites, filtros, grasa | C38: 2400 | D38: 606.54 | F38: =D38*A45 -> 0
A39: 3 | B39: Insumos: carrileria, materiales de desgaste | C39: 4200 | D39: 4317.2 | F39: =D39*A45 -> 0
E40: Sub Total | F40: =SUM(F37:F39) -> 0
A41: Transporte Pereda: (Transporte carga) | E41: Factor | F41: 5,9Tn/9000hr | L41: 1.19
A42: 4,000 kg = S/.2,800 (sin I.G.V.) | E42: S/ x hora | F42: =(9000/F49)*A45 -> 0
A43: 4,000 kg = S/.3,320
A44: 0,001 kg = S/.0,833 | C44: horometro | D44: mes | E44: pack | F44: Peso Transp.
A45: =+I40 -> 0 | C45: 6000 | D45: 2 | E45: 1 | F45: =+D37 -> 328.64
C46: 7200 | D46: 4 | E46: 2 | F46: =+D38 -> 606.54
C47: 8400 | D47: 6 | E47: 1 | F47: =+D37 -> 328.64
C48: 9000 | D48: 7 | E48: 3+1 | F48: =+D39+D37 -> 4645.84
C49: 9600 | D49: 8 | E49: 2 | F49: =SUM(F45:F48) -> 5909.66
C50: 10800 | D50: 10 | E50: 1 | F50: Total Peso
C51: 12000 | D51: 12 | E51: 2
C52: 13200 | D52: 14 | E52: 3+1
C53: 14400 | D53: 16 | E53: 2
C54: 15600 | D54: 18 | E54: 1
C55: 16800 | D55: 20 | E55: 2
C56: 17400 | D56: 21 | E56: 3+1

Sheet 5 EPP
A1: ANEXO V
A3: EQUIPOS DE PROTECCION PARA TODO EL PERSONAL EN MINA
A5: MAQ | B5: RENDIMIENTO Hora /Semestral | C5: Horas/Año | D5: Mes/año | E5: Horas/Mes | F5: Días/Mes | G5: Horas/Día | H5: Operadores | I5: Administra.
A6: =+'2Maq'!B8 -> 10 | B6: =C6/2 -> 2500 | C6: =F6*G6*D6 -> 5000 | D6: =+'6SueAct'!E7 -> 10 | E6: =F6*G6 -> 500 | F6: =+'6SueAct'!G7 -> 25 | G6: 20 | H6: =+'1Planilla'!K54+'1Planilla'!K61 -> 0 | I6: =+'1Planilla'!K30+'1Planilla'!K43 -> 0
A8: Item | B8: DESCRIPCION | C8: Concepto | D8: Cantidad | E8: Und. | F8: Rend.Prome | G8: Consumo | H8: Precio Unitario | I8: COSTO REAL
F9: hr - maquina | G9: por hora
A10: 5.1 | B10: EQUIPOS DE PROTECCION PERSONAL ADMINISTRACION | F10: SUB TOTAL S/. /hora | I10: =SUM(I11:I21)/'2Maq'!B8 -> 0.0016
B11: Casco | C11: Seguridad | D11: =+$I$6 -> 0 | E11: und | F11: =$B$6 -> 2500 | G11: =D11/F11 -> 0 | H11: 33.61 | I11: =G11*H11 -> 0
B12: Zapatos | D12: =+$I$6 -> 0 | E12: und | F12: =$B$6 -> 2500 | G12: =D12/F12 -> 0 | H12: 79.83 | I12: =G12*H12 -> 0
B13: Lentes Oscuros | D13: =+$I$6 -> 0 | E13: und | F13: =$B$6 -> 2500 | G13: =D13/F13 -> 0 | H13: 12.61 | I13: =G13*H13 -> 0
B14: Lentes Transparentes | D14: =+$I$6 -> 0 | E14: und | F14: =$B$6 -> 2500 | G14: =D14/F14 -> 0 | H14: 12.61 | I14: =G14*H14 -> 0
B15: Guantes de Cuero | D15: =+$I$6 -> 0 | E15: und | F15: =$B$6 -> 2500 | G15: =D15/F15 -> 0 | H15: 9.66 | I15: =G15*H15 -> 0
B16: Guantes de Operador | D16: 0 | E16: und | F16: =$B$6 -> 2500 | G16: =D16/F16 -> 0 | H16: 9.66 | I16: =G16*H16 -> 0
B17: Implementos para botiquin de equipos | D17: 1 | E17: und | F17: =$B$6 -> 2500 | G17: =D17/F17 -> 0.0004 | H17: 40 | I17: =G17*H17 -> 0.016
B18: Chalecos tela importada dril | D18: =+$I$6 -> 0 | E18: und | F18: =$B$6 -> 2500 | G18: =D18/F18 -> 0 | H18: 25.21 | I18: =G18*H18 -> 0
B19: Overol impermeable termico | D19: =SUM('1Planilla'!J34:J37) -> 0 | E19: und | F19: =$B$6 -> 2500 | G19: =D19/F19 -> 0 | H19: 117.65 | I19: =G19*H19 -> 0
B20: Overol de tela con cinta reflectivo | D20: =+$I$6 -> 0 | E20: und | F20: =$B$6 -> 2500 | G20: =D20/F20 -> 0 | H20: 46.22 | I20: =G20*H20 -> 0
B21: Tapa oido | D21: =+$I$6 -> 0 | E21: und | F21: 500 | G21: =D21/F21 -> 0 | H21: 3 | I21: =G21*H21 -> 0
A22: 5.2 | B22: EQUIPOS DE PROTECCION PERSONAL OPERACIÓN | F22: SUB TOTAL S/. /hora | I22: =SUM(I23:I42)/'2Maq'!B8 -> 0.0199744
B23: Casco | C23: Seguridad | D23: =+$H$6 -> 0 | E23: und | F23: =$B$6 -> 2500 | G23: =D23/F23 -> 0 | H23: 33.61 | I23: =G23*H23 -> 0
B24: Zapatos | D24: =+D23 -> 0 | E24: und | F24: =$B$6 -> 2500 | G24: =D24/F24 -> 0 | H24: 79.83 | I24: =G24*H24 -> 0
B25: Lentes Oscuros | D25: =+D23 -> 0 | E25: und | F25: =$B$6 -> 2500 | G25: =D25/F25 -> 0 | H25: 12.61 | I25: =G25*H25 -> 0
B26: Lentes Transparentes | D26: =+D23 -> 0 | E26: und | F26: =$B$6 -> 2500 | G26: =D26/F26 -> 0 | H26: 12.61 | I26: =G26*H26 -> 0
B27: Guantes de Cuero | D27: =+D23 -> 0 | E27: und | F27: =$B$6 -> 2500 | G27: =D27/F27 -> 0 | H27: 9.66 | I27: =G27*H27 -> 0
B28: Implementos para botiquin de equipos | D28: 2 | E28: und | F28: =$B$6 -> 2500 | G28: =D28/F28 -> 0.0008 | H28: 40 | I28: =G28*H28 -> 0.032
B29: Chalecos tela importada dril | D29: =+D23 -> 0 | E29: und | F29: =$B$6 -> 2500 | G29: =D29/F29 -> 0 | H29: 25.21 | I29: =G29*H29 -> 0
B30: Overol impermeable termico | D30: =+D24 -> 0 | E30: und | F30: =$B$6 -> 2500 | G30: =D30/F30 -> 0 | H30: 117.65 | I30: =G30*H30 -> 0
B31: Overol de tela con cinta reflectivo | D31: =+D23 -> 0 | E31: und | F31: =$B$6 -> 2500 | G31: =D31/F31 -> 0 | H31: 46.22 | I31: =G31*H31 -> 0
B32: Tapa oido | D32: =+D23 -> 0 | E32: und | F32: =$B$6 -> 2500 | G32: =D32/F32 -> 0 | H32: 3 | I32: =G32*H32 -> 0
B33: Mascarilla | D33: =+D23 -> 0 | E33: und | F33: =$B$6 -> 2500 | G33: =D33/F33 -> 0 | H33: 3 | I33: =G33*H33 -> 0
B34: Pantalon de cuero | D34: 1 | E34: und | F34: =$B$6 -> 2500 | G34: =D34/F34 -> 0.0004 | H34: 66.39 | I34: =G34*H34 -> 0.026556
B35: Casaca de cuero | D35: 1 | E35: und | F35: =$B$6 -> 2500 | G35: =D35/F35 -> 0.0004 | H35: 71.43 | I35: =G35*H35 -> 0.028572
B36: Escarpin de cuero | D36: 1 | E36: und | F36: =$B$6 -> 2500 | G36: =D36/F36 -> 0.0004 | H36: 15 | I36: =G36*H36 -> 0.006
B37: Mandil soldadura | D37: 1 | E37: und | F37: =$B$6 -> 2500 | G37: =D37/F37 -> 0.0004 | H37: 25.21 | I37: =G37*H37 -> 0.010084
B38: Capuchon para soldar | D38: 1 | E38: und | F38: =$B$6 -> 2500 | G38: =D38/F38 -> 0.0004 | H38: 21.85 | I38: =G38*H38 -> 0.00874
B39: Careta para esmerilar | D39: 1 | E39: und | F39: =$B$6 -> 2500 | G39: =D39/F39 -> 0.0004 | H39: 35 | I39: =G39*H39 -> 0.014
B40: Careta de soldador | D40: 2 | E40: und | F40: =$B$6 -> 2500 | G40: =D40/F40 -> 0.0008 | H40: 50 | I40: =G40*H40 -> 0.04
B41: Mascarilla para soldador | D41: 2 | E41: und | F41: =$B$6 -> 2500 | G41: =D41/F41 -> 0.0008 | H41: 23.75 | I41: =G41*H41 -> 0.019
B42: Guantes de cuero para soldar | D42: 2 | E42: und | F42: =$B$6 -> 2500 | G42: =D42/F42 -> 0.0008 | H42: 18.49 | I42: =G42*H42 -> 0.014792
A43: NOTA: Para determinar el costo horario de los equipos de protección personal se considera un rendimiento
A44: semestral de 2,500 hrs y 5,000 al año, la que no sera afectado por la disminución de las horas maquinas.

Sheet 6SueAct
A1: ANEXO VI
A2: ESTRUCTURA DE HONORARIOS ACTUAL DEL PERSONAL - MES
A4: COSTOS ADMINISTRATIVOS Y DE PERSONAL HORA / MAQUINA
C6: % Pago Admi | D6: Horas/Año | E6: Mes / año | F6: Horas /Mes | G6: Días/Mes | H6: Horas/Día | I6: T.C. US$
B7: Derechos y obligaciones laborales % = | C7: 0.485 | D7: =G7*H7*E7 -> 5000 | E7: 10 | F7: =G7*H7 -> 500 | G7: 25 | H7: 20 | I7: ='3insumo'!H6 -> 2.94
A9: Item | B9: DESCRIPCION | C9: Concepto | D9: Personal | F9: hr-maq. Mes Total | G9: Factor Personal÷hr maq. mes | H9: Costo Unitario | I9: Costo Real
A10: 4.1 | B10: PERSONAL ADMINISTRATIVO Y TALLER | I10: =SUM(I11:I38) -> 4.318434
B11: Personal Administrativo Huaraz (3) | C11: Administración | D11: 3 | E11: jornal | F11: =$F$7*'2Maq'!$B$8 -> 5000 | G11: =(D11/F11) -> 0.0006 | H11: =SUM('1Planilla'!B25:B27) -> 0 | I11: =G11*H11 -> 0
B12: Derechos obligaciones Labo administrador Hz | E12: D-OLA | H12: =H11*$C$7 -> 0 | I12: =G11*H12 -> 0
B13: Personal Directivos (3) | C13: Dirección | D13: 3 | E13: Honorario | G13: =(D13/F11) -> 0.0006 | H13: =SUM('1Planilla'!B18:B20) -> 0 | I13: =G13*H13 -> 0
B14: Derechos obligaciones Directivos | E14: D-OLA | H14: 0 | I14: =G13*H14 -> 0
B15: Personal Asesor Legal (1) | C15: Legal | D15: 1 | E15: Honorario | G15: =D15/F11 -> 0.0002 | H15: =+'1Planilla'!B24 -> 0 | I15: =G15*H15 -> 0
B16: Derechos obligaciones Laborales Asesor Legal | H16: =H15*$C$7 -> 0 | I16: =G15*H16 -> 0
B17: Personal Administrativo Mina (2) | C17: Administración | D17: 2 | E17: jornal | F17: =$F$7*'2Maq'!$B$8 -> 5000 | G17: =(D17/F17) -> 0.0004 | H17: =SUM('1Planilla'!B30:B31) -> 0 | I17: =G17*H17 -> 0
B18: Derechos obligaciones laborales administrador | E18: D-OLA | H18: =H17*C7 -> 0 | I18: =G17*H18 -> 0
B19: Personal de Seguridad (2) | D19: 2 | E19: jornal | G19: =(D19/F17) -> 0.0004 | H19: =SUM('1Planilla'!B38:B39) -> 0 | I19: =G19*H19 -> 0
B20: Derechos y obligaciones laborales P.Seguri | E20: D-OLPS | H20: =H19*C7 -> 0 | I20: =G19*H20 -> 0
B21: Personal de Mantenimiento Mecanicos Eléctric (2) | C21: Operación | D21: 2 | E21: jornal | F21: =$F$7*'2Maq'!$B$8 -> 5000 | G21: =(D21/F21) -> 0.0004 | H21: =SUM('1Planilla'!B43:B44) -> 0 | I21: =G21*H21 -> 0
B22: Derechos y obligaciones laborales P.Mante | E22: D-OLPM | H22: =H21*C7 -> 0 | I22: =G21*H22 -> 0
B23: Personal de Apoyo Mantenimiento (2) | C23: Operación | D23: 2 | E23: jornal | F23: =$F$7*'2Maq'!$B$8 -> 5000 | G23: =(D23/F23) -> 0.0004 | H23: =SUM('1Planilla'!B47:B48) -> 0 | I23: =G23*H23 -> 0
B24: Derechos y obligaciones laborales PAMant Mec | E24: D-OLPa | H24: =H23*C7 -> 0 | I24: =G23*H24 -> 0
B25: Personal Eléctricos (2) | C25: Operación | D25: 0 | E25: jornal | F25: =$F$7*'2Maq'!$B$8 -> 5000 | G25: =(D25/F25) -> 0 | H25: =SUM('1Planilla'!B45:B46) -> 0 | I25: =G25*H25 -> 0
B26: Derechos y obligaciones laborales P. Elec | E26: D-OLPM | H26: =H25*C7 -> 0 | I26: =G25*H26 -> 0
B27: Personal Soldador (2) | C27: Operación | D27: 2 | E27: jornal | F27: =$F$7*'2Maq'!$B$8 -> 5000 | G27: =(D27/F27) -> 0.0004 | H27: =SUM('1Planilla'!B49:B50) -> 0 | I27: =G27*H27 -> 0
B28: Derechos y obligaciones laborales P.Soldadr | E28: D-OLPS | H28: =H27*C7 -> 0 | I28: =G27*H28 -> 0
B29: Personal Almacenero (2) | C29: Operación | D29: 2 | E29: jornal | F29: =$F$7*'2Maq'!$B$8 -> 5000 | G29: =(D29/F29) -> 0.0004 | H29: =SUM('1Planilla'!B32:B33) -> 0 | I29: =G29*H29 -> 0
B30: Derechos y obligaciones laborales P.Almace | E30: D-OLPA | H30: =H29*C7 -> 0 | I30: =G29*H30 -> 0
B31: Personal Llantero (2) | C31: Operación | D31: 2 | E31: jornal | F31: =$F$7*'2Maq'!$B$8 -> 5000 | G31: =(D31/F31) -> 0.0004 | H31: =SUM('1Planilla'!B51:B52) -> 0 | I31: =G31*H31 -> 0
B32: Derechos y obligaciones laborales Llantero | E32: D-OLPA | H32: =H31*C7 -> 0 | I32: =G31*H32 -> 0
B33: Personal Supervisor (4) | C33: Operación | D33: 4 | E33: jornal | F33: =$F$7*'2Maq'!$B$8 -> 5000 | G33: =(D33/F33) -> 0.0008 | H33: =SUM('1Planilla'!B34:B37) -> 0 | I33: =G33*H33 -> 0
B34: Derechos y obligaciones laborales P.Super | E34: D-OLPS | H34: =H33*C7 -> 0 | I34: =G33*H34 -> 0
B35: Atencion medica Yanacancha | C35: Operación | D35: =SUM(D17:D34)/2 -> 9 | E35: ATM | F35: =$F$7*'2Maq'!$B$8 -> 5000 | G35: =(D35/F35) -> 0.0018 | H35: =N35*D35 -> 657.72 | I35: =G35*H35 -> 1.183896 | K35: Atención Medica Yanacan | N35: 73.08
B36: Alimentación, Hospedaje, Lavandería | E36: AHLav | H36: =N36*D35 -> 301.41 | I36: =G35*H36 -> 0.542538 | K36: Alimentación, Hospedaje, Lavandería | N36: 33.49
B37: Pasaporte medico | C37: Operación | D37: =SUM(D17:D34) -> 18 | E37: PSME | F37: =$D$7*'2Maq'!$B$8 -> 50000 | G37: =(D37/F37) -> 0.00036 | H37: =N37*D37 -> 3600 | I37: =G37*H37 -> 1.296 | K37: Pasaporte y EPS | N37: 200
B38: EPS | E38: EPS | H38: =N37*D37 -> 3600 | I38: =G37*H38 -> 1.296
A39: 4.2 | B39: PERSONAL OPERATIVO | C39: SUB TOTAL S/. / hora | I39: =SUM(I40:I47) -> 2.18256
B40: Personal Operador Excavadora | C40: Operación | D40: 4 | E40: jornal | F40: =$F$7 -> 500 | G40: =D40/F40 -> 0.008 | H40: ='1Planilla'!B61 -> 0 | I40: =H40*G40 -> 0 | K40: Son el total de haberes a fin de cumplir las 500 hrs mes
B41: Derechos y obligaciones laborales operador | E41: D-OLOx | H41: =H40*C7 -> 0 | I41: =H41*G40 -> 0
B42: Atención Médica en Yanacancha - dias | D42: 2 | E42: ATM/dias | G42: =D42/F40 -> 0.004 | H42: =N35*D42 -> 146.16 | I42: =H42*G42 -> 0.58464 | K42: Al mes solo se considera dos personas día
B43: Alimentación, Hospedaje, Lavandería - dias | E43: AHLav | H43: =N36*D42 -> 66.98 | I43: =H43*G42 -> 0.26792
B44: EPS | D44: 4 | E44: EPS | F44: =+$D$7 -> 5000 | G44: =D44/$F$44 -> 0.0008 | H44: =N37*D44 -> 800 | I44: =H44*G44 -> 0.64 | K44: Son 4 personas y la valides es de 1 año, considero 5,000 hrs
B45: Pasaporte Médico | E45: PSME | H45: =N37*D44 -> 800 | I45: =H45*G44 -> 0.64
B46: Viatico Chofer viaje Lima - Huaraz | C46: Operación | D46: 1 | E46: VCVLIH | G46: =D46/F44 -> 0.0002 | H46: 250 | I46: =H46*G46 -> 0.05
B47: Servicio de terceros | C47: Operación | D47: 2 | E47: SERVTER | G47: =D47/F44 -> 0.0004 | H47: 0 | I47: =H47*G47 -> 0

Sheet 7chrFM
B1: ESTRUCTURA ACTUAL DE COSTO HORARIO MAQUINARIA PESADA | L1: Item | M1: DESCRIPCION | N1: Nº Referencia | O1: Tipo ó Producto | P1: Cant. | Q1: Und. | R1: Rendimiento Promedio hora-maquina | S1: CONSUMO POR HORA | T1: PRECIO UNIT S/. | U1: COSTO REAL Soles/hora
A2: EXCAVADORA KOMATSU PC300-LC8 | L2: 3 | M2: COSTO DE POSESION | S2: SUB TOTAL S/. | U2: =SUM(U3:U12) -> 48.251807
A3: COSTO DE OPERACIÓN HORARIA: MAQUINA SECA EN SOLES (S/.) ( hr - Maq.) | L3: 3.01 | M3: Interes del Capital Invertido Excavadora | Q3: ( Cae ) x i / 200 Nae | U3: =('7,1Grafico'!G20*'7,1Grafico'!G22)/(200*'7,1Grafico'!G24) -> 0.0852845
L4: =+L3+0.01 -> 3.02 | M4: Depreciación Horaria Excavadora | Q4: ( Cae x Kre ) / Nv e | U4: ='7,1Grafico'!G20*'7,1Grafico'!G21/'7,1Grafico'!G23 -> 45.485067
B5: Horas Trabajadas efectivas por dia | C5: 12 | D5: Hrs / Año | E5: Mes/año | F5: Horas/Mes | G5: Días / Mes | H5: T.C. US$ | I5: Hr WM /Día | J5: Hr no WM/día | L5: =+L4+0.01 -> 3.03 | M5: Depreciación Horaria Camioneta | Q5: ( Cac x Kvr ) / Nv c | U5: =(('7,1Grafico'!G25*'7,1Grafico'!G21)/'7,1Grafico'!G26)/'2Maq'!B8 -> 0.45733333
B6: Total de Maquinarias consideradas | C6: =+'2Maq'!B8 -> 10 | D6: =I6*G6*E6 -> 5000 | E6: 10 | F6: =G6*I6 -> 500 | G6: 25 | H6: 2.94 | I6: 20 | J6: =20-I6 -> 0 | L6: =+L5+0.01 -> 3.04 | M6: Interes del Capital Invertido Camioneta | Q6: ( Cac ) x i / 200 Na c | U6: =+'[1]7chrFM'!$U$6 -> 0.00065621448 | W6: I = IMA x %i / Nº de horas anuales
A7: Item | B7: DESCRIPCION | C7: Nº Referencia | D7: Tipo ó Producto | E7: Cant. | F7: Und. | G7: Rendimiento promedio hora-maquina | H7: CONSUMO POR HORA | I7: PRECIO UNIT S/. | J7: COSTO REAL Soles/hora | L7: =+L6+0.01 -> 3.05 | M7: Poliza de seguro del excavadora | P7: 1 | Q7: POSV | R7: =($I$6+$J$6)*$G$6*$E$6 -> 5000 | S7: =P7/R7 -> 0.0002 | T7: 3822 | U7: =S7*T7 -> 0.7644
A8: 1 | B8: COSTO DE OPERACIÓN HORARIA | H8: TOTAL S/. | J8: =SUM(J9,J11,J36,J42,J53,J56,J63,J75,J78,J80,J47) -> 25.593098 | L8: =+L7+0.01 -> 3.06 | M8: Soat | O8: SOAT | P8: 1 | Q8: SOAT | R8: =+C6*D6 -> 50000 | S8: =P8/R8 -> 2e-05 | T8: 800 | U8: =S8*T8 -> 0.016
A9: 1.1 | B9: COMBUSTIBLE | H9: SUB TOTAL S/. | J9: =+J10 -> 0 | L9: =+L8+0.01 -> 3.07 | M9: Certificación de la excavadora | O9: Excavadora | P9: 1 | Q9: certificado | R9: =+G76 -> 5000 | S9: =P9/R9 -> 0.0002 | T9: =1800*H6 -> 5292 | U9: =S9*T9 -> 1.0584
B10: Consumo = 0.0325 x Gal / H x BHP | D10: DIESEL B2 | E10: 4.5 | F10: gal. | H10: =E10 -> 4.5 | I10: ='3insumo'!F50 -> 0 | J10: =H10*I10 -> 0 | L10: =+L9+0.01 -> 3.08 | M10: Depreciación Horaria Equipo de Taller | Q10: ( Ca ta x Kvr ) / Nv t | T10: 51622.49 | U10: =(('7,1Grafico'!G28*'7,1Grafico'!G21)/'7,1Grafico'!G29)/'2Maq'!B8 -> 0.13866667
A11: 1.2 | B11: LUBRICANTES Y FILTROS | H11: SUB TOTAL S/. | J11: =SUM(J12:J35) -> 0 | L11: =+L10+0.01 -> 3.09 | M11: Cetificación de equipos de Taller | P11: 1 | R11: =+C6*D6 -> 50000 | S11: =P11/R11 -> 2e-05 | T11: 12000 | U11: =S11*T11 -> 0.24
B12: ACEITE DE MOTOR | C12: ='3insumo'!C10 -> P15400500 | D12: EO15W40DH | E12: 9.25 | F12: gal. | G12: 250 | H12: =E12/G12 -> 0.037 | I12: ='3insumo'!G10 -> 0 | J12: =H12*I12 -> 0 | L12: =+L11+0.01 -> 3.1 | M12: Cartificación de la camioneta | P12: 1 | R12: =+C6*D6 -> 50000 | S12: =P12/R12 -> 2e-05 | T12: 300 | U12: =S12*T12 -> 0.006
B13: ACEITE CAJA DE MAQUINA DE GIRO | C13: ='3insumo'!C11 -> TO4300500 | D13: TO30 | E13: 4.36 | F13: gal. | G13: 1000 | H13: =E13/G13 -> 0.00436 | I13: ='3insumo'!G11 -> 0 | J13: =H13*I13 -> 0 | N13: SUB - TOTAL COSTO HORARIO (S/. / HORA ) = 1 + 3 | T13: S/. | U13: =U2+J8 -> 73.844905
B14: ACEITE TRAS CAJA DE MANDOS FINALES | C14: ='3insumo'!C11 -> TO4300500 | D14: TO30 | E14: 4.76 | F14: gal. | G14: 2000 | H14: =E14/G14 -> 0.00238 | I14: ='3insumo'!G11 -> 0 | J14: =H14*I14 -> 0 | L14: 4 | M14: COSTOS ADMINISTRATIVOS- TALLER MINA | S14: SUB TOTAL S/. | U14: =+(U15+U47+U68) -> 4.8103398
B15: ACEITE TRA CAJA DEL AMORTIGUADOR | C15: ='3insumo'!C11 -> TO4300500 | D15: TO30 | E15: 0.34 | F15: gal. | G15: 2000 | H15: =E15/G15 -> 0.00017 | I15: ='3insumo'!G11 -> 0 | J15: =H15*I15 -> 0 | L15: 4.1 | M15: PERSONAL ADMINISTRATIVO Y TALLER | U15: =SUM(U16:U46) -> 4.318434
B16: ACEITE SISTEMA HIDRAULICO | C16: ='3insumo'!C12 -> TO4100500 | D16: TO10 | E16: 49.67 | F16: gal. | G16: 5000 | H16: =E16/G16 -> 0.009934 | I16: ='3insumo'!F12 -> 0 | J16: =H16*I16 -> 0 | M16: Personal Administrativo Huaraz (3) | O16: Administración | P16: 3 | Q16: jornal | R16: =+$F$6*$C$6 -> 5000 | S16: =($P$16/$R$16) -> 0.0006 | T16: ='6SueAct'!H11 -> 0 | U16: =S16*T16 -> 0 | V16: Personal Administrativo Hz | Y16: =SUM(U16:U21) -> 0
B17: GRASA VARILLAJE DE PLUMA Y BRAZO | C17: 39W610 | D17: Pto.Engrase | E17: 1 | F17: kg. | G17: 100 | H17: =(E17/G17)+(E18/G18)+(E19/G19)+(E20/G20)+(E21/G21) -> 0.038 | I17: ='3insumo'!F16 -> 0 | J17: =H17*I17 -> 0 | M17: Derechos y obligaciones L. administativo Hz | Q17: D-OLA | T17: ='6SueAct'!H12 -> 0 | U17: =S16*T17 -> 0
B18: GRASA VARILLAJE CUCHARON | C18: 39W610 | D18: Pto.Engrase | E18: 1 | F18: kg. | G18: 100 | M18: Personal Directivos (3) (No esta considerado) | O18: Administración | P18: 0 | Q18: honorario | R18: =+$F$6*$C$6 -> 5000 | S18: =($P$18/$R$18) -> 0 | T18: =+'6SueAct'!H13 -> 0 | U18: =S18*T18 -> 0
B19: GRASA ACOPLAMIENTO RAPIDO | C19: 39W610 | D19: Pto.Engrase | E19: 1 | F19: kg. | G19: 100 | M19: Derechos obligaciones Directivos | Q19: D-OLD | T19: =+'6SueAct'!H14 -> 0 | U19: =S18*T19 -> 0
B20: GRASA COJINETE DE ROTACION | C20: SMOLY0400 | D20: Pto.Engrase | E20: 1 | F20: kg. | G20: 250 | M20: Personal Asesor Legal (1) (No esta considerado) | O20: Administración | P20: 0 | Q20: honorario | R20: =+$F$6*$C$6 -> 5000 | S20: =(P20/R20) -> 0 | T20: =+'6SueAct'!H15 -> 0 | U20: =S20*T20 -> 0
B21: GRASA ENGRANAJE DE ROTACION | C21: SMOLY0400 | D21: Pto.Engrase | E21: 1 | F21: kg. | G21: 250 | M21: Derechos obligaciones Laborales Asesor Legal | Q21: D-OLL | T21: =+'6SueAct'!H16 -> 0 | U21: =S20*T21 -> 0
B22: FILTRO DE AIRE (P) | C22: ='3insumo'!C19 -> 6001856110 | D22: KOMATSU | E22: 1 | F22: und. | G22: 500 | H22: =E22/G22 -> 0.002 | I22: ='3insumo'!G19 -> 0 | J22: =H22*I22 -> 0 | M22: Personal Administrativo Mina (2) | O22: Administración | P22: 2 | Q22: jornal | R22: =+$F$6*$C$6 -> 5000 | S22: =(P22/R22) -> 0.0004 | T22: ='6SueAct'!H17 -> 0 | U22: =S22*T22 -> 0 | V22: Personal Administrativo Mina | Y22: =SUM(U22:U25)+SUM(U40:U41) -> 0
B23: FILTRO DE AIRE (S) | C23: ='3insumo'!C20 -> 6001856120 | D23: =+D22 -> KOMATSU | E23: 1 | F23: und. | G23: 500 | H23: =E23/G23 -> 0.002 | I23: ='3insumo'!F20 -> 0 | J23: =H23*I23 -> 0 | M23: Derechos y obligaciones labor. administ. Mina | Q23: D-OLA | T23: ='6SueAct'!H18 -> 0 | U23: =S22*T23 -> 0
B24: FILTRO DE ACEITE DE MOTOR | C24: ='3insumo'!C21 -> 6742014540 | D24: =+D22 -> KOMATSU | E24: 1 | F24: und. | G24: 250 | H24: =E24/G24 -> 0.004 | I24: ='3insumo'!F21 -> 0 | J24: =H24*I24 -> 0 | M24: Personal de Seguridad (2) | O24: Administración | P24: 2 | Q24: jornal | R24: =+$F$6*$C$6 -> 5000 | S24: =(P24/R24) -> 0.0004 | T24: ='6SueAct'!H19 -> 0 | U24: =S24*T24 -> 0
B25: PRE FILTRO DE COMBUSTIBLE (P) | C25: ='3insumo'!C22 -> 6003193610 | D25: =+D22 -> KOMATSU | E25: 1 | F25: und. | G25: 250 | H25: =E25/G25 -> 0.004 | I25: ='3insumo'!F22 -> 0 | J25: =H25*I25 -> 0 | M25: Derechos y obligaciones labora. P.Seguridad | Q25: D-OLPS | T25: ='6SueAct'!H20 -> 0 | U25: =S24*T25 -> 0
B26: FILTRO DE COMBUSTIBLE (S) | C26: ='3insumo'!C23 -> 6754796140 | D26: =+D22 -> KOMATSU | E26: 1 | F26: und. | G26: 250 | H26: =E26/G26 -> 0.004 | I26: ='3insumo'!F23 -> 0 | J26: =H26*I26 -> 0 | M26: Personal de Mantenimiento (mecanicos) (2) | O26: Taller | P26: 2 | Q26: jornal | R26: =+$F$6*$C$6 -> 5000 | S26: =(P26/R26) -> 0.0004 | T26: ='6SueAct'!H21 -> 0 | U26: =S26*T26 -> 0 | V26: Personal Taller Mina | Y26: =SUM(U26:U41) -> 0
B27: FILTRO HIDRAULICO | C27: ='3insumo'!C27 -> 2076071182 | D27: =+D23 -> KOMATSU | E27: 1 | F27: und. | G27: 1000 | H27: =E27/G27 -> 0.001 | I27: ='3insumo'!F27 -> 0 | J27: =H27*I27 -> 0 | M27: Derechos y obligaciones labora. P.Mantenim. | Q27: D-OLPMM | T27: ='6SueAct'!H22 -> 0 | U27: =S26*T27 -> 0
B28: CARTUCHO o INHIBIDOR DE CORROSION | C28: ='3insumo'!C28 -> 6004111191 | D28: =+D22 -> KOMATSU | E28: 1 | F28: und. | G28: 1000 | H28: =E28/G28 -> 0.001 | I28: ='3insumo'!F28 -> 0 | J28: =H28*I28 -> 0 | M28: Personal de Apoyo Mantenimiento (2) | O28: Taller | P28: 2 | Q28: jornal | R28: =+$F$6*$C$6 -> 5000 | S28: =(P28/R28) -> 0.0004 | T28: ='6SueAct'!H23 -> 0 | U28: =S28*T28 -> 0
B29: FILTRO DE AIRE ACONDICIONADO RECIRCUL | C29: ='3insumo'!C24 -> 2089797620 | D29: =+D23 -> KOMATSU | E29: 1 | F29: und. | G29: =+D6 -> 5000 | H29: =E29/G29 -> 0.0002 | I29: ='3insumo'!F24 -> 0 | J29: =H29*I29 -> 0 | M29: Derechos y obligaciones labora. P.A.Manteni. | Q29: D-OLPa | T29: ='6SueAct'!H24 -> 0 | U29: =S28*T29 -> 0
B30: FILTRO DE AIRE ACONDICIONADO LIMPIO | C30: ='3insumo'!C25 -> 17M9113530 | D30: =+D24 -> KOMATSU | E30: 1 | F30: und. | G30: =G29 -> 5000 | H30: =E30/G30 -> 0.0002 | I30: ='3insumo'!F25 -> 0 | J30: =H30*I30 -> 0 | M30: Personal Mantenimiento Eléctrico (2) | O30: Taller | P30: 0 | Q30: jornal | R30: =+$F$6*$C$6 -> 5000 | S30: =(P30/R30) -> 0 | T30: =+'6SueAct'!H25 -> 0 | U30: =S30*T30 -> 0
B31: RESPIRADERO TANQUE HIDRAULICO | C31: ='3insumo'!C30 -> 20Y6021470 | D31: =+D22 -> KOMATSU | E31: 1 | F31: und. | G31: 500 | H31: =E31/G31 -> 0.002 | I31: ='3insumo'!F30 -> 0 | J31: =H31*I31 -> 0 | M31: Derechos y obligA. labora. P. Mantenimiento Eléctric | Q31: D-OLME | T31: ='6SueAct'!H26 -> 0 | U31: =S30*T31 -> 0
B32: RESPIRADERO ADICIONAL TANQUE HIDRAU | C32: ='3insumo'!C29 -> 2076051310 | D32: =+D22 -> KOMATSU | E32: 1 | F32: und. | G32: 500 | H32: =E32/G32 -> 0.002 | I32: ='3insumo'!F29 -> 0 | J32: =H32*I32 -> 0 | M32: Personal Soldador (2) | O32: Taller | P32: 2 | Q32: jornal | R32: =+$F$6*$C$6 -> 5000 | S32: =(P32/R32) -> 0.0004 | T32: ='6SueAct'!H27 -> 0 | U32: =S32*T32 -> 0
B33: REFRIGERANTE | C33: ='3insumo'!C42 -> 1400164H1 | D33: =+D22 -> KOMATSU | E33: 8.45 | F33: gal. | G33: 4000 | H33: =E33/G33 -> 0.0021125 | I33: ='3insumo'!F42 -> 0 | J33: =H33*I33 -> 0
B34: CORREA DE TRANSMISION | C34: =+'[2]AII insu'!C38 -> 0 | E34: 1 | F34: und. | G34: 6000 | H34: =E34/G34 -> 0.00016666667 | I34: ='3insumo'!F41 -> 0 | J34: =H34*I34 -> 0 | M34: Derechos y obligaciones laborales P.Soldador | T34: ='6SueAct'!H28 -> 0 | U34: =S32*T34 -> 0
B35: BATERIA DE 15 PLACAS 24 VOLTIOS | C35: 0 | E35: 2 | F35: und. | G35: 6000 | H35: =E35/G35 -> 0.00033333333 | I35: ='3insumo'!F43 -> 0 | J35: =H35*I35 -> 0 | Q35: D-OLS
A36: 1.3 | B36: ANALISIS DE ACEITE | H36: SUB TOTAL S/. | J36: =SUM(J37:J41) -> 0 | M36: Personal Almacen (2) | O36: Taller | P36: 2 | Q36: jornal | R36: =+$F$6*$C$6 -> 5000 | S36: =(P36/R36) -> 0.0004 | T36: ='6SueAct'!H29 -> 0 | U36: =S36*T36 -> 0
B37: DEL MOTOR | E37: 14 | F37: Muestras | G37: 2000 | H37: =E37/G37 -> 0.007 | I37: ='3insumo'!F45 -> 0 | J37: =I37*H37 -> 0 | M37: Derechos y obligaciones laborales P.Almacen | Q37: D-OLPA | T37: ='6SueAct'!H30 -> 0 | U37: =S36*T37 -> 0
B38: HIDRAULICO | E38: 3 | F38: Muestras | G38: 2000 | H38: =E38/G38 -> 0.0015 | I38: ='3insumo'!F46 -> 0 | J38: =I38*H38 -> 0 | M38: Personal Llantero (2) | O38: Taller | P38: 2 | Q38: jornal | R38: =+$F$6*$C$6 -> 5000 | S38: =(P38/R38) -> 0.0004 | T38: ='6SueAct'!H31 -> 0 | U38: =S38*T38 -> 0
B39: DE ROTACION | E39: 3 | F39: Muestras | G39: 2000 | H39: =E39/G39 -> 0.0015 | I39: ='3insumo'!F47 -> 0 | J39: =I39*H39 -> 0 | M39: Derechos y obligaciones laborales P.Llantero | Q39: D-OLPA | T39: ='6SueAct'!H32 -> 0 | U39: =S38*T39 -> 0
B40: MANDOS FINALES | E40: 4 | F40: Muestras | G40: 2000 | H40: =E40/G40 -> 0.002 | I40: ='3insumo'!F48 -> 0 | J40: =I40*H40 -> 0 | M40: Personal Supervisor (4) | O40: Supervision | P40: 4 | Q40: jornal | R40: =+$F$6*$C$6 -> 5000 | S40: =(P40/R40) -> 0.0008 | T40: ='6SueAct'!H33 -> 0 | U40: =S40*T40 -> 0
B41: ANALISIS DEL FLUIDO REFRIGERANTE | E41: 4 | F41: Muestras | G41: 2000 | H41: =E41/G41 -> 0.002 | I41: ='3insumo'!F49 -> 0 | J41: =I41*H41 -> 0 | M41: Derechos y obligaciones laborales P.Super | Q41: D-OLPS | T41: ='6SueAct'!H34 -> 0 | U41: =S40*T41 -> 0
B42: TREN DE RODAMIENTO | H42: SUB TOTAL S/. | J42: =SUM(J43:J46) -> 15.1998 | M42: Atencion medica Yanacancha | O42: Personla de | P42: =SUM(P22:P41)/2 -> 9 | Q42: ATM | R42: =+R22 -> 5000 | S42: =(P42/R42) -> 0.0018 | T42: ='6SueAct'!H35 -> 657.72 | U42: =S42*T42 -> 1.183896
B43: Impacto | E43: 0.2 | F43: factor | G43: =(E43+E44+E45)*E46 -> 5.17 | H43: 1 | I43: =G43*H6 -> 15.1998 | J43: =H43*I43 -> 15.1998 | M43: Alimentación, Hospedaje, Lavandería | O43: Turno | Q43: AHLav | T43: ='6SueAct'!H36 -> 301.41 | U43: =S42*T43 -> 0.542538
B44: Abrasividad | E44: 0.4 | F44: factor | M44: Pasaporte medico | O44: seguro | P44: =SUM(P22:P41) -> 18 | Q44: PSME | R44: =+R22*E6 -> 50000 | S44: =(P44/R44) -> 0.00036 | T44: ='6SueAct'!H37 -> 3600 | U44: =S44*T44 -> 1.296
B45: Factor z | E45: 0.5 | F45: factor | M45: EPS (Costo Seguro, proporcionado por Ango Raju) | O45: Personal | Q45: EPS | T45: ='6SueAct'!H38 -> 3600 | U45: =S44*T45 -> 1.296
B46: Factor básico | E46: 4.7 | F46: $/hr.-maq.
A47: 1.4 | B47: ELEMENTOS DE DESGASTE | H47: SUB TOTAL S/. | J47: =SUM(J48:J52) -> 0 | L47: 4.2 | M47: EQUIPOS DE PROTECCION PERSONAL ADMINISTRACION Y TALLER | S47: SUB TOTAL S/. | U47: =SUM(U48:U67)/C6 -> 0.0204568
B48: Punta roquera (Hensley) | C48: ='3insumo'!C32 -> HLK30RP2 | D48: desgaste | E48: 6 | G48: 8000 | H48: =E48/G48 -> 0.00075 | I48: ='3insumo'!F32 -> 0 | J48: =I48*H48 -> 0 | M48: Casco | O48: Seguridad | P48: =+'1Planilla'!$C$68+'1Planilla'!$C$69 -> 0 | Q48: und | R48: =((I6+J6)*G6*E6)/2 -> 2500 | S48: =P48/R48 -> 0 | T48: =+'5 EPP'!H11 -> 33.61 | U48: =S48*T48 -> 0
B49: Pasador de uñas (Lock) | C49: ='3insumo'!C33 -> HLKP30C | D49: =+D48 -> desgaste | E49: 5 | G49: =+G48 -> 8000 | H49: =E49/G49 -> 0.000625 | I49: ='3insumo'!F33 -> 0 | J49: =I49*H49 -> 0 | M49: Zapatos | O49: =+O48 -> Seguridad | P49: =+'1Planilla'!$C$68+'1Planilla'!$C$69 -> 0 | Q49: und | R49: =+R48 -> 2500 | S49: =P49/R49 -> 0 | T49: =+'5 EPP'!H12 -> 79.83 | U49: =S49*T49 -> 0
B50: Cuchilla Lateral (Hensley) | C50: ='3insumo'!C34 -> HLSCB330SO | D50: =+D49 -> desgaste | E50: 2 | G50: =+G48 -> 8000 | H50: =E50/G50 -> 0.00025 | I50: ='3insumo'!F34 -> 0 | J50: =I50*H50 -> 0 | M50: Lentes Oscuros | O50: =+O48 -> Seguridad | P50: =+'1Planilla'!$C$68+'1Planilla'!$C$69 -> 0 | Q50: und | R50: =+R48 -> 2500 | S50: =P50/R50 -> 0 | T50: =+'5 EPP'!H13 -> 12.61 | U50: =S50*T50 -> 0
B51: Pernos y tuerca (kit) | C51: ='3insumo'!C37 -> 2073205061 | D51: unión | E51: 6 | G51: =+G48 -> 8000 | H51: =E51/G51 -> 0.00075 | I51: ='3insumo'!F37 -> 0 | J51: =I51*H51 -> 0 | M51: Lentes Transparentes | O51: =+O48 -> Seguridad | P51: =+'1Planilla'!$C$68+'1Planilla'!$C$69 -> 0 | Q51: und | R51: =+R48 -> 2500 | S51: =P51/R51 -> 0 | T51: =+'5 EPP'!H14 -> 12.61 | U51: =S51*T51 -> 0
B52: Tuercas | C52: ='3insumo'!C35 -> 25531R1 | D52: unión | E52: 6 | G52: =+G48 -> 8000 | H52: =E52/G52 -> 0.00075 | I52: ='3insumo'!F38 -> 0 | J52: =I52*H52 -> 0 | M52: Guantes de Cuero | O52: =+O48 -> Seguridad | P52: =+'1Planilla'!$C$68+'1Planilla'!$C$69 -> 0 | Q52: und | R52: =+R48 -> 2500 | S52: =P52/R52 -> 0 | T52: =+'5 EPP'!H15 -> 9.66 | U52: =S52*T52 -> 0
A53: 1.5 | B53: RESERVA PARA REPARACIONES | H53: SUB TOTAL S/. | J53: =SUM(J54:J55) -> 7.1070417 | M53: Implementos para botiquin de equipos | O53: =+O48 -> Seguridad | P53: 2 | Q53: und | R53: =+R48 -> 2500 | S53: =P53/R53 -> 0.0008 | T53: =+'5 EPP'!H17 -> 40 | U53: =S53*T53 -> 0.032
B54: Repuestos (*) | D54: Overhaul | E54: 1 | F54: Global | G54: 15000 | H54: =E54/G54 -> 6.6666667e-05 | I54: =10%*'7,1Grafico'!G20 -> 85284.5 | J54: =H54*I54 -> 5.6856333 | M54: Chalecos tela importada dril | O54: =+O53 -> Seguridad | P54: =+'1Planilla'!$C$68+'1Planilla'!$C$69 -> 0 | Q54: und | R54: =+R48 -> 2500 | S54: =P54/R54 -> 0 | T54: =+'5 EPP'!H18 -> 25.21 | U54: =S54*T54 -> 0
B55: Mano de Obra | G55: 25% repuestos | H55: 0.25 | J55: =J54*H55 -> 1.4214083 | M55: Overol impermeable termico | O55: =+O53 -> Seguridad | P55: =+'5 EPP'!D19 -> 0 | Q55: und | R55: =+R48 -> 2500 | S55: =P55/R55 -> 0 | T55: =+'5 EPP'!H19 -> 117.65 | U55: =S55*T55 -> 0
A56: 1.6 | B56: PERSONAL OPERATIVO SALARIOS Y DERECHOS LABORALES | H56: SUB TOTAL S/. | J56: =SUM(J57:J62) -> 2.13256 | M56: Overol de tela con cinta reflectivo | O56: =+O53 -> Seguridad | P56: =+'1Planilla'!$C$68+'1Planilla'!$C$69 -> 0 | Q56: und | R56: =+R48 -> 2500 | S56: =P56/R56 -> 0 | T56: =+'5 EPP'!H20 -> 46.22 | U56: =S56*T56 -> 0
B57: Operador | D57: Operación | E57: =+'6SueAct'!D40 -> 4 | F57: jornal | G57: 500 | H57: =E57/G57 -> 0.008 | I57: ='6SueAct'!H40 -> 0 | J57: =H57*I57 -> 0 | M57: Tapa oido | O57: =+O53 -> Seguridad | P57: =+'1Planilla'!$C$68+'1Planilla'!$C$69 -> 0 | Q57: und | R57: =+R48 -> 2500 | S57: =P57/R57 -> 0 | T57: =+'5 EPP'!H21 -> 3 | U57: =S57*T57 -> 0
B58: Derechos y obligaciones laborales operador | D58: =+D57 -> Operación | F58: D-OLOx | I58: =+'6SueAct'!H41 -> 0 | J58: =H57*I58 -> 0 | M58: Mascarilla | O58: =+O53 -> Seguridad | P58: =+'1Planilla'!C69 -> 0 | Q58: und | R58: =+R48 -> 2500 | S58: =P58/R58 -> 0 | T58: =+'5 EPP'!H33 -> 3 | U58: =S58*T58 -> 0
B59: Atención Médica en Yanacancha | D59: =+D57 -> Operación | E59: =+'6SueAct'!D42 -> 2 | F59: ATM | H59: =E59/G57 -> 0.004 | I59: =+'6SueAct'!H42 -> 146.16 | J59: =H59*I59 -> 0.58464 | M59: Pantalon de cuero | O59: Seguridad | P59: 1 | Q59: und | R59: =+R48 -> 2500 | S59: =P59/R59 -> 0.0004 | T59: =+'5 EPP'!H34 -> 66.39 | U59: =S59*T59 -> 0.026556
B60: Alimentación, Hospedaje, Lavandería | D60: =+D57 -> Operación | F60: AHLav | I60: =+'6SueAct'!H43 -> 66.98 | J60: =H59*I60 -> 0.26792 | M60: Casaca de cuero | O60: =+O59 -> Seguridad | P60: 1 | Q60: und | R60: =+R48 -> 2500 | S60: =P60/R60 -> 0.0004 | T60: =+'5 EPP'!H35 -> 71.43 | U60: =S60*T60 -> 0.028572
B61: EPS (Seguro) | D61: =+D57 -> Operación | E61: =+'6SueAct'!D44 -> 4 | F61: EPS | G61: 5000 | H61: =E57/G61 -> 0.0008 | I61: =+'6SueAct'!N37*E61 -> 800 | J61: =H61*I61 -> 0.64 | M61: Escarpin de cuero | O61: =+O59 -> Seguridad | P61: 2 | Q61: par | R61: =+R52 -> 2500 | S61: =P61/R61 -> 0.0008 | T61: =+'5 EPP'!H36 -> 15 | U61: =S61*T61 -> 0.012
B62: Pasaporte Médico | D62: Operación | F62: PSME | I62: =+'6SueAct'!N37*E61 -> 800 | J62: =H61*I62 -> 0.64 | M62: Mandil soldador | O62: =+O59 -> Seguridad | P62: 2 | Q62: und | R62: =+R52 -> 2500 | S62: =P62/R62 -> 0.0008 | T62: =+'5 EPP'!H37 -> 25.21 | U62: =S62*T62 -> 0.020168
A63: 1.7 | B63: EQUIPOS DE PROTECCION PERSONAL OPERADORES MINA | H63: SUB TOTAL S/. | J63: =SUM(J64:J74) -> 0.576096 | M63: Capuchon para soldar | O63: =+O59 -> Seguridad | P63: 2 | Q63: und | R63: =+R52 -> 2500 | S63: =P63/R63 -> 0.0008 | T63: =+'5 EPP'!H38 -> 21.85 | U63: =S63*T63 -> 0.01748
B64: Casco | D64: Seguridad | E64: =+E57 -> 4 | F64: und | G64: =((I6+J6)*G6*E6)/2 -> 2500 | H64: =E64/G64 -> 0.0016 | I64: =+'5 EPP'!H23 -> 33.61 | J64: =H64*I64 -> 0.053776 | M64: Careta para esmerilar | O64: =+O59 -> Seguridad | P64: 1 | Q64: und | R64: =+R52 -> 2500 | S64: =P64/R64 -> 0.0004 | T64: =+'5 EPP'!H39 -> 35 | U64: =S64*T64 -> 0.014
B65: Zapatos | D65: =+D64 -> Seguridad | E65: =+$E$57 -> 4 | F65: und | G65: =G64 -> 2500 | H65: =E65/G65 -> 0.0016 | I65: =+'5 EPP'!H24 -> 79.83 | J65: =H65*I65 -> 0.127728 | M65: Careta de soldador | O65: =+O64 -> Seguridad | P65: 1 | Q65: und | R65: =+R52 -> 2500 | S65: =P65/R65 -> 0.0004 | T65: =+'5 EPP'!H40 -> 50 | U65: =S65*T65 -> 0.02
B66: Lentes Oscuros | D66: =+D64 -> Seguridad | E66: =+$E$57 -> 4 | F66: und | G66: =+G64 -> 2500 | H66: =E66/G66 -> 0.0016 | I66: =+'5 EPP'!H25 -> 12.61 | J66: =H66*I66 -> 0.020176 | M66: Mascarilla para soldador | O66: =+O65 -> Seguridad | P66: 2 | Q66: und | R66: =+R52 -> 2500 | S66: =P66/R66 -> 0.0008 | T66: =+'5 EPP'!H41 -> 23.75 | U66: =S66*T66 -> 0.019
B67: Lentes Transparentes | D67: =+D64 -> Seguridad | E67: =+$E$57 -> 4 | F67: und | G67: =+G64 -> 2500 | H67: =E67/G67 -> 0.0016 | I67: =+'5 EPP'!H26 -> 12.61 | J67: =H67*I67 -> 0.020176 | M67: Guantes de cuero para soldar | O67: =+O64 -> Seguridad | P67: 2 | Q67: und | R67: =+R52 -> 2500 | S67: =P67/R67 -> 0.0008 | T67: =+'5 EPP'!H42 -> 18.49 | U67: =S67*T67 -> 0.014792
B68: Guantes de Cuero | D68: =+D64 -> Seguridad | E68: =+$E$57 -> 4 | F68: und | G68: =+G64 -> 2500 | H68: =E68/G68 -> 0.0016 | I68: =+'5 EPP'!H27 -> 9.66 | J68: =H68*I68 -> 0.015456 | L68: 4.3 | M68: CAMIONETAS ALQUILADA | S68: SUB TOTAL S/. | U68: =SUM(U69:U71) -> 0.47144904
B69: Guantes de Operador | D69: =+D64 -> Seguridad | E69: =+$E$57 -> 4 | F69: und | G69: =+G64 -> 2500 | H69: =E69/G69 -> 0.0016 | I69: ='[3]AV EPP 20hr'!H16 -> 9.66 | J69: =H69*I69 -> 0.015456 | M69: Equipamiento de la camioneta | O69: Movilidad | P69: 1 | Q69: und | R69: =(I6+J6)*G6*E6 -> 5000 | S69: =P69/R69 -> 0.0002 | T69: 1500 | U69: =S69*T69 -> 0.3
B70: Implementos para botiquin de equipos | D70: =+D64 -> Seguridad | E70: 1 | F70: und | G70: =+G64 -> 2500 | H70: =E70/G70 -> 0.0004 | I70: =+'5 EPP'!H28 -> 40 | J70: =H70*I70 -> 0.016 | M70: Curso MD fuera de mina | O70: Movilidad | P70: 1 | Q70: und | R70: =+R69 -> 5000 | S70: =P70/R70 -> 0.0002 | T70: 636.7452 | U70: =S70*T70 -> 0.12734904
B71: Chalecos tela importada dril | D71: =+D70 -> Seguridad | E71: =+$E$57 -> 4 | F71: und | G71: =+G64 -> 2500 | H71: =E71/G71 -> 0.0016 | I71: =+'5 EPP'!H29 -> 25.21 | J71: =H71*I71 -> 0.040336 | M71: Toyota Hilux 4x4 (hr. - maq. / Total) | O71: Movilidad | P71: 1 | Q71: año | R71: =+R69 -> 5000 | S71: =P71/R71 -> 0.0002 | T71: =Y84*H6 -> 220.5 | U71: =S71*T71 -> 0.0441
B72: Overol impermeable termico | D72: =+D70 -> Seguridad | E72: =+$E$57 -> 4 | F72: und | G72: =+G64 -> 2500 | H72: =E72/G72 -> 0.0016 | I72: =+'5 EPP'!H30 -> 117.65 | J72: =H72*I72 -> 0.18824 | M72: RESUMEN DE COSTOS DE MAQUINARIA-UTILIDAD HORARIA | V72: =SUM(S48:S67) -> 0.0064 | W72: =SUM(T48:T67) -> 710.52
B73: Overol de tela con cinta reflectiva | D73: =+D70 -> Seguridad | E73: =+$E$57 -> 4 | F73: und | G73: =+G64 -> 2500 | H73: =E73/G73 -> 0.0016 | I73: =+'5 EPP'!H31 -> 46.22 | J73: =H73*I73 -> 0.073952 | L73: 1+2 | M73: COSTO DE OPERACIÓN HORARIA | S73: SUB TOTAL S/. | U73: =J8 -> 25.593098
B74: Tapa oido | D74: =+D70 -> Seguridad | E74: =+$E$57 -> 4 | F74: und | G74: =+G64 -> 2500 | H74: =E74/G74 -> 0.0016 | I74: =+'5 EPP'!H32 -> 3 | J74: =H74*I74 -> 0.0048 | L74: 3 | M74: COSTO DE POSESION HORARIA | S74: SUB TOTAL S/. | U74: =U2 -> 48.251807
A75: 1.8 | B75: GASTOS CAPACITACION Y CERTIFICACION | H75: SUB TOTAL S/. | J75: =SUM(J76:J77)/E76 -> 0.1776 | L75: 4 | M75: PERSONAL ADMINISTRATIVO Y TALLER MINA HORARIA | S75: SUB TOTAL S/. | U75: =U14 -> 4.8103398
B76: Capacitación y Certificación operarios excavadora | D76: Vehículo | E76: 4 | F76: capacitación | G76: =(I6+J6)*G6*E6 -> 5000 | H76: =E76/G76 -> 0.0008 | I76: 588 | J76: =H76*I76 -> 0.4704 | L76: 5 | M76: GASTOS ADMINISTRATIVOS 5% DE COSTOS 1 + 2 + 3 + 4 | Q76: 0.05 | R76: =SUM(U73:U75) -> 78.655245 | S76: SUB TOTAL S/. | U76: =R76*Q76 -> 3.9327622
B77: Viaticos para la capacitación | D77: =+D76 -> Vehículo | F77: viaticos | H77: =E76/G76 -> 0.0008 | I77: 300 | J77: =H77*I77 -> 0.24 | P77: TOTAL COSTO HORARIO (S/. ÷ HORA ) = 1 + 2 + 3 + 4 | U77: =SUM(U73:U76) -> 82.588007
A78: 1.9 | B78: COSTO DE TRASLADOS DE INSUMOS LIMA - MINA | H78: SUB TOTAL S/. | J78: =SUM(J79) -> 0 | N78: A considerar si no participara en las utilidades anuales UTILIDAD = | T78: 0.05 | U78: =U77*T78 -> 4.1294004
B79: Filtros, lubricantes, carrileria | E79: ='4Trans'!F49 -> 5909.66 | F79: Kg/hr. | G79: 9000 | J79: ='4Trans'!F42 -> 0 | N79: TOTAL FACTURACION HORA / MAQUINA S/. = | T79: =SUM(U77:U78) -> 86.717407
A80: 2 | B80: SERVICIOS Y EQUIPAMIENTOS | H80: SUB TOTAL S/. | J80: =SUM(J81:J82) -> 0.4 | N80: TOTAL FACTURACION HORA / MAQUINA $ = | T80: =+T79/H6 -> 29.495717
A81: 2.1 | B81: Servicios de terceros | E81: 1 | F81: SER TER | G81: =+$D$6 -> 5000 | H81: =E81/G81 -> 0.0002 | I81: 1500 | J81: =H81*I81 -> 0.3
A82: 2.2 | B82: Equipamiento de la excavadora | E82: 1 | F82: EQPV | G82: =+$D$6 -> 5000 | H82: =E82/G82 -> 0.0002 | I82: 500 | J82: =H82*I82 -> 0.1
L83: =SUM(J57:J58) -> 0
W84: Costo alquiler camioneta | Y84: 75

Sheet 7,1Grafico
A1: ESTADISTICA COSTO HORARIO VIGENTE
A2: EXCAVADORA KOMATSU PC300-LC8
A4: Descripción | C4: % | D4: S/.
A5: COSTO DE OPERACIÓN HORARIA | C5: =D5/$D$10 -> 0.29513218 | D5: ='7chrFM'!U73 -> 25.593098
A6: COSTO DE POSESION HORARIA | C6: =D6/$D$10 -> 0.55642585 | D6: ='7chrFM'!U74 -> 48.251807
A7: PERSONAL ADMINISTRATIVO Y TALLER MINA HORARIA | C7: =D7/$D$10 -> 0.055471444 | D7: ='7chrFM'!U75 -> 4.8103398
A8: COSTO ADMINISTRATIVO 5% DE COSTOS 1 + 2 + 3 + 4 | C8: =D8/$D$10 -> 0.045351474 | D8: ='7chrFM'!U76 -> 3.9327622
A9: UTILIDAD | C9: 0.05 | D9: =SUM(D5:D8)*C9 -> 4.1294004
A10: TOTAL FACTURADO SIN EL IGV | D10: =SUM(D5:D9) -> 86.717407
M11: =155.09-33.53 -> 121.56
M12: =M11*0.05 -> 6.078
M13: =SUM(M11:M12) -> 127.638
M14: =+M13*1.05 -> 134.0199
B18: DATOS UTILIZADOS
B19: RUBRO | C19: SIMBOLO | E19: RANGO | G19: VALOR UTILIZADO
B20: Costo Actual de Maquinaria | C20: Ca (volquete) | G20: =+O28 -> 852845 | N20: =(G20*G22)/(200*G24) -> 0.0852845
B21: Coeficiente de Valor residual | C21: Kvr | E21: 0.80 - 0.90 | G21: 0.8
B22: Interes horario de inversión de capital inv. | C22: i ( % ) | E22: 04 - 10 | G22: 0.1 | M22: 0.1
B23: Vida útil Excavadora (hr) | C23: Nv (excavadora) | E23: 8,000 - 16,000 | G23: 15000 | K23: 3 | L23: 1 | M23: =SUM(K23:L23) -> 4
B24: Uso anual (hr) | C24: Na (excavadora) | E24: 5,200 - 7,000 | G24: =+'7chrFM'!D6 -> 5000
B25: Costo Actual Camioneta | C25: Cac (4X4 2D) | G25: 102900
B26: Vida útil Camioneta (hr) | C26: Nvc (camioneta) | E26: 15,000 - 20,000 | G26: 18000 | N26: T:C: Mina | O26: 2.94
B27: Uso anual (hr) camioneta | C27: Nac (camioneta) | E27: 1,500 - 4,000 | G27: 4000 | N27: T:C: compra | O27: 2.891
B28: Equipo de Taller | C28: Ca (taller) | G28: 52000 | L28: 295000 | M28: 1 | N28: =L28*M28 -> 295000 | O28: =N28*O27 -> 852845
B29: Vida Util (hr) taller | C29: Nv (taller) | E29: 15,000- 30,600 | G29: 30000 | L29: 295000 | M29: 1.19 | N29: =L29*M29 -> 351050 | O29: =N29*O27 -> 1014885.6
L30: 295000 | M30: 1.19 | N30: =L30*M30 -> 351050 | O30: =N30*O26 -> 1032087
B31: (N+1) x V x i x N = 3+1 x 1'032,087.00 x 10% x 3 | C31: 4 x 309626,1 | E31: 4 x 309626,1 | G31: =M23*C35/E32 -> 170569
B32: 2N 2 * 3 | C32: =2*K23 -> 6 | E32: =+C32 -> 6 | I32: =G31/G33 -> 11.371267
A33: I = | B33: Ve hrs 15,000 | C33: =+G23 -> 15000 | E33: =+C33 -> 15000 | G33: =+E33 -> 15000
C35: =G20*M22*K23 -> 255853.5
D38: =1032085*0.1*3*4/6/15000 -> 13.761133

Sheet Costo Horario NL12
A1: ESTRUCTURA DE COSTO HORARIO MAQUINARIA PESADA
A2: CAMION VOLQUETE MARCA VOLVO MODELOS: FM12-440
A3: COSTO DE OPERACIÓN HORARIA MAQUINA SECA DEL VOLQUETE EN SOLES (S/.) ( hr - Maq.)
A4: DESCRIPCION | E4: PRODUCTO | F4: RENDIMIENTO PROMEDIO | G4: CONSUMO | H4: PRECIO | I4: COSTO REAL
G5: POR HORA | H5: UNIT S/. | I5: Soles / Hora
A6: 1 | B6: COSTO DE OPERACIÓN HORARIA | I6: =SUM(I7,I9,I30,I36,I41,I44,I51,I64) -> 48.918347
A7: 1.1 | B7: COMBUSTIBLE | G7: SUB TOTAL S/. | I7: =SUM(I8) -> 0
B8: Consumo = 0.0325 x Gal / H x BHP | E8: DIESEL 2 | F8: 4,5 gal. x hr-maq. | G8: 4.5 | H8: 0 | I8: =G8*H8 -> 0
A9: 1.2 | B9: LUBRICANTES Y FILTROS | G9: SUB TOTAL S/. | I9: =SUM(I10:I29) -> 5.8867643
B10: ACEITE MOTOR | D10: 85102465 | E10: VDS-3 15W40 | F10: 10 gal. x 600 hr.-maq. | G10: =10/500 -> 0.02 | H10: 43.51 | I10: =G10*H10 -> 0.8702
B11: FILTRO DE ACEITE | D11: 478736 | E11: Volvo | F11: 2 und. x 600 hr.-maq. | G11: =2/500 -> 0.004 | H11: 39.45 | I11: =G11*H11 -> 0.1578
B12: FILTRO DE COMBUSTIBLE | D12: 20972293 | E12: Volvo | F12: 2 und. x 600 hr.-maq. | G12: =1/500 -> 0.002 | H12: 30 | I12: =G12*H12 -> 0.06
B13: FILTRO SEPARADOR DE AGUA | D13: 20879812 | E13: Volvo | F13: 1 und. x 600 hr.-maq. | G13: =1/500 -> 0.002 | H13: 112.35 | I13: =G13*H13 -> 0.2247
B14: FILTRO DE AIRE PRIMARIO | D14: 8149064 | E14: Volvo | F14: 1 und. x 600 hr.-maq. | G14: =1/500 -> 0.002 | H14: 365.3 | I14: =G14*H14 -> 0.7306
B15: FILTRO DE AIRE SECUNDARIO | E15: Volvo | F15: 1 und x 1800 hr.-maq. | G15: 0.00055555556 | H15: 224.5 | I15: =H15*G15 -> 0.12472222
B16: ACEITE DE CAJA DE C AMBIOS | D16: 1161280 | E16: SAE 80W/90 | F16: 4 gal. x 1800 hr.-maq. | G16: =4/2000 -> 0.002 | H16: 32.77 | I16: =G16*H16 -> 0.06554
B17: ACEITE CORONA Y CUBOS REDUCTORES | D17: 1161279 | E17: API GL5 SAE 85W140 | F17: 10 gal. x 1800 hr.-maq. | G17: =10/2000 -> 0.005 | H17: 32.77 | I17: =G17*H17 -> 0.16385
B18: FILTRO DE DIRECCION HIDRAULICA | D18: 20580233 | E18: Volvo | F18: 1 und. x 600 hr.-maq. | G18: =1/500 -> 0.002 | H18: 22.17 | I18: =G18*H18 -> 0.04434
B19: ACEITE DE DIRECCION HIDRAULICA | D19: 1161997 | E19: ATF Dexron II | F19: 2gal. x 1800 hr.-maq. | G19: =2/2000 -> 0.001 | H19: 60 | I19: =G19*H19 -> 0.06
B20: FILTRO DEL SISTEMA HIDRAULICO | F20: 1 und. x 600 hr.-maq. | G20: =1/500 -> 0.002 | H20: 86.28 | I20: =G20*H20 -> 0.17256
B21: FILTRO SECADOR DE AIRE | D21: 20972915 | E21: Volvo | F21: 1 und x 600 hr.-maq. | G21: =1/500 -> 0.002 | H21: 138.66 | I21: =G21*H21 -> 0.27732
B22: LIQUIDO DE EMBRAGUE | D22: 85112077 | E22: DOT 4 | F22: 1 x 1800 hr.-maq. | G22: =1/2000 -> 0.0005 | H22: 66.62 | I22: =G22*H22 -> 0.03331
B23: ACEITE HIDRAULICO DE LEVANTE DE TOLVA | E23: SAE 30 | F23: 14 gal. x 1800 hr.-maq | G23: =14/2000 -> 0.007 | H23: 32.77 | I23: =G23*H23 -> 0.22939
B24: COMPRESOR DE AIRE | D24: 20701801 | E24: Volvo | F24: 1 kit x 1800 hr.-maq | G24: =1/2000 -> 0.0005 | H24: 2610 | I24: =G24*H24 -> 1.305
B25: GRASA PARA LUBRICACION DE CHASIS/ ARBOL DE TRANSMISION | D25: 1161962 | E25: EP NLGI Nº 2 | F25: 20 kg. x 500 hr.-maq. | G25: =20/500 -> 0.04 | H25: 23.78 | I25: =G25*H25 -> 0.9512
B26: CORREA DE POLEA Y VENTILADOR | D26: 20712530 | E26: Volvo | F26: 1 und. x 2000 hr.-maq | G26: =1/2000 -> 0.0005 | H26: 148.2642 | I26: =G26*H26 -> 0.0741321
B27: LIQUIDO REFRIGERANTE | D27: 1089240 | E27: Volvo Coolant Verde | F27: 11 gal. x 2000 hr.-maq | G27: =11/2000 -> 0.0055 | H27: 62.2 | I27: =G27*H27 -> 0.3421
A30: 1.3 | B30: ANALISIS DE ACEITE | G30: SUB TOTAL S/. | I30: =SUM(I31:I35) -> 0.42336
B31: ANALISIS DE ACEITE DE MOTOR | F31: 4 muestra x 2000 hr.-maq | G31: =4/2000 -> 0.002 | H31: =35.28*2 -> 70.56 | I31: =H31*G31 -> 0.14112
B32: ANALISIS DE ACEITE DE CAJA DE CAMBIOS | F32: 2 muestra x 2000 hr.-maq | G32: =2/2000 -> 0.001 | H32: =35.28*2 -> 70.56 | I32: =H32*G32 -> 0.07056
B33: ANALISIS DE ACEITE CORONA | F33: 2 muestra x 2000 hr.-maq | G33: =2/2000 -> 0.001 | H33: =35.28*2 -> 70.56 | I33: =H33*G33 -> 0.07056
B34: ANALISIS DE REFRIGERANTE | F34: 4 muestra x 2000 hr.-maq | G34: =4/2000 -> 0.002 | H34: =35.28*2 -> 70.56 | I34: =H34*G34 -> 0.14112
A36: 1.4 | B36: NEUMATICO | G36: SUB TOTAL S/. | I36: =SUM(I37:I40) -> 13.811467
B37: Neumático 12.00 x R20 Goodyear 9377 OTR | F37: 08 und. x 1,800 hr.-maq. | G37: =8/1800 -> 0.0044444444 | H37: 2446.08 | I37: =G37*H37 -> 10.871467
B38: Neumático 12.00 x R20 Rack | F38: 02 und. x 1,800 hr.-maq. | G38: =2/1800 -> 0.0011111111 | H38: 1808.1 | I38: =G38*H38 -> 2.009
B39: Camaras Goodyear 12.00 x R20 | F39: 10 und. x 1,800 hr.-maq. | G39: =10/1800 -> 0.0055555556 | H39: 114.66 | I39: =G39*H39 -> 0.637
B40: Protectores Goodyear 12.00 x R | F40: 10 und. x 1,800 hr.-maq. | G40: =10/1800 -> 0.0055555556 | H40: 52.92 | I40: =G40*H40 -> 0.294
A41: 1.5 | B41: RESERVA PARA REPARACIONES | G41: SUB TOTAL S/. | I41: =SUM(I42:I43) -> 5
B42: Repuestos (*) | F42: 1 kit. x 15000 hr.-maq. | G42: =1/15000 -> 6.6666667e-05 | H42: 60000 | I42: =G42*H42 -> 4
B43: Mano de Obra | F43: 25% repuestos | I43: =I42*0.25 -> 1
A44: 1.6 | B44: PERSONAL OPERATIVO | G44: SUB TOTAL S/. | I44: =SUM(I45:I50) -> 22.185178
B45: Operador | E45: Operación | F45: 4 jornal. x 600 hr.-maq. | G45: =4/600 -> 0.0066666667 | H45: 1800 | I45: =H45*G45 -> 12
B46: Derechos y obligaciones laborales operador | E46: =+E45 -> Operación | F46: 4 D-OLOx 600 hr.-maq. | G46: =4/600 -> 0.0066666667 | H46: 873.18 | I46: =H46*G46 -> 5.8212
B47: Viatico Chofer viaje Lima - Huaraz | E47: Operación | F47: 1 VCVLIH x 600 hr.-maq | G47: =1/600 -> 0.0016666667 | H47: 250 | I47: =H47*G47 -> 0.41666667
B48: Atención Médica en Yanacancha | E48: =+E45 -> Operación | F48: 4 ATM x 600 hr.-maq. | G48: =4/600 -> 0.0066666667 | H48: 73.08 | I48: =H48*G48 -> 0.4872
B49: Alimentación, Hospedaje, Lavandería | E49: =+E45 -> Operación | F49: 2 AHLav x 20 hr.-maq. | G49: =2/20 -> 0.1 | H49: 33.49 | I49: =H49*G49 -> 3.349
B50: Pasaporte Médico | E50: =+E45 -> Operación | F50: 4 PSME x 7,200 hr.-maq. | G50: =4/7200 -> 0.00055555556 | H50: 200 | I50: =G50*H50 -> 0.11111111
A51: 1.7 | B51: EQUIPOS DE PROTECCION PERSONAL | G51: SUB TOTAL S/. | I51: =SUM(I52:I63) -> 0.48324444
B52: Casco | E52: Seguridad | F52: 4 und. x 3,600 hr.-maq. | G52: =4/3600 -> 0.0011111111 | H52: 33.61 | I52: =G52*H52 -> 0.037344444
B53: Zapatos | E53: =+E52 -> Seguridad | F53: =+F52 -> 4 und. x 3,600 hr.-maq. | G53: =+G52 -> 0.0011111111 | H53: 79.83 | I53: =G53*H53 -> 0.0887
B54: Lentes Oscuros | E54: =+E52 -> Seguridad | F54: 8 und. x 3,600 hr.-maq. | G54: =8/3600 -> 0.0022222222 | H54: 12.61 | I54: =G54*H54 -> 0.028022222
B55: Lentes Transparentes | E55: =+E52 -> Seguridad | F55: 8 und. x 3,600 hr.-maq. | G55: =+G54 -> 0.0022222222 | H55: 12.61 | I55: =G55*H55 -> 0.028022222
B56: Guantes de Cuero | E56: =+E52 -> Seguridad | F56: 12 und. x 3,600 hr.-maq. | G56: =12/3600 -> 0.0033333333 | H56: 9.66 | I56: =G56*H56 -> 0.0322
B57: Guantes de Operador | E57: =+E52 -> Seguridad | F57: =+F56 -> 12 und. x 3,600 hr.-maq. | G57: =+G56 -> 0.0033333333 | H57: 9.66 | I57: =G57*H57 -> 0.0322
B58: Implementos para botiquin de equipos | E58: =+E52 -> Seguridad | F58: 1 und. x 3,600 hr.-maq. | G58: =1/3600 -> 0.00027777778 | H58: 40 | I58: =G58*H58 -> 0.011111111
B59: Chalecos tela importada dril | E59: =+E58 -> Seguridad | F59: =+F52 -> 4 und. x 3,600 hr.-maq. | G59: =+G52 -> 0.0011111111 | H59: 25.21 | I59: =G59*H59 -> 0.028011111
B60: Overol impermeable termico | E60: =+E58 -> Seguridad | F60: =+F52 -> 4 und. x 3,600 hr.-maq. | G60: =+G52 -> 0.0011111111 | H60: 117.65 | I60: =G60*H60 -> 0.13072222
B61: Overol de tela con cinta reflectivo | E61: =+E58 -> Seguridad | F61: =+F52 -> 4 und. x 3,600 hr.-maq. | G61: =+G52 -> 0.0011111111 | H61: 46.22 | I61: =G61*H61 -> 0.051355556
B62: Tapa oido | E62: =+E58 -> Seguridad | F62: 16 und. x 3,600 hr.-maq. | G62: =16/3600 -> 0.0044444444 | H62: 3 | I62: =G62*H62 -> 0.013333333
B63: Mascarilla | E63: =+E58 -> Seguridad | F63: =+F62 -> 16 und. x 3,600 hr.-maq. | G63: =+G62 -> 0.0044444444 | H63: 0.5 | I63: =G63*H63 -> 0.0022222222
A64: 1.8 | B64: GASTOS CAPACITACION Y CERTIFICACION | G64: SUB TOTAL S/. | I64: =SUM(I65:I67) -> 1.1283333
B65: Capacitación y Certificación operario camion | E65: Vehículo | F65: 4 capa.x 7,200 hr.-maq. | G65: =4/7200 -> 0.00055555556 | H65: =2.04*200 -> 408 | I65: =G65*H65 -> 0.22666667
B66: Viaticos para la capacitación | E66: =+E65 -> Vehículo | F66: 4 viata. x 7,200 hr.-maq. | G66: =+G65 -> 0.00055555556 | H66: 300 | I66: =G66*H66 -> 0.16666667
B67: Certificación de camion | E67: =+E65 -> Vehículo | F67: 01 cert .x 7,200 hr.-maq. | G67: =1/7200 -> 0.00013888889 | H67: =1800*2.94 -> 5292 | I67: =G67*H67 -> 0.735
A70: DESCRIPCION | E70: Valor | F70: RENDIMIENTO PROMEDIO | G70: FACTOR | H70: PRECIO | I70: COSTO REAL
G71: MENSUAL | H71: DIA S/. | I71: S/. / Hr.
A72: 2 | B72: COSTO DE POSESION | G72: SUB TOTAL S/. | I72: =SUM(I73:I80) -> 24.32791
A73: 2.1 | B73: Interes del Capital Invertido Volquete | F73: ( Cav ) x i / 200 Nav | H73: =I73*20 -> 0.0063636364 | I73: =(F88*F90)/(200*F92) -> 0.00031818182
A74: =+A73+0.1 -> 2.2 | B74: Depreciación Horaria Volquete | F74: ( Cav x Kvr ) / Nv v | H74: =((F88*F89)/F91)*20 -> 210 | I74: =(F88*F89)/F91 -> 10.5
A75: =+A74+0.1 -> 2.3 | B75: Depreciación Horaria Camioneta | F75: ( Cac x Kvr ) / Nv c | I75: =((F93*F89)/F94)/10 -> 0.42352941
A76: =+A75+0.1 -> 2.4 | B76: Interes del Capital Invertido Camioneta | F76: ( Cac ) x i / 200 Na c | I76: =(F93*F90)/(200*F95) -> 0.00018
A77: =+A76+0.1 -> 2.5 | B77: Depreciación Horaria Equipo de Taller | E77: 51622.49 | F77: ( Ca ta x Kvr ) / Nv t | I77: =(F96*F89)/F97 -> 1.966571
A78: =+A77+0.1 -> 2.6 | B78: Repuestos y accesorios | G78: 5044.29 | H78: =+G78/30 -> 168.143 | I78: =+H78/15 -> 11.209533
A79: =+A78+0.1 -> 2.7 | B79: Cetificación de equipos de Taller | E79: 12000 | G79: =+E79/120 -> 100 | H79: =+G79/30 -> 3.3333333 | I79: =+H79/15 -> 0.22222222
A80: =+A79+0.1 -> 2.8 | B80: Cartificación de la camioneta | E80: 300 | G80: =+E80/120 -> 2.5 | H80: =+G80/30 -> 0.083333333 | I80: =+H80/15 -> 0.0055555556
A81: SUB - TOTAL COSTO HORARIO (S/. / HORA ) = 1 + 2 | H81: S/. | I81: =I72+I6 -> 73.246256
A82: 3 | B82: IMPUESTO GENERAL A LAS VENTAS 19% DEL SUB TOTAL | H82: S/. | I82: =+I81*0.19 -> 13.916789
A83: TOTAL COSTO HORARIO (S/. ÷ HORA ) = 1 + 2 + 3 | H83: S/. | I83: =I81+I82 -> 87.163045
A85: DATOS UTILIZADOS
A86: RUBRO | D86: SIMBOLO | E86: RANGO | F86: VALOR
F87: UTIIZADO
A88: Costo Actual de Maquinaria | D88: Ca (volquete) | F88: 420000
A89: Coeficiente de Valor residual | D89: Kvr | E89: 0.80 - 0.90 | F89: 0.8
A90: Tasa de Interes anual Soles | D90: i ( % ) | E90: 05 - 10 | F90: 0.001
A91: Vida útil Volquete (hr) | D91: Nv (volquete) | E91: 8,000 - 32,000 | F91: 32000
A92: Uso anual (hr) | D92: Na (volquete) | E92: 5,200 - 7,200 | F92: 6600
A93: Costo Actual Camioneta | D93: Cac (camioneta) | F93: 90000
A94: Vida útil Camioneta (hr) | D94: Nvc (camioneta) | E94: 15,000 - 20,000 | F94: 17000
A95: Uso anual (hr) camioneta | D95: Nac (camioneta) | E95: 1,440 - 2,800 | F95: 2500
A96: Equipo de Taller | D96: Ca (taller) | F96: 51622.49
A97: Vida Util (hr) taller | D97: Nv (taller) | E97: 14,400- 21,600 | F97: 21000
A102: COSTOS ADMINISTRATIVOS- TALLER
A103: 1.7 | B103: PERSONAL ADMINISTRATIVO Y TALLER | G103: SUB TOTAL S/. | I103: =SUM(I104:I137)/10 -> 2.1138799
B104: Personal Administrativo Mina (2) | E104: mes | F104: 2 jornal. x 600 hr.-maq. | G104: =(2/600)/10 -> 0.00033333333 | H104: 3000 | I104: =G104*H104 -> 1
B105: Derechos y obligaciones laborales administ | E105: und | F105: 2 D-OLAx 600 hr.-maq. | G105: =(2/600)/10 -> 0.00033333333 | H105: 1455.3 | I105: =G105*H105 -> 0.4851
B106: Alimentación, Hospedaje, Lavandería | E106: día | F106: 1 AHLav x 20 hr.-maq. | G106: =(1/20)/10 -> 0.005 | H106: 33.49 | I106: =G106*H106 -> 0.16745
B107: Pasaporte Médico | E107: año | F107: 2 PSME x 7,200 hr.-maq. | G107: =(2/7200) -> 0.00027777778 | H107: 200 | I107: =G107*H107 -> 0.055555556
B108: Atención Médica en Yanacancha | E108: und. | F108: 2 ATM x 600 hr.-maq. | G108: =2/6000 -> 0.00033333333 | H108: 73.08 | I108: =G108*H108 -> 0.02436
B109: Personal Administrativo Huaraz (1) | E109: mes | F109: 1 jornal. x 600 hr.-maq. | G109: =(1/600)/10 -> 0.00016666667 | H109: 1120 | I109: =G109*H109 -> 0.18666667
B110: Derechos y obligaciones L. administ Hz | E110: und | F110: 1 D-OLAx 600 hr.-maq. | G110: =(1/600)/10 -> 0.00016666667 | H110: 543.31 | I110: =G110*H110 -> 0.090551667
...

Sheet Propuesto Costo Horario
