Workbook
Name N19ai19: MO!$O$21

Sheet ANALISIS RIESGOS
A1: MATRIZ DE RIESGOS Y OPORTUNIDADES
A3: Ítem | B3: Identificación | C3: ESPECIALIDAD | D3: Análisis | E3: Rubro | F3: Gravedad | G3: Monto S/. | H3: Amenazas | I3: Oportunidad | J3: Observaciones | K3: ESTATUS RO | L3: Responsable | M3: Soluciones
A4: 01 | B4: Debido a la modalidad del contrato (suma alzada): se tenga que ejecutar mayores prestaciones adicionales sin que necesariamente sean reconocidos por la Entidad. Mov. De Tierras | C4: MOV. DE TIERRAS | D4: Gestionar ante la Entidad adicionales y deductivos vinculantes, no obstante sean rechazados se deberá dejar antecedes para un posterior reconocimiento mediante la via que corresponda. | E4: METRADO | F4: MUY BAJA | G4: 15000 | H4: =+IF(G4>0,G4,0) -> 15000 | J4: Costo total que se podria presentar en cualquier momento | K4: No Considerado en RO | L4: Obra | M4: Elaboración del presupuesto compromiso con metrados reales lo que permitirá determinar la brecha entre lo considerado en el Expediente Técnico y lo realmente a ejecutar. | AE4: ALTA
A5: =+A4+1 -> 2 | B5: Debido a la modalidad del contrato (suma alzada): se tenga que ejecutar mayores prestaciones adicionales sin que necesariamente sean reconocidos por la Entidad. Estructuras | C5: ESTRUCTURAS | D5: Gestionar ante la Entidad adicionales y deductivos vinculantes, no obstante sean rechazados se deberá dejar antecedes para un posterior reconocimiento mediante la via que corresponda. | E5: METRADO | F5: MUY BAJA | G5: 25000 | H5: =+IF(G5>0,G5,0) -> 25000 | J5: Costo total que se podria presentar en cualquier momento | K5: No Considerado en RO | L5: Obra | M5: Elaboración del presupuesto compromiso con metrados reales lo que permitirá determinar la brecha entre lo considerado en el Expediente Técnico y lo realmente a ejecutar. | AE5: ALTA
A6: =+A5+1 -> 3 | B6: Adecuaciones | C6: GG | D6: Adecuaciones de instalaciones de obra. | E6: EXTERNO | F6: ALTA | G6: 5000 | H6: =+IF(G6>0,G6,0) -> 5000 | J6: Costo mensual que se podria considerar en el mes de octubre y noviembre | K6: Costo Considerado en RO | L6: Área legal | M6: Se solicita apoyo al área legal
A7: =+A6+1 -> 4 | B7: Paralizaciones varias,: gremios sindicales, paro de transportistas, etc. | C7: GG | D7: Costos Stand by asociados a paralizaciones | E7: EXTERNO | F7: MUY BAJA | G7: 5000 | H7: =+IF(G7>0,G7,0) -> 5000 | J7: Costo mensual que se podria presentar en cada mes de la obra | K7: No Considerado en RO | L7: Externo | M7: Se realizará una contingencia ante estos eventos días antes. Envío de comunicación ante la entidad comunicando evento.
A8: =+A7+1 -> 5 | B8: Alquiler de GE para suministro de energía de obra | C8: ELÉCTRICAS | D8: Se puede dar si se corta la Energia Eléctrica | E8: EXTERNO | F8: ALTA | G8: 3000 | H8: =+IF(G8>0,G8,0) -> 3000 | J8: Costo mensual de combustible y alquiler de GE por si se corta la energia electrica | K8: No Considerado en RO | L8: Area Legal | M8: Enviar costo de adicional a Entidad. Revisar contingencia de órganos de control de contratos, de revisar GE defintivos de acuerdo a rpta de entidad.
A9: =+A8+1 -> 6 | B9: Sobre costo de Agregados (Estructuras) | C9: ESTRUCTURAS | D9: Podria darse debido a la inaccesibilidad de la cantera actual por lluvias | E9: EXTERNO | F9: MUY BAJA | H9: =+IF(G9>0,G9,0) -> 0 | J9: Suministro de agregados en el mes de septiembre, podría ser un 20% al estimado inciialmente debido a la lejanía de las canteras | K9: No Considerado en RO | L9: Obra | M9: Encontrar proveedores con lleguen al costo considerando viaje puesto en obra.
A10: =+A9+1 -> 7 | F10: MUY BAJA | H10: =+IF(G10>0,G10,0) -> 0
A11: =+A10+1 -> 8 | F11: MUY BAJA | H11: =+IF(G11>0,G11,0) -> 0
G12: =SUM(G4:G11) -> 53000 | H12: =SUM(H4:H11) -> 53000 | I12: =SUM(I4:I11) -> 0
B19: Etiquetas de fila | C19: Suma de Amenazas | D19: Suma de Oportunidad
B20: METRADO | C20: 0
B21: PANDEMIA | C21: 0 | D21: 1958414.8
B22: PLAZO | D22: 3779808.1
B23: ALCANCE | C23: -7095143.5 | D23: 681215.99
B24: EXTERNO | C24: -210000
B25: SUPERVISION | C25: -1514650 | D25: 20586
B26: CONTRATO | C26: 0
B27: ENTIDAD | C27: -1087010.2
B28: INGENIERIA | C28: -3582801.2 | D28: 0
B29: Total general | C29: -13489605 | D29: 6440024.9

Sheet RG
B1: =CONCATENATE(B3," - ",B4," - ",B5," - ",B6) -> I.E.N 1182 - - EL BOSQUE - CERCO + INGRESOS Y CASETAS -
N2: =+YEAR(N5) -> 2024 | O2: =+YEAR(O5) -> 2024 | P2: =+YEAR(P5) -> 2025 | Q2: =+YEAR(Q5) -> 2025 | R2: =+YEAR(R5) -> 2025 | S2: =S5 -> 2025
B3: I.E.N 1182 | E3: ACUMULADO | G3: MES ENERO DEL 2025 | J3: ACUMULADO DEL 2024 | K3: ACUMULADO DE OBRA | L3: SALDO DE OBRA | N3: PROYECCIÓN | U3: AÑOS SIGUIENTES | Y3: TOTAL DE OBRA | AH3: Acum. del Ej. | AN3: TOTAL | AO3: MES DEL INFORME | AP3: ANTERIORES | AQ3: 45597 | AR3: 45627 | AS3: 45658 | AT3: 45689 | AU3: 45717
N4: 1 | O4: =+N4+1 -> 2 | P4: =+O4+1 -> 3 | Q4: =+P4+1 -> 4 | R4: =+Q4+1 -> 5 | S4: Saldo del Ejercicio
B5: EL BOSQUE - CERCO + INGRESOS Y CASETAS | E5: Años Anteriores | G5: Previsto | H5: Real | N5: 45597 | O5: =+N5+31 -> 45628 | P5: =+O5+31 -> 45659 | Q5: =+P5+31 -> 45690 | R5: =+Q5+31 -> 45721 | S5: 2025 | U5: =+S5+1 -> 2026 | V5: =+U5+1 -> 2027 | W5: =+V5+1 -> 2028 | Y5: RO con Venta Mejor Escenario | Z5: RO con Venta Aprobada a la Fecha | AA5: RO Sin Adicional Contractual aprobado + 20% ahorro en SC Instalaciones (IISS/IEE) | AB5: RO ABRIL Sin Adicional contractual aprobado | AC5: Anterior | AD5: Meta | AE5: Presupuesto Interno | AF5: Presupuesto | AH5: Anterior
B7: Venta Total Producida | E7: =+E9 -> #REF! | G7: =+G9 -> 0 | H7: =+H9 -> 0 | J7: =+J9 -> 0 | K7: =+K9 -> 0 | L7: =+L9 -> 0 | N7: =+N9 -> 0 | O7: =+O9 -> 0 | P7: =+P9 -> 0 | Q7: =+Q9 -> 0 | R7: =+R9 -> 0 | S7: =+S9 -> 0 | U7: =+U9 -> 0 | V7: =+V9 -> 0 | W7: =+W9 -> 0 | Y7: =+Y9 -> 1511228 | Z7: =+Z9 -> 0 | AA7: =+AA9 -> 0 | AB7: =+AB9 -> 0 | AC7: =+AC9 -> 0 | AD7: =+AD9 -> 0 | AE7: =+AE9 -> 0 | AF7: =+AF9 -> 0 | AH7: =+AH9 -> 0 | AJ7: =+AF7-Z7 -> 0 | AN7: =+AN9 -> 0 | AO7: =+AO9 -> 0 | AQ7: =+AQ9 -> 0 | AR7: =+AR9 -> 0 | AS7: =+AS9 -> 0 | AT7: =+AT9 -> 0 | AU7: =+AU9 -> 0
B9: Venta | E9: =+SUM(E11:E13) -> #REF! | G9: =+SUM(G11:G13) -> 0 | H9: =+SUM(H11:H13) -> 0 | J9: =+SUM(J11:J13) -> 0 | K9: =+SUM(K11:K13) -> 0 | L9: =+SUM(L11:L13) -> 0 | N9: =+SUM(N11:N13) -> 0 | O9: =+SUM(O11:O13) -> 0 | P9: =+SUM(P11:P13) -> 0 | Q9: =+SUM(Q11:Q13) -> 0 | R9: =+SUM(R11:R13) -> 0 | S9: =+SUM(S11:S13) -> 0 | U9: =+SUM(U11:U13) -> 0 | V9: =+SUM(V11:V13) -> 0 | W9: =+SUM(W11:W13) -> 0 | Y9: =+SUM(Y11:Y13) -> 1511228 | Z9: =+SUM(Z11:Z13) -> 0 | AA9: =+SUM(AA11:AA13) -> 0 | AB9: =+SUM(AB11:AB13) -> 0 | AC9: =+SUM(AC11:AC13) -> 0 | AD9: =+SUM(AD11:AD13) -> 0 | AE9: =+SUM(AE11:AE13) -> 0 | AF9: =+SUM(AF11:AF13) -> 0 | AH9: =+SUM(AH11:AH13) -> 0 | AJ9: =+AF9-Z9 -> 0 | AK9: =+Z9-AC9 -> 0 | AN9: =+SUM(AN11:AN13) -> 0 | AO9: =+SUM(AO11:AO13) -> 0 | AQ9: =+SUM(AQ11:AQ13) -> 0 | AR9: =+SUM(AR11:AR13) -> 0 | AS9: =+SUM(AS11:AS13) -> 0 | AT9: =+SUM(AT11:AT13) -> 0 | AU9: =+SUM(AU11:AU13) -> 0
B11: Valorización: Venta Directa - Contrato Principal | E11: =+'DIRECTO '!E11+#REF! -> #REF! | L11: =+SUM(N11:R11) -> 0 | S11: =+SUMIFS(N11:R11,N$2:R$2,$S$5) -> 0 | U11: =+SUMIFS(N11:S11,N$2:S$2,$U$5) -> 0 | V11: =+SUMIFS(N11:S11,N$2:S$2,$V$5) -> 0 | W11: =+SUMIFS(N11:S11,N$2:S$2,$W$5) -> 0 | Y11: =+Z11 -> 0 | Z11: =+K11+L11 -> 0 | AJ11: =+AF11-Z11 -> 0 | AK11: =+Z11-AC11 -> 0
B12: Valorización: Venta Indirecta - Contrato Principal | E12: =+'DIRECTO '!E12+#REF! -> #REF! | L12: =+SUM(N12:R12) -> 0 | S12: =+SUMIFS(N12:R12,N$2:R$2,$S$5) -> 0 | U12: =+SUMIFS(N12:S12,N$2:S$2,$U$5) -> 0 | V12: =+SUMIFS(N12:S12,N$2:S$2,$V$5) -> 0 | W12: =+SUMIFS(N12:S12,N$2:S$2,$W$5) -> 0 | Y12: =+Z12 -> 0 | Z12: =+K12+L12 -> 0 | AJ12: =+AF12-Z12 -> 0 | AK12: =+Z12-AC12 -> 0
B13: Otros | Y13: =1783249.01/1.18 -> 1511228
B15: Costo Total | E15: =+SUM(E17:E26)+E29 -> #REF! | G15: =+SUM(G17:G26,G29) -> #REF! | H15: =SUM(H17:H26,H29) -> #REF! | J15: =+SUM(J17:J26,J29) -> #REF! | K15: =+SUM(K17:K26,K29) -> #REF! | L15: =+SUM(L17:L26,L29) -> 0 | N15: =+SUM(N17:N26,N29) -> 0 | O15: =+SUM(O17:O26,O29) -> 0 | P15: =+SUM(P17:P26,P29) -> 0 | Q15: =+SUM(Q17:Q26,Q29) -> 0 | R15: =+SUM(R17:R26,R29) -> 0 | S15: =+SUM(S17:S26,S29) -> 0 | U15: =+SUM(U17:U26,U29) -> 0 | V15: =+SUM(V17:V26,V29) -> 0 | W15: =+SUM(W17:W26,W29) -> 0 | Y15: =+SUM(Y17:Y26,Y29) -> 0 | Z15: =+SUM(Z17:Z26,Z29) -> #REF! | AA15: =+SUM(AA17:AA26)-(#REF!+#REF!)+AA29+AA28 -> #REF! | AB15: =+SUM(AB17:AB26,AB29) -> 0 | AC15: =+SUM(AC17:AC26,AC29) -> #REF! | AD15: =+SUM(AD17:AD26,AD29) -> #REF! | AE15: =+SUM(AE17:AE26,AE29) -> #REF! | AF15: =+SUM(AF17:AF26,AF29) -> #REF! | AH15: =+SUM(AH17:AH26,AH29) -> #REF! | AJ15: =+AF15-Z15 -> #REF! | AN15: =+SUM(AN17:AN26,AN29) -> #REF! | AO15: =+SUM(AO17:AO26,AO29) -> #REF! | AQ15: =+SUM(AQ17:AQ26,AQ29) -> 0 | AR15: =+SUM(AR17:AR26,AR29) -> 0 | AS15: =+SUM(AS17:AS26,AS29) -> 0 | AT15: =+SUM(AT17:AT26,AT29) -> 0 | AU15: =+SUM(AU17:AU26,AU29) -> 0
B17: Materiales | E17: =+'DIRECTO '!E17+#REF! -> #REF! | L17: =+SUM(N17:R17) -> 0 | S17: =+SUMIFS(N17:R17,N$2:R$2,$S$5) -> 0 | U17: =+SUMIFS(N17:S17,N$2:S$2,$U$5) -> 0 | V17: =+SUMIFS(N17:S17,N$2:S$2,$V$5) -> 0 | W17: =+SUMIFS(N17:S17,N$2:S$2,$W$5) -> 0 | Y17: =+Z17 -> 0 | Z17: =+K17+L17 -> 0 | AJ17: =+AF17-Z17 -> 0 | AK17: =Mat!Y26 -> 0 | AL17: =IF(ABS(Z17-AK17)>1,"Revisar Rubros","OK") -> OK
B18: Mano de Obra | E18: =+'DIRECTO '!E18+#REF! -> #REF! | L18: =+SUM(N18:R18) -> 0 | S18: =+SUMIFS(N18:R18,N$2:R$2,$S$5) -> 0 | U18: =+SUMIFS(N18:S18,N$2:S$2,$U$5) -> 0 | V18: =+SUMIFS(N18:S18,N$2:S$2,$V$5) -> 0 | W18: =+SUMIFS(N18:S18,N$2:S$2,$W$5) -> 0 | Y18: =+Z18 -> 0 | Z18: =+K18+L18 -> 0 | AJ18: =+AF18-Z18 -> 0 | AK18: =+MO!Y75 -> 0 | AL18: =IF(ABS(Z18-AK18)>1,"Revisar Rubros","OK") -> OK
B19: Subcontratos de obra | E19: =+'DIRECTO '!E19+#REF! -> #REF! | L19: =+SUM(N19:R19) -> 0 | S19: =+SUMIFS(N19:R19,N$2:R$2,$S$5) -> 0 | U19: =+SUMIFS(N19:S19,N$2:S$2,$U$5) -> 0 | V19: =+SUMIFS(N19:S19,N$2:S$2,$V$5) -> 0 | W19: =+SUMIFS(N19:S19,N$2:S$2,$W$5) -> 0 | Y19: =+Z19 -> 0 | Z19: =+K19+L19 -> 0 | AJ19: =+AF19-Z19 -> 0 | AK19: =+SC!#REF! -> #REF! | AL19: =IF(ABS(Z19-AK19)>1,"Revisar Rubros","OK") -> #REF!
B20: Servicios Contratados | E20: =+'DIRECTO '!E20+#REF! -> #REF! | L20: =+SUM(N20:R20) -> 0 | S20: =+SUMIFS(N20:R20,N$2:R$2,$S$5) -> 0 | U20: =+SUMIFS(N20:S20,N$2:S$2,$U$5) -> 0 | V20: =+SUMIFS(N20:S20,N$2:S$2,$V$5) -> 0 | W20: =+SUMIFS(N20:S20,N$2:S$2,$W$5) -> 0 | Y20: =+Z20 -> 0 | Z20: =+K20+L20 -> 0 | AJ20: =+AF20-Z20 -> 0 | AK20: =+SER!Y44 -> 22778.589 | AL20: =IF(ABS(Z20-AK20)>1,"Revisar Rubros","OK") -> Revisar Rubros
B21: Equipos y Vehículos | E21: =+'DIRECTO '!E21+#REF! -> #REF! | L21: =+SUM(N21:R21) -> 0 | S21: =+SUMIFS(N21:R21,N$2:R$2,$S$5) -> 0 | U21: =+SUMIFS(N21:S21,N$2:S$2,$U$5) -> 0 | V21: =+SUMIFS(N21:S21,N$2:S$2,$V$5) -> 0 | W21: =+SUMIFS(N21:S21,N$2:S$2,$W$5) -> 0 | Y21: =+Z21 -> 0 | Z21: =+K21+L21 -> 0 | AJ21: =+AF21-Z21 -> 0 | AL21: =IF(ABS(Z21-AK21)>1,"Revisar Rubros","OK") -> OK
C22: Propios | E22: =+'DIRECTO '!E22+#REF! -> #REF! | L22: =+SUM(N22:R22) -> 0 | S22: =+SUMIFS(N22:R22,N$2:R$2,$S$5) -> 0 | U22: =+SUMIFS(N22:S22,N$2:S$2,$U$5) -> 0 | V22: =+SUMIFS(N22:S22,N$2:S$2,$V$5) -> 0 | W22: =+SUMIFS(N22:S22,N$2:S$2,$W$5) -> 0 | Y22: =+Z22 -> 0 | Z22: =+K22+L22 -> 0 | AJ22: =+AF22-Z22 -> 0 | AK22: =+Eq!Y56 -> 0 | AL22: =IF(ABS(Z22-AK22)>1,"Revisar Rubros","OK") -> OK
C23: Terceros | E23: =+'DIRECTO '!E23+#REF! -> #REF! | L23: =+SUM(N23:R23) -> 0 | S23: =+SUMIFS(N23:R23,N$2:R$2,$S$5) -> 0 | U23: =+SUMIFS(N23:S23,N$2:S$2,$U$5) -> 0 | V23: =+SUMIFS(N23:S23,N$2:S$2,$V$5) -> 0 | W23: =+SUMIFS(N23:S23,N$2:S$2,$W$5) -> 0 | Y23: =+Z23 -> 0 | Z23: =+K23+L23 -> 0 | AJ23: =+AF23-Z23 -> 0 | AK23: =+Eq!Y57 -> 0 | AL23: =IF(ABS(Z23-AK23)>1,"Revisar Rubros","OK") -> OK
B24: Fletes | E24: =+'DIRECTO '!E24+#REF! -> #REF! | L24: =+SUM(N24:R24) -> 0 | S24: =+SUMIFS(N24:R24,N$2:R$2,$S$5) -> 0 | U24: =+SUMIFS(N24:S24,N$2:S$2,$U$5) -> 0 | V24: =+SUMIFS(N24:S24,N$2:S$2,$V$5) -> 0 | W24: =+SUMIFS(N24:S24,N$2:S$2,$W$5) -> 0 | Y24: =+Z24 -> 0 | Z24: =+K24+L24 -> 0 | AJ24: =+AF24-Z24 -> 0 | AK24: =+Fletes!Y39 -> 0 | AL24: =IF(ABS(Z24-AK24)>1,"Revisar Rubros","OK") -> OK
B25: Staff (Sueldos) | E25: =+'DIRECTO '!E25+#REF! -> #REF! | L25: =+SUM(N25:R25) -> 0 | S25: =+SUMIFS(N25:R25,N$2:R$2,$S$5) -> 0 | U25: =+SUMIFS(N25:S25,N$2:S$2,$U$5) -> 0 | V25: =+SUMIFS(N25:S25,N$2:S$2,$V$5) -> 0 | W25: =+SUMIFS(N25:S25,N$2:S$2,$W$5) -> 0 | Y25: =+Z25 -> 0 | Z25: =+K25+L25 -> 0 | AJ25: =+AF25-Z25 -> 0 | AK25: =+Staff!BK27 -> 0 | AL25: =IF(ABS(Z25-AK25)>1,"Revisar Rubros","OK") -> OK
B26: Gastos Generales | E26: =+'DIRECTO '!E26+#REF! -> #REF! | L26: =+SUM(N26:R26) -> 0 | S26: =+SUMIFS(N26:R26,N$2:R$2,$S$5) -> 0 | U26: =+SUMIFS(N26:S26,N$2:S$2,$U$5) -> 0 | V26: =+SUMIFS(N26:S26,N$2:S$2,$V$5) -> 0 | W26: =+SUMIFS(N26:S26,N$2:S$2,$W$5) -> 0 | Y26: =+Z26 -> 0 | Z26: =+K26+L26 -> 0 | AJ26: =+AF26-Z26 -> 0 | AK26: =+GG!Y35 -> 24799.991 | AL26: =IF(ABS(Z26-AK26)>1,"Revisar Rubros","OK") -> Revisar Rubros
B28: COSTOS SC CON AHORRO DEL 20%(VENTA) | E28: =+'DIRECTO '!E25+#REF! -> #REF! | S28: =+SUMIFS(N28:R28,N$2:R$2,$S$5) -> 0 | U28: =+SUMIFS(N28:S28,N$2:S$2,$U$5) -> 0 | V28: =+SUMIFS(N28:S28,N$2:S$2,$V$5) -> 0 | W28: =+SUMIFS(N28:S28,N$2:S$2,$W$5) -> 0 | AA28: =(+#REF!+#REF!)*0.8 -> #REF! | AN28: =SUM(AO28:AU28) -> #REF! | AO28: =+'DIRECTO '!AK25+#REF! -> #REF!
B29: COSTO A LA FECHA + PROYECCION A ABRIL ( IISS/IIEE) | E29: =+'DIRECTO '!E28+#REF! -> #REF! | G29: =+'DIRECTO '!G28+#REF! -> #REF! | H29: =+'DIRECTO '!H28+#REF! -> #REF! | J29: =+'DIRECTO '!J28+#REF! -> #REF! | K29: =+'DIRECTO '!K28+#REF! -> #REF! | L29: =+SUM(N29:R29) -> 0 | S29: =+SUMIFS(N29:R29,N$2:R$2,$S$5) -> 0 | U29: =+SUMIFS(N29:S29,N$2:S$2,$U$5) -> 0 | V29: =+SUMIFS(N29:S29,N$2:S$2,$V$5) -> 0 | W29: =+SUMIFS(N29:S29,N$2:S$2,$W$5) -> 0 | Z29: =+K29+L29 -> #REF! | AA29: =+AS37+AS38 -> #REF! | AC29: =+'DIRECTO '!Z28+#REF! -> #REF! | AD29: =+'DIRECTO '!AA28+#REF! -> #REF! | AE29: =+'DIRECTO '!AB28+#REF! -> #REF! | AF29: =+'DIRECTO '!AC28+#REF! -> #REF! | AH29: =+'DIRECTO '!AE28+#REF! -> #REF! | AN29: =SUM(AO29:AU29) -> #REF! | AO29: =+'DIRECTO '!AK28+#REF! -> #REF!
B31: Margen Ponderado S/. | C31: S/. | E31: =+E7*E32 -> #REF! | G31: =+G7*G32 -> 0 | H31: =+H7*H32 -> 0 | J31: =+J7*J32 -> 0 | K31: =+K7*K32 -> 0 | L31: =+L7*L32 -> 0 | N31: =+N7*N32 -> 0 | O31: =+O7*O32 -> 0 | P31: =+P7*P32 -> 0 | Q31: =+Q7*Q32 -> 0 | R31: =+R7*R32 -> 0 | S31: =+S7*S32 -> 0 | U31: =+U7*U32 -> 0 | V31: =+V7*V32 -> 0 | W31: =+W7*W32 -> 0 | Y31: =+Y7-Y15 -> 1511228 | Z31: =+Z7-Z15 -> #REF! | AA31: =+AA7-AA15 -> #REF! | AB31: =+AB7-AB15 -> 0 | AC31: =+AC7-AC15 -> #REF! | AD31: =+AD7-AD15 -> #REF! | AE31: =+AE7-AE15 -> #REF! | AF31: =+AF7-AF15 -> #REF! | AH31: 0 | AJ31: =+Z31-AC31 -> #REF! | AL31: =+Z31 -> #REF!
C32: % | E32: =+$Z$32 -> 0 | G32: =+$Z$32 -> 0 | H32: =+$Z$32 -> 0 | J32: =+$Z$32 -> 0 | K32: =+$Z$32 -> 0 | L32: =+$Z$32 -> 0 | N32: =+$Z$32 -> 0 | O32: =+$Z$32 -> 0 | P32: =+$Z$32 -> 0 | Q32: =+$Z$32 -> 0 | R32: =+$Z$32 -> 0 | S32: =+$Z$32 -> 0 | U32: =+$Z$32 -> 0 | V32: =+$Z$32 -> 0 | W32: =+$Z$32 -> 0 | Y32: =+IF(Y7=0,0,Y31/Y7) -> 1 | Z32: =+IF(Z7=0,0,Z31/Z7) -> 0 | AA32: =+IF(AA7=0,0,AA31/AA7) -> 0 | AB32: =+IF(AB7=0,0,AB31/AB7) -> 0 | AC32: =+IF(AC7=0,0,AC31/AC7) -> 0 | AD32: =+IF(AD7=0,0,AD31/AD7) -> 0 | AE32: =+IF(AE7=0,0,AE31/AE7) -> 0 | AF32: =+IF(AF7=0,0,AF31/AF7) -> 0 | AH32: 0
B34: Margen Absoluto | C34: S/. | E34: =+E7-E15+E29 -> #REF! | G34: =+G7-G15+G29 -> #REF! | H34: =+H7-H15+H29 -> #REF! | J34: =+J7-J15+J29 -> #REF! | K34: =+K7-K15 -> #REF! | L34: =+L7-L15 -> 0 | N34: =+N7-N15+N29 -> 0 | O34: =+O7-O15+O29 -> 0 | P34: =+P7-P15+P29 -> 0 | Q34: =+Q7-Q15+Q29 -> 0 | R34: =+R7-R15+R29 -> 0 | S34: =+S7-S15+S29 -> 0 | U34: =+U7-U15+U29 -> 0 | V34: =+V7-V15+V29 -> 0 | W34: =+W7-W15+W29 -> 0 | Y34: =+Y7-Y15+Y29 -> 1511228 | Z34: =+Z7-Z15+Z29 -> #REF! | AB34: =+AB7-AB15+AB29 -> 0 | AC34: =+AC7-AC15+AC29 -> #REF! | AD34: =+AD7-AD15+AD29 -> #REF! | AE34: =+AE7-AE15+AE29 -> #REF! | AF34: =+AF7-AF15+AF29 -> #REF! | AH34: 0
C35: % | E35: =+IF(E9=0,0,E34/E9) -> #REF! | G35: =+IF(G9=0,0,G34/G9) -> 0 | H35: =+IF(H9=0,0,H34/H9) -> 0 | J35: =+IF(J7=0,0,J34/J7) -> 0 | K35: =+IF(K7=0,0,K34/K7) -> 0 | L35: =+IF(L7=0,0,L34/L7) -> 0 | N35: =+IF(N7=0,0,N34/N7) -> 0 | O35: =+IF(O7=0,0,O34/O7) -> 0 | P35: =+IF(P7=0,0,P34/P7) -> 0 | Q35: =+IF(Q7=0,0,Q34/Q7) -> 0 | R35: =+IF(R7=0,0,R34/R7) -> 0 | S35: =+IF(S7=0,0,S34/S7) -> 0 | U35: =+IF(U7=0,0,U34/U7) -> 0 | V35: =+IF(V7=0,0,V34/V7) -> 0 | W35: =+IF(W7=0,0,W34/W7) -> 0 | Y35: =+IF(Y7=0,0,Y34/Y7) -> 1 | Z35: =+IF(Z7=0,0,Z34/Z7) -> 0 | AB35: =+IF(AB7=0,0,AB34/AB7) -> 0 | AC35: =+IF(AC7=0,0,AC34/AC7) -> 0 | AD35: =+IF(AD7=0,0,AD34/AD7) -> 0 | AE35: =+IF(AE7=0,0,AE34/AE7) -> 0 | AF35: =+IF(AF7=0,0,AF34/AF7) -> 0 | AH35: 0
AO36: AC A FEBRERO | AQ36: MARZO | AR36: ABRIL | AS36: TOTAL
C37: =+#REF!*1.18 -> #REF! | Y37: =+Y35-CONSOLIDADO!W34 -> #REF! | Z37: =+Z35-CONSOLIDADO!W34 -> #REF! | AN37: AHORRO EN IIEE | AO37: =+#REF! -> #REF! | AQ37: =+#REF! -> #REF! | AR37: =+#REF! -> #REF! | AS37: =+AO37+AQ37+AR37 -> #REF!
AN38: AHORRO EN IISS | AO38: =+#REF! -> #REF! | AQ38: =+#REF! -> #REF! | AR38: =+#REF! -> #REF! | AS38: =+AO38+AQ38+AR38 -> #REF!
B39: COSTO APLICADO | K39: =+K7-K31 -> 0 | R39: =R7*(1-R32) -> 0 | Y39: =+Y31-CONSOLIDADO!W33 -> #REF! | Z39: =+Z31-CONSOLIDADO!W33 -> #REF!
B41: RESULTADO PENDIENTE | K41: =K15-K39 -> #REF! | R41: =+R15-R39+K41 -> #REF!
B43: ACTIVOS | K43: ='ER Pendiente'!H40+'ER Pendiente'!H15 -> #REF!
B45: PROVISIONES | K45: =+'ER Pendiente'!I40+'ER Pendiente'!I22 -> 0
B47: DIFERENCIA DE MARGENES | K47: =+'DIRECTO '!K46+#REF! -> #REF!
B49: CONTINGENCIA | K49: =+K41-K43+K45 -> #REF!
C51: Mayor Margen +
C53: Menor Margen -
B56: MARGEN CONSORCIO (PONDERADO) | Z56: 11555 | AF56: 16571
B57: MARGEN GARANTIZADO | Z57: 10554 | AF57: 10554
B58: MARGEN POR PRODUCTIVIDAD | Z58: 10.01 | AF58: 59.97
B60: PARTICIPACION SOCIO/S: | Z60: 5677 | AF60: 7676
B61: MARGEN GARANTIZADO | Z61: 5277 | AF61: 5277
B62: MARGEN POR PRODUCTIVIDAD | Z62: 4 | AF62: 23.99
B64: PARTICIPACION CMO | Z64: 5878 | AF64: 8875
B65: MARGEN GARANTIZADO | Z65: 5277 | AF65: 5277
B66: MARGEN POR PRODUCTIVIDAD | Z66: 6.01 | AF66: 35.98
B100: DESEMPEÑO DEL PROYECTO | K100: =K34 -> #REF! | L100: =+K100+L34 -> #REF! | N100: =+K100+N34 -> #REF! | O100: =+N100+O34 -> #REF! | P100: =+O100+P34 -> #REF! | Q100: =+P100+Q34 -> #REF! | R100: =+#REF!+R34 -> #REF! | S100: =+K100+S34 -> #REF! | U100: =+S100+U34 -> #REF! | V100: =+U100+V34 -> #REF! | Z100: =Z34 -> #REF! | AF100: =AF34 -> #REF!
B101: DIRECTO | C101: ='DIRECTO '!K15 -> #REF! | E101: =IF(C101-SUM(C105:C113)=0,"OK","REVISAR") -> #REF!
B102: INDIRECTO | C102: =#REF! -> #REF! | E102: =IF(C102-SUM(E105:E113)=0,"OK","REVISAR") -> #REF!
C104: DIRECTO | E104: INDIRECTO
B105: Materiales | C105: ='DIRECTO '!K17 -> #REF! | E105: =#REF! -> #REF!
B106: Mano de Obra | C106: ='DIRECTO '!K18 -> #REF! | E106: =#REF! -> #REF!
B107: Subcontratos de obra | C107: ='DIRECTO '!K19 -> #REF! | E107: =#REF! -> #REF!
B108: Servicios Contratados | C108: ='DIRECTO '!K20 -> #REF! | E108: =#REF! -> #REF!
B109: Equipos y Vehículos (Propios) | C109: ='DIRECTO '!K22 -> #REF! | E109: =#REF! -> #REF!
B110: Equipos y Vehículos (Terceros) | C110: ='DIRECTO '!K23 -> #REF! | E110: =#REF! -> #REF!
B111: Fletes | C111: ='DIRECTO '!K24 -> #REF! | E111: =#REF! -> #REF!
B112: Staff (Sueldos) | C112: ='DIRECTO '!K25 -> #REF! | E112: =#REF! -> #REF!
B113: Gastos Generales | C113: ='DIRECTO '!K26 -> #REF! | E113: =#REF! -> #REF!

Sheet Riesgos y Oport.
A1: MATRIZ DE RIESGOS Y OPORTUNIDADES
A3: Ítem | B3: Identificación | C3: ESPECIALIDAD | D3: Análisis | E3: Rubro | F3: Gravedad | G3: Monto S/. | H3: Amenazas | I3: Oportunidad | J3: Observaciones | K3: ESTATUS RO | L3: Responsable | M3: Soluciones
A4: 01 | B4: Debido a la modalidad del contrato (suma alzada): se tenga que ejecutar mayores prestaciones adicionales sin que necesariamente sean reconocidos por la Entidad. Mov. De Tierras | C4: MOV. DE TIERRAS | D4: Gestionar ante la Entidad adicionales y deductivos vinculantes, no obstante sean rechazados se deberá dejar antecedes para un posterior reconocimiento mediante la via que corresponda. | E4: METRADO | F4: MUY BAJA | H4: =+IF(G4>0,G4,0) -> 0 | J4: Costo por definir por especialista | K4: No Considerado en RO | L4: Obra | M4: Elaboración del presupuesto compromiso con metrados reales lo que permitirá determinar la brecha entre lo considerado en el Expediente Técnico y lo realmente a ejecutar. | AE4: ALTA
A5: 02 | B5: Debido a la modalidad del contrato (suma alzada): se tenga que ejecutar mayores prestaciones adicionales sin que necesariamente sean reconocidos por la Entidad. Estructuras | C5: ESTRUCTURAS | D5: Gestionar ante la Entidad adicionales y deductivos vinculantes, no obstante sean rechazados se deberá dejar antecedes para un posterior reconocimiento mediante la via que corresponda. | E5: METRADO | F5: MUY BAJA | H5: =+IF(G5>0,G5,0) -> 0 | J5: Costo por definir por especialista | K5: No Considerado en RO | L5: Obra | M5: Elaboración del presupuesto compromiso con metrados reales lo que permitirá determinar la brecha entre lo considerado en el Expediente Técnico y lo realmente a ejecutar. | AE5: ALTA
A6: 03 | B6: Costos incurridos durante el EEN y Mayores Gastos Generales de las Ampliaciones de Plazo 1 y 2, no sean reconocidos en su totalidad por la Entidad. | C6: GG | D6: Pasos a seguir ante la Entidad: Comunicación, Conciliación, y finalmente Arbitrar.. Entidad ha aprobado un monto de S/.63'268.96 | E6: PLAZO | F6: ALTA | K6: Costo Considerado en RO | L6: Área legal | M6: Se solicita apoyo al área legal | AE6: MUY BAJA
A7: 04 | B7: Costos incurridos durante el EEN y Mayores Gastos Generales de las Ampliaciones de Plazo 3 Parte I | C7: GG | D7: Entidad ha aprobado 10 días. Sin embargo son 23 días . De estos no se está reconociendo ningun costo asociado. Costo ya incurrido. | E7: PLAZO | F7: MODERADA | G7: =21000*10 -> 210000 | I7: =+IF(G7>0,G7,0) -> 210000 | K7: Costo Considerado en RO | L7: Área legal | M7: Se debe aplicar la ley de contrataciones del estado.
A8: 05 | B8: Costos incurridos durante el EEN y Mayores Gastos Generales de las Ampliaciones de Plazo 3 Parte II | C8: GG | D8: Costo y plazo de 13 días aun no aprobados pero si incurridos en costo. | E8: PLAZO | F8: ALTA | G8: =21000*13 -> 273000 | I8: =+IF(G8>0,G8,0) -> 273000 | K8: Costo Considerado en RO | L8: Área legal | M8: Se debe verificar si es posible una AP N°04 y una vez reconocido dicho plazo, se debe aplicar la ley de contrataciones del Estado.
A9: 06 | B9: Costos incurrido en el periodo de Estado de Emergencia. Se ha Presentado un monto de reconocimiento a la entidad de: 1'783'448.06 Inc. IGV | C9: GG | D9: Entidad sólo ha reconocido S/. 40'675.76k. | E9: PLAZO | F9: ALTA | K9: Costo Considerado en RO | L9: Área legal | M9: Se solicita apoyo al área legal
A10: 07 | B10: Adecuaciones | C10: GG | D10: Adecuaciones de instalaciones de obra para reinicio de obra. | E10: PANDEMIA | F10: ALTA | G10: =+RG!Y13 -> 1511228 | I10: =+G10 -> 1511228 | K10: Costo Considerado en RO | L10: Área legal | M10: Se solicita apoyo al área legal
A11: 08 | B11: Removilización | C11: GG | D11: Entidad sólo ha reconocido S/. 18'967.36 | E11: PANDEMIA | F11: ALTA | G11: =212950.08/1.18 -> 180466.17 | I11: =+G11 -> 180466.17 | K11: Costo Considerado en RO | L11: Área legal | M11: Se solicita apoyo al área legal
A12: 09 | B12: Costos de reconocimiento de Plan Sanitario Covid | C12: GG | D12: Se presentan todos los costos asociados a gastos como alojamiento, alimentación, exámenes médicos, pruebas, Costo SB de Mano de Obra. | E12: PANDEMIA | F12: ALTA | K12: Costo Considerado en RO | L12: Área legal | M12: Coordinar un costo reembolsable con la entidad (Tiempo y Material ) Presentar a tiempo los costos asociados al Plan Sanitario Mensualmente.
A13: 10 | B13: Costos de baja de rendimiento, debido a afectación de personal (MO directa) Covid. | C13: OBRA | D13: Bajas de personal fortuitos que disminuyen rendimientos de manera fortuita. | E13: PANDEMIA | F13: MODERADA | H13: =+IF(G13>0,G13,0) -> 0 | J13: Costo por definir | K13: No Considerado en RO | L13: Obra | M13: Implementación de medidas consignadas en el marco legal dado por el Gobierno Central ( 005). Obra planifica tener una cartera de personal listo para ingreso.
A14: 11 | B14: Rellenos: Cambio de especificación de material | C14: MOV. DE TIERRAS | D14: Las canteras que se dieron como punto de extracción en proceso de licitación no tienen el material adecuado. Por lo que se debió traer el material desde otros destinos | E14: ALCANCE | F14: MODERADA | G14: 4453323.8 | H14: =-IF(G14>0,G14,0) -> -4453323.8 | I14: =-H14*0.1 -> 445332.38 | J14: Costo de SC si CSZ asume costo de trabajos. Monto de oportunidad por utilidad de adjudicación | K14: No Considerado en RO | L14: Area Legal | M14: Apoyo en la insisitencia de la aprobación del adicional
A15: 12 | B15: Paralizaciones varias,: gremios sindicales, paro de transportistas, etc. | C15: GG | D15: Costos Stand by asociados a paralizaciones ( provisiona 10 días ) | E15: EXTERNO | F15: MUY BAJA | G15: =-21000*10 -> -210000 | H15: =-21000*10 -> -210000 | K15: No Considerado en RO | L15: Externo | M15: Se realizará una contingencia ante estos eventos días antes. Envío de comunicación ante la entidad comunicando evento.
A16: 13 | B16: Rotación de Encofrados. | C16: ESTRUCTURAS | D16: Oposición de la Supervisión al desencofrado de losas a los 7 días luego de haber alcanzado la resistencia indicada(70%) El criterio de supervisión es desencofrar a mayor tiempo. Por lo que se requeriría mayor equipamiento. Generandose una desviación a lo inicialmente planificado. | E16: SUPERVISION | F16: MODERADA | G16: 1000000 | H16: =-IF(G16>0,G16,0) -> -1000000 | J16: Se está considerando el precio de metrado de encofrado.de acuerdo al cálculo de AC y JZ | K16: No Considerado en RO | L16: Obra | M16: Envio de Informe a la entidad, considerando las consideraciones técnicas y la muestraa de prueba empírica in situ que demuestran al factibilidad de este procedimiento.
A17: 14 | B17: Muros de Contención, Sardineles, Refuerzo en Pavimento Rígido incluye el relleno con Material de Préstamo | C17: ESTRUCTURAS | D17: De no tener respuesta, el CSZ deberá asumir el costo de este trabajo para no impactar en el cronograma. | E17: ALCANCE | F17: ALTA | G17: 2358836.1 | H17: =-IF(G17>0,G17,0) -> -2358836.1 | I17: =-H17*0.1 -> 235883.61 | J17: Considerar que la incidencia de GG en obra es 300k mensuales | K17: No Considerado en RO | L17: Area Legal | M17: Insistencia a nivel de alta dirección para lograr la aprobación.
A18: 15 | B18: Mejoramiento de Suelo en la Proyección de la Cimentación de los Muros de Contención Plataformas 3 y 4 ( Micropilotes) | C18: ESTRUCTURAS | D18: La supervision brindo una opinión favorable para el mejoramiento co micropilotes, en la cimentación de la PT03. Quedando pendiente la rpta de la Entidad. La denegación de este adicional implicará la imposibilidad de ejecutar el edificio (J, I1, I2 ) de la PT03 | E18: SUPERVISION | F18: MODERADA | G18: =141000*3.65 -> 514650 | H18: =-IF(G18>0,G18,0) -> -514650 | I18: =-H18*0.04 -> 20586 | J18: Costo de SC si CSZ asume costo de trabajos. Monto de oportunidad por utilidad de adjudicación | K18: No Considerado en RO | L18: Obra
A19: 16 | B19: Sobre costo de Agregados ( Arquitectura) | C19: ESTRUCTURAS | D19: El expediente técnico consideró como cantera de agregados, a una que se encontraba dentro de la ciudad de Huancavelica. (terreno donde se ubica una chancadora ) cuya producción co cubre la demanda requerida por la obra. Como consecuencia de ellos, se requiere el suministro de material de zonas fuera del área de influencia. | E19: ALCANCE | F19: MUY BAJA | G19: =914918*0.2 -> 182983.6 | H19: =-IF(G19>0,G19,0) -> -182983.6 | J19: Suministro de agregados en acabados húmedos, podría ser un 20% al estimado inciialmente debido a la lejanía de las canteras | K19: No Considerado en RO | L19: Obra | M19: Encontrar proveedores con lleguen al costo considerando viaje puesto en obra.
A20: 17 | B20: Conflicto de zonificación entre Casa de Fuerza Vs. Resonancia Magnetica | C20: GG | D20: De acuerdo a los especialistas de CSZ, la casa de Fuerza debe reubicarse. Ya que esta no se podría reubicar al costado del cuarto de Resonancia Magnética. Este hecho podría ser observado por el usuario final. | E20: ENTIDAD | F20: MUY BAJA | G20: 0 | H20: =+IF(G20>0,G20,0) -> 0 | J20: De ratificarse la entidad en continuar con la ubicación.. CSZ procederá con lo contractual. | K20: No Considerado en RO | L20: Área legal | M20: Envio de cartas, de advertencias y desvinculación de responsabilidad. Y Reportes en cuaderno de Obra
G21: =SUM(G4:G20) -> 10474488 | H21: =SUM(H4:H20) -> -8719793.5 | I21: =SUM(I4:I20) -> 2876496.1
B28: Etiquetas de fila | C28: Suma de Amenazas | D28: Suma de Oportunidad
B29: METRADO | C29: 0
B30: PANDEMIA | C30: 0 | D30: 1958414.8
B31: PLAZO | D31: 3779808.1
B32: ALCANCE | C32: -5633302.8 | D32: 535031.92
B33: EXTERNO | C33: -210000
B34: SUPERVISION | C34: -1514650 | D34: 20586
B35: CONTRATO | C35: 0
B36: ENTIDAD | C36: -1087010.2
B37: INGENIERIA | C37: -3582801.2 | D37: 0
B38: Total general | C38: -12027764 | D38: 6293840.8

Sheet C+AD
B1: =CONCATENATE(B3," - ",B4," - ",B5," - ",B6) -> I.E.N 1182 - - EL BOSQUE - CERCO + INGRESOS Y CASETAS - CONSOLIDADO
N2: =+YEAR(N5) -> 2019 | O2: =+YEAR(O5) -> 2019 | P2: =+YEAR(P5) -> 2019 | Q2: =+YEAR(Q5) -> 2019 | R2: =+YEAR(R5) -> 2019 | S2: =S5 -> 2024
B3: I.E.N 1182 | E3: ACUMULADO | G3: =+RG!G3 -> MES ENERO DEL 2025 | J3: ACUMULADO DEL 2024 | K3: ACUMULADO DE OBRA | L3: SALDO DE OBRA | N3: PROYECCIÓN | U3: AÑOS SIGUIENTES | X3: TOTAL DE OBRA | AD3: Acum. del Ej. | AJ3: TOTAL | AK3: MES DEL INFORME | AL3: 43647 | AM3: 43678 | AN3: 43709 | AO3: 43739 | AP3: 43770 | AQ3: 43800 | AR3: 43831 | AS3: 43862 | AT3: 43891 | AU3: 43922 | AV3: 43952 | AW3: 43983 | AX3: 44013 | AY3: 44044 | AZ3: 44075 | BA3: 44105 | BB3: 44136 | BC3: 44166 | BD3: =BC3+31 -> 44197 | BE3: =BD3+31 -> 44228 | BF3: =BE3+31 -> 44259 | BG3: =BF3+31 -> 44290 | BH3: =BG3+31 -> 44321 | BI3: =BH3+31 -> 44352 | BJ3: =BI3+31 -> 44383 | BK3: =BJ3+31 -> 44414 | ... CA3: =BZ3+31 -> 44910
N4: 1 | O4: =+N4+1 -> 2 | P4: =+O4+1 -> 3 | Q4: =+P4+1 -> 4 | R4: =+Q4+1 -> 5 | S4: Saldo del Ejercicio
B5: EL BOSQUE - CERCO + INGRESOS Y CASETAS | E5: Años Anteriores | G5: Previsto | H5: Real | N5: 43648 | O5: =+N5+31 -> 43679 | P5: =+O5+31 -> 43710 | Q5: =+P5+31 -> 43741 | R5: =+Q5+31 -> 43772 | S5: 2024 | U5: 2024 | W5: MEJOR ESCENARIO | X5: Actual | Y5: Anterior | Z5: Meta | AA5: Presupuesto Interno | AB5: Presupuesto | AD5: Anterior
B6: CONSOLIDADO
B7: Venta Total Producida | E7: =+E9 -> #REF! | G7: =+G9 -> #REF! | H7: =+H9 -> #REF! | J7: =+J9 -> #REF! | K7: =+K9 -> #REF! | L7: =+L9 -> #REF! | N7: =+N9 -> #REF! | O7: =+O9 -> #REF! | P7: =+P9 -> #REF! | Q7: =+Q9 -> #REF! | R7: =+R9 -> #REF! | S7: =+S9 -> 0 | U7: =+U9 -> 0 | W7: =+W9 -> #REF! | X7: =+X9 -> #REF! | Y7: =+Y9 -> #REF! | Z7: =+Z9 -> #REF! | AA7: =+AA9 -> #REF! | AB7: =+AB9 -> #REF! | AD7: =+AD9 -> #REF! | AF7: =+AB7-X7 -> #REF! | AJ7: =+AJ9 -> #REF! | AK7: =+AK9 -> #REF! | AL7: =+AL9 -> #REF! | AM7: =+AM9 -> #REF! | AN7: =+AN9 -> #REF! | AO7: =+AO9 -> #REF! | AP7: =+AP9 -> #REF! | AQ7: =+AQ9 -> #REF! | ... CA7: =+CA9 -> #REF!
B9: Venta | E9: =+SUM(E11:E14) -> #REF! | G9: =+SUM(G11:G14) -> #REF! | H9: =+SUM(H11:H14) -> #REF! | J9: =+SUM(J11:J14) -> #REF! | K9: =+SUM(K11:K14) -> #REF! | L9: =+SUM(L11:L14) -> #REF! | N9: =+SUM(N11:N14) -> #REF! | O9: =+SUM(O11:O14) -> #REF! | P9: =+SUM(P11:P14) -> #REF! | Q9: =+SUM(Q11:Q14) -> #REF! | R9: =+SUM(R11:R14) -> #REF! | S9: =+SUM(S11:S14) -> 0 | U9: =+SUM(U11:U14) -> 0 | W9: =+SUM(W11:W14) -> #REF! | X9: =+SUM(X11:X14) -> #REF! | Y9: =+SUM(Y11:Y14) -> #REF! | Z9: =+SUM(Z11:Z14) -> #REF! | AA9: =+SUM(AA11:AA14) -> #REF! | AB9: =+SUM(AB11:AB14) -> #REF! | AD9: =+SUM(AD11:AD14) -> #REF! | AF9: =+AB9-X9 -> #REF! | AG9: =+X9-Y9 -> #REF! | AJ9: =+SUM(AJ11:AJ14) -> #REF! | AK9: =+SUM(AK11:AK14) -> #REF! | AL9: =+SUM(AL11:AL14) -> #REF! | AM9: =+SUM(AM11:AM14) -> #REF! | AN9: =+SUM(AN11:AN14) -> #REF! | AO9: =+SUM(AO11:AO14) -> #REF! | AP9: =+SUM(AP11:AP14) -> #REF! | AQ9: =+SUM(AQ11:AQ14) -> #REF! | ... CA9: =+SUM(CA11:CA14) -> #REF!
B11: Valorización: Venta Directa - Contrato Principal | E11: =+'DIRECTO '!E11+#REF! -> #REF! | G11: =+'DIRECTO '!G11+#REF! -> #REF! | H11: =+'DIRECTO '!H11+#REF! -> #REF! | J11: =+'DIRECTO '!J11+#REF! -> #REF! | K11: =+'DIRECTO '!K11+#REF! -> #REF! | L11: =+SUM(N11:R11) -> #REF! | N11: =+'DIRECTO '!N11+#REF! -> #REF! | O11: =+'DIRECTO '!O11+#REF! -> #REF! | P11: =+'DIRECTO '!P11+#REF! -> #REF! | Q11: =+'DIRECTO '!Q11+#REF! -> #REF! | R11: =+'DIRECTO '!R11+#REF! -> #REF! | S11: =+SUMIFS(N11:R11,N$2:R$2,$S$5) -> 0 | U11: =+SUMIFS(N11:S11,N$2:S$2,$U$5) -> 0 | W11: =+X11 -> #REF! | X11: =+K11+L11 -> #REF! | Y11: =+'DIRECTO '!Z11+#REF! -> #REF! | Z11: =+'DIRECTO '!AA11+#REF! -> #REF! | AA11: =+'DIRECTO '!AB11+#REF! -> #REF! | AB11: =+'DIRECTO '!AC11+#REF! -> #REF! | AD11: =+'DIRECTO '!AE11+#REF! -> #REF! | AF11: =+AB11-X11 -> #REF! | AG11: =+X11-Y11 -> #REF! | AJ11: =SUM(AK11:CA11) -> #REF! | AK11: =+'DIRECTO '!AK11+#REF! -> #REF! | AL11: =+'DIRECTO '!AM11+#REF! -> #REF! | AM11: =+'DIRECTO '!AN11+#REF! -> #REF! | AN11: =+'DIRECTO '!AO11+#REF! -> #REF! | AO11: =+'DIRECTO '!AP11+#REF! -> #REF! | AP11: =+'DIRECTO '!AQ11+#REF! -> #REF! | AQ11: =+'DIRECTO '!#REF!+#REF! -> #REF! | AR11: =+'DIRECTO '!#REF!+#REF! -> #REF! | AS11: =+'DIRECTO '!#REF!+#REF! -> #REF! | AT11: =+'DIRECTO '!#REF!+#REF! -> #REF! | AU11: =+'DIRECTO '!#REF!+#REF! -> #REF! | AV11: =+'DIRECTO '!#REF!+#REF! -> #REF! | AW11: =+'DIRECTO '!#REF!+#REF! -> #REF! | AX11: =+'DIRECTO '!#REF!+#REF! -> #REF! | ... CA11: =+'DIRECTO '!#REF!+#REF! -> #REF!
B12: Valorización: Venta Indirecta - Contrato Principal | E12: =+'DIRECTO '!E12+#REF! -> #REF! | G12: =+'DIRECTO '!G12+#REF! -> #REF! | H12: =+'DIRECTO '!H12+#REF! -> #REF! | J12: =+'DIRECTO '!J12+#REF! -> #REF! | K12: =+'DIRECTO '!K12+#REF! -> #REF! | L12: =+SUM(N12:R12) -> #REF! | N12: =+'DIRECTO '!N12+#REF! -> #REF! | O12: =+'DIRECTO '!O12+#REF! -> #REF! | P12: =+'DIRECTO '!P12+#REF! -> #REF! | Q12: =+'DIRECTO '!Q12+#REF! -> #REF! | R12: =+'DIRECTO '!R12+#REF! -> #REF! | S12: =+SUMIFS(N12:R12,N$2:R$2,$S$5) -> 0 | U12: =+SUMIFS(N12:S12,N$2:S$2,$U$5) -> 0 | W12: =+X12 -> #REF! | X12: =+K12+L12 -> #REF! | Y12: =+'DIRECTO '!Z12+#REF! -> #REF! | Z12: =+'DIRECTO '!AA12+#REF! -> #REF! | AA12: =+'DIRECTO '!AB12+#REF! -> #REF! | AB12: =+'DIRECTO '!AC12+#REF! -> #REF! | AD12: =+'DIRECTO '!AE12+#REF! -> #REF! | AF12: =+AB12-X12 -> #REF! | AG12: =+X12-Y12 -> #REF! | AJ12: =SUM(AK12:CA12) -> #REF! | AK12: =+'DIRECTO '!AK12+#REF! -> #REF! | AL12: =+'DIRECTO '!AM12+#REF! -> #REF! | AM12: =+'DIRECTO '!AN12+#REF! -> #REF! | AN12: =+'DIRECTO '!AO12+#REF! -> #REF! | AO12: =+'DIRECTO '!AP12+#REF! -> #REF! | AP12: =+'DIRECTO '!AQ12+#REF! -> #REF! | AQ12: =+'DIRECTO '!#REF!+#REF! -> #REF! | AR12: =+'DIRECTO '!#REF!+#REF! -> #REF! | AS12: =+'DIRECTO '!#REF!+#REF! -> #REF! | AT12: =+'DIRECTO '!#REF!+#REF! -> #REF! | AU12: =+'DIRECTO '!#REF!+#REF! -> #REF! | AV12: =+'DIRECTO '!#REF!+#REF! -> #REF! | AW12: =+'DIRECTO '!#REF!+#REF! -> #REF! | AX12: =+'DIRECTO '!#REF!+#REF! -> #REF! | ... CA12: =+'DIRECTO '!#REF!+#REF! -> #REF!
B13: Otros: | E13: =+'DIRECTO '!#REF!+#REF! -> #REF! | G13: =+'DIRECTO '!#REF!+#REF! -> #REF! | H13: =+'DIRECTO '!#REF!+#REF! -> #REF! | J13: =+'DIRECTO '!#REF!+#REF! -> #REF! | K13: =+'DIRECTO '!#REF!+#REF! -> #REF! | L13: =+SUM(N13:R13) -> #REF! | N13: =+'DIRECTO '!#REF!+#REF! -> #REF! | O13: =+'DIRECTO '!#REF!+#REF! -> #REF! | P13: =+'DIRECTO '!#REF!+#REF! -> #REF! | Q13: =+'DIRECTO '!#REF!+#REF! -> #REF! | R13: =+'DIRECTO '!#REF!+#REF! -> #REF! | S13: =+SUMIFS(N13:R13,N$2:R$2,$S$5) -> 0 | U13: =+SUMIFS(N13:S13,N$2:S$2,$U$5) -> 0 | W13: =+X13 -> 0 | X13: 0 | Y13: =+'DIRECTO '!#REF!+#REF! -> #REF! | Z13: =+'DIRECTO '!#REF!+#REF! -> #REF! | AA13: =+'DIRECTO '!#REF!+#REF! -> #REF! | AB13: =+'DIRECTO '!#REF!+#REF! -> #REF! | AD13: =+'DIRECTO '!#REF!+#REF! -> #REF! | AF13: =+AB13-X13 -> #REF! | AG13: =+X13-Y13 -> #REF! | AJ13: =SUM(AK13:CA13) -> #REF! | AK13: =+'DIRECTO '!#REF!+#REF! -> #REF! | AL13: =+'DIRECTO '!#REF!+#REF! -> #REF! | AM13: =+'DIRECTO '!#REF!+#REF! -> #REF! | AN13: =+'DIRECTO '!#REF!+#REF! -> #REF! | AO13: =+'DIRECTO '!#REF!+#REF! -> #REF! | AP13: =+'DIRECTO '!#REF!+#REF! -> #REF! | AQ13: =+'DIRECTO '!#REF!+#REF! -> #REF! | AR13: =+'DIRECTO '!#REF!+#REF! -> #REF! | ... CA13: =+'DIRECTO '!#REF!+#REF! -> #REF!
B14: Ventas de Activos al final de obra(camioneta + minicargador +eq. Electronicos+eq. topografico) | E14: =+'DIRECTO '!E13+#REF! -> #REF! | G14: =+'DIRECTO '!G13+#REF! -> #REF! | H14: =+'DIRECTO '!H13+#REF! -> #REF! | J14: =+'DIRECTO '!J13+#REF! -> #REF! | K14: =+'DIRECTO '!K13+#REF! -> #REF! | L14: =+SUM(N14:R14) -> #REF! | N14: =+'DIRECTO '!N13+#REF! -> #REF! | O14: =+'DIRECTO '!O13+#REF! -> #REF! | P14: =+'DIRECTO '!P13+#REF! -> #REF! | Q14: =+'DIRECTO '!Q13+#REF! -> #REF! | R14: =+'DIRECTO '!R13+#REF! -> #REF! | S14: =+SUMIFS(N14:R14,N$2:R$2,$S$5) -> 0 | U14: =+SUMIFS(N14:S14,N$2:S$2,$U$5) -> 0 | W14: =+X14 -> #REF! | X14: =+CONSOLIDADO!#REF! -> #REF! | Y14: =+'DIRECTO '!Z13+#REF! -> #REF! | Z14: =+'DIRECTO '!AA13+#REF! -> #REF! | AA14: =+'DIRECTO '!AB13+#REF! -> #REF! | AB14: =+'DIRECTO '!AC13+#REF! -> #REF! | AD14: =+'DIRECTO '!AE13+#REF! -> #REF! | AF14: =+AB14-X14 -> #REF! | AG14: =+X14-Y14 -> #REF! | AJ14: =SUM(AK14:CA14) -> #REF! | AK14: =+'DIRECTO '!AK13+#REF! -> #REF! | AL14: =+'DIRECTO '!AM13+#REF! -> #REF! | AM14: =+'DIRECTO '!AN13+#REF! -> #REF! | AN14: =+'DIRECTO '!AO13+#REF! -> #REF! | AO14: =+'DIRECTO '!AP13+#REF! -> #REF! | AP14: =+'DIRECTO '!AQ13+#REF! -> #REF! | AQ14: =+'DIRECTO '!#REF!+#REF! -> #REF! | AR14: =+'DIRECTO '!#REF!+#REF! -> #REF! | AS14: =+'DIRECTO '!#REF!+#REF! -> #REF! | AT14: =+'DIRECTO '!#REF!+#REF! -> #REF! | AU14: =+'DIRECTO '!#REF!+#REF! -> #REF! | AV14: =+'DIRECTO '!#REF!+#REF! -> #REF! | AW14: =+'DIRECTO '!#REF!+#REF! -> #REF! | AX14: =+'DIRECTO '!#REF!+#REF! -> #REF! | ... CA14: =+'DIRECTO '!#REF!+#REF! -> #REF!
B16: Costo Total | E16: =+SUM(E18:E27)+E29 -> #REF! | G16: =+SUM(G18:G27,G29) -> #REF! | H16: =SUM(H18:H27,H29) -> #REF! | J16: =+SUM(J18:J27,J29) -> #REF! | K16: =+SUM(K18:K27,K29) -> #REF! | L16: =+SUM(L18:L27,L29) -> #REF! | N16: =+SUM(N18:N27,N29) -> #REF! | O16: =+SUM(O18:O27,O29) -> #REF! | P16: =+SUM(P18:P27,P29) -> #REF! | Q16: =+SUM(Q18:Q27,Q29) -> #REF! | R16: =+SUM(R18:R27,R29) -> #REF! | S16: =+SUM(S18:S27,S29) -> 0 | U16: =+SUM(U18:U27,U29) -> 0 | W16: =+SUM(W18:W27,W29) -> #REF! | X16: =+SUM(X18:X27,X29) -> #REF! | Y16: =+SUM(Y18:Y27,Y29) -> #REF! | Z16: =+SUM(Z18:Z27,Z29) -> #REF! | AA16: =+SUM(AA18:AA27,AA29) -> #REF! | AB16: =+SUM(AB18:AB27,AB29) -> #REF! | AD16: =+SUM(AD18:AD27,AD29) -> #REF! | AF16: =+AB16-X16 -> #REF! | AJ16: =+SUM(AJ18:AJ27,AJ29) -> #REF! | AK16: =+SUM(AK18:AK27,AK29) -> #REF! | AL16: =+SUM(AL18:AL27,AL29) -> #REF! | AM16: =+SUM(AM18:AM27,AM29) -> #REF! | AN16: =+SUM(AN18:AN27,AN29) -> #REF! | AO16: =+SUM(AO18:AO27,AO29) -> #REF! | AP16: =+SUM(AP18:AP27,AP29) -> #REF! | AQ16: =+SUM(AQ18:AQ27,AQ29) -> #REF! | ... CA16: =+SUM(CA18:CA27,CA29) -> #REF! | CD16: 525387.51
B18: Materiales | E18: =+'DIRECTO '!E17+#REF! -> #REF! | G18: =+'DIRECTO '!G17+#REF! -> #REF! | H18: =+'DIRECTO '!H17+#REF! -> #REF! | J18: =+'DIRECTO '!J17+#REF! -> #REF! | K18: =+'DIRECTO '!K17+#REF! -> #REF! | L18: =+SUM(N18:R18) -> #REF! | N18: =+'DIRECTO '!N17+#REF! -> #REF! | O18: =+'DIRECTO '!O17+#REF! -> #REF! | P18: =+'DIRECTO '!P17+#REF! -> #REF! | Q18: =+'DIRECTO '!Q17+#REF! -> #REF! | R18: =+'DIRECTO '!R17+#REF! -> #REF! | S18: =+SUMIFS(N18:R18,N$2:R$2,$S$5) -> 0 | U18: =+SUMIFS(N18:S18,N$2:S$2,$U$5) -> 0 | W18: =+X18 -> #REF! | X18: =+K18+L18 -> #REF! | Y18: =+'DIRECTO '!Z17+#REF! -> #REF! | Z18: =+'DIRECTO '!AA17+#REF! -> #REF! | AA18: =+'DIRECTO '!AB17+#REF! -> #REF! | AB18: =+'DIRECTO '!AC17+#REF! -> #REF! | AD18: =+'DIRECTO '!AE17+#REF! -> #REF! | AF18: =+AB18-X18 -> #REF! | AG18: =Mat!Y26 -> 0 | AH18: =IF(ABS(X18-AG18)>1,"Revisar Rubros","OK") -> #REF! | AJ18: =SUM(AK18:CA18) -> #REF! | AK18: =+'DIRECTO '!AK17+#REF! -> #REF! | AL18: =+'DIRECTO '!AM17+#REF! -> #REF! | AM18: =+'DIRECTO '!AN17+#REF! -> #REF! | AN18: =+'DIRECTO '!AO17+#REF! -> #REF! | AO18: =+'DIRECTO '!AP17+#REF! -> #REF! | AP18: =+'DIRECTO '!AQ17+#REF! -> #REF! | AQ18: =+'DIRECTO '!#REF!+#REF! -> #REF! | AR18: =+'DIRECTO '!#REF!+#REF! -> #REF! | AS18: =+'DIRECTO '!#REF!+#REF! -> #REF! | AT18: =+'DIRECTO '!#REF!+#REF! -> #REF! | AU18: =+'DIRECTO '!#REF!+#REF! -> #REF! | AV18: =+'DIRECTO '!#REF!+#REF! -> #REF! | AW18: =+'DIRECTO '!#REF!+#REF! -> #REF! | AX18: =+'DIRECTO '!#REF!+#REF! -> #REF! | ... CA18: =+'DIRECTO '!#REF!+#REF! -> #REF!
B19: Mano de Obra | E19: =+'DIRECTO '!E18+#REF! -> #REF! | G19: =+'DIRECTO '!G18+#REF! -> #REF! | H19: =+'DIRECTO '!H18+#REF! -> #REF! | J19: =+'DIRECTO '!J18+#REF! -> #REF! | K19: =+'DIRECTO '!K18+#REF! -> #REF! | L19: =+SUM(N19:R19) -> #REF! | N19: =+'DIRECTO '!N18+#REF! -> #REF! | O19: =+'DIRECTO '!O18+#REF! -> #REF! | P19: =+'DIRECTO '!P18+#REF! -> #REF! | Q19: =+'DIRECTO '!Q18+#REF! -> #REF! | R19: =+'DIRECTO '!R18+#REF! -> #REF! | S19: =+SUMIFS(N19:R19,N$2:R$2,$S$5) -> 0 | U19: =+SUMIFS(N19:S19,N$2:S$2,$U$5) -> 0 | W19: =+X19 -> #REF! | X19: =+K19+L19 -> #REF! | Y19: =+'DIRECTO '!Z18+#REF! -> #REF! | Z19: =+'DIRECTO '!AA18+#REF! -> #REF! | AA19: =+'DIRECTO '!AB18+#REF! -> #REF! | AB19: =+'DIRECTO '!AC18+#REF! -> #REF! | AD19: =+'DIRECTO '!AE18+#REF! -> #REF! | AF19: =+AB19-X19 -> #REF! | AG19: =+MO!Y75 -> 0 | AH19: =IF(ABS(X19-AG19)>1,"Revisar Rubros","OK") -> #REF! | AJ19: =SUM(AK19:CA19) -> #REF! | AK19: =+'DIRECTO '!AK18+#REF! -> #REF! | AL19: =+'DIRECTO '!AM18+#REF! -> #REF! | AM19: =+'DIRECTO '!AN18+#REF! -> #REF! | AN19: =+'DIRECTO '!AO18+#REF! -> #REF! | AO19: =+'DIRECTO '!AP18+#REF! -> #REF! | AP19: =+'DIRECTO '!AQ18+#REF! -> #REF! | AQ19: =+'DIRECTO '!#REF!+#REF! -> #REF! | AR19: =+'DIRECTO '!#REF!+#REF! -> #REF! | AS19: =+'DIRECTO '!#REF!+#REF! -> #REF! | AT19: =+'DIRECTO '!#REF!+#REF! -> #REF! | AU19: =+'DIRECTO '!#REF!+#REF! -> #REF! | AV19: =+'DIRECTO '!#REF!+#REF! -> #REF! | AW19: =+'DIRECTO '!#REF!+#REF! -> #REF! | AX19: =+'DIRECTO '!#REF!+#REF! -> #REF! | ... CA19: =+'DIRECTO '!#REF!+#REF! -> #REF!
B20: Subcontratos de obra | E20: =+'DIRECTO '!E19+#REF! -> #REF! | G20: =+'DIRECTO '!G19+#REF! -> #REF! | H20: =+'DIRECTO '!H19+#REF! -> #REF! | J20: =+'DIRECTO '!J19+#REF! -> #REF! | K20: =+'DIRECTO '!K19+#REF! -> #REF! | L20: =+SUM(N20:R20) -> #REF! | N20: =+'DIRECTO '!N19+#REF! -> #REF! | O20: =+'DIRECTO '!O19+#REF! -> #REF! | P20: =+'DIRECTO '!P19+#REF! -> #REF! | Q20: =+'DIRECTO '!Q19+#REF! -> #REF! | R20: =+'DIRECTO '!R19+#REF! -> #REF! | S20: =+SUMIFS(N20:R20,N$2:R$2,$S$5) -> 0 | U20: =+SUMIFS(N20:S20,N$2:S$2,$U$5) -> 0 | W20: =+X20 -> #REF! | X20: =+K20+L20 -> #REF! | Y20: =+'DIRECTO '!Z19+#REF! -> #REF! | Z20: =+'DIRECTO '!AA19+#REF! -> #REF! | AA20: =+'DIRECTO '!AB19+#REF! -> #REF! | AB20: =+'DIRECTO '!AC19+#REF! -> #REF! | AD20: =+'DIRECTO '!AE19+#REF! -> #REF! | AF20: =+AB20-X20 -> #REF! | AG20: =+SC!#REF! -> #REF! | AH20: =IF(ABS(X20-AG20)>1,"Revisar Rubros","OK") -> #REF! | AJ20: =SUM(AK20:CA20) -> #REF! | AK20: =+'DIRECTO '!AK19+#REF! -> #REF! | AL20: =+'DIRECTO '!AM19+#REF! -> #REF! | AM20: =+'DIRECTO '!AN19+#REF! -> #REF! | AN20: =+'DIRECTO '!AO19+#REF! -> #REF! | AO20: =+'DIRECTO '!AP19+#REF! -> #REF! | AP20: =+'DIRECTO '!AQ19+#REF! -> #REF! | AQ20: =+'DIRECTO '!#REF!+#REF! -> #REF! | AR20: =+'DIRECTO '!#REF!+#REF! -> #REF! | AS20: =+'DIRECTO '!#REF!+#REF! -> #REF! | AT20: =+'DIRECTO '!#REF!+#REF! -> #REF! | AU20: =+'DIRECTO '!#REF!+#REF! -> #REF! | AV20: =+'DIRECTO '!#REF!+#REF! -> #REF! | AW20: =+'DIRECTO '!#REF!+#REF! -> #REF! | AX20: =+'DIRECTO '!#REF!+#REF! -> #REF! | ... CA20: =+'DIRECTO '!#REF!+#REF! -> #REF!
B21: Servicios Contratados | E21: =+'DIRECTO '!E20+#REF! -> #REF! | G21: =+'DIRECTO '!G20+#REF! -> #REF! | H21: =+'DIRECTO '!H20+#REF! -> #REF! | J21: =+'DIRECTO '!J20+#REF! -> #REF! | K21: =+'DIRECTO '!K20+#REF! -> #REF! | L21: =+SUM(N21:R21) -> #REF! | N21: =+'DIRECTO '!N20+#REF! -> #REF! | O21: =+'DIRECTO '!O20+#REF! -> #REF! | P21: =+'DIRECTO '!P20+#REF! -> #REF! | Q21: =+'DIRECTO '!Q20+#REF! -> #REF! | R21: =+'DIRECTO '!R20+#REF! -> #REF! | S21: =+SUMIFS(N21:R21,N$2:R$2,$S$5) -> 0 | U21: =+SUMIFS(N21:S21,N$2:S$2,$U$5) -> 0 | W21: =+X21 -> #REF! | X21: =+K21+L21 -> #REF! | Y21: =+'DIRECTO '!Z20+#REF! -> #REF! | Z21: =+'DIRECTO '!AA20+#REF! -> #REF! | AA21: =+'DIRECTO '!AB20+#REF! -> #REF! | AB21: =+'DIRECTO '!AC20+#REF! -> #REF! | AD21: =+'DIRECTO '!AE20+#REF! -> #REF! | AF21: =+AB21-X21 -> #REF! | AG21: =+SER!Y44 -> 22778.589 | AH21: =IF(ABS(X21-AG21)>1,"Revisar Rubros","OK") -> #REF! | AJ21: =SUM(AK21:CA21) -> #REF! | AK21: =+'DIRECTO '!AK20+#REF! -> #REF! | AL21: =+'DIRECTO '!AM20+#REF! -> #REF! | AM21: =+'DIRECTO '!AN20+#REF! -> #REF! | AN21: =+'DIRECTO '!AO20+#REF! -> #REF! | AO21: =+'DIRECTO '!AP20+#REF! -> #REF! | AP21: =+'DIRECTO '!AQ20+#REF! -> #REF! | AQ21: =+'DIRECTO '!#REF!+#REF! -> #REF! | AR21: =+'DIRECTO '!#REF!+#REF! -> #REF! | AS21: =+'DIRECTO '!#REF!+#REF! -> #REF! | AT21: =+'DIRECTO '!#REF!+#REF! -> #REF! | AU21: =+'DIRECTO '!#REF!+#REF! -> #REF! | AV21: =+'DIRECTO '!#REF!+#REF! -> #REF! | AW21: =+'DIRECTO '!#REF!+#REF! -> #REF! | AX21: =+'DIRECTO '!#REF!+#REF! -> #REF! | ... CA21: =+'DIRECTO '!#REF!+#REF! -> #REF! | CD21: =+X16-X26-X27 -> #REF!
B22: Equipos y Vehículos | E22: =+'DIRECTO '!E21+#REF! -> #REF! | G22: =+'DIRECTO '!G21+#REF! -> #REF! | H22: =+'DIRECTO '!H21+#REF! -> #REF! | J22: =+'DIRECTO '!J21+#REF! -> #REF! | K22: =+'DIRECTO '!K21+#REF! -> #REF! | L22: =+SUM(N22:R22) -> #REF! | N22: =+'DIRECTO '!N21+#REF! -> #REF! | O22: =+'DIRECTO '!O21+#REF! -> #REF! | P22: =+'DIRECTO '!P21+#REF! -> #REF! | Q22: =+'DIRECTO '!Q21+#REF! -> #REF! | R22: =+'DIRECTO '!R21+#REF! -> #REF! | S22: =+SUMIFS(N22:R22,N$2:R$2,$S$5) -> 0 | U22: =+SUMIFS(N22:S22,N$2:S$2,$U$5) -> 0 | W22: =+X22 -> #REF! | X22: =+K22+L22 -> #REF! | Y22: =+'DIRECTO '!Z21+#REF! -> #REF! | Z22: =+'DIRECTO '!AA21+#REF! -> #REF! | AA22: =+'DIRECTO '!AB21+#REF! -> #REF! | AB22: =+'DIRECTO '!AC21+#REF! -> #REF! | AD22: =+'DIRECTO '!AE21+#REF! -> #REF! | AF22: =+AB22-X22 -> #REF! | AH22: =IF(ABS(X22-AG22)>1,"Revisar Rubros","OK") -> #REF! | AJ22: =SUM(AK22:CA22) -> #REF! | AK22: =+'DIRECTO '!AK21+#REF! -> #REF! | AL22: =+'DIRECTO '!AM21+#REF! -> #REF! | AM22: =+'DIRECTO '!AN21+#REF! -> #REF! | AN22: =+'DIRECTO '!AO21+#REF! -> #REF! | AO22: =+'DIRECTO '!AP21+#REF! -> #REF! | AP22: =+'DIRECTO '!AQ21+#REF! -> #REF! | AQ22: =+'DIRECTO '!#REF!+#REF! -> #REF! | AR22: =+'DIRECTO '!#REF!+#REF! -> #REF! | AS22: =+'DIRECTO '!#REF!+#REF! -> #REF! | AT22: =+'DIRECTO '!#REF!+#REF! -> #REF! | AU22: =+'DIRECTO '!#REF!+#REF! -> #REF! | AV22: =+'DIRECTO '!#REF!+#REF! -> #REF! | AW22: =+'DIRECTO '!#REF!+#REF! -> #REF! | AX22: =+'DIRECTO '!#REF!+#REF! -> #REF! | ... CA22: =+'DIRECTO '!#REF!+#REF! -> #REF! | CD22: 20864058
C23: Propios | E23: =+'DIRECTO '!E22+#REF! -> #REF! | G23: =+'DIRECTO '!G22+#REF! -> #REF! | H23: =+'DIRECTO '!H22+#REF! -> #REF! | J23: =+'DIRECTO '!J22+#REF! -> #REF! | K23: =+'DIRECTO '!K22+#REF! -> #REF! | L23: =+SUM(N23:R23) -> #REF! | N23: =+'DIRECTO '!N22+#REF! -> #REF! | O23: =+'DIRECTO '!O22+#REF! -> #REF! | P23: =+'DIRECTO '!P22+#REF! -> #REF! | Q23: =+'DIRECTO '!Q22+#REF! -> #REF! | R23: =+'DIRECTO '!R22+#REF! -> #REF! | S23: =+SUMIFS(N23:R23,N$2:R$2,$S$5) -> 0 | U23: =+SUMIFS(N23:S23,N$2:S$2,$U$5) -> 0 | W23: =+X23 -> #REF! | X23: =+K23+L23 -> #REF! | Y23: =+'DIRECTO '!Z22+#REF! -> #REF! | Z23: =+'DIRECTO '!AA22+#REF! -> #REF! | AA23: =+'DIRECTO '!AB22+#REF! -> #REF! | AB23: =+'DIRECTO '!AC22+#REF! -> #REF! | AD23: =+'DIRECTO '!AE22+#REF! -> #REF! | AF23: =+AB23-X23 -> #REF! | AG23: =+Eq!Y56 -> 0 | AH23: =IF(ABS(X23-AG23)>1,"Revisar Rubros","OK") -> #REF! | AJ23: =SUM(AK23:CA23) -> #REF! | AK23: =+'DIRECTO '!AK22+#REF! -> #REF! | AL23: =+'DIRECTO '!AM22+#REF! -> #REF! | AM23: =+'DIRECTO '!AN22+#REF! -> #REF! | AN23: =+'DIRECTO '!AO22+#REF! -> #REF! | AO23: =+'DIRECTO '!AP22+#REF! -> #REF! | AP23: =+'DIRECTO '!AQ22+#REF! -> #REF! | AQ23: =+'DIRECTO '!#REF!+#REF! -> #REF! | AR23: =+'DIRECTO '!#REF!+#REF! -> #REF! | AS23: =+'DIRECTO '!#REF!+#REF! -> #REF! | AT23: =+'DIRECTO '!#REF!+#REF! -> #REF! | AU23: =+'DIRECTO '!#REF!+#REF! -> #REF! | AV23: =+'DIRECTO '!#REF!+#REF! -> #REF! | AW23: =+'DIRECTO '!#REF!+#REF! -> #REF! | AX23: =+'DIRECTO '!#REF!+#REF! -> #REF! | ... CA23: =+'DIRECTO '!#REF!+#REF! -> #REF!
C24: Terceros | E24: =+'DIRECTO '!E23+#REF! -> #REF! | G24: =+'DIRECTO '!G23+#REF! -> #REF! | H24: =+'DIRECTO '!H23+#REF! -> #REF! | J24: =+'DIRECTO '!J23+#REF! -> #REF! | K24: =+'DIRECTO '!K23+#REF! -> #REF! | L24: =+SUM(N24:R24) -> #REF! | N24: =+'DIRECTO '!N23+#REF! -> #REF! | O24: =+'DIRECTO '!O23+#REF! -> #REF! | P24: =+'DIRECTO '!P23+#REF! -> #REF! | Q24: =+'DIRECTO '!Q23+#REF! -> #REF! | R24: =+'DIRECTO '!R23+#REF! -> #REF! | S24: =+SUMIFS(N24:R24,N$2:R$2,$S$5) -> 0 | U24: =+SUMIFS(N24:S24,N$2:S$2,$U$5) -> 0 | W24: =+X24 -> #REF! | X24: =+K24+L24 -> #REF! | Y24: =+'DIRECTO '!Z23+#REF! -> #REF! | Z24: =+'DIRECTO '!AA23+#REF! -> #REF! | AA24: =+'DIRECTO '!AB23+#REF! -> #REF! | AB24: =+'DIRECTO '!AC23+#REF! -> #REF! | AD24: =+'DIRECTO '!AE23+#REF! -> #REF! | AF24: =+AB24-X24 -> #REF! | AG24: =+Eq!Y57 -> 0 | AH24: =IF(ABS(X24-AG24)>1,"Revisar Rubros","OK") -> #REF! | AJ24: =SUM(AK24:CA24) -> #REF! | AK24: =+'DIRECTO '!AK23+#REF! -> #REF! | AL24: =+'DIRECTO '!AM23+#REF! -> #REF! | AM24: =+'DIRECTO '!AN23+#REF! -> #REF! | AN24: =+'DIRECTO '!AO23+#REF! -> #REF! | AO24: =+'DIRECTO '!AP23+#REF! -> #REF! | AP24: =+'DIRECTO '!AQ23+#REF! -> #REF! | AQ24: =+'DIRECTO '!#REF!+#REF! -> #REF! | AR24: =+'DIRECTO '!#REF!+#REF! -> #REF! | AS24: =+'DIRECTO '!#REF!+#REF! -> #REF! | AT24: =+'DIRECTO '!#REF!+#REF! -> #REF! | AU24: =+'DIRECTO '!#REF!+#REF! -> #REF! | AV24: =+'DIRECTO '!#REF!+#REF! -> #REF! | AW24: =+'DIRECTO '!#REF!+#REF! -> #REF! | AX24: =+'DIRECTO '!#REF!+#REF! -> #REF! | ... CA24: =+'DIRECTO '!#REF!+#REF! -> #REF!
B25: Fletes | E25: =+'DIRECTO '!E24+#REF! -> #REF! | G25: =+'DIRECTO '!G24+#REF! -> #REF! | H25: =+'DIRECTO '!H24+#REF! -> #REF! | J25: =+'DIRECTO '!J24+#REF! -> #REF! | K25: =+'DIRECTO '!K24+#REF! -> #REF! | L25: =+SUM(N25:R25) -> #REF! | N25: =+'DIRECTO '!N24+#REF! -> #REF! | O25: =+'DIRECTO '!O24+#REF! -> #REF! | P25: =+'DIRECTO '!P24+#REF! -> #REF! | Q25: =+'DIRECTO '!Q24+#REF! -> #REF! | R25: =+'DIRECTO '!R24+#REF! -> #REF! | S25: =+SUMIFS(N25:R25,N$2:R$2,$S$5) -> 0 | U25: =+SUMIFS(N25:S25,N$2:S$2,$U$5) -> 0 | W25: =+X25 -> #REF! | X25: =+K25+L25 -> #REF! | Y25: =+'DIRECTO '!Z24+#REF! -> #REF! | Z25: =+'DIRECTO '!AA24+#REF! -> #REF! | AA25: =+'DIRECTO '!AB24+#REF! -> #REF! | AB25: =+'DIRECTO '!AC24+#REF! -> #REF! | AD25: =+'DIRECTO '!AE24+#REF! -> #REF! | AF25: =+AB25-X25 -> #REF! | AG25: =+Fletes!Y39 -> 0 | AH25: =IF(ABS(X25-AG25)>1,"Revisar Rubros","OK") -> #REF! | AJ25: =SUM(AK25:CA25) -> #REF! | AK25: =+'DIRECTO '!AK24+#REF! -> #REF! | AL25: =+'DIRECTO '!AM24+#REF! -> #REF! | AM25: =+'DIRECTO '!AN24+#REF! -> #REF! | AN25: =+'DIRECTO '!AO24+#REF! -> #REF! | AO25: =+'DIRECTO '!AP24+#REF! -> #REF! | AP25: =+'DIRECTO '!AQ24+#REF! -> #REF! | AQ25: =+'DIRECTO '!#REF!+#REF! -> #REF! | AR25: =+'DIRECTO '!#REF!+#REF! -> #REF! | AS25: =+'DIRECTO '!#REF!+#REF! -> #REF! | AT25: =+'DIRECTO '!#REF!+#REF! -> #REF! | AU25: =+'DIRECTO '!#REF!+#REF! -> #REF! | AV25: =+'DIRECTO '!#REF!+#REF! -> #REF! | AW25: =+'DIRECTO '!#REF!+#REF! -> #REF! | AX25: =+'DIRECTO '!#REF!+#REF! -> #REF! | ... CA25: =+'DIRECTO '!#REF!+#REF! -> #REF!
B26: Staff (Sueldos) | E26: =+'DIRECTO '!E25+#REF! -> #REF! | G26: =+'DIRECTO '!G25+#REF! -> #REF! | H26: =+'DIRECTO '!H25+#REF! -> #REF! | J26: =+'DIRECTO '!J25+#REF! -> #REF! | K26: =+'DIRECTO '!K25+#REF! -> #REF! | L26: =+SUM(N26:R26) -> #REF! | N26: =+'DIRECTO '!N25+#REF! -> #REF! | O26: =+'DIRECTO '!O25+#REF! -> #REF! | P26: =+'DIRECTO '!P25+#REF! -> #REF! | Q26: =+'DIRECTO '!Q25+#REF! -> #REF! | R26: =+'DIRECTO '!R25+#REF! -> #REF! | S26: =+SUMIFS(N26:R26,N$2:R$2,$S$5) -> 0 | U26: =+SUMIFS(N26:S26,N$2:S$2,$U$5) -> 0 | W26: =+X26 -> #REF! | X26: =+K26+L26 -> #REF! | Y26: =+'DIRECTO '!Z25+#REF! -> #REF! | Z26: =+'DIRECTO '!AA25+#REF! -> #REF! | AA26: =+'DIRECTO '!AB25+#REF! -> #REF! | AB26: =+'DIRECTO '!AC25+#REF! -> #REF! | AD26: =+'DIRECTO '!AE25+#REF! -> #REF! | AF26: =+AB26-X26 -> #REF! | AG26: =+Staff!BK27 -> 0 | AH26: =IF(ABS(X26-AG26)>1,"Revisar Rubros","OK") -> #REF! | AJ26: =SUM(AK26:CA26) -> #REF! | AK26: =+'DIRECTO '!AK25+#REF! -> #REF! | AL26: =+'DIRECTO '!AM25+#REF! -> #REF! | AM26: =+'DIRECTO '!AN25+#REF! -> #REF! | AN26: =+'DIRECTO '!AO25+#REF! -> #REF! | AO26: =+'DIRECTO '!AP25+#REF! -> #REF! | AP26: =+'DIRECTO '!AQ25+#REF! -> #REF! | AQ26: =+'DIRECTO '!#REF!+#REF! -> #REF! | AR26: =+'DIRECTO '!#REF!+#REF! -> #REF! | AS26: =+'DIRECTO '!#REF!+#REF! -> #REF! | AT26: =+'DIRECTO '!#REF!+#REF! -> #REF! | AU26: =+'DIRECTO '!#REF!+#REF! -> #REF! | AV26: =+'DIRECTO '!#REF!+#REF! -> #REF! | AW26: =+'DIRECTO '!#REF!+#REF! -> #REF! | AX26: =+'DIRECTO '!#REF!+#REF! -> #REF! | ... CA26: =+'DIRECTO '!#REF!+#REF! -> #REF! | CD26: 21280334 | CE26: =+CD26-X26 -> #REF! | CG26: =+CG27/X16 -> #REF!
B27: Gastos Generales | E27: =+'DIRECTO '!E26+#REF! -> #REF! | G27: =+'DIRECTO '!G26+#REF! -> #REF! | H27: =+'DIRECTO '!H26+#REF! -> #REF! | J27: =+'DIRECTO '!J26+#REF! -> #REF! | K27: =+'DIRECTO '!K26+#REF! -> #REF! | L27: =+SUM(N27:R27) -> #REF! | N27: =+'DIRECTO '!N26+#REF! -> #REF! | O27: =+'DIRECTO '!O26+#REF! -> #REF! | P27: =+'DIRECTO '!P26+#REF! -> #REF! | Q27: =+'DIRECTO '!Q26+#REF! -> #REF! | R27: =+'DIRECTO '!R26+#REF! -> #REF! | S27: =+SUMIFS(N27:R27,N$2:R$2,$S$5) -> 0 | U27: =+SUMIFS(N27:S27,N$2:S$2,$U$5) -> 0 | W27: =+X27 -> #REF! | X27: =+K27+L27 -> #REF! | Y27: =+'DIRECTO '!Z26+#REF! -> #REF! | Z27: =+'DIRECTO '!AA26+#REF! -> #REF! | AA27: =+'DIRECTO '!AB26+#REF! -> #REF! | AB27: =+'DIRECTO '!AC26+#REF! -> #REF! | AD27: =+'DIRECTO '!AE26+#REF! -> #REF! | AF27: =+AB27-X27 -> #REF! | AG27: =+GG!Y35 -> 24799.991 | AH27: =IF(ABS(X27-AG27)>1,"Revisar Rubros","OK") -> #REF! | AJ27: =SUM(AK27:CA27) -> #REF! | AK27: =+'DIRECTO '!AK26+#REF! -> #REF! | AL27: =+'DIRECTO '!AM26+#REF! -> #REF! | AM27: =+'DIRECTO '!AN26+#REF! -> #REF! | AN27: =+'DIRECTO '!AO26+#REF! -> #REF! | AO27: =+'DIRECTO '!AP26+#REF! -> #REF! | AP27: =+'DIRECTO '!AQ26+#REF! -> #REF! | AQ27: =+'DIRECTO '!#REF!+#REF! -> #REF! | AR27: =+'DIRECTO '!#REF!+#REF! -> #REF! | AS27: =+'DIRECTO '!#REF!+#REF! -> #REF! | AT27: =+'DIRECTO '!#REF!+#REF! -> #REF! | AU27: =+'DIRECTO '!#REF!+#REF! -> #REF! | AV27: =+'DIRECTO '!#REF!+#REF! -> #REF! | AW27: =+'DIRECTO '!#REF!+#REF! -> #REF! | AX27: =+'DIRECTO '!#REF!+#REF! -> #REF! | ... CA27: =+'DIRECTO '!#REF!+#REF! -> #REF! | CD27: 12574362 | CG27: =+X27+X26 -> #REF!
B29: Stock de Materiales | E29: =+'DIRECTO '!E28+#REF! -> #REF! | G29: =+'DIRECTO '!G28+#REF! -> #REF! | H29: =+'DIRECTO '!H28+#REF! -> #REF! | J29: =+'DIRECTO '!J28+#REF! -> #REF! | K29: =+'DIRECTO '!K28+#REF! -> #REF! | L29: =+SUM(N29:R29) -> #REF! | N29: =+'DIRECTO '!N28+#REF! -> #REF! | O29: =+'DIRECTO '!O28+#REF! -> #REF! | P29: =+'DIRECTO '!P28+#REF! -> #REF! | Q29: =+'DIRECTO '!Q28+#REF! -> #REF! | R29: =+'DIRECTO '!R28+#REF! -> #REF! | S29: =+SUMIFS(N29:R29,N$2:R$2,$S$5) -> 0 | U29: =+SUMIFS(N29:S29,N$2:S$2,$U$5) -> 0 | X29: =+K29+L29 -> #REF! | Y29: =+'DIRECTO '!Z28+#REF! -> #REF! | Z29: =+'DIRECTO '!AA28+#REF! -> #REF! | AA29: =+'DIRECTO '!AB28+#REF! -> #REF! | AB29: =+'DIRECTO '!AC28+#REF! -> #REF! | AD29: =+'DIRECTO '!AE28+#REF! -> #REF! | AJ29: =SUM(AK29:CA29) -> #REF! | AK29: =+'DIRECTO '!AK28+#REF! -> #REF! | AL29: =+'DIRECTO '!AM28+#REF! -> #REF! | AM29: =+'DIRECTO '!AN28+#REF! -> #REF! | AN29: =+'DIRECTO '!AO28+#REF! -> #REF! | AO29: =+'DIRECTO '!AP28+#REF! -> #REF! | AP29: =+'DIRECTO '!AQ28+#REF! -> #REF! | AQ29: =+'DIRECTO '!#REF!+#REF! -> #REF! | AR29: =+'DIRECTO '!#REF!+#REF! -> #REF! | AS29: =+'DIRECTO '!#REF!+#REF! -> #REF! | AT29: =+'DIRECTO '!#REF!+#REF! -> #REF! | AU29: =+'DIRECTO '!#REF!+#REF! -> #REF! | AV29: =+'DIRECTO '!#REF!+#REF! -> #REF! | AW29: =+'DIRECTO '!#REF!+#REF! -> #REF! | AX29: =+'DIRECTO '!#REF!+#REF! -> #REF! | ... CA29: =+'DIRECTO '!#REF!+#REF! -> #REF! | CD29: 5329828.3
B31: Margen Ponderado S/. | C31: S/. | E31: =+E7*E32 -> #REF! | G31: =+G7*G32 -> #REF! | H31: =+H7*H32 -> #REF! | J31: =+J7*J32 -> #REF! | K31: =+K7*K32 -> #REF! | L31: =+L7*L32 -> #REF! | N31: =+N7*N32 -> #REF! | O31: =+O7*O32 -> #REF! | P31: =+P7*P32 -> #REF! | Q31: =+Q7*Q32 -> #REF! | R31: =+R7*R32 -> #REF! | S31: =+S7*S32 -> #REF! | U31: =+U7*U32 -> #REF! | W31: =+W7-W16 -> #REF! | X31: =+X7-X16 -> #REF! | Y31: =+Y7-Y16 -> #REF! | Z31: =+Z7-Z16 -> #REF! | AA31: =+AA7-AA16 -> #REF! | AB31: =+AB7-AB16 -> #REF! | AD31: 0 | AF31: =+X31-Y31 -> #REF! | AH31: =+X31 -> #REF! | CD31: =+X31-Y31 -> #REF!
C32: % | E32: =+$X$32 -> #REF! | G32: =+$X$32 -> #REF! | H32: =+$X$32 -> #REF! | J32: =+$X$32 -> #REF! | K32: =+$X$32 -> #REF! | L32: =+$X$32 -> #REF! | N32: =+$X$32 -> #REF! | O32: =+$X$32 -> #REF! | P32: =+$X$32 -> #REF! | Q32: =+$X$32 -> #REF! | R32: =+$X$32 -> #REF! | S32: =+$X$32 -> #REF! | U32: =+$X$32 -> #REF! | W32: =+IF(W7=0,0,W31/W7) -> #REF! | X32: =+IF(X7=0,0,X31/X7) -> #REF! | Y32: =+IF(Y7=0,0,Y31/Y7) -> #REF! | Z32: =+IF(Z7=0,0,Z31/Z7) -> #REF! | AA32: =+IF(AA7=0,0,AA31/AA7) -> #REF! | AB32: =+IF(AB7=0,0,AB31/AB7) -> #REF! | AD32: 0 | CD32: =+X32-Y32 -> #REF!
B34: Margen Absoluto | C34: S/. | E34: =+E7-E16+E29 -> #REF! | G34: =+G7-G16+G29 -> #REF! | H34: =+H7-H16+H29 -> #REF! | J34: =+J7-J16+J29 -> #REF! | K34: =+K7-K16 -> #REF! | L34: =+L7-L16 -> #REF! | N34: =+N7-N16+N29 -> #REF! | O34: =+O7-O16+O29 -> #REF! | P34: =+P7-P16+P29 -> #REF! | Q34: =+Q7-Q16+Q29 -> #REF! | R34: =+R7-R16+R29 -> #REF! | S34: =+S7-S16+S29 -> 0 | U34: =+U7-U16+U29 -> 0 | W34: =+W7-W16+W29 -> #REF! | X34: =+X7-X16+X29 -> #REF! | Y34: =+Y7-Y16+Y29 -> #REF! | Z34: =+Z7-Z16+Z29 -> #REF! | AA34: =+AA7-AA16+AA29 -> #REF! | AB34: =+AB7-AB16+AB29 -> #REF! | AD34: 0
C35: % | E35: =+IF(E9=0,0,E34/E9) -> #REF! | G35: =+IF(G9=0,0,G34/G9) -> #REF! | H35: =+IF(H9=0,0,H34/H9) -> #REF! | J35: =+IF(J7=0,0,J34/J7) -> #REF! | K35: =+IF(K7=0,0,K34/K7) -> #REF! | L35: =+IF(L7=0,0,L34/L7) -> #REF! | N35: =+IF(N7=0,0,N34/N7) -> #REF! | O35: =+IF(O7=0,0,O34/O7) -> #REF! | P35: =+IF(P7=0,0,P34/P7) -> #REF! | Q35: =+IF(Q7=0,0,Q34/Q7) -> #REF! | R35: =+IF(R7=0,0,R34/R7) -> #REF! | S35: =+IF(S7=0,0,S34/S7) -> 0 | U35: =+IF(U7=0,0,U34/U7) -> 0 | W35: =+IF(W7=0,0,W34/W7) -> #REF! | X35: =+IF(X7=0,0,X34/X7) -> #REF! | Y35: =+IF(Y7=0,0,Y34/Y7) -> #REF! | Z35: =+IF(Z7=0,0,Z34/Z7) -> #REF! | AA35: =+IF(AA7=0,0,AA34/AA7) -> #REF! | AB35: =+IF(AB7=0,0,AB34/AB7) -> #REF! | AD35: 0
W37: =+W35-CONSOLIDADO!W34 -> #REF! | X37: =+X35-CONSOLIDADO!W34 -> #REF!
B39: COSTO APLICADO | K39: =+K7-K31 -> #REF! | W39: =+W31-CONSOLIDADO!W33 -> #REF! | X39: =+X31-CONSOLIDADO!W33 -> #REF! | CD39: =Y31 -> #REF! | CE39: =+X32-Y32 -> #REF!
B41: RESULTADO PENDIENTE | K41: =K16-K39 -> #REF! | CD41: =X31 -> #REF! | CE41: =+CD41-CD39 -> #REF!
B43: ACTIVOS | K43: ='ER Pendiente'!H40+'ER Pendiente'!H15 -> #REF!
B45: PROVISIONES | K45: =+'ER Pendiente'!I40+'ER Pendiente'!I22 -> 0
B47: DIFERENCIA DE MARGENES | K47: =+'DIRECTO '!K46+#REF! -> #REF!
B49: CONTINGENCIA | K49: =+K41-K43+K45 -> #REF!
C51: Mayor Margen +
C53: Menor Margen -
B56: MARGEN CONSORCIO (PONDERADO) | X56: 11555 | AB56: 16571
B57: MARGEN GARANTIZADO | X57: 10554 | AB57: 10554
B58: MARGEN POR PRODUCTIVIDAD | X58: 10.01 | AB58: 59.97
B60: PARTICIPACION SOCIO/S: | X60: 5677 | AB60: 7676
B61: MARGEN GARANTIZADO | X61: 5277 | AB61: 5277
B62: MARGEN POR PRODUCTIVIDAD | X62: 4 | AB62: 23.99
B64: PARTICIPACION CMO | X64: 5878 | AB64: 8875
B65: MARGEN GARANTIZADO | X65: 5277 | AB65: 5277
B66: MARGEN POR PRODUCTIVIDAD | X66: 6.01 | AB66: 35.98
B100: DESEMPEÑO DEL PROYECTO | K100: =K34 -> #REF! | L100: =+K100+L34 -> #REF! | N100: =+K100+N34 -> #REF! | O100: =+N100+O34 -> #REF! | P100: =+O100+P34 -> #REF! | Q100: =+P100+Q34 -> #REF! | R100: =+Q100+R34 -> #REF! | S100: =+K100+S34 -> #REF! | U100: =+S100+U34 -> #REF! | X100: =X34 -> #REF! | AB100: =AB34 -> #REF!
B101: DIRECTO | C101: ='DIRECTO '!K15 -> #REF! | E101: =IF(C101-SUM(C105:C113)=0,"OK","REVISAR") -> #REF!
B102: INDIRECTO | C102: =#REF! -> #REF! | E102: =IF(C102-SUM(E105:E113)=0,"OK","REVISAR") -> #REF!
C104: DIRECTO | E104: INDIRECTO
B105: Materiales | C105: ='DIRECTO '!K17 -> #REF! | E105: =#REF! -> #REF!
B106: Mano de Obra | C106: ='DIRECTO '!K18 -> #REF! | E106: =#REF! -> #REF!
B107: Subcontratos de obra | C107: ='DIRECTO '!K19 -> #REF! | E107: =#REF! -> #REF!
B108: Servicios Contratados | C108: ='DIRECTO '!K20 -> #REF! | E108: =#REF! -> #REF!
B109: Equipos y Vehículos (Propios) | C109: ='DIRECTO '!K22 -> #REF! | E109: =#REF! -> #REF!
B110: Equipos y Vehículos (Terceros) | C110: ='DIRECTO '!K23 -> #REF! | E110: =#REF! -> #REF!
B111: Fletes | C111: ='DIRECTO '!K24 -> #REF! | E111: =#REF! -> #REF!
B112: Staff (Sueldos) | C112: ='DIRECTO '!K25 -> #REF! | E112: =#REF! -> #REF!
B113: Gastos Generales | C113: ='DIRECTO '!K26 -> #REF! | E113: =#REF! -> #REF!

Sheet CONSOLIDADO
B1: =CONCATENATE(B3," - ",B4," - ",B5," - ",B6) -> I.E.N 1182 - MES DE JULIO 2024 - EL BOSQUE - CERCO + INGRESOS Y CASETAS - CONSOLIDADO - JULIO 2024
N2: =+YEAR(N5) -> 2024 | O2: =+YEAR(O5) -> 2024 | P2: =+YEAR(P5) -> 2024 | Q2: =+YEAR(Q5) -> 2024 | R2: =+YEAR(R5) -> 2024 | S2: =S5 -> 2024
B3: I.E.N 1182 | E3: ACUMULADO | G3: MES DE JULIO 2024 | J3: ACUMULADO DEL 2024 | K3: ACUMULADO DE OBRA | L3: SALDO DE OBRA | N3: PROYECCIÓN | U3: AÑOS SIGUIENTES | W3: TOTAL DE OBRA | AC3: Acum. del Ej. | AE3: TOTAL | AF3: MES DEL INFORME | AG3: ANTERIORES | AH3: 45474 | AI3: 45505 | AJ3: 45536 | AK3: 45566 | AL3: 45597
B4: MES DE JULIO 2024 | N4: 1 | O4: =+N4+1 -> 2 | P4: =+O4+1 -> 3 | Q4: =+P4+1 -> 4 | R4: =+Q4+1 -> 5 | S4: Saldo del Ejercicio
B5: EL BOSQUE - CERCO + INGRESOS Y CASETAS | E5: Años Anteriores | G5: Previsto | H5: Real | N5: 45475 | O5: =+N5+31 -> 45506 | P5: =+O5+31 -> 45537 | Q5: =+P5+31 -> 45568 | R5: =+Q5+31 -> 45599 | S5: 2024 | U5: =+S5+1 -> 2025 | W5: Actual | X5: Anterior | Y5: Meta | Z5: Presupuesto Interno | AA5: Presupuesto | AC5: Anterior
B6: CONSOLIDADO - JULIO 2024
B7: Venta Total Producida | E7: =+E9 -> #REF! | G7: =+G9 -> #REF! | H7: =+H9 -> #REF! | J7: =+J9 -> #REF! | K7: =+K9 -> #REF! | L7: =+L9 -> #REF! | N7: =+N9 -> #REF! | O7: =+O9 -> #REF! | P7: =+P9 -> #REF! | Q7: =+Q9 -> #REF! | R7: =+R9 -> #REF! | S7: =+S9 -> #REF! | U7: =+U9 -> 0 | W7: =+W9 -> #REF! | X7: =+X9 -> #REF! | Y7: =+Y9 -> #REF! | Z7: =+Z9 -> #REF! | AA7: =+AA9 -> #REF! | AC7: =+AC9 -> #REF!
B9: Venta | E9: =+SUM(E11:E13) -> #REF! | G9: =+SUM(G11:G13) -> #REF! | H9: =+SUM(H11:H13) -> #REF! | J9: =+SUM(J11:J13) -> #REF! | K9: =+SUM(K11:K13) -> #REF! | L9: =+SUM(L11:L13) -> #REF! | N9: =+SUM(N11:N13) -> #REF! | O9: =+SUM(O11:O13) -> #REF! | P9: =+SUM(P11:P13) -> #REF! | Q9: =+SUM(Q11:Q13) -> #REF! | R9: =+SUM(R11:R13) -> #REF! | S9: =+SUM(S11:S13) -> #REF! | U9: =+SUM(U11:U13) -> 0 | W9: =+SUM(W11:W13) -> #REF! | X9: =+SUM(X11:X13) -> #REF! | Y9: =+SUM(Y11:Y13) -> #REF! | Z9: =+SUM(Z11:Z13) -> #REF! | AA9: =+SUM(AA11:AA13) -> #REF! | AC9: =+SUM(AC11:AC13) -> #REF!
B11: Valorización: Venta Directa - Contrato Principal | E11: =+'DIRECTO '!E11+#REF! -> #REF! | G11: =+'DIRECTO '!G11+#REF! -> #REF! | H11: =+'DIRECTO '!H11+#REF! -> #REF! | J11: =+'DIRECTO '!J11+#REF! -> #REF! | K11: =+'DIRECTO '!K11+#REF! -> #REF! | L11: =+SUM(N11:R11) -> #REF! | N11: =+'DIRECTO '!N11+#REF! -> #REF! | O11: =+'DIRECTO '!O11+#REF! -> #REF! | P11: =+'DIRECTO '!P11+#REF! -> #REF! | Q11: =+'DIRECTO '!Q11+#REF! -> #REF! | R11: =+'DIRECTO '!R11+#REF! -> #REF! | S11: =+SUMIFS(N11:R11,N$2:R$2,$S$5) -> #REF! | U11: =+SUMIFS(N11:S11,N$2:S$2,$U$5) -> 0 | W11: =+K11+L11 -> #REF! | X11: =+'DIRECTO '!Z11+#REF! -> #REF! | Y11: =+'DIRECTO '!AA11+#REF! -> #REF! | Z11: =+'DIRECTO '!AB11+#REF! -> #REF! | AA11: =+'DIRECTO '!AC11+#REF! -> #REF! | AC11: =+'DIRECTO '!AE11+#REF! -> #REF!
B12: Valorización: Venta Indirecta - Contrato Principal | E12: =+'DIRECTO '!E12+#REF! -> #REF! | G12: =+'DIRECTO '!G12+#REF! -> #REF! | H12: =+'DIRECTO '!H12+#REF! -> #REF! | J12: =+'DIRECTO '!J12+#REF! -> #REF! | K12: =+'DIRECTO '!K12+#REF! -> #REF! | L12: =+SUM(N12:R12) -> #REF! | N12: =+'DIRECTO '!N12+#REF! -> #REF! | O12: =+'DIRECTO '!O12+#REF! -> #REF! | P12: =+'DIRECTO '!P12+#REF! -> #REF! | Q12: =+'DIRECTO '!Q12+#REF! -> #REF! | R12: =+'DIRECTO '!R12+#REF! -> #REF! | S12: =+SUMIFS(N12:R12,N$2:R$2,$S$5) -> #REF! | U12: =+SUMIFS(N12:S12,N$2:S$2,$U$5) -> 0 | W12: =+K12+L12 -> #REF! | X12: =+'DIRECTO '!Z12+#REF! -> #REF! | Y12: =+'DIRECTO '!AA12+#REF! -> #REF! | Z12: =+'DIRECTO '!AB12+#REF! -> #REF! | AA12: =+'DIRECTO '!AC12+#REF! -> #REF! | AC12: =+'DIRECTO '!AE12+#REF! -> #REF!
B13: Otros: | E13: =+'DIRECTO '!#REF!+#REF! -> #REF! | G13: =+'DIRECTO '!#REF!+#REF! -> #REF! | H13: =+'DIRECTO '!#REF!+#REF! -> #REF! | J13: =+'DIRECTO '!#REF!+#REF! -> #REF! | K13: =+'DIRECTO '!#REF!+#REF! -> #REF! | L13: =+SUM(N13:R13) -> #REF! | N13: =+'DIRECTO '!#REF!+#REF! -> #REF! | O13: =+'DIRECTO '!#REF!+#REF! -> #REF! | P13: =+'DIRECTO '!#REF!+#REF! -> #REF! | Q13: =+'DIRECTO '!#REF!+#REF! -> #REF! | R13: =+'DIRECTO '!#REF!+#REF! -> #REF! | S13: =+SUMIFS(N13:R13,N$2:R$2,$S$5) -> #REF! | U13: =+SUMIFS(N13:S13,N$2:S$2,$U$5) -> 0 | W13: =+K13+L13 -> #REF! | X13: =+'DIRECTO '!#REF!+#REF! -> #REF! | Y13: =+'DIRECTO '!#REF!+#REF! -> #REF! | Z13: =+'DIRECTO '!#REF!+#REF! -> #REF! | AA13: =+'DIRECTO '!#REF!+#REF! -> #REF! | AC13: =+'DIRECTO '!#REF!+#REF! -> #REF!
B15: Costo Total | E15: =+SUM(E17:E26)+E28 -> #REF! | G15: =+SUM(G17:G26,G28) -> #REF! | H15: =SUM(H17:H26,H28) -> #REF! | J15: =+SUM(J17:J26,J28) -> #REF! | K15: =+SUM(K17:K26,K28) -> #REF! | L15: =+SUM(L17:L26,L28) -> #REF! | N15: =+SUM(N17:N26,N28) -> #REF! | O15: =+SUM(O17:O26,O28) -> #REF! | P15: =+SUM(P17:P26,P28) -> #REF! | Q15: =+SUM(Q17:Q26,Q28) -> #REF! | R15: =+SUM(R17:R26,R28) -> #REF! | S15: =+SUM(S17:S26,S28) -> #REF! | U15: =+SUM(U17:U26,U28) -> 0 | W15: =+SUM(W17:W26,W28) -> #REF! | X15: =+SUM(X17:X26,X28) -> #REF! | Y15: =+SUM(Y17:Y26,Y28) -> #REF! | Z15: =+SUM(Z17:Z26,Z28) -> #REF! | AA15: =+SUM(AA17:AA26,AA28) -> #REF! | AC15: =+SUM(AC17:AC26,AC28) -> #REF! | AO15: 525387.51
B17: Materiales | E17: =+'DIRECTO '!E17+#REF! -> #REF! | G17: =+'DIRECTO '!G17+#REF! -> #REF! | H17: =+'DIRECTO '!H17+#REF! -> #REF! | J17: =+'DIRECTO '!J17+#REF! -> #REF! | K17: =+'DIRECTO '!K17+#REF! -> #REF! | L17: =+SUM(N17:R17) -> #REF! | N17: =+'DIRECTO '!N17+#REF! -> #REF! | O17: =+'DIRECTO '!O17+#REF! -> #REF! | P17: =+'DIRECTO '!P17+#REF! -> #REF! | Q17: =+'DIRECTO '!Q17+#REF! -> #REF! | R17: =+'DIRECTO '!R17+#REF! -> #REF! | S17: =+SUMIFS(N17:R17,N$2:R$2,$S$5) -> #REF! | U17: =+SUMIFS(N17:S17,N$2:S$2,$U$5) -> 0 | W17: =+K17+L17 -> #REF! | X17: =+'DIRECTO '!Z17+#REF! -> #REF! | Y17: =+'DIRECTO '!AA17+#REF! -> #REF! | Z17: =+'DIRECTO '!AB17+#REF! -> #REF! | AA17: =+'DIRECTO '!AC17+#REF! -> #REF! | AC17: =+'DIRECTO '!AE17+#REF! -> #REF!
B18: Mano de Obra | E18: =+'DIRECTO '!E18+#REF! -> #REF! | G18: =+'DIRECTO '!G18+#REF! -> #REF! | H18: =+'DIRECTO '!H18+#REF! -> #REF! | J18: =+'DIRECTO '!J18+#REF! -> #REF! | K18: =+'DIRECTO '!K18+#REF! -> #REF! | L18: =+SUM(N18:R18) -> #REF! | N18: =+'DIRECTO '!N18+#REF! -> #REF! | O18: =+'DIRECTO '!O18+#REF! -> #REF! | P18: =+'DIRECTO '!P18+#REF! -> #REF! | Q18: =+'DIRECTO '!Q18+#REF! -> #REF! | R18: =+'DIRECTO '!R18+#REF! -> #REF! | S18: =+SUMIFS(N18:R18,N$2:R$2,$S$5) -> #REF! | U18: =+SUMIFS(N18:S18,N$2:S$2,$U$5) -> 0 | W18: =+K18+L18 -> #REF! | X18: =+'DIRECTO '!Z18+#REF! -> #REF! | Y18: =+'DIRECTO '!AA18+#REF! -> #REF! | Z18: =+'DIRECTO '!AB18+#REF! -> #REF! | AA18: =+'DIRECTO '!AC18+#REF! -> #REF! | AC18: =+'DIRECTO '!AE18+#REF! -> #REF!
B19: Subcontratos de obra | E19: =+'DIRECTO '!E19+#REF! -> #REF! | G19: =+'DIRECTO '!G19+#REF! -> #REF! | H19: =+'DIRECTO '!H19+#REF! -> #REF! | J19: =+'DIRECTO '!J19+#REF! -> #REF! | K19: =+'DIRECTO '!K19+#REF! -> #REF! | L19: =+SUM(N19:R19) -> #REF! | N19: =+'DIRECTO '!N19+#REF! -> #REF! | O19: =+'DIRECTO '!O19+#REF! -> #REF! | P19: =+'DIRECTO '!P19+#REF! -> #REF! | Q19: =+'DIRECTO '!Q19+#REF! -> #REF! | R19: =+'DIRECTO '!R19+#REF! -> #REF! | S19: =+SUMIFS(N19:R19,N$2:R$2,$S$5) -> #REF! | U19: =+SUMIFS(N19:S19,N$2:S$2,$U$5) -> 0 | W19: =+K19+L19 -> #REF! | X19: =+'DIRECTO '!Z19+#REF! -> #REF! | Y19: =+'DIRECTO '!AA19+#REF! -> #REF! | Z19: =+'DIRECTO '!AB19+#REF! -> #REF! | AA19: =+'DIRECTO '!AC19+#REF! -> #REF! | AC19: =+'DIRECTO '!AE19+#REF! -> #REF!
B20: Servicios Contratados | E20: =+'DIRECTO '!E20+#REF! -> #REF! | G20: =+'DIRECTO '!G20+#REF! -> #REF! | H20: =+'DIRECTO '!H20+#REF! -> #REF! | J20: =+'DIRECTO '!J20+#REF! -> #REF! | K20: =+'DIRECTO '!K20+#REF! -> #REF! | L20: =+SUM(N20:R20) -> #REF! | N20: =+'DIRECTO '!N20+#REF! -> #REF! | O20: =+'DIRECTO '!O20+#REF! -> #REF! | P20: =+'DIRECTO '!P20+#REF! -> #REF! | Q20: =+'DIRECTO '!Q20+#REF! -> #REF! | R20: =+'DIRECTO '!R20+#REF! -> #REF! | S20: =+SUMIFS(N20:R20,N$2:R$2,$S$5) -> #REF! | U20: =+SUMIFS(N20:S20,N$2:S$2,$U$5) -> 0 | W20: =+K20+L20 -> #REF! | X20: =+'DIRECTO '!Z20+#REF! -> #REF! | Y20: =+'DIRECTO '!AA20+#REF! -> #REF! | Z20: =+'DIRECTO '!AB20+#REF! -> #REF! | AA20: =+'DIRECTO '!AC20+#REF! -> #REF! | AC20: =+'DIRECTO '!AE20+#REF! -> #REF! | AO20: =+W15-W25-W26 -> #REF!
B21: Equipos y Vehículos | E21: =+'DIRECTO '!E21+#REF! -> #REF! | G21: =+'DIRECTO '!G21+#REF! -> #REF! | H21: =+'DIRECTO '!H21+#REF! -> #REF! | J21: =+'DIRECTO '!J21+#REF! -> #REF! | K21: =+'DIRECTO '!K21+#REF! -> #REF! | L21: =+SUM(N21:R21) -> #REF! | N21: =+'DIRECTO '!N21+#REF! -> #REF! | O21: =+'DIRECTO '!O21+#REF! -> #REF! | P21: =+'DIRECTO '!P21+#REF! -> #REF! | Q21: =+'DIRECTO '!Q21+#REF! -> #REF! | R21: =+'DIRECTO '!R21+#REF! -> #REF! | S21: =+SUMIFS(N21:R21,N$2:R$2,$S$5) -> #REF! | U21: =+SUMIFS(N21:S21,N$2:S$2,$U$5) -> 0 | W21: =+K21+L21 -> #REF! | X21: =+'DIRECTO '!Z21+#REF! -> #REF! | Y21: =+'DIRECTO '!AA21+#REF! -> #REF! | Z21: =+'DIRECTO '!AB21+#REF! -> #REF! | AA21: =+'DIRECTO '!AC21+#REF! -> #REF! | AC21: =+'DIRECTO '!AE21+#REF! -> #REF! | AO21: 20864058
C22: Propios | E22: =+'DIRECTO '!E22+#REF! -> #REF! | G22: =+'DIRECTO '!G22+#REF! -> #REF! | H22: =+'DIRECTO '!H22+#REF! -> #REF! | J22: =+'DIRECTO '!J22+#REF! -> #REF! | K22: =+'DIRECTO '!K22+#REF! -> #REF! | L22: =+SUM(N22:R22) -> #REF! | N22: =+'DIRECTO '!N22+#REF! -> #REF! | O22: =+'DIRECTO '!O22+#REF! -> #REF! | P22: =+'DIRECTO '!P22+#REF! -> #REF! | Q22: =+'DIRECTO '!Q22+#REF! -> #REF! | R22: =+'DIRECTO '!R22+#REF! -> #REF! | S22: =+SUMIFS(N22:R22,N$2:R$2,$S$5) -> #REF! | U22: =+SUMIFS(N22:S22,N$2:S$2,$U$5) -> 0 | W22: =+K22+L22 -> #REF! | X22: =+'DIRECTO '!Z22+#REF! -> #REF! | Y22: =+'DIRECTO '!AA22+#REF! -> #REF! | Z22: =+'DIRECTO '!AB22+#REF! -> #REF! | AA22: =+'DIRECTO '!AC22+#REF! -> #REF! | AC22: =+'DIRECTO '!AE22+#REF! -> #REF!
C23: Terceros | E23: =+'DIRECTO '!E23+#REF! -> #REF! | G23: =+'DIRECTO '!G23+#REF! -> #REF! | H23: =+'DIRECTO '!H23+#REF! -> #REF! | J23: =+'DIRECTO '!J23+#REF! -> #REF! | K23: =+'DIRECTO '!K23+#REF! -> #REF! | L23: =+SUM(N23:R23) -> #REF! | N23: =+'DIRECTO '!N23+#REF! -> #REF! | O23: =+'DIRECTO '!O23+#REF! -> #REF! | P23: =+'DIRECTO '!P23+#REF! -> #REF! | Q23: =+'DIRECTO '!Q23+#REF! -> #REF! | R23: =+'DIRECTO '!R23+#REF! -> #REF! | S23: =+SUMIFS(N23:R23,N$2:R$2,$S$5) -> #REF! | U23: =+SUMIFS(N23:S23,N$2:S$2,$U$5) -> 0 | W23: =+K23+L23 -> #REF! | X23: =+'DIRECTO '!Z23+#REF! -> #REF! | Y23: =+'DIRECTO '!AA23+#REF! -> #REF! | Z23: =+'DIRECTO '!AB23+#REF! -> #REF! | AA23: =+'DIRECTO '!AC23+#REF! -> #REF! | AC23: =+'DIRECTO '!AE23+#REF! -> #REF!
B24: Fletes | E24: =+'DIRECTO '!E24+#REF! -> #REF! | G24: =+'DIRECTO '!G24+#REF! -> #REF! | H24: =+'DIRECTO '!H24+#REF! -> #REF! | J24: =+'DIRECTO '!J24+#REF! -> #REF! | K24: =+'DIRECTO '!K24+#REF! -> #REF! | L24: =+SUM(N24:R24) -> #REF! | N24: =+'DIRECTO '!N24+#REF! -> #REF! | O24: =+'DIRECTO '!O24+#REF! -> #REF! | P24: =+'DIRECTO '!P24+#REF! -> #REF! | Q24: =+'DIRECTO '!Q24+#REF! -> #REF! | R24: =+'DIRECTO '!R24+#REF! -> #REF! | S24: =+SUMIFS(N24:R24,N$2:R$2,$S$5) -> #REF! | U24: =+SUMIFS(N24:S24,N$2:S$2,$U$5) -> 0 | W24: =+K24+L24 -> #REF! | X24: =+'DIRECTO '!Z24+#REF! -> #REF! | Y24: =+'DIRECTO '!AA24+#REF! -> #REF! | Z24: =+'DIRECTO '!AB24+#REF! -> #REF! | AA24: =+'DIRECTO '!AC24+#REF! -> #REF! | AC24: =+'DIRECTO '!AE24+#REF! -> #REF!
B25: Staff (Sueldos) | E25: =+'DIRECTO '!E25+#REF! -> #REF! | G25: =+'DIRECTO '!G25+#REF! -> #REF! | H25: =+'DIRECTO '!H25+#REF! -> #REF! | J25: =+'DIRECTO '!J25+#REF! -> #REF! | K25: =+'DIRECTO '!K25+#REF! -> #REF! | L25: =+SUM(N25:R25) -> #REF! | N25: =+'DIRECTO '!N25+#REF! -> #REF! | O25: =+'DIRECTO '!O25+#REF! -> #REF! | P25: =+'DIRECTO '!P25+#REF! -> #REF! | Q25: =+'DIRECTO '!Q25+#REF! -> #REF! | R25: =+'DIRECTO '!R25+#REF! -> #REF! | S25: =+SUMIFS(N25:R25,N$2:R$2,$S$5) -> #REF! | U25: =+SUMIFS(N25:S25,N$2:S$2,$U$5) -> 0 | W25: =+K25+L25 -> #REF! | X25: =+'DIRECTO '!Z25+#REF! -> #REF! | Y25: =+'DIRECTO '!AA25+#REF! -> #REF! | Z25: =+'DIRECTO '!AB25+#REF! -> #REF! | AA25: =+'DIRECTO '!AC25+#REF! -> #REF! | AC25: =+'DIRECTO '!AE25+#REF! -> #REF! | AO25: 21280334 | AP25: =+AO25-W25 -> #REF! | AR25: =+AR26/W15 -> #REF!
B26: Gastos Generales | E26: =+'DIRECTO '!E26+#REF! -> #REF! | G26: =+'DIRECTO '!G26+#REF! -> #REF! | H26: =+'DIRECTO '!H26+#REF! -> #REF! | J26: =+'DIRECTO '!J26+#REF! -> #REF! | K26: =+'DIRECTO '!K26+#REF! -> #REF! | L26: =+SUM(N26:R26) -> #REF! | N26: =+'DIRECTO '!N26+#REF! -> #REF! | O26: =+'DIRECTO '!O26+#REF! -> #REF! | P26: =+'DIRECTO '!P26+#REF! -> #REF! | Q26: =+'DIRECTO '!Q26+#REF! -> #REF! | R26: =+'DIRECTO '!R26+#REF! -> #REF! | S26: =+SUMIFS(N26:R26,N$2:R$2,$S$5) -> #REF! | U26: =+SUMIFS(N26:S26,N$2:S$2,$U$5) -> 0 | W26: =+K26+L26 -> #REF! | X26: =+'DIRECTO '!Z26+#REF! -> #REF! | Y26: =+'DIRECTO '!AA26+#REF! -> #REF! | Z26: =+'DIRECTO '!AB26+#REF! -> #REF! | AA26: =+'DIRECTO '!AC26+#REF! -> #REF! | AC26: =+'DIRECTO '!AE26+#REF! -> #REF! | AO26: 12574362 | AR26: =+W26+W25 -> #REF!
B28: Stock de Materiales | E28: =+'DIRECTO '!E28+#REF! -> #REF! | G28: =+'DIRECTO '!G28+#REF! -> #REF! | H28: =+'DIRECTO '!H28+#REF! -> #REF! | J28: =+'DIRECTO '!J28+#REF! -> #REF! | K28: =+'DIRECTO '!K28+#REF! -> #REF! | L28: =+SUM(N28:R28) -> #REF! | N28: =+'DIRECTO '!N28+#REF! -> #REF! | O28: =+'DIRECTO '!O28+#REF! -> #REF! | P28: =+'DIRECTO '!P28+#REF! -> #REF! | Q28: =+'DIRECTO '!Q28+#REF! -> #REF! | R28: =+'DIRECTO '!R28+#REF! -> #REF! | S28: =+SUMIFS(N28:R28,N$2:R$2,$S$5) -> #REF! | U28: =+SUMIFS(N28:S28,N$2:S$2,$U$5) -> 0 | W28: =+K28+L28 -> #REF! | X28: =+'DIRECTO '!Z28+#REF! -> #REF! | Y28: =+'DIRECTO '!AA28+#REF! -> #REF! | Z28: =+'DIRECTO '!AB28+#REF! -> #REF! | AA28: =+'DIRECTO '!AC28+#REF! -> #REF! | AC28: =+'DIRECTO '!AE28+#REF! -> #REF! | AO28: 5329828.3
B30: Margen Ponderado S/. | C30: S/. | E30: =+E7*E31 -> #REF! | G30: =+G7*G31 -> #REF! | H30: =+H7*H31 -> #REF! | J30: =+J7*J31 -> #REF! | K30: =+K7*K31 -> #REF! | L30: =+L7*L31 -> #REF! | N30: =+N7*N31 -> #REF! | O30: =+O7*O31 -> #REF! | P30: =+P7*P31 -> #REF! | Q30: =+Q7*Q31 -> #REF! | R30: =+R7*R31 -> #REF! | S30: =+S7*S31 -> #REF! | U30: =+U7*U31 -> #REF! | W30: =+W7-W15 -> #REF! | X30: =+X7-X15 -> #REF! | Y30: =+Y7-Y15 -> #REF! | Z30: =+Z7-Z15 -> #REF! | AA30: =+AA7-AA15 -> #REF! | AC30: 0 | AO30: =+W30-X30 -> #REF!
C31: % | E31: =+$W$31 -> #REF! | G31: =+$W$31 -> #REF! | H31: =+$W$31 -> #REF! | J31: =+$W$31 -> #REF! | K31: =+$W$31 -> #REF! | L31: =+$W$31 -> #REF! | N31: =+$W$31 -> #REF! | O31: =+$W$31 -> #REF! | P31: =+$W$31 -> #REF! | Q31: =+$W$31 -> #REF! | R31: =+$W$31 -> #REF! | S31: =+$W$31 -> #REF! | U31: =+$W$31 -> #REF! | W31: =+IF(W7=0,0,W30/W7) -> #REF! | X31: =+IF(X7=0,0,X30/X7) -> #REF! | Y31: =+IF(Y7=0,0,Y30/Y7) -> #REF! | Z31: =+IF(Z7=0,0,Z30/Z7) -> #REF! | AA31: =+IF(AA7=0,0,AA30/AA7) -> #REF! | AC31: 0 | AO31: =+W31-X31 -> #REF!
B33: Margen Absoluto | C33: S/. | E33: =+E7-E15+E28 -> #REF! | G33: =+G7-G15+G28 -> #REF! | H33: =+H7-H15+H28 -> #REF! | J33: =+J7-J15+J28 -> #REF! | K33: =+K7-K15 -> #REF! | L33: =+L7-L15 -> #REF! | N33: =+N7-N15+N28 -> #REF! | O33: =+O7-O15+O28 -> #REF! | P33: =+P7-P15+P28 -> #REF! | Q33: =+Q7-Q15+Q28 -> #REF! | R33: =+R7-R15+R28 -> #REF! | S33: =+S7-S15+S28 -> #REF! | U33: =+U7-U15+U28 -> 0 | W33: =+W7-W15+W28 -> #REF! | X33: =+X7-X15+X28 -> #REF! | Y33: =+Y7-Y15+Y28 -> #REF! | Z33: =+Z7-Z15+Z28 -> #REF! | AA33: =+AA7-AA15+AA28 -> #REF! | AC33: 0
C34: % | E34: =+IF(E9=0,0,E33/E9) -> #REF! | G34: =+IF(G9=0,0,G33/G9) -> #REF! | H34: =+IF(H9=0,0,H33/H9) -> #REF! | J34: =+IF(J7=0,0,J33/J7) -> #REF! | K34: =+IF(K7=0,0,K33/K7) -> #REF! | L34: =+IF(L7=0,0,L33/L7) -> #REF! | N34: =+IF(N7=0,0,N33/N7) -> #REF! | O34: =+IF(O7=0,0,O33/O7) -> #REF! | P34: =+IF(P7=0,0,P33/P7) -> #REF! | Q34: =+IF(Q7=0,0,Q33/Q7) -> #REF! | R34: =+IF(R7=0,0,R33/R7) -> #REF! | S34: =+IF(S7=0,0,S33/S7) -> #REF! | U34: =+IF(U7=0,0,U33/U7) -> 0 | W34: =+IF(W7=0,0,W33/W7) -> #REF! | X34: =+IF(X7=0,0,X33/X7) -> #REF! | Y34: =+IF(Y7=0,0,Y33/Y7) -> #REF! | Z34: =+IF(Z7=0,0,Z33/Z7) -> #REF! | AA34: =+IF(AA7=0,0,AA33/AA7) -> #REF! | AC34: 0
W37: =+W31-X31 -> #REF!
B38: COSTO APLICADO | K38: =+K7-K30 -> #REF! | W38: =+W30-X30 -> #REF! | AO38: =X30 -> #REF! | AP38: =+W31-X31 -> #REF!
B40: RESULTADO PENDIENTE | K40: =K15-K38 -> #REF! | AO40: =W30 -> #REF! | AP40: =+AO40-AO38 -> #REF!
B42: ACTIVOS | J42: =14+8 -> 22 | K42: ='ER Pendiente'!H40+'ER Pendiente'!H15 -> #REF!
B44: PROVISIONES | K44: =+'ER Pendiente'!I40+'ER Pendiente'!I22 -> 0
B46: DIFERENCIA DE MARGENES | K46: =+'DIRECTO '!K46+#REF! -> #REF!
B48: CONTINGENCIA | K48: =+K40-K42+K44 -> #REF!
C50: Mayor Margen +
C52: Menor Margen -
B55: MARGEN CONSORCIO (PONDERADO) | W55: 11555 | AA55: 16571
B56: MARGEN GARANTIZADO | W56: 10554 | AA56: 10554
B57: MARGEN POR PRODUCTIVIDAD | W57: 10.01 | AA57: 59.97
B59: PARTICIPACION SOCIO/S: | W59: 5677 | AA59: 7676
B60: MARGEN GARANTIZADO | W60: 5277 | AA60: 5277
B61: MARGEN POR PRODUCTIVIDAD | W61: 4 | AA61: 23.99
B63: PARTICIPACION CMO | W63: 5878 | AA63: 8875
B64: MARGEN GARANTIZADO | W64: 5277 | AA64: 5277
B65: MARGEN POR PRODUCTIVIDAD | W65: 6.01 | AA65: 35.98
B99: DESEMPEÑO DEL PROYECTO | K99: =K33 -> #REF! | L99: =+K99+L33 -> #REF! | N99: =+K99+N33 -> #REF! | O99: =+N99+O33 -> #REF! | P99: =+O99+P33 -> #REF! | Q99: =+P99+Q33 -> #REF! | R99: =+Q99+R33 -> #REF! | S99: =+K99+S33 -> #REF! | U99: =+S99+U33 -> #REF! | W99: =W33 -> #REF! | AA99: =AA33 -> #REF!
B100: DIRECTO | C100: ='DIRECTO '!K15 -> #REF! | E100: =IF(C100-SUM(C104:C111)=0,"OK","REVISAR") -> #REF!
B101: INDIRECTO | C101: =#REF! -> #REF! | E101: =IF(C101-SUM(E104:E111)=0,"OK","REVISAR") -> #REF!
C103: DIRECTO | E103: INDIRECTO
B104: Materiales | C104: =+K17 -> #REF! | E104: =#REF! -> #REF!
B105: Mano de Obra | C105: =+K18 -> #REF! | E105: =#REF! -> #REF!
B106: Subcontratos de obra | C106: =+K19 -> #REF! | E106: =#REF! -> #REF!
B107: Servicios Contratados | C107: =+K20 -> #REF! | E107: =#REF! -> #REF!
B108: Equipos Propios | C108: =+K22 -> #REF! | E108: =#REF! -> #REF!
B109: Equipos Terceros | C109: =+K23 -> #REF! | E109: =#REF! -> #REF!
B110: Fletes | C110: =+K24 -> #REF! | E110: =#REF! -> #REF!
B111: Staff (Sueldos) | C111: =+K25 -> #REF! | E111: =#REF! -> #REF!
B112: Gastos Generales | C112: =+K26 -> #REF!

Sheet DIRECTO 
B1: =CONCATENATE(B3," - ",B4," - ",B5," - ",B6) -> I.E.N 1182 - - EL BOSQUE - CERCO + INGRESOS Y CASETAS - DIRECTO- JULIO 2024
N2: =+YEAR(N5) -> 2019 | O2: =+YEAR(O5) -> 2019 | P2: =+YEAR(P5) -> 2019 | Q2: =+YEAR(Q5) -> 2019 | R2: =+YEAR(R5) -> 2019 | S2: =S5 -> 2024
B3: I.E.N 1182 | E3: ACUMULADO | G3: 45474 | J3: ACUMULADO DEL 2024 | K3: ACUMULADO DE OBRA | L3: SALDO DE OBRA | N3: PROYECCIÓN | U3: AÑOS SIGUIENTES | Y3: TOTAL DE OBRA | AE3: Acum. del Ej. | AJ3: TOTAL | AK3: MES DEL INFORME | AL3: ANTERIORES | AM3: 45474 | AN3: 45505 | AO3: 45536 | AP3: 45566 | AQ3: 45597
N4: 1 | O4: =+N4+1 -> 2 | P4: =+O4+1 -> 3 | Q4: =+P4+1 -> 4 | R4: =+Q4+1 -> 5 | S4: Saldo del Ejercicio
B5: EL BOSQUE - CERCO + INGRESOS Y CASETAS | E5: Años Anteriores | G5: Previsto | H5: Real | N5: 43648 | O5: =+N5+31 -> 43679 | P5: =+O5+31 -> 43710 | Q5: =+P5+31 -> 43741 | R5: =+Q5+31 -> 43772 | S5: =CONSOLIDADO!S5 -> 2024 | U5: 2024 | V5: =+U5+1 -> 2025 | W5: =+V5+1 -> 2026 | Y5: Actual | Z5: Anterior | AA5: Meta | AB5: Presupuesto Interno | AC5: Original | AE5: Anterior
B6: DIRECTO- JULIO 2024
B7: Venta Total Producida | E7: =+E9 -> #REF! | G7: =+G9 -> #REF! | H7: =+H9 -> #REF! | J7: =+J9 -> #REF! | K7: =+K9 -> #REF! | L7: =+L9 -> #REF! | N7: =+N9 -> #REF! | O7: =+O9 -> #REF! | P7: =+P9 -> #REF! | Q7: =+Q9 -> #REF! | R7: =+R9 -> #REF! | S7: =+S9 -> 0 | U7: =+U9 -> 0 | V7: =+V9 -> 0 | W7: =+W9 -> 0 | Y7: =+Y9 -> #REF! | Z7: =+Z9 -> #REF! | AA7: =+AA9 -> #REF! | AB7: =+AB9 -> #REF! | AC7: =+AC9 -> #REF! | AE7: =+AE9 -> #REF! | AG7: =+AC7-Y7 -> #REF! | AJ7: =+AJ9 -> #REF! | AK7: =+AK9 -> #REF!
B9: Venta | E9: =+SUM(E11:E13) -> #REF! | G9: =+SUM(G11:G13) -> #REF! | H9: =+SUM(H11:H13) -> #REF! | J9: =+SUM(J11:J13) -> #REF! | K9: =+SUM(K11:K13) -> #REF! | L9: =+SUM(L11:L12) -> #REF! | N9: =+SUM(N11:N13) -> #REF! | O9: =+SUM(O11:O13) -> #REF! | P9: =+SUM(P11:P13) -> #REF! | Q9: =+SUM(Q11:Q13) -> #REF! | R9: =+SUM(R11:R13) -> #REF! | S9: =+SUM(S11:S13) -> 0 | U9: =+SUM(U11:U13) -> 0 | V9: =+SUM(V11:V13) -> 0 | W9: =+SUM(W11:W13) -> 0 | Y9: =+SUM(Y11:Y13) -> #REF! | Z9: =+SUM(Z11:Z13) -> #REF! | AA9: =+SUM(AA11:AA13) -> #REF! | AB9: =+SUM(AB11:AB13) -> #REF! | AC9: =+SUM(AC11:AC13) -> #REF! | AE9: =+SUM(AE11:AE13) -> #REF! | AG9: =+AC9-Y9 -> #REF! | AJ9: =+SUM(AJ11:AJ13) -> #REF! | AK9: =+SUM(AK11:AK13) -> #REF!
B11: Valorización: Venta Directa - Contrato Principal | E11: =+'F-100'!E11+'F-200'!E11+'F-300'!E11+'F-400'!E11+'F-500'!E11+'F-600'!E11+#REF!+#REF!+#REF!+#REF!+#REF!+#REF! -> #REF! | G11: =+'F-100'!G11+'F-200'!G11+'F-300'!G11+'F-400'!G11+'F-500'!G11+'F-600'!G11+#REF!+#REF!+#REF!+#REF!+#REF!++#REF! -> #REF! | H11: =+'F-100'!H11+'F-200'!H11+'F-300'!H11+'F-400'!H11+'F-500'!H11+'F-600'!H11+#REF!+#REF!+#REF!+#REF!+#REF!++#REF! -> #REF! | J11: =+'F-100'!J11+'F-200'!J11+'F-300'!J11+'F-400'!J11+'F-500'!J11+'F-600'!J11 -> 0 | K11: =+'F-100'!K11+'F-200'!K11+'F-300'!K11+'F-400'!K11+'F-500'!K11+'F-600'!K11+#REF!+#REF!+#REF!+#REF!+#REF! -> #REF! | L11: =+'F-100'!L11+'F-200'!L11+'F-300'!L11+'F-400'!L11+'F-500'!L11+'F-600'!L11+#REF!+#REF!+#REF!+#REF!+#REF! -> #REF! | N11: =+'F-100'!N11+'F-200'!N11+'F-300'!N11+'F-400'!N11+'F-500'!N11+'F-600'!N11+#REF!+#REF!+#REF!+#REF!+#REF!+#REF! -> #REF! | O11: =+'F-100'!O11+'F-200'!O11+'F-300'!O11+'F-400'!O11+'F-500'!O11+'F-600'!O11+#REF!+#REF!+#REF!+#REF!+#REF!+#REF! -> #REF! | P11: =+'F-100'!P11+'F-200'!P11+'F-300'!P11+'F-400'!P11+'F-500'!P11+'F-600'!P11+#REF!+#REF!+#REF!+#REF!+#REF!+#REF! -> #REF! | Q11: =+'F-100'!Q11+'F-200'!Q11+'F-300'!Q11+'F-400'!Q11+'F-500'!Q11+'F-600'!Q11+#REF!+#REF!+#REF!+#REF!+#REF!+#REF! -> #REF! | R11: =+'F-100'!R11+'F-200'!R11+'F-300'!R11+'F-400'!R11+'F-500'!R11+'F-600'!R11+#REF!+#REF!+#REF!+#REF!+#REF!+#REF! -> #REF! | S11: =+SUMIFS(N11:R11,N$2:R$2,$S$5) -> 0 | U11: =+SUMIFS(N11:S11,N$2:S$2,$U$5) -> 0 | V11: =+SUMIFS(N11:S11,N$2:S$2,$V$5) -> 0 | W11: =+SUMIFS(N11:S11,N$2:S$2,$W$5) -> 0 | Y11: =+K11+L11 -> #REF! | Z11: =+'F-100'!Z11+'F-200'!Z11+'F-300'!Z11+'F-400'!Z11+'F-500'!Z11+'F-600'!Z11+#REF!+#REF!+#REF!+#REF!+#REF!+#REF! -> #REF! | AA11: =+'F-100'!AA11+'F-200'!AA11+'F-300'!AA11+'F-400'!AA11+'F-500'!AA11+'F-600'!AA11+#REF!+#REF!+#REF!+#REF!+#REF!+#REF! -> #REF! | AB11: =+'F-100'!AB11+'F-200'!AB11+'F-300'!AB11+'F-400'!AB11+'F-500'!AB11+'F-600'!AB11+#REF!+#REF!+#REF!+#REF!+#REF!+#REF! -> #REF! | AC11: =+'F-100'!AC11+'F-200'!AC11+'F-300'!AC11+'F-400'!AC11+'F-500'!AC11+'F-600'!AC11+#REF!+#REF!+#REF!+#REF!+#REF!+#REF! -> #REF! | AE11: =+'F-100'!AE11+'F-200'!AE11+'F-300'!AE11+'F-400'!AE11+'F-500'!AE11+'F-600'!AE11+#REF!+#REF!+#REF!+#REF!+#REF!+#REF! -> #REF! | AG11: =+AC11-Y11 -> #REF! | AJ11: =SUM(AK11:AQ11) -> #REF! | AK11: =+'F-100'!AK11+'F-200'!AK11+'F-300'!AJ11+'F-400'!AJ11+'F-500'!AJ11+'F-600'!AJ11+#REF!+#REF!+#REF!+#REF!+#REF!+#REF! -> #REF!
B12: Valorización: Venta Indirecta - Contrato Principal | E12: =+'F-100'!E12+'F-200'!E12+'F-300'!E12+'F-400'!E12+'F-500'!E12+'F-600'!E12+#REF!+#REF!+#REF!+#REF!+#REF!+#REF! -> #REF! | G12: =+'F-100'!G12+'F-200'!G12+'F-300'!G12+'F-400'!G12+'F-500'!G12+'F-600'!G12+#REF!+#REF!+#REF!+#REF!+#REF!++#REF! -> #REF! | H12: =+'F-100'!H12+'F-200'!H12+'F-300'!H12+'F-400'!H12+'F-500'!H12+'F-600'!H12+#REF!+#REF!+#REF!+#REF!+#REF!++#REF! -> #REF! | J12: =+'F-100'!J12+'F-200'!J12+'F-300'!J12+'F-400'!J12+'F-500'!J12+'F-600'!J12+#REF!+#REF!+#REF!+#REF!+#REF! -> #REF! | K12: =+'F-100'!K12+'F-200'!K12+'F-300'!K12+'F-400'!K12+'F-500'!K12+'F-600'!K12+#REF!+#REF!+#REF!+#REF!+#REF! -> #REF! | L12: =+'F-100'!L12+'F-200'!L12+'F-300'!L12+'F-400'!L12+'F-500'!L12+'F-600'!L12+#REF!+#REF!+#REF!+#REF!+#REF! -> #REF! | N12: =+'F-100'!N12+'F-200'!N12+'F-300'!N12+'F-400'!N12+'F-500'!N12+'F-600'!N12+#REF!+#REF!+#REF!+#REF!+#REF!+#REF! -> #REF! | O12: =+'F-100'!O12+'F-200'!O12+'F-300'!O12+'F-400'!O12+'F-500'!O12+'F-600'!O12+#REF!+#REF!+#REF!+#REF!+#REF!+#REF! -> #REF! | P12: =+'F-100'!P12+'F-200'!P12+'F-300'!P12+'F-400'!P12+'F-500'!P12+'F-600'!P12+#REF!+#REF!+#REF!+#REF!+#REF!+#REF! -> #REF! | Q12: =+'F-100'!Q12+'F-200'!Q12+'F-300'!Q12+'F-400'!Q12+'F-500'!Q12+'F-600'!Q12+#REF!+#REF!+#REF!+#REF!+#REF!+#REF! -> #REF! | R12: =+'F-100'!R12+'F-200'!R12+'F-300'!R12+'F-400'!R12+'F-500'!R12+'F-600'!R12+#REF!+#REF!+#REF!+#REF!+#REF!+#REF! -> #REF! | S12: =+SUMIFS(N12:R12,N$2:R$2,$S$5) -> 0 | U12: =+SUMIFS(N12:S12,N$2:S$2,$U$5) -> 0 | V12: =+SUMIFS(N12:S12,N$2:S$2,$V$5) -> 0 | W12: =+SUMIFS(N12:S12,N$2:S$2,$W$5) -> 0 | Y12: =+K12+L12 -> #REF! | Z12: =+'F-100'!Z12+'F-200'!Z12+'F-300'!Z12+'F-400'!Z12+'F-500'!Z12+'F-600'!Z12+#REF!+#REF!+#REF!+#REF!+#REF!+#REF! -> #REF! | AA12: =+'F-100'!AA12+'F-200'!AA12+'F-300'!AA12+'F-400'!AA12+'F-500'!AA12+'F-600'!AA12+#REF!+#REF!+#REF!+#REF!+#REF!+#REF! -> #REF! | AB12: =+'F-100'!AB12+'F-200'!AB12+'F-300'!AB12+'F-400'!AB12+'F-500'!AB12+'F-600'!AB12+#REF!+#REF!+#REF!+#REF!+#REF!+#REF! -> #REF! | AC12: =+'F-100'!AC12+'F-200'!AC12+'F-300'!AC12+'F-400'!AC12+'F-500'!AC12+'F-600'!AC12+#REF!+#REF!+#REF!+#REF!+#REF!+#REF! -> #REF! | AE12: =+'F-100'!AE12+'F-200'!AE12+'F-300'!AE12+'F-400'!AE12+'F-500'!AE12+'F-600'!AE12+#REF!+#REF!+#REF!+#REF!+#REF!+#REF! -> #REF! | AG12: =+AC12-Y12 -> #REF! | AJ12: =SUM(AK12:AQ12) -> #REF! | AK12: =+'F-100'!AK12+'F-200'!AK12+'F-300'!AJ12+'F-400'!AJ12+'F-500'!AJ12+'F-600'!AJ12+#REF!+#REF!+#REF!+#REF!+#REF!+#REF! -> #REF!
B13: Otros: | E13: =+'F-100'!E13+'F-200'!E13+'F-300'!E13+'F-400'!#REF!+'F-500'!E13+'F-600'!E13+#REF!+#REF!+#REF!+#REF!+#REF!+#REF! -> #REF! | G13: =+'F-100'!G13+'F-200'!G13+'F-300'!G13+'F-400'!#REF!+'F-500'!G13+'F-600'!G13+#REF!+#REF!+#REF!+#REF!+#REF!++#REF! -> #REF! | H13: =+'F-100'!H13+'F-200'!H13+'F-300'!H13+'F-400'!#REF!+'F-500'!H13+'F-600'!H13+#REF!+#REF!+#REF!+#REF!+#REF!++#REF! -> #REF! | J13: =+'F-100'!J13+'F-200'!J13+'F-300'!J13+'F-400'!#REF!+'F-500'!J13+'F-600'!J13+#REF!+#REF!+#REF!+#REF!+#REF! -> #REF! | K13: =+'F-100'!K13+'F-200'!K13+'F-300'!K13+'F-400'!#REF!+'F-500'!K13+'F-600'!K13+#REF!+#REF!+#REF!+#REF!+#REF! -> #REF! | L13: =+'F-100'!L13+'F-200'!L13+'F-300'!L13+'F-400'!#REF!+'F-500'!L13+'F-600'!L13+#REF!+#REF!+#REF!+#REF!+#REF! -> #REF! | N13: =+'F-100'!N13+'F-200'!N13+'F-300'!N13+'F-400'!#REF!+'F-500'!N13+'F-600'!N13+#REF!+#REF!+#REF!+#REF!+#REF!+#REF! -> #REF! | O13: =+'F-100'!O13+'F-200'!O13+'F-300'!O13+'F-400'!#REF!+'F-500'!O13+'F-600'!O13+#REF!+#REF!+#REF!+#REF!+#REF!+#REF! -> #REF! | P13: =+'F-100'!P13+'F-200'!P13+'F-300'!P13+'F-400'!#REF!+'F-500'!P13+'F-600'!P13+#REF!+#REF!+#REF!+#REF!+#REF!+#REF! -> #REF! | Q13: =+'F-100'!Q13+'F-200'!Q13+'F-300'!Q13+'F-400'!#REF!+'F-500'!Q13+'F-600'!Q13+#REF!+#REF!+#REF!+#REF!+#REF!+#REF! -> #REF! | R13: =+'F-100'!R13+'F-200'!R13+'F-300'!R13+'F-400'!#REF!+'F-500'!R13+'F-600'!R13+#REF!+#REF!+#REF!+#REF!+#REF!+#REF! -> #REF! | S13: =+SUMIFS(N13:R13,N$2:R$2,$S$5) -> 0 | U13: =+SUMIFS(N13:S13,N$2:S$2,$U$5) -> 0 | V13: =+SUMIFS(N13:S13,N$2:S$2,$V$5) -> 0 | W13: =+SUMIFS(N13:S13,N$2:S$2,$W$5) -> 0 | Y13: =+K13+L13 -> #REF! | Z13: =+'F-100'!Z13+'F-200'!Z13+'F-300'!Z13+'F-400'!#REF!+'F-500'!Z13+'F-600'!Z13+#REF!+#REF!+#REF!+#REF!+#REF!+#REF! -> #REF! | AA13: =+'F-100'!AA13+'F-200'!AA13+'F-300'!AA13+'F-400'!#REF!+'F-500'!AA13+'F-600'!AA13+#REF!+#REF!+#REF!+#REF!+#REF!+#REF! -> #REF! | AB13: =+'F-100'!AB13+'F-200'!AB13+'F-300'!AB13+'F-400'!#REF!+'F-500'!AB13+'F-600'!AB13+#REF!+#REF!+#REF!+#REF!+#REF!+#REF! -> #REF! | AC13: =+'F-100'!AC13+'F-200'!AC13+'F-300'!AC13+'F-400'!#REF!+'F-500'!AC13+'F-600'!AC13+#REF!+#REF!+#REF!+#REF!+#REF!+#REF! -> #REF! | AE13: =+'F-100'!AE13+'F-200'!AE13+'F-300'!AE13+'F-400'!#REF!+'F-500'!AE13+'F-600'!AE13+#REF!+#REF!+#REF!+#REF!+#REF!+#REF! -> #REF! | AG13: =+AC13-Y13 -> #REF! | AJ13: =SUM(AK13:AQ13) -> #REF! | AK13: =+'F-100'!AK13+'F-200'!AK13+'F-300'!AJ13+'F-400'!#REF!+'F-500'!AJ13+'F-600'!AJ13+#REF!+#REF!+#REF!+#REF!+#REF!+#REF! -> #REF!
AU14: MAR'2020
B15: Costo Total | E15: =+SUM(E17:E26)+E28 -> #REF! | G15: =+SUM(G17:G26)+G28 -> #REF! | H15: =+SUM(H17:H26)+H28 -> #REF! | J15: =+SUM(J17:J26)+J28 -> #REF! | K15: =+SUM(K17:K26)+K28 -> #REF! | L15: =+SUM(L17:L26)+L28 -> #REF! | N15: =+SUM(N17:N26)+N28 -> #REF! | O15: =+SUM(O17:O26)+O28 -> #REF! | P15: =+SUM(P17:P26)+P28 -> #REF! | Q15: =+SUM(Q17:Q26)+Q28 -> #REF! | R15: =+SUM(R17:R26)+R28 -> #REF! | S15: =+SUM(S17:S26)+S28 -> 0 | U15: =+SUM(U17:U26)+U28 -> 0 | V15: =+SUM(V17:V26)+V28 -> 0 | W15: =+SUM(W17:W26)+W28 -> 0 | Y15: =+SUM(Y17:Y26)+Y28 -> #REF! | Z15: =+SUM(Z17:Z26)+Z28 -> #REF! | AA15: =+SUM(AA17:AA26)+AA28 -> #REF! | AB15: =+SUM(AB17:AB26)+AB28 -> #REF! | AC15: =+SUM(AC17:AC26)+AC28 -> #REF! | AE15: =+SUM(AE17:AE26)+AE28 -> #REF! | AG15: =+AC15-Y15 -> #REF! | AJ15: =+SUM(AJ17:AJ26,AJ28,AJ30:AJ33) -> #REF! | AK15: =+SUM(AK17:AK26,AK28,AK30:AK33) -> #REF! | AU15: 4480984.2 | AV15: =+K15-AU15 -> #REF! | AY15: =+Y15/36000 -> #REF!
B17: Materiales | E17: =+'F-100'!E17+'F-200'!E17+'F-300'!E17+'F-400'!E17+'F-500'!E17+'F-600'!E17+#REF!+#REF!+#REF!+#REF!+#REF!+#REF! -> #REF! | G17: =+'F-100'!G17+'F-200'!G17+'F-300'!G17+'F-400'!G17+'F-500'!G17+'F-600'!G17+#REF!+#REF!+#REF!+#REF!+#REF!+#REF! -> #REF! | H17: =+'F-100'!H17+'F-200'!H17+'F-300'!H17+'F-400'!H17+'F-500'!H17+'F-600'!H17+#REF!+#REF!+#REF!+#REF!+#REF!+#REF! -> #REF! | J17: =+'F-100'!J17+'F-200'!J17+'F-300'!J17+'F-400'!J17+'F-500'!J17+'F-600'!J17+#REF!+#REF!+#REF!+#REF!+#REF!+#REF! -> #REF! | K17: =+'F-100'!K17+'F-200'!K17+'F-300'!K17+'F-400'!K17+'F-500'!K17+'F-600'!K17+#REF!+#REF!+#REF!+#REF!+#REF!+#REF! -> #REF! | L17: =+'F-100'!L17+'F-200'!L17+'F-300'!L17+'F-400'!L17+'F-500'!L17+'F-600'!L17+#REF!+#REF!+#REF!+#REF!+#REF!+#REF! -> #REF! | N17: =+'F-100'!N17+'F-200'!N17+'F-300'!N17+'F-400'!N17+'F-500'!N17+'F-600'!N17+#REF!+#REF!+#REF!+#REF!+#REF!+#REF! -> #REF! | O17: =+'F-100'!O17+'F-200'!O17+'F-300'!O17+'F-400'!O17+'F-500'!O17+'F-600'!O17+#REF!+#REF!+#REF!+#REF!+#REF!+#REF! -> #REF! | P17: =+'F-100'!P17+'F-200'!P17+'F-300'!P17+'F-400'!P17+'F-500'!P17+'F-600'!P17+#REF!+#REF!+#REF!+#REF!+#REF!+#REF! -> #REF! | Q17: =+'F-100'!Q17+'F-200'!Q17+'F-300'!Q17+'F-400'!Q17+'F-500'!Q17+'F-600'!Q17+#REF!+#REF!+#REF!+#REF!+#REF!+#REF! -> #REF! | R17: =+'F-100'!R17+'F-200'!R17+'F-300'!R17+'F-400'!R17+'F-500'!R17+'F-600'!R17+#REF!+#REF!+#REF!+#REF!+#REF!+#REF! -> #REF! | S17: =+SUMIFS(N17:R17,N$2:R$2,$S$5) -> 0 | U17: =+SUMIFS(N17:S17,N$2:S$2,$U$5) -> 0 | V17: =+SUMIFS(N17:S17,N$2:S$2,$V$5) -> 0 | W17: =+SUMIFS(N17:S17,N$2:S$2,$W$5) -> 0 | Y17: =+K17+L17 -> #REF! | Z17: =+'F-100'!Z17+'F-200'!Z17+'F-300'!Z17+'F-400'!Z17+'F-500'!Z17+'F-600'!Z17+#REF!+#REF!+#REF!+#REF!+#REF!+#REF! -> #REF! | AA17: =+'F-100'!AA17+'F-200'!AA17+'F-300'!AA17+'F-400'!AA17+'F-500'!AA17+'F-600'!AA17+#REF!+#REF!+#REF!+#REF!+#REF!+#REF! -> #REF! | AB17: =+'F-100'!AB17+'F-200'!AB17+'F-300'!AB17+'F-400'!AB17+'F-500'!AB17+'F-600'!AB17+#REF!+#REF!+#REF!+#REF!+#REF!+#REF! -> #REF! | AC17: =+'F-100'!AC17+'F-200'!AC17+'F-300'!AC17+'F-400'!AC17+'F-500'!AC17+'F-600'!AC17+#REF!+#REF!+#REF!+#REF!+#REF!+#REF! -> #REF! | AE17: =+'F-100'!AE17+'F-200'!AE17+'F-300'!AE17+'F-400'!AE17+'F-500'!AE17+'F-600'!AE17+#REF!+#REF!+#REF!+#REF!+#REF!+#REF! -> #REF! | AG17: =+AC17-Y17 -> #REF! | AJ17: =SUM(AK17:AQ17) -> #REF! | AK17: =+'F-100'!AK17+'F-200'!AK17+'F-300'!AJ17+'F-400'!AJ17+'F-500'!AJ17+'F-600'!AJ17+#REF!+#REF!+#REF!+#REF!+#REF!+#REF! -> #REF!
B18: Mano de Obra | E18: =+'F-100'!E18+'F-200'!E18+'F-300'!E18+'F-400'!E18+'F-500'!E18+'F-600'!E18+#REF!+#REF!+#REF!+#REF!+#REF!+#REF! -> #REF! | G18: =+'F-100'!G18+'F-200'!G18+'F-300'!G18+'F-400'!G18+'F-500'!G18+'F-600'!G18+#REF!+#REF!+#REF!+#REF!+#REF!+#REF! -> #REF! | H18: =+'F-100'!H18+'F-200'!H18+'F-300'!H18+'F-400'!H18+'F-500'!H18+'F-600'!H18+#REF!+#REF!+#REF!+#REF!+#REF!+#REF! -> #REF! | J18: =+'F-100'!J18+'F-200'!J18+'F-300'!J18+'F-400'!J18+'F-500'!J18+'F-600'!J18+#REF!+#REF!+#REF!+#REF!+#REF!+#REF! -> #REF! | K18: =+'F-100'!K18+'F-200'!K18+'F-300'!K18+'F-400'!K18+'F-500'!K18+'F-600'!K18+#REF!+#REF!+#REF!+#REF!+#REF!+#REF! -> #REF! | L18: =+'F-100'!L18+'F-200'!L18+'F-300'!L18+'F-400'!L18+'F-500'!L18+'F-600'!L18+#REF!+#REF!+#REF!+#REF!+#REF!+#REF! -> #REF! | N18: =+'F-100'!N18+'F-200'!N18+'F-300'!N18+'F-400'!N18+'F-500'!N18+'F-600'!N18+#REF!+#REF!+#REF!+#REF!+#REF!+#REF! -> #REF! | O18: =+'F-100'!O18+'F-200'!O18+'F-300'!O18+'F-400'!O18+'F-500'!O18+'F-600'!O18+#REF!+#REF!+#REF!+#REF!+#REF!+#REF! -> #REF! | P18: =+'F-100'!P18+'F-200'!P18+'F-300'!P18+'F-400'!P18+'F-500'!P18+'F-600'!P18+#REF!+#REF!+#REF!+#REF!+#REF!+#REF! -> #REF! | Q18: =+'F-100'!Q18+'F-200'!Q18+'F-300'!Q18+'F-400'!Q18+'F-500'!Q18+'F-600'!Q18+#REF!+#REF!+#REF!+#REF!+#REF!+#REF! -> #REF! | R18: =+'F-100'!R18+'F-200'!R18+'F-300'!R18+'F-400'!R18+'F-500'!R18+'F-600'!R18+#REF!+#REF!+#REF!+#REF!+#REF!+#REF! -> #REF! | S18: =+SUMIFS(N18:R18,N$2:R$2,$S$5) -> 0 | U18: =+SUMIFS(N18:S18,N$2:S$2,$U$5) -> 0 | V18: =+SUMIFS(N18:S18,N$2:S$2,$V$5) -> 0 | W18: =+SUMIFS(N18:S18,N$2:S$2,$W$5) -> 0 | Y18: =+K18+L18 -> #REF! | Z18: =+'F-100'!Z18+'F-200'!Z18+'F-300'!Z18+'F-400'!Z18+'F-500'!Z18+'F-600'!Z18+#REF!+#REF!+#REF!+#REF!+#REF!+#REF! -> #REF! | AA18: =+'F-100'!AA18+'F-200'!AA18+'F-300'!AA18+'F-400'!AA18+'F-500'!AA18+'F-600'!AA18+#REF!+#REF!+#REF!+#REF!+#REF!+#REF! -> #REF! | AB18: =+'F-100'!AB18+'F-200'!AB18+'F-300'!AB18+'F-400'!AB18+'F-500'!AB18+'F-600'!AB18+#REF!+#REF!+#REF!+#REF!+#REF!+#REF! -> #REF! | AC18: =+'F-100'!AC18+'F-200'!AC18+'F-300'!AC18+'F-400'!AC18+'F-500'!AC18+'F-600'!AC18+#REF!+#REF!+#REF!+#REF!+#REF!+#REF! -> #REF! | AE18: =+'F-100'!AE18+'F-200'!AE18+'F-300'!AE18+'F-400'!AE18+'F-500'!AE18+'F-600'!AE18+#REF!+#REF!+#REF!+#REF!+#REF!+#REF! -> #REF! | AG18: =+AC18-Y18 -> #REF! | AJ18: =SUM(AK18:AQ18) -> #REF! | AK18: =+'F-100'!AK18+'F-200'!AK18+'F-300'!AJ18+'F-400'!AJ18+'F-500'!AJ18+'F-600'!AJ18+#REF!+#REF!+#REF!+#REF!+#REF!+#REF! -> #REF!
B19: Subcontratos de obra | E19: =+'F-100'!E19+'F-200'!E19+'F-300'!E19+'F-400'!E19+'F-500'!E19+'F-600'!E19+#REF!+#REF!+#REF!+#REF!+#REF!+#REF! -> #REF! | G19: =+'F-100'!G19+'F-200'!G19+'F-300'!G19+'F-400'!G19+'F-500'!G19+'F-600'!G19+#REF!+#REF!+#REF!+#REF!+#REF!+#REF! -> #REF! | H19: =+'F-100'!H19+'F-200'!H19+'F-300'!H19+'F-400'!H19+'F-500'!H19+'F-600'!H19+#REF!+#REF!+#REF!+#REF!+#REF!+#REF! -> #REF! | J19: =+'F-100'!J19+'F-200'!J19+'F-300'!J19+'F-400'!J19+'F-500'!J19+'F-600'!J19+#REF!+#REF!+#REF!+#REF!+#REF!+#REF! -> #REF! | K19: =+'F-100'!K19+'F-200'!K19+'F-300'!K19+'F-400'!K19+'F-500'!K19+'F-600'!K19+#REF!+#REF!+#REF!+#REF!+#REF!+#REF! -> #REF! | L19: =+'F-100'!L19+'F-200'!L19+'F-300'!L19+'F-400'!L19+'F-500'!L19+'F-600'!L19+#REF!+#REF!+#REF!+#REF!+#REF!+#REF! -> #REF! | N19: =+'F-100'!N19+'F-200'!N19+'F-300'!N19+'F-400'!N19+'F-500'!N19+'F-600'!N19+#REF!+#REF!+#REF!+#REF!+#REF!+#REF! -> #REF! | O19: =+'F-100'!O19+'F-200'!O19+'F-300'!O19+'F-400'!O19+'F-500'!O19+'F-600'!O19+#REF!+#REF!+#REF!+#REF!+#REF!+#REF! -> #REF! | P19: =+'F-100'!P19+'F-200'!P19+'F-300'!P19+'F-400'!P19+'F-500'!P19+'F-600'!P19+#REF!+#REF!+#REF!+#REF!+#REF!+#REF! -> #REF! | Q19: =+'F-100'!Q19+'F-200'!Q19+'F-300'!Q19+'F-400'!Q19+'F-500'!Q19+'F-600'!Q19+#REF!+#REF!+#REF!+#REF!+#REF!+#REF! -> #REF! | R19: =+'F-100'!R19+'F-200'!R19+'F-300'!R19+'F-400'!R19+'F-500'!R19+'F-600'!R19+#REF!+#REF!+#REF!+#REF!+#REF!+#REF! -> #REF! | S19: =+SUMIFS(N19:R19,N$2:R$2,$S$5) -> 0 | U19: =+SUMIFS(N19:S19,N$2:S$2,$U$5) -> 0 | V19: =+SUMIFS(N19:S19,N$2:S$2,$V$5) -> 0 | W19: =+SUMIFS(N19:S19,N$2:S$2,$W$5) -> 0 | Y19: =+K19+L19 -> #REF! | Z19: =+'F-100'!Z19+'F-200'!Z19+'F-300'!Z19+'F-400'!Z19+'F-500'!Z19+'F-600'!Z19+#REF!+#REF!+#REF!+#REF!+#REF!+#REF! -> #REF! | AA19: =+'F-100'!AA19+'F-200'!AA19+'F-300'!AA19+'F-400'!AA19+'F-500'!AA19+'F-600'!AA19+#REF!+#REF!+#REF!+#REF!+#REF!+#REF! -> #REF! | AB19: =+'F-100'!AB19+'F-200'!AB19+'F-300'!AB19+'F-400'!AB19+'F-500'!AB19+'F-600'!AB19+#REF!+#REF!+#REF!+#REF!+#REF!+#REF! -> #REF! | AC19: =+'F-100'!AC19+'F-200'!AC19+'F-300'!AC19+'F-400'!AC19+'F-500'!AC19+'F-600'!AC19+#REF!+#REF!+#REF!+#REF!+#REF!+#REF! -> #REF! | AE19: =+'F-100'!AE19+'F-200'!AE19+'F-300'!AE19+'F-400'!AE19+'F-500'!AE19+'F-600'!AE19+#REF!+#REF!+#REF!+#REF!+#REF!+#REF! -> #REF! | AG19: =+AC19-Y19 -> #REF! | AJ19: =SUM(AK19:AQ19) -> #REF! | AK19: =+'F-100'!AK19+'F-200'!AK19+'F-300'!AJ19+'F-400'!AJ19+'F-500'!AJ19+'F-600'!AJ19+#REF!+#REF!+#REF!+#REF!+#REF!+#REF! -> #REF!
B20: Servicios Contratados | E20: =+'F-100'!E20+'F-200'!E20+'F-300'!E20+'F-400'!E20+'F-500'!E20+'F-600'!E20+#REF!+#REF!+#REF!+#REF!+#REF!+#REF! -> #REF! | G20: =+'F-100'!G20+'F-200'!G20+'F-300'!G20+'F-400'!G20+'F-500'!G20+'F-600'!G20+#REF!+#REF!+#REF!+#REF!+#REF!+#REF! -> #REF! | H20: =+'F-100'!H20+'F-200'!H20+'F-300'!H20+'F-400'!H20+'F-500'!H20+'F-600'!H20+#REF!+#REF!+#REF!+#REF!+#REF!+#REF! -> #REF! | J20: =+'F-100'!J20+'F-200'!J20+'F-300'!J20+'F-400'!J20+'F-500'!J20+'F-600'!J20+#REF!+#REF!+#REF!+#REF!+#REF!+#REF! -> #REF! | K20: =+'F-100'!K20+'F-200'!K20+'F-300'!K20+'F-400'!K20+'F-500'!K20+'F-600'!K20+#REF!+#REF!+#REF!+#REF!+#REF!+#REF! -> #REF! | L20: =+'F-100'!L20+'F-200'!L20+'F-300'!L20+'F-400'!L20+'F-500'!L20+'F-600'!L20+#REF!+#REF!+#REF!+#REF!+#REF!+#REF! -> #REF! | N20: =+'F-100'!N20+'F-200'!N20+'F-300'!N20+'F-400'!N20+'F-500'!N20+'F-600'!N20+#REF!+#REF!+#REF!+#REF!+#REF!+#REF! -> #REF! | O20: =+'F-100'!O20+'F-200'!O20+'F-300'!O20+'F-400'!O20+'F-500'!O20+'F-600'!O20+#REF!+#REF!+#REF!+#REF!+#REF!+#REF! -> #REF! | P20: =+'F-100'!P20+'F-200'!P20+'F-300'!P20+'F-400'!P20+'F-500'!P20+'F-600'!P20+#REF!+#REF!+#REF!+#REF!+#REF!+#REF! -> #REF! | Q20: =+'F-100'!Q20+'F-200'!Q20+'F-300'!Q20+'F-400'!Q20+'F-500'!Q20+'F-600'!Q20+#REF!+#REF!+#REF!+#REF!+#REF!+#REF! -> #REF! | R20: =+'F-100'!R20+'F-200'!R20+'F-300'!R20+'F-400'!R20+'F-500'!R20+'F-600'!R20+#REF!+#REF!+#REF!+#REF!+#REF!+#REF! -> #REF! | S20: =+SUMIFS(N20:R20,N$2:R$2,$S$5) -> 0 | U20: =+SUMIFS(N20:S20,N$2:S$2,$U$5) -> 0 | V20: =+SUMIFS(N20:S20,N$2:S$2,$V$5) -> 0 | W20: =+SUMIFS(N20:S20,N$2:S$2,$W$5) -> 0 | Y20: =+K20+L20 -> #REF! | Z20: =+'F-100'!Z20+'F-200'!Z20+'F-300'!Z20+'F-400'!Z20+'F-500'!Z20+'F-600'!Z20+#REF!+#REF!+#REF!+#REF!+#REF!+#REF! -> #REF! | AA20: =+'F-100'!AA20+'F-200'!AA20+'F-300'!AA20+'F-400'!AA20+'F-500'!AA20+'F-600'!AA20+#REF!+#REF!+#REF!+#REF!+#REF!+#REF! -> #REF! | AB20: =+'F-100'!AB20+'F-200'!AB20+'F-300'!AB20+'F-400'!AB20+'F-500'!AB20+'F-600'!AB20+#REF!+#REF!+#REF!+#REF!+#REF!+#REF! -> #REF! | AC20: =+'F-100'!AC20+'F-200'!AC20+'F-300'!AC20+'F-400'!AC20+'F-500'!AC20+'F-600'!AC20+#REF!+#REF!+#REF!+#REF!+#REF!+#REF! -> #REF! | AE20: =+'F-100'!AE20+'F-200'!AE20+'F-300'!AE20+'F-400'!AE20+'F-500'!AE20+'F-600'!AE20+#REF!+#REF!+#REF!+#REF!+#REF!+#REF! -> #REF! | AG20: =+AC20-Y20 -> #REF! | AJ20: =SUM(AK20:AQ20) -> #REF! | AK20: =+'F-100'!AK20+'F-200'!AK20+'F-300'!AJ20+'F-400'!AJ20+'F-500'!AJ20+'F-600'!AJ20+#REF!+#REF!+#REF!+#REF!+#REF!+#REF! -> #REF!
B21: Equipos y Vehículos | E21: =+'F-100'!E21+'F-200'!E21+'F-300'!E21+'F-400'!E21+'F-500'!E21+'F-600'!E21+#REF!+#REF!+#REF!+#REF!+#REF!+#REF! -> #REF! | G21: =+'F-100'!G21+'F-200'!G21+'F-300'!G21+'F-400'!G21+'F-500'!G21+'F-600'!G21+#REF!+#REF!+#REF!+#REF!+#REF!+#REF! -> #REF! | H21: =+'F-100'!H21+'F-200'!H21+'F-300'!H21+'F-400'!H21+'F-500'!H21+'F-600'!H21+#REF!+#REF!+#REF!+#REF!+#REF!+#REF! -> #REF! | J21: =+'F-100'!J21+'F-200'!J21+'F-300'!J21+'F-400'!J21+'F-500'!J21+'F-600'!J21+#REF!+#REF!+#REF!+#REF!+#REF!+#REF! -> #REF! | K21: =+'F-100'!K21+'F-200'!K21+'F-300'!K21+'F-400'!K21+'F-500'!K21+'F-600'!K21+#REF!+#REF!+#REF!+#REF!+#REF!+#REF! -> #REF! | L21: =+'F-100'!L21+'F-200'!L21+'F-300'!L21+'F-400'!L21+'F-500'!L21+'F-600'!L21+#REF!+#REF!+#REF!+#REF!+#REF!+#REF! -> #REF! | N21: =+'F-100'!N21+'F-200'!N21+'F-300'!N21+'F-400'!N21+'F-500'!N21+'F-600'!N21+#REF!+#REF!+#REF!+#REF!+#REF!+#REF! -> #REF! | O21: =+'F-100'!O21+'F-200'!O21+'F-300'!O21+'F-400'!O21+'F-500'!O21+'F-600'!O21+#REF!+#REF!+#REF!+#REF!+#REF!+#REF! -> #REF! | P21: =+'F-100'!P21+'F-200'!P21+'F-300'!P21+'F-400'!P21+'F-500'!P21+'F-600'!P21+#REF!+#REF!+#REF!+#REF!+#REF!+#REF! -> #REF! | Q21: =+'F-100'!Q21+'F-200'!Q21+'F-300'!Q21+'F-400'!Q21+'F-500'!Q21+'F-600'!Q21+#REF!+#REF!+#REF!+#REF!+#REF!+#REF! -> #REF! | R21: =+'F-100'!R21+'F-200'!R21+'F-300'!R21+'F-400'!R21+'F-500'!R21+'F-600'!R21+#REF!+#REF!+#REF!+#REF!+#REF!+#REF! -> #REF! | S21: =+SUMIFS(N21:R21,N$2:R$2,$S$5) -> 0 | U21: =+SUMIFS(N21:S21,N$2:S$2,$U$5) -> 0 | V21: =+SUMIFS(N21:S21,N$2:S$2,$V$5) -> 0 | W21: =+SUMIFS(N21:S21,N$2:S$2,$W$5) -> 0 | Y21: =+K21+L21 -> #REF! | Z21: =+'F-100'!Z21+'F-200'!Z21+'F-300'!Z21+'F-400'!Z21+'F-500'!Z21+'F-600'!Z21+#REF!+#REF!+#REF!+#REF!+#REF!+#REF! -> #REF! | AA21: =+'F-100'!AA21+'F-200'!AA21+'F-300'!AA21+'F-400'!AA21+'F-500'!AA21+'F-600'!AA21+#REF!+#REF!+#REF!+#REF!+#REF!+#REF! -> #REF! | AB21: =+'F-100'!AB21+'F-200'!AB21+'F-300'!AB21+'F-400'!AB21+'F-500'!AB21+'F-600'!AB21+#REF!+#REF!+#REF!+#REF!+#REF!+#REF! -> #REF! | AC21: =+'F-100'!AC21+'F-200'!AC21+'F-300'!AC21+'F-400'!AC21+'F-500'!AC21+'F-600'!AC21+#REF!+#REF!+#REF!+#REF!+#REF!+#REF! -> #REF! | AE21: =+'F-100'!AE21+'F-200'!AE21+'F-300'!AE21+'F-400'!AE21+'F-500'!AE21+'F-600'!AE21+#REF!+#REF!+#REF!+#REF!+#REF!+#REF! -> #REF! | AG21: =+AC21-Y21 -> #REF! | AJ21: =SUM(AK21:AQ21) -> #REF! | AK21: =+'F-100'!AK21+'F-200'!AK21+'F-300'!AJ21+'F-400'!AJ21+'F-500'!AJ21+'F-600'!AJ21+#REF!+#REF!+#REF!+#REF!+#REF!+#REF! -> #REF!
C22: Propios | E22: =+'F-100'!E22+'F-200'!E22+'F-300'!E22+'F-400'!E22+'F-500'!E22+'F-600'!E22+#REF!+#REF!+#REF!+#REF!+#REF!+#REF! -> #REF! | G22: =+'F-100'!G22+'F-200'!G22+'F-300'!G22+'F-400'!G22+'F-500'!G22+'F-600'!G22+#REF!+#REF!+#REF!+#REF!+#REF!+#REF! -> #REF! | H22: =+'F-100'!H22+'F-200'!H22+'F-300'!H22+'F-400'!H22+'F-500'!H22+'F-600'!H22+#REF!+#REF!+#REF!+#REF!+#REF!+#REF! -> #REF! | J22: =+'F-100'!J22+'F-200'!J22+'F-300'!J22+'F-400'!J22+'F-500'!J22+'F-600'!J22+#REF!+#REF!+#REF!+#REF!+#REF!+#REF! -> #REF! | K22: =+'F-100'!K22+'F-200'!K22+'F-300'!K22+'F-400'!K22+'F-500'!K22+'F-600'!K22+#REF!+#REF!+#REF!+#REF!+#REF!+#REF! -> #REF! | L22: =+'F-100'!L22+'F-200'!L22+'F-300'!L22+'F-400'!L22+'F-500'!L22+'F-600'!L22+#REF!+#REF!+#REF!+#REF!+#REF!+#REF! -> #REF! | N22: =+'F-100'!N22+'F-200'!N22+'F-300'!N22+'F-400'!N22+'F-500'!N22+'F-600'!N22+#REF!+#REF!+#REF!+#REF!+#REF!+#REF! -> #REF! | O22: =+'F-100'!O22+'F-200'!O22+'F-300'!O22+'F-400'!O22+'F-500'!O22+'F-600'!O22+#REF!+#REF!+#REF!+#REF!+#REF!+#REF! -> #REF! | P22: =+'F-100'!P22+'F-200'!P22+'F-300'!P22+'F-400'!P22+'F-500'!P22+'F-600'!P22+#REF!+#REF!+#REF!+#REF!+#REF!+#REF! -> #REF! | Q22: =+'F-100'!Q22+'F-200'!Q22+'F-300'!Q22+'F-400'!Q22+'F-500'!Q22+'F-600'!Q22+#REF!+#REF!+#REF!+#REF!+#REF!+#REF! -> #REF! | R22: =+'F-100'!R22+'F-200'!R22+'F-300'!R22+'F-400'!R22+'F-500'!R22+'F-600'!R22+#REF!+#REF!+#REF!+#REF!+#REF!+#REF! -> #REF! | S22: =+SUMIFS(N22:R22,N$2:R$2,$S$5) -> 0 | U22: =+SUMIFS(N22:S22,N$2:S$2,$U$5) -> 0 | V22: =+SUMIFS(N22:S22,N$2:S$2,$V$5) -> 0 | W22: =+SUMIFS(N22:S22,N$2:S$2,$W$5) -> 0 | Y22: =+K22+L22 -> #REF! | Z22: =+'F-100'!Z22+'F-200'!Z22+'F-300'!Z22+'F-400'!Z22+'F-500'!Z22+'F-600'!Z22+#REF!+#REF!+#REF!+#REF!+#REF!+#REF! -> #REF! | AA22: =+'F-100'!AA22+'F-200'!AA22+'F-300'!AA22+'F-400'!AA22+'F-500'!AA22+'F-600'!AA22+#REF!+#REF!+#REF!+#REF!+#REF!+#REF! -> #REF! | AB22: =+'F-100'!AB22+'F-200'!AB22+'F-300'!AB22+'F-400'!AB22+'F-500'!AB22+'F-600'!AB22+#REF!+#REF!+#REF!+#REF!+#REF!+#REF! -> #REF! | AC22: =+'F-100'!AC22+'F-200'!AC22+'F-300'!AC22+'F-400'!AC22+'F-500'!AC22+'F-600'!AC22+#REF!+#REF!+#REF!+#REF!+#REF!+#REF! -> #REF! | AE22: =+'F-100'!AE22+'F-200'!AE22+'F-300'!AE22+'F-400'!AE22+'F-500'!AE22+'F-600'!AE22+#REF!+#REF!+#REF!+#REF!+#REF!+#REF! -> #REF! | AG22: =+AC22-Y22 -> #REF! | AJ22: =SUM(AK22:AQ22) -> #REF! | AK22: =+'F-100'!AK22+'F-200'!AK22+'F-300'!AJ22+'F-400'!AJ22+'F-500'!AJ22+'F-600'!AJ22+#REF!+#REF!+#REF!+#REF!+#REF!+#REF! -> #REF!
C23: Terceros | E23: =+'F-100'!E23+'F-200'!E23+'F-300'!E23+'F-400'!E23+'F-500'!E23+'F-600'!E23+#REF!+#REF!+#REF!+#REF!+#REF!+#REF! -> #REF! | G23: =+'F-100'!G23+'F-200'!G23+'F-300'!G23+'F-400'!G23+'F-500'!G23+'F-600'!G23+#REF!+#REF!+#REF!+#REF!+#REF!+#REF! -> #REF! | H23: =+'F-100'!H23+'F-200'!H23+'F-300'!H23+'F-400'!H23+'F-500'!H23+'F-600'!H23+#REF!+#REF!+#REF!+#REF!+#REF!+#REF! -> #REF! | J23: =+'F-100'!J23+'F-200'!J23+'F-300'!J23+'F-400'!J23+'F-500'!J23+'F-600'!J23+#REF!+#REF!+#REF!+#REF!+#REF!+#REF! -> #REF! | K23: =+'F-100'!K23+'F-200'!K23+'F-300'!K23+'F-400'!K23+'F-500'!K23+'F-600'!K23+#REF!+#REF!+#REF!+#REF!+#REF!+#REF! -> #REF! | L23: =+'F-100'!L23+'F-200'!L23+'F-300'!L23+'F-400'!L23+'F-500'!L23+'F-600'!L23+#REF!+#REF!+#REF!+#REF!+#REF!+#REF! -> #REF! | N23: =+'F-100'!N23+'F-200'!N23+'F-300'!N23+'F-400'!N23+'F-500'!N23+'F-600'!N23+#REF!+#REF!+#REF!+#REF!+#REF!+#REF! -> #REF! | O23: =+'F-100'!O23+'F-200'!O23+'F-300'!O23+'F-400'!O23+'F-500'!O23+'F-600'!O23+#REF!+#REF!+#REF!+#REF!+#REF!+#REF! -> #REF! | P23: =+'F-100'!P23+'F-200'!P23+'F-300'!P23+'F-400'!P23+'F-500'!P23+'F-600'!P23+#REF!+#REF!+#REF!+#REF!+#REF!+#REF! -> #REF! | Q23: =+'F-100'!Q23+'F-200'!Q23+'F-300'!Q23+'F-400'!Q23+'F-500'!Q23+'F-600'!Q23+#REF!+#REF!+#REF!+#REF!+#REF!+#REF! -> #REF! | R23: =+'F-100'!R23+'F-200'!R23+'F-300'!R23+'F-400'!R23+'F-500'!R23+'F-600'!R23+#REF!+#REF!+#REF!+#REF!+#REF!+#REF! -> #REF! | S23: =+SUMIFS(N23:R23,N$2:R$2,$S$5) -> 0 | U23: =+SUMIFS(N23:S23,N$2:S$2,$U$5) -> 0 | V23: =+SUMIFS(N23:S23,N$2:S$2,$V$5) -> 0 | W23: =+SUMIFS(N23:S23,N$2:S$2,$W$5) -> 0 | Y23: =+K23+L23 -> #REF! | Z23: =+'F-100'!Z23+'F-200'!Z23+'F-300'!Z23+'F-400'!Z23+'F-500'!Z23+'F-600'!Z23+#REF!+#REF!+#REF!+#REF!+#REF!+#REF! -> #REF! | AA23: =+'F-100'!AA23+'F-200'!AA23+'F-300'!AA23+'F-400'!AA23+'F-500'!AA23+'F-600'!AA23+#REF!+#REF!+#REF!+#REF!+#REF!+#REF! -> #REF! | AB23: =+'F-100'!AB23+'F-200'!AB23+'F-300'!AB23+'F-400'!AB23+'F-500'!AB23+'F-600'!AB23+#REF!+#REF!+#REF!+#REF!+#REF!+#REF! -> #REF! | AC23: =+'F-100'!AC23+'F-200'!AC23+'F-300'!AC23+'F-400'!AC23+'F-500'!AC23+'F-600'!AC23+#REF!+#REF!+#REF!+#REF!+#REF!+#REF! -> #REF! | AE23: =+'F-100'!AE23+'F-200'!AE23+'F-300'!AE23+'F-400'!AE23+'F-500'!AE23+'F-600'!AE23+#REF!+#REF!+#REF!+#REF!+#REF!+#REF! -> #REF! | AG23: =+AC23-Y23 -> #REF! | AJ23: =SUM(AK23:AQ23) -> #REF! | AK23: =+'F-100'!AK23+'F-200'!AK23+'F-300'!AJ23+'F-400'!AJ23+'F-500'!AJ23+'F-600'!AJ23+#REF!+#REF!+#REF!+#REF!+#REF!+#REF! -> #REF!
B24: Fletes | E24: =+'F-100'!E24+'F-200'!E24+'F-300'!E24+'F-400'!E24+'F-500'!E24+'F-600'!E24+#REF!+#REF!+#REF!+#REF!+#REF!+#REF! -> #REF! | G24: =+'F-100'!G24+'F-200'!G24+'F-300'!G24+'F-400'!G24+'F-500'!G24+'F-600'!G24+#REF!+#REF!+#REF!+#REF!+#REF!+#REF! -> #REF! | H24: =+'F-100'!H24+'F-200'!H24+'F-300'!H24+'F-400'!H24+'F-500'!H24+'F-600'!H24+#REF!+#REF!+#REF!+#REF!+#REF!+#REF! -> #REF! | J24: =+'F-100'!J24+'F-200'!J24+'F-300'!J24+'F-400'!J24+'F-500'!J24+'F-600'!J24+#REF!+#REF!+#REF!+#REF!+#REF!+#REF! -> #REF! | K24: =+'F-100'!K24+'F-200'!K24+'F-300'!K24+'F-400'!K24+'F-500'!K24+'F-600'!K24+#REF!+#REF!+#REF!+#REF!+#REF!+#REF! -> #REF! | L24: =+'F-100'!L24+'F-200'!L24+'F-300'!L24+'F-400'!L24+'F-500'!L24+'F-600'!L24+#REF!+#REF!+#REF!+#REF!+#REF!+#REF! -> #REF! | N24: =+'F-100'!N24+'F-200'!N24+'F-300'!N24+'F-400'!N24+'F-500'!N24+'F-600'!N24+#REF!+#REF!+#REF!+#REF!+#REF!+#REF! -> #REF! | O24: =+'F-100'!O24+'F-200'!O24+'F-300'!O24+'F-400'!O24+'F-500'!O24+'F-600'!O24+#REF!+#REF!+#REF!+#REF!+#REF!+#REF! -> #REF! | P24: =+'F-100'!P24+'F-200'!P24+'F-300'!P24+'F-400'!P24+'F-500'!P24+'F-600'!P24+#REF!+#REF!+#REF!+#REF!+#REF!+#REF! -> #REF! | Q24: =+'F-100'!Q24+'F-200'!Q24+'F-300'!Q24+'F-400'!Q24+'F-500'!Q24+'F-600'!Q24+#REF!+#REF!+#REF!+#REF!+#REF!+#REF! -> #REF! | R24: =+'F-100'!R24+'F-200'!R24+'F-300'!R24+'F-400'!R24+'F-500'!R24+'F-600'!R24+#REF!+#REF!+#REF!+#REF!+#REF!+#REF! -> #REF! | S24: =+SUMIFS(N24:R24,N$2:R$2,$S$5) -> 0 | U24: =+SUMIFS(N24:S24,N$2:S$2,$U$5) -> 0 | V24: =+SUMIFS(N24:S24,N$2:S$2,$V$5) -> 0 | W24: =+SUMIFS(N24:S24,N$2:S$2,$W$5) -> 0 | Y24: =+K24+L24 -> #REF! | Z24: =+'F-100'!Z24+'F-200'!Z24+'F-300'!Z24+'F-400'!Z24+'F-500'!Z24+'F-600'!Z24+#REF!+#REF!+#REF!+#REF!+#REF!+#REF! -> #REF! | AA24: =+'F-100'!AA24+'F-200'!AA24+'F-300'!AA24+'F-400'!AA24+'F-500'!AA24+'F-600'!AA24+#REF!+#REF!+#REF!+#REF!+#REF!+#REF! -> #REF! | AB24: =+'F-100'!AB24+'F-200'!AB24+'F-300'!AB24+'F-400'!AB24+'F-500'!AB24+'F-600'!AB24+#REF!+#REF!+#REF!+#REF!+#REF!+#REF! -> #REF! | AC24: =+'F-100'!AC24+'F-200'!AC24+'F-300'!AC24+'F-400'!AC24+'F-500'!AC24+'F-600'!AC24+#REF!+#REF!+#REF!+#REF!+#REF!+#REF! -> #REF! | AE24: =+'F-100'!AE24+'F-200'!AE24+'F-300'!AE24+'F-400'!AE24+'F-500'!AE24+'F-600'!AE24+#REF!+#REF!+#REF!+#REF!+#REF!+#REF! -> #REF! | AG24: =+AC24-Y24 -> #REF! | AJ24: =SUM(AK24:AQ24) -> #REF! | AK24: =+'F-100'!AK24+'F-200'!AK24+'F-300'!AJ24+'F-400'!AJ24+'F-500'!AJ24+'F-600'!AJ24+#REF!+#REF!+#REF!+#REF!+#REF!+#REF! -> #REF!
B25: Staff (Sueldos) | E25: =+'F-100'!E25+'F-200'!E25+'F-300'!E25+'F-400'!E25+'F-500'!E25+'F-600'!E25+#REF!+#REF!+#REF!+#REF!+#REF!+#REF! -> #REF! | G25: =+'F-100'!G25+'F-200'!G25+'F-300'!G25+'F-400'!G25+'F-500'!G25+'F-600'!G25+#REF!+#REF!+#REF!+#REF!+#REF!+#REF! -> #REF! | H25: =+'F-100'!H25+'F-200'!H25+'F-300'!H25+'F-400'!H25+'F-500'!H25+'F-600'!H25+#REF!+#REF!+#REF!+#REF!+#REF!+#REF! -> #REF! | J25: =+'F-100'!J25+'F-200'!J25+'F-300'!J25+'F-400'!J25+'F-500'!J25+'F-600'!J25+#REF!+#REF!+#REF!+#REF!+#REF!+#REF! -> #REF! | K25: =+'F-100'!K25+'F-200'!K25+'F-300'!K25+'F-400'!K25+'F-500'!K25+'F-600'!K25+#REF!+#REF!+#REF!+#REF!+#REF!+#REF! -> #REF! | L25: =+'F-100'!L25+'F-200'!L25+'F-300'!L25+'F-400'!L25+'F-500'!L25+'F-600'!L25+#REF!+#REF!+#REF!+#REF!+#REF!+#REF! -> #REF! | N25: =+'F-100'!N25+'F-200'!N25+'F-300'!N25+'F-400'!N25+'F-500'!N25+'F-600'!N25+#REF!+#REF!+#REF!+#REF!+#REF!+#REF! -> #REF! | O25: =+'F-100'!O25+'F-200'!O25+'F-300'!O25+'F-400'!O25+'F-500'!O25+'F-600'!O25+#REF!+#REF!+#REF!+#REF!+#REF!+#REF! -> #REF! | P25: =+'F-100'!P25+'F-200'!P25+'F-300'!P25+'F-400'!P25+'F-500'!P25+'F-600'!P25+#REF!+#REF!+#REF!+#REF!+#REF!+#REF! -> #REF! | Q25: =+'F-100'!Q25+'F-200'!Q25+'F-300'!Q25+'F-400'!Q25+'F-500'!Q25+'F-600'!Q25+#REF!+#REF!+#REF!+#REF!+#REF!+#REF! -> #REF! | R25: =+'F-100'!R25+'F-200'!R25+'F-300'!R25+'F-400'!R25+'F-500'!R25+'F-600'!R25+#REF!+#REF!+#REF!+#REF!+#REF!+#REF! -> #REF! | S25: =+SUMIFS(N25:R25,N$2:R$2,$S$5) -> 0 | U25: =+SUMIFS(N25:S25,N$2:S$2,$U$5) -> 0 | V25: =+SUMIFS(N25:S25,N$2:S$2,$V$5) -> 0 | W25: =+SUMIFS(N25:S25,N$2:S$2,$W$5) -> 0 | Y25: =+K25+L25 -> #REF! | Z25: =+'F-100'!Z25+'F-200'!Z25+'F-300'!Z25+'F-400'!Z25+'F-500'!Z25+'F-600'!Z25+#REF!+#REF!+#REF!+#REF!+#REF!+#REF! -> #REF! | AA25: =+'F-100'!AA25+'F-200'!AA25+'F-300'!AA25+'F-400'!AA25+'F-500'!AA25+'F-600'!AA25+#REF!+#REF!+#REF!+#REF!+#REF!+#REF! -> #REF! | AB25: =+'F-100'!AB25+'F-200'!AB25+'F-300'!AB25+'F-400'!AB25+'F-500'!AB25+'F-600'!AB25+#REF!+#REF!+#REF!+#REF!+#REF!+#REF! -> #REF! | AC25: =+'F-100'!AC25+'F-200'!AC25+'F-300'!AC25+'F-400'!AC25+'F-500'!AC25+'F-600'!AC25+#REF!+#REF!+#REF!+#REF!+#REF!+#REF! -> #REF! | AE25: =+'F-100'!AE25+'F-200'!AE25+'F-300'!AE25+'F-400'!AE25+'F-500'!AE25+'F-600'!AE25+#REF!+#REF!+#REF!+#REF!+#REF!+#REF! -> #REF! | AG25: =+AC25-Y25 -> #REF! | AJ25: =SUM(AK25:AQ25) -> #REF! | AK25: =+'F-100'!AK25+'F-200'!AK25+'F-300'!AJ25+'F-400'!AJ25+'F-500'!AJ25+'F-600'!AJ25+#REF!+#REF!+#REF!+#REF!+#REF!+#REF! -> #REF!
B26: Gastos Generales | E26: =+'F-100'!E26+'F-200'!E26+'F-300'!E26+'F-400'!E26+'F-500'!E26+'F-600'!E26+#REF!+#REF!+#REF!+#REF!+#REF!+#REF! -> #REF! | G26: =+'F-100'!G26+'F-200'!G26+'F-300'!G26+'F-400'!G26+'F-500'!G26+'F-600'!G26+#REF!+#REF!+#REF!+#REF!+#REF!+#REF! -> #REF! | H26: =+'F-100'!H26+'F-200'!H26+'F-300'!H26+'F-400'!H26+'F-500'!H26+'F-600'!H26+#REF!+#REF!+#REF!+#REF!+#REF!+#REF! -> #REF! | J26: =+'F-100'!J26+'F-200'!J26+'F-300'!J26+'F-400'!J26+'F-500'!J26+'F-600'!J26+#REF!+#REF!+#REF!+#REF!+#REF!+#REF! -> #REF! | K26: =+'F-100'!K26+'F-200'!K26+'F-300'!K26+'F-400'!K26+'F-500'!K26+'F-600'!K26+#REF!+#REF!+#REF!+#REF!+#REF!+#REF! -> #REF! | L26: =+'F-100'!L26+'F-200'!L26+'F-300'!L26+'F-400'!L26+'F-500'!L26+'F-600'!L26+#REF!+#REF!+#REF!+#REF!+#REF!+#REF! -> #REF! | N26: =+'F-100'!N26+'F-200'!N26+'F-300'!N26+'F-400'!N26+'F-500'!N26+'F-600'!N26+#REF!+#REF!+#REF!+#REF!+#REF!+#REF! -> #REF! | O26: =+'F-100'!O26+'F-200'!O26+'F-300'!O26+'F-400'!O26+'F-500'!O26+'F-600'!O26+#REF!+#REF!+#REF!+#REF!+#REF!+#REF! -> #REF! | P26: =+'F-100'!P26+'F-200'!P26+'F-300'!P26+'F-400'!P26+'F-500'!P26+'F-600'!P26+#REF!+#REF!+#REF!+#REF!+#REF!+#REF! -> #REF! | Q26: =+'F-100'!Q26+'F-200'!Q26+'F-300'!Q26+'F-400'!Q26+'F-500'!Q26+'F-600'!Q26+#REF!+#REF!+#REF!+#REF!+#REF!+#REF! -> #REF! | R26: =+'F-100'!R26+'F-200'!R26+'F-300'!R26+'F-400'!R26+'F-500'!R26+'F-600'!R26+#REF!+#REF!+#REF!+#REF!+#REF!+#REF! -> #REF! | S26: =+SUMIFS(N26:R26,N$2:R$2,$S$5) -> 0 | U26: =+SUMIFS(N26:S26,N$2:S$2,$U$5) -> 0 | V26: =+SUMIFS(N26:S26,N$2:S$2,$V$5) -> 0 | W26: =+SUMIFS(N26:S26,N$2:S$2,$W$5) -> 0 | Y26: =+K26+L26 -> #REF! | Z26: =+'F-100'!Z26+'F-200'!Z26+'F-300'!Z26+'F-400'!Z26+'F-500'!Z26+'F-600'!Z26+#REF!+#REF!+#REF!+#REF!+#REF!+#REF! -> #REF! | AA26: =+'F-100'!AA26+'F-200'!AA26+'F-300'!AA26+'F-400'!AA26+'F-500'!AA26+'F-600'!AA26+#REF!+#REF!+#REF!+#REF!+#REF!+#REF! -> #REF! | AB26: =+'F-100'!AB26+'F-200'!AB26+'F-300'!AB26+'F-400'!AB26+'F-500'!AB26+'F-600'!AB26+#REF!+#REF!+#REF!+#REF!+#REF!+#REF! -> #REF! | AC26: =+'F-100'!AC26+'F-200'!AC26+'F-300'!AC26+'F-400'!AC26+'F-500'!AC26+'F-600'!AC26+#REF!+#REF!+#REF!+#REF!+#REF!+#REF! -> #REF! | AE26: =+'F-100'!AE26+'F-200'!AE26+'F-300'!AE26+'F-400'!AE26+'F-500'!AE26+'F-600'!AE26+#REF!+#REF!+#REF!+#REF!+#REF!+#REF! -> #REF! | AG26: =+AC26-Y26 -> #REF! | AJ26: =SUM(AK26:AQ26) -> #REF! | AK26: =+'F-100'!AK26+'F-200'!AK26+'F-300'!AJ26+'F-400'!AJ26+'F-500'!AJ26+'F-600'!AJ26+#REF!+#REF!+#REF!+#REF!+#REF!+#REF! -> #REF!
B28: Stock de Materiales | E28: =+'F-100'!E28+'F-200'!E28+'F-300'!E28+'F-400'!E28+'F-500'!E28+'F-600'!E28+#REF!+#REF!+#REF!+#REF!+#REF!+#REF! -> #REF! | G28: =+'F-100'!G28+'F-200'!G28+'F-300'!G28+'F-400'!G28+'F-500'!G28+'F-600'!G28+#REF!+#REF!+#REF!+#REF!+#REF!+#REF! -> #REF! | H28: =+'F-100'!H28+'F-200'!H28+'F-300'!H28+'F-400'!H28+'F-500'!H28+'F-600'!H28+#REF!+#REF!+#REF!+#REF!+#REF!+#REF! -> #REF! | J28: =+'F-100'!J28+'F-200'!J28+'F-300'!J28+'F-400'!J28+'F-500'!J28+'F-600'!J28+#REF!+#REF!+#REF!+#REF!+#REF!+#REF! -> #REF! | K28: =+'F-100'!K28+'F-200'!K28+'F-300'!K28+'F-400'!K28+'F-500'!K28+'F-600'!K28+#REF!+#REF!+#REF!+#REF!+#REF!+#REF! -> #REF! | L28: =+'F-100'!L28+'F-200'!L28+'F-300'!L28+'F-400'!L28+'F-500'!L28+'F-600'!L28+#REF!+#REF!+#REF!+#REF!+#REF!+#REF! -> #REF! | N28: =+'F-100'!N28+'F-200'!N28+'F-300'!N28+'F-400'!N28+'F-500'!N28+'F-600'!N28+#REF!+#REF!+#REF!+#REF!+#REF!+#REF! -> #REF! | O28: =+'F-100'!O28+'F-200'!O28+'F-300'!O28+'F-400'!O28+'F-500'!O28+'F-600'!O28+#REF!+#REF!+#REF!+#REF!+#REF!+#REF! -> #REF! | P28: =+'F-100'!P28+'F-200'!P28+'F-300'!P28+'F-400'!P28+'F-500'!P28+'F-600'!P28+#REF!+#REF!+#REF!+#REF!+#REF!+#REF! -> #REF! | Q28: =+'F-100'!Q28+'F-200'!Q28+'F-300'!Q28+'F-400'!Q28+'F-500'!Q28+'F-600'!Q28+#REF!+#REF!+#REF!+#REF!+#REF!+#REF! -> #REF! | R28: =+'F-100'!R28+'F-200'!R28+'F-300'!R28+'F-400'!R28+'F-500'!R28+'F-600'!R28+#REF!+#REF!+#REF!+#REF!+#REF!+#REF! -> #REF! | S28: =+SUMIFS(N28:R28,N$2:R$2,$S$5) -> 0 | U28: =+SUMIFS(N28:S28,N$2:S$2,$U$5) -> 0 | V28: =+SUMIFS(N28:S28,N$2:S$2,$V$5) -> 0 | W28: =+SUMIFS(N28:S28,N$2:S$2,$W$5) -> 0 | Y28: 0 | Z28: =+'F-100'!Z28+'F-200'!Z28+'F-300'!Z28+'F-400'!Z28+'F-500'!Z28+'F-600'!Z28+#REF!+#REF!+#REF!+#REF!+#REF!+#REF! -> #REF! | AA28: =+'F-100'!AA28+'F-200'!AA28+'F-300'!AA28+'F-400'!AA28+'F-500'!AA28+'F-600'!AA28+#REF!+#REF!+#REF!+#REF!+#REF!+#REF! -> #REF! | AB28: =+'F-100'!AB28+'F-200'!AB28+'F-300'!AB28+'F-400'!AB28+'F-500'!AB28+'F-600'!AB28+#REF!+#REF!+#REF!+#REF!+#REF!+#REF! -> #REF! | AC28: =+'F-100'!AC28+'F-200'!AC28+'F-300'!AC28+'F-400'!AC28+'F-500'!AC28+'F-600'!AC28+#REF!+#REF!+#REF!+#REF!+#REF!+#REF! -> #REF! | AE28: =+'F-100'!AE28+'F-200'!AE28+'F-300'!AE28+'F-400'!AE28+'F-500'!AE28+'F-600'!AE28+#REF!+#REF!+#REF!+#REF!+#REF!+#REF! -> #REF! | AJ28: =SUM(AK28:AQ28) -> #REF! | AK28: =+'F-100'!AK28+'F-200'!AK28+'F-300'!AJ28+'F-400'!AJ28+'F-500'!AJ28+'F-600'!AJ28+#REF!+#REF!+#REF!+#REF!+#REF!+#REF! -> #REF!
B30: Margen Ponderado S/. | E30: =+E7*E31 -> #REF! | G30: =+G7*G31 -> #REF! | H30: =+H7*H31 -> #REF! | J30: =+J7*J31 -> #REF! | K30: =+K7*K31 -> #REF! | L30: =+L7*L31 -> #REF! | N30: =+N7*N31 -> #REF! | O30: =+O7*O31 -> #REF! | P30: =+P7*P31 -> #REF! | Q30: =+Q7*Q31 -> #REF! | R30: =+R7*R31 -> #REF! | S30: =+S7*S31 -> #REF! | U30: =+U7*U31 -> #REF! | V30: =+V7*V31 -> #REF! | W30: =+W7*W31 -> #REF! | Y30: =+Y7-Y15 -> #REF! | Z30: =+Z7-Z15 -> #REF! | AA30: =+AA7-AA15 -> #REF! | AB30: =+AB7-AB15 -> #REF! | AC30: =+AC7-AC15 -> #REF! | AE30: 0 | AG30: =+Y30-AC30 -> #REF!
B31: Margen Ponderado % | E31: =+$Y$31 -> #REF! | G31: =+$Y$31 -> #REF! | H31: =+$Y$31 -> #REF! | J31: =+$Y$31 -> #REF! | K31: =+$Y$31 -> #REF! | L31: =+$Y$31 -> #REF! | N31: =+$Y$31 -> #REF! | O31: =+$Y$31 -> #REF! | P31: =+$Y$31 -> #REF! | Q31: =+$Y$31 -> #REF! | R31: =+$Y$31 -> #REF! | S31: =+$Y$31 -> #REF! | U31: =+$Y$31 -> #REF! | V31: =+$Y$31 -> #REF! | W31: =+$Y$31 -> #REF! | Y31: =+IF(Y7=0,0,Y30/Y7) -> #REF! | Z31: =+IF(Z7=0,0,Z30/Z7) -> #REF! | AA31: =+IF(AA7=0,0,AA30/AA7) -> #REF! | AB31: =+IF(AB7=0,0,AB30/AB7) -> #REF! | AC31: =+IF(AC7=0,0,AC30/AC7) -> #REF! | AE31: 0
B33: Margen Absoluto S/. | E33: =+E7-E15+E28 -> #REF! | G33: =+G7-G15+G28 -> #REF! | H33: =+H7-H15+H28 -> #REF! | J33: =+J7-J15+J28 -> #REF! | K33: =+K7-K15+K28 -> #REF! | L33: =+L7-L15+L28 -> #REF! | N33: =+N7-N15+N28 -> #REF! | O33: =+O7-O15+O28 -> #REF! | P33: =+P7-P15+P28 -> #REF! | Q33: =+Q7-Q15+Q28 -> #REF! | R33: =+R7-R15+R28 -> #REF! | S33: =+S7-S15+S28 -> 0 | U33: =+U7-U15+U28 -> 0 | V33: =+V7-V15+V28 -> 0 | W33: =+W7-W15+W28 -> 0 | Y33: =+Y7-Y15+Y28 -> #REF! | Z33: =+Z7-Z15+Z28 -> #REF! | AA33: =+AA7-AA15+AA28 -> #REF! | AB33: =+AB7-AB15+AB28 -> #REF! | AC33: =+AC7-AC15+AC28 -> #REF! | AE33: 0
B34: Margen Absoluto % | E34: =+IF(E7=0,0,E33/E7) -> #REF! | G34: =+IF(G7=0,0,G33/G7) -> #REF! | H34: =+IF(H7=0,0,H33/H7) -> #REF! | J34: =+IF(J7=0,0,J33/J7) -> #REF! | K34: =+IF(K7=0,0,K33/K7) -> #REF! | L34: =+IF(L7=0,0,L33/L7) -> #REF! | N34: =+IF(N7=0,0,N33/N7) -> #REF! | O34: =+IF(O7=0,0,O33/O7) -> #REF! | P34: =+IF(P7=0,0,P33/P7) -> #REF! | Q34: =+IF(Q7=0,0,Q33/Q7) -> #REF! | R34: =+IF(R7=0,0,R33/R7) -> #REF! | S34: =+IF(S7=0,0,S33/S7) -> 0 | U34: =+IF(U7=0,0,U33/U7) -> 0 | V34: =+IF(V7=0,0,V33/V7) -> 0 | W34: =+IF(W7=0,0,W33/W7) -> 0 | Y34: =+IF(Y7=0,0,Y33/Y7) -> #REF! | Z34: =+IF(Z7=0,0,Z33/Z7) -> #REF! | AA34: =+IF(AA7=0,0,AA33/AA7) -> #REF! | AB34: =+IF(AB7=0,0,AB33/AB7) -> #REF! | AC34: =+IF(AC7=0,0,AC33/AC7) -> #REF! | AE34: 0
B38: COSTO APLICADO | K38: =+K7-K30 -> #REF!
B40: RESULTADO PENDIENTE | K40: =K15-K38 -> #REF!
B42: ACTIVOS | K42: ='F-100'!K42+'F-200'!K42+'F-300'!K42+'F-400'!K42+'F-500'!K42+'F-600'!K42+#REF!+#REF!+#REF!+#REF!+#REF! -> #REF!
B44: PROVISIONES | K44: ='F-100'!K44+'F-200'!K44+'F-300'!K44+'F-400'!K44+'F-500'!K44+'F-600'!K44+#REF!+#REF!+#REF!+#REF!+#REF! -> #REF!
B46: DIFERENCIA DE MARGENES | K46: ='F-100'!K46+'F-200'!K46+'F-300'!K46+'F-400'!K46+'F-500'!K46+'F-600'!K46+#REF!+#REF!+#REF!+#REF!+#REF! -> #REF!
B48: CONTINGENCIA | K48: =+K40-K42+K44 -> #REF!
C50: Mayor Margen +
C52: Menor Margen -

Sheet F-100
B1: =CONCATENATE(B3," - ",B4," - ",B5," - ",B6) -> I.E.N 1182 - MES DE ENERO DEL 2025 - EL BOSQUE - CERCO + INGRESOS Y CASETAS - FASE 100 : OBRAS PRELIMINARES
K2: =+K7/Y7 -> #DIV/0! | N2: =+YEAR(N5) -> 2019 | O2: =+YEAR(O5) -> 2019 | P2: =+YEAR(P5) -> 2019 | Q2: =+YEAR(Q5) -> 2019 | R2: =+YEAR(R5) -> 2019 | S2: =S5 -> 2024 | U2: 43466
B3: I.E.N 1182 | E3: ACUMULADO | G3: =+B4 -> MES DE ENERO DEL 2025 | J3: ACUMULADO DEL 2024 | K3: ACUMULADO DE OBRA | L3: SALDO DE OBRA | N3: PROYECCIÓN | U3: AÑOS SIGUIENTES | Y3: TOTAL DE OBRA | AE3: Acumulado del ejercicio | AI3: TOTAL | AJ3: AÑOS ANTERIORES | AK3: MES DEL INFORME | AL3: 45597 | AM3: 45627 | AN3: 45658 | AO3: 45689 | AP3: 45717
B4: MES DE ENERO DEL 2025 | N4: 1 | O4: =+N4+1 -> 2 | P4: =+O4+1 -> 3 | Q4: =+P4+1 -> 4 | R4: =+Q4+1 -> 5 | S4: Saldo del Ejercicio
B5: EL BOSQUE - CERCO + INGRESOS Y CASETAS | E5: Años Anteriores | G5: Previsto | H5: Real | N5: 43648 | O5: =+N5+31 -> 43679 | P5: =+O5+31 -> 43710 | Q5: =+P5+31 -> 43741 | R5: =+Q5+31 -> 43772 | S5: =+'DIRECTO '!S5 -> 2024 | U5: 2025 | V5: =+U5+1 -> 2026 | W5: =+V5+1 -> 2027 | Y5: Actual | Z5: Anterior | AA5: Meta | AB5: Presupuesto Interno | AC5: Presupuesto | AE5: Anterior
B6: FASE 100 : OBRAS PRELIMINARES
B7: Venta Total Producida | E7: =+E9 -> 0 | G7: =+G9 -> 0 | H7: =+H9 -> 0 | J7: =+J9 -> 0 | K7: =+K9 -> 0 | L7: =+L9+L14 -> 0 | N7: =+N9 -> 0 | O7: =+O9 -> 0 | P7: =+P9 -> 0 | Q7: =+Q9 -> 0 | R7: =+R9 -> 0 | S7: =+S9+S14 -> 0 | U7: =+U9 -> 0 | V7: =+V9 -> 0 | W7: =+W9 -> 0 | Y7: =+Y9 -> 0 | Z7: =+Z9 -> 0 | AA7: =+AA9 -> 0 | AB7: =+AB9 -> 0 | AC7: =+AC9 -> 0 | AE7: =+AE9 -> 0 | AI7: =+AI9 -> 0 | AK7: =+AK9 -> 0 | AL7: =+AL9 -> 0 | AM7: =+AM9 -> 0 | AN7: =+AN9 -> 0 | AO7: =+AO9 -> 0 | AP7: =+AP9 -> 0
B9: Venta | E9: =+SUM(E11:E13) -> 0 | G9: =+SUM(G11:G13) -> 0 | H9: =+SUM(H11:H13) -> 0 | J9: =+SUM(J11:J13) -> 0 | K9: =+SUM(K11:K13) -> 0 | L9: =+SUM(L11:L12) -> 0 | N9: =+SUM(N11:N13) -> 0 | O9: =+SUM(O11:O13) -> 0 | P9: =+SUM(P11:P13) -> 0 | Q9: =+SUM(Q11:Q13) -> 0 | R9: =+SUM(R11:R13) -> 0 | S9: =+SUM(S11:S13) -> 0 | U9: =+SUM(U11:U13) -> 0 | V9: =+SUM(V11:V13) -> 0 | W9: =+SUM(W11:W13) -> 0 | Y9: =+SUM(Y11:Y13) -> 0 | Z9: =+SUM(Z11:Z13) -> 0 | AA9: =+SUM(AA11:AA13) -> 0 | AB9: =+SUM(AB11:AB13) -> 0 | AC9: =+SUM(AC11:AC13) -> 0 | AE9: =+SUM(AE11:AE13) -> 0 | AI9: =+SUM(AI11:AI13) -> 0 | AK9: =+SUM(AK11:AK13) -> 0 | AL9: =+SUM(AL11:AL13) -> 0 | AM9: =+SUM(AM11:AM13) -> 0 | AN9: =+SUM(AN11:AN13) -> 0 | AO9: =+SUM(AO11:AO13) -> 0 | AP9: =+SUM(AP11:AP13) -> 0
B11: Valorización: Venta Directa - Contrato Principal | E11: =AJ11 -> 0 | G11: 0 | H11: =+AK11 -> 0 | J11: =+H11+AE11 -> 0 | K11: =+E11+J11 -> 0 | L11: =+SUM(O11:R11) -> 0 | N11: 0 | O11: 0 | P11: 0 | Q11: 0 | R11: 0 | S11: =+SUMIFS(N11:R11,N$2:R$2,$S$5) -> 0 | U11: =+SUMIFS(N11:S11,N$2:S$2,$U$5) -> 0 | V11: =+SUMIFS(N11:S11,N$2:S$2,$V$5) -> 0 | W11: =+SUMIFS(N11:S11,N$2:S$2,$W$5) -> 0 | Y11: =+K11+L11 -> 0 | AI11: =SUM(AL11:AP11) -> 0 | AJ11: =SUM(AL11:AM11) -> 0 | AK11: =+AN11 -> 0
B12: Valorización: Venta Indirecta - Contrato Principal | E12: =AJ12 -> 0 | G12: 0 | H12: =+AK12 -> 0 | J12: =+H12+AE12 -> 0 | K12: =+E12+J12 -> 0 | L12: =+SUM(O12:R12) -> 0 | N12: 0 | O12: 0 | P12: 0 | Q12: 0 | R12: 0 | S12: =+SUMIFS(N12:R12,N$2:R$2,$S$5) -> 0 | U12: =+SUMIFS(N12:S12,N$2:S$2,$U$5) -> 0 | V12: =+SUMIFS(N12:S12,N$2:S$2,$V$5) -> 0 | W12: =+SUMIFS(N12:S12,N$2:S$2,$W$5) -> 0 | Y12: =+K12+L12 -> 0 | AI12: =SUM(AL12:AP12) -> 0 | AJ12: =SUM(AL12:AM12) -> 0 | AK12: =+AN12 -> 0
B13: Otros: | E13: =AJ13 -> 0 | G13: 0 | H13: =+AK13 -> 0 | J13: =+H13+AE13 -> 0 | K13: =+E13+J13 -> 0 | L13: =+SUM(O13:R13) -> 0 | N13: 0 | O13: 0 | P13: 0 | Q13: 0 | R13: 0 | S13: =+SUMIFS(N13:R13,N$2:R$2,$S$5) -> 0 | U13: =+SUMIFS(N13:S13,N$2:S$2,$U$5) -> 0 | V13: =+SUMIFS(N13:S13,N$2:S$2,$V$5) -> 0 | W13: =+SUMIFS(N13:S13,N$2:S$2,$W$5) -> 0 | Y13: =+K13+L13 -> 0 | AI13: =SUM(AL13:AP13) -> 0 | AJ13: =SUM(AL13:AM13) -> 0 | AK13: =+AN13 -> 0
B15: Costo Total | E15: =+SUM(E17:E26)+E28 -> 0 | G15: =+SUM(G17:G26)+G28 -> 0 | H15: =+SUM(H17:H26)+H28 -> 0 | J15: =+SUM(J17:J26)+J28 -> 0 | K15: =+SUM(K17:K26)+K28 -> 0 | L15: =+SUM(L17:L26,L28) -> 0 | N15: =+SUM(N17:N26)+N28 -> 0 | O15: =+SUM(O17:O26)+O28 -> 0 | P15: =+SUM(P17:P26)+P28 -> 0 | Q15: =+SUM(Q17:Q26)+Q28 -> 0 | R15: =+SUM(R17:R26)+R28 -> 0 | S15: =+SUM(S17:S26)+S28 -> 0 | U15: =+SUM(U17:U26)+U28 -> 0 | V15: =+SUM(V17:V26)+V28 -> 0 | W15: =+SUM(W17:W26)+W28 -> 0 | Y15: =+SUM(Y17:Y26)+Y28 -> 0 | Z15: =+SUM(Z17:Z26)+Z28 -> 0 | AA15: =+SUM(AA17:AA26)+AA28 -> 0 | AB15: =+SUM(AB17:AB26)+AB28 -> 0 | AC15: =+SUM(AC17:AC26,AC28) -> 4572553.5 | AE15: =+SUM(AE17:AE26)+AE28 -> 0 | AI15: =+SUM(AI17:AI26) -> 0 | AK15: =+SUM(AK17:AK26) -> 0 | AL15: =+SUM(AL17:AL26) -> 0 | AM15: =+SUM(AM17:AM26) -> 0 | AN15: =+SUM(AN17:AN26) -> 0 | AO15: =+SUM(AO17:AO26) -> 0 | AP15: =+SUM(AP17:AP26) -> 0
B17: Materiales | E17: =AJ17 -> 0 | G17: =+Mat!H19 -> 0 | H17: =+AK17 -> 0 | J17: =+H17+AE17 -> 0 | K17: =+E17+J17 -> 0 | L17: =+SUM(O17:R17) -> 0 | N17: =+Mat!O19 -> 0 | O17: =+Mat!P19 -> 0 | P17: =+Mat!Q19 -> 0 | Q17: =+Mat!R19 -> 0 | R17: =+Mat!S19 -> 0 | S17: =+SUMIFS(N17:R17,N$2:R$2,$S$5) -> 0 | U17: =+SUMIFS(N17:S17,N$2:S$2,$U$5) -> 0 | V17: =+SUMIFS(N17:S17,N$2:S$2,$V$5) -> 0 | W17: =+SUMIFS(N17:S17,N$2:S$2,$W$5) -> 0 | Y17: =+K17+L17 -> 0 | Z17: =+Mat!Z19 -> 0 | AA17: =+Mat!AA19 -> 0 | AB17: =+Mat!AB19 -> 0 | AC17: 120349.25 | AI17: =SUM(AL17:AP17) -> 0 | AJ17: =SUM(AL17:AM17) -> 0 | AK17: =+AN17 -> 0
B18: Mano de Obra | E18: =AJ18 -> 0 | G18: =+MO!H21 -> 0 | H18: =+AK18 -> 0 | J18: =+H18+AE18 -> 0 | K18: =+J18+E18 -> 0 | L18: =+SUM(O18:R18) -> 0 | N18: =+N19ai19 -> 0 | O18: =+MO!P21 -> 0 | P18: =+MO!Q21 -> 0 | Q18: =+MO!R21 -> 0 | R18: =+MO!S21 -> 0 | S18: =+SUMIFS(N18:R18,N$2:R$2,$S$5) -> 0 | U18: =+SUMIFS(N18:S18,N$2:S$2,$U$5) -> 0 | V18: =+SUMIFS(N18:S18,N$2:S$2,$V$5) -> 0 | W18: =+SUMIFS(N18:S18,N$2:S$2,$W$5) -> 0 | Y18: =+K18+L18 -> 0 | Z18: =+MO!Z21 -> 0 | AA18: =+MO!AA21 -> 0 | AB18: =+MO!AB21 -> 0 | AC18: 508729.33 | AI18: =SUM(AL18:AP18) -> 0 | AJ18: =SUM(AL18:AM18) -> 0 | AK18: =+AN18 -> 0
B19: Subcontratos de obra | E19: =AJ19 -> 0 | G19: =+SC!H19 -> 0 | H19: =+AK19 -> 0 | J19: =+H19+AE19 -> 0 | K19: =+J19+E19 -> 0 | L19: =+SUM(O19:R19) -> 0 | N19: =+SC!O19 -> 0 | O19: =+SC!P19 -> 0 | P19: =+SC!Q19 -> 0 | Q19: =+SC!R19 -> 0 | R19: =+SC!S19 -> 0 | S19: =+SUMIFS(N19:R19,N$2:R$2,$S$5) -> 0 | U19: =+SUMIFS(N19:S19,N$2:S$2,$U$5) -> 0 | V19: =+SUMIFS(N19:S19,N$2:S$2,$V$5) -> 0 | W19: =+SUMIFS(N19:S19,N$2:S$2,$W$5) -> 0 | Y19: =+K19+L19 -> 0 | Z19: =+SC!Z19 -> 0 | AA19: =+SC!AA19 -> 0 | AB19: =+SC!AB19 -> 0 | AC19: 453396.29 | AI19: =SUM(AL19:AP19) -> 0 | AJ19: =SUM(AL19:AM19) -> 0 | AK19: =+AN19 -> 0
B20: Servicios Contratados | E20: =AJ20 -> 0 | G20: =+SER!H16 -> 0 | H20: =+AK20 -> 0 | J20: =+H20+AE20 -> 0 | K20: =+J20+E20 -> 0 | L20: =+SUM(O20:R20) -> 0 | N20: =+SER!O16 -> 0 | O20: =+SER!P16 -> 0 | P20: =+SER!Q16 -> 0 | Q20: =+SER!R16 -> 0 | R20: =+SER!S16 -> 0 | S20: =+SUMIFS(N20:R20,N$2:R$2,$S$5) -> 0 | U20: =+SUMIFS(N20:S20,N$2:S$2,$U$5) -> 0 | V20: =+SUMIFS(N20:S20,N$2:S$2,$V$5) -> 0 | W20: =+SUMIFS(N20:S20,N$2:S$2,$W$5) -> 0 | Y20: =+K20+L20 -> 0 | Z20: =+SER!Z16 -> 0 | AA20: =+SER!AA16 -> 0 | AB20: =+SER!AB16 -> 0 | AC20: 32000 | AI20: =SUM(AL20:AP20) -> 0 | AJ20: =SUM(AL20:AM20) -> 0 | AK20: =+AN20 -> 0
B21: Equipos y Vehículos | E21: =AJ21 -> 0 | G21: 0 | H21: =+AK21 -> 0 | J21: =+H21+AE21 -> 0 | K21: =+J21+E21 -> 0 | L21: =+SUM(O21:R21) -> 0 | S21: =+SUMIFS(N21:R21,N$2:R$2,$S$5) -> 0 | U21: =+SUMIFS(N21:S21,N$2:S$2,$U$5) -> 0 | V21: =+SUMIFS(N21:S21,N$2:S$2,$V$5) -> 0 | W21: =+SUMIFS(N21:S21,N$2:S$2,$W$5) -> 0 | Y21: =+K21+L21 -> 0 | Z21: 0 | AI21: =SUM(AL21:AP21) -> 0 | AJ21: =SUM(AL21:AM21) -> 0 | AK21: =+AN21 -> 0
C22: Propios | E22: =AJ22 -> 0 | G22: =+Eq!H17 -> 0 | H22: =+AK22 -> 0 | J22: =+H22+AE22 -> 0 | K22: =+J22+E22 -> 0 | L22: =+SUM(O22:R22) -> 0 | N22: =+Eq!O17 -> 0 | O22: =+Eq!P17 -> 0 | P22: =+Eq!Q17 -> 0 | Q22: =+Eq!R17 -> 0 | R22: =+Eq!S17 -> 0 | S22: =+SUMIFS(N22:R22,N$2:R$2,$S$5) -> 0 | U22: =+SUMIFS(N22:S22,N$2:S$2,$U$5) -> 0 | V22: =+SUMIFS(N22:S22,N$2:S$2,$V$5) -> 0 | W22: =+SUMIFS(N22:S22,N$2:S$2,$W$5) -> 0 | Y22: =+K22+L22 -> 0 | Z22: =+Eq!Z17 -> 0 | AA22: =+Eq!AA17 -> 0 | AB22: =+Eq!AB17 -> 0 | AC22: 6691.85 | AI22: =SUM(AL22:AP22) -> 0 | AJ22: =SUM(AL22:AM22) -> 0 | AK22: =+AN22 -> 0
C23: Terceros | E23: =AJ23 -> 0 | G23: =+Eq!H20 -> 0 | H23: =+AK23 -> 0 | J23: =+H23+AE23 -> 0 | K23: =+J23+E23 -> 0 | L23: =+SUM(O23:R23) -> 0 | N23: =+Eq!O20 -> 0 | O23: =+Eq!P20 -> 0 | P23: =+Eq!Q20 -> 0 | Q23: =+Eq!R20 -> 0 | R23: =+Eq!S20 -> 0 | S23: =+SUMIFS(N23:R23,N$2:R$2,$S$5) -> 0 | U23: =+SUMIFS(N23:S23,N$2:S$2,$U$5) -> 0 | V23: =+SUMIFS(N23:S23,N$2:S$2,$V$5) -> 0 | W23: =+SUMIFS(N23:S23,N$2:S$2,$W$5) -> 0 | Y23: =+K23+L23 -> 0 | Z23: =+Eq!Z20 -> 0 | AA23: =+Eq!AA20 -> 0 | AB23: =+Eq!AB20 -> 0 | AC23: 3188211.8 | AI23: =SUM(AL23:AP23) -> 0 | AJ23: =SUM(AL23:AM23) -> 0 | AK23: =+AN23 -> 0
B24: Fletes | E24: =AJ24 -> 0 | G24: =+Fletes!H15 -> 0 | H24: =+AK24 -> 0 | J24: =+H24+AE24 -> 0 | K24: =+J24+E24 -> 0 | L24: =+SUM(O24:R24) -> 0 | N24: =+Fletes!O15 -> 0 | O24: =+Fletes!P15 -> 0 | P24: =+Fletes!Q15 -> 0 | Q24: =+Fletes!R15 -> 0 | R24: =+Fletes!S15 -> 0 | S24: =+SUMIFS(N24:R24,N$2:R$2,$S$5) -> 0 | U24: =+SUMIFS(N24:S24,N$2:S$2,$U$5) -> 0 | V24: =+SUMIFS(N24:S24,N$2:S$2,$V$5) -> 0 | W24: =+SUMIFS(N24:S24,N$2:S$2,$W$5) -> 0 | Y24: =+K24+L24 -> 0 | Z24: =+Fletes!Z15 -> 0 | AA24: =+Fletes!AA39 -> 0 | AB24: =+Fletes!AB39 -> 0 | AC24: 263175 | AI24: =SUM(AL24:AP24) -> 0 | AJ24: =SUM(AL24:AM24) -> 0 | AK24: =+AN24 -> 0
B25: Staff (Sueldos) | E25: =AJ25 -> 0 | G25: 0 | H25: =+AK25 -> 0 | J25: =+H25+AE25 -> 0 | K25: =+J25+E25 -> 0 | L25: =+SUM(O25:R25) -> 0 | S25: =+SUMIFS(N25:R25,N$2:R$2,$S$5) -> 0 | U25: =+SUMIFS(N25:S25,N$2:S$2,$U$5) -> 0 | V25: =+SUMIFS(N25:S25,N$2:S$2,$V$5) -> 0 | W25: =+SUMIFS(N25:S25,N$2:S$2,$W$5) -> 0 | Y25: =+K25+L25 -> 0 | Z25: 0 | AB25: 0 | AC25: 0 | AI25: =SUM(AL25:AP25) -> 0 | AJ25: =SUM(AL25:AM25) -> 0 | AK25: =+AN25 -> 0
B26: Gastos Generales | E26: =AJ26 -> 0 | G26: 0 | H26: =+AK26 -> 0 | J26: =+H26+AE26 -> 0 | K26: =+J26+E26 -> 0 | L26: =+SUM(O26:R26) -> 0 | S26: =+SUMIFS(N26:R26,N$2:R$2,$S$5) -> 0 | U26: =+SUMIFS(N26:S26,N$2:S$2,$U$5) -> 0 | V26: =+SUMIFS(N26:S26,N$2:S$2,$V$5) -> 0 | W26: =+SUMIFS(N26:S26,N$2:S$2,$W$5) -> 0 | Y26: =+K26+L26 -> 0 | Z26: 0 | AA26: 0 | AB26: 0 | AC26: 0 | AI26: =SUM(AL26:AP26) -> 0 | AJ26: =SUM(AL26:AM26) -> 0 | AK26: =+AN26 -> 0
B28: Stock de Materiales | E28: =AJ28 -> 0 | H28: 0 | J28: =+H28+AE28 -> 0 | K28: =+J28+E28 -> 0 | L28: =+SUM(O28:R28) -> 0 | N28: =-H28/3 -> 0 | O28: =+N28 -> 0 | P28: =+O28 -> 0 | S28: =+SUMIFS(N28:R28,N$2:R$2,$S$5) -> 0 | U28: =+SUMIFS(N28:S28,N$2:S$2,$U$5) -> 0 | V28: =+SUMIFS(N28:S28,N$2:S$2,$V$5) -> 0 | W28: =+SUMIFS(N28:S28,N$2:S$2,$W$5) -> 0 | Y28: 0 | Z28: 0 | AA28: 0 | AC28: 0 | AI28: =SUM(AJ28:AP28) -> 0 | AJ28: 0
B30: Margen Ponderado S/. | E30: =+E9*E31 -> 0 | G30: =+G9*G31 -> 0 | H30: =+H9*H31 -> 0 | J30: =+J7*J31 -> 0 | K30: =+K7*K31 -> 0 | L30: =+L7*L31 -> 0 | N30: =+N7*N31 -> 0 | O30: =+O7*O31 -> 0 | P30: =+P7*P31 -> 0 | Q30: =+Q7*Q31 -> 0 | R30: =+R7*R31 -> 0 | S30: =+S7*S31 -> 0 | U30: =+U7*U31 -> 0 | V30: =+V7*V31 -> 0 | W30: =+W7*W31 -> 0 | Y30: =+Y7-Y15 -> 0 | Z30: =+Z7-Z15 -> 0 | AA30: =+AA7-AA15 -> 0 | AB30: =+AB7-AB15 -> 0 | AC30: =+AC7-AC15 -> -4572553.5 | AE30: =+AE9*AE31 -> 0
B31: Margen Ponderado % | E31: =+$Y$31 -> 0 | G31: =+$Y$31 -> 0 | H31: =+$Y$31 -> 0 | J31: =+$Y$31 -> 0 | K31: =+$Y$31 -> 0 | L31: =+$Y$31 -> 0 | N31: =+$Y$31 -> 0 | O31: =+$Y$31 -> 0 | P31: =+$Y$31 -> 0 | Q31: =+$Y$31 -> 0 | R31: =+$Y$31 -> 0 | S31: =+$Y$31 -> 0 | U31: =+$Y$31 -> 0 | V31: =+$Y$31 -> 0 | W31: =+$Y$31 -> 0 | Y31: =+IF(Y7=0,0,Y30/Y7) -> 0 | Z31: =+IF(Z7=0,0,Z30/Z7) -> 0 | AA31: =+IF(AA7=0,0,AA30/AA7) -> 0 | AB31: =+IF(AB7=0,0,AB30/AB7) -> 0 | AC31: =+IF(AC7=0,0,AC30/AC7) -> 0 | AE31: =+$Y$31 -> 0
B33: Margen Absoluto S/. | E33: =+E7-E15+E28 -> 0 | G33: =+G7-G15+G28 -> 0 | H33: =+H7-H15+H28 -> 0 | J33: =+J7-J15+J28 -> 0 | K33: =+K7-K15 -> 0 | L33: =+L7-L15 -> 0 | N33: =+N7-N15+N28 -> 0 | O33: =+O7-O15+O28 -> 0 | P33: =+P7-P15+P28 -> 0 | Q33: =+Q7-Q15+Q28 -> 0 | R33: =+R7-R15+R28 -> 0 | S33: =+S7-S15+S28 -> 0 | U33: =+U7-U15+U28 -> 0 | V33: =+V7-V15+V28 -> 0 | W33: =+W7-W15+W28 -> 0 | Y33: =+Y7-Y15+Y28 -> 0 | Z33: -2144335.5 | AA33: =+AA7-AA15+AA28 -> 0 | AB33: =+AB7-AB15+AB28 -> 0 | AC33: =+AC7-AC15+AC28 -> -4572553.5 | AE33: =+AE7-AE15+AE28 -> 0
B34: Margen Absoluto % | E34: =+IF(E7=0,0,E33/E7) -> 0 | G34: =+IF(G7=0,0,G33/G7) -> 0 | H34: =+IF(H7=0,0,H33/H7) -> 0 | J34: =+IF(J7=0,0,J33/J7) -> 0 | K34: =+IF(K7=0,0,K33/K7) -> 0 | L34: =+IF(L7=0,0,L33/L7) -> 0 | N34: =+IF(N7=0,0,N33/N7) -> 0 | O34: =+IF(O7=0,0,O33/O7) -> 0 | P34: =+IF(P7=0,0,P33/P7) -> 0 | Q34: =+IF(Q7=0,0,Q33/Q7) -> 0 | R34: =+IF(R7=0,0,R33/R7) -> 0 | S34: =+IF(S7=0,0,S33/S7) -> 0 | U34: =+IF(U7=0,0,U33/U7) -> 0 | V34: =+IF(V7=0,0,V33/V7) -> 0 | W34: =+IF(W7=0,0,W33/W7) -> 0 | Y34: =+IF(Y7=0,0,Y33/Y7) -> 0 | Z34: =+IF(Z7=0,0,Z33/Z7) -> 0 | AA34: =+IF(AA7=0,0,AA33/AA7) -> 0 | AB34: =+IF(AB7=0,0,AB33/AB7) -> 0 | AC34: =+IF(AC7=0,0,AC33/AC7) -> 0 | AE34: =+IF(AE7=0,0,AE33/AE7) -> 0
AC36: 0.15002593 | AE36: -98756.833
AC37: 1.3007553e-07 | AE37: -0.39313065
B38: COSTO APLICADO | K38: =+K7-K30 -> 0 | AS38: =H33 -> 0 | AT38: =Y33 -> 0
B40: RESULTADO PENDIENTE | K40: =K15-K38 -> 0
B42: ACTIVOS | K42: =IF('ER Pendiente'!B38>0,'ER Pendiente'!B15+'ER Pendiente'!B38,'ER Pendiente'!B15) -> 0
B44: PROVISIONES | K44: =IF('ER Pendiente'!B38<0,-'ER Pendiente'!B38-'ER Pendiente'!B22,-'ER Pendiente'!B22) -> 0
B46: DIFERENCIA DE MARGENES | K46: ='Dif. Margenes'!I11 -> 0
B48: CONTINGENCIA | K48: =+K40-K42+K44 -> 0
C50: Mayor Margen +
C52: Menor Margen -

Sheet F-200
B1: =CONCATENATE(B3," - ",B4," - ",B5," - ",B6) -> I.E.N 1182 - MES DE ENERO DEL 2025 - EL BOSQUE - CERCO + INGRESOS Y CASETAS - FASE 200 : MOVIMIENTOS DE TIERRAS
K2: =+K7/Y7 -> #DIV/0! | N2: =+YEAR(N5) -> 2024 | O2: =+YEAR(O5) -> 2024 | P2: =+YEAR(P5) -> 2024 | Q2: =+YEAR(Q5) -> 2024 | R2: =+YEAR(R5) -> 2024 | S2: =S5 -> 2024 | U2: 43466
B3: I.E.N 1182 | E3: ACUMULADO | G3: =+B4 -> MES DE ENERO DEL 2025 | J3: ACUMULADO DEL 2024 | K3: ACUMULADO DE OBRA | L3: SALDO DE OBRA | N3: PROYECCIÓN | U3: AÑOS SIGUIENTES | Y3: TOTAL DE OBRA | AE3: Acum. del Ej. | AI3: TOTAL | AJ3: AÑOS ANTERIORES | AK3: MES DEL INFORME | AL3: 45597 | AM3: 45627 | AN3: 45658 | AO3: 45689 | AP3: 45717
B4: MES DE ENERO DEL 2025 | N4: 1 | O4: =+N4+1 -> 2 | P4: =+O4+1 -> 3 | Q4: =+P4+1 -> 4 | R4: =+Q4+1 -> 5 | S4: Saldo del Ejercicio
B5: EL BOSQUE - CERCO + INGRESOS Y CASETAS | E5: Años Anteriores | G5: Previsto | H5: Real | N5: 45475 | O5: =+N5+31 -> 45506 | P5: =+O5+31 -> 45537 | Q5: =+P5+31 -> 45568 | R5: =+Q5+31 -> 45599 | S5: =+'DIRECTO '!S5 -> 2024 | U5: 2024 | V5: =+U5+1 -> 2025 | W5: =+V5+1 -> 2026 | Y5: Actual | Z5: Anterior | AA5: Meta | AB5: Presupuesto Interno | AC5: Original | AE5: Anterior
B6: FASE 200 : MOVIMIENTOS DE TIERRAS
B7: Venta Total Producida | E7: =+E9 -> 0 | G7: =+G9 -> 0 | H7: =+H9 -> 0 | J7: =+J9 -> 0 | K7: =+K9 -> 0 | L7: =+L9 -> 0 | N7: =+N9 -> 0 | O7: =+O9 -> 0 | P7: =+P9 -> 0 | Q7: =+Q9 -> 0 | R7: =+R9 -> 0 | S7: =+S9 -> 0 | U7: =+U9 -> 0 | V7: =+V9 -> 0 | W7: =+W9 -> 0 | Y7: =+Y9 -> 0 | Z7: =+Z9 -> 0 | AA7: =+AA9 -> 0 | AB7: =+AB9 -> 0 | AC7: =+AC9 -> 0 | AE7: =+AE9 -> 0 | AG7: =+AC7-Y7 -> 0
B9: Venta | E9: =+SUM(E11:E13) -> 0 | G9: =+SUM(G11:G13) -> 0 | H9: =+SUM(H11:H13) -> 0 | J9: =+SUM(J11:J13) -> 0 | K9: =+SUM(K11:K13) -> 0 | L9: =+SUM(L11:L12) -> 0 | N9: =+SUM(N11:N13) -> 0 | O9: =+SUM(O11:O13) -> 0 | P9: =+SUM(P11:P13) -> 0 | Q9: =+SUM(Q11:Q13) -> 0 | R9: =+SUM(R11:R13) -> 0 | S9: =+SUM(S11:S13) -> 0 | U9: =+SUM(U11:U13) -> 0 | V9: =+SUM(V11:V13) -> 0 | W9: =+SUM(W11:W13) -> 0 | Y9: =+SUM(Y11:Y13) -> 0 | Z9: =+SUM(Z11:Z13) -> 0 | AA9: =+SUM(AA11:AA13) -> 0 | AB9: =+SUM(AB11:AB13) -> 0 | AC9: =+SUM(AC11:AC13) -> 0 | AE9: =+SUM(AE11:AE13) -> 0 | AG9: =+AC9-Y9 -> 0
B11: Valorización: Venta Directa - Contrato Principal | E11: =+SUM(AL11:AP11) -> 0 | G11: 0 | H11: =+AK11 -> 0 | J11: =+H11+AE11 -> 0 | K11: =+E11+J11 -> 0 | L11: =+SUM(N11:R11) -> 0 | S11: =+SUMIFS(N11:R11,N$2:R$2,$S$5) -> 0 | U11: =+SUMIFS(N11:S11,N$2:S$2,$U$5) -> 0 | V11: =+SUMIFS(N11:S11,N$2:S$2,$V$5) -> 0 | W11: =+SUMIFS(N11:S11,N$2:S$2,$W$5) -> 0 | AG11: =+AC11-Y11 -> 0 | AI11: =SUM(AL11:AP11) -> 0 | AJ11: =SUM(AL11:AM11) -> 0 | AK11: =+AN11 -> 0
B12: Valorización: Venta Indirecta - Contrato Principal | E12: =+SUM(AL12:AP12) -> 0 | G12: 0 | H12: =+AK12 -> 0 | J12: =+H12+AE12 -> 0 | K12: =+E12+J12 -> 0 | L12: =+SUM(N12:R12) -> 0 | N12: 0 | O12: 0 | P12: 0 | Q12: 0 | R12: 0 | S12: =+SUMIFS(N12:R12,N$2:R$2,$S$5) -> 0 | U12: =+SUMIFS(N12:S12,N$2:S$2,$U$5) -> 0 | V12: =+SUMIFS(N12:S12,N$2:S$2,$V$5) -> 0 | W12: =+SUMIFS(N12:S12,N$2:S$2,$W$5) -> 0 | Y12: =+K12+L12 -> 0 | Z12: 0 | AG12: =+AC12-Y12 -> 0 | AI12: =SUM(AL12:AP12) -> 0 | AJ12: =SUM(AL12:AM12) -> 0 | AK12: =+AN12 -> 0
B13: Otros: | E13: =+SUM(AL13:AP13) -> 0 | L13: =+SUM(N13:R13) -> 0 | S13: =+SUMIFS(N13:R13,N$2:R$2,$S$5) -> 0 | U13: =+SUMIFS(N13:S13,N$2:S$2,$U$5) -> 0 | V13: =+SUMIFS(N13:S13,N$2:S$2,$V$5) -> 0 | W13: =+SUMIFS(N13:S13,N$2:S$2,$W$5) -> 0 | Y13: =+K13+L13 -> 0 | Z13: 0 | AG13: =+AC13-Y13 -> 0 | AI13: =SUM(AL13:AP13) -> 0 | AJ13: =SUM(AL13:AM13) -> 0 | AK13: =+AN13 -> 0
B15: Costo Total | E15: =+SUM(E17:E26)+E28 -> 0 | G15: =+SUM(G17:G26)+G28 -> 0 | H15: =+SUM(H17:H26)+H28 -> 0 | J15: =+SUM(J17:J26)+J28 -> 0 | K15: =+SUM(K17:K26)+K28 -> 0 | L15: =+SUM(L17:L26,L28) -> 0 | N15: =+SUM(N17:N26)+N28 -> 0 | O15: =+SUM(O17:O26)+O28 -> 0 | P15: =+SUM(P17:P26)+P28 -> 0 | Q15: =+SUM(Q17:Q26)+Q28 -> 0 | R15: =+SUM(R17:R26)+R28 -> 0 | S15: =+SUM(S17:S26)+S28 -> 0 | U15: =+SUM(U17:U26)+U28 -> 0 | V15: =+SUM(V17:V26)+V28 -> 0 | W15: =+SUM(W17:W26)+W28 -> 0 | Y15: =+SUM(Y17:Y26)+Y28 -> 0 | Z15: =+SUM(Z17:Z26)+Z28 -> 0 | AA15: =+SUM(AA17:AA26)+AA28 -> 0 | AB15: =+SUM(AB17:AB26)+AB28 -> 0 | AC15: =+SUM(AC17:AC26,AC28) -> 0 | AE15: =+SUM(AE17:AE26,AE28) -> 0 | AG15: =+AC15-Y15 -> 0
B17: Materiales | U17: =+SUMIFS(N17:S17,N$2:S$2,$U$5) -> 0 | V17: =+SUMIFS(N17:S17,N$2:S$2,$V$5) -> 0 | W17: =+SUMIFS(N17:S17,N$2:S$2,$W$5) -> 0 | AG17: =+AC17-Y17 -> 0 | AI17: =SUM(AL17:AP17) -> 0 | AJ17: =SUM(AL17:AM17) -> 0 | AK17: =+AN17 -> 0
B18: Mano de Obra | U18: =+SUMIFS(N18:S18,N$2:S$2,$U$5) -> 0 | V18: =+SUMIFS(N18:S18,N$2:S$2,$V$5) -> 0 | W18: =+SUMIFS(N18:S18,N$2:S$2,$W$5) -> 0 | AG18: =+AC18-Y18 -> 0 | AI18: =SUM(AL18:AP18) -> 0 | AJ18: =SUM(AL18:AM18) -> 0 | AK18: =+AN18 -> 0
B19: Subcontratos de obra | U19: =+SUMIFS(N19:S19,N$2:S$2,$U$5) -> 0 | V19: =+SUMIFS(N19:S19,N$2:S$2,$V$5) -> 0 | W19: =+SUMIFS(N19:S19,N$2:S$2,$W$5) -> 0 | AG19: =+AC19-Y19 -> 0 | AI19: =SUM(AL19:AP19) -> 0 | AJ19: =SUM(AL19:AM19) -> 0 | AK19: =+AN19 -> 0
B20: Servicios Contratados | U20: =+SUMIFS(N20:S20,N$2:S$2,$U$5) -> 0 | V20: =+SUMIFS(N20:S20,N$2:S$2,$V$5) -> 0 | W20: =+SUMIFS(N20:S20,N$2:S$2,$W$5) -> 0 | AG20: =+AC20-Y20 -> 0 | AI20: =SUM(AL20:AP20) -> 0 | AJ20: =SUM(AL20:AM20) -> 0 | AK20: =+AN20 -> 0
B21: Equipos y Vehículos | U21: =+SUMIFS(N21:S21,N$2:S$2,$U$5) -> 0 | V21: =+SUMIFS(N21:S21,N$2:S$2,$V$5) -> 0 | W21: =+SUMIFS(N21:S21,N$2:S$2,$W$5) -> 0 | AG21: =+AC21-Y21 -> 0 | AI21: =SUM(AL21:AP21) -> 0 | AJ21: =SUM(AL21:AM21) -> 0 | AK21: =+AN21 -> 0
C22: Propios | U22: =+SUMIFS(N22:S22,N$2:S$2,$U$5) -> 0 | V22: =+SUMIFS(N22:S22,N$2:S$2,$V$5) -> 0 | W22: =+SUMIFS(N22:S22,N$2:S$2,$W$5) -> 0 | AG22: =+AC22-Y22 -> 0 | AI22: =SUM(AL22:AP22) -> 0 | AJ22: =SUM(AL22:AM22) -> 0 | AK22: =+AN22 -> 0
C23: Terceros | U23: =+SUMIFS(N23:S23,N$2:S$2,$U$5) -> 0 | V23: =+SUMIFS(N23:S23,N$2:S$2,$V$5) -> 0 | W23: =+SUMIFS(N23:S23,N$2:S$2,$W$5) -> 0 | AG23: =+AC23-Y23 -> 0 | AI23: =SUM(AL23:AP23) -> 0 | AJ23: =SUM(AL23:AM23) -> 0 | AK23: =+AN23 -> 0
B24: Fletes | U24: =+SUMIFS(N24:S24,N$2:S$2,$U$5) -> 0 | V24: =+SUMIFS(N24:S24,N$2:S$2,$V$5) -> 0 | W24: =+SUMIFS(N24:S24,N$2:S$2,$W$5) -> 0 | AG24: =+AC24-Y24 -> 0 | AI24: =SUM(AL24:AP24) -> 0 | AJ24: =SUM(AL24:AM24) -> 0 | AK24: =+AN24 -> 0
B25: Staff (Sueldos) | U25: =+SUMIFS(N25:S25,N$2:S$2,$U$5) -> 0 | V25: =+SUMIFS(N25:S25,N$2:S$2,$V$5) -> 0 | W25: =+SUMIFS(N25:S25,N$2:S$2,$W$5) -> 0 | AG25: =+AC25-Y25 -> 0 | AI25: =SUM(AL25:AP25) -> 0 | AJ25: =SUM(AL25:AM25) -> 0 | AK25: =+AN25 -> 0
B26: Gastos Generales | U26: =+SUMIFS(N26:S26,N$2:S$2,$U$5) -> 0 | V26: =+SUMIFS(N26:S26,N$2:S$2,$V$5) -> 0 | W26: =+SUMIFS(N26:S26,N$2:S$2,$W$5) -> 0 | AG26: =+AC26-Y26 -> 0 | AI26: =SUM(AL26:AP26) -> 0 | AJ26: =SUM(AL26:AM26) -> 0 | AK26: =+AN26 -> 0
B28: Stock de Materiales | E28: =+SUM(AL28:AP28) -> 0 | G28: 0 | H28: 0 | J28: =+H28+AE28 -> 0 | K28: =+J28+E28 -> 0 | L28: =+SUM(N28:S28) -> 0 | N28: =-K28 -> 0 | S28: =+SUMIFS(N28:R28,N$2:R$2,$S$5) -> 0 | U28: =+SUMIFS(N28:S28,N$2:S$2,$U$5) -> 0 | V28: =+SUMIFS(N28:S28,N$2:S$2,$V$5) -> 0 | W28: =+SUMIFS(N28:S28,N$2:S$2,$W$5) -> 0 | Y28: 0 | Z28: 0 | AA28: 0 | AC28: 0
B30: Margen Ponderado S/. | E30: =+E7*E31 -> 0 | G30: =+G7*G31 -> 0 | H30: =+H7*H31 -> 0 | J30: =+J7*J31 -> 0 | K30: =+K7*K31 -> 0 | L30: =+L7*L31 -> 0 | N30: =+N7*N31 -> 0 | O30: =+O7*O31 -> 0 | P30: =+P7*P31 -> 0 | Q30: =+Q7*Q31 -> 0 | R30: =+R7*R31 -> 0 | S30: =+S7*S31 -> 0 | U30: =+U7*U31 -> 0 | V30: =+V7*V31 -> 0 | W30: =+W7*W31 -> 0 | Y30: =+Y7-Y15 -> 0 | Z30: =+Z7-Z15 -> 0 | AA30: =+AA7-AA15 -> 0 | AB30: =+AB7-AB15 -> 0 | AC30: =+AC7-AC15 -> 0 | AE30: =+AE7*AE31 -> 0 | AG30: =+Y30-AC30 -> 0
B31: Margen Ponderado % | E31: =+$Y$31 -> 0 | G31: =+$Y$31 -> 0 | H31: =+$Y$31 -> 0 | J31: =+$Y$31 -> 0 | K31: =+$Y$31 -> 0 | L31: =+$Y$31 -> 0 | N31: =+$Y$31 -> 0 | O31: =+$Y$31 -> 0 | P31: =+$Y$31 -> 0 | Q31: =+$Y$31 -> 0 | R31: =+$Y$31 -> 0 | S31: =+$Y$31 -> 0 | U31: =+$Y$31 -> 0 | V31: =+$Y$31 -> 0 | W31: =+$Y$31 -> 0 | Y31: =+IF(Y7=0,0,Y30/Y7) -> 0 | Z31: =+IF(Z7=0,0,Z30/Z7) -> 0 | AA31: =+IF(AA7=0,0,AA30/AA7) -> 0 | AB31: =+IF(AB7=0,0,AB30/AB7) -> 0 | AC31: =+IF(AC7=0,0,AC30/AC7) -> 0 | AE31: =+$Y$31 -> 0
B33: Margen Absoluto S/. | E33: =+E7-E15+E28 -> 0 | G33: =+G7-G15+G28 -> 0 | H33: =+H7-H15+H28 -> 0 | J33: =+J7-J15+J28 -> 0 | K33: =+K7-K15+K28 -> 0 | L33: =+L7-L15+L28 -> 0 | N33: =+N7-N15+N28 -> 0 | O33: =+O7-O15+O28 -> 0 | P33: =+P7-P15+P28 -> 0 | Q33: =+Q7-Q15+Q28 -> 0 | R33: =+R7-R15+R28 -> 0 | S33: =+S7-S15+S28 -> 0 | U33: =+U7-U15+U28 -> 0 | V33: =+V7-V15+V28 -> 0 | W33: =+W7-W15+W28 -> 0 | Y33: =+Y7-Y15+Y28 -> 0 | Z33: =+Z7-Z15+Z28 -> 0 | AA33: =+AA7-AA15+AA28 -> 0 | AB33: =+AB7-AB15+AB28 -> 0 | AC33: =+AC7-AC15+AC28 -> 0 | AE33: =+AE7-AE15+AE28 -> 0
B34: Margen Absoluto % | E34: =+IF(E7=0,0,E33/E7) -> 0 | G34: 0 | H34: =+IF(H7=0,0,H33/H7) -> 0 | J34: =+IF(J7=0,0,J33/J7) -> 0 | K34: =+IF(K7=0,0,K33/K7) -> 0 | L34: =+IF(L7=0,0,L33/L7) -> 0 | N34: =+IF(N7=0,0,N33/N7) -> 0 | O34: =+IF(O7=0,0,O33/O7) -> 0 | P34: =+IF(P7=0,0,P33/P7) -> 0 | Q34: =+IF(Q7=0,0,Q33/Q7) -> 0 | R34: =+IF(R7=0,0,R33/R7) -> 0 | S34: =+IF(S7=0,0,S33/S7) -> 0 | U34: =+IF(U7=0,0,U33/U7) -> 0 | V34: =+IF(V7=0,0,V33/V7) -> 0 | W34: =+IF(W7=0,0,W33/W7) -> 0 | Y34: =+IF(Y7=0,0,Y33/Y7) -> 0 | Z34: =+IF(Z7=0,0,Z33/Z7) -> 0 | AA34: =+IF(AA7=0,0,AA33/AA7) -> 0 | AB34: =+IF(AB7=0,0,AB33/AB7) -> 0 | AC34: =+IF(AC7=0,0,AC33/AC7) -> 0 | AE34: =+IF(AE7=0,0,AE33/AE7) -> 0
AC36: 0 | AE36: 0
B38: COSTO APLICADO | K38: =+K7-K30 -> 0
B40: RESULTADO PENDIENTE | K40: =K15-K38 -> 0 | AS40: =H33 -> 0 | AT40: =Y33 -> 0
B42: ACTIVOS | K42: =IF('ER Pendiente'!C38>0,'ER Pendiente'!C15+'ER Pendiente'!C38,'ER Pendiente'!C15) -> 0
B44: PROVISIONES | K44: =IF('ER Pendiente'!C38<0,-'ER Pendiente'!C38-'ER Pendiente'!C22,-'ER Pendiente'!C22) -> 0
B46: DIFERENCIA DE MARGENES | K46: =+'Dif. Margenes'!I12 -> 0
B48: CONTINGENCIA | K48: =+K40-K42+K44 -> 0
C50: Mayor Margen +
C52: Menor Margen -

Sheet F-300
B1: =CONCATENATE(B3," - ",B4," - ",B5," - ",B6) -> I.E.N 1182 - MES DE ENERO DEL 2025 - EL BOSQUE - CERCO + INGRESOS Y CASETAS - FASE 300: CONCRETO
N2: =+YEAR(N5) -> 2019 | O2: =+YEAR(O5) -> 2019 | P2: =+YEAR(P5) -> 2019 | Q2: =+YEAR(Q5) -> 2019 | R2: =+YEAR(R5) -> 2019 | S2: =S5 -> 2024 | U2: 43466
B3: I.E.N 1182 | E3: ACUMULADO | G3: =+B4 -> MES DE ENERO DEL 2025 | J3: ACUMULADO DEL 2024 | K3: ACUMULADO DE OBRA | L3: SALDO DE OBRA | N3: PROYECCIÓN | U3: AÑOS SIGUIENTES | Y3: TOTAL DE OBRA | AE3: Acum. del Ej. | AI3: TOTAL | AJ3: AÑOS ANTERIORES | AK3: MES DEL INFORME | AL3: 45597 | AM3: 45627 | AN3: 45658 | AO3: 45689 | AP3: 45717
B4: MES DE ENERO DEL 2025 | N4: 1 | O4: =+N4+1 -> 2 | P4: =+O4+1 -> 3 | Q4: =+P4+1 -> 4 | R4: =+Q4+1 -> 5 | S4: Saldo del Ejercicio
B5: EL BOSQUE - CERCO + INGRESOS Y CASETAS | E5: Años Anteriores | G5: Previsto | H5: Real | N5: 43648 | O5: =+N5+31 -> 43679 | P5: =+O5+31 -> 43710 | Q5: =+P5+31 -> 43741 | R5: =+Q5+31 -> 43772 | S5: =+'DIRECTO '!S5 -> 2024 | U5: 2024 | V5: =+U5+1 -> 2025 | W5: =+V5+1 -> 2026 | Y5: Actual | Z5: Anterior | AA5: Meta | AB5: Presupuesto Interno | AC5: Original | AE5: Anterior
B6: FASE 300: CONCRETO
B7: Venta Total Producida | E7: =+E9 -> 0 | G7: =+G9 -> 0 | H7: =+H9 -> 0 | J7: =+J9 -> 0 | K7: =+K9 -> 0 | L7: =+L9 -> 0 | N7: =+N9 -> 0 | O7: =+O9 -> 0 | P7: =+P9 -> 0 | Q7: =+Q9 -> 0 | R7: =+R9 -> 0 | S7: =+S9 -> 0 | U7: =+U9 -> 0 | V7: =+V9 -> 0 | W7: =+W9 -> 0 | Y7: =+Y9 -> 0 | Z7: 3283340.2 | AA7: =+AA9 -> 0 | AB7: =+AB9 -> 0 | AC7: =+AC9 -> 0 | AE7: =+AE9 -> 0 | AG7: =+AC7-Y7 -> 0 | AI7: =+AI9 -> 0 | AJ7: =+AJ9 -> 0 | AL7: =+AL9 -> 0 | AM7: =+AM9 -> 0 | AN7: =+AN9 -> 0 | AO7: =+AO9 -> 0 | AP7: =+AP9 -> 0
B9: Venta | E9: =+SUM(E11:E13) -> 0 | G9: =+SUM(G11:G13) -> 0 | H9: =+SUM(H11:H13) -> 0 | J9: =+SUM(J11:J13) -> 0 | K9: =+SUM(K11:K13) -> 0 | L9: =+SUM(L11:L12) -> 0 | N9: =+SUM(N11:N13) -> 0 | O9: =+SUM(O11:O13) -> 0 | P9: =+SUM(P11:P13) -> 0 | Q9: =+SUM(Q11:Q13) -> 0 | R9: =+SUM(R11:R13) -> 0 | S9: =+SUM(S11:S13) -> 0 | U9: =+SUM(U11:U13) -> 0 | V9: =+SUM(V11:V13) -> 0 | W9: =+SUM(W11:W13) -> 0 | Y9: =+SUM(Y11:Y13) -> 0 | Z9: 3283340.2 | AA9: =+SUM(AA11:AA13) -> 0 | AB9: =+SUM(AB11:AB13) -> 0 | AC9: =+SUM(AC11:AC13) -> 0 | AE9: =+SUM(AE11:AE13) -> 0 | AG9: =+AC9-Y9 -> 0 | AI9: =+SUM(AI11:AI13) -> 0 | AJ9: =+SUM(AJ11:AJ13) -> 0 | AL9: =+SUM(AL11:AL13) -> 0 | AM9: =+SUM(AM11:AM13) -> 0 | AN9: =+SUM(AN11:AN13) -> 0 | AO9: =+SUM(AO11:AO13) -> 0 | AP9: =+SUM(AP11:AP13) -> 0
B11: Valorización: Venta Directa - Contrato Principal | E11: =+SUM(AL11:AP11) -> 0 | G11: 0 | H11: =+AJ11 -> 0 | J11: =+H11+AE11 -> 0 | K11: =+E11+J11 -> 0 | S11: =+SUMIFS(N11:R11,N$2:R$2,$S$5) -> 0 | U11: =+SUMIFS(N11:S11,N$2:S$2,$U$5) -> 0 | V11: =+SUMIFS(N11:S11,N$2:S$2,$V$5) -> 0 | W11: =+SUMIFS(N11:S11,N$2:S$2,$W$5) -> 0 | AG11: =+AC11-Y11 -> 0 | AI11: =SUM(AL11:AP11) -> 0 | AJ11: =SUM(AL11:AM11) -> 0 | AK11: =+AN11 -> 0
B12: Valorización: Venta Indirecta - Contrato Principal | E12: =+SUM(AL12:AP12) -> 0 | G12: 0 | H12: =+AJ12 -> 0 | J12: =+H12+AE12 -> 0 | K12: =+E12+J12 -> 0 | N12: 0 | O12: 0 | P12: 0 | Q12: 0 | R12: 0 | S12: =+SUMIFS(N12:R12,N$2:R$2,$S$5) -> 0 | U12: =+SUMIFS(N12:S12,N$2:S$2,$U$5) -> 0 | V12: =+SUMIFS(N12:S12,N$2:S$2,$V$5) -> 0 | W12: =+SUMIFS(N12:S12,N$2:S$2,$W$5) -> 0 | AG12: =+AC12-Y12 -> 0 | AI12: =SUM(AL12:AP12) -> 0 | AJ12: =SUM(AL12:AM12) -> 0 | AK12: =+AN12 -> 0
B13: Otros: | E13: =+SUM(AL13:AP13) -> 0 | S13: =+SUMIFS(N13:R13,N$2:R$2,$S$5) -> 0 | U13: =+SUMIFS(N13:S13,N$2:S$2,$U$5) -> 0 | V13: =+SUMIFS(N13:S13,N$2:S$2,$V$5) -> 0 | W13: =+SUMIFS(N13:S13,N$2:S$2,$W$5) -> 0 | AG13: =+AC13-Y13 -> 0 | AI13: =SUM(AL13:AP13) -> 0 | AJ13: =SUM(AL13:AM13) -> 0 | AK13: =+AN13 -> 0
B15: Costo Total | E15: =+SUM(E17:E26)+E28 -> 0 | G15: =+SUM(G17:G26)+G28 -> 0 | H15: =+SUM(H17:H26)+H28 -> 0 | J15: =+SUM(J17:J26)+J28 -> 0 | K15: =+SUM(K17:K26)+K28 -> 0 | L15: =+SUM(L17:L26,L28) -> 0 | N15: =+SUM(N17:N26)+N28 -> 0 | O15: =+SUM(O17:O26)+O28 -> 0 | P15: =+SUM(P17:P26)+P28 -> 0 | Q15: =+SUM(Q17:Q26)+Q28 -> 0 | R15: =+SUM(R17:R26)+R28 -> 0 | S15: =+SUM(S17:S26)+S28 -> 0 | U15: =+SUM(U17:U26)+U28 -> 0 | V15: =+SUM(V17:V26)+V28 -> 0 | W15: =+SUM(W17:W26)+W28 -> 0 | Y15: =+SUM(Y17:Y26)+Y28 -> 0 | Z15: =+SUM(Z17:Z26)+Z28 -> 0 | AA15: =+SUM(AA17:AA26,AA28) -> 0 | AB15: =+SUM(AB17:AB26,AB28) -> 0 | AC15: =+SUM(AC17:AC26,AC28) -> 0 | AE15: =+SUM(AE17:AE26,AE28) -> 0 | AG15: =+AC15-Y15 -> 0 | AI15: =+SUM(AI17:AI26,AI28) -> 0 | AJ15: =+SUM(AJ17:AJ26,AJ28) -> 0 | AL15: =+SUM(AL17:AL26,AL28) -> 0 | AM15: =+SUM(AM17:AM26,AM28) -> 0 | AN15: =+SUM(AN17:AN26,AN28) -> 0 | AO15: =+SUM(AO17:AO26,AO28) -> 0 | AP15: =+SUM(AP17:AP26,AP28) -> 0
B17: Materiales | E17: =+SUM(AL17:AP17) -> 0 | H17: =+AJ17 -> 0 | J17: =+H17+AE17 -> 0 | K17: =+E17+J17 -> 0 | L17: =+SUM(N17:R17) -> 0 | S17: =+SUMIFS(N17:R17,N$2:R$2,$S$5) -> 0 | U17: =+SUMIFS(N17:S17,N$2:S$2,$U$5) -> 0 | V17: =+SUMIFS(N17:S17,N$2:S$2,$V$5) -> 0 | W17: =+SUMIFS(N17:S17,N$2:S$2,$W$5) -> 0 | AG17: =+AC17-Y17 -> 0 | AI17: =SUM(AL17:AP17) -> 0 | AJ17: =SUM(AL17:AM17) -> 0 | AK17: =+AN17 -> 0
B18: Mano de Obra | E18: =+SUM(AL18:AP18) -> 0 | H18: =+AJ18 -> 0 | J18: =+H18+AE18 -> 0 | K18: =+J18+E18 -> 0 | L18: =+SUM(N18:R18) -> 0 | S18: =+SUMIFS(N18:R18,N$2:R$2,$S$5) -> 0 | U18: =+SUMIFS(N18:S18,N$2:S$2,$U$5) -> 0 | V18: =+SUMIFS(N18:S18,N$2:S$2,$V$5) -> 0 | W18: =+SUMIFS(N18:S18,N$2:S$2,$W$5) -> 0 | AG18: =+AC18-Y18 -> 0 | AI18: =SUM(AL18:AP18) -> 0 | AJ18: =SUM(AL18:AM18) -> 0 | AK18: =+AN18 -> 0
B19: Subcontratos de obra | E19: =+SUM(AL19:AP19) -> 0 | H19: =+AJ19 -> 0 | J19: =+H19+AE19 -> 0 | K19: =+J19+E19 -> 0 | L19: =+SUM(N19:R19) -> 0 | S19: =+SUMIFS(N19:R19,N$2:R$2,$S$5) -> 0 | U19: =+SUMIFS(N19:S19,N$2:S$2,$U$5) -> 0 | V19: =+SUMIFS(N19:S19,N$2:S$2,$V$5) -> 0 | W19: =+SUMIFS(N19:S19,N$2:S$2,$W$5) -> 0 | AG19: =+AC19-Y19 -> 0 | AI19: =SUM(AL19:AP19) -> 0 | AJ19: =SUM(AL19:AM19) -> 0 | AK19: =+AN19 -> 0
A20: 30 | B20: Servicios Contratados | E20: =+SUM(AL20:AP20) -> 0 | H20: =+AJ20 -> 0 | J20: =+H20+AE20 -> 0 | K20: =+J20+E20 -> 0 | L20: =+SUM(N20:R20) -> 0 | S20: =+SUMIFS(N20:R20,N$2:R$2,$S$5) -> 0 | U20: =+SUMIFS(N20:S20,N$2:S$2,$U$5) -> 0 | V20: =+SUMIFS(N20:S20,N$2:S$2,$V$5) -> 0 | W20: =+SUMIFS(N20:S20,N$2:S$2,$W$5) -> 0 | AG20: =+AC20-Y20 -> 0 | AI20: =SUM(AL20:AP20) -> 0 | AJ20: =SUM(AL20:AM20) -> 0 | AK20: =+AN20 -> 0
B21: Equipos y Vehículos | E21: =+SUM(AL21:AP21) -> 0 | H21: =+AJ21 -> 0 | J21: =+H21+AE21 -> 0 | K21: =+J21+E21 -> 0 | L21: =+SUM(N21:R21) -> 0 | S21: =+SUMIFS(N21:R21,N$2:R$2,$S$5) -> 0 | U21: =+SUMIFS(N21:S21,N$2:S$2,$U$5) -> 0 | V21: =+SUMIFS(N21:S21,N$2:S$2,$V$5) -> 0 | W21: =+SUMIFS(N21:S21,N$2:S$2,$W$5) -> 0 | AG21: =+AC21-Y21 -> 0 | AI21: =SUM(AL21:AP21) -> 0 | AJ21: =SUM(AL21:AM21) -> 0 | AK21: =+AN21 -> 0
C22: Propios | E22: =+SUM(AL22:AP22) -> 0 | H22: =+AJ22 -> 0 | J22: =+H22+AE22 -> 0 | K22: =+J22+E22 -> 0 | L22: =+SUM(N22:R22) -> 0 | S22: =+SUMIFS(N22:R22,N$2:R$2,$S$5) -> 0 | U22: =+SUMIFS(N22:S22,N$2:S$2,$U$5) -> 0 | V22: =+SUMIFS(N22:S22,N$2:S$2,$V$5) -> 0 | W22: =+SUMIFS(N22:S22,N$2:S$2,$W$5) -> 0 | AG22: =+AC22-Y22 -> 0 | AI22: =SUM(AL22:AP22) -> 0 | AJ22: =SUM(AL22:AM22) -> 0 | AK22: =+AN22 -> 0
C23: Terceros | E23: =+SUM(AL23:AP23) -> 0 | H23: =+AJ23 -> 0 | J23: =+H23+AE23 -> 0 | K23: =+J23+E23 -> 0 | L23: =+SUM(N23:R23) -> 0 | S23: =+SUMIFS(N23:R23,N$2:R$2,$S$5) -> 0 | U23: =+SUMIFS(N23:S23,N$2:S$2,$U$5) -> 0 | V23: =+SUMIFS(N23:S23,N$2:S$2,$V$5) -> 0 | W23: =+SUMIFS(N23:S23,N$2:S$2,$W$5) -> 0 | AG23: =+AC23-Y23 -> 0 | AI23: =SUM(AL23:AP23) -> 0 | AJ23: =SUM(AL23:AM23) -> 0 | AK23: =+AN23 -> 0
B24: Fletes | E24: =+SUM(AL24:AP24) -> 0 | H24: =+AJ24 -> 0 | J24: =+H24+AE24 -> 0 | K24: =+J24+E24 -> 0 | L24: =+SUM(N24:R24) -> 0 | S24: =+SUMIFS(N24:R24,N$2:R$2,$S$5) -> 0 | U24: =+SUMIFS(N24:S24,N$2:S$2,$U$5) -> 0 | V24: =+SUMIFS(N24:S24,N$2:S$2,$V$5) -> 0 | W24: =+SUMIFS(N24:S24,N$2:S$2,$W$5) -> 0 | AG24: =+AC24-Y24 -> 0 | AI24: =SUM(AL24:AP24) -> 0 | AJ24: =SUM(AL24:AM24) -> 0 | AK24: =+AN24 -> 0
B25: Staff (Sueldos) | E25: =+SUM(AL25:AP25) -> 0 | H25: =+AJ25 -> 0 | J25: =+H25+AE25 -> 0 | K25: =+J25+E25 -> 0 | L25: =+SUM(N25:R25) -> 0 | S25: =+SUMIFS(N25:R25,N$2:R$2,$S$5) -> 0 | U25: =+SUMIFS(N25:S25,N$2:S$2,$U$5) -> 0 | V25: =+SUMIFS(N25:S25,N$2:S$2,$V$5) -> 0 | W25: =+SUMIFS(N25:S25,N$2:S$2,$W$5) -> 0 | AG25: =+AC25-Y25 -> 0 | AI25: =SUM(AL25:AP25) -> 0 | AJ25: =SUM(AL25:AM25) -> 0 | AK25: =+AN25 -> 0
B26: Gastos Generales | E26: =+SUM(AL26:AP26) -> 0 | H26: =+AJ26 -> 0 | J26: =+H26+AE26 -> 0 | K26: =+J26+E26 -> 0 | L26: =+SUM(N26:R26) -> 0 | S26: =+SUMIFS(N26:R26,N$2:R$2,$S$5) -> 0 | U26: =+SUMIFS(N26:S26,N$2:S$2,$U$5) -> 0 | V26: =+SUMIFS(N26:S26,N$2:S$2,$V$5) -> 0 | W26: =+SUMIFS(N26:S26,N$2:S$2,$W$5) -> 0 | Y26: =+K26+L26 -> 0 | Z26: 0 | AA26: 0 | AC26: 0 | AG26: =+AC26-Y26 -> 0 | AI26: =SUM(AL26:AP26) -> 0 | AJ26: =SUM(AL26:AM26) -> 0 | AK26: =+AN26 -> 0
B28: Stock de Materiales | E28: =+SUM(AL28:AP28) -> 0 | G28: 0 | H28: 0 | J28: =+H28+AE28 -> 0 | K28: =+E28+J28 -> 0 | L28: =+SUM(N28:S28) -> 0 | N28: =-K28 -> 0 | O28: 0 | P28: 0 | Q28: 0 | R28: 0 | S28: =+SUMIFS(N28:R28,N$2:R$2,$S$5) -> 0 | U28: =+SUMIFS(N28:S28,N$2:S$2,$U$5) -> 0 | V28: =+SUMIFS(N28:S28,N$2:S$2,$V$5) -> 0 | W28: =+SUMIFS(N28:S28,N$2:S$2,$W$5) -> 0 | Y28: 0 | Z28: 0 | AA28: 0 | AC28: 0 | AI28: =SUM(AJ28:AP28) -> 0
B30: Margen Ponderado S/. | E30: =+E7*E31 -> 0 | G30: 0 | H30: =+H7*H31 -> 0 | J30: =+J7*J31 -> 0 | K30: =+K7*K31 -> 0 | L30: =+L7*L31 -> 0 | N30: =+N7*N31 -> 0 | O30: =+O7*O31 -> 0 | P30: =+P7*P31 -> 0 | Q30: =+Q7*Q31 -> 0 | R30: =+R7*R31 -> 0 | S30: =+S7*S31 -> 0 | U30: =+U7*U31 -> 0 | V30: =+V7*V31 -> 0 | W30: =+W7*W31 -> 0 | Y30: =+Y7-Y15 -> 0 | Z30: =+Z7-Z15 -> 3283340.2 | AA30: =+AA7-AA15 -> 0 | AB30: =+AB7-AB15 -> 0 | AC30: =+AC7-AC15 -> 0 | AE30: =+AE7*AE31 -> 0 | AG30: =+Y30-AC30 -> 0
B31: Margen Ponderado % | E31: =+$Y$31 -> 0 | G31: =+$Y$31 -> 0 | H31: =+$Y$31 -> 0 | J31: =+$Y$31 -> 0 | K31: =+$Y$31 -> 0 | L31: =+$Y$31 -> 0 | N31: =+$Y$31 -> 0 | O31: =+$Y$31 -> 0 | P31: =+$Y$31 -> 0 | Q31: =+$Y$31 -> 0 | R31: =+$Y$31 -> 0 | S31: =+$Y$31 -> 0 | U31: =+$Y$31 -> 0 | V31: =+$Y$31 -> 0 | W31: =+$Y$31 -> 0 | Y31: =+IF(Y7=0,0,Y30/Y7) -> 0 | Z31: =+IF(Z7=0,0,Z30/Z7) -> 1 | AA31: =+IF(AA7=0,0,AA30/AA7) -> 0 | AB31: =+IF(AB7=0,0,AB30/AB7) -> 0 | AC31: =+IF(AC7=0,0,AC30/AC7) -> 0 | AE31: =+$Y$31 -> 0
B33: Margen Absoluto S/. | E33: =+E7-E15+E28 -> 0 | G33: =+G7-G15+G28 -> 0 | H33: =+H7-H15+H28 -> 0 | J33: =+J7-J15+J28 -> 0 | K33: =+K7-K15+K28 -> 0 | L33: =+L7-L15+L28 -> 0 | N33: =+N7-N15+N28 -> 0 | O33: =+O7-O15+O28 -> 0 | P33: =+P7-P15+P28 -> 0 | Q33: =+Q7-Q15+Q28 -> 0 | R33: =+R7-R15+R28 -> 0 | S33: =+S7-S15+S28 -> 0 | U33: =+U7-U15+U28 -> 0 | V33: =+V7-V15+V28 -> 0 | W33: =+W7-W15+W28 -> 0 | Y33: =+Y7-Y15+Y28 -> 0 | Z33: =+Z7-Z15+Z28 -> 3283340.2 | AA33: =+AA7-AA15+AA28 -> 0 | AB33: =+AB7-AB15+AB28 -> 0 | AC33: =+AC7-AC15+AC28 -> 0 | AE33: =+AE7-AE15+AE28 -> 0
B34: Margen Absoluto % | E34: =+IF(E7=0,0,E33/E7) -> 0 | G34: =+IF(G7=0,0,G33/G7) -> 0 | H34: =+IF(H7=0,0,H33/H7) -> 0 | J34: =+IF(J7=0,0,J33/J7) -> 0 | K34: =+IF(K7=0,0,K33/K7) -> 0 | L34: =+IF(L7=0,0,L33/L7) -> 0 | N34: =+IF(N7=0,0,N33/N7) -> 0 | O34: =+IF(O7=0,0,O33/O7) -> 0 | P34: =+IF(P7=0,0,P33/P7) -> 0 | Q34: =+IF(Q7=0,0,Q33/Q7) -> 0 | R34: =+IF(R7=0,0,R33/R7) -> 0 | S34: =+IF(S7=0,0,S33/S7) -> 0 | U34: =+IF(U7=0,0,U33/U7) -> 0 | V34: =+IF(V7=0,0,V33/V7) -> 0 | W34: =+IF(W7=0,0,W33/W7) -> 0 | Y34: =+IF(Y7=0,0,Y33/Y7) -> 0 | Z34: =+IF(Z7=0,0,Z33/Z7) -> 1 | AA34: =+IF(AA7=0,0,AA33/AA7) -> 0 | AB34: =+IF(AB7=0,0,AB33/AB7) -> 0 | AC34: =+IF(AC7=0,0,AC33/AC7) -> 0 | AE34: =+IF(AE7=0,0,AE33/AE7) -> 0
Y36: 113237.67 | Z36: 113237.67 | AC36: -6.9849193e-10 | AE36: -1540.7039
B38: COSTO APLICADO | K38: =+K7-K30 -> 0 | AS38: =H33 -> 0 | AT38: =Y33 -> 0
B40: RESULTADO PENDIENTE | K40: =K15-K38 -> 0
B42: ACTIVOS | K42: =IF('ER Pendiente'!D38>0,'ER Pendiente'!D15+'ER Pendiente'!D38,'ER Pendiente'!D15) -> 0
B44: PROVISIONES | K44: =IF('ER Pendiente'!D38<0,-'ER Pendiente'!D38-'ER Pendiente'!D22,-'ER Pendiente'!D22) -> 0
B46: DIFERENCIA DE MARGENES | K46: =+'Dif. Margenes'!I13 -> 0
B48: CONTINGENCIA | K48: =+K40-K42+K44 -> 0
C50: Mayor Margen +
C52: Menor Margen -

Sheet F-400
B1: =CONCATENATE(B3," - ",B4," - ",B5," - ",B6) -> I.E.N 1182 - MES DE ENERO DEL 2025 - EL BOSQUE - CERCO + INGRESOS Y CASETAS - FASE 400: ENCOFRADO
K2: =+K7/Y7 -> #DIV/0! | N2: =+YEAR(N5) -> 2019 | O2: =+YEAR(O5) -> 2019 | P2: =+YEAR(P5) -> 2019 | Q2: =+YEAR(Q5) -> 2019 | R2: =+YEAR(R5) -> 2019 | S2: =S5 -> 2024 | U2: 43466
B3: I.E.N 1182 | E3: ACUMULADO | G3: =+B4 -> MES DE ENERO DEL 2025 | J3: ACUMULADO DEL 2024 | K3: ACUMULADO DE OBRA | L3: SALDO DE OBRA | N3: PROYECCIÓN | U3: AÑOS SIGUIENTES | Y3: TOTAL DE OBRA | AE3: Acum. del Ej. | AI3: TOTAL | AJ3: AÑOS ANTERIORES | AK3: MES DEL INFORME | AL3: 45597 | AM3: 45627 | AN3: 45658 | AO3: 45689 | AP3: 45717
B4: MES DE ENERO DEL 2025 | N4: 1 | O4: =+N4+1 -> 2 | P4: =+O4+1 -> 3 | Q4: =+P4+1 -> 4 | R4: =+Q4+1 -> 5 | S4: Saldo del Ejercicio
B5: EL BOSQUE - CERCO + INGRESOS Y CASETAS | E5: Años Anteriores | G5: Previsto | H5: Real | N5: 43648 | O5: =+N5+31 -> 43679 | P5: =+O5+31 -> 43710 | Q5: =+P5+31 -> 43741 | R5: =+Q5+31 -> 43772 | S5: =+'DIRECTO '!S5 -> 2024 | U5: 2024 | V5: =+U5+1 -> 2025 | W5: =+V5+1 -> 2026 | Y5: Actual | Z5: Anterior | AA5: Meta | AB5: Presupuesto Interno | AC5: Original | AE5: Anterior
B6: FASE 400: ENCOFRADO
B7: Venta Total Producida | E7: =+E9 -> 0 | G7: =+G9 -> 5240945.6 | H7: =+H9 -> 0 | J7: =+J9 -> 0 | K7: =+K9 -> 0 | L7: =+L9 -> 0 | N7: =+N9 -> 0 | O7: =+O9 -> 0 | P7: =+P9 -> 0 | Q7: =+Q9 -> 0 | R7: =+R9 -> 0 | S7: =+S9 -> 0 | U7: =+U9 -> 0 | V7: =+V9 -> 0 | W7: =+W9 -> 0 | Y7: =+Y9 -> 0 | Z7: =+Z9 -> 46197192 | AA7: =+AA9 -> 0 | AB7: =+AB9 -> 0 | AC7: =+AC9 -> 46197192 | AE7: =+AE9 -> 0 | AG7: =+AC7-Y7 -> 46197192 | AI7: =+AI9 -> 0 | AJ7: =+AJ9 -> 0 | AL7: =+AL9 -> 0 | AM7: =+AM9 -> 0 | AN7: =+AN9 -> 0 | AO7: =+AO9 -> 0 | AP7: =+AP9 -> 0
B9: Venta | E9: =+SUM(E11:E13) -> 0 | G9: =+SUM(G11:G13) -> 5240945.6 | H9: =+SUM(H11:H13) -> 0 | J9: =+SUM(J11:J13) -> 0 | K9: =+SUM(K11:K13) -> 0 | L9: =+SUM(L11:L12) -> 0 | N9: =+SUM(N11:N13) -> 0 | O9: =+SUM(O11:O13) -> 0 | P9: =+SUM(P11:P13) -> 0 | Q9: =+SUM(Q11:Q13) -> 0 | R9: =+SUM(R11:R13) -> 0 | S9: =+SUM(S11:S13) -> 0 | U9: =+SUM(U11:U13) -> 0 | V9: =+SUM(V11:V13) -> 0 | W9: =+SUM(W11:W13) -> 0 | Y9: =+SUM(Y11:Y13) -> 0 | Z9: =+SUM(Z11:Z13) -> 46197192 | AA9: =+SUM(AA11:AA13) -> 0 | AB9: =+SUM(AB11:AB13) -> 0 | AC9: =+SUM(AC11:AC13) -> 46197192 | AE9: =+SUM(AE11:AE13) -> 0 | AG9: =+AC9-Y9 -> 46197192 | AI9: =+SUM(AI11:AI13) -> 0 | AJ9: =+SUM(AJ11:AJ13) -> 0 | AL9: =+SUM(AL11:AL13) -> 0 | AM9: =+SUM(AM11:AM13) -> 0 | AN9: =+SUM(AN11:AN13) -> 0 | AO9: =+SUM(AO11:AO13) -> 0 | AP9: =+SUM(AP11:AP13) -> 0
B11: Valorización: Venta Directa - Contrato Principal | E11: =+SUM(AL11:AP11) -> 0 | G11: 5240945.6 | H11: =AJ11 -> 0 | J11: =+H11+AE11 -> 0 | K11: =+E11+J11 -> 0 | N11: 0 | O11: 0 | P11: 0 | Q11: 0 | S11: =+SUMIFS(N11:R11,N$2:R$2,$S$5) -> 0 | U11: =+SUMIFS(N11:S11,N$2:S$2,$U$5) -> 0 | V11: =+SUMIFS(N11:S11,N$2:S$2,$V$5) -> 0 | W11: =+SUMIFS(N11:S11,N$2:S$2,$W$5) -> 0 | Z11: 46197192 | AA11: 0 | AB11: 0 | AC11: 46197192 | AG11: =+AC11-Y11 -> 46197192 | AI11: =SUM(AL11:AP11) -> 0 | AJ11: =SUM(AL11:AM11) -> 0 | AK11: =+AN11 -> 0
B12: Valorización: Venta Indirecta - Contrato Principal | E12: =+SUM(AL12:AP12) -> 0 | G12: 0 | H12: =AJ12 -> 0 | J12: =+H12+AE12 -> 0 | K12: =+E12+J12 -> 0 | L12: =+SUM(N12:R12) -> 0 | N12: 0 | O12: 0 | P12: 0 | Q12: 0 | R12: 0 | S12: =+SUMIFS(N12:R12,N$2:R$2,$S$5) -> 0 | U12: =+SUMIFS(N12:S12,N$2:S$2,$U$5) -> 0 | V12: =+SUMIFS(N12:S12,N$2:S$2,$V$5) -> 0 | W12: =+SUMIFS(N12:S12,N$2:S$2,$W$5) -> 0 | Y12: =+K12+L12 -> 0 | Z12: 0 | AA12: 0 | AC12: 0 | AG12: =+AC12-Y12 -> 0 | AI12: =SUM(AL12:AP12) -> 0 | AJ12: =SUM(AL12:AM12) -> 0 | AK12: =+AN12 -> 0
B13: Otros: | E13: =+SUM(AL13:AP13) -> 0 | H13: =AJ13 -> 0 | J13: =+H13+AE13 -> 0 | K13: =+E13+J13 -> 0 | L13: =+SUM(N13:R13) -> 0 | S13: =+SUMIFS(N13:R13,N$2:R$2,$S$5) -> 0 | U13: =+SUMIFS(N13:S13,N$2:S$2,$U$5) -> 0 | V13: =+SUMIFS(N13:S13,N$2:S$2,$V$5) -> 0 | W13: =+SUMIFS(N13:S13,N$2:S$2,$W$5) -> 0 | Y13: =+K13+L13 -> 0 | Z13: 0 | AG13: =+AC13-Y13 -> 0 | AI13: =SUM(AL13:AP13) -> 0 | AJ13: =SUM(AL13:AM13) -> 0 | AK13: =+AN13 -> 0
B15: Costo Total | E15: =+SUM(E17:E26)+E28 -> 0 | G15: =+SUM(G17:G26)+G28 -> 0 | H15: =+SUM(H17:H26)+H28 -> 0 | J15: =+SUM(J17:J26)+J28 -> 0 | K15: =+SUM(K17:K26)+K28 -> 0 | L15: =+SUM(L17:L26,L28) -> 0 | N15: =+SUM(N17:N26)+N28 -> 0 | O15: =+SUM(O17:O26)+O28 -> 0 | P15: =+SUM(P17:P26)+P28 -> 0 | Q15: =+SUM(Q17:Q26)+Q28 -> 0 | R15: =+SUM(R17:R26)+R28 -> 0 | S15: =+SUM(S17:S26)+S28 -> 0 | U15: =+SUM(U17:U26)+U28 -> 0 | V15: =+SUM(V17:V26)+V28 -> 0 | W15: =+SUM(W17:W26)+W28 -> 0 | Y15: =+SUM(Y17:Y26)+Y28 -> 0 | Z15: =+SUM(Z17:Z26)+Z28 -> #REF! | AA15: =+SUM(AA17:AA26,AA28) -> #REF! | AB15: =+SUM(AB17:AB26,AB28) -> #REF! | AC15: =+SUM(AC17:AC26,AC28) -> 46197192 | AE15: =+SUM(AE17:AE26,AE28) -> 0 | AG15: =+AC15-Y15 -> 46197192 | AI15: =+SUM(AI17:AI26,AI28) -> 0 | AJ15: =+SUM(AJ17:AJ26,AJ28) -> 0 | AL15: =+SUM(AL17:AL26,AL28) -> 0 | AM15: =+SUM(AM17:AM26,AM28) -> 0 | AN15: =+SUM(AN17:AN26,AN28) -> 0 | AO15: =+SUM(AO17:AO26,AO28) -> 0 | AP15: =+SUM(AP17:AP26,AP28) -> 0
B17: Materiales | E17: =+SUM(AL17:AP17) -> 0 | H17: =AJ17 -> 0 | J17: =+H17+AE17 -> 0 | K17: =+E17+J17 -> 0 | L17: =+SUM(N17:R17) -> 0 | S17: =+SUMIFS(N17:R17,N$2:R$2,$S$5) -> 0 | U17: =+SUMIFS(N17:S17,N$2:S$2,$U$5) -> 0 | V17: =+SUMIFS(N17:S17,N$2:S$2,$V$5) -> 0 | W17: =+SUMIFS(N17:S17,N$2:S$2,$W$5) -> 0 | Y17: =+K17+L17 -> 0 | Z17: =+Mat!#REF! -> #REF! | AA17: =+Mat!#REF! -> #REF! | AB17: =+Mat!#REF! -> #REF! | AC17: 32677216 | AG17: =+AC17-Y17 -> 32677216 | AI17: =SUM(AL17:AP17) -> 0 | AJ17: =SUM(AL17:AM17) -> 0 | AK17: =+AN17 -> 0
B18: Mano de Obra | E18: =+SUM(AL18:AP18) -> 0 | H18: =AJ18 -> 0 | J18: =+H18+AE18 -> 0 | K18: =+J18+E18 -> 0 | L18: =+SUM(N18:R18) -> 0 | S18: =+SUMIFS(N18:R18,N$2:R$2,$S$5) -> 0 | U18: =+SUMIFS(N18:S18,N$2:S$2,$U$5) -> 0 | V18: =+SUMIFS(N18:S18,N$2:S$2,$V$5) -> 0 | W18: =+SUMIFS(N18:S18,N$2:S$2,$W$5) -> 0 | Y18: =+K18+L18 -> 0 | Z18: =+MO!Z57 -> 0 | AA18: =+MO!AA57 -> 0 | AB18: =+MO!AB57 -> 0 | AC18: 11496338 | AG18: =+AC18-Y18 -> 11496338 | AI18: =SUM(AL18:AP18) -> 0 | AJ18: =SUM(AL18:AM18) -> 0 | AK18: =+AN18 -> 0
B19: Subcontratos de obra | E19: =+SUM(AL19:AP19) -> 0 | H19: =AJ19 -> 0 | J19: =+H19+AE19 -> 0 | K19: =+J19+E19 -> 0 | L19: =+SUM(N19:R19) -> 0 | S19: =+SUMIFS(N19:R19,N$2:R$2,$S$5) -> 0 | U19: =+SUMIFS(N19:S19,N$2:S$2,$U$5) -> 0 | V19: =+SUMIFS(N19:S19,N$2:S$2,$V$5) -> 0 | W19: =+SUMIFS(N19:S19,N$2:S$2,$W$5) -> 0 | Y19: =+K19+L19 -> 0 | Z19: =+SC!Z39 -> 0 | AA19: =+SC!AA39 -> 0 | AB19: =+SC!AB39 -> 0 | AC19: 0 | AG19: =+AC19-Y19 -> 0 | AI19: =SUM(AL19:AP19) -> 0 | AJ19: =SUM(AL19:AM19) -> 0 | AK19: =+AN19 -> 0
B20: Servicios Contratados | E20: =+SUM(AL20:AP20) -> 0 | H20: =AJ20 -> 0 | J20: =+H20+AE20 -> 0 | K20: =+J20+E20 -> 0 | L20: =+SUM(N20:R20) -> 0 | S20: =+SUMIFS(N20:R20,N$2:R$2,$S$5) -> 0 | U20: =+SUMIFS(N20:S20,N$2:S$2,$U$5) -> 0 | V20: =+SUMIFS(N20:S20,N$2:S$2,$V$5) -> 0 | W20: =+SUMIFS(N20:S20,N$2:S$2,$W$5) -> 0 | Y20: =+K20+L20 -> 0 | Z20: =+SER!Z35 -> 0 | AG20: =+AC20-Y20 -> 0 | AI20: =SUM(AL20:AP20) -> 0 | AJ20: =SUM(AL20:AM20) -> 0 | AK20: =+AN20 -> 0
B21: Equipos y Vehículos | E21: =+SUM(AL21:AP21) -> 0 | H21: =AJ21 -> 0 | J21: =+H21+AE21 -> 0 | K21: =+J21+E21 -> 0 | L21: =+SUM(N21:R21) -> 0 | S21: =+SUMIFS(N21:R21,N$2:R$2,$S$5) -> 0 | U21: =+SUMIFS(N21:S21,N$2:S$2,$U$5) -> 0 | V21: =+SUMIFS(N21:S21,N$2:S$2,$V$5) -> 0 | W21: =+SUMIFS(N21:S21,N$2:S$2,$W$5) -> 0 | Y21: =+K21+L21 -> 0 | Z21: 0 | AA21: 0 | AB21: 0 | AC21: 0 | AG21: =+AC21-Y21 -> 0 | AI21: =SUM(AL21:AP21) -> 0 | AJ21: =SUM(AL21:AM21) -> 0 | AK21: =+AN21 -> 0
C22: Propios | E22: =+SUM(AL22:AP22) -> 0 | H22: =AJ22 -> 0 | J22: =+H22+AE22 -> 0 | K22: =+J22+E22 -> 0 | L22: =+SUM(N22:R22) -> 0 | S22: =+SUMIFS(N22:R22,N$2:R$2,$S$5) -> 0 | U22: =+SUMIFS(N22:S22,N$2:S$2,$U$5) -> 0 | V22: =+SUMIFS(N22:S22,N$2:S$2,$V$5) -> 0 | W22: =+SUMIFS(N22:S22,N$2:S$2,$W$5) -> 0 | Y22: =+K22+L22 -> 0 | Z22: =+Eq!Z43 -> 0 | AA22: =+Eq!AA43 -> 0 | AB22: =+Eq!AB43 -> 0 | AC22: 449540.39 | AG22: =+AC22-Y22 -> 449540.39 | AI22: =SUM(AL22:AP22) -> 0 | AJ22: =SUM(AL22:AM22) -> 0 | AK22: =+AN22 -> 0
C23: Terceros | E23: =+SUM(AL23:AP23) -> 0 | H23: =AJ23 -> 0 | J23: =+H23+AE23 -> 0 | K23: =+J23+E23 -> 0 | L23: =+SUM(N23:R23) -> 0 | S23: =+SUMIFS(N23:R23,N$2:R$2,$S$5) -> 0 | U23: =+SUMIFS(N23:S23,N$2:S$2,$U$5) -> 0 | V23: =+SUMIFS(N23:S23,N$2:S$2,$V$5) -> 0 | W23: =+SUMIFS(N23:S23,N$2:S$2,$W$5) -> 0 | Y23: =+K23+L23 -> 0 | Z23: =+Eq!Z46 -> 0 | AA23: =+Eq!AA46 -> 0 | AB23: =+Eq!AB46 -> 0 | AC23: 1574098 | AG23: =+AC23-Y23 -> 1574098 | AI23: =SUM(AL23:AP23) -> 0 | AJ23: =SUM(AL23:AM23) -> 0 | AK23: =+AN23 -> 0
B24: Fletes | E24: =+SUM(AL24:AP24) -> 0 | H24: =AJ24 -> 0 | J24: =+H24+AE24 -> 0 | K24: =+J24+E24 -> 0 | L24: =+SUM(N24:R24) -> 0 | S24: =+SUMIFS(N24:R24,N$2:R$2,$S$5) -> 0 | U24: =+SUMIFS(N24:S24,N$2:S$2,$U$5) -> 0 | V24: =+SUMIFS(N24:S24,N$2:S$2,$V$5) -> 0 | W24: =+SUMIFS(N24:S24,N$2:S$2,$W$5) -> 0 | Y24: =+K24+L24 -> 0 | Z24: =+Fletes!Z27 -> 0 | AA24: 0 | AC24: 0 | AG24: =+AC24-Y24 -> 0 | AI24: =SUM(AL24:AP24) -> 0 | AJ24: =SUM(AL24:AM24) -> 0 | AK24: =+AN24 -> 0
B25: Staff (Sueldos) | E25: =+SUM(AL25:AP25) -> 0 | H25: =AJ25 -> 0 | J25: =+H25+AE25 -> 0 | K25: =+J25+E25 -> 0 | L25: =+SUM(N25:R25) -> 0 | S25: =+SUMIFS(N25:R25,N$2:R$2,$S$5) -> 0 | U25: =+SUMIFS(N25:S25,N$2:S$2,$U$5) -> 0 | V25: =+SUMIFS(N25:S25,N$2:S$2,$V$5) -> 0 | W25: =+SUMIFS(N25:S25,N$2:S$2,$W$5) -> 0 | Y25: =+K25+L25 -> 0 | Z25: 0 | AA25: 0 | AC25: 0 | AG25: =+AC25-Y25 -> 0 | AI25: =SUM(AL25:AP25) -> 0 | AJ25: =SUM(AL25:AM25) -> 0 | AK25: =+AN25 -> 0
B26: Gastos Generales | E26: =+SUM(AL26:AP26) -> 0 | H26: =AJ26 -> 0 | J26: =+H26+AE26 -> 0 | K26: =+J26+E26 -> 0 | L26: =+SUM(N26:R26) -> 0 | S26: =+SUMIFS(N26:R26,N$2:R$2,$S$5) -> 0 | U26: =+SUMIFS(N26:S26,N$2:S$2,$U$5) -> 0 | V26: =+SUMIFS(N26:S26,N$2:S$2,$V$5) -> 0 | W26: =+SUMIFS(N26:S26,N$2:S$2,$W$5) -> 0 | Y26: =+K26+L26 -> 0 | Z26: 0 | AA26: 0 | AC26: 0 | AG26: =+AC26-Y26 -> 0 | AI26: =SUM(AL26:AP26) -> 0 | AJ26: =SUM(AL26:AM26) -> 0 | AK26: =+AN26 -> 0
B28: Stock de Materiales | E28: =+SUM(AL28:AP28) -> 0 | G28: 0 | H28: =AJ28 -> 0 | J28: =+H28+AE28 -> 0 | K28: =+E28+J28 -> 0 | L28: =+SUM(N28:S28) -> 0 | N28: =-K28 -> 0 | O28: 0 | P28: 0 | Q28: 0 | R28: 0 | S28: =+SUMIFS(N28:R28,N$2:R$2,$S$5) -> 0 | U28: =+SUMIFS(N28:S28,N$2:S$2,$U$5) -> 0 | V28: =+SUMIFS(N28:S28,N$2:S$2,$V$5) -> 0 | W28: =+SUMIFS(N28:S28,N$2:S$2,$W$5) -> 0 | Y28: 0 | Z28: 0 | AA28: 0 | AC28: 0 | AI28: =SUM(AJ28:AP28) -> 0
B30: Margen Ponderado S/. | E30: =+E7*E31 -> 0 | G30: =+G7*G31 -> 0 | H30: =+H7*H31 -> 0 | J30: =+J7*J31 -> 0 | K30: =+K7*K31 -> 0 | L30: =+L7*L31 -> 0 | N30: =+N7*N31 -> 0 | O30: =+O7*O31 -> 0 | P30: =+P7*P31 -> 0 | Q30: =+Q7*Q31 -> 0 | R30: =+R7*R31 -> 0 | S30: =+S7*S31 -> 0 | U30: =+U7*U31 -> 0 | V30: =+V7*V31 -> 0 | W30: =+W7*W31 -> 0 | Y30: =+Y7-Y15 -> 0 | Z30: =+Z7-Z15 -> #REF! | AA30: =+AA7-AA15 -> #REF! | AB30: =+AB7-AB15 -> #REF! | AC30: =+AC7-AC15 -> 0 | AG30: =+Y30-AC30 -> 0
B31: Margen Ponderado % | E31: =+$Y$31 -> 0 | G31: =+$Y$31 -> 0 | H31: =+$Y$31 -> 0 | J31: =+$Y$31 -> 0 | K31: =+$Y$31 -> 0 | L31: =+$Y$31 -> 0 | N31: =+$Y$31 -> 0 | O31: =+$Y$31 -> 0 | P31: =+$Y$31 -> 0 | Q31: =+$Y$31 -> 0 | R31: =+$Y$31 -> 0 | S31: =+$Y$31 -> 0 | U31: =+$Y$31 -> 0 | V31: =+$Y$31 -> 0 | W31: =+$Y$31 -> 0 | Y31: =+IF(Y7=0,0,Y30/Y7) -> 0 | Z31: =+IF(Z7=0,0,Z30/Z7) -> #REF! | AA31: =+IF(AA7=0,0,AA30/AA7) -> 0 | AB31: =+IF(AB7=0,0,AB30/AB7) -> 0 | AC31: =+IF(AC7=0,0,AC30/AC7) -> 0
B33: Margen Absoluto S/. | E33: =+E7-E15+E28 -> 0 | G33: =+G7-G15+G28 -> 5240945.6 | H33: =+H7-H15+H28 -> 0 | J33: =+J7-J15+J28 -> 0 | K33: =+K7-K15+K28 -> 0 | L33: =+L7-L15+L28 -> 0 | N33: =+N7-N15+N28 -> 0 | O33: =+O7-O15+O28 -> 0 | P33: =+P7-P15+P28 -> 0 | Q33: =+Q7-Q15+Q28 -> 0 | R33: =+R7-R15+R28 -> 0 | S33: =+S7-S15+S28 -> 0 | U33: =+U7-U15+U28 -> 0 | V33: =+V7-V15+V28 -> 0 | W33: =+W7-W15+W28 -> 0 | Y33: =+Y7-Y15+Y28 -> 0 | Z33: =+Z7-Z15+Z28 -> #REF! | AA33: =+AA7-AA15+AA28 -> #REF! | AB33: =+AB7-AB15+AB28 -> #REF! | AC33: =+AC7-AC15+AC28 -> -2.2351742e-08 | AE33: =+AE7-AE15+AE28 -> 0
B34: Margen Absoluto % | E34: =+IF(E7=0,0,E33/E7) -> 0 | G34: 0 | H34: =+IF(H7=0,0,H33/H7) -> 0 | J34: =+IF(J7=0,0,J33/J7) -> 0 | K34: =+IF(K7=0,0,K33/K7) -> 0 | L34: =+IF(L7=0,0,L33/L7) -> 0 | N34: =+IF(N7=0,0,N33/N7) -> 0 | O34: =+IF(O7=0,0,O33/O7) -> 0 | P34: =+IF(P7=0,0,P33/P7) -> 0 | Q34: =+IF(Q7=0,0,Q33/Q7) -> 0 | R34: =+IF(R7=0,0,R33/R7) -> 0 | S34: =+IF(S7=0,0,S33/S7) -> 0 | U34: =+IF(U7=0,0,U33/U7) -> 0 | V34: =+IF(V7=0,0,V33/V7) -> 0 | W34: =+IF(W7=0,0,W33/W7) -> 0 | Y34: =+IF(Y7=0,0,Y33/Y7) -> 0 | Z34: =+IF(Z7=0,0,Z33/Z7) -> #REF! | AA34: =+IF(AA7=0,0,AA33/AA7) -> 0 | AB34: =+IF(AB7=0,0,AB33/AB7) -> 0 | AC34: =+IF(AC7=0,0,AC33/AC7) -> -4.8383334e-16 | AE34: =+IF(AE7=0,0,AE33/AE7) -> 0
AC36: 1.3969839e-09 | AE36: 9819.56
B38: COSTO APLICADO | K38: =+K7-K30 -> 0 | AS38: =H33 -> 0 | AT38: =Y33 -> 0
B40: RESULTADO PENDIENTE | K40: =K15-K38 -> 0
B42: ACTIVOS | K42: =IF('ER Pendiente'!E38>0,'ER Pendiente'!E15+'ER Pendiente'!E38,'ER Pendiente'!E15) -> 0
B44: PROVISIONES | K44: =IF('ER Pendiente'!E38<0,-'ER Pendiente'!E38-'ER Pendiente'!E22,-'ER Pendiente'!E22) -> 0
B46: DIFERENCIA DE MARGENES | G46: =+G11+'F-500'!G11+'F-600'!G11 -> 5369680 | K46: =+'Dif. Margenes'!I14 -> 0
B48: CONTINGENCIA | K48: =+K40-K42+K44 -> 0
C50: Mayor Margen +
C52: Menor Margen -

Sheet F-500
B1: =CONCATENATE(B3," - ",B4," - ",B5," - ",B6) -> I.E.N 1182 - MES DE ENERO DEL 2025 - EL BOSQUE - CERCO + INGRESOS Y CASETAS - FASE 500: ACERO FY=4200KG/CM2
N2: =+YEAR(N5) -> 2019 | O2: =+YEAR(O5) -> 2019 | P2: =+YEAR(P5) -> 2019 | Q2: =+YEAR(Q5) -> 2019 | R2: =+YEAR(R5) -> 2019 | S2: =S5 -> 2024 | U2: 43466
B3: I.E.N 1182 | E3: ACUMULADO | G3: =+B4 -> MES DE ENERO DEL 2025 | J3: ACUMULADO 2024 | K3: ACUMULADO DE OBRA | L3: SALDO DE OBRA | N3: PROYECCIÓN | U3: AÑOS SIGUIENTES | Y3: TOTAL DE OBRA | AE3: Acum. del Ej. | AI3: TOTAL | AJ3: AÑOS ANTERIORES | AK3: MES DEL INFORME | AL3: 45597 | AM3: 45627 | AN3: 45658 | AO3: 45689 | AP3: 45717
B4: MES DE ENERO DEL 2025 | N4: 1 | O4: =+N4+1 -> 2 | P4: =+O4+1 -> 3 | Q4: =+P4+1 -> 4 | R4: =+Q4+1 -> 5 | S4: Saldo del Ejercicio
B5: EL BOSQUE - CERCO + INGRESOS Y CASETAS | E5: Años Anteriores | G5: Previsto | H5: Real | N5: 43648 | O5: =+N5+31 -> 43679 | P5: =+O5+31 -> 43710 | Q5: =+P5+31 -> 43741 | R5: =+Q5+31 -> 43772 | S5: =+'DIRECTO '!S5 -> 2024 | U5: 2024 | V5: =+U5+1 -> 2025 | W5: =+V5+1 -> 2026 | Y5: Actual | Z5: Anterior | AA5: Meta | AB5: Presupuesto Interno | AC5: Original | AE5: Anterior
B6: FASE 500: ACERO FY=4200KG/CM2
B7: Venta Total Producida | E7: =+E9 -> 0 | G7: =+G9 -> 128734.34 | H7: =+H9 -> 0 | J7: =+J9 -> 0 | K7: =+K9 -> 0 | L7: =+L9 -> 0 | N7: =+N9 -> 0 | O7: =+O9 -> 0 | P7: =+P9 -> 0 | Q7: =+Q9 -> 0 | R7: =+R9 -> 0 | S7: =+S9 -> 0 | U7: =+U9 -> 0 | V7: =+V9 -> 0 | W7: =+W9 -> 0 | Y7: =+Y9 -> 0 | Z7: 15306455 | AA7: =+AA9 -> 0 | AB7: =+AB9 -> 0 | AC7: =+AC9 -> 15306455 | AE7: =+AE9 -> 0 | AI7: =+AI9 -> 0 | AJ7: =+AJ9 -> 0 | AL7: =+AL9 -> 0 | AM7: =+AM9 -> 0 | AN7: =+AN9 -> 0 | AO7: =+AO9 -> 0 | AP7: =+AP9 -> 0
B9: Venta | E9: =+SUM(E11:E13) -> 0 | G9: =+SUM(G11:G13) -> 128734.34 | H9: =+SUM(H11:H13) -> 0 | J9: =+SUM(J11:J13) -> 0 | K9: =+SUM(K11:K13) -> 0 | L9: =+SUM(L11:L12) -> 0 | N9: =+SUM(N11:N13) -> 0 | O9: =+SUM(O11:O13) -> 0 | P9: =+SUM(P11:P13) -> 0 | Q9: =+SUM(Q11:Q13) -> 0 | R9: =+SUM(R11:R13) -> 0 | S9: =+SUM(S11:S13) -> 0 | U9: =+SUM(U11:U13) -> 0 | V9: =+SUM(V11:V13) -> 0 | W9: =+SUM(W11:W13) -> 0 | Y9: =+SUM(Y11:Y13) -> 0 | Z9: 15306455 | AA9: =+SUM(AA11:AA13) -> 0 | AB9: =+SUM(AB11:AB13) -> 0 | AC9: =+SUM(AC11:AC13) -> 15306455 | AE9: =+SUM(AE11:AE13) -> 0 | AI9: =+SUM(AI11:AI13) -> 0 | AJ9: =+SUM(AJ11:AJ13) -> 0 | AL9: =+SUM(AL11:AL13) -> 0 | AM9: =+SUM(AM11:AM13) -> 0 | AN9: =+SUM(AN11:AN13) -> 0 | AO9: =+SUM(AO11:AO13) -> 0 | AP9: =+SUM(AP11:AP13) -> 0
B11: Valorización: Venta Directa - Contrato Principal | E11: =+SUM(AL11:AP11) -> 0 | G11: 128734.34 | H11: =AJ11 -> 0 | J11: =+H11+AE11 -> 0 | K11: =+E11+J11 -> 0 | N11: 0 | O11: 0 | P11: 0 | Q11: 0 | R11: 0 | S11: =+SUMIFS(N11:R11,N$2:R$2,$S$5) -> 0 | U11: =+SUMIFS(N11:S11,N$2:S$2,$U$5) -> 0 | V11: =+SUMIFS(N11:S11,N$2:S$2,$V$5) -> 0 | W11: 0 | Y11: =+K11+L11 -> 0 | Z11: 15306455 | AA11: 0 | AB11: 0 | AC11: 15306455 | AI11: =SUM(AL11:AP11) -> 0 | AJ11: =SUM(AL11:AM11) -> 0 | AK11: =+AN11 -> 0
B12: Valorización: Venta Indirecta - Contrato Principal | E12: =+SUM(AL12:AP12) -> 0 | G12: 0 | H12: =AJ12 -> 0 | J12: =+H12+AE12 -> 0 | K12: =+E12+J12 -> 0 | L12: =+SUM(N12:R12) -> 0 | N12: 0 | O12: 0 | P12: 0 | Q12: 0 | R12: 0 | S12: =+SUMIFS(N12:R12,N$2:R$2,$S$5) -> 0 | U12: =+SUMIFS(N12:S12,N$2:S$2,$U$5) -> 0 | V12: =+SUMIFS(N12:S12,N$2:S$2,$V$5) -> 0 | W12: 0 | Y12: =+K12+L12 -> 0 | Z12: 0 | AA12: 0 | AC12: 0 | AI12: =SUM(AL12:AP12) -> 0 | AJ12: =SUM(AL12:AM12) -> 0 | AK12: =+AN12 -> 0
B13: Otros: | E13: =+SUM(AL13:AP13) -> 0 | H13: =AJ13 -> 0 | L13: =+SUM(N13:R13) -> 0 | S13: =+SUMIFS(N13:R13,N$2:R$2,$S$5) -> 0 | U13: =+SUMIFS(N13:S13,N$2:S$2,$U$5) -> 0 | V13: =+SUMIFS(N13:S13,N$2:S$2,$V$5) -> 0 | W13: 0 | Y13: =+K13+L13 -> 0 | Z13: 0 | AA13: 0 | AC13: 0 | AI13: =SUM(AL13:AP13) -> 0 | AJ13: =SUM(AL13:AM13) -> 0 | AK13: =+AN13 -> 0
B15: Costo Total | E15: =+SUM(E17:E26)+E28 -> 0 | G15: =+SUM(G17:G26)+G28 -> 0 | H15: =+SUM(H17:H26)+H28 -> 0 | J15: =+SUM(J17:J26)+J28 -> 0 | K15: =+SUM(K17:K26)+K28 -> 0 | L15: =+SUM(L17:L26,L28) -> 0 | N15: =+SUM(N17:N26)+N28 -> 0 | O15: =+SUM(O17:O26)+O28 -> 0 | P15: =+SUM(P17:P26)+P28 -> 0 | Q15: =+SUM(Q17:Q26)+Q28 -> 0 | R15: =+SUM(R17:R26)+R28 -> 0 | S15: =+SUM(S17:S26)+S28 -> 0 | U15: =+SUM(U17:U26)+U28 -> 0 | V15: =+SUM(V17:V26)+V28 -> 0 | W15: =+SUM(W17:W26)+W28 -> 0 | Y15: =+SUM(Y17:Y26)+Y28 -> 0 | Z15: =+SUM(Z17:Z26)+Z28 -> 0 | AA15: =+SUM(AA17:AA26)+AA28 -> 0 | AB15: =+SUM(AB17:AB26)+AB28 -> 0 | AC15: =+SUM(AC17:AC26,AC28) -> 15306455 | AE15: =+SUM(AE17:AE26,AE28) -> 0 | AI15: =+SUM(AI17:AI26,AI28) -> 0 | AJ15: =+SUM(AJ17:AJ26,AJ28) -> 0 | AL15: =+SUM(AL17:AL26,AL28) -> 0 | AM15: =+SUM(AM17:AM26,AM28) -> 0 | AN15: =+SUM(AN17:AN26,AN28) -> 0 | AO15: =+SUM(AO17:AO26,AO28) -> 0 | AP15: =+SUM(AP17:AP26,AP28) -> 0
B17: Materiales | E17: =+SUM(AL17:AP17) -> 0 | H17: =AJ17 -> 0 | J17: =+H17+AE17 -> 0 | K17: =+E17+J17 -> 0 | L17: =+SUM(N17:R17) -> 0 | S17: =+SUMIFS(N17:R17,N$2:R$2,$S$5) -> 0 | U17: =+SUMIFS(N17:S17,N$2:S$2,$U$5) -> 0 | V17: =+SUMIFS(N17:S17,N$2:S$2,$V$5) -> 0 | W17: 0 | Y17: =+K17+L17 -> 0 | AC17: 12088496 | AI17: =SUM(AL17:AP17) -> 0 | AJ17: =SUM(AL17:AM17) -> 0 | AK17: =+AN17 -> 0
B18: Mano de Obra | E18: =+SUM(AL18:AP18) -> 0 | H18: =AJ18 -> 0 | J18: =+H18+AE18 -> 0 | K18: =+J18+E18 -> 0 | L18: =+SUM(N18:R18) -> 0 | S18: =+SUMIFS(N18:R18,N$2:R$2,$S$5) -> 0 | U18: =+SUMIFS(N18:S18,N$2:S$2,$U$5) -> 0 | V18: =+SUMIFS(N18:S18,N$2:S$2,$V$5) -> 0 | W18: 0 | Y18: =+K18+L18 -> 0 | Z18: =+MO!Z69 -> 0 | AA18: =+MO!AA69 -> 0 | AB18: =+MO!AB69 -> 0 | AC18: 132910.33 | AI18: =SUM(AL18:AP18) -> 0 | AJ18: =SUM(AL18:AM18) -> 0 | AK18: =+AN18 -> 0
B19: Subcontratos de obra | E19: =+SUM(AL19:AP19) -> 0 | H19: =AJ19 -> 0 | J19: =+H19+AE19 -> 0 | K19: =+J19+E19 -> 0 | L19: =+SUM(N19:R19) -> 0 | S19: =+SUMIFS(N19:R19,N$2:R$2,$S$5) -> 0 | U19: =+SUMIFS(N19:S19,N$2:S$2,$U$5) -> 0 | V19: =+SUMIFS(N19:S19,N$2:S$2,$V$5) -> 0 | W19: 0 | Y19: =+K19+L19 -> 0 | Z19: =+SC!Z44 -> 0 | AA19: =+SC!AA44 -> 0 | AB19: =+SC!AB44 -> 0 | AC19: 0 | AI19: =SUM(AL19:AP19) -> 0 | AJ19: =SUM(AL19:AM19) -> 0 | AK19: =+AN19 -> 0
B20: Servicios Contratados | E20: =+SUM(AL20:AP20) -> 0 | H20: =AJ20 -> 0 | J20: =+H20+AE20 -> 0 | K20: =+J20+E20 -> 0 | L20: =+SUM(N20:R20) -> 0 | S20: =+SUMIFS(N20:R20,N$2:R$2,$S$5) -> 0 | U20: =+SUMIFS(N20:S20,N$2:S$2,$U$5) -> 0 | V20: =+SUMIFS(N20:S20,N$2:S$2,$V$5) -> 0 | W20: 0 | Y20: =+K20+L20 -> 0 | Z20: =+SER!Z42 -> 0 | AI20: =SUM(AL20:AP20) -> 0 | AJ20: =SUM(AL20:AM20) -> 0 | AK20: =+AN20 -> 0
B21: Equipos y Vehículos | E21: =+SUM(AL21:AP21) -> 0 | H21: =AJ21 -> 0 | J21: =+H21+AE21 -> 0 | K21: =+J21+E21 -> 0 | L21: =+SUM(N21:R21) -> 0 | S21: =+SUMIFS(N21:R21,N$2:R$2,$S$5) -> 0 | U21: =+SUMIFS(N21:S21,N$2:S$2,$U$5) -> 0 | V21: =+SUMIFS(N21:S21,N$2:S$2,$V$5) -> 0 | W21: 0 | Y21: =+K21+L21 -> 0 | Z21: 0 | AC21: 0 | AI21: =SUM(AL21:AP21) -> 0 | AJ21: =SUM(AL21:AM21) -> 0 | AK21: =+AN21 -> 0
C22: Propios | E22: =+SUM(AL22:AP22) -> 0 | H22: =AJ22 -> 0 | J22: =+H22+AE22 -> 0 | K22: =+J22+E22 -> 0 | L22: =+SUM(N22:R22) -> 0 | S22: =+SUMIFS(N22:R22,N$2:R$2,$S$5) -> 0 | U22: =+SUMIFS(N22:S22,N$2:S$2,$U$5) -> 0 | V22: =+SUMIFS(N22:S22,N$2:S$2,$V$5) -> 0 | W22: 0 | Y22: =+K22+L22 -> 0 | Z22: =+Eq!Z51 -> 0 | AA22: =+Eq!AA51 -> 0 | AB22: =+Eq!AB51 -> 0 | AC22: 3211.2228 | AI22: =SUM(AL22:AP22) -> 0 | AJ22: =SUM(AL22:AM22) -> 0 | AK22: =+AN22 -> 0
C23: Terceros | E23: =+SUM(AL23:AP23) -> 0 | H23: =AJ23 -> 0 | J23: =+H23+AE23 -> 0 | K23: =+J23+E23 -> 0 | L23: =+SUM(N23:R23) -> 0 | S23: =+SUMIFS(N23:R23,N$2:R$2,$S$5) -> 0 | U23: =+SUMIFS(N23:S23,N$2:S$2,$U$5) -> 0 | V23: =+SUMIFS(N23:S23,N$2:S$2,$V$5) -> 0 | W23: 0 | Y23: =+K23+L23 -> 0 | Z23: =+Eq!Z54 -> 0 | AA23: =+Eq!AA54 -> 0 | AB23: =+Eq!AB54 -> 0 | AC23: 38940.724 | AI23: =SUM(AL23:AP23) -> 0 | AJ23: =SUM(AL23:AM23) -> 0 | AK23: =+AN23 -> 0
B24: Fletes | E24: =+SUM(AL24:AP24) -> 0 | H24: =AJ24 -> 0 | J24: =+H24+AE24 -> 0 | K24: =+J24+E24 -> 0 | L24: =+SUM(N24:R24) -> 0 | S24: =+SUMIFS(N24:R24,N$2:R$2,$S$5) -> 0 | U24: =+SUMIFS(N24:S24,N$2:S$2,$U$5) -> 0 | V24: =+SUMIFS(N24:S24,N$2:S$2,$V$5) -> 0 | W24: 0 | Y24: =+K24+L24 -> 0 | Z24: =+Fletes!Z31 -> 0 | AC24: 3042897.5 | AI24: =SUM(AL24:AP24) -> 0 | AJ24: =SUM(AL24:AM24) -> 0 | AK24: =+AN24 -> 0
B25: Staff (Sueldos) | E25: =+SUM(AL25:AP25) -> 0 | H25: =AJ25 -> 0 | J25: =+H25+AE25 -> 0 | K25: =+J25+E25 -> 0 | L25: =+SUM(N25:R25) -> 0 | S25: =+SUMIFS(N25:R25,N$2:R$2,$S$5) -> 0 | U25: =+SUMIFS(N25:S25,N$2:S$2,$U$5) -> 0 | V25: =+SUMIFS(N25:S25,N$2:S$2,$V$5) -> 0 | W25: 0 | Y25: =+K25+L25 -> 0 | Z25: 0 | AC25: 0 | AI25: =SUM(AL25:AP25) -> 0 | AJ25: =SUM(AL25:AM25) -> 0 | AK25: =+AN25 -> 0
B26: Gastos Generales | E26: =+SUM(AL26:AP26) -> 0 | H26: =AJ26 -> 0 | J26: =+H26+AE26 -> 0 | K26: =+J26+E26 -> 0 | L26: =+SUM(N26:R26) -> 0 | S26: =+SUMIFS(N26:R26,N$2:R$2,$S$5) -> 0 | U26: =+SUMIFS(N26:S26,N$2:S$2,$U$5) -> 0 | V26: =+SUMIFS(N26:S26,N$2:S$2,$V$5) -> 0 | W26: 0 | Y26: =+K26+L26 -> 0 | Z26: 0 | AC26: 0 | AI26: =SUM(AL26:AP26) -> 0 | AJ26: =SUM(AL26:AM26) -> 0 | AK26: =+AN26 -> 0
B28: Stock de Materiales | E28: =+SUM(AL28:AP28) -> 0 | H28: =AJ28 -> 0 | J28: =+H28+AE28 -> 0 | K28: =+E28+J28 -> 0 | L28: =+SUM(N28:S28) -> 0 | N28: =-H28 -> 0 | O28: 0 | P28: 0 | Q28: 0 | R28: 0 | S28: =+SUMIFS(N28:R28,N$2:R$2,$S$5) -> 0 | U28: =+SUMIFS(N28:S28,N$2:S$2,$U$5) -> 0 | V28: =+SUMIFS(N28:S28,N$2:S$2,$V$5) -> 0 | W28: 0 | Y28: 0 | Z28: 0 | AA28: 0 | AC28: 0 | AI28: =SUM(AJ28:AP28) -> 0
B30: Margen Ponderado S/. | E30: =+E7*E31 -> 0 | G30: =+G7*G31 -> 0 | H30: =+H7*H31 -> 0 | J30: =+J7*J31 -> 0 | K30: =+K7*K31 -> 0 | L30: =+L7*L31 -> 0 | N30: =+N7*N31 -> 0 | O30: =+O7*O31 -> 0 | P30: =+P7*P31 -> 0 | Q30: =+Q7*Q31 -> 0 | R30: =+R7*R31 -> 0 | S30: =+S7*S31 -> 0 | U30: =+U7*U31 -> 0 | V30: =+V7*V31 -> 0 | W30: =+W7*W31 -> 0 | Y30: =+Y7-Y15 -> 0 | Z30: =+Z7-Z15 -> 15306455 | AA30: =+AA7-AA15 -> 0 | AB30: =+AB7-AB15 -> 0 | AC30: =+AC7-AC15 -> 0 | AE30: =+AE7*AE31 -> 0
B31: Margen Ponderado % | E31: =+$Y$31 -> 0 | G31: =+$Y$31 -> 0 | H31: =+$Y$31 -> 0 | J31: =+$Y$31 -> 0 | K31: =+$Y$31 -> 0 | L31: =+$Y$31 -> 0 | N31: =+$Y$31 -> 0 | O31: =+$Y$31 -> 0 | P31: =+$Y$31 -> 0 | Q31: =+$Y$31 -> 0 | R31: =+$Y$31 -> 0 | S31: =+$Y$31 -> 0 | U31: =+$Y$31 -> 0 | V31: =+$Y$31 -> 0 | W31: =+$Y$31 -> 0 | Y31: =+IF(Y7=0,0,Y30/Y7) -> 0 | Z31: =+IF(Z7=0,0,Z30/Z7) -> 1 | AA31: =+IF(AA7=0,0,AA30/AA7) -> 0 | AB31: =+IF(AB7=0,0,AB30/AB7) -> 0 | AC31: =+IF(AC7=0,0,AC30/AC7) -> 0 | AE31: =+$Y$31 -> 0
B33: Margen Absoluto S/. | E33: =+E7-E15+E28 -> 0 | G33: =+G7-G15+G28 -> 128734.34 | H33: =+H7-H15+H28 -> 0 | J33: =+J7-J15+J28 -> 0 | K33: =+K7-K15+K28 -> 0 | L33: =+L7-L15+L28 -> 0 | N33: =+N7-N15+N28 -> 0 | O33: =+O7-O15+O28 -> 0 | P33: =+P7-P15+P28 -> 0 | Q33: =+Q7-Q15+Q28 -> 0 | R33: =+R7-R15+R28 -> 0 | S33: =+S7-S15+S28 -> 0 | U33: =+U7-U15+U28 -> 0 | V33: =+V7-V15+V28 -> 0 | W33: =+W7-W15+W28 -> 0 | Y33: =+Y7-Y15+Y28 -> 0 | Z33: =+Z7-Z15+Z28 -> 15306455 | AA33: =+AA7-AA15+AA28 -> 0 | AB33: =+AB7-AB15+AB28 -> 0 | AC33: =+AC7-AC15+AC28 -> -1.8626451e-09 | AE33: =+AE7-AE15+AE28 -> 0
B34: Margen Absoluto % | E34: =+IF(E7=0,0,E33/E7) -> 0 | G34: 0 | H34: =+IF(H7=0,0,H33/H7) -> 0 | J34: =+IF(J7=0,0,J33/J7) -> 0 | K34: =+IF(K7=0,0,K33/K7) -> 0 | L34: =+IF(L7=0,0,L33/L7) -> 0 | N34: =+IF(N7=0,0,N33/N7) -> 0 | O34: =+IF(O7=0,0,O33/O7) -> 0 | P34: =+IF(P7=0,0,P33/P7) -> 0 | Q34: =+IF(Q7=0,0,Q33/Q7) -> 0 | R34: =+IF(R7=0,0,R33/R7) -> 0 | S34: =+IF(S7=0,0,S33/S7) -> 0 | U34: =+IF(U7=0,0,U33/U7) -> 0 | V34: =+IF(V7=0,0,V33/V7) -> 0 | W34: =+IF(W7=0,0,W33/W7) -> 0 | Y34: =+IF(Y7=0,0,Y33/Y7) -> 0 | Z34: =+IF(Z7=0,0,Z33/Z7) -> 1 | AA34: =+IF(AA7=0,0,AA33/AA7) -> 0 | AB34: =+IF(AB7=0,0,AB33/AB7) -> 0 | AC34: =+IF(AC7=0,0,AC33/AC7) -> -1.2169017e-16 | AE34: =+IF(AE7=0,0,AE33/AE7) -> 0
AC36: 0 | AE36: -271103.13
Y37: =+Y36-Z30 -> -15306455
B38: COSTO APLICADO | K38: =+K7-K30 -> 0 | AS38: =H33 -> 0 | AT38: =Y33 -> 0
B40: RESULTADO PENDIENTE | K40: =K15-K38 -> 0
B42: ACTIVOS | K42: =IF('ER Pendiente'!F38>0,'ER Pendiente'!F15+'ER Pendiente'!F38,'ER Pendiente'!F15) -> 0
B44: PROVISIONES | K44: =IF('ER Pendiente'!F38<0,-'ER Pendiente'!F38-'ER Pendiente'!F22,-'ER Pendiente'!F22) -> 0
B46: DIFERENCIA DE MARGENES | K46: =+'Dif. Margenes'!I15 -> 0
B48: CONTINGENCIA | K48: =+K40-K42+K44 -> 0
C50: Mayor Margen +
C52: Menor Margen -

Sheet F-600
B1: =CONCATENATE(B3," - ",B4," - ",B5," - ",B6) -> I.E.N 1182 - MES DE ENERO DEL 2025 - EL BOSQUE - CERCO + INGRESOS Y CASETAS - FASE 600: GASTOS GENERALES - JULIO 2024
N2: =+YEAR(N5) -> 2019 | O2: =+YEAR(O5) -> 2019 | P2: =+YEAR(P5) -> 2019 | Q2: =+YEAR(Q5) -> 2019 | R2: =+YEAR(R5) -> 2019 | S2: =S5 -> 2024 | U2: 43466
B3: I.E.N 1182 | E3: ACUMULADO | G3: =+B4 -> MES DE ENERO DEL 2025 | J3: ACUMULADO 2024 | K3: ACUMULADO DE OBRA | L3: SALDO DE OBRA | N3: PROYECCIÓN | U3: AÑOS SIGUIENTES | Y3: TOTAL DE OBRA | AE3: Acum. del Ej. | AI3: TOTAL | AJ3: AÑOS ANTERIORES | AK3: MES DEL INFORME | AL3: 45597 | AM3: 45627 | AN3: 45658 | AO3: 45689 | AP3: 45717
B4: MES DE ENERO DEL 2025 | N4: 1 | O4: =+N4+1 -> 2 | P4: =+O4+1 -> 3 | Q4: =+P4+1 -> 4 | R4: =+Q4+1 -> 5 | S4: Saldo del Ejercicio
B5: EL BOSQUE - CERCO + INGRESOS Y CASETAS | E5: Años Anteriores | G5: Previsto | H5: Real | N5: 43648 | O5: =+N5+31 -> 43679 | P5: =+O5+31 -> 43710 | Q5: =+P5+31 -> 43741 | R5: =+Q5+31 -> 43772 | S5: =+'DIRECTO '!S5 -> 2024 | U5: 2024 | V5: =+U5+1 -> 2025 | W5: =+V5+1 -> 2026 | Y5: Actual | Z5: Anterior | AA5: Meta | AB5: Presupuesto Interno | AC5: Original | AE5: Anterior
B6: FASE 600: GASTOS GENERALES - JULIO 2024
B7: Venta Total Producida | E7: =+E9 -> 0 | G7: =+G9 -> 0 | H7: =+H9 -> 0 | J7: =+J9 -> 0 | K7: =+K9 -> 0 | L7: =+L9 -> 0 | N7: =+N9 -> 0 | O7: =+O9 -> 0 | P7: =+P9 -> 0 | Q7: =+Q9 -> 0 | R7: =+R9 -> 0 | S7: =+S9 -> 0 | U7: =+U9 -> 0 | V7: =+V9 -> 0 | W7: =+W9 -> 0 | Y7: =+Y9 -> 0 | Z7: 33570631 | AA7: =+AA9 -> 0 | AB7: =+AB9 -> 0 | AC7: =+AC9 -> 0 | AE7: =+AE9 -> 0 | AG7: =+AC7-Y7 -> 0 | AI7: =+AI9 -> 0 | AJ7: =+AJ9 -> 0 | AL7: =+AL9 -> 0 | AM7: =+AM9 -> 0 | AN7: =+AN9 -> 0 | AO7: =+AO9 -> 0 | AP7: =+AP9 -> 0
B9: Venta | E9: =+SUM(E11:E13) -> 0 | G9: =+SUM(G11:G13) -> 0 | H9: =+SUM(H11:H13) -> 0 | J9: =+SUM(J11:J13) -> 0 | K9: =+SUM(K11:K13) -> 0 | L9: =+SUM(L11:L12) -> 0 | N9: =+SUM(N11:N13) -> 0 | O9: =+SUM(O11:O13) -> 0 | P9: =+SUM(P11:P13) -> 0 | Q9: =+SUM(Q11:Q13) -> 0 | R9: =+SUM(R11:R13) -> 0 | S9: =+SUM(S11:S13) -> 0 | U9: =+SUM(U11:U13) -> 0 | V9: =+SUM(V11:V13) -> 0 | W9: =+SUM(W11:W13) -> 0 | Y9: =+SUM(Y11:Y13) -> 0 | AA9: =+SUM(AA11:AA13) -> 0 | AB9: =+SUM(AB11:AB13) -> 0 | AC9: =+SUM(AC11:AC13) -> 0 | AE9: =+SUM(AE11:AE13) -> 0 | AG9: =+AC9-Y9 -> 0 | AI9: =+SUM(AI11:AI13) -> 0 | AL9: =+SUM(AL11:AL13) -> 0 | AM9: =+SUM(AM11:AM13) -> 0 | AN9: =+SUM(AN11:AN13) -> 0 | AO9: =+SUM(AO11:AO13) -> 0 | AP9: =+SUM(AP11:AP13) -> 0
B11: Valorización: Venta Directa - Contrato Principal | E11: =+SUM(AL11:AP11) -> 0 | H11: =AJ11 -> 0 | J11: =+H11+AE11 -> 0 | K11: =+E11+J11 -> 0 | N11: 0 | O11: 0 | P11: 0 | Q11: 0 | R11: 0 | S11: =+SUMIFS(N11:R11,N$2:R$2,$S$5) -> 0 | U11: =+SUMIFS(N11:S11,N$2:S$2,$U$5) -> 0 | V11: =+SUMIFS(N11:S11,N$2:S$2,$V$5) -> 0 | W11: =+SUMIFS(N11:S11,N$2:S$2,$W$5) -> 0 | Y11: =+K11+L11 -> 0 | AA11: 0 | AG11: =+AC11-Y11 -> 0 | AI11: =SUM(AL11:AP11) -> 0 | AJ11: =SUM(AL11:AM11) -> 0 | AK11: =+AN11 -> 0
B12: Valorización: Venta Indirecta - Contrato Principal | E12: =+SUM(AL12:AP12) -> 0 | G12: 0 | H12: =AJ12 -> 0 | J12: =+H12+AE12 -> 0 | K12: =+E12+J12 -> 0 | N12: 0 | O12: 0 | P12: 0 | Q12: 0 | R12: 0 | S12: =+SUMIFS(N12:R12,N$2:R$2,$S$5) -> 0 | U12: =+SUMIFS(N12:S12,N$2:S$2,$U$5) -> 0 | V12: =+SUMIFS(N12:S12,N$2:S$2,$V$5) -> 0 | W12: =+SUMIFS(N12:S12,N$2:S$2,$W$5) -> 0 | Y12: =+K12+L12 -> 0 | Z12: 0 | AG12: =+AC12-Y12 -> 0 | AI12: =SUM(AL12:AP12) -> 0 | AJ12: =SUM(AL12:AM12) -> 0 | AK12: =+AN12 -> 0
B13: Otros: | E13: =+SUM(AL13:AP13) -> 0 | G13: 0 | H13: =AJ13 -> 0 | J13: =+H13+AE13 -> 0 | K13: =+E13+J13 -> 0 | N13: 0 | O13: 0 | P13: 0 | Q13: 0 | R13: 0 | S13: =+SUMIFS(N13:R13,N$2:R$2,$S$5) -> 0 | U13: =+SUMIFS(N13:S13,N$2:S$2,$U$5) -> 0 | V13: =+SUMIFS(N13:S13,N$2:S$2,$V$5) -> 0 | W13: =+SUMIFS(N13:S13,N$2:S$2,$W$5) -> 0 | Y13: =+K13+L13 -> 0 | Z13: 0 | AA13: 0 | AG13: =+AC13-Y13 -> 0 | AI13: =SUM(AL13:AP13) -> 0 | AJ13: =SUM(AL13:AM13) -> 0 | AK13: =+AN13 -> 0
B15: Costo Total | E15: =+SUM(E17:E26)+E28 -> 0 | G15: =+SUM(G17:G26)+G28 -> 0 | H15: =+SUM(H17:H26)+H28 -> 0 | J15: =+SUM(J17:J26)+J28 -> 0 | K15: =+SUM(K17:K26)+K28 -> 0 | L15: =+SUM(L17:L26,L28) -> 0 | N15: =+SUM(N17:N26)+N28 -> 0 | O15: =+SUM(O17:O26)+O28 -> 0 | P15: =+SUM(P17:P26)+P28 -> 0 | Q15: =+SUM(Q17:Q26)+Q28 -> 0 | R15: =+SUM(R17:R26)+R28 -> 0 | S15: =+SUM(S17:S26)+S28 -> 0 | U15: =+SUM(U17:U26)+U28 -> 0 | V15: =+SUM(V17:V26)+V28 -> 0 | W15: =+SUM(W17:W26)+W28 -> 0 | Y15: =+SUM(Y17:Y26)+Y28 -> 0 | Z15: =+SUM(Z17:Z26)+Z28 -> 0 | AA15: =+SUM(AA17:AA26)+AA28 -> 0 | AB15: =+SUM(AB17:AB26)+AB28 -> 0 | AC15: =+SUM(AC17:AC26,AC28) -> 0 | AE15: =+SUM(AE17:AE26,AE28) -> 0 | AG15: =+AC15-Y15 -> 0
B17: Materiales | E17: =+SUM(AL17:AP17) -> 0 | H17: =AJ17 -> 0 | J17: =+H17+AE17 -> 0 | K17: =+E17+J17 -> 0 | L17: =+SUM(N17:R17) -> 0 | U17: =+SUMIFS(N17:S17,N$2:S$2,$U$5) -> 0 | V17: =+SUMIFS(N17:S17,N$2:S$2,$V$5) -> 0 | W17: =+SUMIFS(N17:S17,N$2:S$2,$W$5) -> 0 | Y17: =+K17+L17 -> 0 | AG17: =+AC17-Y17 -> 0 | AI17: =SUM(AL17:AP17) -> 0 | AJ17: =SUM(AL17:AM17) -> 0 | AK17: =+AN17 -> 0
B18: Mano de Obra | E18: =+SUM(AL18:AP18) -> 0 | H18: =AJ18 -> 0 | J18: =+H18+AE18 -> 0 | K18: =+J18+E18 -> 0 | L18: =+SUM(N18:R18) -> 0 | U18: =+SUMIFS(N18:S18,N$2:S$2,$U$5) -> 0 | V18: =+SUMIFS(N18:S18,N$2:S$2,$V$5) -> 0 | W18: =+SUMIFS(N18:S18,N$2:S$2,$W$5) -> 0 | Y18: =+K18+L18 -> 0 | AG18: =+AC18-Y18 -> 0 | AI18: =SUM(AL18:AP18) -> 0 | AJ18: =SUM(AL18:AM18) -> 0 | AK18: =+AN18 -> 0
B19: Subcontratos de obra | E19: =+SUM(AL19:AP19) -> 0 | F19: 0 | H19: =AJ19 -> 0 | J19: =+H19+AE19 -> 0 | K19: =+J19+E19 -> 0 | L19: =+SUM(N19:R19) -> 0 | U19: =+SUMIFS(N19:S19,N$2:S$2,$U$5) -> 0 | V19: =+SUMIFS(N19:S19,N$2:S$2,$V$5) -> 0 | W19: =+SUMIFS(N19:S19,N$2:S$2,$W$5) -> 0 | Y19: =+K19+L19 -> 0 | AG19: =+AC19-Y19 -> 0 | AH19: -43926.124 | AI19: =SUM(AL19:AP19) -> 0 | AJ19: =SUM(AL19:AM19) -> 0 | AK19: =+AN19 -> 0
B20: Servicios Contratados | E20: =+SUM(AL20:AP20) -> 0 | H20: =AJ20 -> 0 | J20: =+H20+AE20 -> 0 | K20: =+J20+E20 -> 0 | L20: =+SUM(N20:R20) -> 0 | U20: =+SUMIFS(N20:S20,N$2:S$2,$U$5) -> 0 | V20: =+SUMIFS(N20:S20,N$2:S$2,$V$5) -> 0 | W20: =+SUMIFS(N20:S20,N$2:S$2,$W$5) -> 0 | Y20: =+K20+L20 -> 0 | AG20: =+AC20-Y20 -> 0 | AI20: =SUM(AL20:AP20) -> 0 | AJ20: =SUM(AL20:AM20) -> 0 | AK20: =+AN20 -> 0
B21: Equipos y Vehículos | E21: =+SUM(AL21:AP21) -> 0 | H21: =AJ21 -> 0 | J21: =+H21+AE21 -> 0 | K21: =+J21+E21 -> 0 | L21: =+SUM(N21:R21) -> 0 | U21: =+SUMIFS(N21:S21,N$2:S$2,$U$5) -> 0 | V21: =+SUMIFS(N21:S21,N$2:S$2,$V$5) -> 0 | W21: =+SUMIFS(N21:S21,N$2:S$2,$W$5) -> 0 | Y21: =+K21+L21 -> 0 | AG21: =+AC21-Y21 -> 0 | AI21: =SUM(AL21:AP21) -> 0 | AJ21: =SUM(AL21:AM21) -> 0 | AK21: =+AN21 -> 0
C22: Propios | E22: =+SUM(AL22:AP22) -> 0 | H22: =AJ22 -> 0 | J22: =+H22+AE22 -> 0 | K22: =+J22+E22 -> 0 | L22: =+SUM(N22:R22) -> 0 | U22: =+SUMIFS(N22:S22,N$2:S$2,$U$5) -> 0 | V22: =+SUMIFS(N22:S22,N$2:S$2,$V$5) -> 0 | W22: =+SUMIFS(N22:S22,N$2:S$2,$W$5) -> 0 | Y22: =+K22+L22 -> 0 | AG22: =+AC22-Y22 -> 0 | AI22: =SUM(AL22:AP22) -> 0 | AJ22: =SUM(AL22:AM22) -> 0 | AK22: =+AN22 -> 0
C23: Terceros | E23: =+SUM(AL23:AP23) -> 0 | H23: =AJ23 -> 0 | J23: =+H23+AE23 -> 0 | K23: =+J23+E23 -> 0 | L23: =+SUM(N23:R23) -> 0 | U23: =+SUMIFS(N23:S23,N$2:S$2,$U$5) -> 0 | V23: =+SUMIFS(N23:S23,N$2:S$2,$V$5) -> 0 | W23: =+SUMIFS(N23:S23,N$2:S$2,$W$5) -> 0 | Y23: =+K23+L23 -> 0 | AG23: =+AC23-Y23 -> 0 | AI23: =SUM(AL23:AP23) -> 0 | AJ23: =SUM(AL23:AM23) -> 0 | AK23: =+AN23 -> 0
B24: Fletes | E24: =+SUM(AL24:AP24) -> 0 | H24: =AJ24 -> 0 | J24: =+H24+AE24 -> 0 | K24: =+J24+E24 -> 0 | L24: =+SUM(N24:R24) -> 0 | U24: =+SUMIFS(N24:S24,N$2:S$2,$U$5) -> 0 | V24: =+SUMIFS(N24:S24,N$2:S$2,$V$5) -> 0 | W24: =+SUMIFS(N24:S24,N$2:S$2,$W$5) -> 0 | Y24: =+K24+L24 -> 0 | AG24: =+AC24-Y24 -> 0 | AI24: =SUM(AL24:AP24) -> 0 | AJ24: =SUM(AL24:AM24) -> 0 | AK24: =+AN24 -> 0
B25: Staff (Sueldos) | E25: =+SUM(AL25:AP25) -> 0 | H25: =AJ25 -> 0 | J25: =+H25+AE25 -> 0 | K25: =+J25+E25 -> 0 | L25: =+SUM(N25:R25) -> 0 | U25: =+SUMIFS(N25:S25,N$2:S$2,$U$5) -> 0 | V25: =+SUMIFS(N25:S25,N$2:S$2,$V$5) -> 0 | W25: =+SUMIFS(N25:S25,N$2:S$2,$W$5) -> 0 | Y25: =+K25+L25 -> 0 | Z25: 0 | AA25: 0 | AG25: =+AC25-Y25 -> 0 | AI25: =SUM(AL25:AP25) -> 0 | AJ25: =SUM(AL25:AM25) -> 0 | AK25: =+AN25 -> 0
B26: Gastos Generales | E26: =+SUM(AL26:AP26) -> 0 | H26: =AJ26 -> 0 | J26: =+H26+AE26 -> 0 | K26: =+J26+E26 -> 0 | L26: =+SUM(N26:R26) -> 0 | U26: =+SUMIFS(N26:S26,N$2:S$2,$U$5) -> 0 | V26: =+SUMIFS(N26:S26,N$2:S$2,$V$5) -> 0 | W26: =+SUMIFS(N26:S26,N$2:S$2,$W$5) -> 0 | Y26: =+K26+L26 -> 0 | Z26: 0 | AA26: 0 | AG26: =+AC26-Y26 -> 0 | AI26: =SUM(AL26:AP26) -> 0 | AJ26: =SUM(AL26:AM26) -> 0 | AK26: =+AN26 -> 0
B28: Stock de Materiales | E28: =+SUM(AL28:AP28) -> 0 | G28: 0 | H28: =AJ28 -> 0 | J28: =+H28+AE28 -> 0 | K28: =+E28+J28 -> 0 | L28: =+SUM(N28:S28) -> 0 | N28: =-H28 -> 0 | O28: 0 | P28: 0 | Q28: 0 | R28: 0 | S28: =+SUMIFS(N28:R28,N$2:R$2,$S$5) -> 0 | U28: =+SUMIFS(N28:S28,N$2:S$2,$U$5) -> 0 | V28: =+SUMIFS(N28:S28,N$2:S$2,$V$5) -> 0 | W28: =+SUMIFS(N28:S28,N$2:S$2,$W$5) -> 0 | Y28: 0 | Z28: 0 | AA28: 0 | AC28: 0 | AI28: =SUM(AJ28:AP28) -> 0
B30: Margen Ponderado S/. | E30: =+E7*E31 -> 0 | G30: 0 | H30: =+H7*H31 -> 0 | J30: =+J7*J31 -> 0 | K30: =+K7*K31 -> 0 | L30: =+L7*L31 -> 0 | N30: =+N7*N31 -> 0 | O30: =+O7*O31 -> 0 | P30: =+P7*P31 -> 0 | Q30: =+Q7*Q31 -> 0 | R30: =+R7*R31 -> 0 | S30: =+S7*S31 -> 0 | U30: =+U7*U31 -> 0 | V30: =+V7*V31 -> 0 | W30: =+W7*W31 -> 0 | Y30: =+Y7-Y15 -> 0 | Z30: =+Z7-Z15 -> 33570631 | AA30: =+AA7-AA15 -> 0 | AB30: =+AB7-AB15 -> 0 | AC30: =+AC7-AC15 -> 0 | AE30: =+AE7*AE31 -> 0 | AG30: =+Y30-AC30 -> 0
B31: Margen Ponderado % | E31: =+$Y$31 -> 0 | G31: =+$Y$31 -> 0 | H31: =+$Y$31 -> 0 | J31: =+$Y$31 -> 0 | K31: =+$Y$31 -> 0 | L31: =+$Y$31 -> 0 | N31: =+$Y$31 -> 0 | O31: =+$Y$31 -> 0 | P31: =+$Y$31 -> 0 | Q31: =+$Y$31 -> 0 | R31: =+$Y$31 -> 0 | S31: =+$Y$31 -> 0 | U31: =+$Y$31 -> 0 | V31: =+$Y$31 -> 0 | W31: =+$Y$31 -> 0 | Y31: =+IF(Y7=0,0,Y30/Y7) -> 0 | Z31: =+IF(Z7=0,0,Z30/Z7) -> 1 | AA31: =+IF(AA7=0,0,AA30/AA7) -> 0 | AB31: =+IF(AB7=0,0,AB30/AB7) -> 0 | AC31: =+IF(AC7=0,0,AC30/AC7) -> 0 | AE31: =+$Y$31 -> 0
B33: Margen Absoluto S/. | E33: =+E7-E15+E28 -> 0 | G33: =+G7-G15+G28 -> 0 | H33: =+H7-H15+H28 -> 0 | J33: =+J7-J15+J28 -> 0 | K33: =+K7-K15+K28 -> 0 | L33: =+L7-L15+L28 -> 0 | N33: =+N7-N15+N28 -> 0 | O33: =+O7-O15+O28 -> 0 | P33: =+P7-P15+P28 -> 0 | Q33: =+Q7-Q15+Q28 -> 0 | R33: =+R7-R15+R28 -> 0 | S33: =+S7-S15+S28 -> 0 | U33: =+U7-U15+U28 -> 0 | V33: =+V7-V15+V28 -> 0 | W33: =+W7-W15+W28 -> 0 | Y33: =+Y7-Y15+Y28 -> 0 | Z33: =+Z7-Z15+Z28 -> 33570631 | AA33: =+AA7-AA15+AA28 -> 0 | AB33: =+AB7-AB15+AB28 -> 0 | AC33: =+AC7-AC15+AC28 -> 0 | AE33: =+AE7-AE15+AE28 -> 0
B34: Margen Absoluto % | E34: =+IF(E7=0,0,E33/E7) -> 0 | G34: 0 | H34: =+IF(H7=0,0,H33/H7) -> 0 | J34: =+IF(J7=0,0,J33/J7) -> 0 | K34: =+IF(K7=0,0,K33/K7) -> 0 | L34: =+IF(L7=0,0,L33/L7) -> 0 | N34: =+IF(N7=0,0,N33/N7) -> 0 | O34: =+IF(O7=0,0,O33/O7) -> 0 | P34: =+IF(P7=0,0,P33/P7) -> 0 | Q34: =+IF(Q7=0,0,Q33/Q7) -> 0 | R34: =+IF(R7=0,0,R33/R7) -> 0 | S34: =+IF(S7=0,0,S33/S7) -> 0 | U34: =+IF(U7=0,0,U33/U7) -> 0 | V34: =+IF(V7=0,0,V33/V7) -> 0 | W34: =+IF(W7=0,0,W33/W7) -> 0 | Y34: =+IF(Y7=0,0,Y33/Y7) -> 0 | Z34: =+IF(Z7=0,0,Z33/Z7) -> 1 | AA34: =+IF(AA7=0,0,AA33/AA7) -> 0 | AB34: =+IF(AB7=0,0,AB33/AB7) -> 0 | AC34: =+IF(AC7=0,0,AC33/AC7) -> 0 | AE34: =+IF(AE7=0,0,AE33/AE7) -> 0
Y36: 255551.77 | Z36: 318111.13 | AC36: 0 | AE36: 628589.08
Y37: =+Y36-Z30 -> -33315080
B38: COSTO APLICADO | K38: =+K7-K30 -> 0 | AS38: =H33 -> 0 | AT38: =Y33 -> 0
B40: RESULTADO PENDIENTE | K40: =K15-K38 -> 0
B42: ACTIVOS | K42: =IF('ER Pendiente'!G38>0,'ER Pendiente'!G15+'ER Pendiente'!G38,'ER Pendiente'!G15) -> #REF!
B44: PROVISIONES | K44: =IF('ER Pendiente'!G38<0,-'ER Pendiente'!G38-'ER Pendiente'!G22,-'ER Pendiente'!G22) -> #REF! | W44: =200*120/25 -> 960
B46: DIFERENCIA DE MARGENES | K46: =+'Dif. Margenes'!#REF! -> #REF!
B48: CONTINGENCIA | K48: =+K40-K42+K44 -> #REF!
C50: Mayor Margen +
C52: Menor Margen -

Sheet Mat
A1: DETALLE DE COSTOS - MATERIALES
A2: MES DE ENERO DEL 2025
A5: OBRA: | B5: EL BOSQUE - CERCO + INGRESOS Y CASETAS
A6: CLIENTE : | K6: T/C actual :
AK7: REALES
O8: =+YEAR(O11) -> 2025 | P8: =+YEAR(P11) -> 2025 | Q8: =+YEAR(Q11) -> 2025 | R8: =+YEAR(R11) -> 2025 | S8: =+YEAR(S11) -> 2025
A9: FASE | B9: CONCEPTO | C9: UND | D9: TOTAL ORIGINAL | F9: Acumulado Años Anteriores | H9: =+A2 -> MES DE ENERO DEL 2025 | K9: ACUMULADO DEL 2025 | L9: ACUMULADO DE OBRA | M9: SALDO DE OBRA | O9: Proyección | U9: AÑOS SIGUIENTES | Y9: Total Obra | AE9: Acumulado de meses anteriores | AH9: TOTAL | AI9: AÑOS ANTERIORES | AJ9: MES DEL INFORME | AK9: 45597 | AL9: 45627 | AM9: 45658 | AN9: 45689 | AO9: 45717
O10: 4 | P10: =+O10+1 -> 5 | Q10: =+P10+1 -> 6 | R10: =+Q10+1 -> 7 | S10: =+R10+1 -> 8
H11: Previsto | I11: Real | O11: 45689 | P11: =+O11+31 -> 45720 | Q11: =+P11+31 -> 45751 | R11: =+Q11+31 -> 45782 | S11: =+R11+31 -> 45813 | U11: 2025 | V11: =+U11+1 -> 2026 | W11: =+V11+1 -> 2027 | Y11: Actual | Z11: Anterior | AA11: Meta | AB11: Presupuesto Interno | AC11: Original | AE11: del presente año
A12: 100 | B12: OBRAS PRELIMINARES
A13: 1 | C13: S/. | F13: =AI13 -> 0 | I13: =AJ13 -> 0 | K13: =+I13+AE13 -> 0 | L13: =+K13+F13 -> 0 | M13: =+D13-L13 -> 0 | O13: =+O$12*$M13 -> 0 | P13: =+P$12*$M13 -> 0 | Q13: =+Q$12*$M13 -> 0 | R13: =+R$12*$M13 -> 0 | S13: =+S$12*$M13 -> 0 | U13: =+SUMIFS(O13:S13,O$8:S$8,$U$11) -> 0 | V13: =+SUMIFS(O13:S13,O$8:S$8,$V$11) -> 0 | W13: =+SUMIFS(O13:S13,O$8:S$8,$W$11) -> 0 | Y13: =+L13+M13 -> 0 | AH13: =SUM(AK13:AO13) -> 0 | AI13: =SUM(AK13:AL13) -> 0 | AJ13: =+AM13 -> 0
A14: 2 | C14: S/. | F14: =AI14 -> 0 | I14: =AJ14 -> 0 | K14: =+I14+AE14 -> 0 | L14: =+K14+F14 -> 0 | M14: =+D14-L14 -> 0 | O14: =+O$12*$M14 -> 0 | P14: =+P$12*$M14 -> 0 | Q14: =+Q$12*$M14 -> 0 | R14: =+R$12*$M14 -> 0 | S14: =+S$12*$M14 -> 0 | U14: =+SUMIFS(O14:S14,O$8:S$8,$U$11) -> 0 | V14: =+SUMIFS(O14:S14,O$8:S$8,$V$11) -> 0 | W14: =+SUMIFS(O14:S14,O$8:S$8,$W$11) -> 0 | Y14: =+L14+M14 -> 0 | AH14: =SUM(AK14:AO14) -> 0 | AI14: =SUM(AK14:AL14) -> 0 | AJ14: =+AM14 -> 0
A15: 3 | C15: S/. | F15: =AI15 -> 0 | I15: =AJ15 -> 0 | K15: =+I15+AE15 -> 0 | L15: =+K15+F15 -> 0 | M15: =+D15-L15 -> 0 | O15: =+O$12*$M15 -> 0 | P15: =+P$12*$M15 -> 0 | Q15: =+Q$12*$M15 -> 0 | R15: =+R$12*$M15 -> 0 | S15: =+S$12*$M15 -> 0 | U15: =+SUMIFS(O15:S15,O$8:S$8,$U$11) -> 0 | V15: =+SUMIFS(O15:S15,O$8:S$8,$V$11) -> 0 | W15: =+SUMIFS(O15:S15,O$8:S$8,$W$11) -> 0 | Y15: =+L15+M15 -> 0 | AH15: =SUM(AK15:AO15) -> 0 | AI15: =SUM(AK15:AL15) -> 0 | AJ15: =+AM15 -> 0
A16: 4 | C16: S/. | F16: =AI16 -> 0 | I16: =AJ16 -> 0 | K16: =+I16+AE16 -> 0 | L16: =+K16+F16 -> 0 | M16: =+D16-L16 -> 0 | O16: =+O$12*$M16 -> 0 | P16: =+P$12*$M16 -> 0 | Q16: =+Q$12*$M16 -> 0 | R16: =+R$12*$M16 -> 0 | S16: =+S$12*$M16 -> 0 | U16: =+SUMIFS(O16:S16,O$8:S$8,$U$11) -> 0 | V16: =+SUMIFS(O16:S16,O$8:S$8,$V$11) -> 0 | W16: =+SUMIFS(O16:S16,O$8:S$8,$W$11) -> 0 | Y16: =+L16+M16 -> 0 | AH16: =SUM(AK16:AO16) -> 0 | AI16: =SUM(AK16:AL16) -> 0 | AJ16: =+AM16 -> 0
A17: 5 | C17: S/. | F17: =AI17 -> 0 | I17: =AJ17 -> 0 | K17: =+I17+AE17 -> 0 | L17: =+K17+F17 -> 0 | M17: =+D17-L17 -> 0 | O17: =+O$12*$M17 -> 0 | P17: =+P$12*$M17 -> 0 | Q17: =+Q$12*$M17 -> 0 | R17: =+R$12*$M17 -> 0 | S17: =+S$12*$M17 -> 0 | U17: =+SUMIFS(O17:S17,O$8:S$8,$U$11) -> 0 | V17: =+SUMIFS(O17:S17,O$8:S$8,$V$11) -> 0 | W17: =+SUMIFS(O17:S17,O$8:S$8,$W$11) -> 0 | Y17: =+L17+M17 -> 0 | AH17: =SUM(AK17:AO17) -> 0 | AI17: =SUM(AK17:AL17) -> 0 | AJ17: =+AM17 -> 0
A18: 6 | C18: S/. | F18: =AI18 -> 0 | I18: =AJ18 -> 0 | K18: =+I18+AE18 -> 0 | L18: =+K18+F18 -> 0 | M18: =+D18-L18 -> 0 | O18: =+O$12*$M18 -> 0 | P18: =+P$12*$M18 -> 0 | Q18: =+Q$12*$M18 -> 0 | R18: =+R$12*$M18 -> 0 | S18: =+S$12*$M18 -> 0 | U18: =+SUMIFS(O18:S18,O$8:S$8,$U$11) -> 0 | V18: =+SUMIFS(O18:S18,O$8:S$8,$V$11) -> 0 | W18: =+SUMIFS(O18:S18,O$8:S$8,$W$11) -> 0 | Y18: =+L18+M18 -> 0 | AH18: =SUM(AK18:AO18) -> 0 | AI18: =SUM(AK18:AL18) -> 0 | AJ18: =+AM18 -> 0
A19: =+"TOTAL FASE "&A12&" : "&B12 -> TOTAL FASE 100 : OBRAS PRELIMINARES | D19: S/. | F19: =SUM(F13:F18) -> 0 | H19: =SUM(H13:H18) -> 0 | I19: =SUM(I13:I18) -> 0 | K19: =+I19+AE19 -> 0 | L19: =+K19+F19 -> 0 | M19: =SUM(M13:M18) -> 0 | O19: =SUM(O13:O18) -> 0 | P19: =SUM(P13:P18) -> 0 | Q19: =SUM(Q13:Q18) -> 0 | R19: =SUM(R13:R18) -> 0 | S19: =SUM(S13:S18) -> 0 | U19: =SUM(U13:U18) -> 0 | V19: =SUM(V13:V18) -> 0 | W19: =SUM(W13:W18) -> 0 | Y19: =SUM(Y13:Y18) -> 0 | Z19: =SUM(Z13:Z18) -> 0 | AA19: =SUM(AA13:AA18) -> 0 | AB19: =SUM(AB13:AB18) -> 0 | AC19: =SUM(AC13:AC18) -> 0 | AE19: =SUM(AE13:AE18) -> 0 | AH19: =SUM(AI19:AO19) -> 0 | AI19: =SUM(AJ19:AP19) -> 0 | AJ19: =SUM(AK19:AQ19) -> 0 | AK19: =SUM(AK13:AK18) -> 0 | AL19: =SUM(AL13:AL18) -> 0 | AM19: =SUM(AM13:AM18) -> 0 | AN19: =SUM(AN13:AN18) -> 0 | AO19: =SUM(AO13:AO18) -> 0
A20: 200 | B20: MOVIMIENTO DE TIERRAS | AE20: =+AE22+AE24+#REF!+#REF! -> #REF!
A21: 1 | C21: S/. | F21: =AI21 -> 0 | I21: =AJ21 -> 0 | K21: =+I21+AE21 -> 0 | L21: =+K21+F21 -> 0 | M21: =+D21-L21 -> 0 | O21: =+O$20*$M21 -> 0 | P21: =+P$20*$M21 -> 0 | Q21: =+Q$20*$M21 -> 0 | R21: =+R$20*$M21 -> 0 | S21: =+S$20*$M21 -> 0 | U21: =+SUMIFS(O21:S21,O$8:S$8,$U$11) -> 0 | V21: =+SUMIFS(O21:S21,O$8:S$8,$V$11) -> 0 | W21: =+SUMIFS(P21:T21,P$8:T$8,$W$11) -> 0 | Y21: =+L21+M21 -> 0 | AH21: =SUM(AK21:AO21) -> 0 | AI21: =SUM(AK21:AL21) -> 0 | AJ21: =+AM21 -> 0
A22: 2 | C22: S/. | F22: =AI22 -> 0 | I22: =AJ22 -> 0 | K22: =+I22+AE22 -> 0 | L22: =+K22+F22 -> 0 | M22: =+D22-L22 -> 0 | O22: =+O$20*$M22 -> 0 | P22: =+P$20*$M22 -> 0 | Q22: =+Q$20*$M22 -> 0 | R22: =+R$20*$M22 -> 0 | S22: =+S$20*$M22 -> 0 | U22: =+SUMIFS(O22:S22,O$8:S$8,$U$11) -> 0 | V22: =+SUMIFS(O22:S22,O$8:S$8,$V$11) -> 0 | W22: =+SUMIFS(P22:T22,P$8:T$8,$W$11) -> 0 | Y22: =+L22+M22 -> 0 | AH22: =SUM(AK22:AO22) -> 0 | AI22: =SUM(AK22:AL22) -> 0 | AJ22: =+AM22 -> 0
A23: 3 | C23: S/. | F23: =AI23 -> 0 | I23: =AJ23 -> 0 | K23: =+I23+AE23 -> 0 | L23: =+K23+F23 -> 0 | M23: =+D23-L23 -> 0 | O23: =+O$20*$M23 -> 0 | P23: =+P$20*$M23 -> 0 | Q23: =+Q$20*$M23 -> 0 | R23: =+R$20*$M23 -> 0 | S23: =+S$20*$M23 -> 0 | U23: =+SUMIFS(O23:S23,O$8:S$8,$U$11) -> 0 | V23: =+SUMIFS(O23:S23,O$8:S$8,$V$11) -> 0 | W23: =+SUMIFS(P23:T23,P$8:T$8,$W$11) -> 0 | Y23: =+L23+M23 -> 0 | AH23: =SUM(AK23:AO23) -> 0 | AI23: =SUM(AK23:AL23) -> 0 | AJ23: =+AM23 -> 0
