Workbook

Sheet PRESUPUESTOS
A1: ANALISIS DE PRESUPUESTOS
A3: PROYECTO: | B3: I.E. N° 1182 "EL BOSQUE" - CERCO + INGRESOS Y CASETAS
A5: PC | B5: ITEM | C5: DESCRIPCION | D5: UND | E5: CONTRACTUAL | I5: META INICIAL -MES ANTERIOR | M5: META ACTUALIZADO
E6: METRADO | F6: P.U. (S/.) | G6: PARCIAL (S/.) | I6: METRADO | J6: P.U. (S/.) | K6: PARCIAL (S/.) | M6: METRADO | N6: P.U. (S/.) | O6: MANO DE OBRA | P6: MATERIALES | Q6: EQUIPOS | R6: SERVICIOS | S6: SUBCONTRATOS | T6: PARCIAL (S/.)
B7: 01 | C7: OBRAS PROVISIONALES, TRABAJOS PRELIMINARES, SEGURIDAD Y SALUD
B8: 01.02 | C8: Trabajos Preliminares
B9: 01.02.04 | C9: Trazo, Niveles y Replanteo
A10: 100 | B10: 01.02.04.01 | C10: TRAZO Y REPLANTEO PRELIMINAR | D10: M2 | E10: 897.34 | F10: 2.04 | G10: =ROUND(E10*F10,2) -> 1830.57 | I10: 942.21 | J10: 1.33 | K10: =ROUND(I10*J10,2) -> 1253.14 | M10: 935 | N10: =SUM(O10:S10) -> 1.47 | O10: 0.52 | P10: 0.7 | Q10: 0.25 | T10: =ROUND(M10*N10,2) -> 1374.45
A11: 100 | B11: 01.02.04.02 | C11: TRAZO Y REPLANTEO DURANTE EL PROCESO | D11: m2 | E11: 897.34 | F11: 2.04 | G11: =ROUND(E11*F11,2) -> 1830.57 | I11: 942.21 | J11: 1.33 | K11: =ROUND(I11*J11,2) -> 1253.14 | N11: =SUM(O11:S11) -> 0
B12: 02 | C12: ESTRUCTURAS
B13: 02.01 | C13: Movimiento de Tierras
B14: 02.01.01 | C14: Excavaciones
A15: 200 | B15: 02.01.01.01 | C15: EXCAV.ZANJAS Y ZAPATA RT>2kg/cm2 H=1.5m | D15: m3 | E15: 41.9 | F15: 46.74 | G15: =ROUND(E15*F15,2) -> 1958.41 | I15: 39.81 | J15: 29.22 | K15: =ROUND(I15*J15,2) -> 1163.25 | N15: =SUM(O15:S15) -> 0
A16: 200 | B16: 02.01.01.02 | C16: EXCAV.ZANJAS Y ZAPATA RT>2kg/cm2 H=2.0m | D16: m3 | E16: 1975.16 | F16: 50.99 | G16: =ROUND(E16*F16,2) -> 100713.41 | I16: 1876.4 | J16: 33.36 | K16: =ROUND(I16*J16,2) -> 62596.7 | N16: =SUM(O16:S16) -> 0
B17: 02.01.03 | C17: Rellenos
A18: 200 | B18: 02.01.03.01 | C18: RELLENO COMPACTADO C/EQUIPO MAT/PROPIO | D18: m3 | E18: 1197.91 | F18: 26.01 | G18: =ROUND(E18*F18,2) -> 31157.64 | I18: 1138.01 | J18: 15 | K18: =ROUND(I18*J18,2) -> 17070.15 | N18: =SUM(O18:S18) -> 0
B19: 02.01.04 | C19: Eliminacion de Material Excedente
A20: 200 | B20: 02.01.04.01 | C20: ACARREO INTERNO, MATERIAL PROCEDENTE DE EXCAVACIONES | D20: m3 | E20: 68.91 | F20: 17.53 | G20: =ROUND(E20*F20,2) -> 1207.99
A21: 200 | B21: 02.01.04.02 | C21: ELIMINACION MATERIAL EXCEDENTE ACARREADO | D21: M3 | E21: 68.91 | F21: 16.02 | G21: =ROUND(E21*F21,2) -> 1103.94
A22: 200 | B22: 02.01.04.03 | C22: ELIMINACION MATERIAL EXCEDENTE C/MAQUINA | D22: m3 | E22: 995.9 | F22: 21.84 | G22: =ROUND(E22*F22,2) -> 21750.46 | I22: 1118.06 | J22: 18.27 | K22: =ROUND(I22*J22,2) -> 20426.96 | N22: =SUM(O22:S22) -> 0
B23: 02.01.05 | C23: Nivelacion Interior y Apisonado
A24: 200 | B24: 02.01.05.01 | C24: ESCARIFICADO Y COMPACTACION CON PLANCHA COMPACTADORA e = 30 cm | D24: m2 | E24: 68.95 | F24: 4.72 | G24: =ROUND(E24*F24,2) -> 325.44 | I24: 70.33 | J24: 4.36 | K24: =ROUND(I24*J24,2) -> 306.64 | N24: =SUM(O24:S24) -> 0
A25: 200 | B25: 02.01.05.02 | C25: ESCARIFICADO Y COMPACTACION CON PLANCHA COMPACTADORA H=0.60m (02 CAPAS 30cm c/u) | D25: m2 | E25: 8.56 | F25: 7.85 | G25: =ROUND(E25*F25,2) -> 67.2 | I25: 8.73 | J25: 7.37 | K25: =ROUND(I25*J25,2) -> 64.34 | N25: =SUM(O25:S25) -> 0
A26: 200 | B26: 02.01.05.05 | C26: AFIRMADO DE 8" PARA PISOS,PATIOS Y VEREDAS,COMPACTADO. | D26: m2 | E26: 68.95 | F26: 15.19 | G26: =ROUND(E26*F26,2) -> 1047.35 | I26: 70.33 | J26: 11.5 | K26: =ROUND(I26*J26,2) -> 808.8 | N26: =SUM(O26:S26) -> 0
A27: 200 | B27: 02.01.05.06 | C27: AFIRMADO DE 12" EN PISOS INTERIOR/EXTERIOR,COMPACTADO. | D27: m2 | E27: 8.56 | F27: 21.79 | G27: =ROUND(E27*F27,2) -> 186.52 | I27: 8.73 | J27: 14.5 | K27: =ROUND(I27*J27,2) -> 126.59 | N27: =SUM(O27:S27) -> 0
B28: 02.02 | C28: Obras de Concreto Simple
B29: 02.02.01 | C29: Falsos Cimientos
A30: 300 | B30: 02.02.01.01 | C30: SUBCIMIENTO, SUBZAPATA MEZCLA 1:12 + 30 % P.G. | D30: m3 | E30: 323.69 | F30: 173.72 | G30: =ROUND(E30*F30,2) -> 56231.43 | I30: 330.16 | J30: 184.1 | K30: =ROUND(I30*J30,2) -> 60782.46 | N30: =SUM(O30:S30) -> 0
B31: 02.02.02 | C31: Cimientos
A32: 300 | B32: 02.02.02.02 | C32: CIMIENTOS CORRIDOS 1:10 + 30 % P.G. f'c >=100Kg/cm2 | D32: m3 | E32: 24.73 | F32: 179.78 | G32: =ROUND(E32*F32,2) -> 4445.96 | I32: 24.24 | J32: 182.46 | K32: =ROUND(I32*J32,2) -> 4422.83 | N32: =SUM(O32:S32) -> 0
A33: 400 | B33: 02.02.02.03 | C33: CIMIENTO CORRIDO - ENCOFRADO Y DESENCOFRADO | D33: m2 | E33: 23.09 | F33: 46.17 | G33: =ROUND(E33*F33,2) -> 1066.07 | I33: 22.63 | J33: 23.83 | K33: =ROUND(I33*J33,2) -> 539.27 | N33: =SUM(O33:S33) -> 0
A34: 300 | B34: 02.02.02.04 | C34: CALZADURA: CONCRETO C:H 1:10 + 30 % P.G. | D34: m3 | E34: 163.82 | F34: 179.78 | G34: =ROUND(E34*F34,2) -> 29451.56 | I34: 160.54 | J34: 207.85 | K34: =ROUND(I34*J34,2) -> 33368.24 | N34: =SUM(O34:S34) -> 0
A35: 400 | B35: 02.02.02.05 | C35: CALZADURA: ENCOFRADO Y DESENCOFRADO | D35: m2 | E35: 327.63 | F35: 37.47 | G35: =ROUND(E35*F35,2) -> 12276.3 | I35: 321.08 | J35: 26.53 | K35: =ROUND(I35*J35,2) -> 8518.25 | N35: =SUM(O35:S35) -> 0
B36: 02.02.03 | C36: Sobrecimientos
A37: 300 | B37: 02.02.03.01 | C37: SOBRECIMIENTO, CONCRETO 1:8 + 25% P.M. f'c >=100Kg/cm2 | D37: m3 | E37: 3.21 | F37: 260.59 | G37: =ROUND(E37*F37,2) -> 836.49 | I37: 3.15 | J37: 201.22 | K37: =ROUND(I37*J37,2) -> 633.84 | N37: =SUM(O37:S37) -> 0
A38: 400 | B38: 02.02.03.02 | C38: SOBRECIMIENTO, ENCOFRADO Y DESENCOFRADO | D38: m2 | E38: 43.95 | F38: 37.7 | G38: =ROUND(E38*F38,2) -> 1656.92 | I38: 43.07 | J38: 24.18 | K38: =ROUND(I38*J38,2) -> 1041.43 | N38: =SUM(O38:S38) -> 0
B39: 02.03 | C39: Obras de Concreto Armado
B40: 02.03.02 | C40: Zapatas
A41: 300 | B41: 02.03.02.01 | C41: ZAPATAS.- CONCRETO 210 kg/cm2 | D41: m3 | E41: 396.75 | F41: 292.79 | G41: =ROUND(E41*F41,2) -> 116164.43 | I41: 412.62 | J41: 286.6 | K41: =ROUND(I41*J41,2) -> 118256.89 | N41: =SUM(O41:S41) -> 0
A42: 500 | B42: 02.03.02.03 | C42: ZAPATAS.- ACERO Fy=4200 kg/cm2 | D42: KG | E42: 17534.91 | F42: 4.02 | G42: =ROUND(E42*F42,2) -> 70490.34 | I42: 17359.56 | J42: 3.4 | K42: =ROUND(I42*J42,2) -> 59022.5 | N42: =SUM(O42:S42) -> 0
B43: 02.03.05 | C43: Placas y Muros de Contención
A44: 300 | B44: 02.03.05.02 | C44: PLACAS, CONCRETO F'c=210 kg/cm2 - 1 piso | D44: m3 | E44: 6.69 | F44: 454.82 | G44: =ROUND(E44*F44,2) -> 3042.75 | I44: 6.62 | J44: 290.45 | K44: =ROUND(I44*J44,2) -> 1922.78 | N44: =SUM(O44:S44) -> 0
A45: 400 | B45: 02.03.05.04 | C45: PLACAS, ENCOFRADO Y DESENCOFRADO | D45: m2 | E45: 74.18 | F45: 59.78 | G45: =ROUND(E45*F45,2) -> 4434.48 | I45: 73.44 | J45: 33.69 | K45: =ROUND(I45*J45,2) -> 2474.19 | N45: =SUM(O45:S45) -> 0
A46: 500 | B46: 02.03.05.05 | C46: PLACAS, ACERO Fy=4200 kg/cm2 | D46: KG | E46: 419.35 | F46: 4.02 | G46: =ROUND(E46*F46,2) -> 1685.79 | I46: 415.16 | J46: 3.4 | K46: =ROUND(I46*J46,2) -> 1411.54 | N46: =SUM(O46:S46) -> 0
A47: 300 | B47: 02.03.05.07 | C47: MUROS DE CONTENC.- CONCRETO 210 kg/cm2 | D47: m3 | E47: 256.52 | F47: 417.41 | G47: =ROUND(E47*F47,2) -> 107074.01 | I47: 253.95 | J47: 328.19 | K47: =ROUND(I47*J47,2) -> 83343.85 | N47: =SUM(O47:S47) -> 0
A48: 400 | B48: 02.03.05.09 | C48: MUROS DE CONTENC.- ENCOF. Y DESENCOFRADO | D48: m2 | E48: 2096.19 | F48: 51.21 | G48: =ROUND(E48*F48,2) -> 107345.89 | I48: 2075.23 | J48: 30.97 | K48: =ROUND(I48*J48,2) -> 64269.87 | N48: =SUM(O48:S48) -> 0
A49: 500 | B49: 02.03.05.11 | C49: MUROS DE CONTENC.- ACERO Fy=4200 kg/cm2 | D49: kg | E49: 18595.1 | F49: 4.02 | G49: =ROUND(E49*F49,2) -> 74752.3
B50: 02.03.06 | C50: Columnas
A51: 300 | B51: 02.03.06.02 | C51: COLUMNAS - CONCRETO 210 KG/CM² - 1 PISO | D51: m3 | E51: 66.63 | F51: 442.62 | G51: =ROUND(E51*F51,2) -> 29491.77 | I51: 67.96 | J51: 291.23 | K51: =ROUND(I51*J51,2) -> 19791.99
A52: 400 | B52: 02.03.06.06 | C52: COLUMNAS.- ENCOFRADO Y DESENCOFRADO | D52: m2 | E52: 901.38 | F52: 60.48 | G52: =ROUND(E52*F52,2) -> 54515.46 | I52: 919.41 | J52: 37.49 | K52: =ROUND(I52*J52,2) -> 34468.68
A53: 500 | B53: 02.03.06.10 | C53: COLUMNAS.- ACERO Fy=4200 kg/cm2 | D53: KG | E53: 11604.02 | F53: 4.02 | G53: =ROUND(E53*F53,2) -> 46648.16 | I53: 11836.1 | J53: 3.4 | K53: =ROUND(I53*J53,2) -> 40242.74
B54: 02.03.07 | C54: Vigas
A55: 300 | B55: 02.03.07.02 | C55: VIGAS.- CONCRETO 210 kg/cm2 - 1 piso | D55: m3 | E55: 36.12 | F55: 325.93 | G55: =ROUND(E55*F55,2) -> 11772.59 | I55: 36.84 | J55: 294.5 | K55: =ROUND(I55*J55,2) -> 10849.38 | N55: =SUM(O55:S55) -> 0
A56: 400 | B56: 02.03.07.06 | C56: VIGAS.- ENCOFRADO Y DESENCOFRADO | D56: m2 | E56: 545.23 | F56: 70.38 | G56: =ROUND(E56*F56,2) -> 38373.29 | I56: 556.13 | J56: 43.56 | K56: =ROUND(I56*J56,2) -> 24225.02 | N56: =SUM(O56:S56) -> 0
A57: 500 | B57: 02.03.07.08 | C57: VIGAS.- ACERO Fy=4200 kg/cm2 | D57: KG | E57: 5144.6 | F57: 4.02 | G57: =ROUND(E57*F57,2) -> 20681.29 | I57: 5247.49 | J57: 3.4 | K57: =ROUND(I57*J57,2) -> 17841.47 | N57: =SUM(O57:S57) -> 0
B58: 02.03.08 | C58: Losas Macizas
A59: 300 | B59: 02.03.08.01 | C59: LOSAS MACIZAS.- CONC.210 kg/cm2 - 1 PISO | D59: M3 | E59: 0.63 | F59: 325.93 | G59: =ROUND(E59*F59,2) -> 205.34 | I59: 0.64 | J59: 294.5 | K59: =ROUND(I59*J59,2) -> 188.48 | N59: =SUM(O59:S59) -> 0
A60: 400 | B60: 02.03.08.03 | C60: LOSAS MACIZAS.- ENCOFRADO Y DESENCOFRADO | D60: m2 | E60: 6.54 | F60: 55.43 | G60: =ROUND(E60*F60,2) -> 362.51 | I60: 6.67 | J60: 33.34 | K60: =ROUND(I60*J60,2) -> 222.38 | N60: =SUM(O60:S60) -> 0
A61: 500 | B61: 02.03.08.04 | C61: LOSAS MACIZAS.- ACERO Fy=4,200 kg/cm2 | D61: KG | E61: 73.15 | F61: 4.02 | G61: =ROUND(E61*F61,2) -> 294.06 | I61: 74.61 | J61: 3.4 | K61: =ROUND(I61*J61,2) -> 253.67 | N61: =SUM(O61:S61) -> 0
B62: 02.03.09 | C62: Losas Aligeradas
A63: 300 | B63: 02.03.09.01 | C63: LOSA ALIGERADA - CONCRETO 210 kg/cm2 - 1 PISO | D63: m3 | E63: 2.13 | F63: 315.52 | G63: =ROUND(E63*F63,2) -> 672.06 | I63: 2.17 | J63: 294.5 | K63: =ROUND(I63*J63,2) -> 639.07 | N63: =SUM(O63:S63) -> 0
A64: 400 | B64: 02.03.09.03 | C64: LOSA ALIGERADA.- ENCOFRADO Y DESENCOFRADO | D64: m2 | E64: 24.72 | F64: 43.61 | G64: =ROUND(E64*F64,2) -> 1078.04 | I64: 25.21 | J64: 25.75 | K64: =ROUND(I64*J64,2) -> 649.16 | N64: =SUM(O64:S64) -> 0
A65: 500 | B65: 02.03.09.04 | C65: LOSA ALIGERADA.- ACERO Fy=4,200 kg/cm2 | D65: KG | E65: 93.93 | F65: 4.02 | G65: =ROUND(E65*F65,2) -> 377.6 | I65: 95.81 | J65: 3.4 | K65: =ROUND(I65*J65,2) -> 325.75 | N65: =SUM(O65:S65) -> 0
A66: 300 | B66: 02.03.09.05 | C66: LOSA ALIGERADA.- LADR. HUECO 15x30x30 | D66: und | E66: 205.92 | F66: 2.49 | G66: =ROUND(E66*F66,2) -> 512.74 | I66: 210.04 | J66: 2.39 | K66: =ROUND(I66*J66,2) -> 502 | N66: =SUM(O66:S66) -> 0
B67: 02.03.15 | C67: Gradas Armadas en Pisos
A68: 300 | B68: 02.03.15.01 | C68: GRADAS EN PISO, CONCRETO F'c=175 kg/cm2. | D68: m2 | E68: 12.31 | F68: 80.04 | G68: =ROUND(E68*F68,2) -> 985.29 | I68: 12.56 | J68: 59.8 | K68: =ROUND(I68*J68,2) -> 751.09 | N68: =SUM(O68:S68) -> 0
A69: 400 | B69: 02.03.15.03 | C69: GRADAS, ENCOFRADO Y DESENCOFRADO | D69: m2 | E69: 6.96 | F69: 41.15 | G69: =ROUND(E69*F69,2) -> 286.4 | I69: 7.1 | J69: 27.36 | K69: =ROUND(I69*J69,2) -> 194.26 | N69: =SUM(O69:S69) -> 0
A70: 500 | B70: 02.03.15.04 | C70: GRADAS EN PISO, ACERO fy=4200kg/cm2 | D70: kg | E70: 83.01 | F70: 4.02 | G70: =ROUND(E70*F70,2) -> 333.7 | I70: 84.67 | J70: 3.4 | K70: =ROUND(I70*J70,2) -> 287.88 | N70: =SUM(O70:S70) -> 0
C71: COSTO DIRECTO | G71: =SUM(G7:G70) -> 960724.52 | K71: =SUM(K7:K70) -> 696510.67 | T71: =SUM(T7:T70) -> 1374.45
C72: GASTOS GENERALES (10%) | G72: =ROUND(G71*0.1,2) -> 96072.45 | K72: =ROUND(K71*0.12,2) -> 83581.28 | T72: =ROUND(T71*0.12,2) -> 164.93
C73: UTILIDAD (8%) | G73: =ROUND(G71*0.08,2) -> 76857.96 | K73: 0
C74: SUBTOTAL | G74: =SUM(G71:G73) -> 1133654.9 | K74: =SUM(K71:K73) -> 780091.95 | T74: =SUM(T71:T73) -> 1539.38
C75: IGV (18.00%) | G75: =ROUND(G74*0.18,2) -> 204057.89 | K75: =ROUND(K74*0.18,2) -> 140416.55 | T75: =ROUND(T74*0.18,2) -> 277.09
C76: COSTO TOTAL (INC. IGV) | G76: =SUM(G74:G75) -> 1337712.8 | K76: =SUM(K74:K75) -> 920508.5 | T76: =SUM(T74:T75) -> 1816.47
K77: =+G76-K76 -> 417204.32
C79: TRABAJOS PRELIMINARES | D79: 100 | I79: Ejecutarla mediante cuadrillas de casa
C80: Cantidad de personal, equipos, materiales, viaticos, alquileres
C81: Definir precios
C82: MOVIMIENTO DE TIERRAS | D82: 200 | I82: Subcontrato a todo costo
C83: Pedir cotizaciones
C84: Definir precios
C86: OBRAS DE CONCRETO | D86: 300 | I86: Ejecutarla mediante cuadrillas de casa con equipos alquilados
C87: Planificar personal y buscar empresas que alquilen equipos
C88: Definir precios
C90: VARIOS | D90: 400 | I90: Casa
C91: Planificar personal, materiales y equipos
C92: Definir precios

Sheet COMPARATIVO
A1: ANALISIS DE AVANCE
A3: PROYECTO: | B3: I.E. N° 1182 "EL BOSQUE" - CERCO + INGRESOS Y CASETAS
E4: ANALISIS DE PRECIOS VENTA | L4: COSTO PREVISTO
A5: PC | B5: ITEM | C5: DESCRIPCION | D5: UND | E5: CONTRACTUAL | F5: VENTA ACTUAL | H5: VENTA PENDIENTE | J5: VENTA TOTAL | L5: PREVISTO | M5: PREVISTO ACTUAL | O5: PREVISTO PENDIENTE | Q5: PREVISTO TOTAL
E6: P.U. (S/.) | F6: METRADO EJECUTADO | G6: PARCIAL (S/.) | H6: METRADO POR EJECUT | I6: PARCIAL (S/.) | J6: METRADO CONTRATO | K6: PARCIAL (S/.) | L6: P.U. (S/.) | M6: METRADO EJECUTADO | N6: PARCIAL (S/.) | O6: METRADO POR EJECUT | P6: PARCIAL (S/.) | Q6: METRADO REAL | R6: PARCIAL (S/.)
B7: 01 | C7: OBRAS PROVISIONALES, TRABAJOS PRELIMINARES, SEGURIDAD Y SALUD
B8: 01.02 | C8: Trabajos Preliminares
B9: 01.02.04 | C9: Trazo, Niveles y Replanteo
A10: 100 | B10: 01.02.04.01 | C10: TRAZO Y REPLANTEO PRELIMINAR | D10: M2 | E10: =PRESUPUESTOS!F10 -> 2.04 | F10: =IF(Q10=0,0,((M10/Q10)*J10)) -> 0 | G10: =ROUND(E10*F10,2) -> 0 | H10: =J10-F10 -> 897.34 | I10: =ROUND(E10*H10,2) -> 1830.57 | J10: =PRESUPUESTOS!E10 -> 897.34 | K10: =ROUND(E10*J10,2) -> 1830.57 | L10: =PRESUPUESTOS!N10 -> 1.47 | N10: =ROUND(M10*L10,2) -> 0 | O10: =Q10-M10 -> 935 | P10: =ROUND(O10*L10,2) -> 1374.45 | Q10: =PRESUPUESTOS!M10 -> 935 | R10: =ROUND(Q10*L10,2) -> 1374.45
A11: 100 | B11: 01.02.04.02 | C11: TRAZO Y REPLANTEO DURANTE EL PROCESO | D11: m2 | E11: =PRESUPUESTOS!F11 -> 2.04 | F11: =IF(Q11=0,0,((M11/Q11)*J11)) -> 0 | G11: =ROUND(E11*F11,2) -> 0 | H11: =J11-F11 -> 897.34 | I11: =ROUND(E11*H11,2) -> 1830.57 | J11: =PRESUPUESTOS!E11 -> 897.34 | K11: =ROUND(E11*J11,2) -> 1830.57 | L11: =PRESUPUESTOS!N11 -> 0 | N11: =ROUND(M11*L11,2) -> 0 | O11: =Q11-M11 -> 0 | P11: =ROUND(O11*L11,2) -> 0 | Q11: =PRESUPUESTOS!M11 -> 0 | R11: =ROUND(Q11*L11,2) -> 0
B12: 02 | C12: ESTRUCTURAS
B13: 02.01 | C13: Movimiento de Tierras
B14: 02.01.01 | C14: Excavaciones
A15: 200 | B15: 02.01.01.01 | C15: EXCAV.ZANJAS Y ZAPATA RT>2kg/cm2 H=1.5m | D15: m3 | E15: =PRESUPUESTOS!F15 -> 46.74 | F15: =IF(Q15=0,0,((M15/Q15)*J15)) -> 0 | G15: =ROUND(E15*F15,2) -> 0 | H15: =J15-F15 -> 41.9 | I15: =ROUND(E15*H15,2) -> 1958.41 | J15: =PRESUPUESTOS!E15 -> 41.9 | K15: =ROUND(E15*J15,2) -> 1958.41 | L15: =PRESUPUESTOS!N15 -> 0 | N15: =ROUND(M15*L15,2) -> 0 | O15: =Q15-M15 -> 0 | P15: =ROUND(O15*L15,2) -> 0 | Q15: =PRESUPUESTOS!M15 -> 0 | R15: =ROUND(Q15*L15,2) -> 0
A16: 200 | B16: 02.01.01.02 | C16: EXCAV.ZANJAS Y ZAPATA RT>2kg/cm2 H=2.0m | D16: m3 | E16: =PRESUPUESTOS!F16 -> 50.99 | F16: =IF(Q16=0,0,((M16/Q16)*J16)) -> 0 | G16: =ROUND(E16*F16,2) -> 0 | H16: =J16-F16 -> 1975.16 | I16: =ROUND(E16*H16,2) -> 100713.41 | J16: =PRESUPUESTOS!E16 -> 1975.16 | K16: =ROUND(E16*J16,2) -> 100713.41 | L16: =PRESUPUESTOS!N16 -> 0 | N16: =ROUND(M16*L16,2) -> 0 | O16: =Q16-M16 -> 0 | P16: =ROUND(O16*L16,2) -> 0 | Q16: =PRESUPUESTOS!M16 -> 0 | R16: =ROUND(Q16*L16,2) -> 0
B17: 02.01.03 | C17: Rellenos
A18: 200 | B18: 02.01.03.01 | C18: RELLENO COMPACTADO C/EQUIPO MAT/PROPIO | D18: m3 | E18: =PRESUPUESTOS!F18 -> 26.01 | F18: =IF(Q18=0,0,((M18/Q18)*J18)) -> 0 | G18: =ROUND(E18*F18,2) -> 0 | H18: =J18-F18 -> 1197.91 | I18: =ROUND(E18*H18,2) -> 31157.64 | J18: =PRESUPUESTOS!E18 -> 1197.91 | K18: =ROUND(E18*J18,2) -> 31157.64 | L18: =PRESUPUESTOS!N18 -> 0 | N18: =ROUND(M18*L18,2) -> 0 | O18: =Q18-M18 -> 0 | P18: =ROUND(O18*L18,2) -> 0 | Q18: =PRESUPUESTOS!M18 -> 0 | R18: =ROUND(Q18*L18,2) -> 0
B19: 02.01.04 | C19: Eliminacion de Material Excedente
A20: 200 | B20: 02.01.04.01 | C20: ACARREO INTERNO, MATERIAL PROCEDENTE DE EXCAVACIONES | D20: m3 | E20: =PRESUPUESTOS!F20 -> 17.53 | F20: =IF(Q20=0,0,((M20/Q20)*J20)) -> 0 | G20: =ROUND(E20*F20,2) -> 0 | H20: =J20-F20 -> 68.91 | I20: =ROUND(E20*H20,2) -> 1207.99 | J20: =PRESUPUESTOS!E20 -> 68.91 | K20: =ROUND(E20*J20,2) -> 1207.99 | L20: =PRESUPUESTOS!N20 -> 0 | N20: =ROUND(M20*L20,2) -> 0 | O20: =Q20-M20 -> 0 | P20: =ROUND(O20*L20,2) -> 0 | Q20: =PRESUPUESTOS!M20 -> 0 | R20: =ROUND(Q20*L20,2) -> 0
A21: 200 | B21: 02.01.04.02 | C21: ELIMINACION MATERIAL EXCEDENTE ACARREADO | D21: M3 | E21: =PRESUPUESTOS!F21 -> 16.02 | F21: =IF(Q21=0,0,((M21/Q21)*J21)) -> 0 | G21: =ROUND(E21*F21,2) -> 0 | H21: =J21-F21 -> 68.91 | I21: =ROUND(E21*H21,2) -> 1103.94 | J21: =PRESUPUESTOS!E21 -> 68.91 | K21: =ROUND(E21*J21,2) -> 1103.94 | L21: =PRESUPUESTOS!N21 -> 0 | N21: =ROUND(M21*L21,2) -> 0 | O21: =Q21-M21 -> 0 | P21: =ROUND(O21*L21,2) -> 0 | Q21: =PRESUPUESTOS!M21 -> 0 | R21: =ROUND(Q21*L21,2) -> 0
A22: 200 | B22: 02.01.04.03 | C22: ELIMINACION MATERIAL EXCEDENTE C/MAQUINA | D22: m3 | E22: =PRESUPUESTOS!F22 -> 21.84 | F22: =IF(Q22=0,0,((M22/Q22)*J22)) -> 0 | G22: =ROUND(E22*F22,2) -> 0 | H22: =J22-F22 -> 995.9 | I22: =ROUND(E22*H22,2) -> 21750.46 | J22: =PRESUPUESTOS!E22 -> 995.9 | K22: =ROUND(E22*J22,2) -> 21750.46 | L22: =PRESUPUESTOS!N22 -> 0 | N22: =ROUND(M22*L22,2) -> 0 | O22: =Q22-M22 -> 0 | P22: =ROUND(O22*L22,2) -> 0 | Q22: =PRESUPUESTOS!M22 -> 0 | R22: =ROUND(Q22*L22,2) -> 0
B23: 02.01.05 | C23: Nivelacion Interior y Apisonado | E23: =PRESUPUESTOS!F23 -> 0 | F23: =IF(Q23=0,0,((M23/Q23)*J23)) -> 0 | G23: =ROUND(E23*F23,2) -> 0 | H23: =J23-F23 -> 0 | I23: =ROUND(E23*H23,2) -> 0 | J23: =PRESUPUESTOS!E23 -> 0 | K23: =ROUND(E23*J23,2) -> 0 | L23: =PRESUPUESTOS!N23 -> 0 | N23: =ROUND(M23*L23,2) -> 0 | O23: =Q23-M23 -> 0 | P23: =ROUND(O23*L23,2) -> 0 | Q23: =PRESUPUESTOS!M23 -> 0 | R23: =ROUND(Q23*L23,2) -> 0
A24: 200 | B24: 02.01.05.01 | C24: ESCARIFICADO Y COMPACTACION CON PLANCHA COMPACTADORA e = 30 cm | D24: m2 | E24: =PRESUPUESTOS!F24 -> 4.72 | F24: =IF(Q24=0,0,((M24/Q24)*J24)) -> 0 | G24: =ROUND(E24*F24,2) -> 0 | H24: =J24-F24 -> 68.95 | I24: =ROUND(E24*H24,2) -> 325.44 | J24: =PRESUPUESTOS!E24 -> 68.95 | K24: =ROUND(E24*J24,2) -> 325.44 | L24: =PRESUPUESTOS!N24 -> 0 | N24: =ROUND(M24*L24,2) -> 0 | O24: =Q24-M24 -> 0 | P24: =ROUND(O24*L24,2) -> 0 | Q24: =PRESUPUESTOS!M24 -> 0 | R24: =ROUND(Q24*L24,2) -> 0
A25: 200 | B25: 02.01.05.02 | C25: ESCARIFICADO Y COMPACTACION CON PLANCHA COMPACTADORA H=0.60m (02 CAPAS 30cm c/u) | D25: m2 | E25: =PRESUPUESTOS!F25 -> 7.85 | F25: =IF(Q25=0,0,((M25/Q25)*J25)) -> 0 | G25: =ROUND(E25*F25,2) -> 0 | H25: =J25-F25 -> 8.56 | I25: =ROUND(E25*H25,2) -> 67.2 | J25: =PRESUPUESTOS!E25 -> 8.56 | K25: =ROUND(E25*J25,2) -> 67.2 | L25: =PRESUPUESTOS!N25 -> 0 | N25: =ROUND(M25*L25,2) -> 0 | O25: =Q25-M25 -> 0 | P25: =ROUND(O25*L25,2) -> 0 | Q25: =PRESUPUESTOS!M25 -> 0 | R25: =ROUND(Q25*L25,2) -> 0
A26: 200 | B26: 02.01.05.05 | C26: AFIRMADO DE 8" PARA PISOS,PATIOS Y VEREDAS,COMPACTADO. | D26: m2 | E26: =PRESUPUESTOS!F26 -> 15.19 | F26: =IF(Q26=0,0,((M26/Q26)*J26)) -> 0 | G26: =ROUND(E26*F26,2) -> 0 | H26: =J26-F26 -> 68.95 | I26: =ROUND(E26*H26,2) -> 1047.35 | J26: =PRESUPUESTOS!E26 -> 68.95 | K26: =ROUND(E26*J26,2) -> 1047.35 | L26: =PRESUPUESTOS!N26 -> 0 | N26: =ROUND(M26*L26,2) -> 0 | O26: =Q26-M26 -> 0 | P26: =ROUND(O26*L26,2) -> 0 | Q26: =PRESUPUESTOS!M26 -> 0 | R26: =ROUND(Q26*L26,2) -> 0
A27: 200 | B27: 02.01.05.06 | C27: AFIRMADO DE 12" EN PISOS INTERIOR/EXTERIOR,COMPACTADO. | D27: m2 | E27: =PRESUPUESTOS!F27 -> 21.79 | F27: =IF(Q27=0,0,((M27/Q27)*J27)) -> 0 | G27: =ROUND(E27*F27,2) -> 0 | H27: =J27-F27 -> 8.56 | I27: =ROUND(E27*H27,2) -> 186.52 | J27: =PRESUPUESTOS!E27 -> 8.56 | K27: =ROUND(E27*J27,2) -> 186.52 | L27: =PRESUPUESTOS!N27 -> 0 | N27: =ROUND(M27*L27,2) -> 0 | O27: =Q27-M27 -> 0 | P27: =ROUND(O27*L27,2) -> 0 | Q27: =PRESUPUESTOS!M27 -> 0 | R27: =ROUND(Q27*L27,2) -> 0
B28: 02.02 | C28: Obras de Concreto Simple | E28: =PRESUPUESTOS!F28 -> 0 | F28: =IF(Q28=0,0,((M28/Q28)*J28)) -> 0 | G28: =ROUND(E28*F28,2) -> 0 | H28: =J28-F28 -> 0 | I28: =ROUND(E28*H28,2) -> 0 | J28: =PRESUPUESTOS!E28 -> 0 | K28: =ROUND(E28*J28,2) -> 0 | L28: =PRESUPUESTOS!N28 -> 0 | N28: =ROUND(M28*L28,2) -> 0 | O28: =Q28-M28 -> 0 | P28: =ROUND(O28*L28,2) -> 0 | Q28: =PRESUPUESTOS!M28 -> 0 | R28: =ROUND(Q28*L28,2) -> 0
B29: 02.02.01 | C29: Falsos Cimientos | E29: =PRESUPUESTOS!F29 -> 0 | F29: =IF(Q29=0,0,((M29/Q29)*J29)) -> 0 | G29: =ROUND(E29*F29,2) -> 0 | H29: =J29-F29 -> 0 | I29: =ROUND(E29*H29,2) -> 0 | J29: =PRESUPUESTOS!E29 -> 0 | K29: =ROUND(E29*J29,2) -> 0 | L29: =PRESUPUESTOS!N29 -> 0 | N29: =ROUND(M29*L29,2) -> 0 | O29: =Q29-M29 -> 0 | P29: =ROUND(O29*L29,2) -> 0 | Q29: =PRESUPUESTOS!M29 -> 0 | R29: =ROUND(Q29*L29,2) -> 0
A30: 300 | B30: 02.02.01.01 | C30: SUBCIMIENTO, SUBZAPATA MEZCLA 1:12 + 30 % P.G. | D30: m3 | E30: =PRESUPUESTOS!F30 -> 173.72 | F30: =IF(Q30=0,0,((M30/Q30)*J30)) -> 0 | G30: =ROUND(E30*F30,2) -> 0 | H30: =J30-F30 -> 323.69 | I30: =ROUND(E30*H30,2) -> 56231.43 | J30: =PRESUPUESTOS!E30 -> 323.69 | K30: =ROUND(E30*J30,2) -> 56231.43 | L30: =PRESUPUESTOS!N30 -> 0 | N30: =ROUND(M30*L30,2) -> 0 | O30: =Q30-M30 -> 0 | P30: =ROUND(O30*L30,2) -> 0 | Q30: =PRESUPUESTOS!M30 -> 0 | R30: =ROUND(Q30*L30,2) -> 0
B31: 02.02.02 | C31: Cimientos | E31: =PRESUPUESTOS!F31 -> 0 | F31: =IF(Q31=0,0,((M31/Q31)*J31)) -> 0 | G31: =ROUND(E31*F31,2) -> 0 | H31: =J31-F31 -> 0 | I31: =ROUND(E31*H31,2) -> 0 | J31: =PRESUPUESTOS!E31 -> 0 | K31: =ROUND(E31*J31,2) -> 0 | L31: =PRESUPUESTOS!N31 -> 0 | N31: =ROUND(M31*L31,2) -> 0 | O31: =Q31-M31 -> 0 | P31: =ROUND(O31*L31,2) -> 0 | Q31: =PRESUPUESTOS!M31 -> 0 | R31: =ROUND(Q31*L31,2) -> 0
A32: 300 | B32: 02.02.02.02 | C32: CIMIENTOS CORRIDOS 1:10 + 30 % P.G. f'c >=100Kg/cm2 | D32: m3 | E32: =PRESUPUESTOS!F32 -> 179.78 | F32: =IF(Q32=0,0,((M32/Q32)*J32)) -> 0 | G32: =ROUND(E32*F32,2) -> 0 | H32: =J32-F32 -> 24.73 | I32: =ROUND(E32*H32,2) -> 4445.96 | J32: =PRESUPUESTOS!E32 -> 24.73 | K32: =ROUND(E32*J32,2) -> 4445.96 | L32: =PRESUPUESTOS!N32 -> 0 | N32: =ROUND(M32*L32,2) -> 0 | O32: =Q32-M32 -> 0 | P32: =ROUND(O32*L32,2) -> 0 | Q32: =PRESUPUESTOS!M32 -> 0 | R32: =ROUND(Q32*L32,2) -> 0
A33: 400 | B33: 02.02.02.03 | C33: CIMIENTO CORRIDO - ENCOFRADO Y DESENCOFRADO | D33: m2 | E33: =PRESUPUESTOS!F33 -> 46.17 | F33: =IF(Q33=0,0,((M33/Q33)*J33)) -> 0 | G33: =ROUND(E33*F33,2) -> 0 | H33: =J33-F33 -> 23.09 | I33: =ROUND(E33*H33,2) -> 1066.07 | J33: =PRESUPUESTOS!E33 -> 23.09 | K33: =ROUND(E33*J33,2) -> 1066.07 | L33: =PRESUPUESTOS!N33 -> 0 | N33: =ROUND(M33*L33,2) -> 0 | O33: =Q33-M33 -> 0 | P33: =ROUND(O33*L33,2) -> 0 | Q33: =PRESUPUESTOS!M33 -> 0 | R33: =ROUND(Q33*L33,2) -> 0
A34: 300 | B34: 02.02.02.04 | C34: CALZADURA: CONCRETO C:H 1:10 + 30 % P.G. | D34: m3 | E34: =PRESUPUESTOS!F34 -> 179.78 | F34: =IF(Q34=0,0,((M34/Q34)*J34)) -> 0 | G34: =ROUND(E34*F34,2) -> 0 | H34: =J34-F34 -> 163.82 | I34: =ROUND(E34*H34,2) -> 29451.56 | J34: =PRESUPUESTOS!E34 -> 163.82 | K34: =ROUND(E34*J34,2) -> 29451.56 | L34: =PRESUPUESTOS!N34 -> 0 | N34: =ROUND(M34*L34,2) -> 0 | O34: =Q34-M34 -> 0 | P34: =ROUND(O34*L34,2) -> 0 | Q34: =PRESUPUESTOS!M34 -> 0 | R34: =ROUND(Q34*L34,2) -> 0
A35: 400 | B35: 02.02.02.05 | C35: CALZADURA: ENCOFRADO Y DESENCOFRADO | D35: m2 | E35: =PRESUPUESTOS!F35 -> 37.47 | F35: =IF(Q35=0,0,((M35/Q35)*J35)) -> 0 | G35: =ROUND(E35*F35,2) -> 0 | H35: =J35-F35 -> 327.63 | I35: =ROUND(E35*H35,2) -> 12276.3 | J35: =PRESUPUESTOS!E35 -> 327.63 | K35: =ROUND(E35*J35,2) -> 12276.3 | L35: =PRESUPUESTOS!N35 -> 0 | N35: =ROUND(M35*L35,2) -> 0 | O35: =Q35-M35 -> 0 | P35: =ROUND(O35*L35,2) -> 0 | Q35: =PRESUPUESTOS!M35 -> 0 | R35: =ROUND(Q35*L35,2) -> 0
B36: 02.02.03 | C36: Sobrecimientos | E36: =PRESUPUESTOS!F36 -> 0 | F36: =IF(Q36=0,0,((M36/Q36)*J36)) -> 0 | G36: =ROUND(E36*F36,2) -> 0 | H36: =J36-F36 -> 0 | I36: =ROUND(E36*H36,2) -> 0 | J36: =PRESUPUESTOS!E36 -> 0 | K36: =ROUND(E36*J36,2) -> 0 | L36: =PRESUPUESTOS!N36 -> 0 | N36: =ROUND(M36*L36,2) -> 0 | O36: =Q36-M36 -> 0 | P36: =ROUND(O36*L36,2) -> 0 | Q36: =PRESUPUESTOS!M36 -> 0 | R36: =ROUND(Q36*L36,2) -> 0
A37: 300 | B37: 02.02.03.01 | C37: SOBRECIMIENTO, CONCRETO 1:8 + 25% P.M. f'c >=100Kg/cm2 | D37: m3 | E37: =PRESUPUESTOS!F37 -> 260.59 | F37: =IF(Q37=0,0,((M37/Q37)*J37)) -> 0 | G37: =ROUND(E37*F37,2) -> 0 | H37: =J37-F37 -> 3.21 | I37: =ROUND(E37*H37,2) -> 836.49 | J37: =PRESUPUESTOS!E37 -> 3.21 | K37: =ROUND(E37*J37,2) -> 836.49 | L37: =PRESUPUESTOS!N37 -> 0 | N37: =ROUND(M37*L37,2) -> 0 | O37: =Q37-M37 -> 0 | P37: =ROUND(O37*L37,2) -> 0 | Q37: =PRESUPUESTOS!M37 -> 0 | R37: =ROUND(Q37*L37,2) -> 0
A38: 400 | B38: 02.02.03.02 | C38: SOBRECIMIENTO, ENCOFRADO Y DESENCOFRADO | D38: m2 | E38: =PRESUPUESTOS!F38 -> 37.7 | F38: =IF(Q38=0,0,((M38/Q38)*J38)) -> 0 | G38: =ROUND(E38*F38,2) -> 0 | H38: =J38-F38 -> 43.95 | I38: =ROUND(E38*H38,2) -> 1656.92 | J38: =PRESUPUESTOS!E38 -> 43.95 | K38: =ROUND(E38*J38,2) -> 1656.92 | L38: =PRESUPUESTOS!N38 -> 0 | N38: =ROUND(M38*L38,2) -> 0 | O38: =Q38-M38 -> 0 | P38: =ROUND(O38*L38,2) -> 0 | Q38: =PRESUPUESTOS!M38 -> 0 | R38: =ROUND(Q38*L38,2) -> 0
B39: 02.03 | C39: Obras de Concreto Armado | E39: =PRESUPUESTOS!F39 -> 0 | F39: =IF(Q39=0,0,((M39/Q39)*J39)) -> 0 | G39: =ROUND(E39*F39,2) -> 0 | H39: =J39-F39 -> 0 | I39: =ROUND(E39*H39,2) -> 0 | J39: =PRESUPUESTOS!E39 -> 0 | K39: =ROUND(E39*J39,2) -> 0 | L39: =PRESUPUESTOS!N39 -> 0 | N39: =ROUND(M39*L39,2) -> 0 | O39: =Q39-M39 -> 0 | P39: =ROUND(O39*L39,2) -> 0 | Q39: =PRESUPUESTOS!M39 -> 0 | R39: =ROUND(Q39*L39,2) -> 0
B40: 02.03.02 | C40: Zapatas | E40: =PRESUPUESTOS!F40 -> 0 | F40: =IF(Q40=0,0,((M40/Q40)*J40)) -> 0 | G40: =ROUND(E40*F40,2) -> 0 | H40: =J40-F40 -> 0 | I40: =ROUND(E40*H40,2) -> 0 | J40: =PRESUPUESTOS!E40 -> 0 | K40: =ROUND(E40*J40,2) -> 0 | L40: =PRESUPUESTOS!N40 -> 0 | N40: =ROUND(M40*L40,2) -> 0 | O40: =Q40-M40 -> 0 | P40: =ROUND(O40*L40,2) -> 0 | Q40: =PRESUPUESTOS!M40 -> 0 | R40: =ROUND(Q40*L40,2) -> 0
A41: 300 | B41: 02.03.02.01 | C41: ZAPATAS.- CONCRETO 210 kg/cm2 | D41: m3 | E41: =PRESUPUESTOS!F41 -> 292.79 | F41: =IF(Q41=0,0,((M41/Q41)*J41)) -> 0 | G41: =ROUND(E41*F41,2) -> 0 | H41: =J41-F41 -> 396.75 | I41: =ROUND(E41*H41,2) -> 116164.43 | J41: =PRESUPUESTOS!E41 -> 396.75 | K41: =ROUND(E41*J41,2) -> 116164.43 | L41: =PRESUPUESTOS!N41 -> 0 | N41: =ROUND(M41*L41,2) -> 0 | O41: =Q41-M41 -> 0 | P41: =ROUND(O41*L41,2) -> 0 | Q41: =PRESUPUESTOS!M41 -> 0 | R41: =ROUND(Q41*L41,2) -> 0
A42: 500 | B42: 02.03.02.03 | C42: ZAPATAS.- ACERO Fy=4200 kg/cm2 | D42: KG | E42: =PRESUPUESTOS!F42 -> 4.02 | F42: =IF(Q42=0,0,((M42/Q42)*J42)) -> 0 | G42: =ROUND(E42*F42,2) -> 0 | H42: =J42-F42 -> 17534.91 | I42: =ROUND(E42*H42,2) -> 70490.34 | J42: =PRESUPUESTOS!E42 -> 17534.91 | K42: =ROUND(E42*J42,2) -> 70490.34 | L42: =PRESUPUESTOS!N42 -> 0 | N42: =ROUND(M42*L42,2) -> 0 | O42: =Q42-M42 -> 0 | P42: =ROUND(O42*L42,2) -> 0 | Q42: =PRESUPUESTOS!M42 -> 0 | R42: =ROUND(Q42*L42,2) -> 0
B43: 02.03.05 | C43: Placas y Muros de Contención | E43: =PRESUPUESTOS!F43 -> 0 | F43: =IF(Q43=0,0,((M43/Q43)*J43)) -> 0 | G43: =ROUND(E43*F43,2) -> 0 | H43: =J43-F43 -> 0 | I43: =ROUND(E43*H43,2) -> 0 | J43: =PRESUPUESTOS!E43 -> 0 | K43: =ROUND(E43*J43,2) -> 0 | L43: =PRESUPUESTOS!N43 -> 0 | N43: =ROUND(M43*L43,2) -> 0 | O43: =Q43-M43 -> 0 | P43: =ROUND(O43*L43,2) -> 0 | Q43: =PRESUPUESTOS!M43 -> 0 | R43: =ROUND(Q43*L43,2) -> 0
A44: 300 | B44: 02.03.05.02 | C44: PLACAS, CONCRETO F'c=210 kg/cm2 - 1 piso | D44: m3 | E44: =PRESUPUESTOS!F44 -> 454.82 | F44: =IF(Q44=0,0,((M44/Q44)*J44)) -> 0 | G44: =ROUND(E44*F44,2) -> 0 | H44: =J44-F44 -> 6.69 | I44: =ROUND(E44*H44,2) -> 3042.75 | J44: =PRESUPUESTOS!E44 -> 6.69 | K44: =ROUND(E44*J44,2) -> 3042.75 | L44: =PRESUPUESTOS!N44 -> 0 | N44: =ROUND(M44*L44,2) -> 0 | O44: =Q44-M44 -> 0 | P44: =ROUND(O44*L44,2) -> 0 | Q44: =PRESUPUESTOS!M44 -> 0 | R44: =ROUND(Q44*L44,2) -> 0
A45: 400 | B45: 02.03.05.04 | C45: PLACAS, ENCOFRADO Y DESENCOFRADO | D45: m2 | E45: =PRESUPUESTOS!F45 -> 59.78 | F45: =IF(Q45=0,0,((M45/Q45)*J45)) -> 0 | G45: =ROUND(E45*F45,2) -> 0 | H45: =J45-F45 -> 74.18 | I45: =ROUND(E45*H45,2) -> 4434.48 | J45: =PRESUPUESTOS!E45 -> 74.18 | K45: =ROUND(E45*J45,2) -> 4434.48 | L45: =PRESUPUESTOS!N45 -> 0 | N45: =ROUND(M45*L45,2) -> 0 | O45: =Q45-M45 -> 0 | P45: =ROUND(O45*L45,2) -> 0 | Q45: =PRESUPUESTOS!M45 -> 0 | R45: =ROUND(Q45*L45,2) -> 0
A46: 500 | B46: 02.03.05.05 | C46: PLACAS, ACERO Fy=4200 kg/cm2 | D46: KG | E46: =PRESUPUESTOS!F46 -> 4.02 | F46: =IF(Q46=0,0,((M46/Q46)*J46)) -> 0 | G46: =ROUND(E46*F46,2) -> 0 | H46: =J46-F46 -> 419.35 | I46: =ROUND(E46*H46,2) -> 1685.79 | J46: =PRESUPUESTOS!E46 -> 419.35 | K46: =ROUND(E46*J46,2) -> 1685.79 | L46: =PRESUPUESTOS!N46 -> 0 | N46: =ROUND(M46*L46,2) -> 0 | O46: =Q46-M46 -> 0 | P46: =ROUND(O46*L46,2) -> 0 | Q46: =PRESUPUESTOS!M46 -> 0 | R46: =ROUND(Q46*L46,2) -> 0
A47: 300 | B47: 02.03.05.07 | C47: MUROS DE CONTENC.- CONCRETO 210 kg/cm2 | D47: m3 | E47: =PRESUPUESTOS!F47 -> 417.41 | F47: =IF(Q47=0,0,((M47/Q47)*J47)) -> 0 | G47: =ROUND(E47*F47,2) -> 0 | H47: =J47-F47 -> 256.52 | I47: =ROUND(E47*H47,2) -> 107074.01 | J47: =PRESUPUESTOS!E47 -> 256.52 | K47: =ROUND(E47*J47,2) -> 107074.01 | L47: =PRESUPUESTOS!N47 -> 0 | N47: =ROUND(M47*L47,2) -> 0 | O47: =Q47-M47 -> 0 | P47: =ROUND(O47*L47,2) -> 0 | Q47: =PRESUPUESTOS!M47 -> 0 | R47: =ROUND(Q47*L47,2) -> 0
A48: 400 | B48: 02.03.05.09 | C48: MUROS DE CONTENC.- ENCOF. Y DESENCOFRADO | D48: m2 | E48: =PRESUPUESTOS!F48 -> 51.21 | F48: =IF(Q48=0,0,((M48/Q48)*J48)) -> 0 | G48: =ROUND(E48*F48,2) -> 0 | H48: =J48-F48 -> 2096.19 | I48: =ROUND(E48*H48,2) -> 107345.89 | J48: =PRESUPUESTOS!E48 -> 2096.19 | K48: =ROUND(E48*J48,2) -> 107345.89 | L48: =PRESUPUESTOS!N48 -> 0 | N48: =ROUND(M48*L48,2) -> 0 | O48: =Q48-M48 -> 0 | P48: =ROUND(O48*L48,2) -> 0 | Q48: =PRESUPUESTOS!M48 -> 0 | R48: =ROUND(Q48*L48,2) -> 0
A49: 500 | B49: 02.03.05.11 | C49: MUROS DE CONTENC.- ACERO Fy=4200 kg/cm2 | D49: kg | E49: =PRESUPUESTOS!F49 -> 4.02 | F49: =IF(Q49=0,0,((M49/Q49)*J49)) -> 0 | G49: =ROUND(E49*F49,2) -> 0 | H49: =J49-F49 -> 18595.1 | I49: =ROUND(E49*H49,2) -> 74752.3 | J49: =PRESUPUESTOS!E49 -> 18595.1 | K49: =ROUND(E49*J49,2) -> 74752.3 | L49: =PRESUPUESTOS!N49 -> 0 | N49: =ROUND(M49*L49,2) -> 0 | O49: =Q49-M49 -> 0 | P49: =ROUND(O49*L49,2) -> 0 | Q49: =PRESUPUESTOS!M49 -> 0 | R49: =ROUND(Q49*L49,2) -> 0
B50: 02.03.06 | C50: Columnas | E50: =PRESUPUESTOS!F50 -> 0 | F50: =IF(Q50=0,0,((M50/Q50)*J50)) -> 0 | G50: =ROUND(E50*F50,2) -> 0 | H50: =J50-F50 -> 0 | I50: =ROUND(E50*H50,2) -> 0 | J50: =PRESUPUESTOS!E50 -> 0 | K50: =ROUND(E50*J50,2) -> 0 | L50: =PRESUPUESTOS!N50 -> 0 | N50: =ROUND(M50*L50,2) -> 0 | O50: =Q50-M50 -> 0 | P50: =ROUND(O50*L50,2) -> 0 | Q50: =PRESUPUESTOS!M50 -> 0 | R50: =ROUND(Q50*L50,2) -> 0
A51: 300 | B51: 02.03.06.02 | C51: COLUMNAS - CONCRETO 210 KG/CM² - 1 PISO | D51: m3 | E51: =PRESUPUESTOS!F51 -> 442.62 | F51: =IF(Q51=0,0,((M51/Q51)*J51)) -> 0 | G51: =ROUND(E51*F51,2) -> 0 | H51: =J51-F51 -> 66.63 | I51: =ROUND(E51*H51,2) -> 29491.77 | J51: =PRESUPUESTOS!E51 -> 66.63 | K51: =ROUND(E51*J51,2) -> 29491.77 | L51: =PRESUPUESTOS!N51 -> 0 | N51: =ROUND(M51*L51,2) -> 0 | O51: =Q51-M51 -> 0 | P51: =ROUND(O51*L51,2) -> 0 | Q51: =PRESUPUESTOS!M51 -> 0 | R51: =ROUND(Q51*L51,2) -> 0
A52: 400 | B52: 02.03.06.06 | C52: COLUMNAS.- ENCOFRADO Y DESENCOFRADO | D52: m2 | E52: =PRESUPUESTOS!F52 -> 60.48 | F52: =IF(Q52=0,0,((M52/Q52)*J52)) -> 0 | G52: =ROUND(E52*F52,2) -> 0 | H52: =J52-F52 -> 901.38 | I52: =ROUND(E52*H52,2) -> 54515.46 | J52: =PRESUPUESTOS!E52 -> 901.38 | K52: =ROUND(E52*J52,2) -> 54515.46 | L52: =PRESUPUESTOS!N52 -> 0 | N52: =ROUND(M52*L52,2) -> 0 | O52: =Q52-M52 -> 0 | P52: =ROUND(O52*L52,2) -> 0 | Q52: =PRESUPUESTOS!M52 -> 0 | R52: =ROUND(Q52*L52,2) -> 0
A53: 500 | B53: 02.03.06.10 | C53: COLUMNAS.- ACERO Fy=4200 kg/cm2 | D53: KG | E53: =PRESUPUESTOS!F53 -> 4.02 | F53: =IF(Q53=0,0,((M53/Q53)*J53)) -> 0 | G53: =ROUND(E53*F53,2) -> 0 | H53: =J53-F53 -> 11604.02 | I53: =ROUND(E53*H53,2) -> 46648.16 | J53: =PRESUPUESTOS!E53 -> 11604.02 | K53: =ROUND(E53*J53,2) -> 46648.16 | L53: =PRESUPUESTOS!N53 -> 0 | N53: =ROUND(M53*L53,2) -> 0 | O53: =Q53-M53 -> 0 | P53: =ROUND(O53*L53,2) -> 0 | Q53: =PRESUPUESTOS!M53 -> 0 | R53: =ROUND(Q53*L53,2) -> 0
B54: 02.03.07 | C54: Vigas | E54: =PRESUPUESTOS!F54 -> 0 | F54: =IF(Q54=0,0,((M54/Q54)*J54)) -> 0 | G54: =ROUND(E54*F54,2) -> 0 | H54: =J54-F54 -> 0 | I54: =ROUND(E54*H54,2) -> 0 | J54: =PRESUPUESTOS!E54 -> 0 | K54: =ROUND(E54*J54,2) -> 0 | L54: =PRESUPUESTOS!N54 -> 0 | N54: =ROUND(M54*L54,2) -> 0 | O54: =Q54-M54 -> 0 | P54: =ROUND(O54*L54,2) -> 0 | Q54: =PRESUPUESTOS!M54 -> 0 | R54: =ROUND(Q54*L54,2) -> 0
A55: 300 | B55: 02.03.07.02 | C55: VIGAS.- CONCRETO 210 kg/cm2 - 1 piso | D55: m3 | E55: =PRESUPUESTOS!F55 -> 325.93 | F55: =IF(Q55=0,0,((M55/Q55)*J55)) -> 0 | G55: =ROUND(E55*F55,2) -> 0 | H55: =J55-F55 -> 36.12 | I55: =ROUND(E55*H55,2) -> 11772.59 | J55: =PRESUPUESTOS!E55 -> 36.12 | K55: =ROUND(E55*J55,2) -> 11772.59 | L55: =PRESUPUESTOS!N55 -> 0 | N55: =ROUND(M55*L55,2) -> 0 | O55: =Q55-M55 -> 0 | P55: =ROUND(O55*L55,2) -> 0 | Q55: =PRESUPUESTOS!M55 -> 0 | R55: =ROUND(Q55*L55,2) -> 0
A56: 400 | B56: 02.03.07.06 | C56: VIGAS.- ENCOFRADO Y DESENCOFRADO | D56: m2 | E56: =PRESUPUESTOS!F56 -> 70.38 | F56: =IF(Q56=0,0,((M56/Q56)*J56)) -> 0 | G56: =ROUND(E56*F56,2) -> 0 | H56: =J56-F56 -> 545.23 | I56: =ROUND(E56*H56,2) -> 38373.29 | J56: =PRESUPUESTOS!E56 -> 545.23 | K56: =ROUND(E56*J56,2) -> 38373.29 | L56: =PRESUPUESTOS!N56 -> 0 | N56: =ROUND(M56*L56,2) -> 0 | O56: =Q56-M56 -> 0 | P56: =ROUND(O56*L56,2) -> 0 | Q56: =PRESUPUESTOS!M56 -> 0 | R56: =ROUND(Q56*L56,2) -> 0
A57: 500 | B57: 02.03.07.08 | C57: VIGAS.- ACERO Fy=4200 kg/cm2 | D57: KG | E57: =PRESUPUESTOS!F57 -> 4.02 | F57: =IF(Q57=0,0,((M57/Q57)*J57)) -> 0 | G57: =ROUND(E57*F57,2) -> 0 | H57: =J57-F57 -> 5144.6 | I57: =ROUND(E57*H57,2) -> 20681.29 | J57: =PRESUPUESTOS!E57 -> 5144.6 | K57: =ROUND(E57*J57,2) -> 20681.29 | L57: =PRESUPUESTOS!N57 -> 0 | N57: =ROUND(M57*L57,2) -> 0 | O57: =Q57-M57 -> 0 | P57: =ROUND(O57*L57,2) -> 0 | Q57: =PRESUPUESTOS!M57 -> 0 | R57: =ROUND(Q57*L57,2) -> 0
B58: 02.03.08 | C58: Losas Macizas | E58: =PRESUPUESTOS!F58 -> 0 | F58: =IF(Q58=0,0,((M58/Q58)*J58)) -> 0 | G58: =ROUND(E58*F58,2) -> 0 | H58: =J58-F58 -> 0 | I58: =ROUND(E58*H58,2) -> 0 | J58: =PRESUPUESTOS!E58 -> 0 | K58: =ROUND(E58*J58,2) -> 0 | L58: =PRESUPUESTOS!N58 -> 0 | N58: =ROUND(M58*L58,2) -> 0 | O58: =Q58-M58 -> 0 | P58: =ROUND(O58*L58,2) -> 0 | Q58: =PRESUPUESTOS!M58 -> 0 | R58: =ROUND(Q58*L58,2) -> 0
A59: 300 | B59: 02.03.08.01 | C59: LOSAS MACIZAS.- CONC.210 kg/cm2 - 1 PISO | D59: M3 | E59: =PRESUPUESTOS!F59 -> 325.93 | F59: =IF(Q59=0,0,((M59/Q59)*J59)) -> 0 | G59: =ROUND(E59*F59,2) -> 0 | H59: =J59-F59 -> 0.63 | I59: =ROUND(E59*H59,2) -> 205.34 | J59: =PRESUPUESTOS!E59 -> 0.63 | K59: =ROUND(E59*J59,2) -> 205.34 | L59: =PRESUPUESTOS!N59 -> 0 | N59: =ROUND(M59*L59,2) -> 0 | O59: =Q59-M59 -> 0 | P59: =ROUND(O59*L59,2) -> 0 | Q59: =PRESUPUESTOS!M59 -> 0 | R59: =ROUND(Q59*L59,2) -> 0
A60: 400 | B60: 02.03.08.03 | C60: LOSAS MACIZAS.- ENCOFRADO Y DESENCOFRADO | D60: m2 | E60: =PRESUPUESTOS!F60 -> 55.43 | F60: =IF(Q60=0,0,((M60/Q60)*J60)) -> 0 | G60: =ROUND(E60*F60,2) -> 0 | H60: =J60-F60 -> 6.54 | I60: =ROUND(E60*H60,2) -> 362.51 | J60: =PRESUPUESTOS!E60 -> 6.54 | K60: =ROUND(E60*J60,2) -> 362.51 | L60: =PRESUPUESTOS!N60 -> 0 | N60: =ROUND(M60*L60,2) -> 0 | O60: =Q60-M60 -> 0 | P60: =ROUND(O60*L60,2) -> 0 | Q60: =PRESUPUESTOS!M60 -> 0 | R60: =ROUND(Q60*L60,2) -> 0
A61: 500 | B61: 02.03.08.04 | C61: LOSAS MACIZAS.- ACERO Fy=4,200 kg/cm2 | D61: KG | E61: =PRESUPUESTOS!F61 -> 4.02 | F61: =IF(Q61=0,0,((M61/Q61)*J61)) -> 0 | G61: =ROUND(E61*F61,2) -> 0 | H61: =J61-F61 -> 73.15 | I61: =ROUND(E61*H61,2) -> 294.06 | J61: =PRESUPUESTOS!E61 -> 73.15 | K61: =ROUND(E61*J61,2) -> 294.06 | L61: =PRESUPUESTOS!N61 -> 0 | N61: =ROUND(M61*L61,2) -> 0 | O61: =Q61-M61 -> 0 | P61: =ROUND(O61*L61,2) -> 0 | Q61: =PRESUPUESTOS!M61 -> 0 | R61: =ROUND(Q61*L61,2) -> 0
B62: 02.03.09 | C62: Losas Aligeradas | E62: =PRESUPUESTOS!F62 -> 0 | F62: =IF(Q62=0,0,((M62/Q62)*J62)) -> 0 | G62: =ROUND(E62*F62,2) -> 0 | H62: =J62-F62 -> 0 | I62: =ROUND(E62*H62,2) -> 0 | J62: =PRESUPUESTOS!E62 -> 0 | K62: =ROUND(E62*J62,2) -> 0 | L62: =PRESUPUESTOS!N62 -> 0 | N62: =ROUND(M62*L62,2) -> 0 | O62: =Q62-M62 -> 0 | P62: =ROUND(O62*L62,2) -> 0 | Q62: =PRESUPUESTOS!M62 -> 0 | R62: =ROUND(Q62*L62,2) -> 0
A63: 300 | B63: 02.03.09.01 | C63: LOSA ALIGERADA - CONCRETO 210 kg/cm2 - 1 PISO | D63: m3 | E63: =PRESUPUESTOS!F63 -> 315.52 | F63: =IF(Q63=0,0,((M63/Q63)*J63)) -> 0 | G63: =ROUND(E63*F63,2) -> 0 | H63: =J63-F63 -> 2.13 | I63: =ROUND(E63*H63,2) -> 672.06 | J63: =PRESUPUESTOS!E63 -> 2.13 | K63: =ROUND(E63*J63,2) -> 672.06 | L63: =PRESUPUESTOS!N63 -> 0 | N63: =ROUND(M63*L63,2) -> 0 | O63: =Q63-M63 -> 0 | P63: =ROUND(O63*L63,2) -> 0 | Q63: =PRESUPUESTOS!M63 -> 0 | R63: =ROUND(Q63*L63,2) -> 0
A64: 400 | B64: 02.03.09.03 | C64: LOSA ALIGERADA.- ENCOFRADO Y DESENCOFRADO | D64: m2 | E64: =PRESUPUESTOS!F64 -> 43.61 | F64: =IF(Q64=0,0,((M64/Q64)*J64)) -> 0 | G64: =ROUND(E64*F64,2) -> 0 | H64: =J64-F64 -> 24.72 | I64: =ROUND(E64*H64,2) -> 1078.04 | J64: =PRESUPUESTOS!E64 -> 24.72 | K64: =ROUND(E64*J64,2) -> 1078.04 | L64: =PRESUPUESTOS!N64 -> 0 | N64: =ROUND(M64*L64,2) -> 0 | O64: =Q64-M64 -> 0 | P64: =ROUND(O64*L64,2) -> 0 | Q64: =PRESUPUESTOS!M64 -> 0 | R64: =ROUND(Q64*L64,2) -> 0
A65: 500 | B65: 02.03.09.04 | C65: LOSA ALIGERADA.- ACERO Fy=4,200 kg/cm2 | D65: KG | E65: =PRESUPUESTOS!F65 -> 4.02 | F65: =IF(Q65=0,0,((M65/Q65)*J65)) -> 0 | G65: =ROUND(E65*F65,2) -> 0 | H65: =J65-F65 -> 93.93 | I65: =ROUND(E65*H65,2) -> 377.6 | J65: =PRESUPUESTOS!E65 -> 93.93 | K65: =ROUND(E65*J65,2) -> 377.6 | L65: =PRESUPUESTOS!N65 -> 0 | N65: =ROUND(M65*L65,2) -> 0 | O65: =Q65-M65 -> 0 | P65: =ROUND(O65*L65,2) -> 0 | Q65: =PRESUPUESTOS!M65 -> 0 | R65: =ROUND(Q65*L65,2) -> 0
A66: 300 | B66: 02.03.09.05 | C66: LOSA ALIGERADA.- LADR. HUECO 15x30x30 | D66: und | E66: =PRESUPUESTOS!F66 -> 2.49 | F66: =IF(Q66=0,0,((M66/Q66)*J66)) -> 0 | G66: =ROUND(E66*F66,2) -> 0 | H66: =J66-F66 -> 205.92 | I66: =ROUND(E66*H66,2) -> 512.74 | J66: =PRESUPUESTOS!E66 -> 205.92 | K66: =ROUND(E66*J66,2) -> 512.74 | L66: =PRESUPUESTOS!N66 -> 0 | N66: =ROUND(M66*L66,2) -> 0 | O66: =Q66-M66 -> 0 | P66: =ROUND(O66*L66,2) -> 0 | Q66: =PRESUPUESTOS!M66 -> 0 | R66: =ROUND(Q66*L66,2) -> 0
B67: 02.03.15 | C67: Gradas Armadas en Pisos | E67: =PRESUPUESTOS!F67 -> 0 | F67: =IF(Q67=0,0,((M67/Q67)*J67)) -> 0 | G67: =ROUND(E67*F67,2) -> 0 | H67: =J67-F67 -> 0 | I67: =ROUND(E67*H67,2) -> 0 | J67: =PRESUPUESTOS!E67 -> 0 | K67: =ROUND(E67*J67,2) -> 0 | L67: =PRESUPUESTOS!N67 -> 0 | N67: =ROUND(M67*L67,2) -> 0 | O67: =Q67-M67 -> 0 | P67: =ROUND(O67*L67,2) -> 0 | Q67: =PRESUPUESTOS!M67 -> 0 | R67: =ROUND(Q67*L67,2) -> 0
A68: 300 | B68: 02.03.15.01 | C68: GRADAS EN PISO, CONCRETO F'c=175 kg/cm2. | D68: m2 | E68: =PRESUPUESTOS!F68 -> 80.04 | F68: =IF(Q68=0,0,((M68/Q68)*J68)) -> 0 | G68: =ROUND(E68*F68,2) -> 0 | H68: =J68-F68 -> 12.31 | I68: =ROUND(E68*H68,2) -> 985.29 | J68: =PRESUPUESTOS!E68 -> 12.31 | K68: =ROUND(E68*J68,2) -> 985.29 | L68: =PRESUPUESTOS!N68 -> 0 | N68: =ROUND(M68*L68,2) -> 0 | O68: =Q68-M68 -> 0 | P68: =ROUND(O68*L68,2) -> 0 | Q68: =PRESUPUESTOS!M68 -> 0 | R68: =ROUND(Q68*L68,2) -> 0
A69: 400 | B69: 02.03.15.03 | C69: GRADAS, ENCOFRADO Y DESENCOFRADO | D69: m2 | E69: =PRESUPUESTOS!F69 -> 41.15 | F69: =IF(Q69=0,0,((M69/Q69)*J69)) -> 0 | G69: =ROUND(E69*F69,2) -> 0 | H69: =J69-F69 -> 6.96 | I69: =ROUND(E69*H69,2) -> 286.4 | J69: =PRESUPUESTOS!E69 -> 6.96 | K69: =ROUND(E69*J69,2) -> 286.4 | L69: =PRESUPUESTOS!N69 -> 0 | N69: =ROUND(M69*L69,2) -> 0 | O69: =Q69-M69 -> 0 | P69: =ROUND(O69*L69,2) -> 0 | Q69: =PRESUPUESTOS!M69 -> 0 | R69: =ROUND(Q69*L69,2) -> 0
A70: 500 | B70: 02.03.15.04 | C70: GRADAS EN PISO, ACERO fy=4200kg/cm2 | D70: kg | E70: =PRESUPUESTOS!F70 -> 4.02 | F70: =IF(Q70=0,0,((M70/Q70)*J70)) -> 0 | G70: =ROUND(E70*F70,2) -> 0 | H70: =J70-F70 -> 83.01 | I70: =ROUND(E70*H70,2) -> 333.7 | J70: =PRESUPUESTOS!E70 -> 83.01 | K70: =ROUND(E70*J70,2) -> 333.7 | L70: =PRESUPUESTOS!N70 -> 0 | N70: =ROUND(M70*L70,2) -> 0 | O70: =Q70-M70 -> 0 | P70: =ROUND(O70*L70,2) -> 0 | Q70: =PRESUPUESTOS!M70 -> 0 | R70: =ROUND(Q70*L70,2) -> 0
C71: COSTO DIRECTO | G71: =SUM(G7:G70) -> 0 | I71: =SUM(I7:I70) -> 960724.52 | K71: =SUM(K7:K70) -> 960724.52 | N71: =SUM(N7:N70) -> 0 | P71: =SUM(P7:P70) -> 1374.45 | R71: =SUM(R7:R70) -> 1374.45
C72: GASTOS GENERALES (10%) | G72: =ROUND(G71*0.1,2) -> 0 | I72: =ROUND(I71*0.1,2) -> 96072.45 | K72: =ROUND(K71*0.1,2) -> 96072.45 | N72: =ROUND(N71*0.1,2) -> 0 | P72: =ROUND(P71*0.1,2) -> 137.45 | R72: =ROUND(R71*0.1,2) -> 137.45
C73: UTILIDAD (8%) | G73: =ROUND(G71*0.08,2) -> 0 | I73: =ROUND(I71*0.08,2) -> 76857.96 | K73: =ROUND(K71*0.08,2) -> 76857.96
C74: SUBTOTAL | G74: =SUM(G71:G73) -> 0 | I74: =SUM(I71:I73) -> 1133654.9 | K74: =SUM(K71:K73) -> 1133654.9 | N74: =SUM(N71:N73) -> 0 | P74: =SUM(P71:P73) -> 1511.9 | R74: =SUM(R71:R73) -> 1511.9
C75: IGV (18.00%) | G75: =ROUND(G74*0.18,2) -> 0 | I75: =ROUND(I74*0.18,2) -> 204057.89 | K75: =ROUND(K74*0.18,2) -> 204057.89 | N75: =ROUND(N74*0.18,2) -> 0 | P75: =ROUND(P74*0.18,2) -> 272.14 | R75: =ROUND(R74*0.18,2) -> 272.14
C76: COSTO TOTAL (INC. IGV) | G76: =SUM(G74:G75) -> 0 | I76: =SUM(I74:I75) -> 1337712.8 | K76: =SUM(K74:K75) -> 1337712.8 | N76: =SUM(N74:N75) -> 0 | P76: =SUM(P74:P75) -> 1784.04 | R76: =SUM(R74:R75) -> 1784.04
J81: 130 | L81: 220 | M81: reales
J83: =+L83*0.59 -> 95.3145 | L83: 161.55 | M83: presup
L85: =+J81/L81 -> 0.59090909

Sheet RESUMEN - ANALISIS
A1: RESUMEN
A3: PROYECTO: | B3: I.E. N° 1182 "EL BOSQUE" - CERCO + INGRESOS Y CASETAS
C4: ANALISIS DE PRECIOS VENTA | F4: COSTO PREVISTO | I4: COSTO REAL
A5: CODIGO | B5: PARTIDA DE CONTROL | C5: COSTO TOTAL VENTA | D5: % | E5: COSTO EJECUTADO VENTA | F5: COSTO TOTAL META | G5: % | H5: COSTO EJECUTADO META | I5: COSTO EJECUTADO REAL | J5: MANO DE OBRA | K5: MATERIALES | L5: EQUIPOS | M5: SERVICIOS | N5: SUBCONTRATOS | O5: BRECHA (META - REAL)
B6: PRESUPUESTO CONTRACTUAL
A7: 100 | B7: OBRAS PROVISIONALES | C7: =SUMIF(COMPARATIVO!$A$7:$A$70,'RESUMEN - ANALISIS'!A7,COMPARATIVO!$K$7:$K$70) -> 3661.14 | D7: =E7/C7 -> 0 | E7: =SUMIF(COMPARATIVO!$A$7:$A$70,'RESUMEN - ANALISIS'!A7,COMPARATIVO!$G$7:$G$70) -> 0 | F7: =SUMIF(COMPARATIVO!$A$7:$A$70,'RESUMEN - ANALISIS'!A7,COMPARATIVO!$R$7:$R$70) -> 1374.45 | G7: =H7/F7 -> 0 | H7: =SUMIF(COMPARATIVO!$A$7:$A$70,'RESUMEN - ANALISIS'!A7,COMPARATIVO!$N$7:$N$70) -> 0 | I7: =SUM(J7:N7) -> 229.25 | N7: 229.25 | O7: =H7-I7 -> -229.25
A8: 200 | B8: MOVIMIENTO DE TIERRAS | C8: =SUMIF(COMPARATIVO!$A$7:$A$70,'RESUMEN - ANALISIS'!A8,COMPARATIVO!$K$7:$K$70) -> 159518.36 | D8: =E8/C8 -> 0 | E8: =SUMIF(COMPARATIVO!$A$7:$A$70,'RESUMEN - ANALISIS'!A8,COMPARATIVO!$G$7:$G$70) -> 0 | F8: =SUMIF(COMPARATIVO!$A$7:$A$70,'RESUMEN - ANALISIS'!A8,COMPARATIVO!$R$7:$R$70) -> 0 | G8: =H8/F8 -> #DIV/0! | H8: =SUMIF(COMPARATIVO!$A$7:$A$70,'RESUMEN - ANALISIS'!A8,COMPARATIVO!$N$7:$N$70) -> 0 | I8: =SUM(J8:N8) -> 7319.59 | J8: 200 | N8: 7119.59 | O8: =H8-I8 -> -7319.59
A9: 300 | B9: CONCRETO | C9: =SUMIF(COMPARATIVO!$A$7:$A$70,'RESUMEN - ANALISIS'!A9,COMPARATIVO!$K$7:$K$70) -> 360886.42 | D9: =E9/C9 -> 0 | E9: =SUMIF(COMPARATIVO!$A$7:$A$70,'RESUMEN - ANALISIS'!A9,COMPARATIVO!$G$7:$G$70) -> 0 | F9: =SUMIF(COMPARATIVO!$A$7:$A$70,'RESUMEN - ANALISIS'!A9,COMPARATIVO!$R$7:$R$70) -> 0 | G9: =H9/F9 -> #DIV/0! | H9: =SUMIF(COMPARATIVO!$A$7:$A$70,'RESUMEN - ANALISIS'!A9,COMPARATIVO!$N$7:$N$70) -> 0 | I9: =SUM(J9:N9) -> 17915.1 | N9: 17915.1 | O9: =H9-I9 -> -17915.1
A10: 400 | B10: ENCOFRADO | C10: =SUMIF(COMPARATIVO!$A$7:$A$70,'RESUMEN - ANALISIS'!A10,COMPARATIVO!$K$7:$K$70) -> 221395.36 | D10: =E10/C10 -> 0 | E10: =SUMIF(COMPARATIVO!$A$7:$A$70,'RESUMEN - ANALISIS'!A10,COMPARATIVO!$G$7:$G$70) -> 0 | F10: =SUMIF(COMPARATIVO!$A$7:$A$70,'RESUMEN - ANALISIS'!A10,COMPARATIVO!$R$7:$R$70) -> 0 | G10: =H10/F10 -> #DIV/0! | H10: =SUMIF(COMPARATIVO!$A$7:$A$70,'RESUMEN - ANALISIS'!A10,COMPARATIVO!$N$7:$N$70) -> 0 | I10: =SUM(J10:N10) -> 0
A11: 500 | B11: ACERO | C11: =SUMIF(COMPARATIVO!$A$7:$A$70,'RESUMEN - ANALISIS'!A11,COMPARATIVO!$K$7:$K$70) -> 215263.24 | D11: =E11/C11 -> 0 | E11: =SUMIF(COMPARATIVO!$A$7:$A$70,'RESUMEN - ANALISIS'!A11,COMPARATIVO!$G$7:$G$70) -> 0 | F11: =SUMIF(COMPARATIVO!$A$7:$A$70,'RESUMEN - ANALISIS'!A11,COMPARATIVO!$R$7:$R$70) -> 0 | G11: =H11/F11 -> #DIV/0! | H11: =SUMIF(COMPARATIVO!$A$7:$A$70,'RESUMEN - ANALISIS'!A11,COMPARATIVO!$N$7:$N$70) -> 0 | I11: =SUM(J11:N11) -> 696.08 | J11: 55 | N11: 641.08 | O11: =H11-I11 -> -696.08
B12: TOTALES | C12: =SUM(C7:C11) -> 960724.52 | E12: =SUM(E7:E11) -> 0 | F12: =SUM(F7:F11) -> 1374.45 | H12: =SUM(H7:H11) -> 0 | I12: =SUM(I7:I11) -> 26160.02 | J12: =SUM(J7:J11) -> 255 | K12: =SUM(K7:K11) -> 0 | L12: =SUM(L7:L11) -> 0 | M12: =SUM(M7:M11) -> 0 | N12: =SUM(N7:N11) -> 25905.02 | O12: =SUM(O7:O11) -> -26160.02
B15: RESUMEN | C15: ACUM A MARZO 2023 | E15: META TOTAL | F15: META ANTERIOR | H15: DIFERENCIA
B17: TOTAL COSTO REAL | C17: =I12 -> 26160.02 | E17: =F12 -> 1374.45 | H17: =+F17-E17 -> -1374.45
B19: TOTAL COSTO VENTA | C19: =E12 -> 0 | E19: =C12 -> 960724.52 | H19: =+F19-E19 -> -960724.52
B21: RESULTADO OPERATIVO | C21: =C19-C17 -> -26160.02 | E21: =E19-E17 -> 959350.07 | F21: =F19-F17 -> 0
B22: MARGEN DE UTILIDAD | C22: =C21/C19 -> #DIV/0! | E22: =E21/E19 -> 0.99856936 | F22: =F21/F19 -> #DIV/0!

Sheet COSTOS INCURRIDOS
A2: ITEM | B2: DESCRIPCION | C2: PROVEEDOR | D2: UNIDAD | E2: CANTIDAD | F2: P.U. | G2: SUBTOTAL | H2: PARTIDA DE CONTROL | I2: TIPO DE COSTO | J2: METRADO UTILIZADO | K2: SUB TOTAL
B3: ORDENES DE COMPRA
A4: 1 | B4: MATERIAL AFIRMADO | C4: CANTERA ECONOMICA | D4: m3 | E4: 500 | F4: 120 | G4: =+E4*F4 -> 60000 | H4: 200 | I4: MATERIALES | J4: 130 | K4: =+J4*F4 -> 15600
B11: ORDENES DE SERVICIO
A12: 1 | B12: ALQUILER DE VOLQUETES | C12: NEGOCIOS DIAZ | D12: hm | E12: 50 | F12: 180 | G12: =+E12*F12 -> 9000 | H12: 200 | I12: SERVICIOS | J12: 35 | K12: =+J12*F12 -> 6300

Sheet CRONOG CONT VENTA
A4: ITEM | B4: UND | C4: DESCRIPCION | D4: CONTRACTUAL
D5: METRADO | E5: P.U. (S/.) | F5: PARCIAL (S/.) | G5: MES 1 | H5: MES 2 | I5: MES 3
F8: =ROUND(D8*E8,2) -> 0 | G8: =+$F8*K8 -> 0 | H8: =+$F8*L8 -> 0 | I8: =+$F8*M8 -> 0 | K8: 0.3 | L8: 0.4 | M8: 0.3
F10: =ROUND(D10*E10,2) -> 0 | G10: =+$F10*K10 -> 0 | H10: =+$F10*L10 -> 0 | I10: =+$F10*M10 -> 0 | K10: 0.5 | L10: 0.5
F11: =ROUND(D11*E11,2) -> 0 | G11: =+$F11*K11 -> 0 | H11: =+$F11*L11 -> 0 | I11: =+$F11*M11 -> 0 | K11: 0.5 | L11: 0.5
F12: =ROUND(D12*E12,2) -> 0 | G12: =+$F12*K12 -> 0 | H12: =+$F12*L12 -> 0 | I12: =+$F12*M12 -> 0 | K12: 0.5 | L12: 0.5
F13: =ROUND(D13*E13,2) -> 0 | G13: =+$F13*K13 -> 0 | H13: =+$F13*L13 -> 0 | I13: =+$F13*M13 -> 0 | K13: 0.3 | L13: 0.4 | M13: 0.3
F15: =ROUND(D15*E15,2) -> 0 | G15: =+$F15*K15 -> 0 | H15: =+$F15*L15 -> 0 | I15: =+$F15*M15 -> 0 | L15: 0.5 | M15: 0.5
F16: =ROUND(D16*E16,2) -> 0 | G16: =+$F16*K16 -> 0 | H16: =+$F16*L16 -> 0 | I16: =+$F16*M16 -> 0 | L16: 0.5 | M16: 0.5
F17: =ROUND(D17*E17,2) -> 0 | G17: =+$F17*K17 -> 0 | H17: =+$F17*L17 -> 0 | I17: =+$F17*M17 -> 0 | L17: 0.5 | M17: 0.5
F19: =ROUND(D19*E19,2) -> 0 | G19: =+$F19*K19 -> 0 | H19: =+$F19*L19 -> 0 | I19: =+$F19*M19 -> 0 | L19: 0.5 | M19: 0.5
F21: =ROUND(D21*E21,2) -> 0 | G21: =+$F21*K21 -> 0 | H21: =+$F21*L21 -> 0 | I21: =+$F21*M21 -> 0 | L21: 0.2 | M21: 0.8
F22: =ROUND(D22*E22,2) -> 0 | G22: =+$F22*K22 -> 0 | H22: =+$F22*L22 -> 0 | I22: =+$F22*M22 -> 0 | L22: 0.2 | M22: 0.8
C23: COSTO DIRECTO | F23: =SUM(F6:F22) -> 0 | G23: =SUM(G6:G22) -> 0 | H23: =SUM(H6:H22) -> 0 | I23: =SUM(I6:I22) -> 0
C24: GASTOS GENERALES (10%) | F24: =ROUND(F23*0.1,2) -> 0 | G24: =ROUND(G23*0.1,2) -> 0 | H24: =ROUND(H23*0.1,2) -> 0 | I24: =ROUND(I23*0.1,2) -> 0
C25: UTILIDAD (8%) | F25: =ROUND(F23*0.08,2) -> 0 | G25: =ROUND(G23*0.08,2) -> 0 | H25: =ROUND(H23*0.08,2) -> 0 | I25: =ROUND(I23*0.08,2) -> 0
C26: SUBTOTAL | F26: =SUM(F23:F25) -> 0 | G26: =SUM(G23:G25) -> 0 | H26: =SUM(H23:H25) -> 0 | I26: =SUM(I23:I25) -> 0
C27: IGV (18.00%) | F27: =ROUND(F26*0.18,2) -> 0 | G27: =ROUND(G26*0.18,2) -> 0 | H27: =ROUND(H26*0.18,2) -> 0 | I27: =ROUND(I26*0.18,2) -> 0
C28: COSTO TOTAL (INC. IGV) | F28: =SUM(F26:F27) -> 0 | G28: =SUM(G26:G27) -> 0 | H28: =SUM(H26:H27) -> 0 | I28: =SUM(I26:I27) -> 0

Sheet CRONOG CONT META
A4: ITEM | B4: UND | C4: DESCRIPCION | D4: CONTRACTUAL
D5: METRADO | E5: P.U. (S/.) | F5: PARCIAL (S/.) | G5: MES 1 | H5: MES 2 | I5: MES 3
E8: 0.35 | F8: =ROUND(D8*E8,2) -> 0 | G8: =+$F8*K8 -> 0 | H8: =+$F8*L8 -> 0 | I8: =+$F8*M8 -> 0 | K8: 0.3 | L8: 0.4 | M8: 0.3
E10: 9.2 | F10: =ROUND(D10*E10,2) -> 0 | G10: =+$F10*K10 -> 0 | H10: =+$F10*L10 -> 0 | I10: =+$F10*M10 -> 0 | K10: 0.5 | L10: 0.5
E11: 12.5 | F11: =ROUND(D11*E11,2) -> 0 | G11: =+$F11*K11 -> 0 | H11: =+$F11*L11 -> 0 | I11: =+$F11*M11 -> 0 | K11: 0.5 | L11: 0.5
E12: 0.7 | F12: =ROUND(D12*E12,2) -> 0 | G12: =+$F12*K12 -> 0 | H12: =+$F12*L12 -> 0 | I12: =+$F12*M12 -> 0 | K12: 0.5 | L12: 0.5
E13: 5.6 | F13: =ROUND(D13*E13,2) -> 0 | G13: =+$F13*K13 -> 0 | H13: =+$F13*L13 -> 0 | I13: =+$F13*M13 -> 0 | K13: 0.3 | L13: 0.4 | M13: 0.3
E15: 19 | F15: =ROUND(D15*E15,2) -> 0 | G15: =+$F15*K15 -> 0 | H15: =+$F15*L15 -> 0 | I15: =+$F15*M15 -> 0 | L15: 0.5 | M15: 0.5
E16: 10 | F16: =ROUND(D16*E16,2) -> 0 | G16: =+$F16*K16 -> 0 | H16: =+$F16*L16 -> 0 | I16: =+$F16*M16 -> 0 | L16: 0.5 | M16: 0.5
E17: 190 | F17: =ROUND(D17*E17,2) -> 0 | G17: =+$F17*K17 -> 0 | H17: =+$F17*L17 -> 0 | I17: =+$F17*M17 -> 0 | L17: 0.5 | M17: 0.5
E19: 2 | F19: =ROUND(D19*E19,2) -> 0 | G19: =+$F19*K19 -> 0 | H19: =+$F19*L19 -> 0 | I19: =+$F19*M19 -> 0 | L19: 0.5 | M19: 0.5
E21: 25 | F21: =ROUND(D21*E21,2) -> 0 | G21: =+$F21*K21 -> 0 | H21: =+$F21*L21 -> 0 | I21: =+$F21*M21 -> 0 | L21: 0.2 | M21: 0.8
E22: 0.5 | F22: =ROUND(D22*E22,2) -> 0 | G22: =+$F22*K22 -> 0 | H22: =+$F22*L22 -> 0 | I22: =+$F22*M22 -> 0 | L22: 0.2 | M22: 0.8
C23: COSTO DIRECTO | F23: =SUM(F6:F22) -> 0 | G23: =SUM(G6:G22) -> 0 | H23: =SUM(H6:H22) -> 0 | I23: =SUM(I6:I22) -> 0
C24: GASTOS GENERALES (10%) | F24: =ROUND(F23*0.12,2) -> 0 | G24: =ROUND(G23*0.12,2) -> 0 | H24: =ROUND(H23*0.12,2) -> 0 | I24: =ROUND(I23*0.12,2) -> 0
C25: UTILIDAD (8%)
C26: SUBTOTAL | F26: =SUM(F23:F25) -> 0 | G26: =SUM(G23:G25) -> 0 | H26: =SUM(H23:H25) -> 0 | I26: =SUM(I23:I25) -> 0
C27: IGV (18.00%) | F27: =ROUND(F26*0.18,2) -> 0 | G27: =ROUND(G26*0.18,2) -> 0 | H27: =ROUND(H26*0.18,2) -> 0 | I27: =ROUND(I26*0.18,2) -> 0
C28: COSTO TOTAL (INC. IGV) | F28: =SUM(F26:F27) -> 0 | G28: =SUM(G26:G27) -> 0 | H28: =SUM(H26:H27) -> 0 | I28: =SUM(I26:I27) -> 0

Sheet CRONOG INTERNO VENTA
A4: ITEM | B4: UND | C4: DESCRIPCION | D4: CONTRACTUAL
D5: METRADO | E5: P.U. (S/.) | F5: PARCIAL (S/.) | G5: MES 1 | H5: MES 2 | I5: MES 3
A6: 01.00.00 | C6: VEREDAS
A7: 01.01.00 | C7: TRABAJOS PRELIMINARES
A8: 01.01.01 | B8: M2 | C8: TRAZO Y REPLANTEO | D8: 646.2 | E8: 0.32 | F8: =ROUND(D8*E8,2) -> 206.78 | G8: =+$F8*K8 -> 103.39 | H8: =+$F8*L8 -> 103.39 | I8: =+$F8*M8 -> 0 | K8: 0.5 | L8: 0.5 | M8: 0
A9: 01.02.00 | C9: MOVIMIENTO DE TIERRAS
A10: 01.02.01 | B10: M3 | C10: CORTE A NIVEL DE SUBRASANTE MANUAL | D10: 129.24 | E10: 10.15 | F10: =ROUND(D10*E10,2) -> 1311.79 | G10: =+$F10*K10 -> 918.253 | H10: =+$F10*L10 -> 393.537 | I10: =+$F10*M10 -> 0 | K10: 0.7 | L10: 0.3
A11: 01.02.02 | B11: M3 | C11: ELIMINACION DE MATERIAL EXCEDENTE CON VOLQUETE, CARGUIO A MANO | D11: 161.55 | E11: 14.7 | F11: =ROUND(D11*E11,2) -> 2374.79 | G11: =+$F11*K11 -> 1662.353 | H11: =+$F11*L11 -> 712.437 | I11: =+$F11*M11 -> 0 | K11: 0.7 | L11: 0.3
A12: 01.02.03 | B12: M2 | C12: NIVELACION Y COMPACTACION DE SUB RASANTE MANUAL | D12: 646.2 | E12: 0.78 | F12: =ROUND(D12*E12,2) -> 504.04 | G12: =+$F12*K12 -> 352.828 | H12: =+$F12*L12 -> 151.212 | I12: =+$F12*M12 -> 0 | K12: 0.7 | L12: 0.3
A13: 01.02.04 | B13: M2 | C13: CONFORMACION DE BASE GRANULAR (e=0.10m.) | D13: 646.2 | E13: 6.1 | F13: =ROUND(D13*E13,2) -> 3941.82 | G13: =+$F13*K13 -> 1970.91 | H13: =+$F13*L13 -> 1970.91 | I13: =+$F13*M13 -> 0 | K13: 0.5 | L13: 0.5 | M13: 0
A14: 01.03.00 | C14: OBRAS DE CONCRETO SIMPLE
A15: 01.03.01 | B15: M2 | C15: LOSA DE CONCRETO F'C=140 KG/CM2,e=0.09m. VEREDAS | D15: 646.2 | E15: 22.12 | F15: =ROUND(D15*E15,2) -> 14293.94 | G15: =+$F15*K15 -> 0 | H15: =+$F15*L15 -> 10005.758 | I15: =+$F15*M15 -> 4288.182 | L15: 0.7 | M15: 0.3
A16: 01.03.02 | B16: M2 | C16: ENCOFRADO Y DESENCOFRADO VEREDAS | D16: 271.4 | E16: 12.2 | F16: =ROUND(D16*E16,2) -> 3311.08 | G16: =+$F16*K16 -> 0 | H16: =+$F16*L16 -> 2317.756 | I16: =+$F16*M16 -> 993.324 | L16: 0.7 | M16: 0.3
A17: 01.03.03 | B17: M3 | C17: CONCRETO F'C=140 KG/CM2 EN SARDINELES VEREDAS | D17: 13.57 | E17: 208.81 | F17: =ROUND(D17*E17,2) -> 2833.55 | G17: =+$F17*K17 -> 0 | H17: =+$F17*L17 -> 1983.485 | I17: =+$F17*M17 -> 850.065 | L17: 0.7 | M17: 0.3
A18: 01.04.00 | C18: JUNTAS
A19: 01.04.01 | B19: M | C19: JUNTAS EN VEREDAS | D19: 44.88 | E19: 2.27 | F19: =ROUND(D19*E19,2) -> 101.88 | G19: =+$F19*K19 -> 0 | H19: =+$F19*L19 -> 71.316 | I19: =+$F19*M19 -> 30.564 | L19: 0.7 | M19: 0.3
A20: 01.05.00 | C20: VARIOS
A21: 01.05.01 | B21: UND | C21: ADECUACION DE TAPAS DE DESAGUE | D21: 10 | E21: 27.46 | F21: =ROUND(D21*E21,2) -> 274.6 | G21: =+$F21*K21 -> 0 | H21: =+$F21*L21 -> 137.3 | I21: =+$F21*M21 -> 137.3 | L21: 0.5 | M21: 0.5
A22: 01.05.02 | B22: M2 | C22: CURADO DE OBRAS DE CONCRETO | D22: 646.2 | E22: 0.49 | F22: =ROUND(D22*E22,2) -> 316.64 | G22: =+$F22*K22 -> 0 | H22: =+$F22*L22 -> 158.32 | I22: =+$F22*M22 -> 158.32 | L22: 0.5 | M22: 0.5
C23: COSTO DIRECTO | F23: =SUM(F6:F22) -> 29470.91 | G23: =SUM(G6:G22) -> 5007.734 | H23: =SUM(H6:H22) -> 18005.421 | I23: =SUM(I6:I22) -> 6457.755
C24: GASTOS GENERALES (10%) | F24: =ROUND(F23*0.1,2) -> 2947.09 | G24: =ROUND(G23*0.1,2) -> 500.77 | H24: =ROUND(H23*0.1,2) -> 1800.54 | I24: =ROUND(I23*0.1,2) -> 645.78
C25: UTILIDAD (8%) | F25: =ROUND(F23*0.08,2) -> 2357.67 | G25: =ROUND(G23*0.08,2) -> 400.62 | H25: =ROUND(H23*0.08,2) -> 1440.43 | I25: =ROUND(I23*0.08,2) -> 516.62
C26: SUBTOTAL | F26: =SUM(F23:F25) -> 34775.67 | G26: =SUM(G23:G25) -> 5909.124 | H26: =SUM(H23:H25) -> 21246.391 | I26: =SUM(I23:I25) -> 7620.155
C27: IGV (18.00%) | F27: =ROUND(F26*0.18,2) -> 6259.62 | G27: =ROUND(G26*0.18,2) -> 1063.64 | H27: =ROUND(H26*0.18,2) -> 3824.35 | I27: =ROUND(I26*0.18,2) -> 1371.63
C28: COSTO TOTAL (INC. IGV) | F28: =SUM(F26:F27) -> 41035.29 | G28: =SUM(G26:G27) -> 6972.764 | H28: =SUM(H26:H27) -> 25070.741 | I28: =SUM(I26:I27) -> 8991.785

Sheet CRONOG INTERNO META
A4: ITEM | B4: UND | C4: DESCRIPCION | D4: CONTRACTUAL
D5: METRADO | E5: P.U. (S/.) | F5: PARCIAL (S/.) | G5: MES 1 | H5: MES 2 | I5: MES 3
E8: 0.35 | F8: =ROUND(D8*E8,2) -> 0 | G8: =+$F8*K8 -> 0 | H8: =+$F8*L8 -> 0 | I8: =+$F8*M8 -> 0 | K8: 0.5 | L8: 0.5 | M8: 0
E10: 9.2 | F10: =ROUND(D10*E10,2) -> 0 | G10: =+$F10*K10 -> 0 | H10: =+$F10*L10 -> 0 | I10: =+$F10*M10 -> 0 | K10: 0.7 | L10: 0.3
E11: 12.5 | F11: =ROUND(D11*E11,2) -> 0 | G11: =+$F11*K11 -> 0 | H11: =+$F11*L11 -> 0 | I11: =+$F11*M11 -> 0 | K11: 0.7 | L11: 0.3
E12: 0.7 | F12: =ROUND(D12*E12,2) -> 0 | G12: =+$F12*K12 -> 0 | H12: =+$F12*L12 -> 0 | I12: =+$F12*M12 -> 0 | K12: 0.7 | L12: 0.3
E13: 5.6 | F13: =ROUND(D13*E13,2) -> 0 | G13: =+$F13*K13 -> 0 | H13: =+$F13*L13 -> 0 | I13: =+$F13*M13 -> 0 | K13: 0.5 | L13: 0.5 | M13: 0
E15: 19 | F15: =ROUND(D15*E15,2) -> 0 | G15: =+$F15*K15 -> 0 | H15: =+$F15*L15 -> 0 | I15: =+$F15*M15 -> 0 | L15: 0.7 | M15: 0.3
E16: 10 | F16: =ROUND(D16*E16,2) -> 0 | G16: =+$F16*K16 -> 0 | H16: =+$F16*L16 -> 0 | I16: =+$F16*M16 -> 0 | L16: 0.7 | M16: 0.3
E17: 190 | F17: =ROUND(D17*E17,2) -> 0 | G17: =+$F17*K17 -> 0 | H17: =+$F17*L17 -> 0 | I17: =+$F17*M17 -> 0 | L17: 0.7 | M17: 0.3
E19: 2 | F19: =ROUND(D19*E19,2) -> 0 | G19: =+$F19*K19 -> 0 | H19: =+$F19*L19 -> 0 | I19: =+$F19*M19 -> 0 | L19: 0.7 | M19: 0.3
E21: 25 | F21: =ROUND(D21*E21,2) -> 0 | G21: =+$F21*K21 -> 0 | H21: =+$F21*L21 -> 0 | I21: =+$F21*M21 -> 0 | L21: 0.5 | M21: 0.5
E22: 0.5 | F22: =ROUND(D22*E22,2) -> 0 | G22: =+$F22*K22 -> 0 | H22: =+$F22*L22 -> 0 | I22: =+$F22*M22 -> 0 | L22: 0.5 | M22: 0.5
C23: COSTO DIRECTO | F23: =SUM(F6:F22) -> 0 | G23: =SUM(G6:G22) -> 0 | H23: =SUM(H6:H22) -> 0 | I23: =SUM(I6:I22) -> 0
C24: GASTOS GENERALES (10%) | F24: =ROUND(F23*0.12,2) -> 0 | G24: =ROUND(G23*0.12,2) -> 0 | H24: =ROUND(H23*0.12,2) -> 0 | I24: =ROUND(I23*0.12,2) -> 0
C25: UTILIDAD (8%)
C26: SUBTOTAL | F26: =SUM(F23:F25) -> 0 | G26: =SUM(G23:G25) -> 0 | H26: =SUM(H23:H25) -> 0 | I26: =SUM(I23:I25) -> 0
C27: IGV (18.00%) | F27: =ROUND(F26*0.18,2) -> 0 | G27: =ROUND(G26*0.18,2) -> 0 | H27: =ROUND(H26*0.18,2) -> 0 | I27: =ROUND(I26*0.18,2) -> 0
C28: COSTO TOTAL (INC. IGV) | F28: =SUM(F26:F27) -> 0 | G28: =SUM(G26:G27) -> 0 | H28: =SUM(H26:H27) -> 0 | I28: =SUM(I26:I27) -> 0

Sheet CRONOG COSTOS REALES
A2: EN FUNCION DE LOS COSTOS ACTUALIZADOS DEL RESULTADOS OPERATIVOS
A4: ITEM | B4: UND | C4: DESCRIPCION | D4: CONTRACTUAL
D5: METRADO | E5: P.U. (S/.) | F5: PARCIAL (S/.) | G5: MES 1 | H5: MES 2 | I5: MES 3
E8: 0.35 | F8: =ROUND(D8*E8,2) -> 0 | G8: =+$F8*K8 -> 0 | H8: =+$F8*L8 -> 0 | I8: =+$F8*M8 -> 0 | K8: 0.5 | L8: 0.5 | M8: 0
E10: 9.2 | F10: =ROUND(D10*E10,2) -> 0 | G10: =+$F10*K10 -> 0 | H10: =+$F10*L10 -> 0 | I10: =+$F10*M10 -> 0 | K10: 0.7 | L10: 0.3
E11: 12.5 | F11: =ROUND(D11*E11,2) -> 0 | G11: =+$F11*K11 -> 0 | H11: =+$F11*L11 -> 0 | I11: =+$F11*M11 -> 0 | K11: 0.7 | L11: 0.3
E12: 0.7 | F12: =ROUND(D12*E12,2) -> 0 | G12: =+$F12*K12 -> 0 | H12: =+$F12*L12 -> 0 | I12: =+$F12*M12 -> 0 | K12: 0.7 | L12: 0.3
E13: 5.6 | F13: =ROUND(D13*E13,2) -> 0 | G13: =+$F13*K13 -> 0 | H13: =+$F13*L13 -> 0 | I13: =+$F13*M13 -> 0 | K13: 0.5 | L13: 0.5 | M13: 0
E15: 19 | F15: =ROUND(D15*E15,2) -> 0 | G15: =+$F15*K15 -> 0 | H15: =+$F15*L15 -> 0 | I15: =+$F15*M15 -> 0 | L15: 0.7 | M15: 0.3
E16: 10 | F16: =ROUND(D16*E16,2) -> 0 | G16: =+$F16*K16 -> 0 | H16: =+$F16*L16 -> 0 | I16: =+$F16*M16 -> 0 | L16: 0.7 | M16: 0.3
E17: 190 | F17: =ROUND(D17*E17,2) -> 0 | G17: =+$F17*K17 -> 0 | H17: =+$F17*L17 -> 0 | I17: =+$F17*M17 -> 0 | L17: 0.7 | M17: 0.3
E19: 2 | F19: =ROUND(D19*E19,2) -> 0 | G19: =+$F19*K19 -> 0 | H19: =+$F19*L19 -> 0 | I19: =+$F19*M19 -> 0 | L19: 0.7 | M19: 0.3
E21: 25 | F21: =ROUND(D21*E21,2) -> 0 | G21: =+$F21*K21 -> 0 | H21: =+$F21*L21 -> 0 | I21: =+$F21*M21 -> 0 | L21: 0.5 | M21: 0.5
E22: 0.5 | F22: =ROUND(D22*E22,2) -> 0 | G22: =+$F22*K22 -> 0 | H22: =+$F22*L22 -> 0 | I22: =+$F22*M22 -> 0 | L22: 0.5 | M22: 0.5
C23: COSTO DIRECTO | F23: =SUM(F6:F22) -> 0 | G23: =SUM(G6:G22) -> 0 | H23: =SUM(H6:H22) -> 0 | I23: =SUM(I6:I22) -> 0
C24: GASTOS GENERALES (10%) | F24: =ROUND(F23*0.12,2) -> 0 | G24: =ROUND(G23*0.12,2) -> 0 | H24: =ROUND(H23*0.12,2) -> 0 | I24: =ROUND(I23*0.12,2) -> 0
C25: UTILIDAD (8%)
C26: SUBTOTAL | F26: =SUM(F23:F25) -> 0 | G26: =SUM(G23:G25) -> 0 | H26: =SUM(H23:H25) -> 0 | I26: =SUM(I23:I25) -> 0
C27: IGV (18.00%) | F27: =ROUND(F26*0.18,2) -> 0 | G27: =ROUND(G26*0.18,2) -> 0 | H27: =ROUND(H26*0.18,2) -> 0 | I27: =ROUND(I26*0.18,2) -> 0
C28: COSTO TOTAL (INC. IGV) | F28: =SUM(F26:F27) -> 0 | G28: =SUM(G26:G27) -> 0 | H28: =SUM(H26:H27) -> 0 | I28: =SUM(I26:I27) -> 0
