Workbook

Sheet PRESUPUESTOS
A1: ANALISIS DE PRESUPUESTOS
A3: PROYECTO: | B3: I.E. N° 1182 "EL BOSQUE" - CERCO + INGRESOS Y CASETAS
A5: PC | B5: ITEM | C5: DESCRIPCION | D5: UND | E5: CONTRACTUAL | I5: META INICIAL -MES ANTERIOR | M5: META ACTUALIZADO
E6: METRADO | F6: P.U. (S/.) | G6: PARCIAL (S/.) | I6: METRADO | J6: P.U. (S/.) | K6: PARCIAL (S/.) | M6: METRADO | N6: P.U. (S/.) | O6: MANO DE OBRA | P6: MATERIALES | Q6: EQUIPOS | R6: SERVICIOS | S6: SUBCONTRATOS | T6: PARCIAL (S/.)
B7: 01 | C7: OBRAS PROVISIONALES, TRABAJOS PRELIMINARES, SEGURIDAD Y SALUD
B8: 01.02 | C8: Trabajos Preliminares
B9: 01.02.04 | C9: Trazo, Niveles y Replanteo
A10: 100 | B10: 01.02.04.01 | C10: TRAZO Y REPLANTEO PRELIMINAR | D10: M2 | E10: 897.34 | F10: 2.04 | G10: =ROUND(E10*F10,2) -> 1830.57 | I10: 942.21 | J10: 1.33 | K10: =ROUND(I10*J10,2) -> 1253.14 | M10: 935 | N10: =SUM(O10:S10) -> 1.47 | O10: 0.52 | P10: 0.7 | Q10: 0.25 | T10: =ROUND(M10*N10,2) -> 1374.45
A11: 100 | B11: 01.02.04.02 | C11: TRAZO Y REPLANTEO DURANTE EL PROCESO | D11: m2 | E11: 897.34 | F11: 2.04 | G11: =ROUND(E11*F11,2) -> 1830.57 | I11: 942.21 | J11: 1.33 | K11: =ROUND(I11*J11,2) -> 1253.14 | N11: =SUM(O11:S11) -> 0
B12: 02 | C12: ESTRUCTURAS
B13: 02.01 | C13: Movimiento de Tierras
B14: 02.01.01 | C14: Excavaciones
A15: 200 | B15: 02.01.01.01 | C15: EXCAV.ZANJAS Y ZAPATA RT>2kg/cm2 H=1.5m | D15: m3 | E15: 41.9 | F15: 46.74 | G15: =ROUND(E15*F15,2) -> 1958.41 | I15: 39.81 | J15: 29.22 | K15: =ROUND(I15*J15,2) -> 1163.25 | N15: =SUM(O15:S15) -> 0
A16: 200 | B16: 02.01.01.02 | C16: EXCAV.ZANJAS Y ZAPATA RT>2kg/cm2 H=2.0m | D16: m3 | E16: 1975.16 | F16: 50.99 | G16: =ROUND(E16*F16,2) -> 100713.41 | I16: 1876.4 | J16: 33.36 | K16: =ROUND(I16*J16,2) -> 62596.7 | N16: =SUM(O16:S16) -> 0
B17: 02.01.03 | C17: Rellenos
A18: 200 | B18: 02.01.03.01 | C18: RELLENO COMPACTADO C/EQUIPO MAT/PROPIO | D18: m3 | E18: 1197.91 | F18: 26.01 | G18: =ROUND(E18*F18,2) -> 31157.64 | I18: 1138.01 | J18: 15 | K18: =ROUND(I18*J18,2) -> 17070.15 | N18: =SUM(O18:S18) -> 0
B19: 02.01.04 | C19: Eliminacion de Material Excedente
A20: 200 | B20: 02.01.04.01 | C20: ACARREO INTERNO, MATERIAL PROCEDENTE DE EXCAVACIONES | D20: m3 | E20: 68.91 | F20: 17.53 | G20: =ROUND(E20*F20,2) -> 1207.99
A21: 200 | B21: 02.01.04.02 | C21: ELIMINACION MATERIAL EXCEDENTE ACARREADO | D21: M3 | E21: 68.91 | F21: 16.02 | G21: =ROUND(E21*F21,2) -> 1103.94
A22: 200 | B22: 02.01.04.03 | C22: ELIMINACION MATERIAL EXCEDENTE C/MAQUINA | D22: m3 | E22: 995.9 | F22: 21.84 | G22: =ROUND(E22*F22,2) -> 21750.46 | I22: 1118.06 | J22: 18.27 | K22: =ROUND(I22*J22,2) -> 20426.96 | N22: =SUM(O22:S22) -> 0
B23: 02.01.05 | C23: Nivelacion Interior y Apisonado
A24: 200 | B24: 02.01.05.01 | C24: ESCARIFICADO Y COMPACTACION CON PLANCHA COMPACTADORA e = 30 cm | D24: m2 | E24: 68.95 | F24: 4.72 | G24: =ROUND(E24*F24,2) -> 325.44 | I24: 70.33 | J24: 4.36 | K24: =ROUND(I24*J24,2) -> 306.64 | N24: =SUM(O24:S24) -> 0
A25: 200 | B25: 02.01.05.02 | C25: ESCARIFICADO Y COMPACTACION CON PLANCHA COMPACTADORA H=0.60m (02 CAPAS 30cm c/u) | D25: m2 | E25: 8.56 | F25: 7.85 | G25: =ROUND(E25*F25,2) -> 67.2 | I25: 8.73 | J25: 7.37 | K25: =ROUND(I25*J25,2) -> 64.34 | N25: =SUM(O25:S25) -> 0
A26: 200 | B26: 02.01.05.05 | C26: AFIRMADO DE 8" PARA PISOS,PATIOS Y VEREDAS,COMPACTADO. | D26: m2 | E26: 68.95 | F26: 15.19 | G26: =ROUND(E26*F26,2) -> 1047.35 | I26: 70.33 | J26: 11.5 | K26: =ROUND(I26*J26,2) -> 808.8 | N26: =SUM(O26:S26) -> 0
A27: 200 | B27: 02.01.05.06 | C27: AFIRMADO DE 12" EN PISOS INTERIOR/EXTERIOR,COMPACTADO. | D27: m2 | E27: 8.56 | F27: 21.79 | G27: =ROUND(E27*F27,2) -> 186.52 | I27: 8.73 | J27: 14.5 | K27: =ROUND(I27*J27,2) -> 126.59 | N27: =SUM(O27:S27) -> 0
B28: 02.02 | C28: Obras de Concreto Simple
B29: 02.02.01 | C29: Falsos Cimientos
A30: 300 | B30: 02.02.01.01 | C30: SUBCIMIENTO, SUBZAPATA MEZCLA 1:12 + 30 % P.G. | D30: m3 | E30: 323.69 | F30: 173.72 | G30: =ROUND(E30*F30,2) -> 56231.43 | I30: 330.16 | J30: 184.1 | K30: =ROUND(I30*J30,2) -> 60782.46 | N30: =SUM(O30:S30) -> 0
B31: 02.02.02 | C31: Cimientos
A32: 300 | B32: 02.02.02.02 | C32: CIMIENTOS CORRIDOS 1:10 + 30 % P.G. f'c >=100Kg/cm2 | D32: m3 | E32: 24.73 | F32: 179.78 | G32: =ROUND(E32*F32,2) -> 4445.96 | I32: 24.24 | J32: 182.46 | K32: =ROUND(I32*J32,2) -> 4422.83 | N32: =SUM(O32:S32) -> 0
A33: 400 | B33: 02.02.02.03 | C33: CIMIENTO CORRIDO - ENCOFRADO Y DESENCOFRADO | D33: m2 | E33: 23.09 | F33: 46.17 | G33: =ROUND(E33*F33,2) -> 1066.07 | I33: 22.63 | J33: 23.83 | K33: =ROUND(I33*J33,2) -> 539.27 | N33: =SUM(O33:S33) -> 0
A34: 300 | B34: 02.02.02.04 | C34: CALZADURA: CONCRETO C:H 1:10 + 30 % P.G. | D34: m3 | E34: 163.82 | F34: 179.78 | G34: =ROUND(E34*F34,2) -> 29451.56 | I34: 160.54 | J34: 207.85 | K34: =ROUND(I34*J34,2) -> 33368.24 | N34: =SUM(O34:S34) -> 0
A35: 400 | B35: 02.02.02.05 | C35: CALZADURA: ENCOFRADO Y DESENCOFRADO | D35: m2 | E35: 327.63 | F35: 37.47 | G35: =ROUND(E35*F35,2) -> 12276.3 | I35: 321.08 | J35: 26.53 | K35: =ROUND(I35*J35,2) -> 8518.25 | N35: =SUM(O35:S35) -> 0
B36: 02.02.03 | C36: Sobrecimientos
A37: 300 | B37: 02.02.03.01 | C37: SOBRECIMIENTO, CONCRETO 1:8 + 25% P.M. f'c >=100Kg/cm2 | D37: m3 | E37: 3.21 | F37: 260.59 | G37: =ROUND(E37*F37,2) -> 836.49 | I37: 3.15 | J37: 201.22 | K37: =ROUND(I37*J37,2) -> 633.84 | N37: =SUM(O37:S37) -> 0
A38: 400 | B38: 02.02.03.02 | C38: SOBRECIMIENTO, ENCOFRADO Y DESENCOFRADO | D38: m2 | E38: 43.95 | F38: 37.7 | G38: =ROUND(E38*F38,2) -> 1656.92 | I38: 43.07 | J38: 24.18 | K38: =ROUND(I38*J38,2) -> 1041.43 | N38: =SUM(O38:S38) -> 0
B39: 02.03 | C39: Obras de Concreto Armado
B40: 02.03.02 | C40: Zapatas
A41: 300 | B41: 02.03.02.01 | C41: ZAPATAS.- CONCRETO 210 kg/cm2 | D41: m3 | E41: 396.75 | F41: 292.79 | G41: =ROUND(E41*F41,2) -> 116164.43 | I41: 412.62 | J41: 286.6 | K41: =ROUND(I41*J41,2) -> 118256.89 | N41: =SUM(O41:S41) -> 0
A42: 500 | B42: 02.03.02.03 | C42: ZAPATAS.- ACERO Fy=4200 kg/cm2 | D42: KG | E42: 17534.91 | F42: 4.02 | G42: =ROUND(E42*F42,2) -> 70490.34 | I42: 17359.56 | J42: 3.4 | K42: =ROUND(I42*J42,2) -> 59022.5 | N42: =SUM(O42:S42) -> 0
B43: 02.03.05 | C43: Placas y Muros de Contención
A44: 300 | B44: 02.03.05.02 | C44: PLACAS, CONCRETO F'c=210 kg/cm2 - 1 piso | D44: m3 | E44: 6.69 | F44: 454.82 | G44: =ROUND(E44*F44,2) -> 3042.75 | I44: 6.62 | J44: 290.45 | K44: =ROUND(I44*J44,2) -> 1922.78 | N44: =SUM(O44:S44) -> 0
A45: 400 | B45: 02.03.05.04 | C45: PLACAS, ENCOFRADO Y DESENCOFRADO | D45: m2 | E45: 74.18 | F45: 59.78 | G45: =ROUND(E45*F45,2) -> 4434.48 | I45: 73.44 | J45: 33.69 | K45: =ROUND(I45*J45,2) -> 2474.19 | N45: =SUM(O45:S45) -> 0
A46: 500 | B46: 02.03.05.05 | C46: PLACAS, ACERO Fy=4200 kg/cm2 | D46: KG | E46: 419.35 | F46: 4.02 | G46: =ROUND(E46*F46,2) -> 1685.79 | I46: 415.16 | J46: 3.4 | K46: =ROUND(I46*J46,2) -> 1411.54 | N46: =SUM(O46:S46) -> 0
A47: 300 | B47: 02.03.05.07 | C47: MUROS DE CONTENC.- CONCRETO 210 kg/cm2 | D47: m3 | E47: 256.52 | F47: 417.41 | G47: =ROUND(E47*F47,2) -> 107074.01 | I47: 253.95 | J47: 328.19 | K47: =ROUND(I47*J47,2) -> 83343.85 | N47: =SUM(O47:S47) -> 0
A48: 400 | B48: 02.03.05.09 | C48: MUROS DE CONTENC.- ENCOF. Y DESENCOFRADO | D48: m2 | E48: 2096.19 | F48: 51.21 | G48: =ROUND(E48*F48,2) -> 107345.89 | I48: 2075.23 | J48: 30.97 | K48: =ROUND(I48*J48,2) -> 64269.87 | N48: =SUM(O48:S48) -> 0
A49: 500 | B49: 02.03.05.11 | C49: MUROS DE CONTENC.- ACERO Fy=4200 kg/cm2 | D49: kg | E49: 18595.1 | F49: 4.02 | G49: =ROUND(E49*F49,2) -> 74752.3
B50: 02.03.06 | C50: Columnas
A51: 300 | B51: 02.03.06.02 | C51: COLUMNAS - CONCRETO 210 KG/CM² - 1 PISO | D51: m3 | E51: 66.63 | F51: 442.62 | G51: =ROUND(E51*F51,2) -> 29491.77 | I51: 67.96 | J51: 291.23 | K51: =ROUND(I51*J51,2) -> 19791.99
A52: 400 | B52: 02.03.06.06 | C52: COLUMNAS.- ENCOFRADO Y DESENCOFRADO | D52: m2 | E52: 901.38 | F52: 60.48 | G52: =ROUND(E52*F52,2) -> 54515.46 | I52: 919.41 | J52: 37.49 | K52: =ROUND(I52*J52,2) -> 34468.68
A53: 500 | B53: 02.03.06.10 | C53: COLUMNAS.- ACERO Fy=4200 kg/cm2 | D53: KG | E53: 11604.02 | F53: 4.02 | G53: =ROUND(E53*F53,2) -> 46648.16 | I53: 11836.1 | J53: 3.4 | K53: =ROUND(I53*J53,2) -> 40242.74
B54: 02.03.07 | C54: Vigas
A55: 300 | B55: 02.03.07.02 | C55: VIGAS.- CONCRETO 210 kg/cm2 - 1 piso | D55: m3 | E55: 36.12 | F55: 325.93 | G55: =ROUND(E55*F55,2) -> 11772.59 | I55: 36.84 | J55: 294.5 | K55: =ROUND(I55*J55,2) -> 10849.38 | N55: =SUM(O55:S55) -> 0
A56: 400 | B56: 02.03.07.06 | C56: VIGAS.- ENCOFRADO Y DESENCOFRADO | D56: m2 | E56: 545.23 | F56: 70.38 | G56: =ROUND(E56*F56,2) -> 38373.29 | I56: 556.13 | J56: 43.56 | K56: =ROUND(I56*J56,2) -> 24225.02 | N56: =SUM(O56:S56) -> 0
A57: 500 | B57: 02.03.07.08 | C57: VIGAS.- ACERO Fy=4200 kg/cm2 | D57: KG | E57: 5144.6 | F57: 4.02 | G57: =ROUND(E57*F57,2) -> 20681.29 | I57: 5247.49 | J57: 3.4 | K57: =ROUND(I57*J57,2) -> 17841.47 | N57: =SUM(O57:S57) -> 0
B58: 02.03.08 | C58: Losas Macizas
A59: 300 | B59: 02.03.08.01 | C59: LOSAS MACIZAS.- CONC.210 kg/cm2 - 1 PISO | D59: M3 | E59: 0.63 | F59: 325.93 | G59: =ROUND(E59*F59,2) -> 205.34 | I59: 0.64 | J59: 294.5 | K59: =ROUND(I59*J59,2) -> 188.48 | N59: =SUM(O59:S59) -> 0
A60: 400 | B60: 02.03.08.03 | C60: LOSAS MACIZAS.- ENCOFRADO Y DESENCOFRADO | D60: m2 | E60: 6.54 | F60: 55.43 | G60: =ROUND(E60*F60,2) -> 362.51 | I60: 6.67 | J60: 33.34 | K60: =ROUND(I60*J60,2) -> 222.38 | N60: =SUM(O60:S60) -> 0
A61: 500 | B61: 02.03.08.04 | C61: LOSAS MACIZAS.- ACERO Fy=4,200 kg/cm2 | D61: KG | E61: 73.15 | F61: 4.02 | G61: =ROUND(E61*F61,2) -> 294.06 | I61: 74.61 | J61: 3.4 | K61: =ROUND(I61*J61,2) -> 253.67 | N61: =SUM(O61:S61) -> 0
B62: 02.03.09 | C62: Losas Aligeradas
A63: 300 | B63: 02.03.09.01 | C63: LOSA ALIGERADA - CONCRETO 210 kg/cm2 - 1 PISO | D63: m3 | E63: 2.13 | F63: 315.52 | G63: =ROUND(E63*F63,2) -> 672.06 | I63: 2.17 | J63: 294.5 | K63: =ROUND(I63*J63,2) -> 639.07 | N63: =SUM(O63:S63) -> 0
A64: 400 | B64: 02.03.09.03 | C64: LOSA ALIGERADA.- ENCOFRADO Y DESENCOFRADO | D64: m2 | E64: 24.72 | F64: 43.61 | G64: =ROUND(E64*F64,2) -> 1078.04 | I64: 25.21 | J64: 25.75 | K64: =ROUND(I64*J64,2) -> 649.16 | N64: =SUM(O64:S64) -> 0
A65: 500 | B65: 02.03.09.04 | C65: LOSA ALIGERADA.- ACERO Fy=4,200 kg/cm2 | D65: KG | E65: 93.93 | F65: 4.02 | G65: =ROUND(E65*F65,2) -> 377.6 | I65: 95.81 | J65: 3.4 | K65: =ROUND(I65*J65,2) -> 325.75 | N65: =SUM(O65:S65) -> 0
A66: 300 | B66: 02.03.09.05 | C66: LOSA ALIGERADA.- LADR. HUECO 15x30x30 | D66: und | E66: 205.92 | F66: 2.49 | G66: =ROUND(E66*F66,2) -> 512.74 | I66: 210.04 | J66: 2.39 | K66: =ROUND(I66*J66,2) -> 502 | N66: =SUM(O66:S66) -> 0
B67: 02.03.15 | C67: Gradas Armadas en Pisos
A68: 300 | B68: 02.03.15.01 | C68: GRADAS EN PISO, CONCRETO F'c=175 kg/cm2. | D68: m2 | E68: 12.31 | F68: 80.04 | G68: =ROUND(E68*F68,2) -> 985.29 | I68: 12.56 | J68: 59.8 | K68: =ROUND(I68*J68,2) -> 751.09 | N68: =SUM(O68:S68) -> 0
A69: 400 | B69: 02.03.15.03 | C69: GRADAS, ENCOFRADO Y DESENCOFRADO | D69: m2 | E69: 6.96 | F69: 41.15 | G69: =ROUND(E69*F69,2) -> 286.4 | I69: 7.1 | J69: 27.36 | K69: =ROUND(I69*J69,2) -> 194.26 | N69: =SUM(O69:S69) -> 0
A70: 500 | B70: 02.03.15.04 | C70: GRADAS EN PISO, ACERO fy=4200kg/cm2 | D70: kg | E70: 83.01 | F70: 4.02 | G70: =ROUND(E70*F70,2) -> 333.7 | I70: 84.67 | J70: 3.4 | K70: =ROUND(I70*J70,2) -> 287.88 | N70: =SUM(O70:S70) -> 0
C71: COSTO DIRECTO | G71: =SUM(G7:G70) -> 960724.52 | K71: =SUM(K7:K70) -> 696510.67 | T71: =SUM(T7:T70) -> 1374.45
C72: GASTOS GENERALES (10%) | G72: =ROUND(G71*0.1,2) -> 96072.45 | K72: =ROUND(K71*0.12,2) -> 83581.28 | T72: =ROUND(T71*0.12,2) -> 164.93
C73: UTILIDAD (8%) | G73: =ROUND(G71*0.08,2) -> 76857.96 | K73: 0
C74: SUBTOTAL | G74: =SUM(G71:G73) -> 1133654.9 | K74: =SUM(K71:K73) -> 780091.95 | T74: =SUM(T71:T73) -> 1539.38
C75: IGV (18.00%) | G75: =ROUND(G74*0.18,2) -> 204057.89 | K75: =ROUND(K74*0.18,2) -> 140416.55 | T75: =ROUND(T74*0.18,2) -> 277.09
C76: COSTO TOTAL (INC. IGV) | G76: =SUM(G74:G75) -> 1337712.8 | K76: =SUM(K74:K75) -> 920508.5 | T76: =SUM(T74:T75) -> 1816.47
K77: =+G76-K76 -> 417204.32
C79: TRABAJOS PRELIMINARES | D79: 100 | I79: Ejecutarla mediante cuadrillas de casa
C80: Cantidad de personal, equipos, materiales, viaticos, alquileres
C81: Definir precios
C82: MOVIMIENTO DE TIERRAS | D82: 200 | I82: Subcontrato a todo costo
C83: Pedir cotizaciones
C84: Definir precios
C86: OBRAS DE CONCRETO | D86: 300 | I86: Ejecutarla mediante cuadrillas de casa con equipos alquilados
C87: Planificar personal y buscar empresas que alquilen equipos
C88: Definir precios
C90: VARIOS | D90: 400 | I90: Casa
C91: Planificar personal, materiales y equipos
C92: Definir precios

Sheet COMPARATIVO
A1: ANALISIS DE AVANCE
A3: PROYECTO: | B3: I.E. N° 1182 "EL BOSQUE" - CERCO + INGRESOS Y CASETAS
E4: ANALISIS DE PRECIOS VENTA | L4: COSTO PREVISTO
A5: PC | B5: ITEM | C5: DESCRIPCION | D5: UND | E5: CONTRACTUAL | F5: VENTA ACTUAL | H5: VENTA PENDIENTE | J5: VENTA TOTAL | L5: PREVISTO | M5: PREVISTO ACTUAL | O5: PREVISTO PENDIENTE | Q5: PREVISTO TOTAL
E6: P.U. (S/.) | F6: METRADO EJECUTADO | G6: PARCIAL (S/.) | H6: METRADO POR EJECUT | I6: PARCIAL (S/.) | J6: METRADO CONTRATO | K6: PARCIAL (S/.) | L6: P.U. (S/.) | M6: METRADO EJECUTADO | N6: PARCIAL (S/.) | O6: METRADO POR EJECUT | P6: PARCIAL (S/.) | Q6: METRADO REAL | R6: PARCIAL (S/.)
B7: 01 | C7: OBRAS PROVISIONALES, TRABAJOS PRELIMINARES, SEGURIDAD Y SALUD
B8: 01.02 | C8: Trabajos Preliminares
B9: 01.02.04 | C9: Trazo, Niveles y Replanteo
A10: 100 | B10: 01.02.04.01 | C10: TRAZO Y REPLANTEO PRELIMINAR | D10: M2 | E10: =PRESUPUESTOS!F10 -> 2.04 | F10: =IF(Q10=0,0,((M10/Q10)*J10)) -> 0 | G10: =ROUND(E10*F10,2) -> 0 | H10: =J10-F10 -> 897.34 | I10: =ROUND(E10*H10,2) -> 1830.57 | J10: =PRESUPUESTOS!E10 -> 897.34 | K10: =ROUND(E10*J10,2) -> 1830.57 | L10: =PRESUPUESTOS!N10 -> 1.47 | N10: =ROUND(M10*L10,2) -> 0 | O10: =Q10-M10 -> 935 | P10: =ROUND(O10*L10,2) -> 1374.45 | Q10: =PRESUPUESTOS!M10 -> 935 | R10: =ROUND(Q10*L10,2) -> 1374.45
A11: 100 | B11: 01.02.04.02 | C11: TRAZO Y REPLANTEO DURANTE EL PROCESO | D11: m2 | E11: =PRESUPUESTOS!F11 -> 2.04 | F11: =IF(Q11=0,0,((M11/Q11)*J11)) -> 0 | G11: =ROUND(E11*F11,2) -> 0 | H11: =J11-F11 -> 897.34 | I11: =ROUND(E11*H11,2) -> 1830.57 | J11: =PRESUPUESTOS!E11 -> 897.34 | K11: =ROUND(E11*J11,2) -> 1830.57 | L11: =PRESUPUESTOS!N11 -> 0 | N11: =ROUND(M11*L11,2) -> 0 | O11: =Q11-M11 -> 0 | P11: =ROUND(O11*L11,2) -> 0 | Q11: =PRESUPUESTOS!M11 -> 0 | R11: =ROUND(Q11*L11,2) -> 0
B12: 02 | C12: ESTRUCTURAS
B13: 02.01 | C13: Movimiento de Tierras
B14: 02.01.01 | C14: Excavaciones
A15: 200 | B15: 02.01.01.01 | C15: EXCAV.ZANJAS Y ZAPATA RT>2kg/cm2 H=1.5m | D15: m3 | E15: =PRESUPUESTOS!F15 -> 46.74 | F15: =IF(Q15=0,0,((M15/Q15)*J15)) -> 0 | G15: =ROUND(E15*F15,2) -> 0 | H15: =J15-F15 -> 41.9 | I15: =ROUND(E15*H15,2) -> 1958.41 | J15: =PRESUPUESTOS!E15 -> 41.9 | K15: =ROUND(E15*J15,2) -> 1958.41 | L15: =PRESUPUESTOS!N15 -> 0 | N15: =ROUND(M15*L15,2) -> 0 | O15: =Q15-M15 -> 0 | P15: =ROUND(O15*L15,2) -> 0 | Q15: =PRESUPUESTOS!M15 -> 0 | R15: =ROUND(Q15*L15,2) -> 0
A16: 200 | B16: 02.01.01.02 | C16: EXCAV.ZANJAS Y ZAPATA RT>2kg/cm2 H=2.0m | D16: m3 | E16: =PRESUPUESTOS!F16 -> 50.99 | F16: =IF(Q16=0,0,((M16/Q16)*J16)) -> 0 | G16: =ROUND(E16*F16,2) -> 0 | H16: =J16-F16 -> 1975.16 | I16: =ROUND(E16*H16,2) -> 100713.41 | J16: =PRESUPUESTOS!E16 -> 1975.16 | K16: =ROUND(E16*J16,2) -> 100713.41 | L16: =PRESUPUESTOS!N16 -> 0 | N16: =ROUND(M16*L16,2) -> 0 | O16: =Q16-M16 -> 0 | P16: =ROUND(O16*L16,2) -> 0 | Q16: =PRESUPUESTOS!M16 -> 0 | R16: =ROUND(Q16*L16,2) -> 0
B17: 02.01.03 | C17: Rellenos
A18: 200 | B18: 02.01.03.01 | C18: RELLENO COMPACTADO C/EQUIPO MAT/PROPIO | D18: m3 | E18: =PRESUPUESTOS!F18 -> 26.01 | F18: =IF(Q18=0,0,((M18/Q18)*J18)) -> 0 | G18: =ROUND(E18*F18,2) -> 0 | H18: =J18-F18 -> 1197.91 | I18: =ROUND(E18*H18,2) -> 31157.64 | J18: =PRESUPUESTOS!E18 -> 1197.91 | K18: =ROUND(E18*J18,2) -> 31157.64 | L18: =PRESUPUESTOS!N18 -> 0 | N18: =ROUND(M18*L18,2) -> 0 | O18: =Q18-M18 -> 0 | P18: =ROUND(O18*L18,2) -> 0 | Q18: =PRESUPUESTOS!M18 -> 0 | R18: =ROUND(Q18*L18,2) -> 0
B19: 02.01.04 | C19: Eliminacion de Material Excedente
A20: 200 | B20: 02.01.04.01 | C20: ACARREO INTERNO, MATERIAL PROCEDENTE DE EXCAVACIONES | D20: m3 | E20: =PRESUPUESTOS!F20 -> 17.53 | F20: =IF(Q20=0,0,((M20/Q20)*J20)) -> 0 | G20: =ROUND(E20*F20,2) -> 0 | H20: =J20-F20 -> 68.91 | I20: =ROUND(E20*H20,2) -> 1207.99 | J20: =PRESUPUESTOS!E20 -> 68.91 | K20: =ROUND(E20*J20,2) -> 1207.99 | L20: =PRESUPUESTOS!N20 -> 0 | N20: =ROUND(M20*L20,2) -> 0 | O20: =Q20-M20 -> 0 | P20: =ROUND(O20*L20,2) -> 0 | Q20: =PRESUPUESTOS!M20 -> 0 | R20: =ROUND(Q20*L20,2) -> 0
A21: 200 | B21: 02.01.04.02 | C21: ELIMINACION MATERIAL EXCEDENTE ACARREADO | D21: M3 | E21: =PRESUPUESTOS!F21 -> 16.02 | F21: =IF(Q21=0,0,((M21/Q21)*J21)) -> 0 | G21: =ROUND(E21*F21,2) -> 0 | H21: =J21-F21 -> 68.91 | I21: =ROUND(E21*H21,2) -> 1103.94 | J21: =PRESUPUESTOS!E21 -> 68.91 | K21: =ROUND(E21*J21,2) -> 1103.94 | L21: =PRESUPUESTOS!N21 -> 0 | N21: =ROUND(M21*L21,2) -> 0 | O21: =Q21-M21 -> 0 | P21: =ROUND(O21*L21,2) -> 0 | Q21: =PRESUPUESTOS!M21 -> 0 | R21: =ROUND(Q21*L21,2) -> 0
A22: 200 | B22: 02.01.04.03 | C22: ELIMINACION MATERIAL EXCEDENTE C/MAQUINA | D22: m3 | E22: =PRESUPUESTOS!F22 -> 21.84 | F22: =IF(Q22=0,0,((M22/Q22)*J22)) -> 0 | G22: =ROUND(E22*F22,2) -> 0 | H22: =J22-F22 -> 995.9 | I22: =ROUND(E22*H22,2) -> 21750.46 | J22: =PRESUPUESTOS!E22 -> 995.9 | K22: =ROUND(E22*J22,2) -> 21750.46 | L22: =PRESUPUESTOS!N22 -> 0 | N22: =ROUND(M22*L22,2) -> 0 | O22: =Q22-M22 -> 0 | P22: =ROUND(O22*L22,2) -> 0 | Q22: =PRESUPUESTOS!M22 -> 0 | R22: =ROUND(Q22*L22,2) -> 0
B23: 02.01.05 | C23: Nivelacion Interior y Apisonado | E23: =PRESUPUESTOS!F23 -> 0 | F23: =IF(Q23=0,0,((M23/Q23)*J23)) -> 0 | G23: =ROUND(E23*F23,2) -> 0 | H23: =J23-F23 -> 0 | I23: =ROUND(E23*H23,2) -> 0 | J23: =PRESUPUESTOS!E23 -> 0 | K23: =ROUND(E23*J23,2) -> 0 | L23: =PRESUPUESTOS!N23 -> 0 | N23: =ROUND(M23*L23,2) -> 0 | O23: =Q23-M23 -> 0 | P23: =ROUND(O23*L23,2) -> 0 | Q23: =PRESUPUESTOS!M23 -> 0 | R23: =ROUND(Q23*L23,2) -> 0
A24: 200 | B24: 02.01.05.01 | C24: ESCARIFICADO Y COMPACTACION CON PLANCHA COMPACTADORA e = 30 cm | D24: m2 | E24: =PRESUPUESTOS!F24 -> 4.72 | F24: =IF(Q24=0,0,((M24/Q24)*J24)) -> 0 | G24: =ROUND(E24*F24,2) -> 0 | H24: =J24-F24 -> 68.95 | I24: =ROUND(E24*H24,2) -> 325.44 | J24: =PRESUPUESTOS!E24 -> 68.95 | K24: =ROUND(E24*J24,2) -> 325.44 | L24: =PRESUPUESTOS!N24 -> 0 | N24: =ROUND(M24*L24,2) -> 0 | O24: =Q24-M24 -> 0 | P24: =ROUND(O24*L24,2) -> 0 | Q24: =PRESUPUESTOS!M24 -> 0 | R24: =ROUND(Q24*L24,2) -> 0
A25: 200 | B25: 02.01.05.02 | C25: ESCARIFICADO Y COMPACTACION CON PLANCHA COMPACTADORA H=0.60m (02 CAPAS 30cm c/u) | D25: m2 | E25: =PRESUPUESTOS!F25 -> 7.85 | F25: =IF(Q25=0,0,((M25/Q25)*J25)) -> 0 | G25: =ROUND(E25*F25,2) -> 0 | H25: =J25-F25 -> 8.56 | I25: =ROUND(E25*H25,2) -> 67.2 | J25: =PRESUPUESTOS!E25 -> 8.56 | K25: =ROUND(E25*J25,2) -> 67.2 | L25: =PRESUPUESTOS!N25 -> 0 | N25: =ROUND(M25*L25,2) -> 0 | O25: =Q25-M25 -> 0 | P25: =ROUND(O25*L25,2) -> 0 | Q25: =PRESUPUESTOS!M25 -> 0 | R25: =ROUND(Q25*L25,2) -> 0
A26: 200 | B26: 02.01.05.05 | C26: AFIRMADO DE 8" PARA PISOS,PATIOS Y VEREDAS,COMPACTADO. | D26: m2 | E26: =PRESUPUESTOS!F26 -> 15.19 | F26: =IF(Q26=0,0,((M26/Q26)*J26)) -> 0 | G26: =ROUND(E26*F26,2) -> 0 | H26: =J26-F26 -> 68.95 | I26: =ROUND(E26*H26,2) -> 1047.35 | J26: =PRESUPUESTOS!E26 -> 68.95 | K26: =ROUND(E26*J26,2) -> 1047.35 | L26: =PRESUPUESTOS!N26 -> 0 | N26: =ROUND(M26*L26,2) -> 0 | O26: =Q26-M26 -> 0 | P26: =ROUND(O26*L26,2) -> 0 | Q26: =PRESUPUESTOS!M26 -> 0 | R26: =ROUND(Q26*L26,2) -> 0
A27: 200 | B27: 02.01.05.06 | C27: AFIRMADO DE 12" EN PISOS INTERIOR/EXTERIOR,COMPACTADO. | D27: m2 | E27: =PRESUPUESTOS!F27 -> 21.79 | F27: =IF(Q27=0,0,((M27/Q27)*J27)) -> 0 | G27: =ROUND(E27*F27,2) -> 0 | H27: =J27-F27 -> 8.56 | I27: =ROUND(E27*H27,2) -> 186.52 | J27: =PRESUPUESTOS!E27 -> 8.56 | K27: =ROUND(E27*J27,2) -> 186.52 | L27: =PRESUPUESTOS!N27 -> 0 | N27: =ROUND(M27*L27,2) -> 0 | O27: =Q27-M27 -> 0 | P27: =ROUND(O27*L27,2) -> 0 | Q27: =PRESUPUESTOS!M27 -> 0 | R27: =ROUND(Q27*L27,2) -> 0
B28: 02.02 | C28: Obras de Concreto Simple | E28: =PRESUPUESTOS!F28 -> 0 | F28: =IF(Q28=0,0,((M28/Q28)*J28)) -> 0 | G28: =ROUND(E28*F28,2) -> 0 | H28: =J28-F28 -> 0 | I28: =ROUND(E28*H28,2) -> 0 | J28: =PRESUPUESTOS!E28 -> 0 | K28: =ROUND(E28*J28,2) -> 0 | L28: =PRESUPUESTOS!N28 -> 0 | N28: =ROUND(M28*L28,2) -> 0 | O28: =Q28-M28 -> 0 | P28: =ROUND(O28*L28,2) -> 0 | Q28: =PRESUPUESTOS!M28 -> 0 | R28: =ROUND(Q28*L28,2) -> 0
B29: 02.02.01 | C29: Falsos Cimientos | E29: =PRESUPUESTOS!F29 -> 0 | F29: =IF(Q29=0,0,((M29/Q29)*J29)) -> 0 | G29: =ROUND(E29*F29,2) -> 0 | H29: =J29-F29 -> 0 | I29: =ROUND(E29*H29,2) -> 0 | J29: =PRESUPUESTOS!E29 -> 0 | K29: =ROUND(E29*J29,2) -> 0 | L29: =PRESUPUESTOS!N29 -> 0 | N29: =ROUND(M29*L29,2) -> 0 | O29: =Q29-M29 -> 0 | P29: =ROUND(O29*L29,2) -> 0 | Q29: =PRESUPUESTOS!M29 -> 0 | R29: =ROUND(Q29*L29,2) -> 0
A30: 300 | B30: 02.02.01.01 | C30: SUBCIMIENTO, SUBZAPATA MEZCLA 1:12 + 30 % P.G. | D30: m3 | E30: =PRESUPUESTOS!F30 -> 173.72 | F30: =IF(Q30=0,0,((M30/Q30)*J30)) -> 0 | G30: =ROUND(E30*F30,2) -> 0 | H30: =J30-F30 -> 323.69 | I30: =ROUND(E30*H30,2) -> 56231.43 | J30: =PRESUPUESTOS!E30 -> 323.69 | K30: =ROUND(E30*J30,2) -> 56231.43 | L30: =PRESUPUESTOS!N30 -> 0 | N30: =ROUND(M30*L30,2) -> 0 | O30: =Q30-M30 -> 0 | P30: =ROUND(O30*L30,2) -> 0 | Q30: =PRESUPUESTOS!M30 -> 0 | R30: =ROUND(Q30*L30,2) -> 0
B31: 02.02.02 | C31: Cimientos | E31: =PRESUPUESTOS!F31 -> 0 | F31: =IF(Q31=0,0,((M31/Q31)*J31)) -> 0 | G31: =ROUND(E31*F31,2) -> 0 | H31: =J31-F31 -> 0 | I31: =ROUND(E31*H31,2) -> 0 | J31: =PRESUPUESTOS!E31 -> 0 | K31: =ROUND(E31*J31,2) -> 0 | L31: =PRESUPUESTOS!N31 -> 0 | N31: =ROUND(M31*L31,2) -> 0 | O31: =Q31-M31 -> 0 | P31: =ROUND(O31*L31,2) -> 0 | Q31: =PRESUPUESTOS!M31 -> 0 | R31: =ROUND(Q31*L31,2) -> 0
A32: 300 | B32: 02.02.02.02 | C32: CIMIENTOS CORRIDOS 1:10 + 30 % P.G. f'c >=100Kg/cm2 | D32: m3 | E32: =PRESUPUESTOS!F32 -> 179.78 | F32: =IF(Q32=0,0,((M32/Q32)*J32)) -> 0 | G32: =ROUND(E32*F32,2) -> 0 | H32: =J32-F32 -> 24.73 | I32: =ROUND(E32*H32,2) -> 4445.96 | J32: =PRESUPUESTOS!E32 -> 24.73 | K32: =ROUND(E32*J32,2) -> 4445.96 | L32: =PRESUPUESTOS!N32 -> 0 | N32: =ROUND(M32*L32,2) -> 0 | O32: =Q32-M32 -> 0 | P32: =ROUND(O32*L32,2) -> 0 | Q32: =PRESUPUESTOS!M32 -> 0 | R32: =ROUND(Q32*L32,2) -> 0
A33: 400 | B33: 02.02.02.03 | C33: CIMIENTO CORRIDO - ENCOFRADO Y DESENCOFRADO | D33: m2 | E33: =PRESUPUESTOS!F33 -> 46.17 | F33: =IF(Q33=0,0,((M33/Q33)*J33)) -> 0 | G33: =ROUND(E33*F33,2) -> 0 | H33: =J33-F33 -> 23.09 | I33: =ROUND(E33*H33,2) -> 1066.07 | J33: =PRESUPUESTOS!E33 -> 23.09 | K33: =ROUND(E33*J33,2) -> 1066.07 | L33: =PRESUPUESTOS!N33 -> 0 | N33: =ROUND(M33*L33,2) -> 0 | O33: =Q33-M33 -> 0 | P33: =ROUND(O33*L33,2) -> 0 | Q33: =PRESUPUESTOS!M33 -> 0 | R33: =ROUND(Q33*L33,2) -> 0
A34: 300 | B34: 02.02.02.04 | C34: CALZADURA: CONCRETO C:H 1:10 + 30 % P.G. | D34: m3 | E34: =PRESUPUESTOS!F34 -> 179.78 | F34: =IF(Q34=0,0,((M34/Q34)*J34)) -> 0 | G34: =ROUND(E34*F34,2) -> 0 | H34: =J34-F34 -> 163.82 | I34: =ROUND(E34*H34,2) -> 29451.56 | J34: =PRESUPUESTOS!E34 -> 163.82 | K34: =ROUND(E34*J34,2) -> 29451.56 | L34: =PRESUPUESTOS!N34 -> 0 | N34: =ROUND(M34*L34,2) -> 0 | O34: =Q34-M34 -> 0 | P34: =ROUND(O34*L34,2) -> 0 | Q34: =PRESUPUESTOS!M34 -> 0 | R34: =ROUND(Q34*L34,2) -> 0
A35: 400 | B35: 02.02.02.05 | C35: CALZADURA: ENCOFRADO Y DESENCOFRADO | D35: m2 | E35: =PRESUPUESTOS!F35 -> 37.47 | F35: =IF(Q35=0,0,((M35/Q35)*J35)) -> 0 | G35: =ROUND(E35*F35,2) -> 0 | H35: =J35-F35 -> 327.63 | I35: =ROUND(E35*H35,2) -> 12276.3 | J35: =PRESUPUESTOS!E35 -> 327.63 | K35: =ROUND(E35*J35,2) -> 12276.3 | L35: =PRESUPUESTOS!N35 -> 0 | N35: =ROUND(M35*L35,2) -> 0 | O35: =Q35-M35 -> 0 | P35: =ROUND(O35*L35,2) -> 0 | Q35: =PRESUPUESTOS!M35 -> 0 | R35: =ROUND(Q35*L35,2) -> 0
B36: 02.02.03 | C36: Sobrecimientos | E36: =PRESUPUESTOS!F36 -> 0 | F36: =IF(Q36=0,0,((M36/Q36)*J36)) -> 0 | G36: =ROUND(E36*F36,2) -> 0 | H36: =J36-F36 -> 0 | I36: =ROUND(E36*H36,2) -> 0 | J36: =PRESUPUESTOS!E36 -> 0 | K36: =ROUND(E36*J36,2) -> 0 | L36: =PRESUPUESTOS!N36 -> 0 | N36: =ROUND(M36*L36,2) -> 0 | O36: =Q36-M36 -> 0 | P36: =ROUND(O36*L36,2) -> 0 | Q36: =PRESUPUESTOS!M36 -> 0 | R36: =ROUND(Q36*L36,2) -> 0
A37: 300 | B37: 02.02.03.01 | C37: SOBRECIMIENTO, CONCRETO 1:8 + 25% P.M. f'c >=100Kg/cm2 | D37: m3 | E37: =PRESUPUESTOS!F37 -> 260.59 | F37: =IF(Q37=0,0,((M37/Q37)*J37)) -> 0 | G37: =ROUND(E37*F37,2) -> 0 | H37: =J37-F37 -> 3.21 | I37: =ROUND(E37*H37,2) -> 836.49 | J37: =PRESUPUESTOS!E37 -> 3.21 | K37: =ROUND(E37*J37,2) -> 836.49 | L37: =PRESUPUESTOS!N37 -> 0 | N37: =ROUND(M37*L37,2) -> 0 | O37: =Q37-M37 -> 0 | P37: =ROUND(O37*L37,2) -> 0 | Q37: =PRESUPUESTOS!M37 -> 0 | R37: =ROUND(Q37*L37,2) -> 0
A38: 400 | B38: 02.02.03.02 | C38: SOBRECIMIENTO, ENCOFRADO Y DESENCOFRADO | D38: m2 | E38: =PRESUPUESTOS!F38 -> 37.7 | F38: =IF(Q38=0,0,((M38/Q38)*J38)) -> 0 | G38: =ROUND(E38*F38,2) -> 0 | H38: =J38-F38 -> 43.95 | I38: =ROUND(E38*H38,2) -> 1656.92 | J38: =PRESUPUESTOS!E38 -> 43.95 | K38: =ROUND(E38*J38,2) -> 1656.92 | L38: =PRESUPUESTOS!N38 -> 0 | N38: =ROUND(M38*L38,2) -> 0 | O38: =Q38-M38 -> 0 | P38: =ROUND(O38*L38,2) -> 0 | Q38: =PRESUPUESTOS!M38 -> 0 | R38: =ROUND(Q38*L38,2) -> 0
B39: 02.03 | C39: Obras de Concreto Armado | E39: =PRESUPUESTOS!F39 -> 0 | F39: =IF(Q39=0,0,((M39/Q39)*J39)) -> 0 | G39: =ROUND(E39*F39,2) -> 0 | H39: =J39-F39 -> 0 | I39: =ROUND(E39*H39,2) -> 0 | J39: =PRESUPUESTOS!E39 -> 0 | K39: =ROUND(E39*J39,2) -> 0 | L39: =PRESUPUESTOS!N39 -> 0 | N39: =ROUND(M39*L39,2) -> 0 | O39: =Q39-M39 -> 0 | P39: =ROUND(O39*L39,2) -> 0 | Q39: =PRESUPUESTOS!M39 -> 0 | R39: =ROUND(Q39*L39,2) -> 0
B40: 02.03.02 | C40: Zapatas | E40: =PRESUPUESTOS!F40 -> 0 | F40: =IF(Q40=0,0,((M40/Q40)*J40)) -> 0 | G40: =ROUND(E40*F40,2) -> 0 | H40: =J40-F40 -> 0 | I40: =ROUND(E40*H40,2) -> 0 | J40: =PRESUPUESTOS!E40 -> 0 | K40: =ROUND(E40*J40,2) -> 0 | L40: =PRESUPUESTOS!N40 -> 0 | N40: =ROUND(M40*L40,2) -> 0 | O40: =Q40-M40 -> 0 | P40: =ROUND(O40*L40,2) -> 0 | Q40: =PRESUPUESTOS!M40 -> 0 | R40: =ROUND(Q40*L40,2) -> 0
A41: 300 | B41: 02.03.02.01 | C41: ZAPATAS.- CONCRETO 210 kg/cm2 | D41: m3 | E41: =PRESUPUESTOS!F41 -> 292.79 | F41: =IF(Q41=0,0,((M41/Q41)*J41)) -> 0 | G41: =ROUND(E41*F41,2) -> 0 | H41: =J41-F41 -> 396.75 | I41: =ROUND(E41*H41,2) -> 116164.43 | J41: =PRESUPUESTOS!E41 -> 396.75 | K41: =ROUND(E41*J41,2) -> 116164.43 | L41: =PRESUPUESTOS!N41 -> 0 | N41: =ROUND(M41*L41,2) -> 0 | O41: =Q41-M41 -> 0 | P41: =ROUND(O41*L41,2) -> 0 | Q41: =PRESUPUESTOS!M41 -> 0 | R41: =ROUND(Q41*L41,2) -> 0
A42: 500 | B42: 02.03.02.03 | C42: ZAPATAS.- ACERO Fy=4200 kg/cm2 | D42: KG | E42: =PRESUPUESTOS!F42 -> 4.02 | F42: =IF(Q42=0,0,((M42/Q42)*J42)) -> 0 | G42: =ROUND(E42*F42,2) -> 0 | H42: =J42-F42 -> 17534.91 | I42: =ROUND(E42*H42,2) -> 70490.34 | J42: =PRESUPUESTOS!E42 -> 17534.91 | K42: =ROUND(E42*J42,2) -> 70490.34 | L42: =PRESUPUESTOS!N42 -> 0 | N42: =ROUND(M42*L42,2) -> 0 | O42: =Q42-M42 -> 0 | P42: =ROUND(O42*L42,2) -> 0 | Q42: =PRESUPUESTOS!M42 -> 0 | R42: =ROUND(Q42*L42,2) -> 0
B43: 02.03.05 | C43: Placas y Muros de Contención | E43: =PRESUPUESTOS!F43 -> 0 | F43: =IF(Q43=0,0,((M43/Q43)*J43)) -> 0 | G43: =ROUND(E43*F43,2) -> 0 | H43: =J43-F43 -> 0 | I43: =ROUND(E43*H43,2) -> 0 | J43: =PRESUPUESTOS!E43 -> 0 | K43: =ROUND(E43*J43,2) -> 0 | L43: =PRESUPUESTOS!N43 -> 0 | N43: =ROUND(M43*L43,2) -> 0 | O43: =Q43-M43 -> 0 | P43: =ROUND(O43*L43,2) -> 0 | Q43: =PRESUPUESTOS!M43 -> 0 | R43: =ROUND(Q43*L43,2) -> 0
A44: 300 | B44: 02.03.05.02 | C44: PLACAS, CONCRETO F'c=210 kg/cm2 - 1 piso | D44: m3 | E44: =PRESUPUESTOS!F44 -> 454.82 | F44: =IF(Q44=0,0,((M44/Q44)*J44)) -> 0 | G44: =ROUND(E44*F44,2) -> 0 | H44: =J44-F44 -> 6.69 | I44: =ROUND(E44*H44,2) -> 3042.75 | J44: =PRESUPUESTOS!E44 -> 6.69 | K44: =ROUND(E44*J44,2) -> 3042.75 | L44: =PRESUPUESTOS!N44 -> 0 | N44: =ROUND(M44*L44,2) -> 0 | O44: =Q44-M44 -> 0 | P44: =ROUND(O44*L44,2) -> 0 | Q44: =PRESUPUESTOS!M44 -> 0 | R44: =ROUND(Q44*L44,2) -> 0
A45: 400 | B45: 02.03.05.04 | C45: PLACAS, ENCOFRADO Y DESENCOFRADO | D45: m2 | E45: =PRESUPUESTOS!F45 -> 59.78 | F45: =IF(Q45=0,0,((M45/Q45)*J45)) -> 0 | G45: =ROUND(E45*F45,2) -> 0 | H45: =J45-F45 -> 74.18 | I45: =ROUND(E45*H45,2) -> 4434.48 | J45: =PRESUPUESTOS!E45 -> 74.18 | K45: =ROUND(E45*J45,2) -> 4434.48 | L45: =PRESUPUESTOS!N45 -> 0 | N45: =ROUND(M45*L45,2) -> 0 | O45: =Q45-M45 -> 0 | P45: =ROUND(O45*L45,2) -> 0 | Q45: =PRESUPUESTOS!M45 -> 0 | R45: =ROUND(Q45*L45,2) -> 0
A46: 500 | B46: 02.03.05.05 | C46: PLACAS, ACERO Fy=4200 kg/cm2 | D46: KG | E46: =PRESUPUESTOS!F46 -> 4.02 | F46: =IF(Q46=0,0,((M46/Q46)*J46)) -> 0 | G46: =ROUND(E46*F46,2) -> 0 | H46: =J46-F46 -> 419.35 | I46: =ROUND(E46*H46,2) -> 1685.79 | J46: =PRESUPUESTOS!E46 -> 419.35 | K46: =ROUND(E46*J46,2) -> 1685.79 | L46: =PRESUPUESTOS!N46 -> 0 | N46: =ROUND(M46*L46,2) -> 0 | O46: =Q46-M46 -> 0 | P46: =ROUND(O46*L46,2) -> 0 | Q46: =PRESUPUESTOS!M46 -> 0 | R46: =ROUND(Q46*L46,2) -> 0
A47: 300 | B47: 02.03.05.07 | C47: MUROS DE CONTENC.- CONCRETO 210 kg/cm2 | D47: m3 | E47: =PRESUPUESTOS!F47 -> 417.41 | F47: =IF(Q47=0,0,((M47/Q47)*J47)) -> 0 | G47: =ROUND(E47*F47,2) -> 0 | H47: =J47-F47 -> 256.52 | I47: =ROUND(E47*H47,2) -> 107074.01 | J47: =PRESUPUESTOS!E47 -> 256.52 | K47: =ROUND(E47*J47,2) -> 107074.01 | L47: =PRESUPUESTOS!N47 -> 0 | N47: =ROUND(M47*L47,2) -> 0 | O47: =Q47-M47 -> 0 | P47: =ROUND(O47*L47,2) -> 0 | Q47: =PRESUPUESTOS!M47 -> 0 | R47: =ROUND(Q47*L47,2) -> 0
A48: 400 | B48: 02.03.05.09 | C48: MUROS DE CONTENC.- ENCOF. Y DESENCOFRADO | D48: m2 | E48: =PRESUPUESTOS!F48 -> 51.21 | F48: =IF(Q48=0,0,((M48/Q48)*J48)) -> 0 | G48: =ROUND(E48*F48,2) -> 0 | H48: =J48-F48 -> 2096.19 | I48: =ROUND(E48*H48,2) -> 107345.89 | J48: =PRESUPUESTOS!E48 -> 2096.19 | K48: =ROUND(E48*J48,2) -> 107345.89 | L48: =PRESUPUESTOS!N48 -> 0 | N48: =ROUND(M48*L48,2) -> 0 | O48: =Q48-M48 -> 0 | P48: =ROUND(O48*L48,2) -> 0 | Q48: =PRESUPUESTOS!M48 -> 0 | R48: =ROUND(Q48*L48,2) -> 0
A49: 500 | B49: 02.03.05.11 | C49: MUROS DE CONTENC.- ACERO Fy=4200 kg/cm2 | D49: kg | E49: =PRESUPUESTOS!F49 -> 4.02 | F49: =IF(Q49=0,0,((M49/Q49)*J49)) -> 0 | G49: =ROUND(E49*F49,2) -> 0 | H49: =J49-F49 -> 18595.1 | I49: =ROUND(E49*H49,2) -> 74752.3 | J49: =PRESUPUESTOS!E49 -> 18595.1 | K49: =ROUND(E49*J49,2) -> 74752.3 | L49: =PRESUPUESTOS!N49 -> 0 | N49: =ROUND(M49*L49,2) -> 0 | O49: =Q49-M49 -> 0 | P49: =ROUND(O49*L49,2) -> 0 | Q49: =PRESUPUESTOS!M49 -> 0 | R49: =ROUND(Q49*L49,2) -> 0
B50: 02.03.06 | C50: Columnas | E50: =PRESUPUESTOS!F50 -> 0 | F50: =IF(Q50=0,0,((M50/Q50)*J50)) -> 0 | G50: =ROUND(E50*F50,2) -> 0 | H50: =J50-F50 -> 0 | I50: =ROUND(E50*H50,2) -> 0 | J50: =PRESUPUESTOS!E50 -> 0 | K50: =ROUND(E50*J50,2) -> 0 | L50: =PRESUPUESTOS!N50 -> 0 | N50: =ROUND(M50*L50,2) -> 0 | O50: =Q50-M50 -> 0 | P50: =ROUND(O50*L50,2) -> 0 | Q50: =PRESUPUESTOS!M50 -> 0 | R50: =ROUND(Q50*L50,2) -> 0
A51: 300 | B51: 02.03.06.02 | C51: COLUMNAS - CONCRETO 210 KG/CM² - 1 PISO | D51: m3 | E51: =PRESUPUESTOS!F51 -> 442.62 | F51: =IF(Q51=0,0,((M51/Q51)*J51)) -> 0 | G51: =ROUND(E51*F51,2) -> 0 | H51: =J51-F51 -> 66.63 | I51: =ROUND(E51*H51,2) -> 29491.77 | J51: =PRESUPUESTOS!E51 -> 66.63 | K51: =ROUND(E51*J51,2) -> 29491.77 | L51: =PRESUPUESTOS!N51 -> 0 | N51: =ROUND(M51*L51,2) -> 0 | O51: =Q51-M51 -> 0 | P51: =ROUND(O51*L51,2) -> 0 | Q51: =PRESUPUESTOS!M51 -> 0 | R51: =ROUND(Q51*L51,2) -> 0
A52: 400 | B52: 02.03.06.06 | C52: COLUMNAS.- ENCOFRADO Y DESENCOFRADO | D52: m2 | E52: =PRESUPUESTOS!F52 -> 60.48 | F52: =IF(Q52=0,0,((M52/Q52)*J52)) -> 0 | G52: =ROUND(E52*F52,2) -> 0 | H52: =J52-F52 -> 901.38 | I52: =ROUND(E52*H52,2) -> 54515.46 | J52: =PRESUPUESTOS!E52 -> 901.38 | K52: =ROUND(E52*J52,2) -> 54515.46 | L52: =PRESUPUESTOS!N52 -> 0 | N52: =ROUND(M52*L52,2) -> 0 | O52: =Q52-M52 -> 0 | P52: =ROUND(O52*L52,2) -> 0 | Q52: =PRESUPUESTOS!M52 -> 0 | R52: =ROUND(Q52*L52,2) -> 0
A53: 500 | B53: 02.03.06.10 | C53: COLUMNAS.- ACERO Fy=4200 kg/cm2 | D53: KG | E53: =PRESUPUESTOS!F53 -> 4.02 | F53: =IF(Q53=0,0,((M53/Q53)*J53)) -> 0 | G53: =ROUND(E53*F53,2) -> 0 | H53: =J53-F53 -> 11604.02 | I53: =ROUND(E53*H53,2) -> 46648.16 | J53: =PRESUPUESTOS!E53 -> 11604.02 | K53: =ROUND(E53*J53,2) -> 46648.16 | L53: =PRESUPUESTOS!N53 -> 0 | N53: =ROUND(M53*L53,2) -> 0 | O53: =Q53-M53 -> 0 | P53: =ROUND(O53*L53,2) -> 0 | Q53: =PRESUPUESTOS!M53 -> 0 | R53: =ROUND(Q53*L53,2) -> 0
B54: 02.03.07 | C54: Vigas | E54: =PRESUPUESTOS!F54 -> 0 | F54: =IF(Q54=0,0,((M54/Q54)*J54)) -> 0 | G54: =ROUND(E54*F54,2) -> 0 | H54: =J54-F54 -> 0 | I54: =ROUND(E54*H54,2) -> 0 | J54: =PRESUPUESTOS!E54 -> 0 | K54: =ROUND(E54*J54,2) -> 0 | L54: =PRESUPUESTOS!N54 -> 0 | N54: =ROUND(M54*L54,2) -> 0 | O54: =Q54-M54 -> 0 | P54: =ROUND(O54*L54,2) -> 0 | Q54: =PRESUPUESTOS!M54 -> 0 | R54: =ROUND(Q54*L54,2) -> 0
A55: 300 | B55: 02.03.07.02 | C55: VIGAS.- CONCRETO 210 kg/cm2 - 1 piso | D55: m3 | E55: =PRESUPUESTOS!F55 -> 325.93 | F55: =IF(Q55=0,0,((M55/Q55)*J55)) -> 0 | G55: =ROUND(E55*F55,2) -> 0 | H55: =J55-F55 -> 36.12 | I55: =ROUND(E55*H55,2) -> 11772.59 | J55: =PRESUPUESTOS!E55 -> 36.12 | K55: =ROUND(E55*J55,2) -> 11772.59 | L55: =PRESUPUESTOS!N55 -> 0 | N55: =ROUND(M55*L55,2) -> 0 | O55: =Q55-M55 -> 0 | P55: =ROUND(O55*L55,2) -> 0 | Q55: =PRESUPUESTOS!M55 -> 0 | R55: =ROUND(Q55*L55,2) -> 0
A56: 400 | B56: 02.03.07.06 | C56: VIGAS.- ENCOFRADO Y DESENCOFRADO | D56: m2 | E56: =PRESUPUESTOS!F56 -> 70.38 | F56: =IF(Q56=0,0,((M56/Q56)*J56)) -> 0 | G56: =ROUND(E56*F56,2) -> 0 | H56: =J56-F56 -> 545.23 | I56: =ROUND(E56*H56,2) -> 38373.29 | J56: =PRESUPUESTOS!E56 -> 545.23 | K56: =ROUND(E56*J56,2) -> 38373.29 | L56: =PRESUPUESTOS!N56 -> 0 | N56: =ROUND(M56*L56,2) -> 0 | O56: =Q56-M56 -> 0 | P56: =ROUND(O56*L56,2) -> 0 | Q56: =PRESUPUESTOS!M56 -> 0 | R56: =ROUND(Q56*L56,2) -> 0
A57: 500 | B57: 02.03.07.08 | C57: VIGAS.- ACERO Fy=4200 kg/cm2 | D57: KG | E57: =PRESUPUESTOS!F57 -> 4.02 | F57: =IF(Q57=0,0,((M57/Q57)*J57)) -> 0 | G57: =ROUND(E57*F57,2) -> 0 | H57: =J57-F57 -> 5144.6 | I57: =ROUND(E57*H57,2) -> 20681.29 | J57: =PRESUPUESTOS!E57 -> 5144.6 | K57: =ROUND(E57*J57,2) -> 20681.29 | L57: =PRESUPUESTOS!N57 -> 0 | N57: =ROUND(M57*L57,2) -> 0 | O57: =Q57-M57 -> 0 | P57: =ROUND(O57*L57,2) -> 0 | Q57: =PRESUPUESTOS!M57 -> 0 | R57: =ROUND(Q57*L57,2) -> 0
B58: 02.03.08 | C58: Losas Macizas | E58: =PRESUPUESTOS!F58 -> 0 | F58: =IF(Q58=0,0,((M58/Q58)*J58)) -> 0 | G58: =ROUND(E58*F58,2) -> 0 | H58: =J58-F58 -> 0 | I58: =ROUND(E58*H58,2) -> 0 | J58: =PRESUPUESTOS!E58 -> 0 | K58: =ROUND(E58*J58,2) -> 0 | L58: =PRESUPUESTOS!N58 -> 0 | N58: =ROUND(M58*L58,2) -> 0 | O58: =Q58-M58 -> 0 | P58: =ROUND(O58*L58,2) -> 0 | Q58: =PRESUPUESTOS!M58 -> 0 | R58: =ROUND(Q58*L58,2) -> 0
A59: 300 | B59: 02.03.08.01 | C59: LOSAS MACIZAS.- CONC.210 kg/cm2 - 1 PISO | D59: M3 | E59: =PRESUPUESTOS!F59 -> 325.93 | F59: =IF(Q59=0,0,((M59/Q59)*J59)) -> 0 | G59: =ROUND(E59*F59,2) -> 0 | H59: =J59-F59 -> 0.63 | I59: =ROUND(E59*H59,2) -> 205.34 | J59: =PRESUPUESTOS!E59 -> 0.63 | K59: =ROUND(E59*J59,2) -> 205.34 | L59: =PRESUPUESTOS!N59 -> 0 | N59: =ROUND(M59*L59,2) -> 0 | O59: =Q59-M59 -> 0 | P59: =ROUND(O59*L59,2) -> 0 | Q59: =PRESUPUESTOS!M59 -> 0 | R59: =ROUND(Q59*L59,2) -> 0
A60: 400 | B60: 02.03.08.03 | C60: LOSAS MACIZAS.- ENCOFRADO Y DESENCOFRADO | D60: m2 | E60: =PRESUPUESTOS!F60 -> 55.43 | F60: =IF(Q60=0,0,((M60/Q60)*J60)) -> 0 | G60: =ROUND(E60*F60,2) -> 0 | H60: =J60-F60 -> 6.54 | I60: =ROUND(E60*H60,2) -> 362.51 | J60: =PRESUPUESTOS!E60 -> 6.54 | K60: =ROUND(E60*J60,2) -> 362.51 | L60: =PRESUPUESTOS!N60 -> 0 | N60: =ROUND(M60*L60,2) -> 0 | O60: =Q60-M60 -> 0 | P60: =ROUND(O60*L60,2) -> 0 | Q60: =PRESUPUESTOS!M60 -> 0 | R60: =ROUND(Q60*L60,2) -> 0
A61: 500 | B61: 02.03.08.04 | C61: LOSAS MACIZAS.- ACERO Fy=4,200 kg/cm2 | D61: KG | E61: =PRESUPUESTOS!F61 -> 4.02 | F61: =IF(Q61=0,0,((M61/Q61)*J61)) -> 0 | G61: =ROUND(E61*F61,2) -> 0 | H61: =J61-F61 -> 73.15 | I61: =ROUND(E61*H61,2) -> 294.06 | J61: =PRESUPUESTOS!E61 -> 73.15 | K61: =ROUND(E61*J61,2) -> 294.06 | L61: =PRESUPUESTOS!N61 -> 0 | N61: =ROUND(M61*L61,2) -> 0 | O61: =Q61-M61 -> 0 | P61: =ROUND(O61*L61,2) -> 0 | Q61: =PRESUPUESTOS!M61 -> 0 | R61: =ROUND(Q61*L61,2) -> 0
B62: 02.03.09 | C62: Losas Aligeradas | E62: =PRESUPUESTOS!F62 -> 0 | F62: =IF(Q62=0,0,((M62/Q62)*J62)) -> 0 | G62: =ROUND(E62*F62,2) -> 0 | H62: =J62-F62 -> 0 | I62: =ROUND(E62*H62,2) -> 0 | J62: =PRESUPUESTOS!E62 -> 0 | K62: =ROUND(E62*J62,2) -> 0 | L62: =PRESUPUESTOS!N62 -> 0 | N62: =ROUND(M62*L62,2) -> 0 | O62: =Q62-M62 -> 0 | P62: =ROUND(O62*L62,2) -> 0 | Q62: =PRESUPUESTOS!M62 -> 0 | R62: =ROUND(Q62*L62,2) -> 0
A63: 300 | B63: 02.03.09.01 | C63: LOSA ALIGERADA - CONCRETO 210 kg/cm2 - 1 PISO | D63: m3 | E63: =PRESUPUESTOS!F63 -> 315.52 | F63: =IF(Q63=0,0,((M63/Q63)*J63)) -> 0 | G63: =ROUND(E63*F63,2) -> 0 | H63: =J63-F63 -> 2.13 | I63: =ROUND(E63*H63,2) -> 672.06 | J63: =PRESUPUESTOS!E63 -> 2.13 | K63: =ROUND(E63*J63,2) -> 672.06 | L63: =PRESUPUESTOS!N63 -> 0 | N63: =ROUND(M63*L63,2) -> 0 | O63: =Q63-M63 -> 0 | P63: =ROUND(O63*L63,2) -> 0 | Q63: =PRESUPUESTOS!M63 -> 0 | R63: =ROUND(Q63*L63,2) -> 0
A64: 400 | B64: 02.03.09.03 | C64: LOSA ALIGERADA.- ENCOFRADO Y DESENCOFRADO | D64: m2 | E64: =PRESUPUESTOS!F64 -> 43.61 | F64: =IF(Q64=0,0,((M64/Q64)*J64)) -> 0 | G64: =ROUND(E64*F64,2) -> 0 | H64: =J64-F64 -> 24.72 | I64: =ROUND(E64*H64,2) -> 1078.04 | J64: =PRESUPUESTOS!E64 -> 24.72 | K64: =ROUND(E64*J64,2) -> 1078.04 | L64: =PRESUPUESTOS!N64 -> 0 | N64: =ROUND(M64*L64,2) -> 0 | O64: =Q64-M64 -> 0 | P64: =ROUND(O64*L64,2) -> 0 | Q64: =PRESUPUESTOS!M64 -> 0 | R64: =ROUND(Q64*L64,2) -> 0
A65: 500 | B65: 02.03.09.04 | C65: LOSA ALIGERADA.- ACERO Fy=4,200 kg/cm2 | D65: KG | E65: =PRESUPUESTOS!F65 -> 4.02 | F65: =IF(Q65=0,0,((M65/Q65)*J65)) -> 0 | G65: =ROUND(E65*F65,2) -> 0 | H65: =J65-F65 -> 93.93 | I65: =ROUND(E65*H65,2) -> 377.6 | J65: =PRESUPUESTOS!E65 -> 93.93 | K65: =ROUND(E65*J65,2) -> 377.6 | L65: =PRESUPUESTOS!N65 -> 0 | N65: =ROUND(M65*L65,2) -> 0 | O65: =Q65-M65 -> 0 | P65: =ROUND(O65*L65,2) -> 0 | Q65: =PRESUPUESTOS!M65 -> 0 | R65: =ROUND(Q65*L65,2) -> 0
A66: 300 | B66: 02.03.09.05 | C66: LOSA ALIGERADA.- LADR. HUECO 15x30x30 | D66: und | E66: =PRESUPUESTOS!F66 -> 2.49 | F66: =IF(Q66=0,0,((M66/Q66)*J66)) -> 0 | G66: =ROUND(E66*F66,2) -> 0 | H66: =J66-F66 -> 205.92 | I66: =ROUND(E66*H66,2) -> 512.74 | J66: =PRESUPUESTOS!E66 -> 205.92 | K66: =ROUND(E66*J66,2) -> 512.74 | L66: =PRESUPUESTOS!N66 -> 0 | N66: =ROUND(M66*L66,2) -> 0 | O66: =Q66-M66 -> 0 | P66: =ROUND(O66*L66,2) -> 0 | Q66: =PRESUPUESTOS!M66 -> 0 | R66: =ROUND(Q66*L66,2) -> 0
B67: 02.03.15 | C67: Gradas Armadas en Pisos | E67: =PRESUPUESTOS!F67 -> 0 | F67: =IF(Q67=0,0,((M67/Q67)*J67)) -> 0 | G67: =ROUND(E67*F67,2) -> 0 | H67: =J67-F67 -> 0 | I67: =ROUND(E67*H67,2) -> 0 | J67: =PRESUPUESTOS!E67 -> 0 | K67: =ROUND(E67*J67,2) -> 0 | L67: =PRESUPUESTOS!N67 -> 0 | N67: =ROUND(M67*L67,2) -> 0 | O67: =Q67-M67 -> 0 | P67: =ROUND(O67*L67,2) -> 0 | Q67: =PRESUPUESTOS!M67 -> 0 | R67: =ROUND(Q67*L67,2) -> 0
A68: 300 | B68: 02.03.15.01 | C68: GRADAS EN PISO, CONCRETO F'c=175 kg/cm2. | D68: m2 | E68: =PRESUPUESTOS!F68 -> 80.04 | F68: =IF(Q68=0,0,((M68/Q68)*J68)) -> 0 | G68: =ROUND(E68*F68,2) -> 0 | H68: =J68-F68 -> 12.31 | I68: =ROUND(E68*H68,2) -> 985.29 | J68: =PRESUPUESTOS!E68 -> 12.31 | K68: =ROUND(E68*J68,2) -> 985.29 | L68: =PRESUPUESTOS!N68 -> 0 | N68: =ROUND(M68*L68,2) -> 0 | O68: =Q68-M68 -> 0 | P68: =ROUND(O68*L68,2) -> 0 | Q68: =PRESUPUESTOS!M68 -> 0 | R68: =ROUND(Q68*L68,2) -> 0
A69: 400 | B69: 02.03.15.03 | C69: GRADAS, ENCOFRADO Y DESENCOFRADO | D69: m2 | E69: =PRESUPUESTOS!F69 -> 41.15 | F69: =IF(Q69=0,0,((M69/Q69)*J69)) -> 0 | G69: =ROUND(E69*F69,2) -> 0 | H69: =J69-F69 -> 6.96 | I69: =ROUND(E69*H69,2) -> 286.4 | J69: =PRESUPUESTOS!E69 -> 6.96 | K69: =ROUND(E69*J69,2) -> 286.4 | L69: =PRESUPUESTOS!N69 -> 0 | N69: =ROUND(M69*L69,2) -> 0 | O69: =Q69-M69 -> 0 | P69: =ROUND(O69*L69,2) -> 0 | Q69: =PRESUPUESTOS!M69 -> 0 | R69: =ROUND(Q69*L69,2) -> 0
A70: 500 | B70: 02.03.15.04 | C70: GRADAS EN PISO, ACERO fy=4200kg/cm2 | D70: kg | E70: =PRESUPUESTOS!F70 -> 4.02 | F70: =IF(Q70=0,0,((M70/Q70)*J70)) -> 0 | G70: =ROUND(E70*F70,2) -> 0 | H70: =J70-F70 -> 83.01 | I70: =ROUND(E70*H70,2) -> 333.7 | J70: =PRESUPUESTOS!E70 -> 83.01 | K70: =ROUND(E70*J70,2) -> 333.7 | L70: =PRESUPUESTOS!N70 -> 0 | N70: =ROUND(M70*L70,2) -> 0 | O70: =Q70-M70 -> 0 | P70: =ROUND(O70*L70,2) -> 0 | Q70: =PRESUPUESTOS!M70 -> 0 | R70: =ROUND(Q70*L70,2) -> 0
C71: COSTO DIRECTO | G71: =SUM(G7:G70) -> 0 | I71: =SUM(I7:I70) -> 960724.52 | K71: =SUM(K7:K70) -> 960724.52 | N71: =SUM(N7:N70) -> 0 | P71: =SUM(P7:P70) -> 1374.45 | R71: =SUM(R7:R70) -> 1374.45
C72: GASTOS GENERALES (10%) | G72: =ROUND(G71*0.1,2) -> 0 | I72: =ROUND(I71*0.1,2) -> 96072.45 | K72: =ROUND(K71*0.1,2) -> 96072.45 | N72: =ROUND(N71*0.1,2) -> 0 | P72: =ROUND(P71*0.1,2) -> 137.45 | R72: =ROUND(R71*0.1,2) -> 137.45
C73: UTILIDAD (8%) | G73: =ROUND(G71*0.08,2) -> 0 | I73: =ROUND(I71*0.08,2) -> 76857.96 | K73: =ROUND(K71*0.08,2) -> 76857.96
C74: SUBTOTAL | G74: =SUM(G71:G73) -> 0 | I74: =SUM(I71:I73) -> 1133654.9 | K74: =SUM(K71:K73) -> 1133654.9 | N74: =SUM(N71:N73) -> 0 | P74: =SUM(P71:P73) -> 1511.9 | R74: =SUM(R71:R73) -> 1511.9
C75: IGV (18.00%) | G75: =ROUND(G74*0.18,2) -> 0 | I75: =ROUND(I74*0.18,2) -> 204057.89 | K75: =ROUND(K74*0.18,2) -> 204057.89 | N75: =ROUND(N74*0.18,2) -> 0 | P75: =ROUND(P74*0.18,2) -> 272.14 | R75: =ROUND(R74*0.18,2) -> 272.14
C76: COSTO TOTAL (INC. IGV) | G76: =SUM(G74:G75) -> 0 | I76: =SUM(I74:I75) -> 1337712.8 | K76: =SUM(K74:K75) -> 1337712.8 | N76: =SUM(N74:N75) -> 0 | P76: =SUM(P74:P75) -> 1784.04 | R76: =SUM(R74:R75) -> 1784.04
J81: 130 | L81: 220 | M81: reales
J83: =+L83*0.59 -> 95.3145 | L83: 161.55 | M83: presup
L85: =+J81/L81 -> 0.59090909

Sheet RESUMEN - ANALISIS
A1: RESUMEN
A3: PROYECTO: | B3: I.E. N° 1182 "EL BOSQUE" - CERCO + INGRESOS Y CASETAS
C4: ANALISIS DE PRECIOS VENTA | F4: COSTO PREVISTO | I4: COSTO REAL
A5: CODIGO | B5: PARTIDA DE CONTROL | C5: COSTO TOTAL VENTA | D5: % | E5: COSTO EJECUTADO VENTA | F5: COSTO TOTAL META | G5: % | H5: COSTO EJECUTADO META | I5: COSTO EJECUTADO REAL | J5: MANO DE OBRA | K5: MATERIALES | L5: EQUIPOS | M5: SERVICIOS | N5: SUBCONTRATOS | O5: BRECHA (META - REAL)
B6: PRESUPUESTO CONTRACTUAL
A7: 100 | B7: OBRAS PROVISIONALES | C7: =SUMIF(COMPARATIVO!$A$7:$A$70,'RESUMEN - ANALISIS'!A7,COMPARATIVO!$K$7:$K$70) -> 3661.14 | D7: =E7/C7 -> 0 | E7: =SUMIF(COMPARATIVO!$A$7:$A$70,'RESUMEN - ANALISIS'!A7,COMPARATIVO!$G$7:$G$70) -> 0 | F7: =SUMIF(COMPARATIVO!$A$7:$A$70,'RESUMEN - ANALISIS'!A7,COMPARATIVO!$R$7:$R$70) -> 1374.45 | G7: =H7/F7 -> 0 | H7: =SUMIF(COMPARATIVO!$A$7:$A$70,'RESUMEN - ANALISIS'!A7,COMPARATIVO!$N$7:$N$70) -> 0 | I7: =SUM(J7:N7) -> 229.25 | N7: 229.25 | O7: =H7-I7 -> -229.25
A8: 200 | B8: MOVIMIENTO DE TIERRAS | C8: =SUMIF(COMPARATIVO!$A$7:$A$70,'RESUMEN - ANALISIS'!A8,COMPARATIVO!$K$7:$K$70) -> 159518.36 | D8: =E8/C8 -> 0 | E8: =SUMIF(COMPARATIVO!$A$7:$A$70,'RESUMEN - ANALISIS'!A8,COMPARATIVO!$G$7:$G$70) -> 0 | F8: =SUMIF(COMPARATIVO!$A$7:$A$70,'RESUMEN - ANALISIS'!A8,COMPARATIVO!$R$7:$R$70) -> 0 | G8: =H8/F8 -> #DIV/0! | H8: =SUMIF(COMPARATIVO!$A$7:$A$70,'RESUMEN - ANALISIS'!A8,COMPARATIVO!$N$7:$N$70) -> 0 | I8: =SUM(J8:N8) -> 7319.59 | J8: 200 | N8: 7119.59 | O8: =H8-I8 -> -7319.59
A9: 300 | B9: CONCRETO | C9: =SUMIF(COMPARATIVO!$A$7:$A$70,'RESUMEN - ANALISIS'!A9,COMPARATIVO!$K$7:$K$70) -> 360886.42 | D9: =E9/C9 -> 0 | E9: =SUMIF(COMPARATIVO!$A$7:$A$70,'RESUMEN - ANALISIS'!A9,COMPARATIVO!$G$7:$G$70) -> 0 | F9: =SUMIF(COMPARATIVO!$A$7:$A$70,'RESUMEN - ANALISIS'!A9,COMPARATIVO!$R$7:$R$70) -> 0 | G9: =H9/F9 -> #DIV/0! | H9: =SUMIF(COMPARATIVO!$A$7:$A$70,'RESUMEN - ANALISIS'!A9,COMPARATIVO!$N$7:$N$70) -> 0 | I9: =SUM(J9:N9) -> 17915.1 | N9: 17915.1 | O9: =H9-I9 -> -17915.1
A10: 400 | B10: ENCOFRADO | C10: =SUMIF(COMPARATIVO!$A$7:$A$70,'RESUMEN - ANALISIS'!A10,COMPARATIVO!$K$7:$K$70) -> 221395.36 | D10: =E10/C10 -> 0 | E10: =SUMIF(COMPARATIVO!$A$7:$A$70,'RESUMEN - ANALISIS'!A10,COMPARATIVO!$G$7:$G$70) -> 0 | F10: =SUMIF(COMPARATIVO!$A$7:$A$70,'RESUMEN - ANALISIS'!A10,COMPARATIVO!$R$7:$R$70) -> 0 | G10: =H10/F10 -> #DIV/0! | H10: =SUMIF(COMPARATIVO!$A$7:$A$70,'RESUMEN - ANALISIS'!A10,COMPARATIVO!$N$7:$N$70) -> 0 | I10: =SUM(J10:N10) -> 0
A11: 500 | B11: ACERO | C11: =SUMIF(COMPARATIVO!$A$7:$A$70,'RESUMEN - ANALISIS'!A11,COMPARATIVO!$K$7:$K$70) -> 215263.24 | D11: =E11/C11 -> 0 | E11: =SUMIF(COMPARATIVO!$A$7:$A$70,'RESUMEN - ANALISIS'!A11,COMPARATIVO!$G$7:$G$70) -> 0 | F11: =SUMIF(COMPARATIVO!$A$7:$A$70,'RESUMEN - ANALISIS'!A11,COMPARATIVO!$R$7:$R$70) -> 0 | G11: =H11/F11 -> #DIV/0! | H11: =SUMIF(COMPARATIVO!$A$7:$A$70,'RESUMEN - ANALISIS'!A11,COMPARATIVO!$N$7:$N$70) -> 0 | I11: =SUM(J11:N11) -> 696.08 | J11: 55 | N11: 641.08 | O11: =H11-I11 -> -696.08
B12: TOTALES | C12: =SUM(C7:C11) -> 960724.52 | E12: =SUM(E7:E11) -> 0 | F12: =SUM(F7:F11) -> 1374.45 | H12: =SUM(H7:H11) -> 0 | I12: =SUM(I7:I11) -> 26160.02 | J12: =SUM(J7:J11) -> 255 | K12: =SUM(K7:K11) -> 0 | L12: =SUM(L7:L11) -> 0 | M12: =SUM(M7:M11) -> 0 | N12: =SUM(N7:N11) -> 25905.02 | O12: =SUM(O7:O11) -> -26160.02
B15: RESUMEN | C15: ACUM A MARZO 2023 | E15: META TOTAL | F15: META ANTERIOR | H15: DIFERENCIA
B17: TOTAL COSTO REAL | C17: =I12 -> 26160.02 | E17: =F12 -> 1374.45 | H17: =+F17-E17 -> -1374.45
B19: TOTAL COSTO VENTA | C19: =E12 -> 0 | E19: =C12 -> 960724.52 | H19: =+F19-E19 -> -960724.52
B21: RESULTADO OPERATIVO | C21: =C19-C17 -> -26160.02 | E21: =E19-E17 -> 959350.07 | F21: =F19-F17 -> 0
B22: MARGEN DE UTILIDAD | C22: =C21/C19 -> #DIV/0! | E22: =E21/E19 -> 0.99856936 | F22: =F21/F19 -> #DIV/0!

Sheet DIFERENCIAS
C3: VENTA (S/) | E3: META TOTAL (S/) | I3: META TOTAL (MES ANTERIOR) (S/) | M3: META INICIAL (S/)
A4: UC | B4: DESCRIPCIÓN | C4: INGRESO PREVISTO TOTAL | E4: COSTO PREVISTO | F4: RENTABILIDAD | I4: COSTO PREVISTO | J4: RENTABILIDAD | M4: COSTO PREVISTO | N4: RENTABILIDAD | Q4: DESVIACIONES (META INICIAL TOTAL- META TOTAL)
B5: PRESUPUESTO CONTRACTUAL
A6: 100 | B6: OBRAS PROVISIONALES | C6: =+'RESUMEN - ANALISIS'!C7 -> 3661.14 | E6: =+'RESUMEN - ANALISIS'!F7 -> 1374.45 | F6: =C6-E6 -> 2286.69 | G6: =+F6/C6 -> 0.62458415 | J6: =C6-I6 -> 3661.14 | K6: =J6/C6 -> 1 | N6: =C6-M6 -> 3661.14 | O6: =N6/C6 -> 1 | Q6: =E6-M6 -> 1374.45 | R6: =M6/E6 -> 0
A7: 200 | B7: MOVIMIENTO DE TIERRAS | C7: =+'RESUMEN - ANALISIS'!C8 -> 159518.36 | E7: =+'RESUMEN - ANALISIS'!F8 -> 0 | F7: =C7-E7 -> 159518.36 | G7: =+F7/C7 -> 1 | J7: =C7-I7 -> 159518.36 | K7: =J7/C7 -> 1 | N7: =C7-M7 -> 159518.36 | O7: =N7/C7 -> 1 | Q7: =E7-M7 -> 0 | R7: =M7/E7 -> #DIV/0!
A8: 300 | B8: CONCRETO | C8: =+'RESUMEN - ANALISIS'!C9 -> 360886.42 | E8: =+'RESUMEN - ANALISIS'!F9 -> 0 | F8: =C8-E8 -> 360886.42 | G8: =+F8/C8 -> 1 | J8: =C8-I8 -> 360886.42 | K8: =J8/C8 -> 1 | N8: =C8-M8 -> 360886.42 | O8: =N8/C8 -> 1 | Q8: =E8-M8 -> 0 | R8: =M8/E8 -> #DIV/0!
A9: 400 | B9: ENCOFRADO | C9: =+'RESUMEN - ANALISIS'!C10 -> 221395.36 | E9: =+'RESUMEN - ANALISIS'!F10 -> 0 | F9: =C9-E9 -> 221395.36 | G9: =+F9/C9 -> 1 | J9: =C9-I9 -> 221395.36 | K9: =J9/C9 -> 1 | N9: =C9-M9 -> 221395.36 | O9: =N9/C9 -> 1 | Q9: =E9-M9 -> 0 | R9: =M9/E9 -> #DIV/0!
A10: 500 | B10: ACERO | C10: =+'RESUMEN - ANALISIS'!C11 -> 215263.24 | E10: =+'RESUMEN - ANALISIS'!F11 -> 0 | F10: =C10-E10 -> 215263.24 | G10: =+F10/C10 -> 1 | J10: =C10-I10 -> 215263.24 | K10: =J10/C10 -> 1 | N10: =C10-M10 -> 215263.24 | O10: =N10/C10 -> 1 | Q10: =E10-M10 -> 0 | R10: =M10/E10 -> #DIV/0!
A11: TOTALES VENTA Y COSTE DIRECTO | C11: =SUM(C5:C10) -> 960724.52 | E11: =SUM(E5:E10) -> 1374.45 | F11: =C11-E11 -> 959350.07 | G11: =F11/C11 -> 0.99856936 | I11: =SUM(I5:I10) -> 0 | J11: =C11-I11 -> 960724.52 | K11: =J11/C11 -> 1 | M11: =SUM(M5:M10) -> 0 | N11: =C11-M11 -> 960724.52 | O11: =N11/C11 -> 1 | Q11: =SUM(Q5:Q10) -> 1374.45 | R11: =E11/M11 -> #DIV/0!

Sheet COSTOS INCURRIDOS
A2: ITEM | B2: DESCRIPCION | C2: PROVEEDOR | D2: UNIDAD | E2: CANTIDAD | F2: P.U. | G2: SUBTOTAL | H2: PARTIDA DE CONTROL | I2: TIPO DE COSTO | J2: METRADO UTILIZADO | K2: SUB TOTAL
B3: ORDENES DE COMPRA
A4: 1 | B4: MATERIAL AFIRMADO | C4: CANTERA ECONOMICA | D4: m3 | E4: 500 | F4: 120 | G4: =+E4*F4 -> 60000 | H4: 200 | I4: MATERIALES | J4: 130 | K4: =+J4*F4 -> 15600
B11: ORDENES DE SERVICIO
A12: 1 | B12: ALQUILER DE VOLQUETES | C12: NEGOCIOS DIAZ | D12: hm | E12: 50 | F12: 180 | G12: =+E12*F12 -> 9000 | H12: 200 | I12: SERVICIOS | J12: 35 | K12: =+J12*F12 -> 6300

Sheet CRONOG CONT VENTA
A1: CRONOGRAMA VALORIZADO DE OBRA - PROGRAMACION VENTA
A3: PROYECTO: | B3: I.E. N° 1182 "EL BOSQUE" - CERCO + INGRESOS Y CASETAS
A5: ITEM | B5: DESCRIPCION | C5: UND | D5: CONTRACTUAL | G5: PROGRAMACION
D6: METRADO | E6: P.U. (S/.) | F6: PARCIAL (S/.) | G6: 45474 | H6: 45505 | I6: 45536 | J6: 45566 | K6: 45597
A7: 01 | B7: OBRAS PROVISIONALES, TRABAJOS PRELIMINARES, SEGURIDAD Y SALUD
A8: 01.02 | B8: Trabajos Preliminares
A9: 01.02.04 | B9: Trazo, Niveles y Replanteo
A10: 01.02.04.01 | B10: TRAZO Y REPLANTEO PRELIMINAR | C10: M2 | D10: 897.34 | E10: 2.04 | F10: 1830.57 | G10: =$F10*N10 -> 915.285 | H10: =$F10*O10 -> 915.285 | I10: =$F10*P10 -> 0 | J10: =$F10*Q10 -> 0 | K10: =$F10*R10 -> 0 | L10: =F10-SUM(G10:K10) -> 0 | N10: 0.5 | O10: 0.5
A11: 01.02.04.02 | B11: TRAZO Y REPLANTEO DURANTE EL PROCESO | C11: m2 | D11: 897.34 | E11: 2.04 | F11: 1830.57 | G11: =$F11*N11 -> 457.6425 | H11: =$F11*O11 -> 457.6425 | I11: =$F11*P11 -> 457.6425 | J11: =$F11*Q11 -> 457.6425 | K11: =$F11*R11 -> 0 | L11: =F11-SUM(G11:K11) -> 0 | N11: 0.25 | O11: 0.25 | P11: 0.25 | Q11: 0.25
A12: 02 | B12: ESTRUCTURAS
A13: 02.01 | B13: Movimiento de Tierras
A14: 02.01.01 | B14: Excavaciones
A15: 02.01.01.01 | B15: EXCAV.ZANJAS Y ZAPATA RT>2kg/cm2 H=1.5m | C15: m3 | D15: 41.9 | E15: 46.74 | F15: 1958.41 | G15: =$F15*N15 -> 979.205 | H15: =$F15*O15 -> 979.205 | I15: =$F15*P15 -> 0 | J15: =$F15*Q15 -> 0 | K15: =$F15*R15 -> 0 | L15: =F15-SUM(G15:K15) -> 0 | N15: 0.5 | O15: 0.5
A16: 02.01.01.02 | B16: EXCAV.ZANJAS Y ZAPATA RT>2kg/cm2 H=2.0m | C16: m3 | D16: 1975.16 | E16: 50.99 | F16: 100713.41 | G16: =$F16*N16 -> 50356.705 | H16: =$F16*O16 -> 50356.705 | I16: =$F16*P16 -> 0 | J16: =$F16*Q16 -> 0 | K16: =$F16*R16 -> 0 | L16: =F16-SUM(G16:K16) -> 0 | N16: 0.5 | O16: 0.5
A17: 02.01.03 | B17: Rellenos
A18: 02.01.03.01 | B18: RELLENO COMPACTADO C/EQUIPO MAT/PROPIO | C18: m3 | D18: 1197.91 | E18: 26.01 | F18: 31157.64 | G18: =$F18*N18 -> 0 | H18: =$F18*O18 -> 15578.82 | I18: =$F18*P18 -> 15578.82 | J18: =$F18*Q18 -> 0 | K18: =$F18*R18 -> 0 | L18: =F18-SUM(G18:K18) -> 0 | O18: 0.5 | P18: 0.5
A19: 02.01.04 | B19: Eliminacion de Material Excedente
A20: 02.01.04.01 | B20: ACARREO INTERNO, MATERIAL PROCEDENTE DE EXCAVACIONES | C20: m3 | D20: 68.91 | E20: 17.53 | F20: 1207.99 | G20: =$F20*N20 -> 362.397 | H20: =$F20*O20 -> 603.995 | I20: =$F20*P20 -> 241.598 | J20: =$F20*Q20 -> 0 | K20: =$F20*R20 -> 0 | L20: =F20-SUM(G20:K20) -> 0 | N20: 0.3 | O20: 0.5 | P20: 0.2
A21: 02.01.04.02 | B21: ELIMINACION MATERIAL EXCEDENTE ACARREADO | C21: M3 | D21: 68.91 | E21: 16.02 | F21: 1103.94 | G21: =$F21*N21 -> 331.182 | H21: =$F21*O21 -> 331.182 | I21: =$F21*P21 -> 441.576 | J21: =$F21*Q21 -> 0 | K21: =$F21*R21 -> 0 | L21: =F21-SUM(G21:K21) -> 0 | N21: 0.3 | O21: 0.3 | P21: 0.4
A22: 02.01.04.03 | B22: ELIMINACION MATERIAL EXCEDENTE C/MAQUINA | C22: m3 | D22: 995.9 | E22: 21.84 | F22: 21750.46 | G22: =$F22*N22 -> 6525.138 | H22: =$F22*O22 -> 6525.138 | I22: =$F22*P22 -> 8700.184 | J22: =$F22*Q22 -> 0 | K22: =$F22*R22 -> 0 | L22: =F22-SUM(G22:K22) -> 0 | N22: 0.3 | O22: 0.3 | P22: 0.4
A23: 02.01.05 | B23: Nivelacion Interior y Apisonado
A24: 02.01.05.01 | B24: ESCARIFICADO Y COMPACTACION CON PLANCHA COMPACTADORA e = 30 cm | C24: m2 | D24: 68.95 | E24: 4.72 | F24: 325.44 | G24: =$F24*N24 -> 65.088 | H24: =$F24*O24 -> 130.176 | I24: =$F24*P24 -> 130.176 | J24: =$F24*Q24 -> 0 | K24: =$F24*R24 -> 0 | L24: =F24-SUM(G24:K24) -> 0 | N24: 0.2 | O24: 0.4 | P24: 0.4
A25: 02.01.05.02 | B25: ESCARIFICADO Y COMPACTACION CON PLANCHA COMPACTADORA H=0.60m (02 CAPAS 30cm c/u) | C25: m2 | D25: 8.56 | E25: 7.85 | F25: 67.2 | G25: =$F25*N25 -> 13.44 | H25: =$F25*O25 -> 26.88 | I25: =$F25*P25 -> 26.88 | J25: =$F25*Q25 -> 0 | K25: =$F25*R25 -> 0 | L25: =F25-SUM(G25:K25) -> 0 | N25: 0.2 | O25: 0.4 | P25: 0.4
A26: 02.01.05.05 | B26: AFIRMADO DE 8" PARA PISOS,PATIOS Y VEREDAS,COMPACTADO. | C26: m2 | D26: 68.95 | E26: 15.19 | F26: 1047.35 | G26: =$F26*N26 -> 209.47 | H26: =$F26*O26 -> 418.94 | I26: =$F26*P26 -> 418.94 | J26: =$F26*Q26 -> 0 | K26: =$F26*R26 -> 0 | L26: =F26-SUM(G26:K26) -> 0 | N26: 0.2 | O26: 0.4 | P26: 0.4
A27: 02.01.05.06 | B27: AFIRMADO DE 12" EN PISOS INTERIOR/EXTERIOR,COMPACTADO. | C27: m2 | D27: 8.56 | E27: 21.79 | F27: 186.52 | G27: =$F27*N27 -> 37.304 | H27: =$F27*O27 -> 74.608 | I27: =$F27*P27 -> 74.608 | J27: =$F27*Q27 -> 0 | K27: =$F27*R27 -> 0 | L27: =F27-SUM(G27:K27) -> 0 | N27: 0.2 | O27: 0.4 | P27: 0.4
A28: 02.02 | B28: Obras de Concreto Simple
A29: 02.02.01 | B29: Falsos Cimientos
A30: 02.02.01.01 | B30: SUBCIMIENTO, SUBZAPATA MEZCLA 1:12 + 30 % P.G. | C30: m3 | D30: 323.69 | E30: 173.72 | F30: 56231.43 | G30: =$F30*N30 -> 0 | H30: =$F30*O30 -> 28115.715 | I30: =$F30*P30 -> 28115.715 | J30: =$F30*Q30 -> 0 | K30: =$F30*R30 -> 0 | L30: =F30-SUM(G30:K30) -> 0 | O30: 0.5 | P30: 0.5
A31: 02.02.02 | B31: Cimientos
A32: 02.02.02.02 | B32: CIMIENTOS CORRIDOS 1:10 + 30 % P.G. f'c >=100Kg/cm2 | C32: m3 | D32: 24.73 | E32: 179.78 | F32: 4445.96 | G32: =$F32*N32 -> 0 | H32: =$F32*O32 -> 0 | I32: =$F32*P32 -> 2222.98 | J32: =$F32*Q32 -> 2222.98 | K32: =$F32*R32 -> 0 | L32: =F32-SUM(G32:K32) -> 0 | P32: 0.5 | Q32: 0.5
A33: 02.02.02.03 | B33: CIMIENTO CORRIDO - ENCOFRADO Y DESENCOFRADO | C33: m2 | D33: 23.09 | E33: 46.17 | F33: 1066.07 | G33: =$F33*N33 -> 0 | H33: =$F33*O33 -> 426.428 | I33: =$F33*P33 -> 426.428 | J33: =$F33*Q33 -> 213.214 | K33: =$F33*R33 -> 0 | L33: =F33-SUM(G33:K33) -> 0 | O33: 0.4 | P33: 0.4 | Q33: 0.2
A34: 02.02.02.04 | B34: CALZADURA: CONCRETO C:H 1:10 + 30 % P.G. | C34: m3 | D34: 163.82 | E34: 179.78 | F34: 29451.56 | G34: =$F34*N34 -> 29451.56 | H34: =$F34*O34 -> 0 | I34: =$F34*P34 -> 0 | J34: =$F34*Q34 -> 0 | K34: =$F34*R34 -> 0 | L34: =F34-SUM(G34:K34) -> 0 | N34: 1
A35: 02.02.02.05 | B35: CALZADURA: ENCOFRADO Y DESENCOFRADO | C35: m2 | D35: 327.63 | E35: 37.47 | F35: 12276.3 | G35: =$F35*N35 -> 12276.3 | H35: =$F35*O35 -> 0 | I35: =$F35*P35 -> 0 | J35: =$F35*Q35 -> 0 | K35: =$F35*R35 -> 0 | L35: =F35-SUM(G35:K35) -> 0 | N35: 1
A36: 02.02.03 | B36: Sobrecimientos
A37: 02.02.03.01 | B37: SOBRECIMIENTO, CONCRETO 1:8 + 25% P.M. f'c >=100Kg/cm2 | C37: m3 | D37: 3.21 | E37: 260.59 | F37: 836.49 | G37: =$F37*N37 -> 0 | H37: =$F37*O37 -> 0 | I37: =$F37*P37 -> 418.245 | J37: =$F37*Q37 -> 418.245 | K37: =$F37*R37 -> 0 | L37: =F37-SUM(G37:K37) -> 0 | P37: 0.5 | Q37: 0.5
A38: 02.02.03.02 | B38: SOBRECIMIENTO, ENCOFRADO Y DESENCOFRADO | C38: m2 | D38: 43.95 | E38: 37.7 | F38: 1656.92 | G38: =$F38*N38 -> 0 | H38: =$F38*O38 -> 662.768 | I38: =$F38*P38 -> 662.768 | J38: =$F38*Q38 -> 331.384 | K38: =$F38*R38 -> 0 | L38: =F38-SUM(G38:K38) -> 0 | O38: 0.4 | P38: 0.4 | Q38: 0.2
A39: 02.03 | B39: Obras de Concreto Armado
A40: 02.03.02 | B40: Zapatas
A41: 02.03.02.01 | B41: ZAPATAS.- CONCRETO 210 kg/cm2 | C41: m3 | D41: 396.75 | E41: 292.79 | F41: 116164.43 | G41: =$F41*N41 -> 34849.329 | H41: =$F41*O41 -> 81315.101 | I41: =$F41*P41 -> 0 | J41: =$F41*Q41 -> 0 | K41: =$F41*R41 -> 0 | L41: =F41-SUM(G41:K41) -> 0 | N41: 0.3 | O41: 0.7
A42: 02.03.02.03 | B42: ZAPATAS.- ACERO Fy=4200 kg/cm2 | C42: KG | D42: 17534.91 | E42: 4.02 | F42: 70490.34 | G42: =$F42*N42 -> 21147.102 | H42: =$F42*O42 -> 49343.238 | I42: =$F42*P42 -> 0 | J42: =$F42*Q42 -> 0 | K42: =$F42*R42 -> 0 | L42: =F42-SUM(G42:K42) -> 0 | N42: 0.3 | O42: 0.7
A43: 02.03.05 | B43: Placas y Muros de Contención
A44: 02.03.05.02 | B44: PLACAS, CONCRETO F'c=210 kg/cm2 - 1 piso | C44: m3 | D44: 6.69 | E44: 454.82 | F44: 3042.75 | G44: =$F44*N44 -> 0 | H44: =$F44*O44 -> 912.825 | I44: =$F44*P44 -> 912.825 | J44: =$F44*Q44 -> 1217.1 | K44: =$F44*R44 -> 0 | L44: =F44-SUM(G44:K44) -> 0 | O44: 0.3 | P44: 0.3 | Q44: 0.4
A45: 02.03.05.04 | B45: PLACAS, ENCOFRADO Y DESENCOFRADO | C45: m2 | D45: 74.18 | E45: 59.78 | F45: 4434.48 | G45: =$F45*N45 -> 0 | H45: =$F45*O45 -> 1330.344 | I45: =$F45*P45 -> 1330.344 | J45: =$F45*Q45 -> 1773.792 | K45: =$F45*R45 -> 0 | L45: =F45-SUM(G45:K45) -> 0 | O45: 0.3 | P45: 0.3 | Q45: 0.4
A46: 02.03.05.05 | B46: PLACAS, ACERO Fy=4200 kg/cm2 | C46: KG | D46: 419.35 | E46: 4.02 | F46: 1685.79 | G46: =$F46*N46 -> 0 | H46: =$F46*O46 -> 505.737 | I46: =$F46*P46 -> 505.737 | J46: =$F46*Q46 -> 674.316 | K46: =$F46*R46 -> 0 | L46: =F46-SUM(G46:K46) -> 0 | O46: 0.3 | P46: 0.3 | Q46: 0.4
A47: 02.03.05.07 | B47: MUROS DE CONTENC.- CONCRETO 210 kg/cm2 | C47: m3 | D47: 256.52 | E47: 417.41 | F47: 107074.01 | G47: =$F47*N47 -> 0 | H47: =$F47*O47 -> 32122.203 | I47: =$F47*P47 -> 32122.203 | J47: =$F47*Q47 -> 42829.604 | K47: =$F47*R47 -> 0 | L47: =F47-SUM(G47:K47) -> 0 | O47: 0.3 | P47: 0.3 | Q47: 0.4
A48: 02.03.05.09 | B48: MUROS DE CONTENC.- ENCOF. Y DESENCOFRADO | C48: m2 | D48: 2096.19 | E48: 51.21 | F48: 107345.89 | G48: =$F48*N48 -> 0 | H48: =$F48*O48 -> 32203.767 | I48: =$F48*P48 -> 32203.767 | J48: =$F48*Q48 -> 42938.356 | K48: =$F48*R48 -> 0 | L48: =F48-SUM(G48:K48) -> 0 | O48: 0.3 | P48: 0.3 | Q48: 0.4
A49: 02.03.05.11 | B49: MUROS DE CONTENC.- ACERO Fy=4200 kg/cm2 | C49: kg | D49: 18595.1 | E49: 4.02 | F49: 74752.3 | G49: =$F49*N49 -> 0 | H49: =$F49*O49 -> 22425.69 | I49: =$F49*P49 -> 22425.69 | J49: =$F49*Q49 -> 29900.92 | K49: =$F49*R49 -> 0 | L49: =F49-SUM(G49:K49) -> 0 | O49: 0.3 | P49: 0.3 | Q49: 0.4
A50: 02.03.06 | B50: Columnas
A51: 02.03.06.02 | B51: COLUMNAS - CONCRETO 210 KG/CM² - 1 PISO | C51: m3 | D51: 66.63 | E51: 442.62 | F51: 29491.77 | G51: =$F51*N51 -> 0 | H51: =$F51*O51 -> 0 | I51: =$F51*P51 -> 8847.531 | J51: =$F51*Q51 -> 8847.531 | K51: =$F51*R51 -> 11796.708 | L51: =F51-SUM(G51:K51) -> 0 | P51: 0.3 | Q51: 0.3 | R51: 0.4
A52: 02.03.06.06 | B52: COLUMNAS.- ENCOFRADO Y DESENCOFRADO | C52: m2 | D52: 901.38 | E52: 60.48 | F52: 54515.46 | G52: =$F52*N52 -> 0 | H52: =$F52*O52 -> 0 | I52: =$F52*P52 -> 16354.638 | J52: =$F52*Q52 -> 16354.638 | K52: =$F52*R52 -> 21806.184 | L52: =F52-SUM(G52:K52) -> 0 | P52: 0.3 | Q52: 0.3 | R52: 0.4
A53: 02.03.06.10 | B53: COLUMNAS.- ACERO Fy=4200 kg/cm2 | C53: KG | D53: 11604.02 | E53: 4.02 | F53: 46648.16 | G53: =$F53*N53 -> 0 | H53: =$F53*O53 -> 0 | I53: =$F53*P53 -> 13994.448 | J53: =$F53*Q53 -> 13994.448 | K53: =$F53*R53 -> 18659.264 | L53: =F53-SUM(G53:K53) -> 0 | P53: 0.3 | Q53: 0.3 | R53: 0.4
A54: 02.03.07 | B54: Vigas
A55: 02.03.07.02 | B55: VIGAS.- CONCRETO 210 kg/cm2 - 1 piso | C55: m3 | D55: 36.12 | E55: 325.93 | F55: 11772.59 | G55: =$F55*N55 -> 0 | H55: =$F55*O55 -> 0 | I55: =$F55*P55 -> 3531.777 | J55: =$F55*Q55 -> 3531.777 | K55: =$F55*R55 -> 4709.036 | L55: =F55-SUM(G55:K55) -> 0 | P55: 0.3 | Q55: 0.3 | R55: 0.4
A56: 02.03.07.06 | B56: VIGAS.- ENCOFRADO Y DESENCOFRADO | C56: m2 | D56: 545.23 | E56: 70.38 | F56: 38373.29 | G56: =$F56*N56 -> 0 | H56: =$F56*O56 -> 0 | I56: =$F56*P56 -> 11511.987 | J56: =$F56*Q56 -> 11511.987 | K56: =$F56*R56 -> 15349.316 | L56: =F56-SUM(G56:K56) -> 0 | P56: 0.3 | Q56: 0.3 | R56: 0.4
A57: 02.03.07.08 | B57: VIGAS.- ACERO Fy=4200 kg/cm2 | C57: KG | D57: 5144.6 | E57: 4.02 | F57: 20681.29 | G57: =$F57*N57 -> 0 | H57: =$F57*O57 -> 0 | I57: =$F57*P57 -> 6204.387 | J57: =$F57*Q57 -> 6204.387 | K57: =$F57*R57 -> 8272.516 | L57: =F57-SUM(G57:K57) -> 0 | P57: 0.3 | Q57: 0.3 | R57: 0.4
A58: 02.03.08 | B58: Losas Macizas
A59: 02.03.08.01 | B59: LOSAS MACIZAS.- CONC.210 kg/cm2 - 1 PISO | C59: M3 | D59: 0.63 | E59: 325.93 | F59: 205.34 | G59: =$F59*N59 -> 0 | H59: =$F59*O59 -> 0 | I59: =$F59*P59 -> 61.602 | J59: =$F59*Q59 -> 61.602 | K59: =$F59*R59 -> 82.136 | L59: =F59-SUM(G59:K59) -> 0 | P59: 0.3 | Q59: 0.3 | R59: 0.4
A60: 02.03.08.03 | B60: LOSAS MACIZAS.- ENCOFRADO Y DESENCOFRADO | C60: m2 | D60: 6.54 | E60: 55.43 | F60: 362.51 | G60: =$F60*N60 -> 0 | H60: =$F60*O60 -> 0 | I60: =$F60*P60 -> 108.753 | J60: =$F60*Q60 -> 108.753 | K60: =$F60*R60 -> 145.004 | L60: =F60-SUM(G60:K60) -> 0 | P60: 0.3 | Q60: 0.3 | R60: 0.4
A61: 02.03.08.04 | B61: LOSAS MACIZAS.- ACERO Fy=4,200 kg/cm2 | C61: KG | D61: 73.15 | E61: 4.02 | F61: 294.06 | G61: =$F61*N61 -> 0 | H61: =$F61*O61 -> 0 | I61: =$F61*P61 -> 88.218 | J61: =$F61*Q61 -> 88.218 | K61: =$F61*R61 -> 117.624 | L61: =F61-SUM(G61:K61) -> 0 | P61: 0.3 | Q61: 0.3 | R61: 0.4
A62: 02.03.09 | B62: Losas Aligeradas
A63: 02.03.09.01 | B63: LOSA ALIGERADA - CONCRETO 210 kg/cm2 - 1 PISO | C63: m3 | D63: 2.13 | E63: 315.52 | F63: 672.06 | G63: =$F63*N63 -> 0 | H63: =$F63*O63 -> 0 | I63: =$F63*P63 -> 201.618 | J63: =$F63*Q63 -> 201.618 | K63: =$F63*R63 -> 268.824 | L63: =F63-SUM(G63:K63) -> 0 | P63: 0.3 | Q63: 0.3 | R63: 0.4
A64: 02.03.09.03 | B64: LOSA ALIGERADA.- ENCOFRADO Y DESENCOFRADO | C64: m2 | D64: 24.72 | E64: 43.61 | F64: 1078.04 | G64: =$F64*N64 -> 0 | H64: =$F64*O64 -> 0 | I64: =$F64*P64 -> 323.412 | J64: =$F64*Q64 -> 323.412 | K64: =$F64*R64 -> 431.216 | L64: =F64-SUM(G64:K64) -> 0 | P64: 0.3 | Q64: 0.3 | R64: 0.4
A65: 02.03.09.04 | B65: LOSA ALIGERADA.- ACERO Fy=4,200 kg/cm2 | C65: KG | D65: 93.93 | E65: 4.02 | F65: 377.6 | G65: =$F65*N65 -> 0 | H65: =$F65*O65 -> 0 | I65: =$F65*P65 -> 113.28 | J65: =$F65*Q65 -> 113.28 | K65: =$F65*R65 -> 151.04 | L65: =F65-SUM(G65:K65) -> 0 | P65: 0.3 | Q65: 0.3 | R65: 0.4
A66: 02.03.09.05 | B66: LOSA ALIGERADA.- LADR. HUECO 15x30x30 | C66: und | D66: 205.92 | E66: 2.49 | F66: 512.74 | G66: =$F66*N66 -> 0 | H66: =$F66*O66 -> 0 | I66: =$F66*P66 -> 153.822 | J66: =$F66*Q66 -> 153.822 | K66: =$F66*R66 -> 205.096 | L66: =F66-SUM(G66:K66) -> 0 | P66: 0.3 | Q66: 0.3 | R66: 0.4
A67: 02.03.15 | B67: Gradas Armadas en Pisos
A68: 02.03.15.01 | B68: GRADAS EN PISO, CONCRETO F'c=175 kg/cm2. | C68: m2 | D68: 12.31 | E68: 80.04 | F68: 985.29 | G68: =$F68*N68 -> 0 | H68: =$F68*O68 -> 0 | I68: =$F68*P68 -> 295.587 | J68: =$F68*Q68 -> 295.587 | K68: =$F68*R68 -> 394.116 | L68: =F68-SUM(G68:K68) -> 0 | P68: 0.3 | Q68: 0.3 | R68: 0.4
A69: 02.03.15.03 | B69: GRADAS, ENCOFRADO Y DESENCOFRADO | C69: m2 | D69: 6.96 | E69: 41.15 | F69: 286.4 | G69: =$F69*N69 -> 0 | H69: =$F69*O69 -> 0 | I69: =$F69*P69 -> 85.92 | J69: =$F69*Q69 -> 85.92 | K69: =$F69*R69 -> 114.56 | L69: =F69-SUM(G69:K69) -> 0 | P69: 0.3 | Q69: 0.3 | R69: 0.4
A70: 02.03.15.04 | B70: GRADAS EN PISO, ACERO fy=4200kg/cm2 | C70: kg | D70: 83.01 | E70: 4.02 | F70: 333.7 | G70: =$F70*N70 -> 0 | H70: =$F70*O70 -> 0 | I70: =$F70*P70 -> 100.11 | J70: =$F70*Q70 -> 100.11 | K70: =$F70*R70 -> 133.48 | L70: =F70-SUM(G70:K70) -> 0 | P70: 0.3 | Q70: 0.3 | R70: 0.4
B71: COSTO DIRECTO | F71: =SUM(F7:F70) -> 960724.52 | G71: =SUM(G7:G70) -> 157977.15 | H71: =SUM(H7:H70) -> 325762.39 | I71: =SUM(I7:I70) -> 209394.22 | J71: =SUM(J7:J70) -> 184954.64 | K71: =SUM(K7:K70) -> 82636.12
B72: GASTOS GENERALES (10%) | F72: =F71*0.15 -> 144108.68 | G72: =G71*0.15 -> 23696.572 | H72: =H71*0.15 -> 48864.359 | I72: =I71*0.15 -> 31409.132 | J72: =J71*0.15 -> 27743.197 | K72: =K71*0.15 -> 12395.418
B73: UTILIDAD (5%) | F73: =F71*0.05 -> 48036.226 | G73: =G71*0.05 -> 7898.8574 | H73: =H71*0.05 -> 16288.12 | I73: =I71*0.05 -> 10469.711 | J73: =J71*0.05 -> 9247.7322 | K73: =K71*0.05 -> 4131.806
B74: SUBTOTAL | F74: =SUM(F71:F73) -> 1152869.4 | G74: =SUM(G71:G73) -> 189572.58 | H74: =SUM(H71:H73) -> 390914.87 | I74: =SUM(I71:I73) -> 251273.06 | J74: =SUM(J71:J73) -> 221945.57 | K74: =SUM(K71:K73) -> 99163.344
B75: IGV (18.00%) | F75: =ROUND(F74*0.18,2) -> 207516.5 | G75: =ROUND(G74*0.18,2) -> 34123.06 | H75: =ROUND(H74*0.18,2) -> 70364.68 | I75: =ROUND(I74*0.18,2) -> 45229.15 | J75: =ROUND(J74*0.18,2) -> 39950.2 | K75: =ROUND(K74*0.18,2) -> 17849.4
B76: COSTO TOTAL (INC. IGV) | F76: =SUM(F74:F75) -> 1360385.9 | G76: =SUM(G74:G75) -> 223695.64 | H76: =SUM(H74:H75) -> 461279.55 | I76: =SUM(I74:I75) -> 296502.21 | J76: =SUM(J74:J75) -> 261895.77 | K76: =SUM(K74:K75) -> 117012.74

Sheet CRONOG CONT META
A1: CRONOGRAMA VALORIZADO DE OBRA - PROGRAMACION VENTA CON COSTOS META
A3: PROYECTO: | B3: I.E. N° 1182 "EL BOSQUE" - CERCO + INGRESOS Y CASETAS
A5: ITEM | B5: DESCRIPCION | C5: UND | D5: CONTRACTUAL | G5: PROGRAMACION
D6: METRADO | E6: P.U. (S/.) | F6: PARCIAL (S/.) | G6: 45474 | H6: 45505 | I6: 45536 | J6: 45566 | K6: 45597
A7: 01 | B7: OBRAS PROVISIONALES, TRABAJOS PRELIMINARES, SEGURIDAD Y SALUD
A8: 01.02 | B8: Trabajos Preliminares
A9: 01.02.04 | B9: Trazo, Niveles y Replanteo
A10: 01.02.04.01 | B10: TRAZO Y REPLANTEO PRELIMINAR | C10: M2 | D10: 942.21 | E10: 1.33 | F10: 1253.14 | G10: =$F10*N10 -> 626.57 | H10: =$F10*O10 -> 626.57 | I10: =$F10*P10 -> 0 | J10: =$F10*Q10 -> 0 | K10: =$F10*R10 -> 0 | L10: =F10-SUM(G10:K10) -> 0 | N10: 0.5 | O10: 0.5
A11: 01.02.04.02 | B11: TRAZO Y REPLANTEO DURANTE EL PROCESO | C11: m2 | D11: 942.21 | E11: 1.33 | F11: 1253.14 | G11: =$F11*N11 -> 313.285 | H11: =$F11*O11 -> 313.285 | I11: =$F11*P11 -> 313.285 | J11: =$F11*Q11 -> 313.285 | K11: =$F11*R11 -> 0 | L11: =F11-SUM(G11:K11) -> 0 | N11: 0.25 | O11: 0.25 | P11: 0.25 | Q11: 0.25
A12: 02 | B12: ESTRUCTURAS
A13: 02.01 | B13: Movimiento de Tierras
A14: 02.01.01 | B14: Excavaciones
A15: 02.01.01.01 | B15: EXCAV.ZANJAS Y ZAPATA RT>2kg/cm2 H=1.5m | C15: m3 | D15: 39.81 | E15: 29.22 | F15: 1163.25 | G15: =$F15*N15 -> 581.625 | H15: =$F15*O15 -> 581.625 | I15: =$F15*P15 -> 0 | J15: =$F15*Q15 -> 0 | K15: =$F15*R15 -> 0 | L15: =F15-SUM(G15:K15) -> 0 | N15: 0.5 | O15: 0.5
A16: 02.01.01.02 | B16: EXCAV.ZANJAS Y ZAPATA RT>2kg/cm2 H=2.0m | C16: m3 | D16: 1876.4 | E16: 33.36 | F16: 62596.7 | G16: =$F16*N16 -> 31298.35 | H16: =$F16*O16 -> 31298.35 | I16: =$F16*P16 -> 0 | J16: =$F16*Q16 -> 0 | K16: =$F16*R16 -> 0 | L16: =F16-SUM(G16:K16) -> 0 | N16: 0.5 | O16: 0.5
A17: 02.01.03 | B17: Rellenos
A18: 02.01.03.01 | B18: RELLENO COMPACTADO C/EQUIPO MAT/PROPIO | C18: m3 | D18: 1138.01 | E18: 15 | F18: 17070.15 | G18: =$F18*N18 -> 0 | H18: =$F18*O18 -> 8535.075 | I18: =$F18*P18 -> 8535.075 | J18: =$F18*Q18 -> 0 | K18: =$F18*R18 -> 0 | L18: =F18-SUM(G18:K18) -> 0 | O18: 0.5 | P18: 0.5
A19: 02.01.04 | B19: Eliminacion de Material Excedente
A20: 02.01.04.01 | B20: ACARREO INTERNO, MATERIAL PROCEDENTE DE EXCAVACIONES | C20: m3 | D20: 1118.06 | E20: 18.27 | F20: 20426.96 | G20: =$F20*N20 -> 6128.088 | H20: =$F20*O20 -> 10213.48 | I20: =$F20*P20 -> 4085.392 | J20: =$F20*Q20 -> 0 | K20: =$F20*R20 -> 0 | L20: =F20-SUM(G20:K20) -> 0 | N20: 0.3 | O20: 0.5 | P20: 0.2
A21: 02.01.04.02 | B21: ELIMINACION MATERIAL EXCEDENTE ACARREADO | C21: M3 | G21: =$F21*N21 -> 0 | H21: =$F21*O21 -> 0 | I21: =$F21*P21 -> 0 | J21: =$F21*Q21 -> 0 | K21: =$F21*R21 -> 0 | L21: =F21-SUM(G21:K21) -> 0 | N21: 0.3 | O21: 0.3 | P21: 0.4
A22: 02.01.04.03 | B22: ELIMINACION MATERIAL EXCEDENTE C/MAQUINA | C22: m3 | G22: =$F22*N22 -> 0 | H22: =$F22*O22 -> 0 | I22: =$F22*P22 -> 0 | J22: =$F22*Q22 -> 0 | K22: =$F22*R22 -> 0 | L22: =F22-SUM(G22:K22) -> 0 | N22: 0.3 | O22: 0.3 | P22: 0.4
A23: 02.01.05 | B23: Nivelacion Interior y Apisonado
A24: 02.01.05.01 | B24: ESCARIFICADO Y COMPACTACION CON PLANCHA COMPACTADORA e = 30 cm | C24: m2 | D24: 70.33 | E24: 4.36 | F24: 306.64 | G24: =$F24*N24 -> 61.328 | H24: =$F24*O24 -> 122.656 | I24: =$F24*P24 -> 122.656 | J24: =$F24*Q24 -> 0 | K24: =$F24*R24 -> 0 | L24: =F24-SUM(G24:K24) -> 0 | N24: 0.2 | O24: 0.4 | P24: 0.4
A25: 02.01.05.02 | B25: ESCARIFICADO Y COMPACTACION CON PLANCHA COMPACTADORA H=0.60m (02 CAPAS 30cm c/u) | C25: m2 | D25: 8.73 | E25: 7.37 | F25: 64.34 | G25: =$F25*N25 -> 12.868 | H25: =$F25*O25 -> 25.736 | I25: =$F25*P25 -> 25.736 | J25: =$F25*Q25 -> 0 | K25: =$F25*R25 -> 0 | L25: =F25-SUM(G25:K25) -> 0 | N25: 0.2 | O25: 0.4 | P25: 0.4
A26: 02.01.05.05 | B26: AFIRMADO DE 8" PARA PISOS,PATIOS Y VEREDAS,COMPACTADO. | C26: m2 | D26: 70.33 | E26: 11.5 | F26: 808.8 | G26: =$F26*N26 -> 161.76 | H26: =$F26*O26 -> 323.52 | I26: =$F26*P26 -> 323.52 | J26: =$F26*Q26 -> 0 | K26: =$F26*R26 -> 0 | L26: =F26-SUM(G26:K26) -> 0 | N26: 0.2 | O26: 0.4 | P26: 0.4
A27: 02.01.05.06 | B27: AFIRMADO DE 12" EN PISOS INTERIOR/EXTERIOR,COMPACTADO. | C27: m2 | D27: 8.73 | E27: 14.5 | F27: 126.59 | G27: =$F27*N27 -> 25.318 | H27: =$F27*O27 -> 50.636 | I27: =$F27*P27 -> 50.636 | J27: =$F27*Q27 -> 0 | K27: =$F27*R27 -> 0 | L27: =F27-SUM(G27:K27) -> 0 | N27: 0.2 | O27: 0.4 | P27: 0.4
A28: 02.02 | B28: Obras de Concreto Simple
A29: 02.02.01 | B29: Falsos Cimientos
A30: 02.02.01.01 | B30: SUBCIMIENTO, SUBZAPATA MEZCLA 1:12 + 30 % P.G. | C30: m3 | D30: 330.16 | E30: 184.1 | F30: 60782.46 | G30: =$F30*N30 -> 0 | H30: =$F30*O30 -> 30391.23 | I30: =$F30*P30 -> 30391.23 | J30: =$F30*Q30 -> 0 | K30: =$F30*R30 -> 0 | L30: =F30-SUM(G30:K30) -> 0 | O30: 0.5 | P30: 0.5
A31: 02.02.02 | B31: Cimientos
A32: 02.02.02.02 | B32: CIMIENTOS CORRIDOS 1:10 + 30 % P.G. f'c >=100Kg/cm2 | C32: m3 | D32: 24.24 | E32: 182.46 | F32: 4422.83 | G32: =$F32*N32 -> 0 | H32: =$F32*O32 -> 0 | I32: =$F32*P32 -> 2211.415 | J32: =$F32*Q32 -> 2211.415 | K32: =$F32*R32 -> 0 | L32: =F32-SUM(G32:K32) -> 0 | P32: 0.5 | Q32: 0.5
A33: 02.02.02.03 | B33: CIMIENTO CORRIDO - ENCOFRADO Y DESENCOFRADO | C33: m2 | D33: 22.63 | E33: 23.83 | F33: 539.27 | G33: =$F33*N33 -> 0 | H33: =$F33*O33 -> 215.708 | I33: =$F33*P33 -> 215.708 | J33: =$F33*Q33 -> 107.854 | K33: =$F33*R33 -> 0 | L33: =F33-SUM(G33:K33) -> 0 | O33: 0.4 | P33: 0.4 | Q33: 0.2
A34: 02.02.02.04 | B34: CALZADURA: CONCRETO C:H 1:10 + 30 % P.G. | C34: m3 | D34: 160.54 | E34: 207.85 | F34: 33368.24 | G34: =$F34*N34 -> 33368.24 | H34: =$F34*O34 -> 0 | I34: =$F34*P34 -> 0 | J34: =$F34*Q34 -> 0 | K34: =$F34*R34 -> 0 | L34: =F34-SUM(G34:K34) -> 0 | N34: 1
A35: 02.02.02.05 | B35: CALZADURA: ENCOFRADO Y DESENCOFRADO | C35: m2 | D35: 321.08 | E35: 26.53 | F35: 8518.25 | G35: =$F35*N35 -> 8518.25 | H35: =$F35*O35 -> 0 | I35: =$F35*P35 -> 0 | J35: =$F35*Q35 -> 0 | K35: =$F35*R35 -> 0 | L35: =F35-SUM(G35:K35) -> 0 | N35: 1
A36: 02.02.03 | B36: Sobrecimientos
A37: 02.02.03.01 | B37: SOBRECIMIENTO, CONCRETO 1:8 + 25% P.M. f'c >=100Kg/cm2 | C37: m3 | D37: 3.15 | E37: 201.22 | F37: 633.84 | G37: =$F37*N37 -> 0 | H37: =$F37*O37 -> 0 | I37: =$F37*P37 -> 316.92 | J37: =$F37*Q37 -> 316.92 | K37: =$F37*R37 -> 0 | L37: =F37-SUM(G37:K37) -> 0 | P37: 0.5 | Q37: 0.5
A38: 02.02.03.02 | B38: SOBRECIMIENTO, ENCOFRADO Y DESENCOFRADO | C38: m2 | D38: 43.07 | E38: 24.18 | F38: 1041.43 | G38: =$F38*N38 -> 0 | H38: =$F38*O38 -> 416.572 | I38: =$F38*P38 -> 416.572 | J38: =$F38*Q38 -> 208.286 | K38: =$F38*R38 -> 0 | L38: =F38-SUM(G38:K38) -> 0 | O38: 0.4 | P38: 0.4 | Q38: 0.2
A39: 02.03 | B39: Obras de Concreto Armado
A40: 02.03.02 | B40: Zapatas
A41: 02.03.02.01 | B41: ZAPATAS.- CONCRETO 210 kg/cm2 | C41: m3 | D41: 412.62 | E41: 286.6 | F41: 118256.89 | G41: =$F41*N41 -> 35477.067 | H41: =$F41*O41 -> 82779.823 | I41: =$F41*P41 -> 0 | J41: =$F41*Q41 -> 0 | K41: =$F41*R41 -> 0 | L41: =F41-SUM(G41:K41) -> 0 | N41: 0.3 | O41: 0.7
A42: 02.03.02.03 | B42: ZAPATAS.- ACERO Fy=4200 kg/cm2 | C42: KG | D42: 17359.56 | E42: 3.4 | F42: 59022.5 | G42: =$F42*N42 -> 17706.75 | H42: =$F42*O42 -> 41315.75 | I42: =$F42*P42 -> 0 | J42: =$F42*Q42 -> 0 | K42: =$F42*R42 -> 0 | L42: =F42-SUM(G42:K42) -> 0 | N42: 0.3 | O42: 0.7
A43: 02.03.05 | B43: Placas y Muros de Contención
A44: 02.03.05.02 | B44: PLACAS, CONCRETO F'c=210 kg/cm2 - 1 piso | C44: m3 | D44: 6.62 | E44: 290.45 | F44: 1922.78 | G44: =$F44*N44 -> 0 | H44: =$F44*O44 -> 576.834 | I44: =$F44*P44 -> 576.834 | J44: =$F44*Q44 -> 769.112 | K44: =$F44*R44 -> 0 | L44: =F44-SUM(G44:K44) -> 0 | O44: 0.3 | P44: 0.3 | Q44: 0.4
A45: 02.03.05.04 | B45: PLACAS, ENCOFRADO Y DESENCOFRADO | C45: m2 | D45: 73.44 | E45: 33.69 | F45: 2474.19 | G45: =$F45*N45 -> 0 | H45: =$F45*O45 -> 742.257 | I45: =$F45*P45 -> 742.257 | J45: =$F45*Q45 -> 989.676 | K45: =$F45*R45 -> 0 | L45: =F45-SUM(G45:K45) -> 0 | O45: 0.3 | P45: 0.3 | Q45: 0.4
A46: 02.03.05.05 | B46: PLACAS, ACERO Fy=4200 kg/cm2 | C46: KG | D46: 415.16 | E46: 3.4 | F46: 1411.54 | G46: =$F46*N46 -> 0 | H46: =$F46*O46 -> 423.462 | I46: =$F46*P46 -> 423.462 | J46: =$F46*Q46 -> 564.616 | K46: =$F46*R46 -> 0 | L46: =F46-SUM(G46:K46) -> 0 | O46: 0.3 | P46: 0.3 | Q46: 0.4
A47: 02.03.05.07 | B47: MUROS DE CONTENC.- CONCRETO 210 kg/cm2 | C47: m3 | D47: 253.95 | E47: 328.19 | F47: 83343.85 | G47: =$F47*N47 -> 0 | H47: =$F47*O47 -> 25003.155 | I47: =$F47*P47 -> 25003.155 | J47: =$F47*Q47 -> 33337.54 | K47: =$F47*R47 -> 0 | L47: =F47-SUM(G47:K47) -> 0 | O47: 0.3 | P47: 0.3 | Q47: 0.4
A48: 02.03.05.09 | B48: MUROS DE CONTENC.- ENCOF. Y DESENCOFRADO | C48: m2 | D48: 2075.23 | E48: 30.97 | F48: 64269.87 | G48: =$F48*N48 -> 0 | H48: =$F48*O48 -> 19280.961 | I48: =$F48*P48 -> 19280.961 | J48: =$F48*Q48 -> 25707.948 | K48: =$F48*R48 -> 0 | L48: =F48-SUM(G48:K48) -> 0 | O48: 0.3 | P48: 0.3 | Q48: 0.4
A49: 02.03.05.11 | B49: MUROS DE CONTENC.- ACERO Fy=4200 kg/cm2 | C49: kg | G49: =$F49*N49 -> 0 | H49: =$F49*O49 -> 0 | I49: =$F49*P49 -> 0 | J49: =$F49*Q49 -> 0 | K49: =$F49*R49 -> 0 | L49: =F49-SUM(G49:K49) -> 0 | O49: 0.3 | P49: 0.3 | Q49: 0.4
A50: 02.03.06 | B50: Columnas
A51: 02.03.06.02 | B51: COLUMNAS - CONCRETO 210 KG/CM² - 1 PISO | C51: m3 | D51: 67.96 | E51: 291.23 | F51: 19791.99 | G51: =$F51*N51 -> 0 | H51: =$F51*O51 -> 0 | I51: =$F51*P51 -> 5937.597 | J51: =$F51*Q51 -> 5937.597 | K51: =$F51*R51 -> 7916.796 | L51: =F51-SUM(G51:K51) -> 0 | P51: 0.3 | Q51: 0.3 | R51: 0.4
A52: 02.03.06.06 | B52: COLUMNAS.- ENCOFRADO Y DESENCOFRADO | C52: m2 | D52: 919.41 | E52: 37.49 | F52: 34468.68 | G52: =$F52*N52 -> 0 | H52: =$F52*O52 -> 0 | I52: =$F52*P52 -> 10340.604 | J52: =$F52*Q52 -> 10340.604 | K52: =$F52*R52 -> 13787.472 | L52: =F52-SUM(G52:K52) -> 0 | P52: 0.3 | Q52: 0.3 | R52: 0.4
A53: 02.03.06.10 | B53: COLUMNAS.- ACERO Fy=4200 kg/cm2 | C53: KG | D53: 11836.1 | E53: 3.4 | F53: 40242.74 | G53: =$F53*N53 -> 0 | H53: =$F53*O53 -> 0 | I53: =$F53*P53 -> 12072.822 | J53: =$F53*Q53 -> 12072.822 | K53: =$F53*R53 -> 16097.096 | L53: =F53-SUM(G53:K53) -> 0 | P53: 0.3 | Q53: 0.3 | R53: 0.4
A54: 02.03.07 | B54: Vigas
A55: 02.03.07.02 | B55: VIGAS.- CONCRETO 210 kg/cm2 - 1 piso | C55: m3 | D55: 36.84 | E55: 294.5 | F55: 10849.38 | G55: =$F55*N55 -> 0 | H55: =$F55*O55 -> 0 | I55: =$F55*P55 -> 3254.814 | J55: =$F55*Q55 -> 3254.814 | K55: =$F55*R55 -> 4339.752 | L55: =F55-SUM(G55:K55) -> 0 | P55: 0.3 | Q55: 0.3 | R55: 0.4
A56: 02.03.07.06 | B56: VIGAS.- ENCOFRADO Y DESENCOFRADO | C56: m2 | D56: 556.13 | E56: 43.56 | F56: 24225.02 | G56: =$F56*N56 -> 0 | H56: =$F56*O56 -> 0 | I56: =$F56*P56 -> 7267.506 | J56: =$F56*Q56 -> 7267.506 | K56: =$F56*R56 -> 9690.008 | L56: =F56-SUM(G56:K56) -> 0 | P56: 0.3 | Q56: 0.3 | R56: 0.4
A57: 02.03.07.08 | B57: VIGAS.- ACERO Fy=4200 kg/cm2 | C57: KG | D57: 5247.49 | E57: 3.4 | F57: 17841.47 | G57: =$F57*N57 -> 0 | H57: =$F57*O57 -> 0 | I57: =$F57*P57 -> 5352.441 | J57: =$F57*Q57 -> 5352.441 | K57: =$F57*R57 -> 7136.588 | L57: =F57-SUM(G57:K57) -> 0 | P57: 0.3 | Q57: 0.3 | R57: 0.4
A58: 02.03.08 | B58: Losas Macizas
A59: 02.03.08.01 | B59: LOSAS MACIZAS.- CONC.210 kg/cm2 - 1 PISO | C59: M3 | D59: 0.63 | E59: 325.93 | F59: 205.34 | G59: =$F59*N59 -> 0 | H59: =$F59*O59 -> 0 | I59: =$F59*P59 -> 61.602 | J59: =$F59*Q59 -> 61.602 | K59: =$F59*R59 -> 82.136 | L59: =F59-SUM(G59:K59) -> 0 | P59: 0.3 | Q59: 0.3 | R59: 0.4
A60: 02.03.08.03 | B60: LOSAS MACIZAS.- ENCOFRADO Y DESENCOFRADO | C60: m2 | D60: 6.54 | E60: 55.43 | F60: 362.51 | G60: =$F60*N60 -> 0 | H60: =$F60*O60 -> 0 | I60: =$F60*P60 -> 108.753 | J60: =$F60*Q60 -> 108.753 | K60: =$F60*R60 -> 145.004 | L60: =F60-SUM(G60:K60) -> 0 | P60: 0.3 | Q60: 0.3 | R60: 0.4
A61: 02.03.08.04 | B61: LOSAS MACIZAS.- ACERO Fy=4,200 kg/cm2 | C61: KG | D61: 73.15 | E61: 4.02 | F61: 294.06 | G61: =$F61*N61 -> 0 | H61: =$F61*O61 -> 0 | I61: =$F61*P61 -> 88.218 | J61: =$F61*Q61 -> 88.218 | K61: =$F61*R61 -> 117.624 | L61: =F61-SUM(G61:K61) -> 0 | P61: 0.3 | Q61: 0.3 | R61: 0.4
A62: 02.03.09 | B62: Losas Aligeradas
A63: 02.03.09.01 | B63: LOSA ALIGERADA - CONCRETO 210 kg/cm2 - 1 PISO | C63: m3 | D63: 2.17 | E63: 294.5 | F63: 639.07 | G63: =$F63*N63 -> 0 | H63: =$F63*O63 -> 0 | I63: =$F63*P63 -> 191.721 | J63: =$F63*Q63 -> 191.721 | K63: =$F63*R63 -> 255.628 | L63: =F63-SUM(G63:K63) -> 0 | P63: 0.3 | Q63: 0.3 | R63: 0.4
A64: 02.03.09.03 | B64: LOSA ALIGERADA.- ENCOFRADO Y DESENCOFRADO | C64: m2 | D64: 25.21 | E64: 25.75 | F64: 649.16 | G64: =$F64*N64 -> 0 | H64: =$F64*O64 -> 0 | I64: =$F64*P64 -> 194.748 | J64: =$F64*Q64 -> 194.748 | K64: =$F64*R64 -> 259.664 | L64: =F64-SUM(G64:K64) -> 0 | P64: 0.3 | Q64: 0.3 | R64: 0.4
A65: 02.03.09.04 | B65: LOSA ALIGERADA.- ACERO Fy=4,200 kg/cm2 | C65: KG | D65: 95.81 | E65: 3.4 | F65: 325.75 | G65: =$F65*N65 -> 0 | H65: =$F65*O65 -> 0 | I65: =$F65*P65 -> 97.725 | J65: =$F65*Q65 -> 97.725 | K65: =$F65*R65 -> 130.3 | L65: =F65-SUM(G65:K65) -> 0 | P65: 0.3 | Q65: 0.3 | R65: 0.4
A66: 02.03.09.05 | B66: LOSA ALIGERADA.- LADR. HUECO 15x30x30 | C66: und | D66: 210.04 | E66: 2.39 | F66: 502 | G66: =$F66*N66 -> 0 | H66: =$F66*O66 -> 0 | I66: =$F66*P66 -> 150.6 | J66: =$F66*Q66 -> 150.6 | K66: =$F66*R66 -> 200.8 | L66: =F66-SUM(G66:K66) -> 0 | P66: 0.3 | Q66: 0.3 | R66: 0.4
A67: 02.03.15 | B67: Gradas Armadas en Pisos
A68: 02.03.15.01 | B68: GRADAS EN PISO, CONCRETO F'c=175 kg/cm2. | C68: m2 | D68: 12.56 | E68: 59.8 | F68: 751.09 | G68: =$F68*N68 -> 0 | H68: =$F68*O68 -> 0 | I68: =$F68*P68 -> 225.327 | J68: =$F68*Q68 -> 225.327 | K68: =$F68*R68 -> 300.436 | L68: =F68-SUM(G68:K68) -> 0 | P68: 0.3 | Q68: 0.3 | R68: 0.4
A69: 02.03.15.03 | B69: GRADAS, ENCOFRADO Y DESENCOFRADO | C69: m2 | D69: 7.1 | E69: 27.36 | F69: 194.26 | G69: =$F69*N69 -> 0 | H69: =$F69*O69 -> 0 | I69: =$F69*P69 -> 58.278 | J69: =$F69*Q69 -> 58.278 | K69: =$F69*R69 -> 77.704 | L69: =F69-SUM(G69:K69) -> 0 | P69: 0.3 | Q69: 0.3 | R69: 0.4
A70: 02.03.15.04 | B70: GRADAS EN PISO, ACERO fy=4200kg/cm2 | C70: kg | D70: 84.67 | E70: 3.4 | F70: 287.88 | G70: =$F70*N70 -> 0 | H70: =$F70*O70 -> 0 | I70: =$F70*P70 -> 86.364 | J70: =$F70*Q70 -> 86.364 | K70: =$F70*R70 -> 115.152 | L70: =F70-SUM(G70:K70) -> 0 | P70: 0.3 | Q70: 0.3 | R70: 0.4
B71: COSTO DIRECTO | F71: =SUM(F7:F70) -> 696708.05 | G71: =SUM(G7:G70) -> 134279.5 | H71: =SUM(H7:H70) -> 253236.68 | I71: =SUM(I7:I70) -> 138523.93 | J71: =SUM(J7:J70) -> 110015.77 | K71: =SUM(K7:K70) -> 60652.16
B72: GASTOS GENERALES (10%) | F72: =F71*0.15 -> 104506.21 | G72: =G71*0.15 -> 20141.925 | H72: =H71*0.15 -> 37985.503 | I72: =I71*0.15 -> 20778.59 | J72: =J71*0.15 -> 16502.366 | K72: =K71*0.15 -> 9097.824
B73: UTILIDAD (5%) | F73: =F71*0.05 -> 34835.402 | G73: =G71*0.05 -> 6713.975 | H73: =H71*0.05 -> 12661.834 | I73: =I71*0.05 -> 6926.1967 | J73: =J71*0.05 -> 5500.7886 | K73: =K71*0.05 -> 3032.608
B74: SUBTOTAL | F74: =SUM(F71:F73) -> 836049.66 | G74: =SUM(G71:G73) -> 161135.4 | H74: =SUM(H71:H73) -> 303884.02 | I74: =SUM(I71:I73) -> 166228.72 | J74: =SUM(J71:J73) -> 132018.93 | K74: =SUM(K71:K73) -> 72782.592
B75: IGV (18.00%) | F75: =ROUND(F74*0.18,2) -> 150488.94 | G75: =ROUND(G74*0.18,2) -> 29004.37 | H75: =ROUND(H74*0.18,2) -> 54699.12 | I75: =ROUND(I74*0.18,2) -> 29921.17 | J75: =ROUND(J74*0.18,2) -> 23763.41 | K75: =ROUND(K74*0.18,2) -> 13100.87
B76: COSTO TOTAL (INC. IGV) | F76: =SUM(F74:F75) -> 986538.6 | G76: =SUM(G74:G75) -> 190139.77 | H76: =SUM(H74:H75) -> 358583.14 | I76: =SUM(I74:I75) -> 196149.89 | J76: =SUM(J74:J75) -> 155782.34 | K76: =SUM(K74:K75) -> 85883.462

Sheet CRONOG INTERNO VENTA
A1: CRONOGRAMA VALORIZADO DE OBRA - PROGRAMACION VENTA
A3: PROYECTO: | B3: I.E. N° 1182 "EL BOSQUE" - CERCO + INGRESOS Y CASETAS
A5: ITEM | B5: DESCRIPCION | C5: UND | D5: CONTRACTUAL | G5: PROGRAMACION
D6: METRADO | E6: P.U. (S/.) | F6: PARCIAL (S/.) | G6: 45474 | H6: 45505 | I6: 45536 | J6: 45566 | K6: 45597
A7: 01 | B7: OBRAS PROVISIONALES, TRABAJOS PRELIMINARES, SEGURIDAD Y SALUD
A8: 01.02 | B8: Trabajos Preliminares
A9: 01.02.04 | B9: Trazo, Niveles y Replanteo
A10: 01.02.04.01 | B10: TRAZO Y REPLANTEO PRELIMINAR | C10: M2 | D10: 897.34 | E10: 2.04 | F10: 1830.57 | G10: =$F10*N10 -> 915.285 | H10: =$F10*O10 -> 915.285 | I10: =$F10*P10 -> 0 | J10: =$F10*Q10 -> 0 | K10: =$F10*R10 -> 0 | L10: =F10-SUM(G10:K10) -> 0 | N10: 0.5 | O10: 0.5
A11: 01.02.04.02 | B11: TRAZO Y REPLANTEO DURANTE EL PROCESO | C11: m2 | D11: 897.34 | E11: 2.04 | F11: 1830.57 | G11: =$F11*N11 -> 457.6425 | H11: =$F11*O11 -> 457.6425 | I11: =$F11*P11 -> 457.6425 | J11: =$F11*Q11 -> 457.6425 | K11: =$F11*R11 -> 0 | L11: =F11-SUM(G11:K11) -> 0 | N11: 0.25 | O11: 0.25 | P11: 0.25 | Q11: 0.25
A12: 02 | B12: ESTRUCTURAS
A13: 02.01 | B13: Movimiento de Tierras
A14: 02.01.01 | B14: Excavaciones
A15: 02.01.01.01 | B15: EXCAV.ZANJAS Y ZAPATA RT>2kg/cm2 H=1.5m | C15: m3 | D15: 41.9 | E15: 46.74 | F15: 1958.41 | G15: =$F15*N15 -> 1370.887 | H15: =$F15*O15 -> 587.523 | I15: =$F15*P15 -> 0 | J15: =$F15*Q15 -> 0 | K15: =$F15*R15 -> 0 | L15: =F15-SUM(G15:K15) -> 0 | N15: 0.7 | O15: 0.3
A16: 02.01.01.02 | B16: EXCAV.ZANJAS Y ZAPATA RT>2kg/cm2 H=2.0m | C16: m3 | D16: 1975.16 | E16: 50.99 | F16: 100713.41 | G16: =$F16*N16 -> 70499.387 | H16: =$F16*O16 -> 30214.023 | I16: =$F16*P16 -> 0 | J16: =$F16*Q16 -> 0 | K16: =$F16*R16 -> 0 | L16: =F16-SUM(G16:K16) -> 0 | N16: 0.7 | O16: 0.3
A17: 02.01.03 | B17: Rellenos
A18: 02.01.03.01 | B18: RELLENO COMPACTADO C/EQUIPO MAT/PROPIO | C18: m3 | D18: 1197.91 | E18: 26.01 | F18: 31157.64 | G18: =$F18*N18 -> 0 | H18: =$F18*O18 -> 9347.292 | I18: =$F18*P18 -> 21810.348 | J18: =$F18*Q18 -> 0 | K18: =$F18*R18 -> 0 | L18: =F18-SUM(G18:K18) -> 0 | O18: 0.3 | P18: 0.7
A19: 02.01.04 | B19: Eliminacion de Material Excedente
A20: 02.01.04.01 | B20: ACARREO INTERNO, MATERIAL PROCEDENTE DE EXCAVACIONES | C20: m3 | D20: 68.91 | E20: 17.53 | F20: 1207.99 | G20: =$F20*N20 -> 603.995 | H20: =$F20*O20 -> 603.995 | I20: =$F20*P20 -> 0 | J20: =$F20*Q20 -> 0 | K20: =$F20*R20 -> 0 | L20: =F20-SUM(G20:K20) -> 0 | N20: 0.5 | O20: 0.5
A21: 02.01.04.02 | B21: ELIMINACION MATERIAL EXCEDENTE ACARREADO | C21: M3 | D21: 68.91 | E21: 16.02 | F21: 1103.94 | G21: =$F21*N21 -> 551.97 | H21: =$F21*O21 -> 551.97 | I21: =$F21*P21 -> 0 | J21: =$F21*Q21 -> 0 | K21: =$F21*R21 -> 0 | L21: =F21-SUM(G21:K21) -> 0 | N21: 0.5 | O21: 0.5
A22: 02.01.04.03 | B22: ELIMINACION MATERIAL EXCEDENTE C/MAQUINA | C22: m3 | D22: 995.9 | E22: 21.84 | F22: 21750.46 | G22: =$F22*N22 -> 10875.23 | H22: =$F22*O22 -> 10875.23 | I22: =$F22*P22 -> 0 | J22: =$F22*Q22 -> 0 | K22: =$F22*R22 -> 0 | L22: =F22-SUM(G22:K22) -> 0 | N22: 0.5 | O22: 0.5
A23: 02.01.05 | B23: Nivelacion Interior y Apisonado
A24: 02.01.05.01 | B24: ESCARIFICADO Y COMPACTACION CON PLANCHA COMPACTADORA e = 30 cm | C24: m2 | D24: 68.95 | E24: 4.72 | F24: 325.44 | G24: =$F24*N24 -> 0 | H24: =$F24*O24 -> 0 | I24: =$F24*P24 -> 0 | J24: =$F24*Q24 -> 162.72 | K24: =$F24*R24 -> 162.72 | L24: =F24-SUM(G24:K24) -> 0 | Q24: 0.5 | R24: 0.5
A25: 02.01.05.02 | B25: ESCARIFICADO Y COMPACTACION CON PLANCHA COMPACTADORA H=0.60m (02 CAPAS 30cm c/u) | C25: m2 | D25: 8.56 | E25: 7.85 | F25: 67.2 | G25: =$F25*N25 -> 0 | H25: =$F25*O25 -> 0 | I25: =$F25*P25 -> 40.32 | J25: =$F25*Q25 -> 26.88 | K25: =$F25*R25 -> 0 | L25: =F25-SUM(G25:K25) -> 0 | P25: 0.6 | Q25: 0.4
A26: 02.01.05.05 | B26: AFIRMADO DE 8" PARA PISOS,PATIOS Y VEREDAS,COMPACTADO. | C26: m2 | D26: 68.95 | E26: 15.19 | F26: 1047.35 | G26: =$F26*N26 -> 0 | H26: =$F26*O26 -> 0 | I26: =$F26*P26 -> 0 | J26: =$F26*Q26 -> 418.94 | K26: =$F26*R26 -> 628.41 | L26: =F26-SUM(G26:K26) -> 0 | Q26: 0.4 | R26: 0.6
A27: 02.01.05.06 | B27: AFIRMADO DE 12" EN PISOS INTERIOR/EXTERIOR,COMPACTADO. | C27: m2 | D27: 8.56 | E27: 21.79 | F27: 186.52 | G27: =$F27*N27 -> 0 | H27: =$F27*O27 -> 0 | I27: =$F27*P27 -> 93.26 | J27: =$F27*Q27 -> 93.26 | K27: =$F27*R27 -> 0 | L27: =F27-SUM(G27:K27) -> 0 | P27: 0.5 | Q27: 0.5
A28: 02.02 | B28: Obras de Concreto Simple
A29: 02.02.01 | B29: Falsos Cimientos
A30: 02.02.01.01 | B30: SUBCIMIENTO, SUBZAPATA MEZCLA 1:12 + 30 % P.G. | C30: m3 | D30: 323.69 | E30: 173.72 | F30: 56231.43 | G30: =$F30*N30 -> 0 | H30: =$F30*O30 -> 39362.001 | I30: =$F30*P30 -> 16869.429 | J30: =$F30*Q30 -> 0 | K30: =$F30*R30 -> 0 | L30: =F30-SUM(G30:K30) -> 0 | O30: 0.7 | P30: 0.3
A31: 02.02.02 | B31: Cimientos
A32: 02.02.02.02 | B32: CIMIENTOS CORRIDOS 1:10 + 30 % P.G. f'c >=100Kg/cm2 | C32: m3 | D32: 24.73 | E32: 179.78 | F32: 4445.96 | G32: =$F32*N32 -> 0 | H32: =$F32*O32 -> 1333.788 | I32: =$F32*P32 -> 3112.172 | J32: =$F32*Q32 -> 0 | K32: =$F32*R32 -> 0 | L32: =F32-SUM(G32:K32) -> 0 | O32: 0.3 | P32: 0.7
A33: 02.02.02.03 | B33: CIMIENTO CORRIDO - ENCOFRADO Y DESENCOFRADO | C33: m2 | D33: 23.09 | E33: 46.17 | F33: 1066.07 | G33: =$F33*N33 -> 0 | H33: =$F33*O33 -> 426.428 | I33: =$F33*P33 -> 639.642 | J33: =$F33*Q33 -> 0 | K33: =$F33*R33 -> 0 | L33: =F33-SUM(G33:K33) -> 0 | O33: 0.4 | P33: 0.6
A34: 02.02.02.04 | B34: CALZADURA: CONCRETO C:H 1:10 + 30 % P.G. | C34: m3 | D34: 163.82 | E34: 179.78 | F34: 29451.56 | G34: =$F34*N34 -> 29451.56 | H34: =$F34*O34 -> 0 | I34: =$F34*P34 -> 0 | J34: =$F34*Q34 -> 0 | K34: =$F34*R34 -> 0 | L34: =F34-SUM(G34:K34) -> 0 | N34: 1
A35: 02.02.02.05 | B35: CALZADURA: ENCOFRADO Y DESENCOFRADO | C35: m2 | D35: 327.63 | E35: 37.47 | F35: 12276.3 | G35: =$F35*N35 -> 12276.3 | H35: =$F35*O35 -> 0 | I35: =$F35*P35 -> 0 | J35: =$F35*Q35 -> 0 | K35: =$F35*R35 -> 0 | L35: =F35-SUM(G35:K35) -> 0 | N35: 1
A36: 02.02.03 | B36: Sobrecimientos
A37: 02.02.03.01 | B37: SOBRECIMIENTO, CONCRETO 1:8 + 25% P.M. f'c >=100Kg/cm2 | C37: m3 | D37: 3.21 | E37: 260.59 | F37: 836.49 | G37: =$F37*N37 -> 0 | H37: =$F37*O37 -> 0 | I37: =$F37*P37 -> 418.245 | J37: =$F37*Q37 -> 418.245 | K37: =$F37*R37 -> 0 | L37: =F37-SUM(G37:K37) -> 0 | P37: 0.5 | Q37: 0.5
A38: 02.02.03.02 | B38: SOBRECIMIENTO, ENCOFRADO Y DESENCOFRADO | C38: m2 | D38: 43.95 | E38: 37.7 | F38: 1656.92 | G38: =$F38*N38 -> 0 | H38: =$F38*O38 -> 662.768 | I38: =$F38*P38 -> 662.768 | J38: =$F38*Q38 -> 331.384 | K38: =$F38*R38 -> 0 | L38: =F38-SUM(G38:K38) -> 0 | O38: 0.4 | P38: 0.4 | Q38: 0.2
A39: 02.03 | B39: Obras de Concreto Armado
A40: 02.03.02 | B40: Zapatas
A41: 02.03.02.01 | B41: ZAPATAS.- CONCRETO 210 kg/cm2 | C41: m3 | D41: 396.75 | E41: 292.79 | F41: 116164.43 | G41: =$F41*N41 -> 0 | H41: =$F41*O41 -> 58082.215 | I41: =$F41*P41 -> 58082.215 | J41: =$F41*Q41 -> 0 | K41: =$F41*R41 -> 0 | L41: =F41-SUM(G41:K41) -> 0 | O41: 0.5 | P41: 0.5
A42: 02.03.02.03 | B42: ZAPATAS.- ACERO Fy=4200 kg/cm2 | C42: KG | D42: 17534.91 | E42: 4.02 | F42: 70490.34 | G42: =$F42*N42 -> 0 | H42: =$F42*O42 -> 35245.17 | I42: =$F42*P42 -> 35245.17 | J42: =$F42*Q42 -> 0 | K42: =$F42*R42 -> 0 | L42: =F42-SUM(G42:K42) -> 0 | O42: 0.5 | P42: 0.5
A43: 02.03.05 | B43: Placas y Muros de Contención
A44: 02.03.05.02 | B44: PLACAS, CONCRETO F'c=210 kg/cm2 - 1 piso | C44: m3 | D44: 6.69 | E44: 454.82 | F44: 3042.75 | G44: =$F44*N44 -> 0 | H44: =$F44*O44 -> 0 | I44: =$F44*P44 -> 1825.65 | J44: =$F44*Q44 -> 1217.1 | K44: =$F44*R44 -> 0 | L44: =F44-SUM(G44:K44) -> 0 | P44: 0.6 | Q44: 0.4
A45: 02.03.05.04 | B45: PLACAS, ENCOFRADO Y DESENCOFRADO | C45: m2 | D45: 74.18 | E45: 59.78 | F45: 4434.48 | G45: =$F45*N45 -> 0 | H45: =$F45*O45 -> 2217.24 | I45: =$F45*P45 -> 1330.344 | J45: =$F45*Q45 -> 886.896 | K45: =$F45*R45 -> 0 | L45: =F45-SUM(G45:K45) -> 0 | O45: 0.5 | P45: 0.3 | Q45: 0.2
A46: 02.03.05.05 | B46: PLACAS, ACERO Fy=4200 kg/cm2 | C46: KG | D46: 419.35 | E46: 4.02 | F46: 1685.79 | G46: =$F46*N46 -> 0 | H46: =$F46*O46 -> 1180.053 | I46: =$F46*P46 -> 505.737 | J46: =$F46*Q46 -> 0 | K46: =$F46*R46 -> 0 | L46: =F46-SUM(G46:K46) -> 0 | O46: 0.7 | P46: 0.3
A47: 02.03.05.07 | B47: MUROS DE CONTENC.- CONCRETO 210 kg/cm2 | C47: m3 | D47: 256.52 | E47: 417.41 | F47: 107074.01 | G47: =$F47*N47 -> 0 | H47: =$F47*O47 -> 0 | I47: =$F47*P47 -> 64244.406 | J47: =$F47*Q47 -> 42829.604 | K47: =$F47*R47 -> 0 | L47: =F47-SUM(G47:K47) -> 0 | P47: 0.6 | Q47: 0.4
A48: 02.03.05.09 | B48: MUROS DE CONTENC.- ENCOF. Y DESENCOFRADO | C48: m2 | D48: 2096.19 | E48: 51.21 | F48: 107345.89 | G48: =$F48*N48 -> 0 | H48: =$F48*O48 -> 53672.945 | I48: =$F48*P48 -> 32203.767 | J48: =$F48*Q48 -> 21469.178 | K48: =$F48*R48 -> 0 | L48: =F48-SUM(G48:K48) -> 0 | O48: 0.5 | P48: 0.3 | Q48: 0.2
A49: 02.03.05.11 | B49: MUROS DE CONTENC.- ACERO Fy=4200 kg/cm2 | C49: kg | D49: 18595.1 | E49: 4.02 | F49: 74752.3 | G49: =$F49*N49 -> 0 | H49: =$F49*O49 -> 52326.61 | I49: =$F49*P49 -> 22425.69 | J49: =$F49*Q49 -> 0 | K49: =$F49*R49 -> 0 | L49: =F49-SUM(G49:K49) -> 0 | O49: 0.7 | P49: 0.3
A50: 02.03.06 | B50: Columnas
A51: 02.03.06.02 | B51: COLUMNAS - CONCRETO 210 KG/CM² - 1 PISO | C51: m3 | D51: 66.63 | E51: 442.62 | F51: 29491.77 | G51: =$F51*N51 -> 0 | H51: =$F51*O51 -> 0 | I51: =$F51*P51 -> 0 | J51: =$F51*Q51 -> 17695.062 | K51: =$F51*R51 -> 11796.708 | L51: =F51-SUM(G51:K51) -> 0 | Q51: 0.6 | R51: 0.4
A52: 02.03.06.06 | B52: COLUMNAS.- ENCOFRADO Y DESENCOFRADO | C52: m2 | D52: 901.38 | E52: 60.48 | F52: 54515.46 | G52: =$F52*N52 -> 0 | H52: =$F52*O52 -> 0 | I52: =$F52*P52 -> 16354.638 | J52: =$F52*Q52 -> 38160.822 | K52: =$F52*R52 -> 0 | L52: =F52-SUM(G52:K52) -> 0 | P52: 0.3 | Q52: 0.7
A53: 02.03.06.10 | B53: COLUMNAS.- ACERO Fy=4200 kg/cm2 | C53: KG | D53: 11604.02 | E53: 4.02 | F53: 46648.16 | G53: =$F53*N53 -> 0 | H53: =$F53*O53 -> 0 | I53: =$F53*P53 -> 27988.896 | J53: =$F53*Q53 -> 18659.264 | K53: =$F53*R53 -> 0 | L53: =F53-SUM(G53:K53) -> 0 | P53: 0.6 | Q53: 0.4
A54: 02.03.07 | B54: Vigas
A55: 02.03.07.02 | B55: VIGAS.- CONCRETO 210 kg/cm2 - 1 piso | C55: m3 | D55: 36.12 | E55: 325.93 | F55: 11772.59 | G55: =$F55*N55 -> 0 | H55: =$F55*O55 -> 0 | I55: =$F55*P55 -> 0 | J55: =$F55*Q55 -> 7063.554 | K55: =$F55*R55 -> 4709.036 | L55: =F55-SUM(G55:K55) -> 0 | Q55: 0.6 | R55: 0.4
A56: 02.03.07.06 | B56: VIGAS.- ENCOFRADO Y DESENCOFRADO | C56: m2 | D56: 545.23 | E56: 70.38 | F56: 38373.29 | G56: =$F56*N56 -> 0 | H56: =$F56*O56 -> 0 | I56: =$F56*P56 -> 11511.987 | J56: =$F56*Q56 -> 26861.303 | K56: =$F56*R56 -> 0 | L56: =F56-SUM(G56:K56) -> 0 | P56: 0.3 | Q56: 0.7
A57: 02.03.07.08 | B57: VIGAS.- ACERO Fy=4200 kg/cm2 | C57: KG | D57: 5144.6 | E57: 4.02 | F57: 20681.29 | G57: =$F57*N57 -> 0 | H57: =$F57*O57 -> 0 | I57: =$F57*P57 -> 12408.774 | J57: =$F57*Q57 -> 8272.516 | K57: =$F57*R57 -> 0 | L57: =F57-SUM(G57:K57) -> 0 | P57: 0.6 | Q57: 0.4
A58: 02.03.08 | B58: Losas Macizas
A59: 02.03.08.01 | B59: LOSAS MACIZAS.- CONC.210 kg/cm2 - 1 PISO | C59: M3 | D59: 0.63 | E59: 325.93 | F59: 205.34 | G59: =$F59*N59 -> 0 | H59: =$F59*O59 -> 0 | I59: =$F59*P59 -> 0 | J59: =$F59*Q59 -> 123.204 | K59: =$F59*R59 -> 82.136 | L59: =F59-SUM(G59:K59) -> 0 | Q59: 0.6 | R59: 0.4
A60: 02.03.08.03 | B60: LOSAS MACIZAS.- ENCOFRADO Y DESENCOFRADO | C60: m2 | D60: 6.54 | E60: 55.43 | F60: 362.51 | G60: =$F60*N60 -> 0 | H60: =$F60*O60 -> 0 | I60: =$F60*P60 -> 108.753 | J60: =$F60*Q60 -> 253.757 | K60: =$F60*R60 -> 0 | L60: =F60-SUM(G60:K60) -> 0 | P60: 0.3 | Q60: 0.7
A61: 02.03.08.04 | B61: LOSAS MACIZAS.- ACERO Fy=4,200 kg/cm2 | C61: KG | D61: 73.15 | E61: 4.02 | F61: 294.06 | G61: =$F61*N61 -> 0 | H61: =$F61*O61 -> 0 | I61: =$F61*P61 -> 176.436 | J61: =$F61*Q61 -> 117.624 | K61: =$F61*R61 -> 0 | L61: =F61-SUM(G61:K61) -> 0 | P61: 0.6 | Q61: 0.4
A62: 02.03.09 | B62: Losas Aligeradas
A63: 02.03.09.01 | B63: LOSA ALIGERADA - CONCRETO 210 kg/cm2 - 1 PISO | C63: m3 | D63: 2.13 | E63: 315.52 | F63: 672.06 | G63: =$F63*N63 -> 0 | H63: =$F63*O63 -> 0 | I63: =$F63*P63 -> 0 | J63: =$F63*Q63 -> 403.236 | K63: =$F63*R63 -> 268.824 | L63: =F63-SUM(G63:K63) -> 0 | Q63: 0.6 | R63: 0.4
A64: 02.03.09.03 | B64: LOSA ALIGERADA.- ENCOFRADO Y DESENCOFRADO | C64: m2 | D64: 24.72 | E64: 43.61 | F64: 1078.04 | G64: =$F64*N64 -> 0 | H64: =$F64*O64 -> 0 | I64: =$F64*P64 -> 323.412 | J64: =$F64*Q64 -> 754.628 | K64: =$F64*R64 -> 0 | L64: =F64-SUM(G64:K64) -> 0 | P64: 0.3 | Q64: 0.7
A65: 02.03.09.04 | B65: LOSA ALIGERADA.- ACERO Fy=4,200 kg/cm2 | C65: KG | D65: 93.93 | E65: 4.02 | F65: 377.6 | G65: =$F65*N65 -> 0 | H65: =$F65*O65 -> 0 | I65: =$F65*P65 -> 226.56 | J65: =$F65*Q65 -> 151.04 | K65: =$F65*R65 -> 0 | L65: =F65-SUM(G65:K65) -> 0 | P65: 0.6 | Q65: 0.4
A66: 02.03.09.05 | B66: LOSA ALIGERADA.- LADR. HUECO 15x30x30 | C66: und | D66: 205.92 | E66: 2.49 | F66: 512.74 | G66: =$F66*N66 -> 0 | H66: =$F66*O66 -> 0 | I66: =$F66*P66 -> 153.822 | J66: =$F66*Q66 -> 358.918 | K66: =$F66*R66 -> 0 | L66: =F66-SUM(G66:K66) -> 0 | P66: 0.3 | Q66: 0.7
A67: 02.03.15 | B67: Gradas Armadas en Pisos
A68: 02.03.15.01 | B68: GRADAS EN PISO, CONCRETO F'c=175 kg/cm2. | C68: m2 | D68: 12.31 | E68: 80.04 | F68: 985.29 | G68: =$F68*N68 -> 0 | H68: =$F68*O68 -> 0 | I68: =$F68*P68 -> 0 | J68: =$F68*Q68 -> 591.174 | K68: =$F68*R68 -> 394.116 | L68: =F68-SUM(G68:K68) -> 0 | Q68: 0.6 | R68: 0.4
A69: 02.03.15.03 | B69: GRADAS, ENCOFRADO Y DESENCOFRADO | C69: m2 | D69: 6.96 | E69: 41.15 | F69: 286.4 | G69: =$F69*N69 -> 0 | H69: =$F69*O69 -> 0 | I69: =$F69*P69 -> 85.92 | J69: =$F69*Q69 -> 200.48 | K69: =$F69*R69 -> 0 | L69: =F69-SUM(G69:K69) -> 0 | P69: 0.3 | Q69: 0.7
A70: 02.03.15.04 | B70: GRADAS EN PISO, ACERO fy=4200kg/cm2 | C70: kg | D70: 83.01 | E70: 4.02 | F70: 333.7 | G70: =$F70*N70 -> 0 | H70: =$F70*O70 -> 0 | I70: =$F70*P70 -> 100.11 | J70: =$F70*Q70 -> 233.59 | K70: =$F70*R70 -> 0 | L70: =F70-SUM(G70:K70) -> 0 | P70: 0.3 | Q70: 0.7
B71: COSTO DIRECTO | F71: =SUM(F7:F70) -> 960724.52 | G71: =SUM(G7:G70) -> 127002.26 | H71: =SUM(H7:H70) -> 298062.18 | I71: =SUM(I7:I70) -> 329406.11 | J71: =SUM(J7:J70) -> 188212.02 | K71: =SUM(K7:K70) -> 18041.95
B72: GASTOS GENERALES (10%) | F72: =F71*0.15 -> 144108.68 | G72: =G71*0.15 -> 19050.338 | H72: =H71*0.15 -> 44709.327 | I72: =I71*0.15 -> 49410.917 | J72: =J71*0.15 -> 28231.803 | K72: =K71*0.15 -> 2706.2925
B73: UTILIDAD (5%) | F73: =F71*0.05 -> 48036.226 | G73: =G71*0.05 -> 6350.1128 | H73: =H71*0.05 -> 14903.109 | I73: =I71*0.05 -> 16470.306 | J73: =J71*0.05 -> 9410.6011 | K73: =K71*0.05 -> 902.0975
B74: SUBTOTAL | F74: =SUM(F71:F73) -> 1152869.4 | G74: =SUM(G71:G73) -> 152402.71 | H74: =SUM(H71:H73) -> 357674.61 | I74: =SUM(I71:I73) -> 395287.34 | J74: =SUM(J71:J73) -> 225854.43 | K74: =SUM(K71:K73) -> 21650.34
B75: IGV (18.00%) | F75: =ROUND(F74*0.18,2) -> 207516.5 | G75: =ROUND(G74*0.18,2) -> 27432.49 | H75: =ROUND(H74*0.18,2) -> 64381.43 | I75: =ROUND(I74*0.18,2) -> 71151.72 | J75: =ROUND(J74*0.18,2) -> 40653.8 | K75: =ROUND(K74*0.18,2) -> 3897.06
B76: COSTO TOTAL (INC. IGV) | F76: =SUM(F74:F75) -> 1360385.9 | G76: =SUM(G74:G75) -> 179835.2 | H76: =SUM(H74:H75) -> 422056.04 | I76: =SUM(I74:I75) -> 466439.06 | J76: =SUM(J74:J75) -> 266508.23 | K76: =SUM(K74:K75) -> 25547.4

Sheet CRONOG INTERNO META
A1: CRONOGRAMA VALORIZADO DE OBRA - PROGRAMACION VENTA CON COSTOS META
A3: PROYECTO: | B3: I.E. N° 1182 "EL BOSQUE" - CERCO + INGRESOS Y CASETAS
A5: ITEM | B5: DESCRIPCION | C5: UND | D5: CONTRACTUAL | G5: PROGRAMACION
D6: METRADO | E6: P.U. (S/.) | F6: PARCIAL (S/.) | G6: 45474 | H6: 45505 | I6: 45536 | J6: 45566 | K6: 45597
A7: 01 | B7: OBRAS PROVISIONALES, TRABAJOS PRELIMINARES, SEGURIDAD Y SALUD
A8: 01.02 | B8: Trabajos Preliminares
A9: 01.02.04 | B9: Trazo, Niveles y Replanteo
A10: 01.02.04.01 | B10: TRAZO Y REPLANTEO PRELIMINAR | C10: M2 | D10: 942.21 | E10: 1.33 | F10: 1253.14 | G10: =$F10*N10 -> 626.57 | H10: =$F10*O10 -> 626.57 | I10: =$F10*P10 -> 0 | J10: =$F10*Q10 -> 0 | K10: =$F10*R10 -> 0 | L10: =F10-SUM(G10:K10) -> 0 | N10: 0.5 | O10: 0.5
A11: 01.02.04.02 | B11: TRAZO Y REPLANTEO DURANTE EL PROCESO | C11: m2 | D11: 942.21 | E11: 1.33 | F11: 1253.14 | G11: =$F11*N11 -> 313.285 | H11: =$F11*O11 -> 313.285 | I11: =$F11*P11 -> 313.285 | J11: =$F11*Q11 -> 313.285 | K11: =$F11*R11 -> 0 | L11: =F11-SUM(G11:K11) -> 0 | N11: 0.25 | O11: 0.25 | P11: 0.25 | Q11: 0.25
A12: 02 | B12: ESTRUCTURAS
A13: 02.01 | B13: Movimiento de Tierras
A14: 02.01.01 | B14: Excavaciones
A15: 02.01.01.01 | B15: EXCAV.ZANJAS Y ZAPATA RT>2kg/cm2 H=1.5m | C15: m3 | D15: 39.81 | E15: 29.22 | F15: 1163.25 | G15: =$F15*N15 -> 814.275 | H15: =$F15*O15 -> 348.975 | I15: =$F15*P15 -> 0 | J15: =$F15*Q15 -> 0 | K15: =$F15*R15 -> 0 | L15: =F15-SUM(G15:K15) -> 0 | N15: 0.7 | O15: 0.3
A16: 02.01.01.02 | B16: EXCAV.ZANJAS Y ZAPATA RT>2kg/cm2 H=2.0m | C16: m3 | D16: 1876.4 | E16: 33.36 | F16: 62596.7 | G16: =$F16*N16 -> 43817.69 | H16: =$F16*O16 -> 18779.01 | I16: =$F16*P16 -> 0 | J16: =$F16*Q16 -> 0 | K16: =$F16*R16 -> 0 | L16: =F16-SUM(G16:K16) -> 0 | N16: 0.7 | O16: 0.3
A17: 02.01.03 | B17: Rellenos
A18: 02.01.03.01 | B18: RELLENO COMPACTADO C/EQUIPO MAT/PROPIO | C18: m3 | D18: 1138.01 | E18: 15 | F18: 17070.15 | G18: =$F18*N18 -> 0 | H18: =$F18*O18 -> 5121.045 | I18: =$F18*P18 -> 11949.105 | J18: =$F18*Q18 -> 0 | K18: =$F18*R18 -> 0 | L18: =F18-SUM(G18:K18) -> 0 | O18: 0.3 | P18: 0.7
A19: 02.01.04 | B19: Eliminacion de Material Excedente
A20: 02.01.04.01 | B20: ACARREO INTERNO, MATERIAL PROCEDENTE DE EXCAVACIONES | C20: m3 | D20: 1118.06 | E20: 18.27 | F20: 20426.96 | G20: =$F20*N20 -> 10213.48 | H20: =$F20*O20 -> 10213.48 | I20: =$F20*P20 -> 0 | J20: =$F20*Q20 -> 0 | K20: =$F20*R20 -> 0 | L20: =F20-SUM(G20:K20) -> 0 | N20: 0.5 | O20: 0.5
A21: 02.01.04.02 | B21: ELIMINACION MATERIAL EXCEDENTE ACARREADO | C21: M3 | G21: =$F21*N21 -> 0 | H21: =$F21*O21 -> 0 | I21: =$F21*P21 -> 0 | J21: =$F21*Q21 -> 0 | K21: =$F21*R21 -> 0 | L21: =F21-SUM(G21:K21) -> 0 | N21: 0.5 | O21: 0.5
A22: 02.01.04.03 | B22: ELIMINACION MATERIAL EXCEDENTE C/MAQUINA | C22: m3 | G22: =$F22*N22 -> 0 | H22: =$F22*O22 -> 0 | I22: =$F22*P22 -> 0 | J22: =$F22*Q22 -> 0 | K22: =$F22*R22 -> 0 | L22: =F22-SUM(G22:K22) -> 0 | N22: 0.5 | O22: 0.5
A23: 02.01.05 | B23: Nivelacion Interior y Apisonado
A24: 02.01.05.01 | B24: ESCARIFICADO Y COMPACTACION CON PLANCHA COMPACTADORA e = 30 cm | C24: m2 | D24: 70.33 | E24: 4.36 | F24: 306.64 | G24: =$F24*N24 -> 0 | H24: =$F24*O24 -> 0 | I24: =$F24*P24 -> 0 | J24: =$F24*Q24 -> 153.32 | K24: =$F24*R24 -> 153.32 | L24: =F24-SUM(G24:K24) -> 0 | Q24: 0.5 | R24: 0.5
A25: 02.01.05.02 | B25: ESCARIFICADO Y COMPACTACION CON PLANCHA COMPACTADORA H=0.60m (02 CAPAS 30cm c/u) | C25: m2 | D25: 8.73 | E25: 7.37 | F25: 64.34 | G25: =$F25*N25 -> 0 | H25: =$F25*O25 -> 0 | I25: =$F25*P25 -> 38.604 | J25: =$F25*Q25 -> 25.736 | K25: =$F25*R25 -> 0 | L25: =F25-SUM(G25:K25) -> 0 | P25: 0.6 | Q25: 0.4
A26: 02.01.05.05 | B26: AFIRMADO DE 8" PARA PISOS,PATIOS Y VEREDAS,COMPACTADO. | C26: m2 | D26: 70.33 | E26: 11.5 | F26: 808.8 | G26: =$F26*N26 -> 0 | H26: =$F26*O26 -> 0 | I26: =$F26*P26 -> 0 | J26: =$F26*Q26 -> 323.52 | K26: =$F26*R26 -> 485.28 | L26: =F26-SUM(G26:K26) -> 0 | Q26: 0.4 | R26: 0.6
A27: 02.01.05.06 | B27: AFIRMADO DE 12" EN PISOS INTERIOR/EXTERIOR,COMPACTADO. | C27: m2 | D27: 8.73 | E27: 14.5 | F27: 126.59 | G27: =$F27*N27 -> 0 | H27: =$F27*O27 -> 0 | I27: =$F27*P27 -> 63.295 | J27: =$F27*Q27 -> 63.295 | K27: =$F27*R27 -> 0 | L27: =F27-SUM(G27:K27) -> 0 | P27: 0.5 | Q27: 0.5
A28: 02.02 | B28: Obras de Concreto Simple
A29: 02.02.01 | B29: Falsos Cimientos
A30: 02.02.01.01 | B30: SUBCIMIENTO, SUBZAPATA MEZCLA 1:12 + 30 % P.G. | C30: m3 | D30: 330.16 | E30: 184.1 | F30: 60782.46 | G30: =$F30*N30 -> 0 | H30: =$F30*O30 -> 42547.722 | I30: =$F30*P30 -> 18234.738 | J30: =$F30*Q30 -> 0 | K30: =$F30*R30 -> 0 | L30: =F30-SUM(G30:K30) -> 0 | O30: 0.7 | P30: 0.3
A31: 02.02.02 | B31: Cimientos
A32: 02.02.02.02 | B32: CIMIENTOS CORRIDOS 1:10 + 30 % P.G. f'c >=100Kg/cm2 | C32: m3 | D32: 24.24 | E32: 182.46 | F32: 4422.83 | G32: =$F32*N32 -> 0 | H32: =$F32*O32 -> 1326.849 | I32: =$F32*P32 -> 3095.981 | J32: =$F32*Q32 -> 0 | K32: =$F32*R32 -> 0 | L32: =F32-SUM(G32:K32) -> 0 | O32: 0.3 | P32: 0.7
A33: 02.02.02.03 | B33: CIMIENTO CORRIDO - ENCOFRADO Y DESENCOFRADO | C33: m2 | D33: 22.63 | E33: 23.83 | F33: 539.27 | G33: =$F33*N33 -> 0 | H33: =$F33*O33 -> 215.708 | I33: =$F33*P33 -> 323.562 | J33: =$F33*Q33 -> 0 | K33: =$F33*R33 -> 0 | L33: =F33-SUM(G33:K33) -> 0 | O33: 0.4 | P33: 0.6
A34: 02.02.02.04 | B34: CALZADURA: CONCRETO C:H 1:10 + 30 % P.G. | C34: m3 | D34: 160.54 | E34: 207.85 | F34: 33368.24 | G34: =$F34*N34 -> 33368.24 | H34: =$F34*O34 -> 0 | I34: =$F34*P34 -> 0 | J34: =$F34*Q34 -> 0 | K34: =$F34*R34 -> 0 | L34: =F34-SUM(G34:K34) -> 0 | N34: 1
A35: 02.02.02.05 | B35: CALZADURA: ENCOFRADO Y DESENCOFRADO | C35: m2 | D35: 321.08 | E35: 26.53 | F35: 8518.25 | G35: =$F35*N35 -> 8518.25 | H35: =$F35*O35 -> 0 | I35: =$F35*P35 -> 0 | J35: =$F35*Q35 -> 0 | K35: =$F35*R35 -> 0 | L35: =F35-SUM(G35:K35) -> 0 | N35: 1
A36: 02.02.03 | B36: Sobrecimientos
A37: 02.02.03.01 | B37: SOBRECIMIENTO, CONCRETO 1:8 + 25% P.M. f'c >=100Kg/cm2 | C37: m3 | D37: 3.15 | E37: 201.22 | F37: 633.84 | G37: =$F37*N37 -> 0 | H37: =$F37*O37 -> 0 | I37: =$F37*P37 -> 316.92 | J37: =$F37*Q37 -> 316.92 | K37: =$F37*R37 -> 0 | L37: =F37-SUM(G37:K37) -> 0 | P37: 0.5 | Q37: 0.5
A38: 02.02.03.02 | B38: SOBRECIMIENTO, ENCOFRADO Y DESENCOFRADO | C38: m2 | D38: 43.07 | E38: 24.18 | F38: 1041.43 | G38: =$F38*N38 -> 0 | H38: =$F38*O38 -> 416.572 | I38: =$F38*P38 -> 416.572 | J38: =$F38*Q38 -> 208.286 | K38: =$F38*R38 -> 0 | L38: =F38-SUM(G38:K38) -> 0 | O38: 0.4 | P38: 0.4 | Q38: 0.2
A39: 02.03 | B39: Obras de Concreto Armado
A40: 02.03.02 | B40: Zapatas
A41: 02.03.02.01 | B41: ZAPATAS.- CONCRETO 210 kg/cm2 | C41: m3 | D41: 412.62 | E41: 286.6 | F41: 118256.89 | G41: =$F41*N41 -> 0 | H41: =$F41*O41 -> 59128.445 | I41: =$F41*P41 -> 59128.445 | J41: =$F41*Q41 -> 0 | K41: =$F41*R41 -> 0 | L41: =F41-SUM(G41:K41) -> 0 | O41: 0.5 | P41: 0.5
A42: 02.03.02.03 | B42: ZAPATAS.- ACERO Fy=4200 kg/cm2 | C42: KG | D42: 17359.56 | E42: 3.4 | F42: 59022.5 | G42: =$F42*N42 -> 0 | H42: =$F42*O42 -> 29511.25 | I42: =$F42*P42 -> 29511.25 | J42: =$F42*Q42 -> 0 | K42: =$F42*R42 -> 0 | L42: =F42-SUM(G42:K42) -> 0 | O42: 0.5 | P42: 0.5
A43: 02.03.05 | B43: Placas y Muros de Contención
A44: 02.03.05.02 | B44: PLACAS, CONCRETO F'c=210 kg/cm2 - 1 piso | C44: m3 | D44: 6.62 | E44: 290.45 | F44: 1922.78 | G44: =$F44*N44 -> 0 | H44: =$F44*O44 -> 0 | I44: =$F44*P44 -> 1153.668 | J44: =$F44*Q44 -> 769.112 | K44: =$F44*R44 -> 0 | L44: =F44-SUM(G44:K44) -> 0 | P44: 0.6 | Q44: 0.4
A45: 02.03.05.04 | B45: PLACAS, ENCOFRADO Y DESENCOFRADO | C45: m2 | D45: 73.44 | E45: 33.69 | F45: 2474.19 | G45: =$F45*N45 -> 0 | H45: =$F45*O45 -> 1237.095 | I45: =$F45*P45 -> 742.257 | J45: =$F45*Q45 -> 494.838 | K45: =$F45*R45 -> 0 | L45: =F45-SUM(G45:K45) -> 0 | O45: 0.5 | P45: 0.3 | Q45: 0.2
A46: 02.03.05.05 | B46: PLACAS, ACERO Fy=4200 kg/cm2 | C46: KG | D46: 415.16 | E46: 3.4 | F46: 1411.54 | G46: =$F46*N46 -> 0 | H46: =$F46*O46 -> 988.078 | I46: =$F46*P46 -> 423.462 | J46: =$F46*Q46 -> 0 | K46: =$F46*R46 -> 0 | L46: =F46-SUM(G46:K46) -> 0 | O46: 0.7 | P46: 0.3
A47: 02.03.05.07 | B47: MUROS DE CONTENC.- CONCRETO 210 kg/cm2 | C47: m3 | D47: 253.95 | E47: 328.19 | F47: 83343.85 | G47: =$F47*N47 -> 0 | H47: =$F47*O47 -> 0 | I47: =$F47*P47 -> 50006.31 | J47: =$F47*Q47 -> 33337.54 | K47: =$F47*R47 -> 0 | L47: =F47-SUM(G47:K47) -> 0 | P47: 0.6 | Q47: 0.4
A48: 02.03.05.09 | B48: MUROS DE CONTENC.- ENCOF. Y DESENCOFRADO | C48: m2 | D48: 2075.23 | E48: 30.97 | F48: 64269.87 | G48: =$F48*N48 -> 0 | H48: =$F48*O48 -> 32134.935 | I48: =$F48*P48 -> 19280.961 | J48: =$F48*Q48 -> 12853.974 | K48: =$F48*R48 -> 0 | L48: =F48-SUM(G48:K48) -> 0 | O48: 0.5 | P48: 0.3 | Q48: 0.2
A49: 02.03.05.11 | B49: MUROS DE CONTENC.- ACERO Fy=4200 kg/cm2 | C49: kg | G49: =$F49*N49 -> 0 | H49: =$F49*O49 -> 0 | I49: =$F49*P49 -> 0 | J49: =$F49*Q49 -> 0 | K49: =$F49*R49 -> 0 | L49: =F49-SUM(G49:K49) -> 0 | O49: 0.7 | P49: 0.3
A50: 02.03.06 | B50: Columnas
A51: 02.03.06.02 | B51: COLUMNAS - CONCRETO 210 KG/CM² - 1 PISO | C51: m3 | D51: 67.96 | E51: 291.23 | F51: 19791.99 | G51: =$F51*N51 -> 0 | H51: =$F51*O51 -> 0 | I51: =$F51*P51 -> 0 | J51: =$F51*Q51 -> 11875.194 | K51: =$F51*R51 -> 7916.796 | L51: =F51-SUM(G51:K51) -> 0 | Q51: 0.6 | R51: 0.4
A52: 02.03.06.06 | B52: COLUMNAS.- ENCOFRADO Y DESENCOFRADO | C52: m2 | D52: 919.41 | E52: 37.49 | F52: 34468.68 | G52: =$F52*N52 -> 0 | H52: =$F52*O52 -> 0 | I52: =$F52*P52 -> 10340.604 | J52: =$F52*Q52 -> 24128.076 | K52: =$F52*R52 -> 0 | L52: =F52-SUM(G52:K52) -> 0 | P52: 0.3 | Q52: 0.7
A53: 02.03.06.10 | B53: COLUMNAS.- ACERO Fy=4200 kg/cm2 | C53: KG | D53: 11836.1 | E53: 3.4 | F53: 40242.74 | G53: =$F53*N53 -> 0 | H53: =$F53*O53 -> 0 | I53: =$F53*P53 -> 24145.644 | J53: =$F53*Q53 -> 16097.096 | K53: =$F53*R53 -> 0 | L53: =F53-SUM(G53:K53) -> 0 | P53: 0.6 | Q53: 0.4
A54: 02.03.07 | B54: Vigas
A55: 02.03.07.02 | B55: VIGAS.- CONCRETO 210 kg/cm2 - 1 piso | C55: m3 | D55: 36.84 | E55: 294.5 | F55: 10849.38 | G55: =$F55*N55 -> 0 | H55: =$F55*O55 -> 0 | I55: =$F55*P55 -> 0 | J55: =$F55*Q55 -> 6509.628 | K55: =$F55*R55 -> 4339.752 | L55: =F55-SUM(G55:K55) -> 0 | Q55: 0.6 | R55: 0.4
A56: 02.03.07.06 | B56: VIGAS.- ENCOFRADO Y DESENCOFRADO | C56: m2 | D56: 556.13 | E56: 43.56 | F56: 24225.02 | G56: =$F56*N56 -> 0 | H56: =$F56*O56 -> 0 | I56: =$F56*P56 -> 7267.506 | J56: =$F56*Q56 -> 16957.514 | K56: =$F56*R56 -> 0 | L56: =F56-SUM(G56:K56) -> 0 | P56: 0.3 | Q56: 0.7
A57: 02.03.07.08 | B57: VIGAS.- ACERO Fy=4200 kg/cm2 | C57: KG | D57: 5247.49 | E57: 3.4 | F57: 17841.47 | G57: =$F57*N57 -> 0 | H57: =$F57*O57 -> 0 | I57: =$F57*P57 -> 10704.882 | J57: =$F57*Q57 -> 7136.588 | K57: =$F57*R57 -> 0 | L57: =F57-SUM(G57:K57) -> 0 | P57: 0.6 | Q57: 0.4
A58: 02.03.08 | B58: Losas Macizas
A59: 02.03.08.01 | B59: LOSAS MACIZAS.- CONC.210 kg/cm2 - 1 PISO | C59: M3 | D59: 0.63 | E59: 325.93 | F59: 205.34 | G59: =$F59*N59 -> 0 | H59: =$F59*O59 -> 0 | I59: =$F59*P59 -> 0 | J59: =$F59*Q59 -> 123.204 | K59: =$F59*R59 -> 82.136 | L59: =F59-SUM(G59:K59) -> 0 | Q59: 0.6 | R59: 0.4
A60: 02.03.08.03 | B60: LOSAS MACIZAS.- ENCOFRADO Y DESENCOFRADO | C60: m2 | D60: 6.54 | E60: 55.43 | F60: 362.51 | G60: =$F60*N60 -> 0 | H60: =$F60*O60 -> 0 | I60: =$F60*P60 -> 108.753 | J60: =$F60*Q60 -> 253.757 | K60: =$F60*R60 -> 0 | L60: =F60-SUM(G60:K60) -> 0 | P60: 0.3 | Q60: 0.7
A61: 02.03.08.04 | B61: LOSAS MACIZAS.- ACERO Fy=4,200 kg/cm2 | C61: KG | D61: 73.15 | E61: 4.02 | F61: 294.06 | G61: =$F61*N61 -> 0 | H61: =$F61*O61 -> 0 | I61: =$F61*P61 -> 176.436 | J61: =$F61*Q61 -> 117.624 | K61: =$F61*R61 -> 0 | L61: =F61-SUM(G61:K61) -> 0 | P61: 0.6 | Q61: 0.4
A62: 02.03.09 | B62: Losas Aligeradas
A63: 02.03.09.01 | B63: LOSA ALIGERADA - CONCRETO 210 kg/cm2 - 1 PISO | C63: m3 | D63: 2.17 | E63: 294.5 | F63: 639.07 | G63: =$F63*N63 -> 0 | H63: =$F63*O63 -> 0 | I63: =$F63*P63 -> 0 | J63: =$F63*Q63 -> 383.442 | K63: =$F63*R63 -> 255.628 | L63: =F63-SUM(G63:K63) -> 0 | Q63: 0.6 | R63: 0.4
A64: 02.03.09.03 | B64: LOSA ALIGERADA.- ENCOFRADO Y DESENCOFRADO | C64: m2 | D64: 25.21 | E64: 25.75 | F64: 649.16 | G64: =$F64*N64 -> 0 | H64: =$F64*O64 -> 0 | I64: =$F64*P64 -> 194.748 | J64: =$F64*Q64 -> 454.412 | K64: =$F64*R64 -> 0 | L64: =F64-SUM(G64:K64) -> 0 | P64: 0.3 | Q64: 0.7
A65: 02.03.09.04 | B65: LOSA ALIGERADA.- ACERO Fy=4,200 kg/cm2 | C65: KG | D65: 95.81 | E65: 3.4 | F65: 325.75 | G65: =$F65*N65 -> 0 | H65: =$F65*O65 -> 0 | I65: =$F65*P65 -> 195.45 | J65: =$F65*Q65 -> 130.3 | K65: =$F65*R65 -> 0 | L65: =F65-SUM(G65:K65) -> 0 | P65: 0.6 | Q65: 0.4
A66: 02.03.09.05 | B66: LOSA ALIGERADA.- LADR. HUECO 15x30x30 | C66: und | D66: 210.04 | E66: 2.39 | F66: 502 | G66: =$F66*N66 -> 0 | H66: =$F66*O66 -> 0 | I66: =$F66*P66 -> 150.6 | J66: =$F66*Q66 -> 351.4 | K66: =$F66*R66 -> 0 | L66: =F66-SUM(G66:K66) -> 0 | P66: 0.3 | Q66: 0.7
A67: 02.03.15 | B67: Gradas Armadas en Pisos
A68: 02.03.15.01 | B68: GRADAS EN PISO, CONCRETO F'c=175 kg/cm2. | C68: m2 | D68: 12.56 | E68: 59.8 | F68: 751.09 | G68: =$F68*N68 -> 0 | H68: =$F68*O68 -> 0 | I68: =$F68*P68 -> 0 | J68: =$F68*Q68 -> 450.654 | K68: =$F68*R68 -> 300.436 | L68: =F68-SUM(G68:K68) -> 0 | Q68: 0.6 | R68: 0.4
A69: 02.03.15.03 | B69: GRADAS, ENCOFRADO Y DESENCOFRADO | C69: m2 | D69: 7.1 | E69: 27.36 | F69: 194.26 | G69: =$F69*N69 -> 0 | H69: =$F69*O69 -> 0 | I69: =$F69*P69 -> 58.278 | J69: =$F69*Q69 -> 135.982 | K69: =$F69*R69 -> 0 | L69: =F69-SUM(G69:K69) -> 0 | P69: 0.3 | Q69: 0.7
A70: 02.03.15.04 | B70: GRADAS EN PISO, ACERO fy=4200kg/cm2 | C70: kg | D70: 84.67 | E70: 3.4 | F70: 287.88 | G70: =$F70*N70 -> 0 | H70: =$F70*O70 -> 0 | I70: =$F70*P70 -> 86.364 | J70: =$F70*Q70 -> 201.516 | K70: =$F70*R70 -> 0 | L70: =F70-SUM(G70:K70) -> 0 | P70: 0.3 | Q70: 0.7
B71: COSTO DIRECTO | F71: =SUM(F7:F70) -> 696708.05 | G71: =SUM(G7:G70) -> 97671.79 | H71: =SUM(H7:H70) -> 202909.02 | I71: =SUM(I7:I70) -> 248427.68 | J71: =SUM(J7:J70) -> 134166.21 | K71: =SUM(K7:K70) -> 13533.348
B72: GASTOS GENERALES (10%) | F72: =F71*0.15 -> 104506.21 | G72: =G71*0.15 -> 14650.768 | H72: =H71*0.15 -> 30436.353 | I72: =I71*0.15 -> 37264.152 | J72: =J71*0.15 -> 20124.932 | K72: =K71*0.15 -> 2030.0022
B73: UTILIDAD (5%) | F73: =F71*0.05 -> 34835.402 | G73: =G71*0.05 -> 4883.5895 | H73: =H71*0.05 -> 10145.451 | I73: =I71*0.05 -> 12421.384 | J73: =J71*0.05 -> 6708.3107 | K73: =K71*0.05 -> 676.6674
B74: SUBTOTAL | F74: =SUM(F71:F73) -> 836049.66 | G74: =SUM(G71:G73) -> 117206.15 | H74: =SUM(H71:H73) -> 243490.82 | I74: =SUM(I71:I73) -> 298113.22 | J74: =SUM(J71:J73) -> 160999.46 | K74: =SUM(K71:K73) -> 16240.018
B75: IGV (18.00%) | F75: =ROUND(F74*0.18,2) -> 150488.94 | G75: =ROUND(G74*0.18,2) -> 21097.11 | H75: =ROUND(H74*0.18,2) -> 43828.35 | I75: =ROUND(I74*0.18,2) -> 53660.38 | J75: =ROUND(J74*0.18,2) -> 28979.9 | K75: =ROUND(K74*0.18,2) -> 2923.2
B76: COSTO TOTAL (INC. IGV) | F76: =SUM(F74:F75) -> 986538.6 | G76: =SUM(G74:G75) -> 138303.26 | H76: =SUM(H74:H75) -> 287319.17 | I76: =SUM(I74:I75) -> 351773.6 | J76: =SUM(J74:J75) -> 189979.36 | K76: =SUM(K74:K75) -> 19163.218

Sheet CRONOG COSTOS REALES
A1: CRONOGRAMA VALORIZADO DE OBRA - PROGRAMACION VENTA CON COSTOS META
A3: PROYECTO: | B3: I.E. N° 1182 "EL BOSQUE" - CERCO + INGRESOS Y CASETAS
A5: ITEM | B5: DESCRIPCION | C5: UND | D5: CONTRACTUAL | G5: PROGRAMACION
D6: METRADO | E6: P.U. (S/.) | F6: PARCIAL (S/.) | G6: 45474 | H6: 45505 | I6: 45536 | J6: 45566 | K6: 45597
A7: 01 | B7: OBRAS PROVISIONALES, TRABAJOS PRELIMINARES, SEGURIDAD Y SALUD
A8: 01.02 | B8: Trabajos Preliminares
A9: 01.02.04 | B9: Trazo, Niveles y Replanteo
A10: 01.02.04.01 | B10: TRAZO Y REPLANTEO PRELIMINAR | C10: M2 | G10: =$F10*N10 -> 0 | H10: =$F10*O10 -> 0 | I10: =$F10*P10 -> 0 | J10: =$F10*Q10 -> 0 | K10: =$F10*R10 -> 0 | L10: =F10-SUM(G10:K10) -> 0
A11: 01.02.04.02 | B11: TRAZO Y REPLANTEO DURANTE EL PROCESO | C11: m2 | G11: =$F11*N11 -> 0 | H11: =$F11*O11 -> 0 | I11: =$F11*P11 -> 0 | J11: =$F11*Q11 -> 0 | K11: =$F11*R11 -> 0 | L11: =F11-SUM(G11:K11) -> 0
A12: 02 | B12: ESTRUCTURAS
A13: 02.01 | B13: Movimiento de Tierras
A14: 02.01.01 | B14: Excavaciones
A15: 02.01.01.01 | B15: EXCAV.ZANJAS Y ZAPATA RT>2kg/cm2 H=1.5m | C15: m3 | G15: =$F15*N15 -> 0 | H15: =$F15*O15 -> 0 | I15: =$F15*P15 -> 0 | J15: =$F15*Q15 -> 0 | K15: =$F15*R15 -> 0 | L15: =F15-SUM(G15:K15) -> 0
A16: 02.01.01.02 | B16: EXCAV.ZANJAS Y ZAPATA RT>2kg/cm2 H=2.0m | C16: m3 | G16: =$F16*N16 -> 0 | H16: =$F16*O16 -> 0 | I16: =$F16*P16 -> 0 | J16: =$F16*Q16 -> 0 | K16: =$F16*R16 -> 0 | L16: =F16-SUM(G16:K16) -> 0
A17: 02.01.03 | B17: Rellenos
A18: 02.01.03.01 | B18: RELLENO COMPACTADO C/EQUIPO MAT/PROPIO | C18: m3 | G18: =$F18*N18 -> 0 | H18: =$F18*O18 -> 0 | I18: =$F18*P18 -> 0 | J18: =$F18*Q18 -> 0 | K18: =$F18*R18 -> 0 | L18: =F18-SUM(G18:K18) -> 0
A19: 02.01.04 | B19: Eliminacion de Material Excedente
A20: 02.01.04.01 | B20: ACARREO INTERNO, MATERIAL PROCEDENTE DE EXCAVACIONES | C20: m3 | G20: =$F20*N20 -> 0 | H20: =$F20*O20 -> 0 | I20: =$F20*P20 -> 0 | J20: =$F20*Q20 -> 0 | K20: =$F20*R20 -> 0 | L20: =F20-SUM(G20:K20) -> 0
A21: 02.01.04.02 | B21: ELIMINACION MATERIAL EXCEDENTE ACARREADO | C21: M3 | G21: =$F21*N21 -> 0 | H21: =$F21*O21 -> 0 | I21: =$F21*P21 -> 0 | J21: =$F21*Q21 -> 0 | K21: =$F21*R21 -> 0 | L21: =F21-SUM(G21:K21) -> 0
A22: 02.01.04.03 | B22: ELIMINACION MATERIAL EXCEDENTE C/MAQUINA | C22: m3 | G22: =$F22*N22 -> 0 | H22: =$F22*O22 -> 0 | I22: =$F22*P22 -> 0 | J22: =$F22*Q22 -> 0 | K22: =$F22*R22 -> 0 | L22: =F22-SUM(G22:K22) -> 0
A23: 02.01.05 | B23: Nivelacion Interior y Apisonado
A24: 02.01.05.01 | B24: ESCARIFICADO Y COMPACTACION CON PLANCHA COMPACTADORA e = 30 cm | C24: m2 | G24: =$F24*N24 -> 0 | H24: =$F24*O24 -> 0 | I24: =$F24*P24 -> 0 | J24: =$F24*Q24 -> 0 | K24: =$F24*R24 -> 0 | L24: =F24-SUM(G24:K24) -> 0
A25: 02.01.05.02 | B25: ESCARIFICADO Y COMPACTACION CON PLANCHA COMPACTADORA H=0.60m (02 CAPAS 30cm c/u) | C25: m2 | G25: =$F25*N25 -> 0 | H25: =$F25*O25 -> 0 | I25: =$F25*P25 -> 0 | J25: =$F25*Q25 -> 0 | K25: =$F25*R25 -> 0 | L25: =F25-SUM(G25:K25) -> 0
A26: 02.01.05.05 | B26: AFIRMADO DE 8" PARA PISOS,PATIOS Y VEREDAS,COMPACTADO. | C26: m2 | G26: =$F26*N26 -> 0 | H26: =$F26*O26 -> 0 | I26: =$F26*P26 -> 0 | J26: =$F26*Q26 -> 0 | K26: =$F26*R26 -> 0 | L26: =F26-SUM(G26:K26) -> 0
A27: 02.01.05.06 | B27: AFIRMADO DE 12" EN PISOS INTERIOR/EXTERIOR,COMPACTADO. | C27: m2 | G27: =$F27*N27 -> 0 | H27: =$F27*O27 -> 0 | I27: =$F27*P27 -> 0 | J27: =$F27*Q27 -> 0 | K27: =$F27*R27 -> 0 | L27: =F27-SUM(G27:K27) -> 0
A28: 02.02 | B28: Obras de Concreto Simple
A29: 02.02.01 | B29: Falsos Cimientos
A30: 02.02.01.01 | B30: SUBCIMIENTO, SUBZAPATA MEZCLA 1:12 + 30 % P.G. | C30: m3 | G30: =$F30*N30 -> 0 | H30: =$F30*O30 -> 0 | I30: =$F30*P30 -> 0 | J30: =$F30*Q30 -> 0 | K30: =$F30*R30 -> 0 | L30: =F30-SUM(G30:K30) -> 0
A31: 02.02.02 | B31: Cimientos
A32: 02.02.02.02 | B32: CIMIENTOS CORRIDOS 1:10 + 30 % P.G. f'c >=100Kg/cm2 | C32: m3 | G32: =$F32*N32 -> 0 | H32: =$F32*O32 -> 0 | I32: =$F32*P32 -> 0 | J32: =$F32*Q32 -> 0 | K32: =$F32*R32 -> 0 | L32: =F32-SUM(G32:K32) -> 0
A33: 02.02.02.03 | B33: CIMIENTO CORRIDO - ENCOFRADO Y DESENCOFRADO | C33: m2 | G33: =$F33*N33 -> 0 | H33: =$F33*O33 -> 0 | I33: =$F33*P33 -> 0 | J33: =$F33*Q33 -> 0 | K33: =$F33*R33 -> 0 | L33: =F33-SUM(G33:K33) -> 0
A34: 02.02.02.04 | B34: CALZADURA: CONCRETO C:H 1:10 + 30 % P.G. | C34: m3 | G34: =$F34*N34 -> 0 | H34: =$F34*O34 -> 0 | I34: =$F34*P34 -> 0 | J34: =$F34*Q34 -> 0 | K34: =$F34*R34 -> 0 | L34: =F34-SUM(G34:K34) -> 0
A35: 02.02.02.05 | B35: CALZADURA: ENCOFRADO Y DESENCOFRADO | C35: m2 | G35: =$F35*N35 -> 0 | H35: =$F35*O35 -> 0 | I35: =$F35*P35 -> 0 | J35: =$F35*Q35 -> 0 | K35: =$F35*R35 -> 0 | L35: =F35-SUM(G35:K35) -> 0
A36: 02.02.03 | B36: Sobrecimientos
A37: 02.02.03.01 | B37: SOBRECIMIENTO, CONCRETO 1:8 + 25% P.M. f'c >=100Kg/cm2 | C37: m3 | G37: =$F37*N37 -> 0 | H37: =$F37*O37 -> 0 | I37: =$F37*P37 -> 0 | J37: =$F37*Q37 -> 0 | K37: =$F37*R37 -> 0 | L37: =F37-SUM(G37:K37) -> 0
A38: 02.02.03.02 | B38: SOBRECIMIENTO, ENCOFRADO Y DESENCOFRADO | C38: m2 | G38: =$F38*N38 -> 0 | H38: =$F38*O38 -> 0 | I38: =$F38*P38 -> 0 | J38: =$F38*Q38 -> 0 | K38: =$F38*R38 -> 0 | L38: =F38-SUM(G38:K38) -> 0
A39: 02.03 | B39: Obras de Concreto Armado
A40: 02.03.02 | B40: Zapatas
A41: 02.03.02.01 | B41: ZAPATAS.- CONCRETO 210 kg/cm2 | C41: m3 | G41: =$F41*N41 -> 0 | H41: =$F41*O41 -> 0 | I41: =$F41*P41 -> 0 | J41: =$F41*Q41 -> 0 | K41: =$F41*R41 -> 0 | L41: =F41-SUM(G41:K41) -> 0
A42: 02.03.02.03 | B42: ZAPATAS.- ACERO Fy=4200 kg/cm2 | C42: KG | G42: =$F42*N42 -> 0 | H42: =$F42*O42 -> 0 | I42: =$F42*P42 -> 0 | J42: =$F42*Q42 -> 0 | K42: =$F42*R42 -> 0 | L42: =F42-SUM(G42:K42) -> 0
A43: 02.03.05 | B43: Placas y Muros de Contención
A44: 02.03.05.02 | B44: PLACAS, CONCRETO F'c=210 kg/cm2 - 1 piso | C44: m3 | G44: =$F44*N44 -> 0 | H44: =$F44*O44 -> 0 | I44: =$F44*P44 -> 0 | J44: =$F44*Q44 -> 0 | K44: =$F44*R44 -> 0 | L44: =F44-SUM(G44:K44) -> 0
A45: 02.03.05.04 | B45: PLACAS, ENCOFRADO Y DESENCOFRADO | C45: m2 | G45: =$F45*N45 -> 0 | H45: =$F45*O45 -> 0 | I45: =$F45*P45 -> 0 | J45: =$F45*Q45 -> 0 | K45: =$F45*R45 -> 0 | L45: =F45-SUM(G45:K45) -> 0
A46: 02.03.05.05 | B46: PLACAS, ACERO Fy=4200 kg/cm2 | C46: KG | G46: =$F46*N46 -> 0 | H46: =$F46*O46 -> 0 | I46: =$F46*P46 -> 0 | J46: =$F46*Q46 -> 0 | K46: =$F46*R46 -> 0 | L46: =F46-SUM(G46:K46) -> 0
A47: 02.03.05.07 | B47: MUROS DE CONTENC.- CONCRETO 210 kg/cm2 | C47: m3 | G47: =$F47*N47 -> 0 | H47: =$F47*O47 -> 0 | I47: =$F47*P47 -> 0 | J47: =$F47*Q47 -> 0 | K47: =$F47*R47 -> 0 | L47: =F47-SUM(G47:K47) -> 0
A48: 02.03.05.09 | B48: MUROS DE CONTENC.- ENCOF. Y DESENCOFRADO | C48: m2 | G48: =$F48*N48 -> 0 | H48: =$F48*O48 -> 0 | I48: =$F48*P48 -> 0 | J48: =$F48*Q48 -> 0 | K48: =$F48*R48 -> 0 | L48: =F48-SUM(G48:K48) -> 0
A49: 02.03.05.11 | B49: MUROS DE CONTENC.- ACERO Fy=4200 kg/cm2 | C49: kg | G49: =$F49*N49 -> 0 | H49: =$F49*O49 -> 0 | I49: =$F49*P49 -> 0 | J49: =$F49*Q49 -> 0 | K49: =$F49*R49 -> 0 | L49: =F49-SUM(G49:K49) -> 0
A50: 02.03.06 | B50: Columnas
A51: 02.03.06.02 | B51: COLUMNAS - CONCRETO 210 KG/CM² - 1 PISO | C51: m3 | G51: =$F51*N51 -> 0 | H51: =$F51*O51 -> 0 | I51: =$F51*P51 -> 0 | J51: =$F51*Q51 -> 0 | K51: =$F51*R51 -> 0 | L51: =F51-SUM(G51:K51) -> 0
A52: 02.03.06.06 | B52: COLUMNAS.- ENCOFRADO Y DESENCOFRADO | C52: m2 | G52: =$F52*N52 -> 0 | H52: =$F52*O52 -> 0 | I52: =$F52*P52 -> 0 | J52: =$F52*Q52 -> 0 | K52: =$F52*R52 -> 0 | L52: =F52-SUM(G52:K52) -> 0
A53: 02.03.06.10 | B53: COLUMNAS.- ACERO Fy=4200 kg/cm2 | C53: KG | G53: =$F53*N53 -> 0 | H53: =$F53*O53 -> 0 | I53: =$F53*P53 -> 0 | J53: =$F53*Q53 -> 0 | K53: =$F53*R53 -> 0 | L53: =F53-SUM(G53:K53) -> 0
A54: 02.03.07 | B54: Vigas
A55: 02.03.07.02 | B55: VIGAS.- CONCRETO 210 kg/cm2 - 1 piso | C55: m3 | G55: =$F55*N55 -> 0 | H55: =$F55*O55 -> 0 | I55: =$F55*P55 -> 0 | J55: =$F55*Q55 -> 0 | K55: =$F55*R55 -> 0 | L55: =F55-SUM(G55:K55) -> 0
A56: 02.03.07.06 | B56: VIGAS.- ENCOFRADO Y DESENCOFRADO | C56: m2 | G56: =$F56*N56 -> 0 | H56: =$F56*O56 -> 0 | I56: =$F56*P56 -> 0 | J56: =$F56*Q56 -> 0 | K56: =$F56*R56 -> 0 | L56: =F56-SUM(G56:K56) -> 0
A57: 02.03.07.08 | B57: VIGAS.- ACERO Fy=4200 kg/cm2 | C57: KG | G57: =$F57*N57 -> 0 | H57: =$F57*O57 -> 0 | I57: =$F57*P57 -> 0 | J57: =$F57*Q57 -> 0 | K57: =$F57*R57 -> 0 | L57: =F57-SUM(G57:K57) -> 0
A58: 02.03.08 | B58: Losas Macizas
A59: 02.03.08.01 | B59: LOSAS MACIZAS.- CONC.210 kg/cm2 - 1 PISO | C59: M3 | G59: =$F59*N59 -> 0 | H59: =$F59*O59 -> 0 | I59: =$F59*P59 -> 0 | J59: =$F59*Q59 -> 0 | K59: =$F59*R59 -> 0 | L59: =F59-SUM(G59:K59) -> 0
A60: 02.03.08.03 | B60: LOSAS MACIZAS.- ENCOFRADO Y DESENCOFRADO | C60: m2 | G60: =$F60*N60 -> 0 | H60: =$F60*O60 -> 0 | I60: =$F60*P60 -> 0 | J60: =$F60*Q60 -> 0 | K60: =$F60*R60 -> 0 | L60: =F60-SUM(G60:K60) -> 0
A61: 02.03.08.04 | B61: LOSAS MACIZAS.- ACERO Fy=4,200 kg/cm2 | C61: KG | G61: =$F61*N61 -> 0 | H61: =$F61*O61 -> 0 | I61: =$F61*P61 -> 0 | J61: =$F61*Q61 -> 0 | K61: =$F61*R61 -> 0 | L61: =F61-SUM(G61:K61) -> 0
A62: 02.03.09 | B62: Losas Aligeradas
A63: 02.03.09.01 | B63: LOSA ALIGERADA - CONCRETO 210 kg/cm2 - 1 PISO | C63: m3 | G63: =$F63*N63 -> 0 | H63: =$F63*O63 -> 0 | I63: =$F63*P63 -> 0 | J63: =$F63*Q63 -> 0 | K63: =$F63*R63 -> 0 | L63: =F63-SUM(G63:K63) -> 0
A64: 02.03.09.03 | B64: LOSA ALIGERADA.- ENCOFRADO Y DESENCOFRADO | C64: m2 | G64: =$F64*N64 -> 0 | H64: =$F64*O64 -> 0 | I64: =$F64*P64 -> 0 | J64: =$F64*Q64 -> 0 | K64: =$F64*R64 -> 0 | L64: =F64-SUM(G64:K64) -> 0
A65: 02.03.09.04 | B65: LOSA ALIGERADA.- ACERO Fy=4,200 kg/cm2 | C65: KG | G65: =$F65*N65 -> 0 | H65: =$F65*O65 -> 0 | I65: =$F65*P65 -> 0 | J65: =$F65*Q65 -> 0 | K65: =$F65*R65 -> 0 | L65: =F65-SUM(G65:K65) -> 0
A66: 02.03.09.05 | B66: LOSA ALIGERADA.- LADR. HUECO 15x30x30 | C66: und | G66: =$F66*N66 -> 0 | H66: =$F66*O66 -> 0 | I66: =$F66*P66 -> 0 | J66: =$F66*Q66 -> 0 | K66: =$F66*R66 -> 0 | L66: =F66-SUM(G66:K66) -> 0
A67: 02.03.15 | B67: Gradas Armadas en Pisos
A68: 02.03.15.01 | B68: GRADAS EN PISO, CONCRETO F'c=175 kg/cm2. | C68: m2 | G68: =$F68*N68 -> 0 | H68: =$F68*O68 -> 0 | I68: =$F68*P68 -> 0 | J68: =$F68*Q68 -> 0 | K68: =$F68*R68 -> 0 | L68: =F68-SUM(G68:K68) -> 0
A69: 02.03.15.03 | B69: GRADAS, ENCOFRADO Y DESENCOFRADO | C69: m2 | G69: =$F69*N69 -> 0 | H69: =$F69*O69 -> 0 | I69: =$F69*P69 -> 0 | J69: =$F69*Q69 -> 0 | K69: =$F69*R69 -> 0 | L69: =F69-SUM(G69:K69) -> 0
A70: 02.03.15.04 | B70: GRADAS EN PISO, ACERO fy=4200kg/cm2 | C70: kg | G70: =$F70*N70 -> 0 | H70: =$F70*O70 -> 0 | I70: =$F70*P70 -> 0 | J70: =$F70*Q70 -> 0 | K70: =$F70*R70 -> 0 | L70: =F70-SUM(G70:K70) -> 0 | P70: 0.3 | Q70: 0.7
B71: COSTO DIRECTO | F71: =SUM(F7:F70) -> 0 | G71: =SUM(G7:G70) -> 0 | H71: =SUM(H7:H70) -> 0 | I71: =SUM(I7:I70) -> 0 | J71: =SUM(J7:J70) -> 0 | K71: =SUM(K7:K70) -> 0
B72: GASTOS GENERALES (10%) | F72: =F71*0.15 -> 0 | G72: =G71*0.15 -> 0 | H72: =H71*0.15 -> 0 | I72: =I71*0.15 -> 0 | J72: =J71*0.15 -> 0 | K72: =K71*0.15 -> 0
B73: UTILIDAD (5%) | F73: =F71*0.05 -> 0 | G73: =G71*0.05 -> 0 | H73: =H71*0.05 -> 0 | I73: =I71*0.05 -> 0 | J73: =J71*0.05 -> 0 | K73: =K71*0.05 -> 0
B74: SUBTOTAL | F74: =SUM(F71:F73) -> 0 | G74: =SUM(G71:G73) -> 0 | H74: =SUM(H71:H73) -> 0 | I74: =SUM(I71:I73) -> 0 | J74: =SUM(J71:J73) -> 0 | K74: =SUM(K71:K73) -> 0
B75: IGV (18.00%) | F75: =ROUND(F74*0.18,2) -> 0 | G75: =ROUND(G74*0.18,2) -> 0 | H75: =ROUND(H74*0.18,2) -> 0 | I75: =ROUND(I74*0.18,2) -> 0 | J75: =ROUND(J74*0.18,2) -> 0 | K75: =ROUND(K74*0.18,2) -> 0
B76: COSTO TOTAL (INC. IGV) | F76: =SUM(F74:F75) -> 0 | G76: =SUM(G74:G75) -> 0 | H76: =SUM(H74:H75) -> 0 | I76: =SUM(I74:I75) -> 0 | J76: =SUM(J74:J75) -> 0 | K76: =SUM(K74:K75) -> 0

Sheet CURVAS
A1: CURVAS DE GESTION DE COSTOS
A3: PROYECTO:
A4: DURACION:
A6: CUADRO RESUMEN DE VENTA LINEA BASE Y REAL
